Workbook
Name __FDS_UNIQUE_RANGE_ID_GENERATOR_COUNTER: 1
Name is: #REF!
Name MARKET_DATA: 'SCB Ticker Sheet'!$P$2:$R$13
Name NewToCopy: 'SCB Ticker Sheet'!$B$160:$N$161
Name sh: #REF!

Sheet BERNSTEIN Cover
K5: =TODAY() -> 46226
C10: For the exclusive use of ANDREW CHUNG at BERNSTEIN on 23-Jul-2026
C15: T-Mobile (TMUS)
C16: U.S. Media & Telecom
C18: Laurent Yoon | H18: laurent.yoon@bernsteinsg.com
C19: Martin Boruchowicz | H19: martin.boruchowicz@bernsteinsg.com
C20: Andrew Chung | H20: andrew.chung@bernsteinsg.com
C32: This model is directed to and intended only for our clients who are “eligible counterparties”, “professional clients”, “institutional investors” and/or “professional investors” as defined by applicable local regulations and must not be redistributed to retail clients. This model is being provided to you with the understanding that you are an investment professional familiar with its limitations and that it may not be reproduced, re-distributed, transmitted or otherwise made available to, or shared with, any third party. Clients may not create derivative works, resell, or commercially exploit any part of the information contained herein with any third party for any purpose without Bernstein’s express prior written consent. This restriction includes extracting data, using this content to develop indexes or products, or inputting any portion of the information contained herein into machine learning or artificial intelligence systems. The analysis contained herein is based on numerous assumptions. Different assumptions could result in materially different results. We believe that the data in this model obtained from public sources is reliable; however, we make no representation that such data is accurate or complete. Estimates of future performance in this model are based on assumptions that may not be realized due to unforeseen factors like market volatility/fluctuation. This model is not a research report, nor is it a substitute for our published research; on its own, this model should not be relied upon to make an investment decision. For our latest research reports, which contain information that may be used to support investment decisions and important disclosures, please see our website at https://www.bernsteinresearch.com.

Sheet Summary
A2: T-Mobile Finanical Summary | AH2: Check sum
A3: in $ millions | B3: 1Q21 | C3: 2Q21 | D3: 3Q21 | E3: 4Q21 | F3: 2021 | G3: 1Q22 | H3: 2Q22 | I3: 3Q22 | J3: 4Q22 | K3: 2022 | L3: 1Q23 | M3: 2Q23 | N3: 3Q23 | O3: 4Q23 | P3: 2023 | Q3: 1Q24 | R3: 2Q24 | S3: 3Q24 | T3: 4Q24 | U3: 2024 | V3: 1Q25 | W3: 2Q25 | X3: 3Q25 | Y3: 4Q25 | Z3: 2025E | AA3: 1Q26 | AB3: 2Q26 | AC3: 3Q26 | AD3: 4Q26 | AE3: 2026E | AH3: 2021 | AI3: =+AH3+1 -> 2022 | AJ3: =+AI3+1 -> 2023 | AK3: =+AJ3+1 -> 2024 | AL3: =+AK3+1 -> 2025 | AM3: =+AL3+1 -> 2026
A4: Income Statement
A5: Postpaid revenues | B5: ='FC - 3FS'!L6 -> 10303 | C5: ='FC - 3FS'!M6 -> 10492 | D5: ='FC - 3FS'!N6 -> 10804 | E5: ='FC - 3FS'!O6 -> 10963 | F5: ='FC - 3FS'!AM6 -> 42562 | G5: ='FC - 3FS'!P6 -> 11201 | H5: ='FC - 3FS'!Q6 -> 11445 | I5: ='FC - 3FS'!R6 -> 11548 | J5: ='FC - 3FS'!S6 -> 11725 | K5: ='FC - 3FS'!AN6 -> 45919 | L5: ='FC - 3FS'!T6 -> 11862 | M5: ='FC - 3FS'!U6 -> 12070 | N5: ='FC - 3FS'!V6 -> 12288 | O5: ='FC - 3FS'!W6 -> 12472 | P5: ='FC - 3FS'!AO6 -> 48692 | Q5: ='FC - 3FS'!X6 -> 12631 | R5: ='FC - 3FS'!Y6 -> 12899 | S5: ='FC - 3FS'!Z6 -> 13308 | T5: ='FC - 3FS'!AA6 -> 13502 | U5: ='FC - 3FS'!AP6 -> 52340 | V5: ='FC - 3FS'!AB6 -> 13594 | W5: ='FC - 3FS'!AC6 -> 14078 | X5: ='FC - 3FS'!AD6 -> 14882 | Y5: ='FC - 3FS'!AE6 -> 15201.075 | Z5: ='FC - 3FS'!AQ6 -> 57755.075 | AA5: ='FC - 3FS'!AF6 -> 15280.936 | AB5: ='FC - 3FS'!AG6 -> 15801.255 | AC5: ='FC - 3FS'!AH6 -> 16201.782 | AD5: ='FC - 3FS'!AI6 -> 16299.262 | AE5: ='FC - 3FS'!AR6 -> 63583.234 | AH5: =+SUM(B5:E5)=F5 -> TRUE | AI5: =+SUM(G5:J5)=K5 -> TRUE | AJ5: =+SUM(L5:O5)=P5 -> TRUE | AK5: =+SUM(Q5:T5)=U5 -> TRUE | AL5: =+SUM(V5:Y5)=Z5 -> TRUE | AM5: =+SUM(AA5:AD5)=AE5 -> TRUE
A6: Prepaid revenues | B6: ='FC - 3FS'!L7 -> 2351 | C6: ='FC - 3FS'!M7 -> 2427 | D6: ='FC - 3FS'!N7 -> 2481 | E6: ='FC - 3FS'!O7 -> 2474 | F6: ='FC - 3FS'!AM7 -> 9733 | G6: ='FC - 3FS'!P7 -> 2455 | H6: ='FC - 3FS'!Q7 -> 2469 | I6: ='FC - 3FS'!R7 -> 2484 | J6: ='FC - 3FS'!S7 -> 2449 | K6: ='FC - 3FS'!AN7 -> 9857 | L6: ='FC - 3FS'!T7 -> 2417 | M6: ='FC - 3FS'!U7 -> 2444 | N6: ='FC - 3FS'!V7 -> 2473 | O6: ='FC - 3FS'!W7 -> 2433 | P6: ='FC - 3FS'!AO7 -> 9767 | Q6: ='FC - 3FS'!X7 -> 2403 | R6: ='FC - 3FS'!Y7 -> 2592 | S6: ='FC - 3FS'!Z7 -> 2716 | T6: ='FC - 3FS'!AA7 -> 2688 | U6: ='FC - 3FS'!AP7 -> 10399 | V6: ='FC - 3FS'!AB7 -> 2643 | W6: ='FC - 3FS'!AC7 -> 2643 | X6: ='FC - 3FS'!AD7 -> 2625 | Y6: ='FC - 3FS'!AE7 -> 2603.7494 | Z6: ='FC - 3FS'!AQ7 -> 10514.749 | AA6: ='FC - 3FS'!AF7 -> 2557.3003 | AB6: ='FC - 3FS'!AG7 -> 2565.5624 | AC6: ='FC - 3FS'!AH7 -> 2549.753 | AD6: ='FC - 3FS'!AI7 -> 2556.1863 | AE6: ='FC - 3FS'!AR7 -> 10228.802 | AH6: =+SUM(B6:E6)=F6 -> TRUE | AI6: =+SUM(G6:J6)=K6 -> TRUE | AJ6: =+SUM(L6:O6)=P6 -> TRUE | AK6: =+SUM(Q6:T6)=U6 -> TRUE | AL6: =+SUM(V6:Y6)=Z6 -> TRUE | AM6: =+SUM(AA6:AD6)=AE6 -> TRUE
A7: Wholesale and other service revenues | B7: ='FC - 3FS'!L8 -> 1538 | C7: ='FC - 3FS'!M8 -> 1573 | D7: ='FC - 3FS'!N8 -> 1437 | E7: ='FC - 3FS'!O8 -> 1526 | F7: ='FC - 3FS'!AM8 -> 6074 | G7: ='FC - 3FS'!P8 -> 1472 | H7: ='FC - 3FS'!Q8 -> 1402 | I7: ='FC - 3FS'!R8 -> 1329 | J7: ='FC - 3FS'!S8 -> 1344 | K7: ='FC - 3FS'!AN8 -> 5547 | L7: ='FC - 3FS'!T8 -> 1267 | M7: ='FC - 3FS'!U8 -> 1224 | N7: ='FC - 3FS'!V8 -> 1153 | O7: ='FC - 3FS'!W8 -> 1138 | P7: ='FC - 3FS'!AO8 -> 4782 | Q7: ='FC - 3FS'!X8 -> 1062 | R7: ='FC - 3FS'!Y8 -> 938 | S7: ='FC - 3FS'!Z8 -> 701 | T7: ='FC - 3FS'!AA8 -> 738 | U7: ='FC - 3FS'!AP8 -> 3439 | V7: ='FC - 3FS'!AB8 -> 688 | W7: ='FC - 3FS'!AC8 -> 717 | X7: ='FC - 3FS'!AD8 -> 734 | Y7: ='FC - 3FS'!AE8 -> 752.76 | Z7: ='FC - 3FS'!AQ8 -> 2891.76 | AA7: ='FC - 3FS'!AF8 -> 694.88 | AB7: ='FC - 3FS'!AG8 -> 731.34 | AC7: ='FC - 3FS'!AH8 -> 756.02 | AD7: ='FC - 3FS'!AI8 -> 782.8704 | AE7: ='FC - 3FS'!AR8 -> 2965.1104 | AH7: =+SUM(B7:E7)=F7 -> TRUE | AI7: =+SUM(G7:J7)=K7 -> TRUE | AJ7: =+SUM(L7:O7)=P7 -> TRUE | AK7: =+SUM(Q7:T7)=U7 -> TRUE | AL7: =+SUM(V7:Y7)=Z7 -> TRUE | AM7: =+SUM(AA7:AD7)=AE7 -> TRUE
A8: Total service revenues | B8: =+SUM(B5:B7) -> 14192 | C8: =+SUM(C5:C7) -> 14492 | D8: =+SUM(D5:D7) -> 14722 | E8: =+SUM(E5:E7) -> 14963 | F8: =+SUM(F5:F7) -> 58369 | G8: =+SUM(G5:G7) -> 15128 | H8: =+SUM(H5:H7) -> 15316 | I8: =+SUM(I5:I7) -> 15361 | ... AE8: =+SUM(AE5:AE7) -> 76777.146 | AH8: =+SUM(B8:E8)=F8 -> TRUE | AI8: =+SUM(G8:J8)=K8 -> TRUE | AJ8: =+SUM(L8:O8)=P8 -> TRUE | AK8: =+SUM(Q8:T8)=U8 -> TRUE | AL8: =+ROUND(SUM(V8:Y8),0)=ROUND(Z8,0) -> TRUE | AM8: =+SUM(AA8:AD8)=AE8 -> TRUE
A9: Equipment revenues | B9: =+'FC - 3FS'!L12 -> 5346 | C9: =+'FC - 3FS'!M12 -> 5215 | D9: =+'FC - 3FS'!N12 -> 4660 | E9: =+'FC - 3FS'!O12 -> 5506 | F9: =+'FC - 3FS'!AM12 -> 20727 | G9: =+'FC - 3FS'!P12 -> 4694 | H9: =+'FC - 3FS'!Q12 -> 4130 | I9: =+'FC - 3FS'!R12 -> 3855 | J9: =+'FC - 3FS'!S12 -> 4451 | K9: =+'FC - 3FS'!AN12 -> 17130 | L9: =+'FC - 3FS'!T12 -> 3719 | M9: =+'FC - 3FS'!U12 -> 3169 | N9: =+'FC - 3FS'!V12 -> 3076 | O9: =+'FC - 3FS'!W12 -> 4174 | P9: =+'FC - 3FS'!AO12 -> 14138 | Q9: =+'FC - 3FS'!X12 -> 3251 | R9: =+'FC - 3FS'!Y12 -> 3106 | S9: =+'FC - 3FS'!Z12 -> 3207 | T9: =+'FC - 3FS'!AA12 -> 4699 | U9: =+'FC - 3FS'!AP12 -> 14263 | V9: =+'FC - 3FS'!AB12 -> 3704 | W9: =+'FC - 3FS'!AC12 -> 3439 | X9: =+'FC - 3FS'!AD12 -> 3465 | Y9: =+'FC - 3FS'!AE12 -> 5051.1421 | Z9: =+'FC - 3FS'!AQ12 -> 15659.142 | AA9: =+'FC - 3FS'!AF12 -> 3756.7179 | AB9: =+'FC - 3FS'!AG12 -> 3782.0806 | AC9: =+'FC - 3FS'!AH12 -> 3696.9684 | AD9: =+'FC - 3FS'!AI12 -> 5317.7985 | AE9: =+'FC - 3FS'!AR12 -> 16553.565 | AH9: =+SUM(B9:E9)=F9 -> TRUE | AI9: =+SUM(G9:J9)=K9 -> TRUE | AJ9: =+SUM(L9:O9)=P9 -> TRUE | AK9: =+SUM(Q9:T9)=U9 -> TRUE | AL9: =+SUM(V9:Y9)=Z9 -> TRUE | AM9: =+SUM(AA9:AD9)=AE9 -> TRUE
A10: Other revenues | B10: =+'FC - 3FS'!L13 -> 221 | C10: =+'FC - 3FS'!M13 -> 243 | D10: =+'FC - 3FS'!N13 -> 242 | E10: =+'FC - 3FS'!O13 -> 316 | F10: =+'FC - 3FS'!AM13 -> 1022 | G10: =+'FC - 3FS'!P13 -> 298 | H10: =+'FC - 3FS'!Q13 -> 255 | I10: =+'FC - 3FS'!R13 -> 261 | J10: =+'FC - 3FS'!S13 -> 304 | K10: =+'FC - 3FS'!AN13 -> 1118 | L10: =+'FC - 3FS'!T13 -> 367 | M10: =+'FC - 3FS'!U13 -> 289 | N10: =+'FC - 3FS'!V13 -> 262 | O10: =+'FC - 3FS'!W13 -> 261 | P10: =+'FC - 3FS'!AO13 -> 1179 | Q10: =+'FC - 3FS'!X13 -> 247 | R10: =+'FC - 3FS'!Y13 -> 237 | S10: =+'FC - 3FS'!Z13 -> 230 | T10: =+'FC - 3FS'!AA13 -> 245 | U10: =+'FC - 3FS'!AP13 -> 959 | V10: =+'FC - 3FS'!AB13 -> 257 | W10: =+'FC - 3FS'!AC13 -> 255 | X10: =+'FC - 3FS'!AD13 -> 251 | Y10: =+'FC - 3FS'!AE13 -> 263.76916 | Z10: =+'FC - 3FS'!AQ13 -> 1026.7692 | AA10: =+'FC - 3FS'!AF13 -> 260.45058 | AB10: =+'FC - 3FS'!AG13 -> 280.63226 | AC10: =+'FC - 3FS'!AH13 -> 267.82291 | AD10: =+'FC - 3FS'!AI13 -> 277.70492 | AE10: =+'FC - 3FS'!AR13 -> 1086.6107 | AH10: =+SUM(B10:E10)=F10 -> TRUE | AI10: =+SUM(G10:J10)=K10 -> TRUE | AJ10: =+SUM(L10:O10)=P10 -> TRUE | AK10: =+SUM(Q10:T10)=U10 -> TRUE | AL10: =+SUM(V10:Y10)=Z10 -> TRUE | AM10: =+SUM(AA10:AD10)=AE10 -> TRUE
A11: Total revenues | B11: =+SUM(B8:B10) -> 19759 | C11: =+SUM(C8:C10) -> 19950 | D11: =+SUM(D8:D10) -> 19624 | E11: =+SUM(E8:E10) -> 20785 | F11: =+SUM(F8:F10) -> 80118 | G11: =+SUM(G8:G10) -> 20120 | H11: =+SUM(H8:H10) -> 19701 | I11: =+SUM(I8:I10) -> 19477 | ... AE11: =+SUM(AE8:AE10) -> 94417.322 | AH11: =+SUM(B11:E11)=F11 -> TRUE | AI11: =+SUM(G11:J11)=K11 -> TRUE | AJ11: =+SUM(L11:O11)=P11 -> TRUE | AK11: =+SUM(Q11:T11)=U11 -> TRUE | AL11: =+ROUND(SUM(V11:Y11),1)=ROUND(Z11,1) -> TRUE | AM11: =+SUM(AA11:AD11)=AE11 -> TRUE
A12: Operating expenses
A13: Cost of services, exclusive of D&A | B13: =+'FC - 3FS'!L16 -> 3384 | C13: =+'FC - 3FS'!M16 -> 3491 | D13: =+'FC - 3FS'!N16 -> 3538 | E13: =+'FC - 3FS'!O16 -> 3521 | F13: =+'FC - 3FS'!AM16 -> 13934 | G13: =+'FC - 3FS'!P16 -> 3727 | H13: =+'FC - 3FS'!Q16 -> 4060 | I13: =+'FC - 3FS'!R16 -> 3712 | J13: =+'FC - 3FS'!S16 -> 3167 | K13: =+'FC - 3FS'!AN16 -> 14666 | L13: =+'FC - 3FS'!T16 -> 3061 | M13: =+'FC - 3FS'!U16 -> 2916 | N13: =+'FC - 3FS'!V16 -> 2886 | O13: =+'FC - 3FS'!W16 -> 2792 | P13: =+'FC - 3FS'!AO16 -> 11655 | Q13: =+'FC - 3FS'!X16 -> 2688 | R13: =+'FC - 3FS'!Y16 -> 2664 | S13: =+'FC - 3FS'!Z16 -> 2722 | T13: =+'FC - 3FS'!AA16 -> 2697 | U13: =+'FC - 3FS'!AP16 -> 10771 | V13: =+'FC - 3FS'!AB16 -> 2602 | W13: =+'FC - 3FS'!AC16 -> 2717 | X13: =+'FC - 3FS'!AD16 -> 2873 | Y13: =+'FC - 3FS'!AE16 -> 2938.0707 | Z13: =+'FC - 3FS'!AQ16 -> 11130.071 | AA13: =+'FC - 3FS'!AF16 -> 2830.694 | AB13: =+'FC - 3FS'!AG16 -> 2956.5695 | AC13: =+'FC - 3FS'!AH16 -> 3052.9778 | AD13: =+'FC - 3FS'!AI16 -> 3089.5363 | AE13: =+'FC - 3FS'!AR16 -> 11929.777 | AH13: =+SUM(B13:E13)=F13 -> TRUE | AI13: =+SUM(G13:J13)=K13 -> TRUE | AJ13: =+SUM(L13:O13)=P13 -> TRUE | AK13: =+SUM(Q13:T13)=U13 -> TRUE | AL13: =+SUM(V13:Y13)=Z13 -> TRUE | AM13: =+SUM(AA13:AD13)=AE13 -> TRUE
A14: Cost of equipment sales, exclusive of D&A | B14: =+'FC - 3FS'!L17 -> 5142 | C14: =+'FC - 3FS'!M17 -> 5453 | D14: =+'FC - 3FS'!N17 -> 5145 | E14: =+'FC - 3FS'!O17 -> 6931 | F14: =+'FC - 3FS'!AM17 -> 22671 | G14: =+'FC - 3FS'!P17 -> 5946 | H14: =+'FC - 3FS'!Q17 -> 5108 | I14: =+'FC - 3FS'!R17 -> 4982 | J14: =+'FC - 3FS'!S17 -> 5504 | K14: =+'FC - 3FS'!AN17 -> 21540 | L14: =+'FC - 3FS'!T17 -> 4588 | M14: =+'FC - 3FS'!U17 -> 4088 | N14: =+'FC - 3FS'!V17 -> 4249 | O14: =+'FC - 3FS'!W17 -> 5608 | P14: =+'FC - 3FS'!AO17 -> 18533 | Q14: =+'FC - 3FS'!X17 -> 4399 | R14: =+'FC - 3FS'!Y17 -> 4088 | S14: =+'FC - 3FS'!Z17 -> 4307 | T14: =+'FC - 3FS'!AA17 -> 6088 | U14: =+'FC - 3FS'!AP17 -> 18882 | V14: =+'FC - 3FS'!AB17 -> 4798 | W14: =+'FC - 3FS'!AC17 -> 4659 | X14: =+'FC - 3FS'!AD17 -> 4853 | Y14: =+'FC - 3FS'!AE17 -> 6907.6944 | Z14: =+'FC - 3FS'!AQ17 -> 21217.694 | AA14: =+'FC - 3FS'!AF17 -> 4862.4198 | AB14: =+'FC - 3FS'!AG17 -> 5127.3165 | AC14: =+'FC - 3FS'!AH17 -> 5178.2652 | AD14: =+'FC - 3FS'!AI17 -> 7272.6497 | AE14: =+'FC - 3FS'!AR17 -> 22440.651 | AH14: =+SUM(B14:E14)=F14 -> TRUE | AI14: =+SUM(G14:J14)=K14 -> TRUE | AJ14: =+SUM(L14:O14)=P14 -> TRUE | AK14: =+SUM(Q14:T14)=U14 -> TRUE | AL14: =+SUM(V14:Y14)=Z14 -> TRUE | AM14: =+SUM(AA14:AD14)=AE14 -> TRUE
A15: Selling, general and administrative | B15: =+'FC - 3FS'!L18 -> 4805 | C15: =+'FC - 3FS'!M18 -> 4823 | D15: =+'FC - 3FS'!N18 -> 5212 | E15: =+'FC - 3FS'!O18 -> 5398 | F15: =+'FC - 3FS'!AM18 -> 20238 | G15: =+'FC - 3FS'!P18 -> 5056 | H15: =+'FC - 3FS'!Q18 -> 5856 | I15: =+'FC - 3FS'!R18 -> 5118 | J15: =+'FC - 3FS'!S18 -> 5577 | K15: =+'FC - 3FS'!AN18 -> 21607 | L15: =+'FC - 3FS'!T18 -> 5425 | M15: =+'FC - 3FS'!U18 -> 5272 | N15: =+'FC - 3FS'!V18 -> 5334 | O15: =+'FC - 3FS'!W18 -> 5280 | P15: =+'FC - 3FS'!AO18 -> 21311 | Q15: =+'FC - 3FS'!X18 -> 5138 | R15: =+'FC - 3FS'!Y18 -> 5142 | S15: =+'FC - 3FS'!Z18 -> 5186 | T15: =+'FC - 3FS'!AA18 -> 5352 | U15: =+'FC - 3FS'!AP18 -> 20818 | V15: =+'FC - 3FS'!AB18 -> 5488 | W15: =+'FC - 3FS'!AC18 -> 5397 | X15: =+'FC - 3FS'!AD18 -> 6015 | Y15: =+'FC - 3FS'!AE18 -> 6320.3537 | Z15: =+'FC - 3FS'!AQ18 -> 23220.354 | AA15: =+'FC - 3FS'!AF18 -> 6186.0398 | AB15: =+'FC - 3FS'!AG18 -> 6055.6418 | AC15: =+'FC - 3FS'!AH18 -> 6542.3422 | AD15: =+'FC - 3FS'!AI18 -> 6325.5909 | AE15: =+'FC - 3FS'!AR18 -> 25109.615 | AH15: =+SUM(B15:E15)=F15 -> TRUE | AI15: =+SUM(G15:J15)=K15 -> TRUE | AJ15: =+SUM(L15:O15)=P15 -> TRUE | AK15: =+SUM(Q15:T15)=U15 -> TRUE | AL15: =+SUM(V15:Y15)=Z15 -> TRUE | AM15: =+SUM(AA15:AD15)=AE15 -> TRUE
A16: Depreciation and amortization | B16: =+'FC - 3FS'!L21 -> 4289 | C16: =+'FC - 3FS'!M21 -> 4077 | D16: =+'FC - 3FS'!N21 -> 4145 | E16: =+'FC - 3FS'!O21 -> 3872 | F16: =+'FC - 3FS'!AM21 -> 16383 | G16: =+'FC - 3FS'!P21 -> 3585 | H16: =+'FC - 3FS'!Q21 -> 3491 | I16: =+'FC - 3FS'!R21 -> 3313 | J16: =+'FC - 3FS'!S21 -> 3262 | K16: =+'FC - 3FS'!AN21 -> 13651 | L16: =+'FC - 3FS'!T21 -> 3203 | M16: =+'FC - 3FS'!U21 -> 3110 | N16: =+'FC - 3FS'!V21 -> 3187 | O16: =+'FC - 3FS'!W21 -> 3318 | P16: =+'FC - 3FS'!AO21 -> 12818 | Q16: =+'FC - 3FS'!X21 -> 3371 | R16: =+'FC - 3FS'!Y21 -> 3248 | S16: =+'FC - 3FS'!Z21 -> 3151 | T16: =+'FC - 3FS'!AA21 -> 3149 | U16: =+'FC - 3FS'!AP21 -> 12919 | V16: =+'FC - 3FS'!AB21 -> 3198 | W16: =+'FC - 3FS'!AC21 -> 3146 | X16: =+'FC - 3FS'!AD21 -> 3408 | Y16: =+'FC - 3FS'!AE21 -> 3670.0321 | Z16: =+'FC - 3FS'!AQ21 -> 13422.032 | AA16: =+'FC - 3FS'!AF21 -> 3720.8608 | AB16: =+'FC - 3FS'!AG21 -> 3615.6245 | AC16: =+'FC - 3FS'!AH21 -> 3525.2306 | AD16: =+'FC - 3FS'!AI21 -> 3446.8785 | AE16: =+'FC - 3FS'!AR21 -> 14308.594 | AH16: =+SUM(B16:E16)=F16 -> TRUE | AI16: =+SUM(G16:J16)=K16 -> TRUE | AJ16: =+SUM(L16:O16)=P16 -> TRUE | AK16: =+SUM(Q16:T16)=U16 -> TRUE | AL16: =+SUM(V16:Y16)=Z16 -> TRUE | AM16: =+SUM(AA16:AD16)=AE16 -> TRUE
A17: Other OpEx | B17: =SUM('FC - 3FS'!L19:L20) -> 0 | C17: =SUM('FC - 3FS'!M19:M20) -> 0 | D17: =SUM('FC - 3FS'!N19:N20) -> 0 | E17: =SUM('FC - 3FS'!O19:O20) -> 0 | F17: =SUM('FC - 3FS'!AM19:AM20) -> 0 | G17: =SUM('FC - 3FS'!P19:P20) -> 0 | H17: =SUM('FC - 3FS'!Q19:Q20) -> 477 | I17: =SUM('FC - 3FS'!R19:R20) -> 1071 | J17: =SUM('FC - 3FS'!S19:S20) -> 16 | K17: =SUM('FC - 3FS'!AN19:AN20) -> 1564 | L17: =SUM('FC - 3FS'!T19:T20) -> -42 | M17: =SUM('FC - 3FS'!U19:U20) -> 17 | N17: =SUM('FC - 3FS'!V19:V20) -> 0 | O17: =SUM('FC - 3FS'!W19:W20) -> 0 | P17: =SUM('FC - 3FS'!AO19:AO20) -> -25 | Q17: =SUM('FC - 3FS'!X19:X20) -> 0 | R17: =SUM('FC - 3FS'!Y19:Y20) -> 0 | S17: =SUM('FC - 3FS'!Z19:Z20) -> 0 | T17: =SUM('FC - 3FS'!AA19:AA20) -> 0 | U17: =SUM('FC - 3FS'!AP19:AP20) -> 0 | V17: =SUM('FC - 3FS'!AB19:AB20) -> 0 | W17: =SUM('FC - 3FS'!AC19:AC20) -> 0 | X17: =SUM('FC - 3FS'!AD19:AD20) -> 278 | Y17: =SUM('FC - 3FS'!AE19:AE20) -> 0 | Z17: =SUM('FC - 3FS'!AQ19:AQ20) -> 278 | AA17: =SUM('FC - 3FS'!AF19:AF20) -> 0 | AB17: =SUM('FC - 3FS'!AG19:AG20) -> 0 | AC17: =SUM('FC - 3FS'!AH19:AH20) -> 0 | AD17: =SUM('FC - 3FS'!AI19:AI20) -> 0 | AE17: =SUM('FC - 3FS'!AR19:AR20) -> 0 | AH17: =+SUM(B17:E17)=F17 -> TRUE | AI17: =+SUM(G17:J17)=K17 -> TRUE | AJ17: =+SUM(L17:O17)=P17 -> TRUE | AK17: =+SUM(Q17:T17)=U17 -> TRUE | AL17: =+SUM(V17:Y17)=Z17 -> TRUE | AM17: =+SUM(AA17:AD17)=AE17 -> TRUE
A18: Operating income | B18: =B11-SUM(B13:B17) -> 2139 | C18: =C11-SUM(C13:C17) -> 2106 | D18: =D11-SUM(D13:D17) -> 1584 | E18: =E11-SUM(E13:E17) -> 1063 | F18: =F11-SUM(F13:F17) -> 6892 | G18: =G11-SUM(G13:G17) -> 1806 | H18: =H11-SUM(H13:H17) -> 709 | I18: =I11-SUM(I13:I17) -> 1281 | ... AE18: =AE11-SUM(AE13:AE17) -> 20628.685 | AH18: =+SUM(B18:E18)=F18 -> TRUE | AI18: =+SUM(G18:J18)=K18 -> TRUE | AJ18: =+SUM(L18:O18)=P18 -> TRUE | AK18: =+SUM(Q18:T18)=U18 -> TRUE | AL18: =+SUM(V18:Y18)=Z18 -> TRUE | AM18: =+SUM(AA18:AD18)=AE18 -> TRUE
A19: Other expense, net | B19: =+'FC - 3FS'!L27 -> -960 | C19: =+'FC - 3FS'!M27 -> -851 | D19: =+'FC - 3FS'!N27 -> -896 | E19: =+'FC - 3FS'!O27 -> -834 | F19: =+'FC - 3FS'!AM27 -> -3541 | G19: =+'FC - 3FS'!P27 -> -875 | H19: =+'FC - 3FS'!Q27 -> -872 | I19: =+'FC - 3FS'!R27 -> -830 | J19: =+'FC - 3FS'!S27 -> -820 | K19: =+'FC - 3FS'!AN27 -> -3397 | L19: =+'FC - 3FS'!T27 -> -826 | M19: =+'FC - 3FS'!U27 -> -855 | N19: =+'FC - 3FS'!V27 -> -749 | O19: =+'FC - 3FS'!W27 -> -837 | P19: =+'FC - 3FS'!AO27 -> -3267 | Q19: =+'FC - 3FS'!X27 -> -860 | R19: =+'FC - 3FS'!Y27 -> -862 | S19: =+'FC - 3FS'!Z27 -> -829 | T19: =+'FC - 3FS'!AA27 -> -747 | U19: =+'FC - 3FS'!AP27 -> -3298 | V19: =+'FC - 3FS'!AB27 -> -962 | W19: =+'FC - 3FS'!AC27 -> -933 | X19: =+'FC - 3FS'!AD27 -> -1002 | Y19: =+'FC - 3FS'!AE27 -> -1092.6249 | Z19: =+'FC - 3FS'!AQ27 -> -3989.6249 | AA19: =+'FC - 3FS'!AF27 -> -1011.0225 | AB19: =+'FC - 3FS'!AG27 -> -1022.2125 | AC19: =+'FC - 3FS'!AH27 -> -1051.9728 | AD19: =+'FC - 3FS'!AI27 -> -1077.5697 | AE19: =+'FC - 3FS'!AR27 -> -4162.7775 | AH19: =+SUM(B19:E19)=F19 -> TRUE | AI19: =+SUM(G19:J19)=K19 -> TRUE | AJ19: =+SUM(L19:O19)=P19 -> TRUE | AK19: =+SUM(Q19:T19)=U19 -> TRUE | AL19: =+SUM(V19:Y19)=Z19 -> TRUE | AM19: =+SUM(AA19:AD19)=AE19 -> TRUE
A20: Income (loss) before income taxes | B20: =+B18+B19 -> 1179 | C20: =+C18+C19 -> 1255 | D20: =+D18+D19 -> 688 | E20: =+E18+E19 -> 229 | F20: =+F18+F19 -> 3351 | G20: =+G18+G19 -> 931 | H20: =+H18+H19 -> -163 | I20: =+I18+I19 -> 451 | ... AE20: =+AE18+AE19 -> 16465.907 | AH20: =+SUM(B20:E20)=F20 -> TRUE | AI20: =+SUM(G20:J20)=K20 -> TRUE | AJ20: =+SUM(L20:O20)=P20 -> TRUE | AK20: =+SUM(Q20:T20)=U20 -> TRUE | AL20: =ROUND(SUM(V20:Y20),1)=ROUND(Z20,1) -> TRUE | AM20: =+SUM(AA20:AD20)=AE20 -> TRUE
A21: Income tax (expense) benefit | B21: =+'FC - 3FS'!L29 -> -246 | C21: =+'FC - 3FS'!M29 -> -277 | D21: =+'FC - 3FS'!N29 -> 3 | E21: =+'FC - 3FS'!O29 -> 193 | F21: =+'FC - 3FS'!AM29 -> -327 | G21: =+'FC - 3FS'!P29 -> -218 | H21: =+'FC - 3FS'!Q29 -> 55 | I21: =+'FC - 3FS'!R29 -> 57 | J21: =+'FC - 3FS'!S29 -> -450 | K21: =+'FC - 3FS'!AN29 -> -556 | L21: =+'FC - 3FS'!T29 -> -631 | M21: =+'FC - 3FS'!U29 -> -717 | N21: =+'FC - 3FS'!V29 -> -705 | O21: =+'FC - 3FS'!W29 -> -629 | P21: =+'FC - 3FS'!AO29 -> -2682 | Q21: =+'FC - 3FS'!X29 -> -764 | R21: =+'FC - 3FS'!Y29 -> -843 | S21: =+'FC - 3FS'!Z29 -> -908 | T21: =+'FC - 3FS'!AA29 -> -858 | U21: =+'FC - 3FS'!AP29 -> -3373 | V21: =+'FC - 3FS'!AB29 -> -885 | W21: =+'FC - 3FS'!AC29 -> -1058 | X21: =+'FC - 3FS'!AD29 -> -814 | Y21: =+'FC - 3FS'!AE29 -> -679.19148 | Z21: =+'FC - 3FS'!AQ29 -> -3436.1915 | AA21: =+'FC - 3FS'!AF29 -> -908.88543 | AB21: =+'FC - 3FS'!AG29 -> -1011.3869 | AC21: =+'FC - 3FS'!AH29 -> -950.94892 | AD21: =+'FC - 3FS'!AI29 -> -927.88543 | AE21: =+'FC - 3FS'!AR29 -> -3799.1067 | AH21: =+SUM(B21:E21)=F21 -> TRUE | AI21: =+SUM(G21:J21)=K21 -> TRUE | AJ21: =+SUM(L21:O21)=P21 -> TRUE | AK21: =+SUM(Q21:T21)=U21 -> TRUE | AL21: =+SUM(V21:Y21)=Z21 -> TRUE | AM21: =+SUM(AA21:AD21)=AE21 -> TRUE
A22: Net income (loss) | B22: =+B21+B20 -> 933 | C22: =+C21+C20 -> 978 | D22: =+D21+D20 -> 691 | E22: =+E21+E20 -> 422 | F22: =+F21+F20 -> 3024 | G22: =+G21+G20 -> 713 | H22: =+H21+H20 -> -108 | I22: =+I21+I20 -> 508 | ... AE22: =+AE21+AE20 -> 12666.801 | AH22: =+SUM(B22:E22)=F22 -> TRUE | AI22: =+SUM(G22:J22)=K22 -> TRUE | AJ22: =+SUM(L22:O22)=P22 -> TRUE | AK22: =+ROUND(SUM(Q22:T22),1)=ROUND(U22,1) -> TRUE | AL22: =+SUM(V22:Y22)=Z22 -> TRUE | AM22: =+SUM(AA22:AD22)=AE22 -> TRUE
A24: Basic EPS | B24: =+'FC - 3FS'!L35 -> 0.75028949 | C24: =+'FC - 3FS'!M35 -> 0.78392814 | D24: =+'FC - 3FS'!N35 -> 0.55360174 | E24: =+'FC - 3FS'!O35 -> 0.33779665 | F24: =+'FC - 3FS'!AM35 -> 2.4247187 | G24: =+'FC - 3FS'!P35 -> 0.5701692 | H24: =+'FC - 3FS'!Q35 -> -0.086129005 | I24: =+'FC - 3FS'!R35 -> 0.40514456 | J24: =+'FC - 3FS'!S35 -> 1.1903345 | K24: =+'FC - 3FS'!AN35 -> 2.0723914 | L24: =+'FC - 3FS'!T35 -> 1.5906746 | M24: =+'FC - 3FS'!U35 -> 1.8615701 | N24: =+'FC - 3FS'!V35 -> 1.8286805 | O24: =+'FC - 3FS'!W35 -> 1.7402374 | P24: =+'FC - 3FS'!AO35 -> 7.0178455 | Q24: =+'FC - 3FS'!X35 -> 2.002871 | R24: =+'FC - 3FS'!Y35 -> 2.4999447 | S24: =+'FC - 3FS'!Z35 -> 2.621337 | T24: =+'FC - 3FS'!AA35 -> 2.5816689 | U24: =+'FC - 3FS'!AP35 -> 9.6981225 | V24: =+'FC - 3FS'!AB35 -> 2.5891291 | W24: =+'FC - 3FS'!AC35 -> 2.8443789 | X24: =+'FC - 3FS'!AD35 -> 2.4151191 | Y24: =+'FC - 3FS'!AE35 -> 2.0011985 | Z24: =+'FC - 3FS'!AQ35 -> 9.8498256 | AA24: =+'FC - 3FS'!AF35 -> 2.7111826 | AB24: =+'FC - 3FS'!AG35 -> 3.0376562 | AC24: =+'FC - 3FS'!AH35 -> 2.8790239 | AD24: =+'FC - 3FS'!AI35 -> 2.7897559 | AE24: =+'FC - 3FS'!AR35 -> 11.417619 | AH24: =+ROUND(SUM(B24:E24),2)=ROUND(F24,2) -> FALSE | AI24: =+ROUND(SUM(G24:J24),2)=ROUND(K24,2) -> FALSE | AJ24: =ROUND(SUM(L24:O24),2)=ROUND(P24,2) -> TRUE | AK24: =ROUND(SUM(Q24:T24),2)=ROUND(U24,2) -> FALSE | AL24: =+SUM(V24:Y24)=Z24 -> TRUE | AM24: =+SUM(AA24:AD24)=AE24 -> TRUE
A25: Diluted EPS | B25: =+'FC - 3FS'!L36 -> 0.74474157 | C25: =+'FC - 3FS'!M36 -> 0.78007965 | D25: =+'FC - 3FS'!N36 -> 0.55118558 | E25: =+'FC - 3FS'!O36 -> 0.33644554 | F25: =+'FC - 3FS'!AM36 -> 2.4100036 | G25: =+'FC - 3FS'!P36 -> 0.56796068 | H25: =+'FC - 3FS'!Q36 -> -0.086129005 | I25: =+'FC - 3FS'!R36 -> 0.40342746 | J25: =+'FC - 3FS'!S36 -> 1.1845565 | K25: =+'FC - 3FS'!AN36 -> 2.0631256 | L25: =+'FC - 3FS'!T36 -> 1.5841847 | M25: =+'FC - 3FS'!U36 -> 1.857748 | N25: =+'FC - 3FS'!V36 -> 1.8239249 | O25: =+'FC - 3FS'!W36 -> 1.6713497 | P25: =+'FC - 3FS'!AO36 -> 6.9291804 | Q25: =+'FC - 3FS'!X36 -> 1.9964813 | R25: =+'FC - 3FS'!Y36 -> 2.4947815 | S25: =+'FC - 3FS'!Z36 -> 2.6130792 | T25: =+'FC - 3FS'!AA36 -> 2.5718325 | U25: =+'FC - 3FS'!AP36 -> 9.6649043 | V25: =+'FC - 3FS'!AB36 -> 2.579816 | W25: =+'FC - 3FS'!AC36 -> 2.8391493 | X25: =+'FC - 3FS'!AD36 -> 2.408959 | Y25: =+'FC - 3FS'!AE36 -> 1.9960941 | Z25: =+'FC - 3FS'!AQ36 -> 9.8240185 | AA25: =+'FC - 3FS'!AF36 -> 2.7042674 | AB25: =+'FC - 3FS'!AG36 -> 3.0299083 | AC25: =+'FC - 3FS'!AH36 -> 2.8716805 | AD25: =+'FC - 3FS'!AI36 -> 2.7826403 | AE25: =+'FC - 3FS'!AR36 -> 11.388496 | AH25: =+ROUND(SUM(B25:E25),2)=ROUND(F25,2) -> TRUE | AI25: =+ROUND(SUM(G25:J25),2)=ROUND(K25,2) -> FALSE | AJ25: =ROUND(SUM(L25:O25),2)=ROUND(P25,2) -> FALSE | AK25: =+SUM(Q25:T25)=U25 -> FALSE | AL25: =+SUM(V25:Y25)=Z25 -> TRUE | AM25: =+SUM(AA25:AD25)=AE25 -> TRUE
A26: Basic Shares Outstanding | B26: =+'FC - 3FS'!L38 -> 1243.52 | C26: =+'FC - 3FS'!M38 -> 1247.5633 | D26: =+'FC - 3FS'!N38 -> 1248.1897 | E26: =+'FC - 3FS'!O38 -> 1249.2723 | F26: =+'FC - 3FS'!AM38 -> 1247.155 | G26: =+'FC - 3FS'!P38 -> 1250.506 | H26: =+'FC - 3FS'!Q38 -> 1253.933 | I26: =+'FC - 3FS'!R38 -> 1253.8734 | J26: =+'FC - 3FS'!S38 -> 1240.8277 | K26: =+'FC - 3FS'!AN38 -> 1249.7639 | L26: =+'FC - 3FS'!T38 -> 1219.6084 | M26: =+'FC - 3FS'!U38 -> 1193.0789 | N26: =+'FC - 3FS'!V38 -> 1171.3364 | O26: =+'FC - 3FS'!W38 -> 1157.3134 | P26: =+'FC - 3FS'!AO38 -> 1185.1216 | Q26: =+'FC - 3FS'!X38 -> 1185.2985 | R26: =+'FC - 3FS'!Y38 -> 1170.0259 | S26: =+'FC - 3FS'!Z38 -> 1166.9618 | T26: =+'FC - 3FS'!AA38 -> 1154.6794 | U26: =+'FC - 3FS'!AP38 -> 1169.1954 | V26: =+'FC - 3FS'!AB38 -> 1140.5379 | W26: =+'FC - 3FS'!AC38 -> 1132.7605 | X26: =+'FC - 3FS'!AD38 -> 1123.7541 | Y26: =+'FC - 3FS'!AE38 -> 1131.5859 | Z26: =+'FC - 3FS'!AQ38 -> 1132.3579 | AA26: =+'FC - 3FS'!AF38 -> 1117.7272 | AB26: =+'FC - 3FS'!AG38 -> 1110.1053 | AC26: =+'FC - 3FS'!AH38 -> 1101.279 | AD26: =+'FC - 3FS'!AI38 -> 1108.9541 | AE26: =+'FC - 3FS'!AR38 -> 1109.4083
A27: Diluted Shares Outstanding | B27: =+'FC - 3FS'!L39 -> 1252.7836 | C27: =+'FC - 3FS'!M39 -> 1253.7181 | D27: =+'FC - 3FS'!N39 -> 1253.6612 | E27: =+'FC - 3FS'!O39 -> 1254.2892 | F27: =+'FC - 3FS'!AM39 -> 1254.7699 | G27: =+'FC - 3FS'!P39 -> 1255.3686 | H27: =+'FC - 3FS'!Q39 -> 1253.933 | I27: =+'FC - 3FS'!R39 -> 1259.2103 | J27: =+'FC - 3FS'!S39 -> 1246.8801 | K27: =+'FC - 3FS'!AN39 -> 1255.3768 | L27: =+'FC - 3FS'!T39 -> 1224.6047 | M27: =+'FC - 3FS'!U39 -> 1195.5335 | N27: =+'FC - 3FS'!V39 -> 1174.3905 | O27: =+'FC - 3FS'!W39 -> 1205.0141 | P27: =+'FC - 3FS'!AO39 -> 1200.2863 | Q27: =+'FC - 3FS'!X39 -> 1189.092 | R27: =+'FC - 3FS'!Y39 -> 1172.4474 | S27: =+'FC - 3FS'!Z39 -> 1170.6496 | T27: =+'FC - 3FS'!AA39 -> 1159.0957 | U27: =+'FC - 3FS'!AP39 -> 1173.2139 | V27: =+'FC - 3FS'!AB39 -> 1144.6553 | W27: =+'FC - 3FS'!AC39 -> 1134.847 | X27: =+'FC - 3FS'!AD39 -> 1126.6277 | Y27: =+'FC - 3FS'!AE39 -> 1134.4795 | Z27: =+'FC - 3FS'!AQ39 -> 1135.3325 | AA27: =+'FC - 3FS'!AF39 -> 1120.5854 | AB27: =+'FC - 3FS'!AG39 -> 1112.944 | AC27: =+'FC - 3FS'!AH39 -> 1104.0952 | AD27: =+'FC - 3FS'!AI39 -> 1111.7899 | AE27: =+'FC - 3FS'!AR39 -> 1112.2452
A29: Adj. EBITDA | B29: =+'FC - 3FS'!L56 -> 6905 | C29: =+'FC - 3FS'!M56 -> 6906 | D29: =+'FC - 3FS'!N56 -> 6811 | E29: =+'FC - 3FS'!O56 -> 6302 | F29: =+'FC - 3FS'!AM56 -> 26924 | G29: =+'FC - 3FS'!P56 -> 6950 | H29: =+'FC - 3FS'!Q56 -> 7004 | I29: =+'FC - 3FS'!R56 -> 7039 | J29: =+'FC - 3FS'!S56 -> 6828 | K29: =+'FC - 3FS'!AN56 -> 27821 | L29: =+'FC - 3FS'!T56 -> 7199 | M29: =+'FC - 3FS'!U56 -> 7405 | N29: =+'FC - 3FS'!V56 -> 7600 | O29: =+'FC - 3FS'!W56 -> 7224 | P29: =+'FC - 3FS'!AO56 -> 29428 | Q29: =+'FC - 3FS'!X56 -> 7652 | R29: =+'FC - 3FS'!Y56 -> 8053 | S29: =+'FC - 3FS'!Z56 -> 8243 | T29: =+'FC - 3FS'!AA56 -> 7916 | U29: =+'FC - 3FS'!AP56 -> 31864 | V29: =+'FC - 3FS'!AB56 -> 8259 | W29: =+'FC - 3FS'!AC56 -> 8547 | X29: =+'FC - 3FS'!AD56 -> 8684 | Y29: =+'FC - 3FS'!AE56 -> 8394.3925 | Z29: =+'FC - 3FS'!AQ56 -> 33884.392 | AA29: =+'FC - 3FS'!AF56 -> 9279.3016 | AB29: =+'FC - 3FS'!AG56 -> 9624.8083 | AC29: =+'FC - 3FS'!AH56 -> 9319.7855 | AD29: =+'FC - 3FS'!AI56 -> 9159.25 | AE29: =+'FC - 3FS'!AR56 -> 37383.145 | AH29: =+SUM(B29:E29)=F29 -> TRUE | AI29: =+SUM(G29:J29)=K29 -> TRUE | AJ29: =+SUM(L29:O29)=P29 -> TRUE | AK29: =+SUM(Q29:T29)=U29 -> TRUE | AL29: =+ROUND(SUM(V29:Y29),0)=ROUND(Z29,0) -> TRUE | AM29: =+SUM(AA29:AD29)=AE29 -> FALSE
A30: Adj. Core EBITDA | B30: =+'FC - 3FS'!L58 -> 5864 | C30: =+'FC - 3FS'!M58 -> 5992 | D30: =+'FC - 3FS'!N58 -> 6041 | E30: =+'FC - 3FS'!O58 -> 5679 | F30: =+'FC - 3FS'!AM58 -> 23576 | G30: =+'FC - 3FS'!P58 -> 6463 | H30: =+'FC - 3FS'!Q58 -> 6618 | I30: =+'FC - 3FS'!R58 -> 6728 | J30: =+'FC - 3FS'!S58 -> 6582 | K30: =+'FC - 3FS'!AN58 -> 26391 | L30: =+'FC - 3FS'!T58 -> 7052 | M30: =+'FC - 3FS'!U58 -> 7336 | N30: =+'FC - 3FS'!V58 -> 7547 | O30: =+'FC - 3FS'!W58 -> 7181 | P30: =+'FC - 3FS'!AO58 -> 29116 | Q30: =+'FC - 3FS'!X58 -> 7617 | R30: =+'FC - 3FS'!Y58 -> 8027 | S30: =+'FC - 3FS'!Z58 -> 8222 | T30: =+'FC - 3FS'!AA58 -> 7905 | U30: =+'FC - 3FS'!AP58 -> 31771 | V30: =+'FC - 3FS'!AB58 -> 8258 | W30: =+'FC - 3FS'!AC58 -> 8541 | X30: =+'FC - 3FS'!AD58 -> 8680 | Y30: =+'FC - 3FS'!AE58 -> 8390.3925 | Z30: =+'FC - 3FS'!AQ58 -> 33869.392 | AA30: =+'FC - 3FS'!AF58 -> 9275.3016 | AB30: =+'FC - 3FS'!AG58 -> 9620.8083 | AC30: =+'FC - 3FS'!AH58 -> 9315.7855 | AD30: =+'FC - 3FS'!AI58 -> 9155.25 | AE30: =+'FC - 3FS'!AR58 -> 37367.145 | AH30: =+SUM(B30:E30)=F30 -> TRUE | AI30: =+SUM(G30:J30)=K30 -> TRUE | AJ30: =+SUM(L30:O30)=P30 -> TRUE | AK30: =+SUM(Q30:T30)=U30 -> TRUE | AL30: =+ROUND(SUM(V30:Y30),0)=ROUND(Z30,0) -> TRUE | AM30: =+SUM(AA30:AD30)=AE30 -> FALSE
A32: Balance Sheet
A33: Total current assets | B33: =+'FC - 3FS'!L75 -> 18779 | C33: =+'FC - 3FS'!M75 -> 20570 | D33: =+'FC - 3FS'!N75 -> 16772 | E33: =+'FC - 3FS'!O75 -> 20891 | F33: =+'FC - 3FS'!AM75 -> 20891 | G33: =+'FC - 3FS'!P75 -> 17455 | H33: =+'FC - 3FS'!Q75 -> 17476 | I33: =+'FC - 3FS'!R75 -> 21427 | J33: =+'FC - 3FS'!S75 -> 19067 | K33: =+'FC - 3FS'!AN75 -> 19067 | L33: =+'FC - 3FS'!T75 -> 18876 | M33: =+'FC - 3FS'!U75 -> 20237 | N33: =+'FC - 3FS'!V75 -> 18669 | O33: =+'FC - 3FS'!W75 -> 19015 | P33: =+'FC - 3FS'!AO75 -> 19015 | Q33: =+'FC - 3FS'!X75 -> 19295 | R33: =+'FC - 3FS'!Y75 -> 19297 | S33: =+'FC - 3FS'!Z75 -> 22531 | T33: =+'FC - 3FS'!AA75 -> 18404 | U33: =+'FC - 3FS'!AP75 -> 18404 | V33: =+'FC - 3FS'!AB75 -> 27441 | W33: =+'FC - 3FS'!AC75 -> 26772 | X33: =+'FC - 3FS'!AD75 -> 21703 | Y33: =+'FC - 3FS'!AE75 -> 20285.235 | Z33: =+'FC - 3FS'!AQ75 -> 20285.235 | AA33: =+'FC - 3FS'!AF75 -> 20828.285 | AB33: =+'FC - 3FS'!AG75 -> 22703.216 | AC33: =+'FC - 3FS'!AH75 -> 25623.945 | AD33: =+'FC - 3FS'!AI75 -> 26887.641 | AE33: =+'FC - 3FS'!AR75 -> 26887.641 | AH33: =E33=F33 -> TRUE | AI33: =J33=K33 -> TRUE | AJ33: =O33=P33 -> TRUE | AK33: =T33=U33 -> TRUE | AL33: =Y33=Z33 -> TRUE | AM33: =AD33=AE33 -> TRUE
A34: Property and equipment, net | B34: =+'FC - 3FS'!L76 -> 40549 | C34: =+'FC - 3FS'!M76 -> 39752 | D34: =+'FC - 3FS'!N76 -> 39355 | E34: =+'FC - 3FS'!O76 -> 39803 | F34: =+'FC - 3FS'!AM76 -> 39803 | G34: =+'FC - 3FS'!P76 -> 40006 | H34: =+'FC - 3FS'!Q76 -> 40245 | I34: =+'FC - 3FS'!R76 -> 41034 | J34: =+'FC - 3FS'!S76 -> 42086 | K34: =+'FC - 3FS'!AN76 -> 42086 | L34: =+'FC - 3FS'!T76 -> 42053 | M34: =+'FC - 3FS'!U76 -> 41804 | N34: =+'FC - 3FS'!V76 -> 41080 | O34: =+'FC - 3FS'!W76 -> 40432 | P34: =+'FC - 3FS'!AO76 -> 40432 | Q34: =+'FC - 3FS'!X76 -> 39286 | R34: =+'FC - 3FS'!Y76 -> 38222 | S34: =+'FC - 3FS'!Z76 -> 37603 | T34: =+'FC - 3FS'!AA76 -> 38533 | U34: =+'FC - 3FS'!AP76 -> 38533 | V34: =+'FC - 3FS'!AB76 -> 37897 | W34: =+'FC - 3FS'!AC76 -> 37481 | X34: =+'FC - 3FS'!AD76 -> 38718 | Y34: =+'FC - 3FS'!AE76 -> 37585.235 | Z34: =+'FC - 3FS'!AQ76 -> 37585.235 | AA34: =+'FC - 3FS'!AF76 -> 36439.382 | AB34: =+'FC - 3FS'!AG76 -> 35450.659 | AC34: =+'FC - 3FS'!AH76 -> 34589.33 | AD34: =+'FC - 3FS'!AI76 -> 33838.887 | AE34: =+'FC - 3FS'!AR76 -> 33838.887 | AH34: =E34=F34 -> TRUE | AI34: =J34=K34 -> TRUE | AJ34: =O34=P34 -> TRUE | AK34: =T34=U34 -> TRUE | AL34: =Y34=Z34 -> TRUE | AM34: =AD34=AE34 -> TRUE
A35: Operating lease right-of-use assets | B35: =+'FC - 3FS'!L77 -> 27793 | C35: =+'FC - 3FS'!M77 -> 27511 | D35: =+'FC - 3FS'!N77 -> 27446 | E35: =+'FC - 3FS'!O77 -> 26959 | F35: =+'FC - 3FS'!AM77 -> 26959 | G35: =+'FC - 3FS'!P77 -> 31449 | H35: =+'FC - 3FS'!Q77 -> 30110 | I35: =+'FC - 3FS'!R77 -> 29264 | J35: =+'FC - 3FS'!S77 -> 28715 | K35: =+'FC - 3FS'!AN77 -> 28715 | L35: =+'FC - 3FS'!T77 -> 28146 | M35: =+'FC - 3FS'!U77 -> 27891 | N35: =+'FC - 3FS'!V77 -> 27568 | O35: =+'FC - 3FS'!W77 -> 27135 | P35: =+'FC - 3FS'!AO77 -> 27135 | Q35: =+'FC - 3FS'!X77 -> 26766 | R35: =+'FC - 3FS'!Y77 -> 26240 | S35: =+'FC - 3FS'!Z77 -> 25833 | T35: =+'FC - 3FS'!AA77 -> 25398 | U35: =+'FC - 3FS'!AP77 -> 25398 | V35: =+'FC - 3FS'!AB77 -> 25025 | W35: =+'FC - 3FS'!AC77 -> 24735 | X35: =+'FC - 3FS'!AD77 -> 26070 | Y35: =+'FC - 3FS'!AE77 -> 26969.97 | Z35: =+'FC - 3FS'!AQ77 -> 26969.97 | AA35: =+'FC - 3FS'!AF77 -> 25801.608 | AB35: =+'FC - 3FS'!AG77 -> 24589.387 | AC35: =+'FC - 3FS'!AH77 -> 26020.107 | AD35: =+'FC - 3FS'!AI77 -> 26996.866 | AE35: =+'FC - 3FS'!AR77 -> 26996.866 | AH35: =E35=F35 -> TRUE | AI35: =J35=K35 -> TRUE | AJ35: =O35=P35 -> TRUE | AK35: =T35=U35 -> TRUE | AL35: =Y35=Z35 -> TRUE | AM35: =AD35=AE35 -> TRUE
A36: Financing lease right-of-use assets | B36: =+'FC - 3FS'!L78 -> 2899 | C36: =+'FC - 3FS'!M78 -> 3072 | D36: =+'FC - 3FS'!N78 -> 3396 | E36: =+'FC - 3FS'!O78 -> 3322 | F36: =+'FC - 3FS'!AM78 -> 3322 | G36: =+'FC - 3FS'!P78 -> 3287 | H36: =+'FC - 3FS'!Q78 -> 3588 | I36: =+'FC - 3FS'!R78 -> 3619 | J36: =+'FC - 3FS'!S78 -> 3257 | K36: =+'FC - 3FS'!AN78 -> 3257 | L36: =+'FC - 3FS'!T78 -> 3282 | M36: =+'FC - 3FS'!U78 -> 3365 | N36: =+'FC - 3FS'!V78 -> 3390 | O36: =+'FC - 3FS'!W78 -> 3270 | P36: =+'FC - 3FS'!AO78 -> 3270 | Q36: =+'FC - 3FS'!X78 -> 3180 | R36: =+'FC - 3FS'!Y78 -> 3271 | S36: =+'FC - 3FS'!Z78 -> 3352 | T36: =+'FC - 3FS'!AA78 -> 3091 | U36: =+'FC - 3FS'!AP78 -> 3091 | V36: =+'FC - 3FS'!AB78 -> 2977 | W36: =+'FC - 3FS'!AC78 -> 3105 | X36: =+'FC - 3FS'!AD78 -> 2955 | Y36: =+'FC - 3FS'!AE78 -> 2962.1068 | Z36: =+'FC - 3FS'!AQ78 -> 2962.1068 | AA36: =+'FC - 3FS'!AF78 -> 2975.9763 | AB36: =+'FC - 3FS'!AG78 -> 2997.3839 | AC36: =+'FC - 3FS'!AH78 -> 3022.9234 | AD36: =+'FC - 3FS'!AI78 -> 3051.3194 | AE36: =+'FC - 3FS'!AR78 -> 3051.3194 | AH36: =E36=F36 -> TRUE | AI36: =J36=K36 -> TRUE | AJ36: =O36=P36 -> TRUE | AK36: =T36=U36 -> TRUE | AL36: =Y36=Z36 -> TRUE | AM36: =AD36=AE36 -> TRUE
A37: Goodwill | B37: =+'FC - 3FS'!L79 -> 11158 | C37: =+'FC - 3FS'!M79 -> 11152 | D37: =+'FC - 3FS'!N79 -> 12188 | E37: =+'FC - 3FS'!O79 -> 12188 | F37: =+'FC - 3FS'!AM79 -> 12188 | G37: =+'FC - 3FS'!P79 -> 12234 | H37: =+'FC - 3FS'!Q79 -> 12234 | I37: =+'FC - 3FS'!R79 -> 12234 | J37: =+'FC - 3FS'!S79 -> 12234 | K37: =+'FC - 3FS'!AN79 -> 12234 | L37: =+'FC - 3FS'!T79 -> 12234 | M37: =+'FC - 3FS'!U79 -> 12234 | N37: =+'FC - 3FS'!V79 -> 12234 | O37: =+'FC - 3FS'!W79 -> 12234 | P37: =+'FC - 3FS'!AO79 -> 12234 | Q37: =+'FC - 3FS'!X79 -> 12234 | R37: =+'FC - 3FS'!Y79 -> 13015 | S37: =+'FC - 3FS'!Z79 -> 13015 | T37: =+'FC - 3FS'!AA79 -> 13005 | U37: =+'FC - 3FS'!AP79 -> 13005 | V37: =+'FC - 3FS'!AB79 -> 13467 | W37: =+'FC - 3FS'!AC79 -> 13460 | X37: =+'FC - 3FS'!AD79 -> 13690 | Y37: =+'FC - 3FS'!AE79 -> 13690 | Z37: =+'FC - 3FS'!AQ79 -> 13690 | AA37: =+'FC - 3FS'!AF79 -> 13690 | AB37: =+'FC - 3FS'!AG79 -> 13690 | AC37: =+'FC - 3FS'!AH79 -> 13690 | AD37: =+'FC - 3FS'!AI79 -> 13690 | AE37: =+'FC - 3FS'!AR79 -> 13690 | AH37: =E37=F37 -> TRUE | AI37: =J37=K37 -> TRUE | AJ37: =O37=P37 -> TRUE | AK37: =T37=U37 -> TRUE | AL37: =Y37=Z37 -> TRUE | AM37: =AD37=AE37 -> TRUE
A38: Spectrum licenses | B38: =+'FC - 3FS'!L80 -> 82901 | C38: =+'FC - 3FS'!M80 -> 82917 | D38: =+'FC - 3FS'!N80 -> 92589 | E38: =+'FC - 3FS'!O80 -> 92606 | F38: =+'FC - 3FS'!AM80 -> 92606 | G38: =+'FC - 3FS'!P80 -> 92661 | H38: =+'FC - 3FS'!Q80 -> 95632 | I38: =+'FC - 3FS'!R80 -> 95767 | J38: =+'FC - 3FS'!S80 -> 95798 | K38: =+'FC - 3FS'!AN80 -> 95798 | L38: =+'FC - 3FS'!T80 -> 95878 | M38: =+'FC - 3FS'!U80 -> 95889 | N38: =+'FC - 3FS'!V80 -> 96689 | O38: =+'FC - 3FS'!W80 -> 96707 | P38: =+'FC - 3FS'!AO80 -> 96707 | Q38: =+'FC - 3FS'!X80 -> 97154 | R38: =+'FC - 3FS'!Y80 -> 98661 | S38: =+'FC - 3FS'!Z80 -> 98736 | T38: =+'FC - 3FS'!AA80 -> 100558 | U38: =+'FC - 3FS'!AP80 -> 100558 | V38: =+'FC - 3FS'!AB80 -> 98733 | W38: =+'FC - 3FS'!AC80 -> 95928 | X38: =+'FC - 3FS'!AD80 -> 97749 | Y38: =+'FC - 3FS'!AE80 -> 99303.702 | Z38: =+'FC - 3FS'!AQ80 -> 99303.702 | AA38: =+'FC - 3FS'!AF80 -> 100883.13 | AB38: =+'FC - 3FS'!AG80 -> 102487.68 | AC38: =+'FC - 3FS'!AH80 -> 104117.75 | AD38: =+'FC - 3FS'!AI80 -> 105773.75 | AE38: =+'FC - 3FS'!AR80 -> 105773.75 | AH38: =E38=F38 -> TRUE | AI38: =J38=K38 -> TRUE | AJ38: =O38=P38 -> TRUE | AK38: =T38=U38 -> TRUE | AL38: =Y38=Z38 -> TRUE | AM38: =AD38=AE38 -> TRUE
A39: Other long-term assets | B39: =SUM('FC - 3FS'!L81:L83) -> 19253 | C39: =SUM('FC - 3FS'!M81:M83) -> 19150 | D39: =SUM('FC - 3FS'!N81:N83) -> 10379 | E39: =SUM('FC - 3FS'!O81:O83) -> 10794 | F39: =SUM('FC - 3FS'!AM81:AM83) -> 10794 | G39: =SUM('FC - 3FS'!P81:P83) -> 13561 | H39: =SUM('FC - 3FS'!Q81:Q83) -> 10178 | I39: =SUM('FC - 3FS'!R81:R83) -> 10154 | J39: =SUM('FC - 3FS'!S81:S83) -> 10181 | K39: =SUM('FC - 3FS'!AN81:AN83) -> 10181 | L39: =SUM('FC - 3FS'!T81:T83) -> 9704 | M39: =SUM('FC - 3FS'!U81:U83) -> 9182 | N39: =SUM('FC - 3FS'!V81:V83) -> 8949 | O39: =SUM('FC - 3FS'!W81:W83) -> 8889 | P39: =SUM('FC - 3FS'!AO81:AO83) -> 8889 | Q39: =SUM('FC - 3FS'!X81:X83) -> 8353 | R39: =SUM('FC - 3FS'!Y81:Y83) -> 9851 | S39: =SUM('FC - 3FS'!Z81:Z83) -> 9672 | T39: =SUM('FC - 3FS'!AA81:AA83) -> 9046 | U39: =SUM('FC - 3FS'!AP81:AP83) -> 9046 | V39: =SUM('FC - 3FS'!AB81:AB83) -> 9093 | W39: =SUM('FC - 3FS'!AC81:AC83) -> 11162 | X39: =SUM('FC - 3FS'!AD81:AD83) -> 16295 | Y39: =SUM('FC - 3FS'!AE81:AE83) -> 16298.637 | Z39: =SUM('FC - 3FS'!AQ81:AQ83) -> 16298.637 | AA39: =SUM('FC - 3FS'!AF81:AF83) -> 16372.323 | AB39: =SUM('FC - 3FS'!AG81:AG83) -> 16489.626 | AC39: =SUM('FC - 3FS'!AH81:AH83) -> 16591.706 | AD39: =SUM('FC - 3FS'!AI81:AI83) -> 16699.875 | AE39: =SUM('FC - 3FS'!AR81:AR83) -> 16699.875 | AH39: =E39=F39 -> TRUE | AI39: =J39=K39 -> TRUE | AJ39: =O39=P39 -> TRUE | AK39: =T39=U39 -> TRUE | AL39: =Y39=Z39 -> TRUE | AM39: =AD39=AE39 -> TRUE
A40: Total assets | B40: =+SUM(B33:B39) -> 203332 | C40: =+SUM(C33:C39) -> 204124 | D40: =+SUM(D33:D39) -> 202125 | E40: =+SUM(E33:E39) -> 206563 | F40: =+SUM(F33:F39) -> 206563 | G40: =+SUM(G33:G39) -> 210653 | H40: =+SUM(H33:H39) -> 209463 | I40: =+SUM(I33:I39) -> 213499 | ... AE40: =+SUM(AE33:AE39) -> 226938.34 | AH40: =E40=F40 -> TRUE | AI40: =J40=K40 -> TRUE | AJ40: =O40=P40 -> TRUE | AK40: =T40=U40 -> TRUE | AL40: =Y40=Z40 -> TRUE | AM40: =AD40=AE40 -> TRUE
A41: short-term debt total | B41: =+'FC - 3FS'!L88+'FC - 3FS'!L89 -> 4423 | C41: =+'FC - 3FS'!M88+'FC - 3FS'!M89 -> 6883 | D41: =+'FC - 3FS'!N88+'FC - 3FS'!N89 -> 4336 | E41: =+'FC - 3FS'!O88+'FC - 3FS'!O89 -> 5623 | F41: =+'FC - 3FS'!AM88+'FC - 3FS'!AM89 -> 5623 | G41: =+'FC - 3FS'!P88+'FC - 3FS'!P89 -> 4115 | H41: =+'FC - 3FS'!Q88+'FC - 3FS'!Q89 -> 2942 | I41: =+'FC - 3FS'!R88+'FC - 3FS'!R89 -> 7398 | J41: =+'FC - 3FS'!S88+'FC - 3FS'!S89 -> 5164 | K41: =+'FC - 3FS'!AN88+'FC - 3FS'!AN89 -> 5164 | L41: =+'FC - 3FS'!T88+'FC - 3FS'!T89 -> 5215 | M41: =+'FC - 3FS'!U88+'FC - 3FS'!U89 -> 7731 | N41: =+'FC - 3FS'!V88+'FC - 3FS'!V89 -> 3437 | O41: =+'FC - 3FS'!W88+'FC - 3FS'!W89 -> 3619 | P41: =+'FC - 3FS'!AO88+'FC - 3FS'!AO89 -> 3619 | Q41: =+'FC - 3FS'!X88+'FC - 3FS'!X89 -> 5356 | R41: =+'FC - 3FS'!Y88+'FC - 3FS'!Y89 -> 5867 | S41: =+'FC - 3FS'!Z88+'FC - 3FS'!Z89 -> 5851 | T41: =+'FC - 3FS'!AA88+'FC - 3FS'!AA89 -> 4068 | U41: =+'FC - 3FS'!AP88+'FC - 3FS'!AP89 -> 4068 | V41: =+'FC - 3FS'!AB88+'FC - 3FS'!AB89 -> 8214 | W41: =+'FC - 3FS'!AC88+'FC - 3FS'!AC89 -> 6408 | X41: =+'FC - 3FS'!AD88+'FC - 3FS'!AD89 -> 6333 | Y41: =+'FC - 3FS'!AE88+'FC - 3FS'!AE89 -> 6333 | Z41: =+'FC - 3FS'!AQ88+'FC - 3FS'!AQ89 -> 6333 | AA41: =+'FC - 3FS'!AF88+'FC - 3FS'!AF89 -> 6333 | AB41: =+'FC - 3FS'!AG88+'FC - 3FS'!AG89 -> 6333 | AC41: =+'FC - 3FS'!AH88+'FC - 3FS'!AH89 -> 6333 | AD41: =+'FC - 3FS'!AI88+'FC - 3FS'!AI89 -> 6333 | AE41: =+'FC - 3FS'!AR88+'FC - 3FS'!AR89 -> 6333 | AH41: =E41=F41 -> TRUE | AI41: =J41=K41 -> TRUE | AJ41: =O41=P41 -> TRUE | AK41: =T41=U41 -> TRUE | AL41: =Y41=Z41 -> TRUE | AM41: =AD41=AE41 -> TRUE
A42: Short-term financing lease liabilities | B42: =+'FC - 3FS'!L92 -> 1013 | C42: =+'FC - 3FS'!M92 -> 1045 | D42: =+'FC - 3FS'!N92 -> 1154 | E42: =+'FC - 3FS'!O92 -> 1120 | F42: =+'FC - 3FS'!AM92 -> 1120 | G42: =+'FC - 3FS'!P92 -> 1121 | H42: =+'FC - 3FS'!Q92 -> 1220 | I42: =+'FC - 3FS'!R92 -> 1239 | J42: =+'FC - 3FS'!S92 -> 1161 | K42: =+'FC - 3FS'!AN92 -> 1161 | L42: =+'FC - 3FS'!T92 -> 1180 | M42: =+'FC - 3FS'!U92 -> 1220 | N42: =+'FC - 3FS'!V92 -> 1286 | O42: =+'FC - 3FS'!W92 -> 1260 | P42: =+'FC - 3FS'!AO92 -> 1260 | Q42: =+'FC - 3FS'!X92 -> 1265 | R42: =+'FC - 3FS'!Y92 -> 1252 | S42: =+'FC - 3FS'!Z92 -> 1252 | T42: =+'FC - 3FS'!AA92 -> 1175 | U42: =+'FC - 3FS'!AP92 -> 1175 | V42: =+'FC - 3FS'!AB92 -> 1136 | W42: =+'FC - 3FS'!AC92 -> 1157 | X42: =+'FC - 3FS'!AD92 -> 1157 | Y42: =+'FC - 3FS'!AE92 -> 1159.7826 | Z42: =+'FC - 3FS'!AQ92 -> 1159.7826 | AA42: =+'FC - 3FS'!AF92 -> 1165.2131 | AB42: =+'FC - 3FS'!AG92 -> 1173.595 | AC42: =+'FC - 3FS'!AH92 -> 1183.5947 | AD42: =+'FC - 3FS'!AI92 -> 1194.7129 | AE42: =+'FC - 3FS'!AR92 -> 1194.7129 | AH42: =E42=F42 -> TRUE | AI42: =J42=K42 -> TRUE | AJ42: =O42=P42 -> TRUE | AK42: =T42=U42 -> TRUE | AL42: =Y42=Z42 -> TRUE | AM42: =AD42=AE42 -> TRUE
A43: Other current liabilities | B43: =+SUM('FC - 3FS'!L87,'FC - 3FS'!L90,'FC - 3FS'!L91,'FC - 3FS'!L93) -> 14059 | C43: =+SUM('FC - 3FS'!M87,'FC - 3FS'!M90,'FC - 3FS'!M91,'FC - 3FS'!M93) -> 13909 | D43: =+SUM('FC - 3FS'!N87,'FC - 3FS'!N90,'FC - 3FS'!N91,'FC - 3FS'!N93) -> 13757 | E43: =+SUM('FC - 3FS'!O87,'FC - 3FS'!O90,'FC - 3FS'!O91,'FC - 3FS'!O93) -> 16756 | F43: =+SUM('FC - 3FS'!AM87,'FC - 3FS'!AM90,'FC - 3FS'!AM91,'FC - 3FS'!AM93) -> 16756 | G43: =+SUM('FC - 3FS'!P87,'FC - 3FS'!P90,'FC - 3FS'!P91,'FC - 3FS'!P93) -> 16187 | H43: =+SUM('FC - 3FS'!Q87,'FC - 3FS'!Q90,'FC - 3FS'!Q91,'FC - 3FS'!Q93) -> 16460 | I43: =+SUM('FC - 3FS'!R87,'FC - 3FS'!R90,'FC - 3FS'!R91,'FC - 3FS'!R93) -> 17725 | J43: =+SUM('FC - 3FS'!S87,'FC - 3FS'!S90,'FC - 3FS'!S91,'FC - 3FS'!S93) -> 18417 | K43: =+SUM('FC - 3FS'!AN87,'FC - 3FS'!AN90,'FC - 3FS'!AN91,'FC - 3FS'!AN93) -> 18417 | L43: =+SUM('FC - 3FS'!T87,'FC - 3FS'!T90,'FC - 3FS'!T91,'FC - 3FS'!T93) -> 17451 | M43: =+SUM('FC - 3FS'!U87,'FC - 3FS'!U90,'FC - 3FS'!U91,'FC - 3FS'!U93) -> 15618 | N43: =+SUM('FC - 3FS'!V87,'FC - 3FS'!V90,'FC - 3FS'!V91,'FC - 3FS'!V93) -> 16988 | O43: =+SUM('FC - 3FS'!W87,'FC - 3FS'!W90,'FC - 3FS'!W91,'FC - 3FS'!W93) -> 16049 | P43: =+SUM('FC - 3FS'!AO87,'FC - 3FS'!AO90,'FC - 3FS'!AO91,'FC - 3FS'!AO93) -> 16049 | Q43: =+SUM('FC - 3FS'!X87,'FC - 3FS'!X90,'FC - 3FS'!X91,'FC - 3FS'!X93) -> 13942 | R43: =+SUM('FC - 3FS'!Y87,'FC - 3FS'!Y90,'FC - 3FS'!Y91,'FC - 3FS'!Y93) -> 15919 | S43: =+SUM('FC - 3FS'!Z87,'FC - 3FS'!Z90,'FC - 3FS'!Z91,'FC - 3FS'!Z93) -> 13852 | T43: =+SUM('FC - 3FS'!AA87,'FC - 3FS'!AA90,'FC - 3FS'!AA91,'FC - 3FS'!AA93) -> 14931 | U43: =+SUM('FC - 3FS'!AP87,'FC - 3FS'!AP90,'FC - 3FS'!AP91,'FC - 3FS'!AP93) -> 14931 | V43: =+SUM('FC - 3FS'!AB87,'FC - 3FS'!AB90,'FC - 3FS'!AB91,'FC - 3FS'!AB93) -> 14279 | W43: =+SUM('FC - 3FS'!AC87,'FC - 3FS'!AC90,'FC - 3FS'!AC91,'FC - 3FS'!AC93) -> 14537 | X43: =+SUM('FC - 3FS'!AD87,'FC - 3FS'!AD90,'FC - 3FS'!AD91,'FC - 3FS'!AD93) -> 16811 | Y43: =+SUM('FC - 3FS'!AE87,'FC - 3FS'!AE90,'FC - 3FS'!AE91,'FC - 3FS'!AE93) -> 16204.003 | Z43: =+SUM('FC - 3FS'!AQ87,'FC - 3FS'!AQ90,'FC - 3FS'!AQ91,'FC - 3FS'!AQ93) -> 16204.003 | AA43: =+SUM('FC - 3FS'!AF87,'FC - 3FS'!AF90,'FC - 3FS'!AF91,'FC - 3FS'!AF93) -> 15235.393 | AB43: =+SUM('FC - 3FS'!AG87,'FC - 3FS'!AG90,'FC - 3FS'!AG91,'FC - 3FS'!AG93) -> 15284.423 | AC43: =+SUM('FC - 3FS'!AH87,'FC - 3FS'!AH90,'FC - 3FS'!AH91,'FC - 3FS'!AH93) -> 16936.214 | AD43: =+SUM('FC - 3FS'!AI87,'FC - 3FS'!AI90,'FC - 3FS'!AI91,'FC - 3FS'!AI93) -> 16950.536 | AE43: =+SUM('FC - 3FS'!AR87,'FC - 3FS'!AR90,'FC - 3FS'!AR91,'FC - 3FS'!AR93) -> 16950.536 | AH43: =E43=F43 -> TRUE | AI43: =J43=K43 -> TRUE | AJ43: =O43=P43 -> TRUE | AK43: =T43=U43 -> TRUE | AL43: =Y43=Z43 -> TRUE | AM43: =AD43=AE43 -> TRUE
A44: Total current liabilities | B44: =+SUM(B41:B43) -> 19495 | C44: =+SUM(C41:C43) -> 21837 | D44: =+SUM(D41:D43) -> 19247 | E44: =+SUM(E41:E43) -> 23499 | F44: =+SUM(F41:F43) -> 23499 | G44: =+SUM(G41:G43) -> 21423 | H44: =+SUM(H41:H43) -> 20622 | I44: =+SUM(I41:I43) -> 26362 | ... AE44: =+SUM(AE41:AE43) -> 24478.248 | AH44: =E44=F44 -> TRUE | AI44: =J44=K44 -> TRUE | AJ44: =O44=P44 -> TRUE | AK44: =T44=U44 -> TRUE | AL44: =Y44=Z44 -> TRUE | AM44: =AD44=AE44 -> TRUE
A45: Long-term debt total | B45: =+'FC - 3FS'!L96+'FC - 3FS'!L95 -> 71116 | C45: =+'FC - 3FS'!M96+'FC - 3FS'!M95 -> 68387 | D45: =+'FC - 3FS'!N96+'FC - 3FS'!N95 -> 68139 | E45: =+'FC - 3FS'!O96+'FC - 3FS'!O95 -> 68570 | F45: =+'FC - 3FS'!AM96+'FC - 3FS'!AM95 -> 68570 | G45: =+'FC - 3FS'!P96+'FC - 3FS'!P95 -> 68355 | H45: =+'FC - 3FS'!Q96+'FC - 3FS'!Q95 -> 68047 | I45: =+'FC - 3FS'!R96+'FC - 3FS'!R95 -> 66329 | J45: =+'FC - 3FS'!S96+'FC - 3FS'!S95 -> 66796 | K45: =+'FC - 3FS'!AN96+'FC - 3FS'!AN95 -> 66796 | L45: =+'FC - 3FS'!T96+'FC - 3FS'!T95 -> 69530 | M45: =+'FC - 3FS'!U96+'FC - 3FS'!U95 -> 70141 | N45: =+'FC - 3FS'!V96+'FC - 3FS'!V95 -> 71861 | O45: =+'FC - 3FS'!W96+'FC - 3FS'!W95 -> 71399 | P45: =+'FC - 3FS'!AO96+'FC - 3FS'!AO95 -> 71399 | Q45: =+'FC - 3FS'!X96+'FC - 3FS'!X95 -> 72857 | R45: =+'FC - 3FS'!Y96+'FC - 3FS'!Y95 -> 71699 | S45: =+'FC - 3FS'!Z96+'FC - 3FS'!Z95 -> 74019 | T45: =+'FC - 3FS'!AA96+'FC - 3FS'!AA95 -> 74197 | U45: =+'FC - 3FS'!AP96+'FC - 3FS'!AP95 -> 74197 | V45: =+'FC - 3FS'!AB96+'FC - 3FS'!AB95 -> 77530 | W45: =+'FC - 3FS'!AC96+'FC - 3FS'!AC95 -> 76515 | X45: =+'FC - 3FS'!AD96+'FC - 3FS'!AD95 -> 77863 | Y45: =+'FC - 3FS'!AE96+'FC - 3FS'!AE95 -> 77595.299 | Z45: =+'FC - 3FS'!AQ96+'FC - 3FS'!AQ95 -> 77595.299 | AA45: =+'FC - 3FS'!AF96+'FC - 3FS'!AF95 -> 79116.123 | AB45: =+'FC - 3FS'!AG96+'FC - 3FS'!AG95 -> 80667.635 | AC45: =+'FC - 3FS'!AH96+'FC - 3FS'!AH95 -> 82250.455 | AD45: =+'FC - 3FS'!AI96+'FC - 3FS'!AI95 -> 83865.213 | AE45: =+'FC - 3FS'!AR96+'FC - 3FS'!AR95 -> 83865.213 | AH45: =E45=F45 -> TRUE | AI45: =J45=K45 -> TRUE | AJ45: =O45=P45 -> TRUE | AK45: =T45=U45 -> TRUE | AL45: =Y45=Z45 -> TRUE | AM45: =AD45=AE45 -> TRUE
A46: Financing lease liabilities | B46: =+'FC - 3FS'!L100 -> 1316 | C46: =+'FC - 3FS'!M100 -> 1376 | D46: =+'FC - 3FS'!N100 -> 1587 | E46: =+'FC - 3FS'!O100 -> 1455 | F46: =+'FC - 3FS'!AM100 -> 1455 | G46: =+'FC - 3FS'!P100 -> 1447 | H46: =+'FC - 3FS'!Q100 -> 1597 | I46: =+'FC - 3FS'!R100 -> 1590 | J46: =+'FC - 3FS'!S100 -> 1370 | K46: =+'FC - 3FS'!AN100 -> 1370 | L46: =+'FC - 3FS'!T100 -> 1284 | M46: =+'FC - 3FS'!U100 -> 1254 | N46: =+'FC - 3FS'!V100 -> 1273 | O46: =+'FC - 3FS'!W100 -> 1236 | P46: =+'FC - 3FS'!AO100 -> 1236 | Q46: =+'FC - 3FS'!X100 -> 1163 | R46: =+'FC - 3FS'!Y100 -> 1133 | S46: =+'FC - 3FS'!Z100 -> 1185 | T46: =+'FC - 3FS'!AA100 -> 1151 | U46: =+'FC - 3FS'!AP100 -> 1151 | V46: =+'FC - 3FS'!AB100 -> 1117 | W46: =+'FC - 3FS'!AC100 -> 1188 | X46: =+'FC - 3FS'!AD100 -> 1186 | Y46: =+'FC - 3FS'!AE100 -> 1188.8524 | Z46: =+'FC - 3FS'!AQ100 -> 1188.8524 | AA46: =+'FC - 3FS'!AF100 -> 1194.4189 | AB46: =+'FC - 3FS'!AG100 -> 1203.0109 | AC46: =+'FC - 3FS'!AH100 -> 1213.2613 | AD46: =+'FC - 3FS'!AI100 -> 1224.6581 | AE46: =+'FC - 3FS'!AR100 -> 1224.6581 | AH46: =E46=F46 -> TRUE | AI46: =J46=K46 -> TRUE | AJ46: =O46=P46 -> TRUE | AK46: =T46=U46 -> TRUE | AL46: =Y46=Z46 -> TRUE | AM46: =AD46=AE46 -> TRUE
A47: Other long-term liabilities | B47: =+SUM('FC - 3FS'!L97,'FC - 3FS'!L98,'FC - 3FS'!L99,'FC - 3FS'!L101) -> 45028 | C47: =+SUM('FC - 3FS'!M97,'FC - 3FS'!M98,'FC - 3FS'!M99,'FC - 3FS'!M101) -> 45054 | D47: =+SUM('FC - 3FS'!N97,'FC - 3FS'!N98,'FC - 3FS'!N99,'FC - 3FS'!N101) -> 44725 | E47: =+SUM('FC - 3FS'!O97,'FC - 3FS'!O98,'FC - 3FS'!O99,'FC - 3FS'!O101) -> 43937 | F47: =+SUM('FC - 3FS'!AM97,'FC - 3FS'!AM98,'FC - 3FS'!AM99,'FC - 3FS'!AM101) -> 43937 | G47: =+SUM('FC - 3FS'!P97,'FC - 3FS'!P98,'FC - 3FS'!P99,'FC - 3FS'!P101) -> 49452 | H47: =+SUM('FC - 3FS'!Q97,'FC - 3FS'!Q98,'FC - 3FS'!Q99,'FC - 3FS'!Q101) -> 49163 | I47: =+SUM('FC - 3FS'!R97,'FC - 3FS'!R98,'FC - 3FS'!R99,'FC - 3FS'!R101) -> 49068 | J47: =+SUM('FC - 3FS'!S97,'FC - 3FS'!S98,'FC - 3FS'!S99,'FC - 3FS'!S101) -> 48774 | K47: =+SUM('FC - 3FS'!AN97,'FC - 3FS'!AN98,'FC - 3FS'!AN99,'FC - 3FS'!AN101) -> 48774 | L47: =+SUM('FC - 3FS'!T97,'FC - 3FS'!T98,'FC - 3FS'!T99,'FC - 3FS'!T101) -> 48588 | M47: =+SUM('FC - 3FS'!U97,'FC - 3FS'!U98,'FC - 3FS'!U99,'FC - 3FS'!U101) -> 48888 | N47: =+SUM('FC - 3FS'!V97,'FC - 3FS'!V98,'FC - 3FS'!V99,'FC - 3FS'!V101) -> 49036 | O47: =+SUM('FC - 3FS'!W97,'FC - 3FS'!W98,'FC - 3FS'!W99,'FC - 3FS'!W101) -> 49404 | P47: =+SUM('FC - 3FS'!AO97,'FC - 3FS'!AO98,'FC - 3FS'!AO99,'FC - 3FS'!AO101) -> 49404 | Q47: =+SUM('FC - 3FS'!X97,'FC - 3FS'!X98,'FC - 3FS'!X99,'FC - 3FS'!X101) -> 49611 | R47: =+SUM('FC - 3FS'!Y97,'FC - 3FS'!Y98,'FC - 3FS'!Y99,'FC - 3FS'!Y101) -> 50051 | S47: =+SUM('FC - 3FS'!Z97,'FC - 3FS'!Z98,'FC - 3FS'!Z99,'FC - 3FS'!Z101) -> 50333 | T47: =+SUM('FC - 3FS'!AA97,'FC - 3FS'!AA98,'FC - 3FS'!AA99,'FC - 3FS'!AA101) -> 50772 | U47: =+SUM('FC - 3FS'!AP97,'FC - 3FS'!AP98,'FC - 3FS'!AP99,'FC - 3FS'!AP101) -> 50772 | V47: =+SUM('FC - 3FS'!AB97,'FC - 3FS'!AB98,'FC - 3FS'!AB99,'FC - 3FS'!AB101) -> 51252 | W47: =+SUM('FC - 3FS'!AC97,'FC - 3FS'!AC98,'FC - 3FS'!AC99,'FC - 3FS'!AC101) -> 51731 | X47: =+SUM('FC - 3FS'!AD97,'FC - 3FS'!AD98,'FC - 3FS'!AD99,'FC - 3FS'!AD101) -> 53353 | Y47: =+SUM('FC - 3FS'!AE97,'FC - 3FS'!AE98,'FC - 3FS'!AE99,'FC - 3FS'!AE101) -> 55216.863 | Z47: =+SUM('FC - 3FS'!AQ97,'FC - 3FS'!AQ98,'FC - 3FS'!AQ99,'FC - 3FS'!AQ101) -> 55216.863 | AA47: =+SUM('FC - 3FS'!AF97,'FC - 3FS'!AF98,'FC - 3FS'!AF99,'FC - 3FS'!AF101) -> 55103.548 | AB47: =+SUM('FC - 3FS'!AG97,'FC - 3FS'!AG98,'FC - 3FS'!AG99,'FC - 3FS'!AG101) -> 55112.837 | AC47: =+SUM('FC - 3FS'!AH97,'FC - 3FS'!AH98,'FC - 3FS'!AH99,'FC - 3FS'!AH101) -> 57488.608 | AD47: =+SUM('FC - 3FS'!AI97,'FC - 3FS'!AI98,'FC - 3FS'!AI99,'FC - 3FS'!AI101) -> 59725.747 | AE47: =+SUM('FC - 3FS'!AR97,'FC - 3FS'!AR98,'FC - 3FS'!AR99,'FC - 3FS'!AR101) -> 59725.747 | AH47: =E47=F47 -> TRUE | AI47: =J47=K47 -> TRUE | AJ47: =O47=P47 -> TRUE | AK47: =T47=U47 -> TRUE | AL47: =Y47=Z47 -> TRUE | AM47: =AD47=AE47 -> TRUE
A48: Total long-term liabilities | B48: =+SUM(B45:B47) -> 117460 | C48: =+SUM(C45:C47) -> 114817 | D48: =+SUM(D45:D47) -> 114451 | E48: =+SUM(E45:E47) -> 113962 | F48: =+SUM(F45:F47) -> 113962 | G48: =+SUM(G45:G47) -> 119254 | H48: =+SUM(H45:H47) -> 118807 | I48: =+SUM(I45:I47) -> 116987 | ... AE48: =+SUM(AE45:AE47) -> 144815.62 | AH48: =E48=F48 -> TRUE | AI48: =J48=K48 -> TRUE | AJ48: =O48=P48 -> TRUE | AK48: =T48=U48 -> TRUE | AL48: =Y48=Z48 -> TRUE | AM48: =AD48=AE48 -> TRUE
A49: Total stockholders' equity | B49: ='FC - 3FS'!L110 -> 66377 | C49: ='FC - 3FS'!M110 -> 67470 | D49: ='FC - 3FS'!N110 -> 68427 | E49: ='FC - 3FS'!O110 -> 69102 | F49: ='FC - 3FS'!AM110 -> 69102 | G49: ='FC - 3FS'!P110 -> 69976 | H49: ='FC - 3FS'!Q110 -> 70034 | I49: ='FC - 3FS'!R110 -> 70150 | J49: ='FC - 3FS'!S110 -> 69656 | K49: ='FC - 3FS'!AN110 -> 69656 | L49: ='FC - 3FS'!T110 -> 66925 | M49: ='FC - 3FS'!U110 -> 65750 | N49: ='FC - 3FS'!V110 -> 64698 | O49: ='FC - 3FS'!W110 -> 64715 | P49: ='FC - 3FS'!AO110 -> 64715 | Q49: ='FC - 3FS'!X110 -> 62074 | R49: ='FC - 3FS'!Y110 -> 62636 | S49: ='FC - 3FS'!Z110 -> 64250 | T49: ='FC - 3FS'!AA110 -> 61741 | U49: ='FC - 3FS'!AP110 -> 61741 | V49: ='FC - 3FS'!AB110 -> 61105 | W49: ='FC - 3FS'!AC110 -> 61107 | X49: ='FC - 3FS'!AD110 -> 60477 | Y49: ='FC - 3FS'!AE110 -> 59397.085 | Z49: ='FC - 3FS'!AQ110 -> 59397.085 | AA49: ='FC - 3FS'!AF110 -> 58843.01 | AB49: ='FC - 3FS'!AG110 -> 58633.452 | AC49: ='FC - 3FS'!AH110 -> 58250.631 | AD49: ='FC - 3FS'!AI110 -> 57644.472 | AE49: ='FC - 3FS'!AR110 -> 57644.472 | AH49: =E49=F49 -> TRUE | AI49: =J49=K49 -> TRUE | AJ49: =O49=P49 -> TRUE | AK49: =T49=U49 -> TRUE | AL49: =Y49=Z49 -> TRUE | AM49: =AD49=AE49 -> TRUE
A50: Total liabilities and stockholders' equity | B50: =B49+B48+B44 -> 203332 | C50: =C49+C48+C44 -> 204124 | D50: =D49+D48+D44 -> 202125 | E50: =E49+E48+E44 -> 206563 | F50: =F49+F48+F44 -> 206563 | G50: =G49+G48+G44 -> 210653 | H50: =H49+H48+H44 -> 209463 | I50: =I49+I48+I44 -> 213499 | ... AE50: =AE49+AE48+AE44 -> 226938.34 | AH50: =E50=F50 -> TRUE | AI50: =J50=K50 -> TRUE | AJ50: =O50=P50 -> TRUE | AK50: =T50=U50 -> TRUE | AL50: =Y50=Z50 -> TRUE | AM50: =AD50=AE50 -> TRUE
B51: =+B40-B50 -> 0 | C51: =+C40-C50 -> 0 | D51: =+D40-D50 -> 0 | E51: =+E40-E50 -> 0 | F51: =+F40-F50 -> 0 | G51: =+G40-G50 -> 0 | H51: =+H40-H50 -> 0 | I51: =+I40-I50 -> 0 | ... AE51: =+AE40-AE50 -> 0
A52: Cash Flow Statements
A53: Cash provided by operating activities | B53: =+'FC - 3FS'!L140 -> 3661 | C53: =+'FC - 3FS'!M140 -> 3779 | D53: =+'FC - 3FS'!N140 -> 3477 | E53: =+'FC - 3FS'!O140 -> 3000 | F53: =+'FC - 3FS'!AM140 -> 13917 | G53: =+'FC - 3FS'!P140 -> 3845 | H53: =+'FC - 3FS'!Q140 -> 4209 | I53: =+'FC - 3FS'!R140 -> 4391 | J53: =+'FC - 3FS'!S140 -> 4336 | K53: =+'FC - 3FS'!AN140 -> 16781 | L53: =+'FC - 3FS'!T140 -> 4051 | M53: =+'FC - 3FS'!U140 -> 4355 | N53: =+'FC - 3FS'!V140 -> 5294 | O53: =+'FC - 3FS'!W140 -> 4859 | P53: =+'FC - 3FS'!AO140 -> 18559 | Q53: =+'FC - 3FS'!X140 -> 5084 | R53: =+'FC - 3FS'!Y140 -> 5521 | S53: =+'FC - 3FS'!Z140 -> 6139 | T53: =+'FC - 3FS'!AA140 -> 5549 | U53: =+'FC - 3FS'!AP140 -> 22293 | V53: =+'FC - 3FS'!AB140 -> 6847 | W53: =+'FC - 3FS'!AC140 -> 6992 | X53: =+'FC - 3FS'!AD140 -> 7457 | Y53: =+'FC - 3FS'!AE140 -> 6550.8663 | Z53: =+'FC - 3FS'!AQ140 -> 27846.866 | AA53: =+'FC - 3FS'!AF140 -> 6823.6751 | AB53: =+'FC - 3FS'!AG140 -> 7968.6219 | AC53: =+'FC - 3FS'!AH140 -> 8840.6826 | AD53: =+'FC - 3FS'!AI140 -> 7880.2164 | AE53: =+'FC - 3FS'!AR140 -> 31513.196 | AH53: =+ROUND(SUM(B53:E53),1)=ROUND(F53,1) -> TRUE | AI53: =+SUM(G53:J53)=K53 -> TRUE | AJ53: =+SUM(L53:O53)=P53 -> TRUE | AK53: =+SUM(Q53:T53)=U53 -> TRUE | AL53: =+SUM(V53:Y53)=Z53 -> TRUE | AM53: =+SUM(AA53:AD53)=AE53 -> TRUE
A54: Cash used in investing activities | B54: =+'FC - 3FS'!L148 -> -11239 | C54: =+'FC - 3FS'!M148 -> -2083 | D54: =+'FC - 3FS'!N148 -> -4152 | E54: =+'FC - 3FS'!O148 -> -1912 | F54: =+'FC - 3FS'!AM148 -> -19386 | G54: =+'FC - 3FS'!P148 -> -5092 | H54: =+'FC - 3FS'!Q148 -> -2559 | I54: =+'FC - 3FS'!R148 -> -2555 | J54: =+'FC - 3FS'!S148 -> -2153 | K54: =+'FC - 3FS'!AN148 -> -12359 | L54: =+'FC - 3FS'!T148 -> -1728 | M54: =+'FC - 3FS'!U148 -> -1487 | N54: =+'FC - 3FS'!V148 -> -1393 | O54: =+'FC - 3FS'!W148 -> -1221 | P54: =+'FC - 3FS'!AO148 -> -5829 | Q54: =+'FC - 3FS'!X148 -> -1787 | R54: =+'FC - 3FS'!Y148 -> -1678 | S54: =+'FC - 3FS'!Z148 -> -3307 | T54: =+'FC - 3FS'!AA148 -> -2300 | U54: =+'FC - 3FS'!AP148 -> -9072 | V54: =+'FC - 3FS'!AB148 -> -3409 | W54: =+'FC - 3FS'!AC148 -> -1559 | X54: =+'FC - 3FS'!AD148 -> -10139 | Y54: =+'FC - 3FS'!AE148 -> -4157.45 | Z54: =+'FC - 3FS'!AQ148 -> -19264.45 | AA54: =+'FC - 3FS'!AF148 -> -4220.9603 | AB54: =+'FC - 3FS'!AG148 -> -4299.032 | AC54: =+'FC - 3FS'!AH148 -> -4362.6279 | AD54: =+'FC - 3FS'!AI148 -> -4422.1803 | AE54: =+'FC - 3FS'!AR148 -> -17304.801 | AH54: =+SUM(B54:E54)=F54 -> TRUE | AI54: =+SUM(G54:J54)=K54 -> TRUE | AJ54: =+SUM(L54:O54)=P54 -> TRUE | AK54: =+SUM(Q54:T54)=U54 -> TRUE | AL54: =+SUM(V54:Y54)=Z54 -> TRUE | AM54: =+SUM(AA54:AD54)=AE54 -> TRUE
A55: Cash (used in) provided by financing activities | B55: =+'FC - 3FS'!L161 -> 3874 | C55: =+'FC - 3FS'!M161 -> -577 | D55: =+'FC - 3FS'!N161 -> -3060 | E55: =+'FC - 3FS'!O161 -> 1472 | F55: =+'FC - 3FS'!AM161 -> 1709 | G55: =+'FC - 3FS'!P161 -> -2136 | H55: =+'FC - 3FS'!Q161 -> -1744 | I55: =+'FC - 3FS'!R161 -> 1927 | J55: =+'FC - 3FS'!S161 -> -4498 | K55: =+'FC - 3FS'!AN161 -> -6451 | L55: =+'FC - 3FS'!T161 -> -2273 | M55: =+'FC - 3FS'!U161 -> -784 | N55: =+'FC - 3FS'!V161 -> -5510 | O55: =+'FC - 3FS'!W161 -> -3530 | P55: =+'FC - 3FS'!AO161 -> -12097 | Q55: =+'FC - 3FS'!X161 -> -1666 | R55: =+'FC - 3FS'!Y161 -> -4134 | S55: =+'FC - 3FS'!Z161 -> 507 | T55: =+'FC - 3FS'!AA161 -> -7522 | U55: =+'FC - 3FS'!AP161 -> -12815 | V55: =+'FC - 3FS'!AB161 -> 3193 | W55: =+'FC - 3FS'!AC161 -> -7205 | X55: =+'FC - 3FS'!AD161 -> -4238 | Y55: =+'FC - 3FS'!AE161 -> -3845.032 | Z55: =+'FC - 3FS'!AQ161 -> -12095.032 | AA55: =+'FC - 3FS'!AF161 -> -2286.0719 | AB55: =+'FC - 3FS'!AG161 -> -2241.7237 | AC55: =+'FC - 3FS'!AH161 -> -2197.2618 | AD55: =+'FC - 3FS'!AI161 -> -2301.3185 | AE55: =+'FC - 3FS'!AR161 -> -9026.3758 | AH55: =+SUM(B55:E55)=F55 -> TRUE | AI55: =+SUM(G55:J55)=K55 -> TRUE | AJ55: =+SUM(L55:O55)=P55 -> TRUE | AK55: =ROUND(SUM(Q55:T55),1)=ROUND(U55,1) -> TRUE | AL55: =ROUND(SUM(V55:Y55),0)=ROUND(Z55,0) -> TRUE | AM55: =+ROUND(SUM(AA55:AD55),0)=ROUND(AE55,0) -> TRUE
A56: Change in cash and cash equivalents | B56: =+SUM(B53:B55) -> -3704 | C56: =+SUM(C53:C55) -> 1119 | D56: =+SUM(D53:D55) -> -3735 | E56: =+SUM(E53:E55) -> 2560 | F56: =+SUM(F53:F55) -> -3760 | G56: =+SUM(G53:G55) -> -3383 | H56: =+SUM(H53:H55) -> -94 | I56: =+SUM(I53:I55) -> 3763 | ... AE56: =+SUM(AE53:AE55) -> 5182.0196 | AH56: =+SUM(B56:E56)=F56 -> TRUE | AI56: =+SUM(G56:J56)=K56 -> TRUE | AJ56: =+SUM(L56:O56)=P56 -> TRUE | AK56: =+ROUND(SUM(Q56:T56),0)=ROUND(U56,0) -> TRUE | AL56: =ROUND(SUM(V56:Y56),0)=ROUND(Z56,0) -> TRUE | AM56: =ROUND(SUM(AA56:AD56),0)=ROUND(AE56,0) -> TRUE
A57: Beginning of period cash | B57: =+'FC - 3FS'!L164 -> 10463 | C57: =+'FC - 3FS'!M164 -> 6759 | D57: =+'FC - 3FS'!N164 -> 7878 | E57: =+'FC - 3FS'!O164 -> 4143 | F57: =+'FC - 3FS'!AM164 -> 10463 | G57: =+'FC - 3FS'!P164 -> 6703 | H57: =+'FC - 3FS'!Q164 -> 3320 | I57: =+'FC - 3FS'!R164 -> 3226 | J57: =+'FC - 3FS'!S164 -> 6989 | K57: =+'FC - 3FS'!AN164 -> 6703 | L57: =+'FC - 3FS'!T164 -> 4674 | M57: =+'FC - 3FS'!U164 -> 4724 | N57: =+'FC - 3FS'!V164 -> 6808 | O57: =+'FC - 3FS'!W164 -> 5199 | P57: =+'FC - 3FS'!AO164 -> 4674 | Q57: =+'FC - 3FS'!X164 -> 5307 | R57: =+'FC - 3FS'!Y164 -> 6938 | S57: =+'FC - 3FS'!Z164 -> 6647 | T57: =+'FC - 3FS'!AA164 -> 9986 | U57: =+'FC - 3FS'!AP164 -> 5307 | V57: =+'FC - 3FS'!AB164 -> 5713 | W57: =+'FC - 3FS'!AC164 -> 12344 | X57: =+'FC - 3FS'!AD164 -> 10572 | Y57: =+'FC - 3FS'!AE164 -> 3652 | Z57: =+'FC - 3FS'!AQ164 -> 5713 | AA57: =+'FC - 3FS'!AF164 -> 2200.3843 | AB57: =+'FC - 3FS'!AG164 -> 2517.0272 | AC57: =+'FC - 3FS'!AH164 -> 3944.8934 | AD57: =+'FC - 3FS'!AI164 -> 6225.6863 | AE57: =+'FC - 3FS'!AR164 -> 2200.3843 | AH57: =B57=F57 -> TRUE | AI57: =G57=K57 -> TRUE | AJ57: =L57=P57 -> TRUE | AK57: =Q57=U57 -> TRUE | AL57: =V57=Z57 -> TRUE | AM57: =ROUND(AA57,1)=ROUND(AE57,1) -> TRUE
A58: End of period cash | B58: =+B57+B56 -> 6759 | C58: =+C57+C56 -> 7878 | D58: =+D57+D56 -> 4143 | E58: =+E57+E56 -> 6703 | F58: =+F57+F56 -> 6703 | G58: =+G57+G56 -> 3320 | H58: =+H57+H56 -> 3226 | I58: =+I57+I56 -> 6989 | ... AE58: =+AE57+AE56 -> 7382.4039 | AH58: =E58=F58 -> TRUE | AI58: =J58=K58 -> TRUE | AJ58: =O58=P58 -> TRUE | AK58: =T58=U58 -> TRUE | AL58: =ROUND(Y58,0)=ROUND(Z58,0) -> TRUE | AM58: =ROUND(AD58,0)=ROUND(AE58,0) -> TRUE
A59: Adj. Free Cash Flow | B59: ='FC - 3FS'!L173 -> 1369 | C59: ='FC - 3FS'!M173 -> 1677 | D59: ='FC - 3FS'!N173 -> 1604 | E59: ='FC - 3FS'!O173 -> 1112 | F59: ='FC - 3FS'!AM173 -> 5762 | G59: ='FC - 3FS'!P173 -> 1649 | H59: ='FC - 3FS'!Q173 -> 1758 | I59: ='FC - 3FS'!R173 -> 2065 | J59: ='FC - 3FS'!S173 -> 2184 | K59: ='FC - 3FS'!AN173 -> 7656 | L59: ='FC - 3FS'!T173 -> 2401 | M59: ='FC - 3FS'!U173 -> 2877 | N59: ='FC - 3FS'!V173 -> 4003 | O59: ='FC - 3FS'!W173 -> 4305 | P59: ='FC - 3FS'!AO173 -> 13586 | Q59: ='FC - 3FS'!X173 -> 3347 | R59: ='FC - 3FS'!Y173 -> 4439 | S59: ='FC - 3FS'!Z173 -> 5162 | T59: ='FC - 3FS'!AA173 -> 4084 | U59: ='FC - 3FS'!AP173 -> 17032 | V59: ='FC - 3FS'!AB173 -> 4396 | W59: ='FC - 3FS'!AC173 -> 4596 | X59: ='FC - 3FS'!AD173 -> 4818 | Y59: ='FC - 3FS'!AE173 -> 4013.5992 | Z59: ='FC - 3FS'!AQ173 -> 17823.599 | AA59: ='FC - 3FS'!AF173 -> 4248.6668 | AB59: ='FC - 3FS'!AG173 -> 5341.7208 | AC59: ='FC - 3FS'!AH173 -> 6176.7809 | AD59: ='FC - 3FS'!AI173 -> 5183.7807 | AE59: ='FC - 3FS'!AR173 -> 20950.949 | AH59: =+SUM(B59:E59)=F59 -> TRUE | AI59: =+SUM(G59:J59)=K59 -> TRUE | AJ59: =+SUM(L59:O59)=P59 -> TRUE | AK59: =ROUND(SUM(Q59:T59),0)=ROUND(U59,0) -> TRUE | AL59: =ROUND(SUM(V59:Y59),0)=ROUND(Z59,0) -> TRUE | AM59: =+SUM(AA59:AD59)=AE59 -> TRUE

Sheet Valuation
A1: hide
B2: VALUATION METHOD 1: DCF | T2: Start Date | U2: =TODAY()-365*10 -> 42576
T3: Field | U3: BEST_CUR_EV_TO_EBITDA | V3: EV/EBITDA | W3: 10-year average
B4: Current Quarter | C4: =N6&"Q"&RIGHT(O6,2) -> 1Q25 | H4: Assumptions | N4: Last Reported Fiscal | T4: TMUS | U4: 42380 | W4: =AVERAGE($V$4:$V$2517) -> #DIV/0!
B5: +1 Year Quarter | C5: =N8&"Q"&RIGHT(O8,2) -> 1Q26 | H5: WACC | I5: 0.08 | K5: b | L5: 0.8 | N5: Quarter | O5: Year | W5: =AVERAGE($V$4:$V$2517) -> #DIV/0!
B6: Current Share Price | C6: =L10 -> 259.64 | H6: D | I6: =INDEX('BS Drivers'!97:97,MATCH(Valuation!C4,'BS Drivers'!4:4,0)) -> 87997 | K6: Rf | L6: 0.03 | N6: 1 | O6: 2025 | W6: =AVERAGE($V$4:$V$2517) -> #DIV/0!
B7: Target Price | C7: =C48 -> -28 | H7: E | I7: =L9*L10 -> 297198.3 | K7: Risk Prem. | L7: 0.08 | N7: +1 Year | W7: =AVERAGE($V$4:$V$2517) -> #DIV/0!
B8: Upside (Downside) from Current Price | C8: =C7/C6-1 -> -1.1078416 | H8: D/(D+E) | I8: =I6/(I6+I7) -> 0.22844775 | K8: Tax Rate | L8: 0.23 | N8: =N6 -> 1 | O8: =O6+1 -> 2026 | W8: =AVERAGE($V$4:$V$2517) -> #DIV/0!
H9: Kd | I9: 0.04 | K9: Shares | L9: =INDEX('FC - 3FS'!39:39, MATCH(Valuation!C4,'FC - 3FS'!4:4, 0)) -> 1144.6553 | N9: Bloomberg price | W9: =AVERAGE($V$4:$V$2517) -> #DIV/0!
B10: Median Cons. TP | C10: 270 | H10: Ke | I10: =L6+L5*L7 -> 0.094 | K10: Stock Price | L10: 259.64 | N10: 198.6 | W10: =AVERAGE($V$4:$V$2517) -> #DIV/0!
H11: WACC (Calculated) | I11: =I9*(1-L8)*I8+I10*(1-I8) -> 0.079562102 | K11: Terminal Growth | L11: 0.02 | W11: =AVERAGE($V$4:$V$2517) -> #DIV/0!
W12: =AVERAGE($V$4:$V$2517) -> #DIV/0!
B13: ($ MM) | C13: 2020 | D13: 2021 | E13: 2022 | F13: =E13+1 -> 2023 | G13: =F13+1 -> 2024 | H13: =G13+1 -> 2025 | I13: =H13+1 -> 2026 | J13: =I13+1 -> 2027 | K13: =J13+1 -> 2028 | L13: =K13+1 -> 2029 | M13: =L13+1 -> 2030 | W13: =AVERAGE($V$4:$V$2517) -> #DIV/0!
W14: =AVERAGE($V$4:$V$2517) -> #DIV/0!
B15: Revenue | C15: ='FC - 3FS'!AL14 -> 68397 | D15: ='FC - 3FS'!AM14 -> 80118 | E15: ='FC - 3FS'!AN14 -> 79571 | F15: ='FC - 3FS'!AO14 -> 78558 | G15: ='FC - 3FS'!AP14 -> 81400 | H15: ='FC - 3FS'!AQ14 -> 87847.495 | I15: ='FC - 3FS'!AR14 -> 94417.322 | J15: ='FC - 3FS'!AS14 -> 99251.787 | ... M15: ='FC - 3FS'!AV14 -> 0 | W15: =AVERAGE($V$4:$V$2517) -> #DIV/0!
B16: yoy growth | D16: =D15/C15-1 -> 0.17136717 | E16: =E15/D15-1 -> -0.0068274295 | F16: =F15/E15-1 -> -0.012730769 | G16: =G15/F15-1 -> 0.036177092 | H16: =H15/G15-1 -> 0.079207559 | I16: =I15/H15-1 -> 0.074786732 | J16: =J15/I15-1 -> 0.051203153 | K16: =K15/J15-1 -> -1 | ... M16: =M15/L15-1 -> #DIV/0! | W16: =AVERAGE($V$4:$V$2517) -> #DIV/0!
W17: =AVERAGE($V$4:$V$2517) -> #DIV/0!
B18: EBIT | C18: =+'FC - 3FS'!AL23 -> 6636 | D18: =+'FC - 3FS'!AM23 -> 6892 | E18: =+'FC - 3FS'!AN23 -> 6543 | F18: =+'FC - 3FS'!AO23 -> 14266 | G18: =+'FC - 3FS'!AP23 -> 18010 | H18: =+'FC - 3FS'!AQ23 -> 18579.344 | I18: =+'FC - 3FS'!AR23 -> 20628.685 | J18: =+'FC - 3FS'!AS23 -> 23736.335 | ... M18: =+'FC - 3FS'!AV23 -> 0 | W18: =AVERAGE($V$4:$V$2517) -> #DIV/0!
B19: Cost to Achieve | H19: ='IS Drivers'!AQ218 -> 460 | I19: ='IS Drivers'!AR218 -> 1540 | J19: ='IS Drivers'!AS218 -> 660 | K19: ='IS Drivers'!AT218 -> 0 | L19: ='IS Drivers'!AU218 -> 0 | M19: ='IS Drivers'!AV218 -> 0 | W19: =AVERAGE($V$4:$V$2517) -> #DIV/0!
B20: Adj. EBIT | H20: =SUM(H18:H19) -> 19039.344 | I20: =SUM(I18:I19) -> 22168.685 | J20: =SUM(J18:J19) -> 24396.335 | K20: =SUM(K18:K19) -> 0 | L20: =SUM(L18:L19) -> 0 | M20: =SUM(M18:M19) -> 0 | W20: =AVERAGE($V$4:$V$2517) -> #DIV/0!
B21: Operating Margin % | C21: =C18/C15 -> 0.097021799 | D21: =D18/D15 -> 0.086023116 | E21: =E18/E15 -> 0.08222845 | F21: =F18/F15 -> 0.18159831 | G21: =G18/G15 -> 0.22125307 | H21: =H20/H15 -> 0.21673178 | I21: =I20/I15 -> 0.23479468 | J21: =J20/J15 -> 0.24580248 | K21: =K20/K15 -> #DIV/0! | L21: =L20/L15 -> #DIV/0! | M21: =M20/M15 -> #DIV/0! | W21: =AVERAGE($V$4:$V$2517) -> #DIV/0!
W22: =AVERAGE($V$4:$V$2517) -> #DIV/0!
B23: Tax Rate % | C23: =-'BS Drivers'!AL124 -> 0.22266289 | D23: =-'BS Drivers'!AM124 -> 0.097582811 | E23: =-'BS Drivers'!AN124 -> 0.17673236 | F23: =-'BS Drivers'!AO124 -> 0.24384035 | G23: =-'BS Drivers'!AP124 -> 0.22926862 | H23: =-'BS Drivers'!AQ124 -> 0.23552142 | I23: =-'BS Drivers'!AR124 -> 0.23072562 | J23: =-'BS Drivers'!AS124 -> 0.23072562 | ... M23: =-'BS Drivers'!AV124 -> 0 | W23: =AVERAGE($V$4:$V$2517) -> #DIV/0!
B24: NOPAT | C24: =+(1-C23)*C18 -> 5158.4091 | D24: =+(1-D23)*D18 -> 6219.4593 | E24: =+(1-E23)*E18 -> 5386.6402 | F24: =+(1-F23)*F18 -> 10787.374 | G24: =+(1-G23)*G18 -> 13880.872 | H24: =+(1-H23)*H20 -> 14555.171 | I24: =+(1-I23)*I20 -> 17053.801 | J24: =+(1-J23)*J20 -> 18767.475 | K24: =+(1-K23)*K20 -> 0 | L24: =+(1-L23)*L20 -> 0 | M24: =+(1-M23)*M20 -> 0 | W24: =AVERAGE($V$4:$V$2517) -> #DIV/0!
B25: change in working capital | C25: =SUM('FC - 3FS'!AL131:AL138)+'FC - 3FS'!AL145 -> -8751 | D25: =SUM('FC - 3FS'!AM131:AM138)+'FC - 3FS'!AM145 -> -2983 | E25: =SUM('FC - 3FS'!AN131:AN138)+'FC - 3FS'!AN145 -> 1781 | F25: =SUM('FC - 3FS'!AO131:AO138)+'FC - 3FS'!AO145 -> -2242 | G25: =SUM('FC - 3FS'!AP131:AP138)+'FC - 3FS'!AP145 -> -3430 | H25: =SUM('FC - 3FS'!AQ131:AQ138) -> -2766.9768 | I25: =SUM('FC - 3FS'!AR131:AR138) -> -2340.0684 | J25: =SUM('FC - 3FS'!AS131:AS138) -> -1865.3836 | K25: =SUM('FC - 3FS'!AT131:AT138) -> 0 | L25: =SUM('FC - 3FS'!AU131:AU138) -> 0 | M25: =SUM('FC - 3FS'!AV131:AV138) -> 0 | W25: =AVERAGE($V$4:$V$2517) -> #DIV/0!
B26: D&A | C26: ='FC - 3FS'!AL122 -> 14151 | D26: ='FC - 3FS'!AM122 -> 16383 | E26: ='FC - 3FS'!AN122 -> 13651 | F26: ='FC - 3FS'!AO122 -> 12818 | G26: ='FC - 3FS'!AP122 -> 12919 | H26: ='FC - 3FS'!AQ122 -> 13422.032 | I26: ='FC - 3FS'!AR122 -> 14308.594 | J26: ='FC - 3FS'!AS122 -> 14771.983 | ... M26: ='FC - 3FS'!AV122 -> 0 | W26: =AVERAGE($V$4:$V$2517) -> #DIV/0!
B27: CapEx | C27: =+'FC - 3FS'!AL142 -> -11034 | D27: =+'FC - 3FS'!AM142 -> -12326 | E27: =+'FC - 3FS'!AN142 -> -13970 | F27: =+'FC - 3FS'!AO142 -> -9801 | G27: =+'FC - 3FS'!AP142 -> -8840 | H27: =+'FC - 3FS'!AQ142 -> -10023.267 | I27: =+'FC - 3FS'!AR142 -> -10562.247 | J27: =+'FC - 3FS'!AS142 -> -10941.004 | ... M27: =+'FC - 3FS'!AV142 -> 0
B28: as % of revenue | C28: =C27/C15 -> -0.16132287 | D28: =D27/D15 -> -0.15384807 | E28: =E27/E15 -> -0.17556648 | F28: =F27/F15 -> -0.12476132 | G28: =G27/G15 -> -0.10859951 | H28: =H27/H15 -> -0.1140985 | I28: =I27/I15 -> -0.11186768 | J28: =J27/J15 -> -0.11023483 | ... M28: =M27/M15 -> #DIV/0! | W28: =AVERAGE($V$4:$V$2517) -> #DIV/0!
B29: yoy growth | D29: =D27/C27-1 -> 0.11709262 | E29: =E27/D27-1 -> 0.1333766 | F29: =F27/E27-1 -> -0.2984252 | G29: =G27/F27-1 -> -0.098051219 | H29: =H27/G27-1 -> 0.13385374 | I29: =I27/H27-1 -> 0.053772849 | J29: =J27/I27-1 -> 0.035859496 | K29: =K27/J27-1 -> -1 | ... M29: =M27/L27-1 -> #DIV/0! | W29: =AVERAGE($V$4:$V$2517) -> #DIV/0!
W30: =AVERAGE($V$4:$V$2517) -> #DIV/0!
B31: Unlevered FCF | C31: =SUM(C24:C27) -> -475.59093 | D31: =SUM(D24:D27) -> 7293.4593 | E31: =SUM(E24:E27) -> 6848.6402 | F31: =SUM(F24:F27) -> 11562.374 | G31: =SUM(G24:G27) -> 14529.872 | H31: =SUM(H24:H27) -> 15186.959 | I31: =SUM(I24:I27) -> 18460.08 | J31: =SUM(J24:J27) -> 20733.071 | ... M31: =SUM(M24:M27) -> 0 | W31: =AVERAGE($V$4:$V$2517) -> #DIV/0!
B32: yoy growth | E32: =E31/D31-1 -> -0.060988767 | F32: =F31/E31-1 -> 0.68827289 | G32: =G31/F31-1 -> 0.25665132 | H32: =H31/G31-1 -> 0.045223177 | I32: =I31/H31-1 -> 0.21552184 | J32: =J31/I31-1 -> 0.12313006 | K32: =K31/J31-1 -> -1 | L32: =L31/K31-1 -> #DIV/0! | M32: =M31/L31-1 -> #DIV/0! | W32: =AVERAGE($V$4:$V$2517) -> #DIV/0!
B33: FCF Margin | C33: =C31/C15 -> -0.0069533888 | D33: =D31/D15 -> 0.091033966 | E33: =E31/E15 -> 0.08606955 | F33: =F31/F15 -> 0.14718264 | G33: =G31/G15 -> 0.17849966 | H33: =H31/H15 -> 0.17287868 | I33: =I31/I15 -> 0.19551582 | J33: =J31/J15 -> 0.20889368 | ... M33: =M31/M15 -> #DIV/0! | W33: =AVERAGE($V$4:$V$2517) -> #DIV/0!
W34: =AVERAGE($V$4:$V$2517) -> #DIV/0!
B35: Years to Discount | G35: =((G13-$O$6)+(4-$N$6)/4) -> -0.25 | H35: =((H13-$O$6)+(4-$N$6)/4) -> 0.75 | I35: =((I13-$O$6)+(4-$N$6)/4) -> 1.75 | J35: =((J13-$O$6)+(4-$N$6)/4) -> 2.75 | K35: =((K13-$O$6)+(4-$N$6)/4) -> 3.75 | L35: =((L13-$O$6)+(4-$N$6)/4) -> 4.75 | M35: =((M13-$O$6)+(4-$N$6)/4) -> 5.75 | W35: =AVERAGE($V$4:$V$2517) -> #DIV/0!
B36: Discount Factor | G36: =IF(G35>0,1/(1+$I$5)^G35,0) -> 0 | H36: =IF(H35>0,1/(1+$I$5)^H35,0) -> 0.94391347 | I36: =IF(I35>0,1/(1+$I$5)^I35,0) -> 0.87399395 | J36: =IF(J35>0,1/(1+$I$5)^J35,0) -> 0.80925366 | K36: =IF(K35>0,1/(1+$I$5)^K35,0) -> 0.74930894 | L36: =IF(L35>0,1/(1+$I$5)^L35,0) -> 0.69380458 | M36: =IF(M35>0,1/(1+$I$5)^M35,0) -> 0.64241165 | W36: =AVERAGE($V$4:$V$2517) -> #DIV/0!
B37: FCFF Present Value | G37: =G31*G36 -> 0 | H37: =H31*H36 -> 14335.175 | I37: =I31*I36 -> 16133.999 | J37: =J31*J36 -> 16778.314 | K37: =K31*K36 -> 0 | L37: =L31*L36 -> 0 | M37: =M31*M36 -> 0 | W37: =AVERAGE($V$4:$V$2517) -> #DIV/0!
W38: =AVERAGE($V$4:$V$2517) -> #DIV/0!
B39: Terminal Value | C39: =M31*(1+L11)/(I5-L11) -> 0 | D39: Terminal as % of total | W39: =AVERAGE($V$4:$V$2517) -> #DIV/0!
B40: PV of Terminal Value | C40: =C39*M36 -> 0 | D40: =+C40/C41 -> 0 | W40: =AVERAGE($V$4:$V$2517) -> #DIV/0!
B41: Enterprise Value | C41: =SUM(G37:M37,C40) -> 47247.488 | W41: =AVERAGE($V$4:$V$2517) -> #DIV/0!
B42: (-) Debt | C42: =I6 -> 87997 | W42: =AVERAGE($V$4:$V$2517) -> #DIV/0!
B43: (+) Cash & Cash Equivalents | C43: =+INDEX('FC - 3FS'!69:69, MATCH(Valuation!C4,'FC - 3FS'!4:4, 0)) -> 12003 | W43: =AVERAGE($V$4:$V$2517) -> #DIV/0!
B44: Equity | C44: =+C41-C42+C43 -> -28746.512 | W44: =AVERAGE($V$4:$V$2517) -> #DIV/0!
B45: Equity Value +1 Year | C45: =C44*(1+I10) -> -31448.685 | W45: =AVERAGE($V$4:$V$2517) -> #DIV/0!
B46: Shares Outstanding +1 Year | C46: =INDEX('FC - 3FS'!39:39, MATCH(Valuation!C5,'FC - 3FS'!4:4, 0)) -> 1120.5854 | W46: =AVERAGE($V$4:$V$2517) -> #DIV/0!
W47: =AVERAGE($V$4:$V$2517) -> #DIV/0!
B48: Implied Share Price, +1 Year | C48: =ROUND(C45/C46,0) -> -28 | W48: =AVERAGE($V$4:$V$2517) -> #DIV/0!
B49: Upside (Downside) from Current Price | C49: =C48/C6-1 -> -1.1078416 | W49: =AVERAGE($V$4:$V$2517) -> #DIV/0!
W50: =AVERAGE($V$4:$V$2517) -> #DIV/0!
W51: =AVERAGE($V$4:$V$2517) -> #DIV/0!
B52: VALUATION METHOD 2: Multiples | W52: =AVERAGE($V$4:$V$2517) -> #DIV/0!
W53: =AVERAGE($V$4:$V$2517) -> #DIV/0!
B54: NTM | C54: =IF($N$6=4,"1Q"&RIGHT($O$6,2)+1,$N$6+1&"Q"&RIGHT($O$6,2)) -> 2Q25 | D54: =IF(LEFT(C54,1)="4","1Q"&RIGHT(C54,2)+1,LEFT(C54,1)+1&"Q"&RIGHT(C54,2)) -> 3Q25 | E54: =IF(LEFT(D54,1)="4","1Q"&RIGHT(D54,2)+1,LEFT(D54,1)+1&"Q"&RIGHT(D54,2)) -> 4Q25 | F54: =IF(LEFT(E54,1)="4","1Q"&RIGHT(E54,2)+1,LEFT(E54,1)+1&"Q"&RIGHT(E54,2)) -> 1Q26 | G54: NTM Sum | H54: BERN 2025 | I54: CON 2025 | W54: =AVERAGE($V$4:$V$2517) -> #DIV/0!
B55: Revenue | C55: =INDEX('FC - 3FS'!14:14, MATCH(Valuation!C54, 'FC - 3FS'!4:4,0)) -> 21132 | D55: =INDEX('FC - 3FS'!14:14, MATCH(Valuation!D54, 'FC - 3FS'!4:4,0)) -> 21957 | E55: =INDEX('FC - 3FS'!14:14, MATCH(Valuation!E54, 'FC - 3FS'!4:4,0)) -> 23872.495 | F55: =INDEX('FC - 3FS'!14:14, MATCH(Valuation!F54, 'FC - 3FS'!4:4,0)) -> 22550.285 | G55: =+SUM(C55:F55) -> 89511.78 | H55: ='FC - 3FS'!AQ14 -> 87847.495 | I55: =Consensus!AA6 -> 86037.607 | W55: =AVERAGE($V$4:$V$2517) -> #DIV/0!
B56: EBITDA | C56: =INDEX('FC - 3FS'!56:56, MATCH(Valuation!C$54, 'FC - 3FS'!$4:$4,0)) -> 8547 | D56: =INDEX('FC - 3FS'!56:56, MATCH(Valuation!D$54, 'FC - 3FS'!$4:$4,0)) -> 8684 | E56: =INDEX('FC - 3FS'!56:56, MATCH(Valuation!E$54, 'FC - 3FS'!$4:$4,0)) -> 8394.3925 | F56: =INDEX('FC - 3FS'!56:56, MATCH(Valuation!F$54, 'FC - 3FS'!$4:$4,0)) -> 9279.3016 | G56: =+SUM(C56:F56) -> 34904.694 | H56: ='FC - 3FS'!AQ56 -> 33884.392 | I56: =Consensus!AA22 -> 33463.739 | W56: =AVERAGE($V$4:$V$2517) -> #DIV/0!
B57: EBIT | C57: =INDEX('FC - 3FS'!23:23, MATCH(Valuation!C$54, 'FC - 3FS'!$4:$4,0)) -> 5213 | D57: =INDEX('FC - 3FS'!23:23, MATCH(Valuation!D$54, 'FC - 3FS'!$4:$4,0)) -> 4530 | E57: =INDEX('FC - 3FS'!23:23, MATCH(Valuation!E$54, 'FC - 3FS'!$4:$4,0)) -> 4036.3443 | F57: =INDEX('FC - 3FS'!23:23, MATCH(Valuation!F$54, 'FC - 3FS'!$4:$4,0)) -> 4950.2704 | G57: =+SUM(C57:F57) -> 18729.615 | H57: ='FC - 3FS'!AQ23 -> 18579.344 | I57: =Consensus!AA14 -> 19729.905 | W57: =AVERAGE($V$4:$V$2517) -> #DIV/0!
B58: Diluted EPS | C58: =INDEX('FC - 3FS'!36:36, MATCH(Valuation!C$54, 'FC - 3FS'!$4:$4,0)) -> 2.8391493 | D58: =INDEX('FC - 3FS'!36:36, MATCH(Valuation!D$54, 'FC - 3FS'!$4:$4,0)) -> 2.408959 | E58: =INDEX('FC - 3FS'!36:36, MATCH(Valuation!E$54, 'FC - 3FS'!$4:$4,0)) -> 1.9960941 | F58: =INDEX('FC - 3FS'!36:36, MATCH(Valuation!F$54, 'FC - 3FS'!$4:$4,0)) -> 2.7042674 | G58: =+SUM(C58:F58) -> 9.9484699 | H58: ='FC - 3FS'!AQ36 -> 9.8240185 | I58: =Consensus!AA46 -> 10.732 | W58: =AVERAGE($V$4:$V$2517) -> #DIV/0!
W59: =AVERAGE($V$4:$V$2517) -> #DIV/0!
C60: Bernstein +1 year | E60: CON PT | G60: using current price | W60: =AVERAGE($V$4:$V$2517) -> #DIV/0!
B61: Market Cap | C61: =C45 -> -31448.685 | E61: =C10*L9 -> 309056.93 | G61: =C6*L9 -> 297198.3 | W61: =AVERAGE($V$4:$V$2517) -> #DIV/0!
B62: EV | C62: =C41*(1+I5) -> 51027.287 | E62: =E61+C42-C43 -> 385050.93 | G62: =G61+C42-C43 -> 373192.3 | W62: =AVERAGE($V$4:$V$2517) -> #DIV/0!
C63: NTM | D63: 2025 | E63: CON 2025 | G63: 2025 | H63: NTM | W63: =AVERAGE($V$4:$V$2517) -> #DIV/0!
B64: Implied EV/EBITDA | C64: =$C$62/$G56 -> 1.4619033 | D64: =$C$62/$H56 -> 1.505923 | E64: =$E$62/I56 -> 11.506512 | G64: =G62/I56 -> 11.15214 | H64: 8.2818275 | W64: =AVERAGE($V$4:$V$2517) -> #DIV/0!
B65: Implied EV/EBIT | C65: =$C$62/$G57 -> 2.7244173 | D65: =$C$62/$H57 -> 2.7464525 | E65: =$E$62/I57 -> 19.516106 | G65: =G62/I57 -> 18.915058 | H65: 15.056695 | W65: =AVERAGE($V$4:$V$2517) -> #DIV/0!
B66: Implied P/E | C66: =$C$48/$G58 -> -2.8145032 | D66: =$C$48/$H58 -> -2.8501575 | E66: =C10/I58 -> 25.158405 | G66: =L10/I58 -> 24.193067 | H66: 18.739496 | W66: =AVERAGE($V$4:$V$2517) -> #DIV/0!
B67: Implied EV/Sales | C67: =$C$62/$G55 -> 0.57006225 | D67: =$C$62/$H55 -> 0.58086217 | H67: 3.6183573 | W67: =AVERAGE($V$4:$V$2517) -> #DIV/0!
W68: =AVERAGE($V$4:$V$2517) -> #DIV/0!
W69: =AVERAGE($V$4:$V$2517) -> #DIV/0!
W70: =AVERAGE($V$4:$V$2517) -> #DIV/0!
W71: =AVERAGE($V$4:$V$2517) -> #DIV/0!
W72: =AVERAGE($V$4:$V$2517) -> #DIV/0!
W73: =AVERAGE($V$4:$V$2517) -> #DIV/0!
W74: =AVERAGE($V$4:$V$2517) -> #DIV/0!
W75: =AVERAGE($V$4:$V$2517) -> #DIV/0!
W76: =AVERAGE($V$4:$V$2517) -> #DIV/0!
W77: =AVERAGE($V$4:$V$2517) -> #DIV/0!
W78: =AVERAGE($V$4:$V$2517) -> #DIV/0!
W79: =AVERAGE($V$4:$V$2517) -> #DIV/0!
... W2518: =AVERAGE($V$4:$V$2517) -> #DIV/0!

Sheet Valuation (Don't Use)
A1: hide
B2: VALUATION METHOD 1: DCF | T2: Start Date | U2: =TODAY()-365*10 -> 42576
T3: Field | U3: BEST_CUR_EV_TO_EBITDA | V3: EV/EBITDA | W3: 10-year average
B4: Current Quarter | C4: =N6&"Q"&RIGHT(O6,2) -> 3Q24 | H4: Assumptions | N4: Last Reported Fiscal | T4: TMUS | U4: 42380 | W4: =AVERAGE($V$4:$V$2517) -> #DIV/0!
B5: +1 Year Quarter | C5: =N8&"Q"&RIGHT(O8,2) -> 3Q25 | H5: WACC | I5: =I9*(1-L8)*I8+I10*(1-I8) -> 0.076299929 | K5: b | L5: 0.8 | N5: Quarter | O5: Year | W5: =AVERAGE($V$4:$V$2517) -> #DIV/0!
B6: Current Share Price | C6: =L10 -> 246.94 | H6: D | I6: =INDEX('BS Drivers'!97:97,MATCH('Valuation (Don''t Use)'!C4,'BS Drivers'!4:4,0))+INDEX('BS Drivers'!112:112,MATCH('Valuation (Don''t Use)'!C4,'BS Drivers'!4:4,0)) -> 112456 | K6: Rf | L6: 0.03 | N6: 3 | O6: 2024 | W6: =AVERAGE($V$4:$V$2517) -> #DIV/0!
B7: Target Price | C7: =C46 -> -27 | H7: E | I7: =L9*L10 -> 289080.2 | K7: Risk Prem. | L7: 0.08 | N7: +1 Year | W7: =AVERAGE($V$4:$V$2517) -> #DIV/0!
B8: Upside (Downside) from Current Price | C8: =C7/C6-1 -> -1.1093383 | H8: D/(D+E) | I8: =I6/(I6+I7) -> 0.28006441 | K8: Tax Rate | L8: 0.23 | N8: =N6 -> 3 | O8: =O6+1 -> 2025 | W8: =AVERAGE($V$4:$V$2517) -> #DIV/0!
H9: Kd | I9: 0.04 | K9: Shares | L9: =INDEX('FC - 3FS'!39:39, MATCH('Valuation (Don''t Use)'!C4,'FC - 3FS'!4:4, 0)) -> 1170.6496 | N9: Bloomberg price | W9: =AVERAGE($V$4:$V$2517) -> #DIV/0!
B10: Median Cons. TP | C10: 270 | H10: Ke | I10: =L6+L5*L7 -> 0.094 | K10: Stock Price | L10: 246.94 | N10: 198.6 | W10: =AVERAGE($V$4:$V$2517) -> #DIV/0!
K11: Terminal Growth | L11: 0.02 | W11: =AVERAGE($V$4:$V$2517) -> #DIV/0!
W12: =AVERAGE($V$4:$V$2517) -> #DIV/0!
B13: ($ MM) | C13: 2020 | D13: 2021 | E13: 2022 | F13: =E13+1 -> 2023 | G13: =F13+1 -> 2024 | H13: =G13+1 -> 2025 | I13: =H13+1 -> 2026 | J13: =I13+1 -> 2027 | K13: =J13+1 -> 2028 | L13: =K13+1 -> 2029 | M13: =L13+1 -> 2030 | W13: =AVERAGE($V$4:$V$2517) -> #DIV/0!
W14: =AVERAGE($V$4:$V$2517) -> #DIV/0!
B15: Revenue | C15: ='FC - 3FS'!AL14 -> 68397 | D15: ='FC - 3FS'!AM14 -> 80118 | E15: ='FC - 3FS'!AN14 -> 79571 | F15: ='FC - 3FS'!AO14 -> 78558 | G15: ='FC - 3FS'!AP14 -> 81400 | H15: ='FC - 3FS'!AQ14 -> 87847.495 | I15: ='FC - 3FS'!AR14 -> 94417.322 | J15: ='FC - 3FS'!AS14 -> 99251.787 | ... M15: ='FC - 3FS'!AV14 -> 0 | W15: =AVERAGE($V$4:$V$2517) -> #DIV/0!
B16: yoy growth | D16: =D15/C15-1 -> 0.17136717 | E16: =E15/D15-1 -> -0.0068274295 | F16: =F15/E15-1 -> -0.012730769 | G16: =G15/F15-1 -> 0.036177092 | H16: =H15/G15-1 -> 0.079207559 | I16: =I15/H15-1 -> 0.074786732 | J16: =J15/I15-1 -> 0.051203153 | K16: =K15/J15-1 -> -1 | ... M16: =M15/L15-1 -> #DIV/0! | W16: =AVERAGE($V$4:$V$2517) -> #DIV/0!
W17: =AVERAGE($V$4:$V$2517) -> #DIV/0!
B18: EBIT | C18: =+'FC - 3FS'!AL23 -> 6636 | D18: =+'FC - 3FS'!AM23 -> 6892 | E18: =+'FC - 3FS'!AN23 -> 6543 | F18: =+'FC - 3FS'!AO23 -> 14266 | G18: =+'FC - 3FS'!AP23 -> 18010 | H18: =+'FC - 3FS'!AQ23 -> 18579.344 | I18: =+'FC - 3FS'!AR23 -> 20628.685 | J18: =+'FC - 3FS'!AS23 -> 23736.335 | ... M18: =+'FC - 3FS'!AV23 -> 0 | W18: =AVERAGE($V$4:$V$2517) -> #DIV/0!
B19: Operating Margin % | C19: =C18/C15 -> 0.097021799 | D19: =D18/D15 -> 0.086023116 | E19: =E18/E15 -> 0.08222845 | F19: =F18/F15 -> 0.18159831 | G19: =G18/G15 -> 0.22125307 | H19: =H18/H15 -> 0.21149544 | I19: =I18/I15 -> 0.21848411 | J19: =J18/J15 -> 0.23915272 | ... M19: =M18/M15 -> #DIV/0! | W19: =AVERAGE($V$4:$V$2517) -> #DIV/0!
W20: =AVERAGE($V$4:$V$2517) -> #DIV/0!
B21: Tax Rate % | C21: =-'BS Drivers'!AL124 -> 0.22266289 | D21: =-'BS Drivers'!AM124 -> 0.097582811 | E21: =-'BS Drivers'!AN124 -> 0.17673236 | F21: =-'BS Drivers'!AO124 -> 0.24384035 | G21: =-'BS Drivers'!AP124 -> 0.22926862 | H21: =-'BS Drivers'!AQ124 -> 0.23552142 | I21: =-'BS Drivers'!AR124 -> 0.23072562 | J21: =-'BS Drivers'!AS124 -> 0.23072562 | ... M21: =-'BS Drivers'!AV124 -> 0 | W21: =AVERAGE($V$4:$V$2517) -> #DIV/0!
B22: NOPAT | C22: =+(1-C21)*C18 -> 5158.4091 | D22: =+(1-D21)*D18 -> 6219.4593 | E22: =+(1-E21)*E18 -> 5386.6402 | F22: =+(1-F21)*F18 -> 10787.374 | G22: =+(1-G21)*G18 -> 13880.872 | H22: =+(1-H21)*H18 -> 14203.511 | I22: =+(1-I21)*I18 -> 15869.119 | J22: =+(1-J21)*J18 -> 18259.754 | ... M22: =+(1-M21)*M18 -> 0 | W22: =AVERAGE($V$4:$V$2517) -> #DIV/0!
B23: change in working capital | C23: =SUM('FC - 3FS'!AL131:AL138) -> -11885 | D23: =SUM('FC - 3FS'!AM131:AM138) -> -7114 | E23: =SUM('FC - 3FS'!AN131:AN138) -> -3055 | F23: =SUM('FC - 3FS'!AO131:AO138) -> -7058 | G23: =SUM('FC - 3FS'!AP131:AP138) -> -7009 | H23: =SUM('FC - 3FS'!AQ131:AQ138) -> -2766.9768 | I23: =SUM('FC - 3FS'!AR131:AR138) -> -2340.0684 | J23: =SUM('FC - 3FS'!AS131:AS138) -> -1865.3836 | ... M23: =SUM('FC - 3FS'!AV131:AV138) -> 0 | W23: =AVERAGE($V$4:$V$2517) -> #DIV/0!
B24: other non-cash adjustments | C24: =SUM('FC - 3FS'!AL122:AL129,'FC - 3FS'!AL139) -> 17461 | D24: =SUM('FC - 3FS'!AM122:AM129,'FC - 3FS'!AM139) -> 18007 | E24: =SUM('FC - 3FS'!AN122:AN129,'FC - 3FS'!AN139) -> 17246 | F24: =SUM('FC - 3FS'!AO122:AO129,'FC - 3FS'!AO139) -> 17300 | G24: =SUM('FC - 3FS'!AP122:AP129,'FC - 3FS'!AP139) -> 17963 | H24: =SUM('FC - 3FS'!AQ122:AQ129,'FC - 3FS'!AQ139) -> 19460.315 | I24: =SUM('FC - 3FS'!AR122:AR129,'FC - 3FS'!AR139) -> 21186.464 | J24: =SUM('FC - 3FS'!AS122:AS129,'FC - 3FS'!AS139) -> 19478.43 | ... M24: =SUM('FC - 3FS'!AV122:AV129,'FC - 3FS'!AV139) -> 0 | W24: =AVERAGE($V$4:$V$2517) -> #DIV/0!
B25: CapEx | C25: =+'FC - 3FS'!AL142 -> -11034 | D25: =+'FC - 3FS'!AM142 -> -12326 | E25: =+'FC - 3FS'!AN142 -> -13970 | F25: =+'FC - 3FS'!AO142 -> -9801 | G25: =+'FC - 3FS'!AP142 -> -8840 | H25: =+'FC - 3FS'!AQ142 -> -10023.267 | I25: =+'FC - 3FS'!AR142 -> -10562.247 | J25: =+'FC - 3FS'!AS142 -> -10941.004 | ... M25: =+'FC - 3FS'!AV142 -> 0 | W25: =AVERAGE($V$4:$V$2517) -> #DIV/0!
B26: as % of revenue | C26: =C25/C15 -> -0.16132287 | D26: =D25/D15 -> -0.15384807 | E26: =E25/E15 -> -0.17556648 | F26: =F25/F15 -> -0.12476132 | G26: =G25/G15 -> -0.10859951 | H26: =H25/H15 -> -0.1140985 | I26: =I25/I15 -> -0.11186768 | J26: =J25/J15 -> -0.11023483 | ... M26: =M25/M15 -> #DIV/0! | W26: =AVERAGE($V$4:$V$2517) -> #DIV/0!
W28: =AVERAGE($V$4:$V$2517) -> #DIV/0!
B29: Unlevered FCF | C29: =SUM(C22:C25) -> -299.59093 | D29: =SUM(D22:D25) -> 4786.4593 | E29: =SUM(E22:E25) -> 5607.6402 | F29: =SUM(F22:F25) -> 11228.374 | G29: =SUM(G22:G25) -> 15994.872 | H29: =SUM(H22:H25) -> 20873.582 | I29: =SUM(I22:I25) -> 24153.267 | J29: =SUM(J22:J25) -> 24931.797 | ... M29: =SUM(M22:M25) -> 0 | W29: =AVERAGE($V$4:$V$2517) -> #DIV/0!
B30: yoy growth | E30: =E29/D29-1 -> 0.17156333 | F30: =F29/E29-1 -> 1.0023349 | G30: =G29/F29-1 -> 0.4245048 | H30: =H29/G29-1 -> 0.30501713 | I30: =I29/H29-1 -> 0.15712135 | J30: =J29/I29-1 -> 0.032232914 | K30: =K29/J29-1 -> -1 | L30: =L29/K29-1 -> #DIV/0! | M30: =M29/L29-1 -> #DIV/0! | W30: =AVERAGE($V$4:$V$2517) -> #DIV/0!
B31: FCF Margin | C31: =C29/C15 -> -0.0043801765 | D31: =D29/D15 -> 0.05974262 | E31: =E29/E15 -> 0.070473416 | F31: =F29/F15 -> 0.142931 | G31: =G29/G15 -> 0.1964972 | H31: =H29/H15 -> 0.23761158 | I31: =I29/I15 -> 0.25581394 | J31: =J29/J15 -> 0.25119747 | ... M31: =M29/M15 -> #DIV/0! | W31: =AVERAGE($V$4:$V$2517) -> #DIV/0!
W32: =AVERAGE($V$4:$V$2517) -> #DIV/0!
B33: Years to Discount | G33: =((G13-$O$6)+(4-$N$6)/4) -> 0.25 | H33: =((H13-$O$6)+(4-$N$6)/4) -> 1.25 | I33: =((I13-$O$6)+(4-$N$6)/4) -> 2.25 | J33: =((J13-$O$6)+(4-$N$6)/4) -> 3.25 | K33: =((K13-$O$6)+(4-$N$6)/4) -> 4.25 | L33: =((L13-$O$6)+(4-$N$6)/4) -> 5.25 | M33: =((M13-$O$6)+(4-$N$6)/4) -> 6.25 | W33: =AVERAGE($V$4:$V$2517) -> #DIV/0!
B34: Discount Factor | G34: =IF(G33>0,1/(1+$I$5)^G33,0) -> 0.98178563 | H34: =IF(H33>0,1/(1+$I$5)^H33,0) -> 0.91218591 | I34: =IF(I33>0,1/(1+$I$5)^I33,0) -> 0.84752018 | J34: =IF(J33>0,1/(1+$I$5)^J33,0) -> 0.78743867 | K34: =IF(K33>0,1/(1+$I$5)^K33,0) -> 0.73161639 | L34: =IF(L33>0,1/(1+$I$5)^L33,0) -> 0.6797514 | M34: =IF(M33>0,1/(1+$I$5)^M33,0) -> 0.63156318 | W34: =AVERAGE($V$4:$V$2517) -> #DIV/0!
B35: FCFF Present Value | G35: =G29*G34 -> 15703.536 | H35: =H29*H34 -> 19040.587 | I35: =I29*I34 -> 20470.381 | J35: =J29*J34 -> 19632.261 | K35: =K29*K34 -> 0 | L35: =L29*L34 -> 0 | M35: =M29*M34 -> 0 | W35: =AVERAGE($V$4:$V$2517) -> #DIV/0!
W36: =AVERAGE($V$4:$V$2517) -> #DIV/0!
B37: Terminal Value | C37: =M29*(1+L11)/(I5-L11) -> 0 | D37: Terminal as % of total | W37: =AVERAGE($V$4:$V$2517) -> #DIV/0!
B38: PV of Terminal Value | C38: =C37*M34 -> 0 | D38: =+C38/C39 -> 0 | W38: =AVERAGE($V$4:$V$2517) -> #DIV/0!
B39: Enterprise Value | C39: =SUM(G35:M35,C38) -> 74846.766 | W39: =AVERAGE($V$4:$V$2517) -> #DIV/0!
B40: (-) Debt | C40: =I6 -> 112456 | W40: =AVERAGE($V$4:$V$2517) -> #DIV/0!
B41: (+) Cash & Cash Equivalents | C41: =+INDEX('FC - 3FS'!69:69, MATCH('Valuation (Don''t Use)'!C4,'FC - 3FS'!4:4, 0)) -> 9754 | W41: =AVERAGE($V$4:$V$2517) -> #DIV/0!
B42: Equity | C42: =+C39-C40+C41 -> -27855.234 | W42: =AVERAGE($V$4:$V$2517) -> #DIV/0!
B43: Equity Value +1 Year | C43: =C42*(1+I10) -> -30473.626 | W43: =AVERAGE($V$4:$V$2517) -> #DIV/0!
B44: Shares Outstanding +1 Year | C44: =INDEX('FC - 3FS'!39:39, MATCH('Valuation (Don''t Use)'!C5,'FC - 3FS'!4:4, 0)) -> 1126.6277 | W44: =AVERAGE($V$4:$V$2517) -> #DIV/0!
W45: =AVERAGE($V$4:$V$2517) -> #DIV/0!
B46: Implied Share Price, +1 Year | C46: =ROUND(C43/C44,0) -> -27 | W46: =AVERAGE($V$4:$V$2517) -> #DIV/0!
B47: Upside (Downside) from Current Price | C47: =C46/C6-1 -> -1.1093383 | W47: =AVERAGE($V$4:$V$2517) -> #DIV/0!
W48: =AVERAGE($V$4:$V$2517) -> #DIV/0!
W49: =AVERAGE($V$4:$V$2517) -> #DIV/0!
B50: VALUATION METHOD 2: Multiples | W50: =AVERAGE($V$4:$V$2517) -> #DIV/0!
W51: =AVERAGE($V$4:$V$2517) -> #DIV/0!
B52: NTM | C52: =IF($N$6=4,"1Q"&RIGHT($O$6,2)+1,$N$6+1&"Q"&RIGHT($O$6,2)) -> 4Q24 | D52: =IF(LEFT(C52,1)="4","1Q"&RIGHT(C52,2)+1,LEFT(C52,1)+1&"Q"&RIGHT(C52,2)) -> 1Q25 | E52: =IF(LEFT(D52,1)="4","1Q"&RIGHT(D52,2)+1,LEFT(D52,1)+1&"Q"&RIGHT(D52,2)) -> 2Q25 | F52: =IF(LEFT(E52,1)="4","1Q"&RIGHT(E52,2)+1,LEFT(E52,1)+1&"Q"&RIGHT(E52,2)) -> 3Q25 | G52: NTM Sum | H52: BERN 2025 | I52: CON 2025 | W52: =AVERAGE($V$4:$V$2517) -> #DIV/0!
B53: Revenue | C53: =INDEX('FC - 3FS'!14:14, MATCH('Valuation (Don''t Use)'!C52, 'FC - 3FS'!4:4,0)) -> 21872 | D53: =INDEX('FC - 3FS'!14:14, MATCH('Valuation (Don''t Use)'!D52, 'FC - 3FS'!4:4,0)) -> 20886 | E53: =INDEX('FC - 3FS'!14:14, MATCH('Valuation (Don''t Use)'!E52, 'FC - 3FS'!4:4,0)) -> 21132 | F53: =INDEX('FC - 3FS'!14:14, MATCH('Valuation (Don''t Use)'!F52, 'FC - 3FS'!4:4,0)) -> 21957 | G53: =+SUM(C53:F53) -> 85847 | H53: ='FC - 3FS'!AQ14 -> 87847.495 | I53: =Consensus!AA6 -> 86037.607 | W53: =AVERAGE($V$4:$V$2517) -> #DIV/0!
B54: EBITDA | C54: =INDEX('FC - 3FS'!56:56, MATCH('Valuation (Don''t Use)'!C$52, 'FC - 3FS'!$4:$4,0)) -> 7916 | D54: =INDEX('FC - 3FS'!56:56, MATCH('Valuation (Don''t Use)'!D$52, 'FC - 3FS'!$4:$4,0)) -> 8259 | E54: =INDEX('FC - 3FS'!56:56, MATCH('Valuation (Don''t Use)'!E$52, 'FC - 3FS'!$4:$4,0)) -> 8547 | F54: =INDEX('FC - 3FS'!56:56, MATCH('Valuation (Don''t Use)'!F$52, 'FC - 3FS'!$4:$4,0)) -> 8684 | G54: =+SUM(C54:F54) -> 33406 | H54: ='FC - 3FS'!AQ56 -> 33884.392 | I54: =Consensus!AA22 -> 33463.739 | W54: =AVERAGE($V$4:$V$2517) -> #DIV/0!
B55: EBIT | C55: =INDEX('FC - 3FS'!23:23, MATCH('Valuation (Don''t Use)'!C$52, 'FC - 3FS'!$4:$4,0)) -> 4586 | D55: =INDEX('FC - 3FS'!23:23, MATCH('Valuation (Don''t Use)'!D$52, 'FC - 3FS'!$4:$4,0)) -> 4800 | E55: =INDEX('FC - 3FS'!23:23, MATCH('Valuation (Don''t Use)'!E$52, 'FC - 3FS'!$4:$4,0)) -> 5213 | F55: =INDEX('FC - 3FS'!23:23, MATCH('Valuation (Don''t Use)'!F$52, 'FC - 3FS'!$4:$4,0)) -> 4530 | G55: =+SUM(C55:F55) -> 19129 | H55: ='FC - 3FS'!AQ23 -> 18579.344 | I55: =Consensus!AA14 -> 19729.905 | W55: =AVERAGE($V$4:$V$2517) -> #DIV/0!
B56: Diluted EPS | C56: =INDEX('FC - 3FS'!36:36, MATCH('Valuation (Don''t Use)'!C$52, 'FC - 3FS'!$4:$4,0)) -> 2.5718325 | D56: =INDEX('FC - 3FS'!36:36, MATCH('Valuation (Don''t Use)'!D$52, 'FC - 3FS'!$4:$4,0)) -> 2.579816 | E56: =INDEX('FC - 3FS'!36:36, MATCH('Valuation (Don''t Use)'!E$52, 'FC - 3FS'!$4:$4,0)) -> 2.8391493 | F56: =INDEX('FC - 3FS'!36:36, MATCH('Valuation (Don''t Use)'!F$52, 'FC - 3FS'!$4:$4,0)) -> 2.408959 | G56: =+SUM(C56:F56) -> 10.399757 | H56: ='FC - 3FS'!AQ36 -> 9.8240185 | I56: =Consensus!AA46 -> 10.732 | W56: =AVERAGE($V$4:$V$2517) -> #DIV/0!
W57: =AVERAGE($V$4:$V$2517) -> #DIV/0!
C58: Bernstein | E58: CON PT | G58: using current price | W58: =AVERAGE($V$4:$V$2517) -> #DIV/0!
B59: Market Cap | C59: =C43 -> -30473.626 | E59: =C10*L9 -> 316075.38 | G59: =C6*L9 -> 289080.2 | W59: =AVERAGE($V$4:$V$2517) -> #DIV/0!
B60: EV | C60: =C59+C40-C41 -> 72228.374 | E60: =E59+C40-C41 -> 418777.38 | G60: =G59+C40-C41 -> 391782.2 | W60: =AVERAGE($V$4:$V$2517) -> #DIV/0!
C61: NTM | D61: 2025 | E61: CON 2025 | G61: 2025 | H61: NTM | W61: =AVERAGE($V$4:$V$2517) -> #DIV/0!
B62: Implied EV/EBITDA | C62: =$C$60/$G54 -> 2.1621378 | D62: =$C$60/$H54 -> 2.1316119 | E62: =$E$60/I54 -> 12.514363 | G62: =G60/I54 -> 11.707664 | H62: 8.2818275 | W62: =AVERAGE($V$4:$V$2517) -> #DIV/0!
B63: Implied EV/EBIT | C63: =$C$60/$G55 -> 3.7758573 | D63: =$C$60/$H55 -> 3.8875631 | E63: =$E$60/I55 -> 21.225514 | G63: =G60/I55 -> 19.857277 | H63: 15.056695 | W63: =AVERAGE($V$4:$V$2517) -> #DIV/0!
B64: Implied P/E | C64: =$C$46/$G56 -> -2.5962145 | D64: =$C$46/$H56 -> -2.7483662 | E64: =C10/I56 -> 25.158405 | G64: =L10/I56 -> 23.009691 | H64: 18.739496 | W64: =AVERAGE($V$4:$V$2517) -> #DIV/0!
B65: Implied EV/Sales | C65: =$C$60/$G53 -> 0.84136165 | D65: =$C$60/$H53 -> 0.82220186 | H65: 3.6183573 | W65: =AVERAGE($V$4:$V$2517) -> #DIV/0!
W66: =AVERAGE($V$4:$V$2517) -> #DIV/0!
W67: =AVERAGE($V$4:$V$2517) -> #DIV/0!
W68: =AVERAGE($V$4:$V$2517) -> #DIV/0!
W69: =AVERAGE($V$4:$V$2517) -> #DIV/0!
W70: =AVERAGE($V$4:$V$2517) -> #DIV/0!
W71: =AVERAGE($V$4:$V$2517) -> #DIV/0!
W72: =AVERAGE($V$4:$V$2517) -> #DIV/0!
W73: =AVERAGE($V$4:$V$2517) -> #DIV/0!
W74: =AVERAGE($V$4:$V$2517) -> #DIV/0!
W75: =AVERAGE($V$4:$V$2517) -> #DIV/0!
W76: =AVERAGE($V$4:$V$2517) -> #DIV/0!
W77: =AVERAGE($V$4:$V$2517) -> #DIV/0!
... W2518: =AVERAGE($V$4:$V$2517) -> #DIV/0!

Sheet Consensus
A1: hide
B3: ="Date: "&TEXT(TODAY(),"mmm/dd/yyyy") -> Date: Jul/23/2026 | P3: 1Q | Q3: 2Q | R3: 3Q | S3: 4Q | T3: 5Q | U3: 6Q | V3: 7Q | AA3: 1A | AB3: 2A | AC3: 3A | AD3: 4A | AE3: 5A | AF3: 6A
C4: 1Q22 | D4: 2Q22 | E4: 3Q22 | F4: 4Q22 | G4: 1Q23 | H4: 2Q23 | I4: 3Q23 | J4: 4Q23 | K4: 1Q24 | L4: 2Q24 | M4: 3Q24 | N4: 4Q24 | O4: 1Q25 | P4: 2Q25 | Q4: 3Q25 | R4: 4Q25 | S4: 1Q26 | T4: 2Q26 | U4: 3Q26 | V4: 4Q26 | X4: 2022 | Y4: 2023 | Z4: 2024 | AA4: =Z4+1 -> 2025 | AB4: =AA4+1 -> 2026 | AC4: =AB4+1 -> 2027 | AD4: =AC4+1 -> 2028 | AE4: =AD4+1 -> 2029 | AF4: =AE4+1 -> 2030
B5: Total Revenue
B6: Con | Q6: 21320.591 | R6: 23057.091 | S6: 21905.909 | T6: 21945.727 | U6: 22380.1 | V6: 23979.3 | AA6: 86037.607 | AB6: 90228.857 | AC6: 94465.125 | AD6: 97694.5 | AE6: 99348.455 | AF6: 104578.89
B7: Bern | C7: ='FC - 3FS'!P14 -> 20120 | D7: ='FC - 3FS'!Q14 -> 19701 | E7: ='FC - 3FS'!R14 -> 19477 | F7: ='FC - 3FS'!S14 -> 20273 | G7: ='FC - 3FS'!T14 -> 19632 | H7: ='FC - 3FS'!U14 -> 19196 | I7: ='FC - 3FS'!V14 -> 19252 | J7: ='FC - 3FS'!W14 -> 20478 | ... V7: ='FC - 3FS'!AI14 -> 25233.822 | X7: ='FC - 3FS'!AN14 -> 79571 | Y7: ='FC - 3FS'!AO14 -> 78558 | Z7: ='FC - 3FS'!AP14 -> 81400 | AA7: ='FC - 3FS'!AQ14 -> 87847.495 | AB7: ='FC - 3FS'!AR14 -> 94417.322 | AC7: ='FC - 3FS'!AS14 -> 99251.787 | AD7: ='FC - 3FS'!AT14 -> 0 | AE7: ='FC - 3FS'!AU14 -> 0 | AF7: ='FC - 3FS'!AV14 -> 0
B8: Delta | Q8: =IFERROR(IF(Q6>=0,Q7/Q6-1,1-Q7/Q6), "n.a.") -> 0.029849501 | R8: =IFERROR(IF(R6>=0,R7/R6-1,1-R7/R6), "n.a.") -> 0.035364577 | S8: =IFERROR(IF(S6>=0,S7/S6-1,1-S7/S6), "n.a.") -> 0.02941561 | T8: =IFERROR(IF(T6>=0,T7/T6-1,1-T7/T6), "n.a.") -> 0.055370361 | U8: =IFERROR(IF(U6>=0,U7/U6-1,1-U7/U6), "n.a.") -> 0.048804342 | V8: =IFERROR(IF(V6>=0,V7/V6-1,1-V7/V6), "n.a.") -> 0.052316865 | AA8: =IFERROR(IF(AA6>=0,AA7/AA6-1,1-AA7/AA6), "n.a.") -> 0.021036014 | AB8: =IFERROR(IF(AB6>=0,AB7/AB6-1,1-AB7/AB6), "n.a.") -> 0.046420463 | AC8: =IFERROR(IF(AC6>=0,AC7/AC6-1,1-AC7/AC6), "n.a.") -> 0.050671207 | AD8: =IFERROR(IF(AD6>=0,AD7/AD6-1,1-AD7/AD6), "n.a.") -> -1 | AE8: =IFERROR(IF(AE6>=0,AE7/AE6-1,1-AE7/AE6), "n.a.") -> -1 | AF8: =IFERROR(IF(AF6>=0,AF7/AF6-1,1-AF7/AF6), "n.a.") -> -1
B9: Service Revenue ($M)
B10: Con | Q10: 17698.499 | R10: 17984.61 | S10: 18059.084 | T10: 18373.652 | U10: 18771.72 | V10: 19010.64 | AA10: 69874.388 | AB10: 73905.018 | AC10: 77751.408 | AD10: 81336.154 | AE10: 83248.232 | AF10: 87593.896
B11: Bern | C11: ='FC - 3FS'!P11 -> 15128 | D11: ='FC - 3FS'!Q11 -> 15316 | E11: ='FC - 3FS'!R11 -> 15361 | F11: ='FC - 3FS'!S11 -> 15518 | G11: ='FC - 3FS'!T11 -> 15546 | H11: ='FC - 3FS'!U11 -> 15738 | I11: ='FC - 3FS'!V11 -> 15914 | J11: ='FC - 3FS'!W11 -> 16043 | ... V11: ='FC - 3FS'!AI11 -> 19638.318 | X11: ='FC - 3FS'!AN11 -> 61323 | Y11: ='FC - 3FS'!AO11 -> 63241 | Z11: ='FC - 3FS'!AP11 -> 66178 | AA11: ='FC - 3FS'!AQ11 -> 71161.584 | AB11: ='FC - 3FS'!AR11 -> 76777.146 | AC11: ='FC - 3FS'!AS11 -> 81051.676 | AD11: ='FC - 3FS'!AT11 -> 0 | AE11: ='FC - 3FS'!AU11 -> 0 | AF11: ='FC - 3FS'!AV11 -> 0
B12: Difference | Q12: =IFERROR(IF(Q10>=0,Q11/Q10-1,1-Q11/Q10), "n.a.") -> 0.030652355 | R12: =IFERROR(IF(R10>=0,R11/R10-1,1-R11/R10), "n.a.") -> 0.031859137 | S12: =IFERROR(IF(S10>=0,S11/S10-1,1-S11/S10), "n.a.") -> 0.026248945 | T12: =IFERROR(IF(T10>=0,T11/T10-1,1-T11/T10), "n.a.") -> 0.039431753 | U12: =IFERROR(IF(U10>=0,U11/U10-1,1-U11/U10), "n.a.") -> 0.039199087 | V12: =IFERROR(IF(V10>=0,V11/V10-1,1-V11/V10), "n.a.") -> 0.033017192 | AA12: =IFERROR(IF(AA10>=0,AA11/AA10-1,1-AA11/AA10), "n.a.") -> 0.018421574 | AB12: =IFERROR(IF(AB10>=0,AB11/AB10-1,1-AB11/AB10), "n.a.") -> 0.03886242 | AC12: =IFERROR(IF(AC10>=0,AC11/AC10-1,1-AC11/AC10), "n.a.") -> 0.042446412 | AD12: =IFERROR(IF(AD10>=0,AD11/AD10-1,1-AD11/AD10), "n.a.") -> -1 | AE12: =IFERROR(IF(AE10>=0,AE11/AE10-1,1-AE11/AE10), "n.a.") -> -1 | AF12: =IFERROR(IF(AF10>=0,AF11/AF10-1,1-AF11/AF10), "n.a.") -> -1
B13: Operating Income
B14: Con | Q14: 5140.7217 | R14: 4787.92 | S14: 5253.1926 | T14: 5611.6538 | U14: 5823.8232 | V14: 5471.4096 | AA14: 19729.905 | AB14: 22133.428 | AC14: 24770.761 | AD14: 27076.243 | AE14: 28030.192 | AF14: 30053.193
B15: Bern | C15: ='FC - 3FS'!P23 -> 1806 | D15: ='FC - 3FS'!Q23 -> 709 | E15: ='FC - 3FS'!R23 -> 1281 | F15: ='FC - 3FS'!S23 -> 2747 | G15: ='FC - 3FS'!T23 -> 3397 | H15: ='FC - 3FS'!U23 -> 3793 | I15: ='FC - 3FS'!V23 -> 3596 | J15: ='FC - 3FS'!W23 -> 3480 | ... V15: ='FC - 3FS'!AI23 -> 5099.1664 | X15: ='FC - 3FS'!AN23 -> 6543 | Y15: ='FC - 3FS'!AO23 -> 14266 | Z15: ='FC - 3FS'!AP23 -> 18010 | AA15: ='FC - 3FS'!AQ23 -> 18579.344 | AB15: ='FC - 3FS'!AR23 -> 20628.685 | AC15: ='FC - 3FS'!AS23 -> 23736.335 | AD15: ='FC - 3FS'!AT23 -> 0 | AE15: ='FC - 3FS'!AU23 -> 0 | AF15: ='FC - 3FS'!AV23 -> 0
B16: Difference | Q16: =Q15/Q14-1 -> -0.11880077 | R16: =R15/R14-1 -> -0.15697332 | S16: =S15/S14-1 -> -0.057664404 | T16: =T15/T14-1 -> -0.036697959 | U16: =U15/U14-1 -> -0.11166082 | V16: =V15/V14-1 -> -0.068034232 | AA16: =IFERROR(IF(AA14>=0,AA15/AA14-1,1-AA15/AA14), "n.a.") -> -0.058315589 | AB16: =IFERROR(IF(AB14>=0,AB15/AB14-1,1-AB15/AB14), "n.a.") -> -0.067985093 | AC16: =IFERROR(IF(AC14>=0,AC15/AC14-1,1-AC15/AC14), "n.a.") -> -0.041759982 | AD16: =IFERROR(IF(AD14>=0,AD15/AD14-1,1-AD15/AD14), "n.a.") -> -1 | AE16: =IFERROR(IF(AE14>=0,AE15/AE14-1,1-AE15/AE14), "n.a.") -> -1 | AF16: =IFERROR(IF(AF14>=0,AF15/AF14-1,1-AF15/AF14), "n.a.") -> -1
B18: Consensus Margin | Q18: =Q14/Q6 -> 0.24111535 | R18: =R14/R6 -> 0.20765499 | S18: =S14/S6 -> 0.2398071 | T18: =T14/T6 -> 0.25570599 | U18: =U14/U6 -> 0.26022329 | V18: =V14/V6 -> 0.2281722 | AA18: =AA14/AA6 -> 0.22931723 | AB18: =AB14/AB6 -> 0.24530321 | AC18: =AC14/AC6 -> 0.26222123 | AD18: =AD14/AD6 -> 0.27715217 | AE18: =AE14/AE6 -> 0.28214019 | AF18: =AF14/AF6 -> 0.28737342
B19: Bernstein Margin | G19: =G15/G7 -> 0.17303382 | H19: =H15/H7 -> 0.19759325 | I19: =I15/I7 -> 0.18678579 | J19: =J15/J7 -> 0.16993847 | K19: =K15/K7 -> 0.20404205 | L19: =L15/L7 -> 0.23416953 | M19: =M15/M7 -> 0.23787323 | N19: =N15/N7 -> 0.20967447 | ... V19: =V15/V7 -> 0.20207666 | X19: =X15/X7 -> 0.08222845 | Y19: =Y15/Y7 -> 0.18159831 | Z19: =Z15/Z7 -> 0.22125307 | AA19: =AA15/AA7 -> 0.21149544 | AB19: =AB15/AB7 -> 0.21848411 | AC19: =AC15/AC7 -> 0.23915272 | AD19: =AD15/AD7 -> #DIV/0! | AE19: =AE15/AE7 -> #DIV/0! | AF19: =AF15/AF7 -> #DIV/0!
B20: Delta | Q20: =Q19-Q18 -> -0.034803008 | R20: =R19-R18 -> -0.038575711 | S20: =S19-S18 -> -0.02028569 | T20: =T19-T18 -> -0.02230726 | U20: =U19-U18 -> -0.03981369 | V20: =V19-V18 -> -0.026095538 | AA20: =AA19-AA18 -> -0.01782179 | AB20: =AB19-AB18 -> -0.026819095 | AC20: =AC19-AC18 -> -0.023068511 | AD20: =AD19-AD18 -> #DIV/0! | AE20: =AE19-AE18 -> #DIV/0! | AF20: =AF19-AF18 -> #DIV/0!
B21: Adj. EBITDA ($M)
B22: Con | Q22: 8584.526 | R22: 8285.421 | S22: 8856.455 | T22: 9181.727 | U22: 9376.455 | V22: 8968.455 | AA22: 33463.739 | AB22: 35699 | AC22: 38857.333 | AD22: 40577.333 | AE22: 42432.2 | AF22: 44291.222
B23: Bern | C23: ='FC - 3FS'!P56 -> 6950 | D23: ='FC - 3FS'!Q56 -> 7004 | E23: ='FC - 3FS'!R56 -> 7039 | F23: ='FC - 3FS'!S56 -> 6828 | G23: ='FC - 3FS'!T56 -> 7199 | H23: ='FC - 3FS'!U56 -> 7405 | I23: ='FC - 3FS'!V56 -> 7600 | J23: ='FC - 3FS'!W56 -> 7224 | ... V23: ='FC - 3FS'!AI56 -> 9159.25 | X23: ='FC - 3FS'!AN56 -> 27821 | Y23: ='FC - 3FS'!AO56 -> 29428 | Z23: ='FC - 3FS'!AP56 -> 31864 | AA23: ='FC - 3FS'!AQ56 -> 33884.392 | AB23: ='FC - 3FS'!AR56 -> 37383.145 | AC23: ='FC - 3FS'!AS56 -> 40069.347 | AD23: ='FC - 3FS'!AT56 -> 0 | AE23: ='FC - 3FS'!AU56 -> 0 | AF23: ='FC - 3FS'!AV56 -> 0
B24: Difference | Q24: =IFERROR(IF(Q22>=0,Q23/Q22-1,1-Q23/Q22), "n.a.") -> 0.011587594 | R24: =IFERROR(IF(R22>=0,R23/R22-1,1-R23/R22), "n.a.") -> 0.013152197 | S24: =IFERROR(IF(S22>=0,S23/S22-1,1-S23/S22), "n.a.") -> 0.047744458 | T24: =IFERROR(IF(T22>=0,T23/T22-1,1-T23/T22), "n.a.") -> 0.048256858 | U24: =IFERROR(IF(U22>=0,U23/U22-1,1-U23/U22), "n.a.") -> -0.0060438073 | V24: =IFERROR(IF(V22>=0,V23/V22-1,1-V23/V22), "n.a.") -> 0.021274005 | AA24: =IFERROR(IF(AA22>=0,AA23/AA22-1,1-AA23/AA22), "n.a.") -> 0.012570427 | AB24: =IFERROR(IF(AB22>=0,AB23/AB22-1,1-AB23/AB22), "n.a.") -> 0.047176263 | AC24: =IFERROR(IF(AC22>=0,AC23/AC22-1,1-AC23/AC22), "n.a.") -> 0.031191381 | AD24: =IFERROR(IF(AD22>=0,AD23/AD22-1,1-AD23/AD22), "n.a.") -> -1 | AE24: =IFERROR(IF(AE22>=0,AE23/AE22-1,1-AE23/AE22), "n.a.") -> -1 | AF24: =IFERROR(IF(AF22>=0,AF23/AF22-1,1-AF23/AF22), "n.a.") -> -1
B26: Con | Q26: =Q22/Q10 -> 0.48504259 | R26: =R22/R10 -> 0.46069507 | S26: =S22/S10 -> 0.49041551 | T26: =T22/T10 -> 0.49972249 | U26: =U22/U10 -> 0.49949897 | V26: =V22/V10 -> 0.47175975 | AA26: =AA22/AA10 -> 0.4789128 | AB26: =AB22/AB10 -> 0.48303892 | AC26: =AC22/AC10 -> 0.49976372 | AD26: =AD22/AD10 -> 0.49888433 | AE26: =AE22/AE10 -> 0.50970692 | AF26: =AF22/AF10 -> 0.50564279
B27: Bern | C27: =C23/C11 -> 0.45941301 | D27: =D23/D11 -> 0.45729956 | E27: =E23/E11 -> 0.4582384 | F27: =F23/F11 -> 0.44000516 | G27: =G23/G11 -> 0.46307732 | H27: =H23/H11 -> 0.47051722 | I27: =I23/I11 -> 0.47756692 | J27: =J23/J11 -> 0.45028985 | ... V27: =V23/V11 -> 0.46639686 | X27: =X23/X11 -> 0.4536797 | Y27: =Y23/Y11 -> 0.46533104 | Z27: =Z23/Z11 -> 0.48148932 | AA27: =AA23/AA11 -> 0.4761613 | AB27: =AB23/AB11 -> 0.4869046 | AC27: =AC23/AC11 -> 0.4943679 | AD27: =AD23/AD11 -> #DIV/0! | AE27: =AE23/AE11 -> #DIV/0! | AF27: =AF23/AF11 -> #DIV/0!
B28: Delta | Q28: =Q27-Q26 -> -0.008972202 | R28: =R27-R26 -> -0.0083521042 | S28: =S27-S26 -> 0.010272102 | T28: =T27-T26 -> 0.0042428021 | U28: =U27-U26 -> -0.021746342 | V28: =V27-V26 -> -0.0053628955 | AA28: =AA27-AA26 -> -0.0027515023 | AB28: =AB27-AB26 -> 0.0038656798 | AC28: =AC27-AC26 -> -0.0053958228 | AD28: =AD27-AD26 -> #DIV/0! | AE28: =AE27-AE26 -> #DIV/0! | AF28: =AF27-AF26 -> #DIV/0!
B29: Core Adj. EBITDA
B30: Con | Q30: 8598.119 | R30: 8293.6831 | S30: 8876.1037 | T30: 9212.8436 | U30: 9408.5501 | V30: 8999.469 | AA30: 33526.304 | AB30: 36254.431 | AC30: 39001.072 | AD30: 41322.23 | AE30: 42560.689 | AF30: 45397.347
B31: Bern | C31: ='FC - 3FS'!P58 -> 6463 | D31: ='FC - 3FS'!Q58 -> 6618 | E31: ='FC - 3FS'!R58 -> 6728 | F31: ='FC - 3FS'!S58 -> 6582 | G31: ='FC - 3FS'!T58 -> 7052 | H31: ='FC - 3FS'!U58 -> 7336 | I31: ='FC - 3FS'!V58 -> 7547 | J31: ='FC - 3FS'!W58 -> 7181 | ... V31: ='FC - 3FS'!AI58 -> 9155.25 | X31: ='FC - 3FS'!AN58 -> 26391 | Y31: ='FC - 3FS'!AO58 -> 29116 | Z31: ='FC - 3FS'!AP58 -> 31771 | AA31: ='FC - 3FS'!AQ58 -> 33869.392 | AB31: ='FC - 3FS'!AR58 -> 37367.145 | AC31: ='FC - 3FS'!AS58 -> 40069.347 | AD31: ='FC - 3FS'!AT58 -> 0 | AE31: ='FC - 3FS'!AU58 -> 0 | AF31: ='FC - 3FS'!AV58 -> 0
B32: Delta | Q32: =IFERROR(IF(Q30>=0,Q31/Q30-1,1-Q31/Q30), "n.a.") -> 0.0095231262 | R32: =IFERROR(IF(R30>=0,R31/R30-1,1-R31/R30), "n.a.") -> 0.01166061 | S32: =IFERROR(IF(S30>=0,S31/S30-1,1-S31/S30), "n.a.") -> 0.044974454 | T32: =IFERROR(IF(T30>=0,T31/T30-1,1-T31/T30), "n.a.") -> 0.044282172 | U32: =IFERROR(IF(U30>=0,U31/U30-1,1-U31/U30), "n.a.") -> -0.0098596016 | V32: =IFERROR(IF(V30>=0,V31/V30-1,1-V31/V30), "n.a.") -> 0.017310019 | AA32: =IFERROR(IF(AA30>=0,AA31/AA30-1,1-AA31/AA30), "n.a.") -> 0.010233427 | AB32: =IFERROR(IF(AB30>=0,AB31/AB30-1,1-AB31/AB30), "n.a.") -> 0.030691831 | AC32: =IFERROR(IF(AC30>=0,AC31/AC30-1,1-AC31/AC30), "n.a.") -> 0.027390921 | AD32: =IFERROR(IF(AD30>=0,AD31/AD30-1,1-AD31/AD30), "n.a.") -> -1 | AE32: =IFERROR(IF(AE30>=0,AE31/AE30-1,1-AE31/AE30), "n.a.") -> -1 | AF32: =IFERROR(IF(AF30>=0,AF31/AF30-1,1-AF31/AF30), "n.a.") -> -1
B34: Con | Q34: =Q30/Q10 -> 0.48581063 | R34: =R30/R10 -> 0.46115446 | S34: =S30/S10 -> 0.49150353 | T34: =T30/T10 -> 0.50141604 | U34: =U30/U10 -> 0.50120873 | V34: =V30/V10 -> 0.47339115 | AA34: =AA30/AA10 -> 0.47980819 | AB34: =AB30/AB10 -> 0.49055438 | AC34: =AC30/AC10 -> 0.50161242 | AD34: =AD30/AD10 -> 0.50804259 | AE34: =AE30/AE10 -> 0.51125036 | AF34: =AF30/AF10 -> 0.51827066
B35: Bern | C35: =C31/C11 -> 0.42722105 | D35: =D31/D11 -> 0.43209715 | E35: =E31/E11 -> 0.43799232 | F35: =F31/F11 -> 0.4241526 | G35: =G31/G11 -> 0.45362151 | H35: =H31/H11 -> 0.46613293 | I35: =I31/I11 -> 0.47423652 | J35: =J31/J11 -> 0.44760955 | ... V35: =V31/V11 -> 0.46619317 | X35: =X31/X11 -> 0.43036055 | Y35: =Y31/Y11 -> 0.46039753 | Z35: =Z31/Z11 -> 0.48008402 | AA35: =AA31/AA11 -> 0.47595051 | AB35: =AB31/AB11 -> 0.4866962 | AC35: =AC31/AC11 -> 0.4943679 | AD35: =AD31/AD11 -> #DIV/0! | AE35: =AE31/AE11 -> #DIV/0! | AF35: =AF31/AF11 -> #DIV/0!
B36: Delta | Q36: =Q35-Q34 -> -0.009959521 | R36: =R35-R34 -> -0.0090270468 | S36: =S35-S34 -> 0.0089682469 | T36: =T35-T34 -> 0.0023398149 | U36: =U35-U34 -> -0.023661147 | V36: =V35-V34 -> -0.0071979797 | AA36: =AA35-AA34 -> -0.0038576757 | AB36: =AB35-AB34 -> -0.0038581802 | AC36: =AC35-AC34 -> -0.0072445174 | AD36: =AD35-AD34 -> #DIV/0! | AE36: =AE35-AE34 -> #DIV/0! | AF36: =AF35-AF34 -> #DIV/0!
B37: Net Income
B38: Con | Q38: 3151 | R38: 2840.667 | S38: 3227.833 | T38: 3370.333 | U38: 3499.167 | V38: 3270.5 | AA38: 12070.875 | AB38: 13822.261 | AC38: 15526.556 | AD38: 16698.889 | AE38: 17934.429 | AF38: 18673.333
B39: Bern | C39: ='FC - 3FS'!P32 -> 713 | D39: ='FC - 3FS'!Q32 -> -108 | E39: ='FC - 3FS'!R32 -> 508 | F39: ='FC - 3FS'!S32 -> 1477 | G39: ='FC - 3FS'!T32 -> 1940 | H39: ='FC - 3FS'!U32 -> 2221 | I39: ='FC - 3FS'!V32 -> 2142 | J39: ='FC - 3FS'!W32 -> 2014 | ... V39: ='FC - 3FS'!AI32 -> 3093.7114 | X39: ='FC - 3FS'!AN32 -> 2590 | Y39: ='FC - 3FS'!AO32 -> 8317 | Z39: ='FC - 3FS'!AP32 -> 11339 | AA39: ='FC - 3FS'!AQ32 -> 11153.528 | AB39: ='FC - 3FS'!AR32 -> 12666.801 | AC39: ='FC - 3FS'!AS32 -> 14834.136 | AD39: ='FC - 3FS'!AT32 -> 0 | AE39: ='FC - 3FS'!AU32 -> 0 | AF39: ='FC - 3FS'!AV32 -> 0
B40: Delta | Q40: =IFERROR(IF(Q38>=0,Q39/Q38-1,1-Q39/Q38), "n.a.") -> -0.13868613 | R40: =IFERROR(IF(R38>=0,R39/R38-1,1-R39/R38), "n.a.") -> -0.20281826 | S40: =IFERROR(IF(S38>=0,S39/S38-1,1-S39/S38), "n.a.") -> -0.06117743 | T40: =IFERROR(IF(T38>=0,T39/T38-1,1-T39/T38), "n.a.") -> 0.000529664 | U40: =IFERROR(IF(U38>=0,U39/U38-1,1-U39/U38), "n.a.") -> -0.093896189 | V40: =IFERROR(IF(V38>=0,V39/V38-1,1-V39/V38), "n.a.") -> -0.054055537 | AA40: =IFERROR(IF(AA38>=0,AA39/AA38-1,1-AA39/AA38), "n.a.") -> -0.07599674 | AB40: =IFERROR(IF(AB38>=0,AB39/AB38-1,1-AB39/AB38), "n.a.") -> -0.083594172 | AC40: =IFERROR(IF(AC38>=0,AC39/AC38-1,1-AC39/AC38), "n.a.") -> -0.044595873 | AD40: =IFERROR(IF(AD38>=0,AD39/AD38-1,1-AD39/AD38), "n.a.") -> -1 | AE40: =IFERROR(IF(AE38>=0,AE39/AE38-1,1-AE39/AE38), "n.a.") -> -1 | AF40: =IFERROR(IF(AF38>=0,AF39/AF38-1,1-AF39/AF38), "n.a.") -> -1
B42: Consensus Margin | Q42: =Q38/Q6 -> 0.1477914 | R42: =R38/R6 -> 0.12320145 | S42: =S38/S6 -> 0.14734988 | T42: =T38/T6 -> 0.15357582 | U42: =U38/U6 -> 0.15635171 | V42: =V38/V6 -> 0.13638847 | AA42: =AA38/AA6 -> 0.14029766 | AB42: =AB38/AB6 -> 0.15319113 | AC42: =AC38/AC6 -> 0.16436284 | AD42: =AD38/AD6 -> 0.17092967 | AE42: =AE38/AE6 -> 0.18052046 | AF42: =AF38/AF6 -> 0.17855739
B43: Bernstein Margin | C43: =C39/C7 -> 0.035437376 | D43: =D39/D7 -> -0.0054819552 | E43: =E39/E7 -> 0.026082045 | F43: =F39/F7 -> 0.072855522 | G43: =G39/G7 -> 0.098818256 | H43: =H39/H7 -> 0.11570119 | I43: =I39/I7 -> 0.11126117 | J43: =J39/J7 -> 0.098349448 | ... V43: =V39/V7 -> 0.12260178 | X43: =X39/X7 -> 0.032549547 | Y43: =Y39/Y7 -> 0.10587082 | Z43: =Z39/Z7 -> 0.13929975 | AA43: =AA39/AA7 -> 0.12696467 | AB43: =AB39/AB7 -> 0.13415759 | AC43: =AC39/AC7 -> 0.14945963 | AD43: =AD39/AD7 -> #DIV/0! | AE43: =AE39/AE7 -> #DIV/0! | AF43: =AF39/AF7 -> #DIV/0!
B44: Delta | Q44: =Q43-Q42 -> -0.024186172 | R44: =R43-R42 -> -0.028342162 | S44: =S43-S42 -> -0.012967429 | T44: =T43-T42 -> -0.0079803312 | U44: =U43-U42 -> -0.021273246 | V44: =V43-V42 -> -0.013786692 | AA44: =AA43-AA42 -> -0.013332995 | AB44: =AB43-AB42 -> -0.019033544 | AC44: =AC43-AC42 -> -0.014903204 | AD44: =AD43-AD42 -> #DIV/0! | AE44: =AE43-AE42 -> #DIV/0! | AF44: =AF43-AF42 -> #DIV/0!
B45: Adj. EPS
B46: Con | Q46: 2.806 | R46: 2.576 | S46: 2.936 | T46: 3.139 | U46: 3.258 | V46: 3.106 | AA46: 10.732 | AB46: 12.704 | AC46: 14.93 | AD46: 16.955 | AE46: 19.134 | AF46: 20.95
B47: Bern | C47: ='FC - 3FS'!P36 -> 0.56796068 | D47: ='FC - 3FS'!Q36 -> -0.086129005 | E47: ='FC - 3FS'!R36 -> 0.40342746 | F47: ='FC - 3FS'!S36 -> 1.1845565 | G47: ='FC - 3FS'!T36 -> 1.5841847 | H47: ='FC - 3FS'!U36 -> 1.857748 | I47: ='FC - 3FS'!V36 -> 1.8239249 | J47: ='FC - 3FS'!W36 -> 1.6713497 | ... V47: ='FC - 3FS'!AI36 -> 2.7826403 | X47: ='FC - 3FS'!AN36 -> 2.0631256 | Y47: ='FC - 3FS'!AO36 -> 6.9291804 | Z47: ='FC - 3FS'!AP36 -> 9.6649043 | AA47: ='FC - 3FS'!AQ36 -> 9.8240185 | AB47: ='FC - 3FS'!AR36 -> 11.388496 | AC47: ='FC - 3FS'!AS36 -> 13.613006 | AD47: ='FC - 3FS'!AT36 -> 0 | AE47: ='FC - 3FS'!AU36 -> 0 | AF47: ='FC - 3FS'!AV36 -> 0
B48: Delta | Q48: =IFERROR(IF(Q46>=0,Q47/Q46-1,1-Q47/Q46), "n.a.") -> -0.14149714 | R48: =IFERROR(IF(R46>=0,R47/R46-1,1-R47/R46), "n.a.") -> -0.22511874 | S48: =IFERROR(IF(S46>=0,S47/S46-1,1-S47/S46), "n.a.") -> -0.078928006 | T48: =IFERROR(IF(T46>=0,T47/T46-1,1-T47/T46), "n.a.") -> -0.034753652 | U48: =IFERROR(IF(U46>=0,U47/U46-1,1-U47/U46), "n.a.") -> -0.11857565 | V48: =IFERROR(IF(V46>=0,V47/V46-1,1-V47/V46), "n.a.") -> -0.10410809 | AA48: =IFERROR(IF(AA46>=0,AA47/AA46-1,1-AA47/AA46), "n.a.") -> -0.084605064 | AB48: =IFERROR(IF(AB46>=0,AB47/AB46-1,1-AB47/AB46), "n.a.") -> -0.10355034 | AC48: =IFERROR(IF(AC46>=0,AC47/AC46-1,1-AC47/AC46), "n.a.") -> -0.088211285 | AD48: =IFERROR(IF(AD46>=0,AD47/AD46-1,1-AD47/AD46), "n.a.") -> -1 | AE48: =IFERROR(IF(AE46>=0,AE47/AE46-1,1-AE47/AE46), "n.a.") -> -1 | AF48: =IFERROR(IF(AF46>=0,AF47/AF46-1,1-AF47/AF46), "n.a.") -> -1
B49: Adj. FCF
B50: Con | Q50: 4789.9667 | R50: 4557.049 | S50: 4152.7803 | T50: 4619.3023 | U50: 4814.6109 | V50: 4909.0734 | AA50: 17786.778 | AB50: 18728.96 | AC50: 19552.05 | AD50: 21158.268 | AE50: 21725.505 | AF50: 23366.362
B51: Bern | C51: ='FC - 3FS'!P173 -> 1649 | D51: ='FC - 3FS'!Q173 -> 1758 | E51: ='FC - 3FS'!R173 -> 2065 | F51: ='FC - 3FS'!S173 -> 2184 | G51: ='FC - 3FS'!T173 -> 2401 | H51: ='FC - 3FS'!U173 -> 2877 | I51: ='FC - 3FS'!V173 -> 4003 | J51: ='FC - 3FS'!W173 -> 4305 | ... V51: ='FC - 3FS'!AI173 -> 5183.7807 | X51: ='FC - 3FS'!AN173 -> 7656 | Y51: ='FC - 3FS'!AO173 -> 13586 | Z51: ='FC - 3FS'!AP173 -> 17032 | AA51: ='FC - 3FS'!AQ173 -> 17823.599 | AB51: ='FC - 3FS'!AR173 -> 20950.949 | AC51: ='FC - 3FS'!AS173 -> 21506.179 | AD51: ='FC - 3FS'!AT173 -> 0 | AE51: ='FC - 3FS'!AU173 -> 0 | AF51: ='FC - 3FS'!AV173 -> 0
B52: Delta | Q52: =IFERROR(IF(Q50>=0,Q51/Q50-1,1-Q51/Q50), "n.a.") -> 0.0058524938 | R52: =IFERROR(IF(R50>=0,R51/R50-1,1-R51/R50), "n.a.") -> -0.11925477 | S52: =IFERROR(IF(S50>=0,S51/S50-1,1-S51/S50), "n.a.") -> 0.023089727 | T52: =IFERROR(IF(T50>=0,T51/T50-1,1-T51/T50), "n.a.") -> 0.15639127 | U52: =IFERROR(IF(U50>=0,U51/U50-1,1-U51/U50), "n.a.") -> 0.28292423 | V52: =IFERROR(IF(V50>=0,V51/V50-1,1-V51/V50), "n.a.") -> 0.055959095 | AA52: =IFERROR(IF(AA50>=0,AA51/AA50-1,1-AA51/AA50), "n.a.") -> 0.002070163 | AB52: =IFERROR(IF(AB50>=0,AB51/AB50-1,1-AB51/AB50), "n.a.") -> 0.11863922 | AC52: =IFERROR(IF(AC50>=0,AC51/AC50-1,1-AC51/AC50), "n.a.") -> 0.09994496 | AD52: =IFERROR(IF(AD50>=0,AD51/AD50-1,1-AD51/AD50), "n.a.") -> -1 | AE52: =IFERROR(IF(AE50>=0,AE51/AE50-1,1-AE51/AE50), "n.a.") -> -1 | AF52: =IFERROR(IF(AF50>=0,AF51/AF50-1,1-AF51/AF50), "n.a.") -> -1
B54: Consensus Margin | Q54: =Q50/Q10 -> 0.27064254 | R54: =R50/R10 -> 0.25338604 | S54: =S50/S10 -> 0.2299552 | T54: =T50/T10 -> 0.25140905 | U54: =U50/U10 -> 0.25648213 | V54: =V50/V10 -> 0.25822767 | AA54: =AA50/AA10 -> 0.25455361 | AB54: =AB50/AB10 -> 0.25341933 | AC54: =AC50/AC10 -> 0.25146876 | AD54: =AD50/AD10 -> 0.26013362 | AE54: =AE50/AE10 -> 0.26097257 | AF54: =AF50/AF10 -> 0.26675788
B55: Bernstein Margin | C55: =C51/C11 -> 0.10900317 | D55: =D51/D11 -> 0.11478193 | E55: =E51/E11 -> 0.13443135 | F55: =F51/F11 -> 0.14073979 | G55: =G51/G11 -> 0.15444487 | H55: =H51/H11 -> 0.18280595 | I55: =I51/I11 -> 0.25153952 | J55: =J51/J11 -> 0.26834133 | ... V55: =V51/V11 -> 0.26396256 | X55: =X51/X11 -> 0.12484712 | Y55: =Y51/Y11 -> 0.21482899 | Z55: =Z51/Z11 -> 0.2573665 | AA55: =AA51/AA11 -> 0.25046659 | AB55: =AB51/AB11 -> 0.27288002 | AC55: =AC51/AC11 -> 0.2653391 | AD55: =AD51/AD11 -> #DIV/0! | AE55: =AE51/AE11 -> #DIV/0! | AF55: =AF51/AF11 -> #DIV/0!
B56: Delta | Q56: =+Q55-Q54 -> -0.0065122806 | R56: =+R55-R54 -> -0.037107927 | S56: =+S55-S54 -> -0.00070789692 | T56: =+T55-T54 -> 0.028289188 | U56: =+U55-U54 -> 0.060153193 | V56: =+V55-V54 -> 0.0057348845 | AA56: =+AA55-AA54 -> -0.0040870214 | AB56: =+AB55-AB54 -> 0.019460693 | AC56: =+AC55-AC54 -> 0.013870342 | AD56: =+AD55-AD54 -> #DIV/0! | AE56: =+AE55-AE54 -> #DIV/0! | AF56: =+AF55-AF54 -> #DIV/0!
B57: CapEx
B58: Con | Q58: 2272.4737 | R58: 2361.4737 | S58: 2398.9 | T58: 2423 | U58: 2446.6 | V58: 2467.3 | AA58: 9514.0952 | AB58: 9706.7619 | AC58: 9875.55 | AD58: 10155.143 | AE58: 10388 | AF58: 10782
B59: Bern | C59: =-'FC - 3FS'!P170 -> 3381 | D59: =-'FC - 3FS'!Q170 -> 3572 | E59: =-'FC - 3FS'!R170 -> 3634 | F59: =-'FC - 3FS'!S170 -> 3383 | G59: =-'FC - 3FS'!T170 -> 3001 | H59: =-'FC - 3FS'!U170 -> 2789 | I59: =-'FC - 3FS'!V170 -> 2424 | J59: =-'FC - 3FS'!W170 -> 1587 | ... V59: =-'FC - 3FS'!AI170 -> 2696.4357 | X59: =-'FC - 3FS'!AN170 -> 13970 | Y59: =-'FC - 3FS'!AO170 -> 9801 | Z59: =-'FC - 3FS'!AP170 -> 8840 | AA59: =-'FC - 3FS'!AQ170 -> 10023.267 | AB59: =-'FC - 3FS'!AR170 -> 10562.247 | AC59: =-'FC - 3FS'!AS170 -> 10941.004 | AD59: =-'FC - 3FS'!AT170 -> 0 | AE59: =-'FC - 3FS'!AU170 -> 0 | AF59: =-'FC - 3FS'!AV170 -> 0
B60: Delta | Q60: =IFERROR(IF(Q58>=0,Q59/Q58-1,1-Q59/Q58), "n.a.") -> 0.16128958 | R60: =IFERROR(IF(R58>=0,R59/R58-1,1-R59/R58), "n.a.") -> 0.074442237 | S60: =IFERROR(IF(S58>=0,S59/S58-1,1-S59/S58), "n.a.") -> 0.073412099 | T60: =IFERROR(IF(T58>=0,T59/T58-1,1-T59/T58), "n.a.") -> 0.084152318 | U60: =IFERROR(IF(U58>=0,U59/U58-1,1-U59/U58), "n.a.") -> 0.088817811 | V60: =IFERROR(IF(V58>=0,V59/V58-1,1-V59/V58), "n.a.") -> 0.092868999 | AA60: =IFERROR(IF(AA58>=0,AA59/AA58-1,1-AA59/AA58), "n.a.") -> 0.05351763 | AB60: =IFERROR(IF(AB58>=0,AB59/AB58-1,1-AB59/AB58), "n.a.") -> 0.08813287 | AC60: =IFERROR(IF(AC58>=0,AC59/AC58-1,1-AC59/AC58), "n.a.") -> 0.10788802 | AD60: =IFERROR(IF(AD58>=0,AD59/AD58-1,1-AD59/AD58), "n.a.") -> -1 | AE60: =IFERROR(IF(AE58>=0,AE59/AE58-1,1-AE59/AE58), "n.a.") -> -1 | AF60: =IFERROR(IF(AF58>=0,AF59/AF58-1,1-AF59/AF58), "n.a.") -> -1
B62: KPIs (in 000's except ARPU)
B63: Postpaid Phone Subs
B64: Con | Q64: 81253.026 | R64: 82235.021 | S64: 83148.435 | T64: 83774.842 | U64: 84498.601 | V64: 85267.859 | AA64: 81692.288 | AB64: 84777.398 | AC64: 87264.533 | AD64: 89270.054 | AE64: 89510.674 | AF64: 92000.221
B65: Bern | C65: ='IS Drivers'!P36 -> 70656 | D65: ='IS Drivers'!Q36 -> 71053 | E65: ='IS Drivers'!R36 -> 71907 | F65: ='IS Drivers'!S36 -> 72834 | G65: ='IS Drivers'!T36 -> 73372 | H65: ='IS Drivers'!U36 -> 74132 | I65: ='IS Drivers'!V36 -> 74982 | J65: ='IS Drivers'!W36 -> 75936 | ... V65: ='IS Drivers'!AI36 -> 88770.438 | X65: ='IS Drivers'!AN36 -> 72834 | Y65: ='IS Drivers'!AO36 -> 75936 | Z65: ='IS Drivers'!AP36 -> 79013 | AA65: ='IS Drivers'!AQ36 -> 85630.676 | AB65: ='IS Drivers'!AR36 -> 88770.438 | AC65: ='IS Drivers'!AS36 -> 91816.006 | AD65: ='IS Drivers'!AT36 -> 0 | AE65: ='IS Drivers'!AU36 -> 0 | AF65: ='IS Drivers'!AV36 -> 0
B66: Delta | Q66: =IFERROR(IF(Q64>=0,Q65/Q64-1,1-Q65/Q64), "n.a.") -> 0.041585827 | R66: =IFERROR(IF(R64>=0,R65/R64-1,1-R65/R64), "n.a.") -> 0.041292087 | S66: =IFERROR(IF(S64>=0,S65/S64-1,1-S65/S64), "n.a.") -> 0.035905327 | T66: =IFERROR(IF(T64>=0,T65/T64-1,1-T65/T64), "n.a.") -> 0.037558935 | U66: =IFERROR(IF(U64>=0,U65/U64-1,1-U65/U64), "n.a.") -> 0.039527458 | V66: =IFERROR(IF(V64>=0,V65/V64-1,1-V65/V64), "n.a.") -> 0.041077363 | AA66: =IFERROR(IF(AA64>=0,AA65/AA64-1,1-AA65/AA64), "n.a.") -> 0.048210034 | AB66: =IFERROR(IF(AB64>=0,AB65/AB64-1,1-AB65/AB64), "n.a.") -> 0.047100285 | AC66: =IFERROR(IF(AC64>=0,AC65/AC64-1,1-AC65/AC64), "n.a.") -> 0.052157196 | AD66: =IFERROR(IF(AD64>=0,AD65/AD64-1,1-AD65/AD64), "n.a.") -> -1 | AE66: =IFERROR(IF(AE64>=0,AE65/AE64-1,1-AE65/AE64), "n.a.") -> -1 | AF66: =IFERROR(IF(AF64>=0,AF65/AF64-1,1-AF65/AF64), "n.a.") -> -1
B67: Postpaid Phone ARPU
B68: Con | Q68: 50.427161 | R68: 50.374254 | S68: 49.985858 | T68: 50.331933 | U68: 50.860074 | V68: 50.755195 | AA68: 49.98985 | AB68: 50.573943 | AC68: 51.090062 | AD68: 51.642933 | AE68: 52.112613 | AF68: 52.841644
B69: Bern | C69: ='IS Drivers'!P117 -> 48.41 | D69: ='IS Drivers'!Q117 -> 48.96 | E69: ='IS Drivers'!R117 -> 48.89 | F69: ='IS Drivers'!S117 -> 48.86 | G69: ='IS Drivers'!T117 -> 48.63 | H69: ='IS Drivers'!U117 -> 48.84 | I69: ='IS Drivers'!V117 -> 48.93 | J69: ='IS Drivers'!W117 -> 48.91 | ... V69: ='IS Drivers'!AI117 -> 51.434993 | X69: ='IS Drivers'!AN117 -> 48.78 | Y69: ='IS Drivers'!AO117 -> 48.83 | Z69: ='IS Drivers'!AP117 -> 49.35 | AA69: ='IS Drivers'!AQ117 -> 50.04652 | AB69: ='IS Drivers'!AR117 -> 51.002129 | AC69: ='IS Drivers'!AS117 -> 51.869165 | AD69: ='IS Drivers'!AT117 -> 0 | AE69: ='IS Drivers'!AU117 -> 0 | AF69: ='IS Drivers'!AV117 -> 0
B70: Delta | Q70: =IFERROR(IF(Q68>=0,Q69/Q68-1,1-Q69/Q68), "n.a.") -> 0.0056088667 | R70: =IFERROR(IF(R68>=0,R69/R68-1,1-R69/R68), "n.a.") -> 0.0059676471 | S70: =IFERROR(IF(S68>=0,S69/S68-1,1-S69/S68), "n.a.") -> 0.0026975936 | T70: =IFERROR(IF(T68>=0,T69/T68-1,1-T69/T68), "n.a.") -> 0.020809204 | U70: =IFERROR(IF(U68>=0,U69/U68-1,1-U69/U68), "n.a.") -> 0.01200502 | V70: =IFERROR(IF(V68>=0,V69/V68-1,1-V69/V68), "n.a.") -> 0.013393655 | AA70: =IFERROR(IF(AA68>=0,AA69/AA68-1,1-AA69/AA68), "n.a.") -> 0.001133631 | AB70: =IFERROR(IF(AB68>=0,AB69/AB68-1,1-AB69/AB68), "n.a.") -> 0.008466521 | AC70: =IFERROR(IF(AC68>=0,AC69/AC68-1,1-AC69/AC68), "n.a.") -> 0.015249604 | AD70: =IFERROR(IF(AD68>=0,AD69/AD68-1,1-AD69/AD68), "n.a.") -> -1 | AE70: =IFERROR(IF(AE68>=0,AE69/AE68-1,1-AE69/AE68), "n.a.") -> -1 | AF70: =IFERROR(IF(AF68>=0,AF69/AF68-1,1-AF69/AF68), "n.a.") -> -1
B71: Total Postpaid Subs
B72: Con | Q72: 108476.64 | R72: 110192.1 | S72: 111757.06 | T72: 112957.54 | U72: 114303.47 | V72: 115868.23 | AA72: 110141.03 | AB72: 115575.54 | AC72: 120311.44 | AD72: 124246.9 | AE72: 125446.61 | AF72: 130510.41
B73: Bern | C73: ='IS Drivers'!P41 -> 88423 | D73: ='IS Drivers'!Q41 -> 88787 | E73: ='IS Drivers'!R41 -> 90414 | F73: ='IS Drivers'!S41 -> 92232 | G73: ='IS Drivers'!T41 -> 93525 | H73: ='IS Drivers'!U41 -> 95086 | I73: ='IS Drivers'!V41 -> 96312 | J73: ='IS Drivers'!W41 -> 98052 | ... V73: ='IS Drivers'!AI41 -> 122095.92 | X73: ='IS Drivers'!AN41 -> 92232 | Y73: ='IS Drivers'!AO41 -> 98052 | Z73: ='IS Drivers'!AP41 -> 104118 | AA73: ='IS Drivers'!AQ41 -> 115595.34 | AB73: ='IS Drivers'!AR41 -> 122095.92 | AC73: ='IS Drivers'!AS41 -> 128488.21 | AD73: ='IS Drivers'!AT41 -> 0 | AE73: ='IS Drivers'!AU41 -> 0 | AF73: ='IS Drivers'!AV41 -> 0
B74: Delta | Q74: =IFERROR(IF(Q72>=0,Q73/Q72-1,1-Q73/Q72), "n.a.") -> 0.051498236 | R74: =IFERROR(IF(R72>=0,R73/R72-1,1-R73/R72), "n.a.") -> 0.049034735 | S74: =IFERROR(IF(S72>=0,S73/S72-1,1-S73/S72), "n.a.") -> 0.045722282 | T74: =IFERROR(IF(T72>=0,T73/T72-1,1-T73/T72), "n.a.") -> 0.047878988 | U74: =IFERROR(IF(U72>=0,U73/U72-1,1-U73/U72), "n.a.") -> 0.051642745 | V74: =IFERROR(IF(V72>=0,V73/V72-1,1-V73/V72), "n.a.") -> 0.053748072 | AA74: =IFERROR(IF(AA72>=0,AA73/AA72-1,1-AA73/AA72), "n.a.") -> 0.049521108 | AB74: =IFERROR(IF(AB72>=0,AB73/AB72-1,1-AB73/AB72), "n.a.") -> 0.056416608 | AC74: =IFERROR(IF(AC72>=0,AC73/AC72-1,1-AC73/AC72), "n.a.") -> 0.067963286 | AD74: =IFERROR(IF(AD72>=0,AD73/AD72-1,1-AD73/AD72), "n.a.") -> -1 | AE74: =IFERROR(IF(AE72>=0,AE73/AE72-1,1-AE73/AE72), "n.a.") -> -1 | AF74: =IFERROR(IF(AF72>=0,AF73/AF72-1,1-AF73/AF72), "n.a.") -> -1
B75: Postpaid ARPU
B76: Con | Q76: 44.096735 | R76: 44.002916 | S76: 43.770446 | T76: 44.140557 | U76: 44.706579 | V76: 44.645787 | AA76: 43.722948 | AB76: 44.131061 | AC76: 44.531698 | AD76: 44.898541 | AE76: 45.439712 | AF76: 45.937121
B77: Bern | Q77: ='IS Drivers'!AD126 -> 44.822534 | R77: ='IS Drivers'!AE126 -> 44.126636 | S77: ='IS Drivers'!AF126 -> 43.823431 | T77: ='IS Drivers'!AG126 -> 44.781915 | U77: ='IS Drivers'!AH126 -> 45.274285 | V77: ='IS Drivers'!AI126 -> 44.84552 | X77: ='IS Drivers'!AN126 -> 42.542409 | Y77: ='IS Drivers'!AO126 -> 42.648532 | Z77: ='IS Drivers'!AP126 -> 43.148505 | AA77: ='IS Drivers'!AQ126 -> 43.810931 | AB77: ='IS Drivers'!AR126 -> 44.58391 | AC77: ='IS Drivers'!AS126 -> 45.259907 | AD77: ='IS Drivers'!AT126 -> 0 | AE77: ='IS Drivers'!AU126 -> 0 | AF77: ='IS Drivers'!AV126 -> 0
B78: Delta | Q78: =IFERROR(IF(Q76>=0,Q77/Q76-1,1-Q77/Q76), "n.a.") -> 0.016459229 | R78: =IFERROR(IF(R76>=0,R77/R76-1,1-R77/R76), "n.a.") -> 0.0028116146 | S78: =IFERROR(IF(S76>=0,S77/S76-1,1-S77/S76), "n.a.") -> 0.0012105301 | T78: =IFERROR(IF(T76>=0,T77/T76-1,1-T77/T76), "n.a.") -> 0.014529896 | U78: =IFERROR(IF(U76>=0,U77/U76-1,1-U77/U76), "n.a.") -> 0.012698485 | V78: =IFERROR(IF(V76>=0,V77/V76-1,1-V77/V76), "n.a.") -> 0.0044737184 | AA78: =IFERROR(IF(AA76>=0,AA77/AA76-1,1-AA77/AA76), "n.a.") -> 0.0020122756 | AB78: =IFERROR(IF(AB76>=0,AB77/AB76-1,1-AB77/AB76), "n.a.") -> 0.010261458 | AC78: =IFERROR(IF(AC76>=0,AC77/AC76-1,1-AC77/AC76), "n.a.") -> 0.016352597 | AD78: =IFERROR(IF(AD76>=0,AD77/AD76-1,1-AD77/AD76), "n.a.") -> -1 | AE78: =IFERROR(IF(AE76>=0,AE77/AE76-1,1-AE77/AE76), "n.a.") -> -1 | AF78: =IFERROR(IF(AF76>=0,AF77/AF76-1,1-AF77/AF76), "n.a.") -> -1
B79: Postpaid ARPA
B80: Con | Q80: 149.92283 | R80: 150.53788 | S80: 150.07825 | T80: 151.58261 | U80: 153.86924 | V80: 154.2548 | AA80: 148.25761 | AB80: 151.86218 | AC80: 155.23362 | AD80: 158.30207 | AE80: 161.25574 | AF80: 167.48092
B81: Bern | C81: ='IS Drivers'!P112 -> 136.53 | D81: ='IS Drivers'!Q112 -> 137.92 | E81: ='IS Drivers'!R112 -> 137.49 | F81: ='IS Drivers'!S112 -> 137.78 | G81: ='IS Drivers'!T112 -> 138.04 | H81: ='IS Drivers'!U112 -> 138.94 | I81: ='IS Drivers'!V112 -> 139.83 | J81: ='IS Drivers'!W112 -> 140.23 | ... V81: ='IS Drivers'!AI112 -> 151.27669 | X81: ='IS Drivers'!AN112 -> 137.43 | Y81: ='IS Drivers'!AO112 -> 139.27 | Z81: ='IS Drivers'!AP112 -> 143.85 | AA81: ='IS Drivers'!AQ112 -> 147.90273 | AB81: ='IS Drivers'!AR112 -> 150.8416 | AC81: ='IS Drivers'!AS112 -> 153.08502 | AD81: ='IS Drivers'!AT112 -> 0 | AE81: ='IS Drivers'!AU112 -> 0 | AF81: ='IS Drivers'!AV112 -> 0
B82: Delta | Q82: =IFERROR(IF(Q80>=0,Q81/Q80-1,1-Q81/Q80), "n.a.") -> -0.003220497 | R82: =IFERROR(IF(R80>=0,R81/R80-1,1-R81/R80), "n.a.") -> -0.012444944 | S82: =IFERROR(IF(S80>=0,S81/S80-1,1-S81/S80), "n.a.") -> -0.010633894 | T82: =IFERROR(IF(T80>=0,T81/T80-1,1-T81/T80), "n.a.") -> 0.0052218299 | U82: =IFERROR(IF(U80>=0,U81/U80-1,1-U81/U80), "n.a.") -> -0.0039647248 | V82: =IFERROR(IF(V80>=0,V81/V80-1,1-V81/V80), "n.a.") -> -0.019306424 | AA82: =IFERROR(IF(AA80>=0,AA81/AA80-1,1-AA81/AA80), "n.a.") -> -0.0023936507 | AB82: =IFERROR(IF(AB80>=0,AB81/AB80-1,1-AB81/AB80), "n.a.") -> -0.0067204534 | AC82: =IFERROR(IF(AC80>=0,AC81/AC80-1,1-AC81/AC80), "n.a.") -> -0.013841031 | AD82: =IFERROR(IF(AD80>=0,AD81/AD80-1,1-AD81/AD80), "n.a.") -> -1 | AE82: =IFERROR(IF(AE80>=0,AE81/AE80-1,1-AE81/AE80), "n.a.") -> -1 | AF82: =IFERROR(IF(AF80>=0,AF81/AF80-1,1-AF81/AF80), "n.a.") -> -1
B83: Total Prepaid Subs
B84: Con | Q84: 25303.094 | R84: 25387.311 | S84: 25616.998 | T84: 25691.221 | U84: 25750.337 | V84: 25829.804 | AA84: 25339.395 | AB84: 25601.875 | AC84: 25788.978 | AD84: 25842.968 | AE84: 25634.774 | AF84: 26235.701
B85: Bern | C85: ='IS Drivers'!P145 -> 21118 | D85: ='IS Drivers'!Q145 -> 21236 | E85: ='IS Drivers'!R145 -> 21341 | F85: ='IS Drivers'!S145 -> 21366 | G85: ='IS Drivers'!T145 -> 21392 | H85: ='IS Drivers'!U145 -> 21516 | I85: ='IS Drivers'!V145 -> 21595 | J85: ='IS Drivers'!W145 -> 21648 | ... V85: ='IS Drivers'!AI145 -> 26507.447 | X85: ='IS Drivers'!AN145 -> 21366 | Y85: ='IS Drivers'!AO145 -> 21648 | Z85: ='IS Drivers'!AP145 -> 25410 | AA85: ='IS Drivers'!AQ145 -> 25965.567 | AB85: ='IS Drivers'!AR145 -> 26507.447 | AC85: ='IS Drivers'!AS145 -> 26992.672 | AD85: ='IS Drivers'!AT145 -> 0 | AE85: ='IS Drivers'!AU145 -> 0 | AF85: ='IS Drivers'!AV145 -> 0
B86: Delta | Q86: =IFERROR(IF(Q84>=0,Q85/Q84-1,1-Q85/Q84), "n.a.") -> 0.023036946 | R86: =IFERROR(IF(R84>=0,R85/R84-1,1-R85/R84), "n.a.") -> 0.022777384 | S86: =IFERROR(IF(S84>=0,S85/S84-1,1-S85/S84), "n.a.") -> 0.011048809 | T86: =IFERROR(IF(T84>=0,T85/T84-1,1-T85/T84), "n.a.") -> 0.0094408552 | U86: =IFERROR(IF(U84>=0,U85/U84-1,1-U85/U84), "n.a.") -> 0.024315077 | V86: =IFERROR(IF(V84>=0,V85/V84-1,1-V85/V84), "n.a.") -> 0.026234939 | AA86: =IFERROR(IF(AA84>=0,AA85/AA84-1,1-AA85/AA84), "n.a.") -> 0.02471143 | AB86: =IFERROR(IF(AB84>=0,AB85/AB84-1,1-AB85/AB84), "n.a.") -> 0.035371299 | AC86: =IFERROR(IF(AC84>=0,AC85/AC84-1,1-AC85/AC84), "n.a.") -> 0.046674755 | AD86: =IFERROR(IF(AD84>=0,AD85/AD84-1,1-AD85/AD84), "n.a.") -> -1 | AE86: =IFERROR(IF(AE84>=0,AE85/AE84-1,1-AE85/AE84), "n.a.") -> -1 | AF86: =IFERROR(IF(AF84>=0,AF85/AF84-1,1-AF85/AF84), "n.a.") -> -1
B87: Prepaid ARPU
B88: Con | Q88: 35.250782 | R88: 35.113656 | S88: 34.594193 | T88: 34.817878 | U88: 34.840906 | V88: 34.72027 | AA88: 35.247986 | AB88: 35.337936 | AC88: 35.482596 | AD88: 36.235768 | AE88: 36.952856 | AF88: 37.35168
B89: Bern | C89: ='IS Drivers'!P178 -> 39.19 | D89: ='IS Drivers'!Q178 -> 38.71 | E89: ='IS Drivers'!R178 -> 38.86 | F89: ='IS Drivers'!S178 -> 38.29 | G89: ='IS Drivers'!T178 -> 37.98 | H89: ='IS Drivers'!U178 -> 37.98 | I89: ='IS Drivers'!V178 -> 38.18 | J89: ='IS Drivers'!W178 -> 37.55 | ... V89: ='IS Drivers'!AI178 -> 32.223872 | X89: ='IS Drivers'!AN178 -> 38.76 | Y89: ='IS Drivers'!AO178 -> 37.92 | Z89: ='IS Drivers'!AP178 -> 36.06 | AA89: ='IS Drivers'!AQ178 -> 34.110733 | AB89: ='IS Drivers'!AR178 -> 32.489087 | AC89: ='IS Drivers'!AS178 -> 30.944536 | AD89: ='IS Drivers'!AT178 -> 0 | AE89: ='IS Drivers'!AU178 -> 0 | AF89: ='IS Drivers'!AV178 -> 0
B90: Delta | Q90: =IFERROR(IF(Q88>=0,Q89/Q88-1,1-Q89/Q88), "n.a.") -> -0.03746817 | R90: =IFERROR(IF(R88>=0,R89/R88-1,1-R89/R88), "n.a.") -> -0.046611333 | S90: =IFERROR(IF(S88>=0,S89/S88-1,1-S89/S88), "n.a.") -> -0.049815739 | T90: =IFERROR(IF(T88>=0,T89/T88-1,1-T89/T88), "n.a.") -> -0.052288927 | U90: =IFERROR(IF(U88>=0,U89/U88-1,1-U89/U88), "n.a.") -> -0.067323986 | V90: =IFERROR(IF(V88>=0,V89/V88-1,1-V89/V88), "n.a.") -> -0.071900288 | AA90: =IFERROR(IF(AA88>=0,AA89/AA88-1,1-AA89/AA88), "n.a.") -> -0.032264356 | AB90: =IFERROR(IF(AB88>=0,AB89/AB88-1,1-AB89/AB88), "n.a.") -> -0.080617285 | AC90: =IFERROR(IF(AC88>=0,AC89/AC88-1,1-AC89/AC88), "n.a.") -> -0.12789537 | AD90: =IFERROR(IF(AD88>=0,AD89/AD88-1,1-AD89/AD88), "n.a.") -> -1 | AE90: =IFERROR(IF(AE88>=0,AE89/AE88-1,1-AE89/AE88), "n.a.") -> -1 | AF90: =IFERROR(IF(AF88>=0,AF89/AF88-1,1-AF89/AF88), "n.a.") -> -1
B91: Total FWA Subs
B92: Con | Q92: 7598.9413 | R92: 7990.1284 | S92: 8373.8065 | T92: 8725.3375 | U92: 9091.3956 | V92: 9453.4871 | AA92: 7990.1284 | AB92: 9408.4451 | AC92: 10786.507 | AD92: 12024.79 | AE92: 12878.109 | AF92: 13657.25
B93: Bern | C93: ='IS Drivers'!P20 -> 984 | D93: ='IS Drivers'!Q20 -> 1544 | E93: ='IS Drivers'!R20 -> 2122 | F93: ='IS Drivers'!S20 -> 2646 | G93: ='IS Drivers'!T20 -> 3169 | H93: ='IS Drivers'!U20 -> 3678 | I93: ='IS Drivers'!V20 -> 4235 | J93: ='IS Drivers'!W20 -> 4776 | ... V93: ='IS Drivers'!AI20 -> 9962.5709 | X93: ='IS Drivers'!AN20 -> 2646 | Y93: ='IS Drivers'!AO20 -> 4776 | Z93: ='IS Drivers'!AP20 -> 6430 | AA93: ='IS Drivers'!AQ20 -> 8365.8536 | AB93: ='IS Drivers'!AR20 -> 9962.5709 | AC93: ='IS Drivers'!AS20 -> 11490.171 | AD93: ='IS Drivers'!AT20 -> 0 | AE93: ='IS Drivers'!AU20 -> 0 | AF93: ='IS Drivers'!AV20 -> 0
B94: Delta | Q94: =IFERROR(IF(Q92>=0,Q93/Q92-1,1-Q93/Q92), "n.a.") -> 0.046856356 | R94: =IFERROR(IF(R92>=0,R93/R92-1,1-R93/R92), "n.a.") -> 0.047023672 | S94: =IFERROR(IF(S92>=0,S93/S92-1,1-S93/S92), "n.a.") -> 0.046110896 | T94: =IFERROR(IF(T92>=0,T93/T92-1,1-T93/T92), "n.a.") -> 0.047825015 | U94: =IFERROR(IF(U92>=0,U93/U92-1,1-U93/U92), "n.a.") -> 0.052727425 | V94: =IFERROR(IF(V92>=0,V93/V92-1,1-V93/V92), "n.a.") -> 0.053851436 | AA94: =IFERROR(IF(AA92>=0,AA93/AA92-1,1-AA93/AA92), "n.a.") -> 0.047023672 | AB94: =IFERROR(IF(AB92>=0,AB93/AB92-1,1-AB93/AB92), "n.a.") -> 0.058896637 | AC94: =IFERROR(IF(AC92>=0,AC93/AC92-1,1-AC93/AC92), "n.a.") -> 0.065235607 | AD94: =IFERROR(IF(AD92>=0,AD93/AD92-1,1-AD93/AD92), "n.a.") -> -1 | AE94: =IFERROR(IF(AE92>=0,AE93/AE92-1,1-AE93/AE92), "n.a.") -> -1 | AF94: =IFERROR(IF(AF92>=0,AF93/AF92-1,1-AF93/AF92), "n.a.") -> -1

Sheet Guidance
A1: hide
B3: in millions | D3: FY2023 | I3: FY2024 | N3: FY2025 | S3: FY2027 | U3: FY2028
B4: Guidance provided in: | D4: 4Q22 | E4: 1Q23 | F4: 2Q23 | G4: 3Q23 | I4: 4Q23 | J4: 1Q24 | K4: 2Q24 | L4: 3Q24 | N4: 45536 | O4: 4Q24 | P4: 1Q25 | Q4: 2Q25 | S4: 45536
B5: Cash from operating activities
B6: low | D6: 17800 | E6: 17900 | F6: 18000 | G6: 18300 | I6: 21500 | J6: 21600 | K6: 21800 | L6: 22000 | O6: 26800 | P6: 27000 | Q6: 27100 | S6: 24000
B7: high | D7: 18300 | E7: 18300 | F7: 18300 | G7: 18500 | I7: 22300 | J7: 22300 | K7: 22200 | L7: 22300 | O7: 27500 | P7: 27500 | Q7: 27500 | S7: 25000
B8: mid | D8: =+AVERAGE(D6:D7) -> 18050 | E8: =+AVERAGE(E6:E7) -> 18100 | F8: =+AVERAGE(F6:F7) -> 18150 | G8: =+AVERAGE(G6:G7) -> 18400 | I8: =+AVERAGE(I6:I7) -> 21900 | J8: =+AVERAGE(J6:J7) -> 21950 | K8: =+AVERAGE(K6:K7) -> 22000 | L8: =+AVERAGE(L6:L7) -> 22150 | O8: =+AVERAGE(O6:O7) -> 27150 | P8: =+AVERAGE(P6:P7) -> 27250 | Q8: =+AVERAGE(Q6:Q7) -> 27300 | S8: =+AVERAGE(S6:S7) -> 24500
B9: raise | E9: =+E8-D8 -> 50 | F9: =+F8-E8 -> 50 | G9: =+G8-F8 -> 250 | J9: =+J8-I8 -> 50 | K9: =+K8-J8 -> 50 | L9: =+L8-K8 -> 150
B10: actual | D10: ='FC - 3FS'!AO140 -> 18559 | E10: =+D10 -> 18559 | F10: =+E10 -> 18559 | G10: =+F10 -> 18559 | I10: ='FC - 3FS'!AP140 -> 22293 | J10: =+I10 -> 22293 | K10: =+J10 -> 22293 | L10: =+K10 -> 22293 | O10: ='FC - 3FS'!AQ140 -> 27846.866 | P10: =+O10 -> 27846.866 | Q10: =+P10 -> 27846.866 | S10: ='FC - 3FS'!AS140 -> 32447.182
B11: delta | D11: =+D10/D8-1 -> 0.028199446 | E11: =+E10/E8-1 -> 0.025359116 | F11: =+F10/F8-1 -> 0.022534435 | G11: =+G10/G8-1 -> 0.0086413043 | I11: =+I10/I8-1 -> 0.017945205 | J11: =+J10/J8-1 -> 0.015626424 | K11: =+K10/K8-1 -> 0.013318182 | L11: =+L10/L8-1 -> 0.0064559819 | O11: =+O10/O8-1 -> 0.025667267 | P11: =+P10/P8-1 -> 0.02190335 | Q11: =+Q10/Q8-1 -> 0.020031732 | S11: =S10/S8-1 -> 0.3243748
B13: Cash purchase of PP&E
B14: low | D14: 9400 | E14: 9400 | F14: 9500 | G14: 9600 | I14: 8600 | J14: 8600 | K14: 8700 | L14: 8800 | S14: 9000
B15: high | D15: 9700 | E15: 9700 | F15: 9700 | G15: 9800 | I15: 9400 | J15: 9400 | K15: 9100 | L15: 9000 | S15: 10000
B16: mid | D16: =+AVERAGE(D14:D15) -> 9550 | E16: =+AVERAGE(E14:E15) -> 9550 | F16: =+AVERAGE(F14:F15) -> 9600 | G16: =+AVERAGE(G14:G15) -> 9700 | I16: =+AVERAGE(I14:I15) -> 9000 | J16: =+AVERAGE(J14:J15) -> 9000 | K16: =+AVERAGE(K14:K15) -> 8900 | L16: =+AVERAGE(L14:L15) -> 8900 | O16: 9500 | P16: 9500 | Q16: 9500 | S16: =+AVERAGE(S14:S15) -> 9500
B17: actual | D17: =-'FC - 3FS'!AO142 -> 9801 | E17: =+D17 -> 9801 | F17: =+E17 -> 9801 | G17: =+F17 -> 9801 | I17: =-'FC - 3FS'!AP142 -> 8840 | J17: =+I17 -> 8840 | K17: =+J17 -> 8840 | L17: =+K17 -> 8840 | O17: =-'FC - 3FS'!AQ170 -> 10023.267 | P17: =+O17 -> 10023.267 | Q17: =+P17 -> 10023.267 | S17: =-'FC - 3FS'!AS142 -> 10941.004
B18: delta | D18: =+D17/D16-1 -> 0.026282723 | E18: =+E17/E16-1 -> 0.026282723 | F18: =+F17/F16-1 -> 0.0209375 | G18: =+G17/G16-1 -> 0.010412371 | I18: =+I17/I16-1 -> -0.017777778 | J18: =+J17/J16-1 -> -0.017777778 | K18: =+K17/K16-1 -> -0.006741573 | L18: =+L17/L16-1 -> -0.006741573 | O18: =+O17/O16-1 -> 0.055080744 | P18: =+P17/P16-1 -> 0.055080744 | Q18: =+Q17/Q16-1 -> 0.055080744 | S18: =S17/S16-1 -> 0.15168458
B20: Adjusted FCF | D20: does not assume any material net cash inflows from securitization
B21: low | D21: 13100 | E21: 13200 | F21: 13200 | G21: 13400 | I21: =+I6-I14+I86 -> 16300 | J21: =+J6-J14+J86 -> 16400 | K21: =+K6-K14+K86 -> 16600 | L21: =+L6-L14+L86 -> 16700 | O21: 17300 | P21: 17500 | Q21: 17600 | S21: 18000
B22: high | D22: 13600 | E22: 13600 | F22: 13600 | G22: 13600 | I22: =+I7-I15+I87 -> 16900 | J22: =+J7-J15+J87 -> 16900 | K22: =+K7-K15+K87 -> 17000 | L22: =+L7-L15+L87 -> 17000 | N22: YoY | O22: 18000 | P22: 18000 | Q22: 18000 | S22: 19000 | T22: CAGR
B23: mid | D23: =+AVERAGE(D21:D22) -> 13350 | E23: =+AVERAGE(E21:E22) -> 13400 | F23: =+AVERAGE(F21:F22) -> 13400 | G23: =+AVERAGE(G21:G22) -> 13500 | I23: =+I8-I16+I88 -> 16600 | J23: =+J8-J16+J88 -> 16650 | K23: =+K8-K16+K88 -> 16800 | L23: =+L8-L16+L88 -> 16850 | N23: =+O23/L25-1 -> 0.036284641 | O23: =+O8-O16+O88 -> 17650 | P23: =+P8-P16+P88 -> 17750 | Q23: =+Q8-Q16+Q88 -> 17800 | S23: =+AVERAGE(S21:S22) -> 18500 | T23: 0.08
B24: raise | E24: =+E23-D23 -> 50 | F24: =+F23-E23 -> 0 | G24: =+G23-F23 -> 100 | J24: =+J23-I23 -> 50 | K24: =+K23-J23 -> 150 | L24: =+L23-K23 -> 50
B25: actual | D25: ='FC - 3FS'!AO173 -> 13586 | E25: =+D25 -> 13586 | F25: =+E25 -> 13586 | G25: =+F25 -> 13586 | I25: ='FC - 3FS'!AP173 -> 17032 | J25: =+I25 -> 17032 | K25: =+J25 -> 17032 | L25: =+K25 -> 17032 | O25: ='FC - 3FS'!AQ173 -> 17823.599 | P25: =+O25 -> 17823.599 | Q25: =+P25 -> 17823.599 | S25: ='FC - 3FS'!AS173 -> 21506.179
B26: delta | D26: =D25/D23-1 -> 0.017677903 | E26: =E25/E23-1 -> 0.013880597 | F26: =F25/F23-1 -> 0.013880597 | G26: =G25/G23-1 -> 0.0063703704 | I26: =I25/I23-1 -> 0.026024096 | J26: =J25/J23-1 -> 0.022942943 | K26: =K25/K23-1 -> 0.013809524 | L26: =+L25/L23-1 -> 0.010801187 | O26: =+O25/O23-1 -> 0.0098356503 | P26: =+P25/P23-1 -> 0.0041464353 | Q26: =+Q25/Q23-1 -> 0.0013257993 | S26: =S25/S23-1 -> 0.16249616
B28: Postpaid net adds (in K)
B29: low | D29: 5000 | E29: 5300 | F29: 5600 | G29: 5700 | I29: 5000 | J29: 5200 | K29: 5400 | L29: 5600 | O29: 5500 | P29: 5500 | Q29: 6100
B30: high | D30: 5500 | E30: 5700 | F30: 5900 | G30: 5900 | I30: 5500 | J30: 5600 | K30: 5700 | L30: 5800 | O30: 6000 | P30: 6000 | Q30: 6400
B31: mid | D31: =+AVERAGE(D29:D30) -> 5250 | E31: =+AVERAGE(E29:E30) -> 5500 | F31: =+AVERAGE(F29:F30) -> 5750 | G31: =+AVERAGE(G29:G30) -> 5800 | I31: =+AVERAGE(I29:I30) -> 5250 | J31: =+AVERAGE(J29:J30) -> 5400 | K31: =+AVERAGE(K29:K30) -> 5550 | L31: =+AVERAGE(L29:L30) -> 5700 | O31: =+AVERAGE(O29:O30) -> 5750 | P31: =+AVERAGE(P29:P30) -> 5750 | Q31: =+AVERAGE(Q29:Q30) -> 6250
B32: raise | E32: =+E31-D31 -> 250 | F32: =+F31-E31 -> 250 | G32: =+G31-F31 -> 50 | J32: =+J31-I31 -> 150 | K32: =+K31-J31 -> 150 | L32: =+L31-K31 -> 150
B33: actual | D33: ='IS Drivers'!AO90 -> 5799 | E33: =+D33 -> 5799 | F33: =+E33 -> 5799 | G33: =+F33 -> 5799 | I33: ='IS Drivers'!AP90 -> 6058 | J33: =+I33 -> 6058 | K33: =+J33 -> 6058 | L33: =+K33 -> 6058 | O33: ='IS Drivers'!AQ90 -> 7197.3362 | P33: =+O33 -> 7197.3362 | Q33: =+P33 -> 7197.3362
B34: delta | D34: =+D33/D31-1 -> 0.10457143 | E34: =+E33/E31-1 -> 0.054363636 | F34: =+F33/F31-1 -> 0.0085217391 | G34: =+G33/G31-1 -> -0.00017241379 | I34: =+I33/I31-1 -> 0.15390476 | J34: =+J33/J31-1 -> 0.12185185 | K34: =+K33/K31-1 -> 0.091531532 | L34: =+L33/L31-1 -> 0.062807018 | O34: =+O33/O31-1 -> 0.25171065 | P34: =+P33/P31-1 -> 0.25171065 | Q34: =+Q33/Q31-1 -> 0.1515738
B36: Postpaid Phone net adds (in K)
B37: mid | K37: =F31/2 -> 2875 | L37: =G31/2 -> 2900 | O37: =+O31/2 -> 2875 | P37: =+P31/2 -> 2875 | Q37: =(2950+3100)/2 -> 3025
B38: actual | K38: ='IS Drivers'!AP62 -> 3077 | L38: =K38 -> 3077 | O38: ='IS Drivers'!AQ62 -> 3330.6762 | P38: =+O38 -> 3330.6762 | Q38: =+P38 -> 3330.6762
B39: delta | K39: =+K38/K37-1 -> 0.07026087 | L39: =+L38/L37-1 -> 0.061034483 | O39: =+O38/O37-1 -> 0.15849608 | P39: =+P38/P37-1 -> 0.15849608 | Q39: =+Q38/Q37-1 -> 0.10105
B41: Core Adjusted EBITDA
B42: low | D42: 28700 | E42: 28800 | F42: 28900 | G42: 29000 | I42: 31300 | J42: 31400 | K42: 31500 | L42: 31600 | O42: 33100 | P42: 33200 | Q42: 33300 | S42: 38000
B43: high | D43: 29200 | E43: 29200 | F43: 29200 | G43: 29200 | I43: 31900 | J43: 31900 | K43: 31800 | L43: 31800 | N43: YoY | O43: 33600 | P43: 33700 | Q43: 33700 | S43: 39000 | T43: CAGR
B44: mid | D44: =+AVERAGE(D42:D43) -> 28950 | E44: =+AVERAGE(E42:E43) -> 29000 | F44: =+AVERAGE(F42:F43) -> 29050 | G44: =+AVERAGE(G42:G43) -> 29100 | I44: =+AVERAGE(I42:I43) -> 31600 | J44: =+AVERAGE(J42:J43) -> 31650 | K44: =+AVERAGE(K42:K43) -> 31650 | L44: =+AVERAGE(L42:L43) -> 31700 | N44: =+O44/L46-1 -> 0.049699411 | O44: =+AVERAGE(O42:O43) -> 33350 | P44: =+AVERAGE(P42:P43) -> 33450 | Q44: =+AVERAGE(Q42:Q43) -> 33500 | S44: =AVERAGE(S42:S43) -> 38500 | T44: 0.07
B45: raise | E45: =+E44-D44 -> 50 | F45: =+F44-E44 -> 50 | G45: =+G44-F44 -> 50 | J45: =+J44-I44 -> 50 | K45: =+K44-J44 -> 0 | L45: =+L44-K44 -> 50 | N45: YoY
B46: actual | D46: ='FC - 3FS'!AO58 -> 29116 | E46: =+D46 -> 29116 | F46: =+E46 -> 29116 | G46: =+F46 -> 29116 | I46: ='FC - 3FS'!AP58 -> 31771 | J46: =+I46 -> 31771 | K46: =+J46 -> 31771 | L46: =+K46 -> 31771 | N46: =+O46/L46-1 -> 0.066047417 | O46: ='FC - 3FS'!AQ58 -> 33869.392 | P46: =+O46 -> 33869.392 | Q46: =+P46 -> 33869.392 | S46: ='FC - 3FS'!AS58 -> 40069.347
B47: delta | D47: =+D46/D44-1 -> 0.0057340242 | E47: =+E46/E44-1 -> 0.004 | F47: =+F46/F44-1 -> 0.0022719449 | G47: =+G46/G44-1 -> 0.00054982818 | I47: =+I46/I44-1 -> 0.0054113924 | J47: =+J46/J44-1 -> 0.0038230648 | K47: =+K46/K44-1 -> 0.0038230648 | L47: =+L46/L44-1 -> 0.0022397476 | O47: =+O46/O44-1 -> 0.015573988 | P47: =+P46/P44-1 -> 0.012537892 | Q47: =+Q46/Q44-1 -> 0.011026641 | S47: =+S46/S44-1 -> 0.040762257
B48: guided margin | O48: =+O44/O67 -> 0.47994658 | P48: =+P44/P67 -> 0.47774573 | S48: =S44/S67 -> 0.50993377
B49: model margin | L49: ='FC - 3FS'!AP60 -> 0.48008402 | O49: ='FC - 3FS'!AQ60 -> 0.47595051 | P49: =+O49 -> 0.47595051 | S49: =S46/S68 -> 0.4943679
B51: Postpaid Service Revenue
B52: low
B53: high
B54: mid | S54: ='FC - 3FS'!AO6*(1+6%)^4 -> 61472.528
B55: model | S55: ='FC - 3FS'!AS6 -> 68048.486
B56: delta | S56: =S55/S54-1 -> 0.10697393
B58: Postpaid ARPA
B59: guided CAGR | K59: 0.03 | L59: =K59 -> 0.03 | O59: 0.03 | P59: 0.035 | S59: 0.02
B60: implied ARPA | K60: =(1+K59)*'IS Drivers'!AO112 -> 143.4481 | L60: =K60 -> 143.4481 | O60: =(1+O59)*L61 -> 148.1655 | P60: =(1+P59)*L61 -> 148.88475 | S60: ='IS Drivers'!AO112*(1+2%)^4 -> 150.75033
B61: model | K61: =+'IS Drivers'!AP112 -> 143.85 | L61: =K61 -> 143.85 | O61: ='IS Drivers'!AQ112 -> 147.90273 | P61: =+O61 -> 147.90273 | S61: ='IS Drivers'!AS112 -> 153.08502
B62: delta | K62: =K61/K60-1 -> 0.0028017102 | L62: =L61/L60-1 -> 0.0028017102 | O62: =O61/O60-1 -> -0.0017734625 | P62: =P61/P60-1 -> -0.0065958129 | S62: =S61/S60-1 -> 0.015487169
P63: =+P61/L61-1 -> 0.028173334
B64: Total Service Revenue
B65: low | S65: 75000
B66: high | P66: =+'FC - 3FS'!AQ11 -> 71161.584 | S66: 76000
B67: mid | K67: accelerate at a higher rate | N67: =(1+N70)*'FC - 3FS'!$AP$11 -> 68825.12 | O67: =(1+O70)*'FC - 3FS'!$AP$11 -> 69486.9 | P67: =(1+P70)*'FC - 3FS'!$AP$11 -> 70016.324 | Q67: =(1+Q70)*'FC - 3FS'!$AP$11 -> 70148.68 | S67: =AVERAGE(S65:S66) -> 75500
B68: model | L68: ='IS Drivers'!AP7 -> 0.046441391 | N68: =+'IS Drivers'!AQ6/'IS Drivers'!AP6-1 -> 0.075305751 | O68: =+N68 -> 0.075305751 | P68: =+O68 -> 0.075305751 | Q68: =+P68 -> 0.075305751 | S68: ='FC - 3FS'!AS11 -> 81051.676
B69: delta | O69: =+O68-O70 -> 0.025305751 | P69: =+P68-P70 -> 0.017305751 | Q69: =+Q68-Q70 -> 0.015305751 | S69: =S68/S67-1 -> 0.073532137
B70: YoY growth rate | N70: 0.04 | O70: 0.05 | P70: 0.058 | Q70: 0.06
B71: $ amount raised | P71: =+P67-O67 -> 529.424
B73: Effective tax rate
B74: low | I74: 0.24 | J74: 0.24 | K74: 0.24 | O74: 0.24 | P74: 0.24
B75: high | I75: 0.26 | J75: 0.26 | K75: 0.25 | O75: 0.26 | P75: 0.26
B76: mid | I76: =+AVERAGE(I74:I75) -> 0.25 | J76: =+AVERAGE(J74:J75) -> 0.25 | K76: =+AVERAGE(K74:K75) -> 0.245 | L76: 0.24 | O76: =+AVERAGE(O74:O75) -> 0.25 | P76: =+AVERAGE(P74:P75) -> 0.25
B77: actual | I77: =-'FC - 3FS'!AP29/'FC - 3FS'!AP28 -> 0.22926862 | J77: =+I77 -> 0.22926862 | K77: =+J77 -> 0.22926862 | L77: =+K77 -> 0.22926862 | O77: =-'FC - 3FS'!AQ29/'FC - 3FS'!AQ28 -> 0.23552142 | P77: =+O77 -> 0.23552142
B78: delta | I78: =+I77-I76 -> -0.020731376 | J78: =+J77-J76 -> -0.020731376 | K78: =+K77-K76 -> -0.015731376 | L78: =+L77-L76 -> -0.010731376 | O78: =+O77-O76 -> -0.014478576 | P78: =+P77-P76 -> -0.014478576
B80: FWA Subscribers (in K)
B81: guidance | U81: 12000
B82: model | U82: ='IS Drivers'!AT20 -> 0
B83: delta
B85: Proceeds related to beneficial interests in securitization transactions
B86: low | I86: 3400 | J86: 3400 | K86: 3500 | L86: 3500 | S86: =+S21+S14-S6 -> 3000
B87: high | I87: 4000 | J87: 4000 | K87: 3900 | L87: 3700 | S87: =+S22+S15-S7 -> 4000
B88: mid | I88: =+AVERAGE(I86:I87) -> 3700 | J88: =+AVERAGE(J86:J87) -> 3700 | K88: =+AVERAGE(K86:K87) -> 3700 | L88: =+AVERAGE(L86:L87) -> 3600 | S88: =+S23+S16-S8 -> 3500
B89: actual | I89: ='FC - 3FS'!AP172 -> 3579 | J89: =+I89 -> 3579 | K89: =+J89 -> 3579 | L89: =+K89 -> 3579 | S89: ='FC - 3FS'!AS172 -> 0
B90: delta | I90: =+I89/I88-1 -> -0.032702703 | J90: =+J89/J88-1 -> -0.032702703 | K90: =+K89/K88-1 -> -0.032702703 | L90: =+L89/L88-1 -> -0.0058333333 | S90: =+S89/S88-1 -> -1
B92: Fiber net customer additions
B93: guidance
B94: model
B95: delta
B97: Core Adjusted EBITDA
B98: low
B99: high
B100: mid | Q100: =8500 -> 8500
B101: actual | Q101: ='FC - 3FS'!AD58 -> 8680
B102: delta | Q102: =+Q101/Q100-1 -> 0.021176471
B105: Cash Tax Benefit of $1.5B in 2026

Sheet Model Review
A1: hide
B3: Q3 Eearnings
C5: Guidance | D5: Curent | E5: Our Previous model
B6: 2025 fiber net add | C6: 130K | D6: ='IS Drivers'!AQ84 -> 133 | E6: N/A | F6: passings, cadence of build, seasonality to builds, 40% penetration,
B7: Postpaid net adds | C7: 7.2M - 7.4M | D7: ='IS Drivers'!AQ90 -> 7197.3362 | E7: 6407.76
B8: postpaid phone net adds | C8: 3.3M | D8: ='IS Drivers'!AQ62 -> 3330.6762 | E8: 3101
B9: 2025 postpaid ARPA | C9: 3.5% YoY | D9: ='IS Drivers'!AQ113 -> 0.028173334 | E9: 0.03045361
B10: Postpaid Phone ARPU | C10: 2% YoY (prev 1.5%) | D10: ='IS Drivers'!AQ118 -> 0.014113886 | E10: 0.024756635
B11: 2025 Core Adj. EBITDA | C11: 33.7B - 33.9B | D11: ='FC - 3FS'!AQ58 -> 33869.392 | E11: 33842.073
B12: Q4 D&A | C12: 3.7B | D12: ='FC - 3FS'!AE21 -> 3670.0321 | E12: 3256.6022
B13: Q4 Interest Expense | C13: 1B | D13: ='FC - 3FS'!AE25 -> -1014.6249 | E13: -877.41877
B14: 2025 Capex | C14: 10B | D14: ='BS Drivers'!AQ42 -> 10002.434 | E14: 9553.4839
B15: 2025 FCF | C15: 17.8 - 18B | D15: ='FC - 3FS'!AQ173 -> 17823.599 | E15: 17256.633

Sheet Impacts from USC
A1: hide
C2: Impacts of USC on TMUS
D4: 3Q25 | E4: 4Q25 | F4: 1Q26 | G4: 2Q26 | H4: 3Q26 | I4: 4Q26 | J4: 1Q27 | K4: 2Q27 | L4: 3Q27 | M4: 4Q27 | N4: 1Q28 | O4: 2Q28 | P4: 3Q28 | Q4: 4Q28 | R4: 1Q29 | S4: 2Q29 | T4: 3Q29 | U4: 4Q29 | V4: 1Q30 | W4: 2Q30 | X4: 3Q30 | Y4: 4Q30 | AA4: 2025 | AB4: 2026 | AC4: 2027 | AD4: 2028 | AE4: 2029 | AF4: 2030
C5: Additional Service revenue | D5: 400 | E5: =(D5*1.015) -> 406 | F5: =(E5*1.015) -> 412.09 | G5: =(F5*1.015) -> 418.27135 | H5: =(G5*1.015) -> 424.54542 | I5: =(H5*1.015) -> 430.9136 | J5: =(I5*1.015) -> 437.37731 | K5: =(J5*1.015) -> 443.93797 | L5: =(K5*1.015) -> 450.59703 | ... Y5: =(X5*1.015) -> 546.82313 | AA5: =SUM(D5:E5) -> 806 | AB5: =SUM(F5:I5) -> 1685.8204 | AC5: =SUM(J5:M5) -> 1789.2683 | AD5: =SUM(N5:Q5) -> 1899.0642 | AE5: =SUM(R5:U5) -> 2015.5975 | AF5: =SUM(V5:Y5) -> 2139.2817
C6: Operating expenses related to USC | D6: 275 | E6: =(D6/D5)*E5 -> 279.125 | F6: =(E6/E5)*F5 -> 283.31187 | G6: =(F6/F5)*G5 -> 287.56155 | H6: =(G6/G5)*H5 -> 291.87498 | I6: =(H6/H5)*I5 -> 296.2531 | J6: =(I6/I5)*J5 -> 300.6969 | K6: =(J6/J5)*K5 -> 305.20735 | L6: =(K6/K5)*L5 -> 309.78546 | ... Y6: =(X6/X5)*Y5 -> 375.9409 | AA6: =SUM(D6:E6) -> 554.125 | AB6: =SUM(F6:I6) -> 1159.0015 | AC6: =SUM(J6:M6) -> 1230.122 | AD6: =SUM(N6:Q6) -> 1305.6066 | AE6: =SUM(R6:U6) -> 1385.7233 | AF6: =SUM(V6:Y6) -> 1470.7562
C7: Cost to Achieve | D7: 100 | E7: 300 | F7: =((2600-400) *0.7)/4 -> 385 | G7: =((2600-400) *0.7)/4 -> 385 | H7: =((2600-400) *0.7)/4 -> 385 | I7: =((2600-400) *0.7)/4 -> 385 | J7: =((2600-400) *0.3)/2 -> 330 | K7: =((2600-400) *0.3)/2 -> 330 | L7: 0 | M7: 0 | N7: 0 | O7: 0 | P7: 0 | Q7: 0 | R7: 0 | S7: 0 | T7: 0 | U7: 0 | V7: 0 | W7: 0 | X7: 0 | Y7: 0 | AA7: =SUM(D7:E7) -> 400 | AB7: =SUM(F7:I7) -> 1540 | AC7: =SUM(J7:M7) -> 660 | AD7: =SUM(N7:Q7) -> 0 | AE7: =SUM(R7:U7) -> 0 | AF7: =SUM(V7:Y7) -> 0
C8: Depreciation & Ammortization | D8: 175 | E8: =(D8/D5)*E5 -> 177.625 | F8: =(E8/E5)*F5 -> 180.28937 | G8: =(F8/F5)*G5 -> 182.99372 | H8: =(G8/G5)*H5 -> 185.73862 | I8: =(H8/H5)*I5 -> 188.5247 | J8: =(I8/I5)*J5 -> 191.35257 | K8: =(J8/J5)*K5 -> 194.22286 | L8: =(K8/K5)*L5 -> 197.1362 | ... Y8: =(X8/X5)*Y5 -> 239.23512 | AA8: =SUM(D8:E8) -> 352.625 | AB8: =SUM(F8:I8) -> 737.54641 | AC8: =SUM(J8:M8) -> 782.80488 | AD8: =SUM(N8:Q8) -> 830.84057 | AE8: =SUM(R8:U8) -> 881.82389 | AF8: =SUM(V8:Y8) -> 935.93574
C9: Digital technology expense | D9: 470 | E9: 0 | F9: 0 | G9: 0 | H9: 0 | I9: 0 | J9: 0 | K9: 0 | L9: 0 | M9: 0 | N9: 0 | O9: 0 | P9: 0 | Q9: 0 | R9: 0 | S9: 0 | T9: 0 | U9: 0 | V9: 0 | W9: 0 | X9: 0 | Y9: 0 | AA9: =SUM(D9:E9) -> 470 | AB9: =SUM(F9:I9) -> 0 | AC9: =SUM(J9:M9) -> 0 | AD9: =SUM(N9:Q9) -> 0 | AE9: =SUM(R9:U9) -> 0 | AF9: =SUM(V9:Y9) -> 0
C10: Impacts to Operating income | D10: =D5-SUM(D6:D9) -> -620 | E10: =E5-SUM(E6:E9) -> -350.75 | F10: =F5-SUM(F6:F9) -> -436.51125 | G10: =G5-SUM(G6:G9) -> -437.28392 | H10: =H5-SUM(H6:H9) -> -438.06818 | I10: =I5-SUM(I6:I9) -> -438.8642 | J10: =J5-SUM(J6:J9) -> -384.67216 | K10: =K5-SUM(K6:K9) -> -385.49225 | ... Y10: =Y5-SUM(Y6:Y9) -> -68.352892 | AA10: =SUM(D10:E10) -> -970.75 | AB10: =SUM(F10:I10) -> -1750.7275 | AC10: =SUM(J10:M10) -> -883.65854 | AD10: =SUM(N10:Q10) -> -237.38302 | AE10: =SUM(R10:U10) -> -251.94968 | AF10: =SUM(V10:Y10) -> -267.41021
C13: Changes to Core adjusted EBITDA
C15: Operating income related to USC | D15: =D10 -> -620 | E15: =E10 -> -350.75 | F15: =F10 -> -436.51125 | G15: =G10 -> -437.28392 | H15: =H10 -> -438.06818 | I15: =I10 -> -438.8642 | J15: =J10 -> -384.67216 | K15: =K10 -> -385.49225 | ... Y15: =Y10 -> -68.352892
C16: =C8 -> Depreciation & Ammortization | D16: =D8 -> 175 | E16: =E8 -> 177.625 | F16: =F8 -> 180.28937 | G16: =G8 -> 182.99372 | H16: =H8 -> 185.73862 | I16: =I8 -> 188.5247 | J16: =J8 -> 191.35257 | ... Y16: =Y8 -> 239.23512
C17: =C7 -> Cost to Achieve | D17: =D7 -> 100 | E17: =E7 -> 300 | F17: =F7 -> 385 | G17: =G7 -> 385 | H17: =H7 -> 385 | I17: =I7 -> 385 | J17: =J7 -> 330 | ... Y17: =Y7 -> 0
C18: =C9 -> Digital technology expense | D18: =D9 -> 470 | E18: =E9 -> 0 | F18: =F9 -> 0 | G18: =G9 -> 0 | H18: =H9 -> 0 | I18: =I9 -> 0 | J18: =J9 -> 0 | ... Y18: =Y9 -> 0
C19: Impact to Core Adjusted EBITDA | D19: =D15+(SUM(D16:D18)) -> 125 | E19: =E15+(SUM(E16:E18)) -> 126.875 | F19: =F15+(SUM(F16:F18)) -> 128.77813 | G19: =G15+(SUM(G16:G18)) -> 130.7098 | H19: =H15+(SUM(H16:H18)) -> 132.67044 | I19: =I15+(SUM(I16:I18)) -> 134.6605 | J19: =J15+(SUM(J16:J18)) -> 136.68041 | K19: =K15+(SUM(K16:K18)) -> 138.73061 | ... Y19: =Y15+(SUM(Y16:Y18)) -> 170.88223
C21: Effective tax rate | D21: =-'BS Drivers'!AD124 -> 0.23072562 | E21: =-'BS Drivers'!AE124 -> 0.23072562 | F21: =-'BS Drivers'!AF124 -> 0.23072562 | G21: =-'BS Drivers'!AG124 -> 0.23072562 | H21: =-'BS Drivers'!AH124 -> 0.23072562 | I21: =-'BS Drivers'!AI124 -> 0.23072562 | J21: =I21 -> 0.23072562 | K21: =J21 -> 0.23072562 | L21: =K21 -> 0.23072562 | M21: =L21 -> 0.23072562 | N21: =M21 -> 0.23072562 | O21: =N21 -> 0.23072562 | P21: =O21 -> 0.23072562 | Q21: =P21 -> 0.23072562 | ... Y21: =X21 -> 0.23072562
C22: Impacts to Operating income | D22: =D10 -> -620 | E22: =E10 -> -350.75 | F22: =F10 -> -436.51125 | G22: =G10 -> -437.28392 | H22: =H10 -> -438.06818 | I22: =I10 -> -438.8642 | J22: =J10 -> -384.67216 | K22: =K10 -> -385.49225 | ... Y22: =Y10 -> -68.352892
C23: Post tax impact | D23: =D22*(1-D21) -> -476.95011 | E23: =E22*(1-E21) -> -269.82299 | F23: =F22*(1-F21) -> -335.79692 | G23: =G22*(1-G21) -> -336.39131 | H23: =H22*(1-H21) -> -336.99462 | I23: =I22*(1-I21) -> -337.60698 | J23: =J22*(1-J21) -> -295.91844 | K23: =K22*(1-K21) -> -296.54931 | ... Y23: =Y22*(1-Y21) -> -52.582128
C27: Cost synergies | D27: 1 | E27: 2 | F27: 3 | G27: 4 | H27: 5 | I27: 6 | J27: 7 | K27: 8
C28: OpEx | D28: =L28/9 -> 26.388889 | E28: =$D$28*E27 -> 52.777778 | F28: =$D$28*F27 -> 79.166667 | G28: =$D$28*G27 -> 105.55556 | H28: =$D$28*H27 -> 131.94444 | I28: =$D$28*I27 -> 158.33333 | J28: =$D$28*J27 -> 184.72222 | K28: =$D$28*K27 -> 211.11111 | L28: =950/4 -> 237.5 | M28: =950/4 -> 237.5 | N28: =950/4 -> 237.5 | O28: =950/4 -> 237.5 | P28: =950/4 -> 237.5 | Q28: =950/4 -> 237.5 | R28: =950/4 -> 237.5 | S28: =950/4 -> 237.5 | ... Y28: =950/4 -> 237.5 | AA28: =SUM(D28:E28) -> 79.166667 | AB28: =SUM(F28:I28) -> 475 | AC28: =SUM(J28:M28) -> 870.83333 | AD28: =SUM(N28:Q28) -> 950 | AE28: =SUM(R28:U28) -> 950 | AF28: =SUM(V28:Y28) -> 950
C29: CapEx | D29: =L29/9 -> 6.9444444 | E29: =$D$29*E27 -> 13.888889 | F29: =$D$29*F27 -> 20.833333 | G29: =$D$29*G27 -> 27.777778 | H29: =$D$29*H27 -> 34.722222 | I29: =$D$29*I27 -> 41.666667 | J29: =$D$29*J27 -> 48.611111 | K29: =$D$29*K27 -> 55.555556 | L29: =250/4 -> 62.5 | M29: =250/4 -> 62.5 | N29: =250/4 -> 62.5 | O29: =250/4 -> 62.5 | P29: =250/4 -> 62.5 | Q29: =250/4 -> 62.5 | R29: =250/4 -> 62.5 | S29: =250/4 -> 62.5 | ... Y29: =250/4 -> 62.5 | AA29: =SUM(D29:E29) -> 20.833333 | AB29: =SUM(F29:I29) -> 125 | AC29: =SUM(J29:M29) -> 229.16667 | AD29: =SUM(N29:Q29) -> 250 | AE29: =SUM(R29:U29) -> 250 | AF29: =SUM(V29:Y29) -> 250

Sheet Fiber Forecast
A1: hide
F4: in M
C5: Fiber Passings target by 2030 | F5: 15
C6: realisitc capabilities by 2030 | F6: 12
C7: Curent Fiber passings (from lumos and metronet | F7: 2.5
C8: Left to buildi | F8: =12-2.5 -> 9.5
C9: years to build | F9: 5
C10: implied builds per year | F10: =F8/F9 -> 1.9
P17: Max Penetration | Q17: 0.3
C18: Seasonality of builds | I18: Acceleration of builds | P18: Penetration ramp rate
C19: Q1 | D19: Q2 | E19: Q3 | F19: Q4 | I19: Year 1 | J19: Year 2 | K19: Year 3 | L19: Year 4 | M19: Year 5 | P19: =C19 -> Q1 | Q19: =D19 -> Q2 | R19: =E19 -> Q3 | S19: =F19 -> Q4 | T19: Q5 | U19: Q6 | V19: Q7 | W19: Q8 | X19: Q9 | Y19: Q10
C20: 0.15 | D20: 0.35 | E20: 0.3 | F20: 0.2 | I20: 0.95 | J20: 1.425 | K20: 1.9 | L20: 2.375 | M20: 2.85 | P20: 0.1 | Q20: 0.15 | R20: 0.3 | S20: 0.45 | T20: 0.55 | U20: 0.65 | V20: 0.8 | W20: 0.9 | X20: 0.96 | Y20: 1
O21: Subscriber penetration | P21: =P20*$Q$17 -> 0.03 | Q21: =Q20*$Q$17 -> 0.045 | R21: =R20*$Q$17 -> 0.09 | S21: =S20*$Q$17 -> 0.135 | T21: =T20*$Q$17 -> 0.165 | U21: =U20*$Q$17 -> 0.195 | V21: =V20*$Q$17 -> 0.24 | W21: =W20*$Q$17 -> 0.27 | ... Y21: =Y20*$Q$17 -> 0.3
C24: 1Q26 | D24: 2Q26 | E24: 3Q26 | F24: 4Q26 | G24: 1Q27 | H24: 2Q27 | I24: 3Q27 | J24: 4Q27 | K24: 1Q28 | L24: 2Q28 | M24: 3Q28 | N24: 4Q28 | O24: 1Q29 | P24: 2Q29 | Q24: 3Q29 | R24: 4Q29 | S24: 1Q30 | T24: 2Q30 | U24: 3Q30 | V24: 4Q30
C25: =C20*$I$20 -> 0.1425 | D25: =D20*$I$20 -> 0.3325 | E25: =E20*$I$20 -> 0.285 | F25: =F20*$I$20 -> 0.19 | G25: =C20*$J$20 -> 0.21375 | H25: =D20*$J$20 -> 0.49875 | I25: =E20*$J$20 -> 0.4275 | J25: =F20*$J$20 -> 0.285 | K25: =C20*$K$20 -> 0.285 | L25: =D20*$K$20 -> 0.665 | M25: =E20*$K$20 -> 0.57 | N25: =F20*$K$20 -> 0.38 | O25: =C20*$L$20 -> 0.35625 | P25: =D20*$L$20 -> 0.83125 | Q25: =E20*$L$20 -> 0.7125 | R25: =F20*$L$20 -> 0.475 | S25: =C20*$M$20 -> 0.4275 | T25: =D20*$M$20 -> 0.9975 | U25: =E20*$M$20 -> 0.855 | V25: =F20*$M$20 -> 0.57
D32: Timing
C33: Tranche | D33: =C24 -> 1Q26 | E33: =D24 -> 2Q26 | F33: =E24 -> 3Q26 | G33: =F24 -> 4Q26 | H33: =G24 -> 1Q27 | I33: =H24 -> 2Q27 | J33: =I24 -> 3Q27 | K33: =J24 -> 4Q27 | ... W33: =V24 -> 4Q30
C34: 1Q26 | D34: =$C$25*P21 -> 0.004275 | E34: =$C$25*Q21 -> 0.0064125 | F34: =$C$25*R21 -> 0.012825 | G34: =$C$25*S21 -> 0.0192375 | H34: =$C$25*T21 -> 0.0235125 | I34: =$C$25*U21 -> 0.0277875 | J34: =$C$25*V21 -> 0.0342 | K34: =$C$25*W21 -> 0.038475 | L34: =$C$25*X21 -> 0.04104 | M34: =$C$25*$Y$21 -> 0.04275 | N34: =$C$25*$Y$21 -> 0.04275 | O34: =$C$25*$Y$21 -> 0.04275 | P34: =$C$25*$Y$21 -> 0.04275 | Q34: =$C$25*$Y$21 -> 0.04275 | R34: =$C$25*$Y$21 -> 0.04275 | S34: =$C$25*$Y$21 -> 0.04275 | T34: =$C$25*$Y$21 -> 0.04275 | ... W34: =$C$25*$Y$21 -> 0.04275
C35: 2Q26 | E35: =$D$25*P21 -> 0.009975 | F35: =$D$25*Q21 -> 0.0149625 | G35: =$D$25*R21 -> 0.029925 | H35: =$D$25*S21 -> 0.0448875 | I35: =$D$25*T21 -> 0.0548625 | J35: =$D$25*U21 -> 0.0648375 | K35: =$D$25*V21 -> 0.0798 | L35: =$D$25*W21 -> 0.089775 | M35: =$D$25*X21 -> 0.09576 | N35: =$D$25*$Y$21 -> 0.09975 | O35: =$D$25*$Y$21 -> 0.09975 | P35: =$D$25*$Y$21 -> 0.09975 | Q35: =$D$25*$Y$21 -> 0.09975 | R35: =$D$25*$Y$21 -> 0.09975 | S35: =$D$25*$Y$21 -> 0.09975 | T35: =$D$25*$Y$21 -> 0.09975 | U35: =$D$25*$Y$21 -> 0.09975 | ... W35: =$D$25*$Y$21 -> 0.09975
C36: 3Q26 | F36: =$E$25*P21 -> 0.00855 | G36: =$E$25*Q21 -> 0.012825 | H36: =$E$25*R21 -> 0.02565 | I36: =$E$25*S21 -> 0.038475 | J36: =$E$25*T21 -> 0.047025 | K36: =$E$25*U21 -> 0.055575 | L36: =$E$25*V21 -> 0.0684 | M36: =$E$25*W21 -> 0.07695 | N36: =$E$25*X21 -> 0.08208 | O36: =$E$25*$Y$21 -> 0.0855 | P36: =$E$25*$Y$21 -> 0.0855 | Q36: =$E$25*$Y$21 -> 0.0855 | R36: =$E$25*$Y$21 -> 0.0855 | S36: =$E$25*$Y$21 -> 0.0855 | T36: =$E$25*$Y$21 -> 0.0855 | U36: =$E$25*$Y$21 -> 0.0855 | V36: =$E$25*$Y$21 -> 0.0855 | W36: =$E$25*$Y$21 -> 0.0855
C37: 4Q26 | G37: =$F$25*P21 -> 0.0057 | H37: =$F$25*Q21 -> 0.00855 | I37: =$F$25*R21 -> 0.0171 | J37: =$F$25*S21 -> 0.02565 | K37: =$F$25*T21 -> 0.03135 | L37: =$F$25*U21 -> 0.03705 | M37: =$F$25*V21 -> 0.0456 | N37: =$F$25*W21 -> 0.0513 | O37: =$F$25*X21 -> 0.05472 | P37: =$F$25*$Y$21 -> 0.057 | Q37: =$F$25*$Y$21 -> 0.057 | R37: =$F$25*$Y$21 -> 0.057 | S37: =$F$25*$Y$21 -> 0.057 | T37: =$F$25*$Y$21 -> 0.057 | U37: =$F$25*$Y$21 -> 0.057 | V37: =$F$25*$Y$21 -> 0.057 | W37: =$F$25*$Y$21 -> 0.057
C38: 1Q27 | H38: =$G$25*P21 -> 0.0064125 | I38: =$G$25*Q21 -> 0.00961875 | J38: =$G$25*R21 -> 0.0192375 | K38: =$G$25*S21 -> 0.02885625 | L38: =$G$25*T21 -> 0.03526875 | M38: =$G$25*U21 -> 0.04168125 | N38: =$G$25*V21 -> 0.0513 | O38: =$G$25*W21 -> 0.0577125 | P38: =$G$25*X21 -> 0.06156 | Q38: =$G$25*$Y$21 -> 0.064125 | R38: =$G$25*$Y$21 -> 0.064125 | S38: =$G$25*$Y$21 -> 0.064125 | T38: =$G$25*$Y$21 -> 0.064125 | U38: =$G$25*$Y$21 -> 0.064125 | V38: =$G$25*$Y$21 -> 0.064125 | W38: =$G$25*$Y$21 -> 0.064125
C39: 2Q27 | I39: =$H$25*P21 -> 0.0149625 | J39: =$H$25*Q21 -> 0.02244375 | K39: =$H$25*R21 -> 0.0448875 | L39: =$H$25*S21 -> 0.06733125 | M39: =$H$25*T21 -> 0.08229375 | N39: =$H$25*U21 -> 0.09725625 | O39: =$H$25*V21 -> 0.1197 | P39: =$H$25*W21 -> 0.1346625 | Q39: =$H$25*X21 -> 0.14364 | R39: =$H$25*$Y$21 -> 0.149625 | S39: =$H$25*$Y$21 -> 0.149625 | T39: =$H$25*$Y$21 -> 0.149625 | U39: =$H$25*$Y$21 -> 0.149625 | V39: =$H$25*$Y$21 -> 0.149625 | W39: =$H$25*$Y$21 -> 0.149625
C40: 3Q27 | J40: =$I$25*P21 -> 0.012825 | K40: =$I$25*Q21 -> 0.0192375 | L40: =$I$25*R21 -> 0.038475 | M40: =$I$25*S21 -> 0.0577125 | N40: =$I$25*T21 -> 0.0705375 | O40: =$I$25*U21 -> 0.0833625 | P40: =$I$25*V21 -> 0.1026 | Q40: =$I$25*W21 -> 0.115425 | R40: =$I$25*X21 -> 0.12312 | S40: =$I$25*$Y$21 -> 0.12825 | T40: =$I$25*$Y$21 -> 0.12825 | U40: =$I$25*$Y$21 -> 0.12825 | V40: =$I$25*$Y$21 -> 0.12825 | W40: =$I$25*$Y$21 -> 0.12825
C41: 4Q27 | K41: =$J$25*P21 -> 0.00855 | L41: =$J$25*Q21 -> 0.012825 | M41: =$J$25*R21 -> 0.02565 | N41: =$J$25*S21 -> 0.038475 | O41: =$J$25*T21 -> 0.047025 | P41: =$J$25*U21 -> 0.055575 | Q41: =$J$25*V21 -> 0.0684 | R41: =$J$25*W21 -> 0.07695 | S41: =$J$25*X21 -> 0.08208 | T41: =$J$25*$Y$21 -> 0.0855 | U41: =$J$25*$Y$21 -> 0.0855 | V41: =$J$25*$Y$21 -> 0.0855 | W41: =$J$25*$Y$21 -> 0.0855
C42: 1Q28 | L42: =$K$25*P21 -> 0.00855 | M42: =$K$25*Q21 -> 0.012825 | N42: =$K$25*R21 -> 0.02565 | O42: =$K$25*S21 -> 0.038475 | P42: =$K$25*T21 -> 0.047025 | Q42: =$K$25*U21 -> 0.055575 | R42: =$K$25*V21 -> 0.0684 | S42: =$K$25*W21 -> 0.07695 | T42: =$K$25*X21 -> 0.08208 | U42: =$K$25*$Y$21 -> 0.0855 | V42: =$K$25*$Y$21 -> 0.0855 | W42: =$K$25*$Y$21 -> 0.0855
C43: 2Q28 | M43: =$M$25*P21 -> 0.0171 | N43: =$M$25*Q21 -> 0.02565 | O43: =$M$25*R21 -> 0.0513 | P43: =$M$25*S21 -> 0.07695 | Q43: =$M$25*T21 -> 0.09405 | R43: =$M$25*U21 -> 0.11115 | S43: =$M$25*V21 -> 0.1368 | T43: =$M$25*W21 -> 0.1539 | U43: =$M$25*X21 -> 0.16416 | V43: =$M$25*$Y$21 -> 0.171 | W43: =$M$25*$Y$21 -> 0.171
C44: 3Q28 | N44: =$M$25*P21 -> 0.0171 | O44: =$M$25*Q21 -> 0.02565 | P44: =$M$25*R21 -> 0.0513 | Q44: =$M$25*S21 -> 0.07695 | R44: =$M$25*T21 -> 0.09405 | S44: =$M$25*U21 -> 0.11115 | T44: =$M$25*V21 -> 0.1368 | U44: =$M$25*W21 -> 0.1539 | V44: =$M$25*X21 -> 0.16416 | W44: =$M$25*$Y$21 -> 0.171
C45: 4Q28 | O45: =$N$25*P21 -> 0.0114 | P45: =$N$25*Q21 -> 0.0171 | Q45: =$N$25*R21 -> 0.0342 | R45: =$N$25*S21 -> 0.0513 | S45: =$N$25*T21 -> 0.0627 | T45: =$N$25*U21 -> 0.0741 | U45: =$N$25*V21 -> 0.0912 | V45: =$N$25*W21 -> 0.1026 | W45: =$N$25*X21 -> 0.10944
C46: 1Q29 | P46: =$O$25*P21 -> 0.0106875 | Q46: =$O$25*Q21 -> 0.01603125 | R46: =$O$25*R21 -> 0.0320625 | S46: =$O$25*S21 -> 0.04809375 | T46: =$O$25*T21 -> 0.05878125 | U46: =$O$25*U21 -> 0.06946875 | V46: =$O$25*V21 -> 0.0855 | W46: =$O$25*W21 -> 0.0961875
C47: 2Q29 | Q47: =$P$25*P21 -> 0.0249375 | R47: =$P$25*Q21 -> 0.03740625 | S47: =$P$25*R21 -> 0.0748125 | T47: =$P$25*S21 -> 0.11221875 | U47: =$P$25*T21 -> 0.13715625 | V47: =$P$25*U21 -> 0.16209375 | W47: =$P$25*V21 -> 0.1995
C48: 3Q29 | R48: =$Q$25*P21 -> 0.021375 | S48: =$Q$25*Q21 -> 0.0320625 | T48: =$Q$25*R21 -> 0.064125 | U48: =$Q$25*S21 -> 0.0961875 | V48: =$Q$25*T21 -> 0.1175625 | W48: =$Q$25*U21 -> 0.1389375
C49: 4Q29 | S49: =$R$25*P21 -> 0.01425 | T49: =$R$25*Q21 -> 0.021375 | U49: =$R$25*R21 -> 0.04275 | V49: =$R$25*S21 -> 0.064125 | W49: =$R$25*T21 -> 0.078375
C50: 1Q30 | T50: =$S$25*P21 -> 0.012825 | U50: =$S$25*Q21 -> 0.0192375 | V50: =$S$25*R21 -> 0.038475 | W50: =$S$25*S21 -> 0.0577125
C51: 2Q30 | U51: =$T$25*P21 -> 0.029925 | V51: =$T$25*Q21 -> 0.0448875 | W51: =$T$25*R21 -> 0.089775
C52: 3Q30 | V52: =$U$25*P21 -> 0.02565 | W52: =$U$25*Q21 -> 0.038475
C53: 4Q30 | W53: =V25*P21 -> 0.0171
C54: Subs | D54: =SUM(D34:D53) -> 0.004275 | E54: =SUM(E34:E53) -> 0.0163875 | F54: =SUM(F34:F53) -> 0.0363375 | G54: =SUM(G34:G53) -> 0.0676875 | H54: =SUM(H34:H53) -> 0.1090125 | I54: =SUM(I34:I53) -> 0.16280625 | J54: =SUM(J34:J53) -> 0.22621875 | K54: =SUM(K34:K53) -> 0.30673125 | ... W54: =SUM(W34:W53) -> 1.9655025
C55: Net Adds | D55: =D54 -> 0.004275 | E55: =E54-D54 -> 0.0121125 | F55: =F54-E54 -> 0.01995 | G55: =G54-F54 -> 0.03135 | H55: =H54-G54 -> 0.041325 | I55: =I54-H54 -> 0.05379375 | J55: =J54-I54 -> 0.0634125 | K55: =K54-J54 -> 0.0805125 | L55: =L54-K54 -> 0.09198375 | ... W55: =W54-V54 -> 0.19144875
C56: Net adds thousands | D56: =D55*1000 -> 4.275 | E56: =E55*1000 -> 12.1125 | F56: =F55*1000 -> 19.95 | G56: =G55*1000 -> 31.35 | H56: =H55*1000 -> 41.325 | I56: =I55*1000 -> 53.79375 | J56: =J55*1000 -> 63.4125 | K56: =K55*1000 -> 80.5125 | ... W56: =W55*1000 -> 191.44875
J62: 2027 | K62: =J62+1 -> 2028 | L62: =K62+1 -> 2029 | M62: =L62+1 -> 2030
J63: =SUM(H56:K56) -> 239.04375 | K63: =SUM(L56:O56) -> 410.61375 | L63: =SUM(P56:S56) -> 548.55375 | M63: =SUM(T56:W56) -> 699.60375

Sheet FC - 3FS
D1: Pre Merger Pro Forma
D2: 1 | E2: 2 | F2: 3 | G2: 4 | H2: 1 | I2: 2 | J2: 3 | K2: 4 | L2: 1 | M2: 2 | N2: 3 | O2: 4 | P2: 1 | Q2: 2 | R2: 3 | S2: 4 | T2: =+P2 -> 1 | U2: =+Q2 -> 2 | V2: =+R2 -> 3 | W2: =+S2 -> 4 | X2: =+T2 -> 1 | Y2: =+U2 -> 2 | Z2: =+V2 -> 3 | AA2: =+W2 -> 4 | ... AI2: =+AE2 -> 4
D3: 2019 | E3: 2019 | F3: 2019 | G3: 2019 | H3: 2020 | I3: 2020 | J3: 2020 | K3: 2020 | L3: 2021 | M3: 2021 | N3: 2021 | O3: 2021 | P3: 2022 | Q3: 2022 | R3: 2022 | S3: 2022 | T3: =+P3+1 -> 2023 | U3: =+Q3+1 -> 2023 | V3: =+R3+1 -> 2023 | W3: =+S3+1 -> 2023 | X3: =+T3+1 -> 2024 | Y3: =+U3+1 -> 2024 | Z3: =+V3+1 -> 2024 | AA3: =+W3+1 -> 2024 | ... AI3: =+AE3+1 -> 2026 | AK3: =+AK4 -> 2019 | AL3: =+AL4 -> 2020 | AM3: =+AM4 -> 2021 | AN3: =+AN4 -> 2022 | AO3: =+AO4 -> 2023 | AP3: =+AP4 -> 2024 | AQ3: =+AP3+1 -> 2025 | AR3: =+AQ3+1 -> 2026 | AS3: =+AR3+1 -> 2027
B4: in millions dollars | D4: 1Q19 | E4: 2Q19 | F4: 3Q19 | G4: 4Q19 | H4: 1Q20 | I4: 2Q20 | J4: 3Q20 | K4: 4Q20 | L4: 1Q21 | M4: 2Q21 | N4: 3Q21 | O4: 4Q21 | P4: 1Q22 | Q4: 2Q22 | R4: 3Q22 | S4: 4Q22 | T4: 1Q23 | U4: 2Q23 | V4: 3Q23 | W4: 4Q23 | X4: 1Q24 | Y4: 2Q24 | Z4: 3Q24 | AA4: 4Q24 | AB4: 1Q25 | AC4: 2Q25 | AD4: 3Q25 | AE4: =+_xlfn.CONCAT(AE2,"Q",RIGHT(AE3,2)) -> 4Q25 | AF4: =+_xlfn.CONCAT(AF2,"Q",RIGHT(AF3,2)) -> 1Q26 | AG4: =+_xlfn.CONCAT(AG2,"Q",RIGHT(AG3,2)) -> 2Q26 | AH4: =+_xlfn.CONCAT(AH2,"Q",RIGHT(AH3,2)) -> 3Q26 | AI4: =+_xlfn.CONCAT(AI2,"Q",RIGHT(AI3,2)) -> 4Q26 | AK4: 2019 | AL4: =+AK4+1 -> 2020 | AM4: =+AL4+1 -> 2021 | AN4: =+AM4+1 -> 2022 | AO4: =+AN4+1 -> 2023 | AP4: =+AO4+1 -> 2024 | AQ4: =+_xlfn.CONCAT(AQ3,"E") -> 2025E | AR4: =+_xlfn.CONCAT(AR3,"E") -> 2026E | AS4: =+_xlfn.CONCAT(AS3,"E") -> 2027E
A5: x | B5: Income Statement
B6: Postpaid revenues | D6: ='3FS'!K6 -> 0 | E6: ='3FS'!L6 -> 0 | F6: ='3FS'!M6 -> 0 | G6: ='3FS'!N6 -> 0 | H6: ='3FS'!O6 -> 0 | I6: ='3FS'!P6 -> 9959 | J6: ='3FS'!Q6 -> 10209 | K6: ='3FS'!R6 -> 10251 | ... AD6: ='3FS'!AK6 -> 14882 | AE6: =+'IS Drivers'!AE9 -> 15201.075 | AF6: =+'IS Drivers'!AF9 -> 15280.936 | AG6: =+'IS Drivers'!AG9 -> 15801.255 | AH6: =+'IS Drivers'!AH9 -> 16201.782 | AI6: =+'IS Drivers'!AI9 -> 16299.262 | AK6: ='3FS'!D6 -> 22673 | AL6: ='3FS'!E6 -> 36306 | AM6: ='3FS'!F6 -> 42562 | AN6: ='3FS'!G6 -> 45919 | AO6: ='3FS'!H6 -> 48692 | AP6: ='3FS'!I6 -> 52340 | AQ6: =SUMIFS($F6:$AI6,$F$3:$AI$3,AQ$3) -> 57755.075 | AR6: =SUMIFS($F6:$AI6,$F$3:$AI$3,AR$3) -> 63583.234 | AS6: =+'IS Drivers'!AS9 -> 68048.486
B7: Prepaid revenues | D7: ='3FS'!K7 -> 0 | E7: ='3FS'!L7 -> 0 | F7: ='3FS'!M7 -> 0 | G7: ='3FS'!N7 -> 0 | H7: ='3FS'!O7 -> 0 | I7: ='3FS'!P7 -> 2311 | J7: ='3FS'!Q7 -> 2383 | K7: ='3FS'!R7 -> 2354 | ... AD7: ='3FS'!AK7 -> 2625 | AE7: =+'IS Drivers'!AE11 -> 2603.7494 | AF7: =+'IS Drivers'!AF11 -> 2557.3003 | AG7: =+'IS Drivers'!AG11 -> 2565.5624 | AH7: =+'IS Drivers'!AH11 -> 2549.753 | AI7: =+'IS Drivers'!AI11 -> 2556.1863 | AK7: ='3FS'!D7 -> 9543 | AL7: ='3FS'!E7 -> 9421 | AM7: ='3FS'!F7 -> 9733 | AN7: ='3FS'!G7 -> 9857 | AO7: ='3FS'!H7 -> 9767 | AP7: ='3FS'!I7 -> 10399 | AQ7: =SUMIFS($F7:$AI7,$F$3:$AI$3,AQ$3) -> 10514.749 | AR7: =SUMIFS($F7:$AI7,$F$3:$AI$3,AR$3) -> 10228.802 | AS7: =+'IS Drivers'!AS11 -> 9933.2181
B8: Wholesale and other service revenues | D8: =SUM(D9:D10) -> 0 | E8: =SUM(E9:E10) -> 0 | F8: =SUM(F9:F10) -> 0 | G8: =SUM(G9:G10) -> 0 | H8: =SUM(H9:H10) -> 0 | I8: =SUM(I9:I10) -> 960 | J8: =SUM(J9:J10) -> 1547 | K8: =SUM(K9:K10) -> 1575 | ... O8: =SUM(O9:O10) -> 1526 | P8: ='3FS'!W8 -> 1472 | Q8: ='3FS'!X8 -> 1402 | R8: ='3FS'!Y8 -> 1329 | S8: ='3FS'!Z8 -> 1344 | T8: ='3FS'!AA8 -> 1267 | U8: ='3FS'!AB8 -> 1224 | V8: ='3FS'!AC8 -> 1153 | W8: ='3FS'!AD8 -> 1138 | ... AD8: ='3FS'!AK8 -> 734 | AE8: =+'IS Drivers'!AE12 -> 752.76 | AF8: =+'IS Drivers'!AF12 -> 694.88 | AG8: =+'IS Drivers'!AG12 -> 731.34 | AH8: =+'IS Drivers'!AH12 -> 756.02 | AI8: =+'IS Drivers'!AI12 -> 782.8704 | AK8: =SUM(AK9:AK10) -> 2284 | AL8: =SUM(AL9:AL10) -> 4668 | AM8: =SUM(AM9:AM10) -> 6074 | AN8: =SUMIFS($F8:$AI8,$F$3:$AI$3,AN$3) -> 5547 | AO8: =SUMIFS($F8:$AI8,$F$3:$AI$3,AO$3) -> 4782 | AP8: =SUMIFS($F8:$AI8,$F$3:$AI$3,AP$3) -> 3439 | AQ8: =SUMIFS($F8:$AI8,$F$3:$AI$3,AQ$3) -> 2891.76 | AR8: =SUMIFS($F8:$AI8,$F$3:$AI$3,AR$3) -> 2965.1104 | AS8: =+'IS Drivers'!AS12 -> 3069.9725
B9: Wholesale revenues | D9: ='3FS'!K9 -> 0 | E9: ='3FS'!L9 -> 0 | F9: ='3FS'!M9 -> 0 | G9: ='3FS'!N9 -> 0 | H9: ='3FS'!O9 -> 0 | I9: ='3FS'!P9 -> 408 | J9: ='3FS'!Q9 -> 930 | K9: ='3FS'!R9 -> 927 | ... AD9: ='3FS'!AK9 -> 0 | AK9: ='3FS'!D9 -> 1279 | AL9: ='3FS'!E9 -> 2590 | AM9: ='3FS'!F9 -> 3751 | AN9: ='3FS'!G9 -> 0 | AO9: ='3FS'!H9 -> 0 | AP9: ='3FS'!I9 -> 0
B10: Other service revenues | D10: ='3FS'!K10 -> 0 | E10: ='3FS'!L10 -> 0 | F10: ='3FS'!M10 -> 0 | G10: ='3FS'!N10 -> 0 | H10: ='3FS'!O10 -> 0 | I10: ='3FS'!P10 -> 552 | J10: ='3FS'!Q10 -> 617 | K10: ='3FS'!R10 -> 648 | ... AD10: ='3FS'!AK10 -> 0 | AK10: ='3FS'!D10 -> 1005 | AL10: ='3FS'!E10 -> 2078 | AM10: ='3FS'!F10 -> 2323 | AN10: ='3FS'!G10 -> 0 | AO10: ='3FS'!H10 -> 0 | AP10: ='3FS'!I10 -> 0
B11: Total service revenues | D11: ='3FS'!K11 -> 12901 | E11: ='3FS'!L11 -> 13008 | F11: ='3FS'!M11 -> 12910 | G11: ='3FS'!N11 -> 13208 | H11: ='3FS'!O11 -> 13197 | I11: =+SUM(I6:I8) -> 13230 | J11: =+SUM(J6:J8) -> 14139 | K11: =+SUM(K6:K8) -> 14180 | L11: =+SUM(L6:L8) -> 14192 | M11: =+SUM(M6:M8) -> 14492 | N11: =+SUM(N6:N8) -> 14722 | O11: =+SUM(O6:O8) -> 14963 | P11: =+SUM(P6:P8) -> 15128 | ... AD11: =+SUM(AD6:AD8) -> 18241 | AE11: =+SUM(AE6:AE10) -> 18557.584 | AF11: =+SUM(AF6:AF10) -> 18533.116 | AG11: =+SUM(AG6:AG10) -> 19098.157 | AH11: =+SUM(AH6:AH10) -> 19507.555 | AI11: =+SUM(AI6:AI10) -> 19638.318 | AK11: =+SUM(AK6:AK8) -> 34500 | AL11: =+SUM(AL6:AL8) -> 50395 | AM11: =+SUM(AM6:AM8) -> 58369 | AN11: =+SUM(AN6:AN8) -> 61323 | AO11: =+SUM(AO6:AO8) -> 63241 | AP11: =+SUM(AP6:AP8) -> 66178 | AQ11: =+SUM(AQ6:AQ10) -> 71161.584 | AR11: =+SUM(AR6:AR10) -> 76777.146 | AS11: =+SUM(AS6:AS10) -> 81051.676
B12: Equipment revenues | D12: ='3FS'!K12 -> 4369 | E12: ='3FS'!L12 -> 4099 | F12: ='3FS'!M12 -> 3974 | G12: ='3FS'!N12 -> 4704 | H12: ='3FS'!O12 -> 3876 | I12: ='3FS'!P12 -> 4269 | J12: ='3FS'!Q12 -> 4953 | K12: ='3FS'!R12 -> 5973 | ... AD12: ='3FS'!AK12 -> 3465 | AE12: =+'IS Drivers'!AE13 -> 5051.1421 | AF12: =+'IS Drivers'!AF13 -> 3756.7179 | AG12: =+'IS Drivers'!AG13 -> 3782.0806 | AH12: =+'IS Drivers'!AH13 -> 3696.9684 | AI12: =+'IS Drivers'!AI13 -> 5317.7985 | AK12: ='3FS'!D12 -> 9840 | AL12: ='3FS'!E12 -> 17312 | AM12: ='3FS'!F12 -> 20727 | AN12: ='3FS'!G12 -> 17130 | AO12: ='3FS'!H12 -> 14138 | AP12: ='3FS'!I12 -> 14263 | AQ12: =SUMIFS($F12:$AI12,$F$3:$AI$3,AQ$3) -> 15659.142 | AR12: =SUMIFS($F12:$AI12,$F$3:$AI$3,AR$3) -> 16553.565 | AS12: =+'IS Drivers'!AS13 -> 17077.991
B13: Other revenues | D13: ='3FS'!K13 -> 349 | E13: ='3FS'!L13 -> 353 | F13: ='3FS'!M13 -> 359 | G13: ='3FS'!N13 -> 373 | H13: ='3FS'!O13 -> 335 | I13: ='3FS'!P13 -> 172 | J13: ='3FS'!Q13 -> 180 | K13: ='3FS'!R13 -> 188 | ... AD13: ='3FS'!AK13 -> 251 | AE13: =+'IS Drivers'!AE16 -> 263.76916 | AF13: =+'IS Drivers'!AF16 -> 260.45058 | AG13: =+'IS Drivers'!AG16 -> 280.63226 | AH13: =+'IS Drivers'!AH16 -> 267.82291 | AI13: =+'IS Drivers'!AI16 -> 277.70492 | AK13: ='3FS'!D13 -> 658 | AL13: ='3FS'!E13 -> 690 | AM13: ='3FS'!F13 -> 1022 | AN13: ='3FS'!G13 -> 1118 | AO13: ='3FS'!H13 -> 1179 | AP13: ='3FS'!I13 -> 959 | AQ13: =SUMIFS($F13:$AI13,$F$3:$AI$3,AQ$3) -> 1026.7692 | AR13: =SUMIFS($F13:$AI13,$F$3:$AI$3,AR$3) -> 1086.6107 | AS13: =+'IS Drivers'!AS16 -> 1122.1196
B14: Total revenues | D14: =+D13+D12+D11 -> 17619 | E14: =+E13+E12+E11 -> 17460 | F14: =+F13+F12+F11 -> 17243 | G14: =+G13+G12+G11 -> 18285 | H14: =+H13+H12+H11 -> 17408 | I14: =+I13+I12+I11 -> 17671 | J14: =+J13+J12+J11 -> 19272 | K14: =+K13+K12+K11 -> 20341 | ... AI14: =+AI13+AI12+AI11 -> 25233.822 | AK14: =+AK13+AK12+AK11 -> 44998 | AL14: =+AL13+AL12+AL11 -> 68397 | AM14: =+AM13+AM12+AM11 -> 80118 | AN14: =+AN13+AN12+AN11 -> 79571 | AO14: =+AO13+AO12+AO11 -> 78558 | AP14: =+AP13+AP12+AP11 -> 81400 | AQ14: =+AQ13+AQ12+AQ11 -> 87847.495 | AR14: =+AR13+AR12+AR11 -> 94417.322 | AS14: =+AS13+AS12+AS11 -> 99251.787
B15: Operating expenses
B16: Cost of services, exclusive of D&A | D16: ='3FS'!K16 -> 3342 | E16: ='3FS'!L16 -> 3219 | F16: ='3FS'!M16 -> 3366 | G16: ='3FS'!N16 -> 3297 | H16: ='3FS'!O16 -> 3200 | I16: ='3FS'!P16 -> 3098 | J16: ='3FS'!Q16 -> 3314 | K16: ='3FS'!R16 -> 3827 | ... AD16: ='3FS'!AK16 -> 2873 | AE16: =+'IS Drivers'!AE202 -> 2938.0707 | AF16: =+'IS Drivers'!AF202 -> 2830.694 | AG16: =+'IS Drivers'!AG202 -> 2956.5695 | AH16: =+'IS Drivers'!AH202 -> 3052.9778 | AI16: =+'IS Drivers'!AI202 -> 3089.5363 | AK16: ='3FS'!D16 -> 6622 | AL16: ='3FS'!E16 -> 11878 | AM16: ='3FS'!F16 -> 13934 | AN16: ='3FS'!G16 -> 14666 | AO16: ='3FS'!H16 -> 11655 | AP16: ='3FS'!I16 -> 10771 | AQ16: =SUMIFS($F16:$AI16,$F$3:$AI$3,AQ$3) -> 11130.071 | AR16: =SUMIFS($F16:$AI16,$F$3:$AI$3,AR$3) -> 11929.777 | AS16: =+'IS Drivers'!AS202 -> 12593.962
B17: Cost of equipment sales, exclusive of D&A | D17: ='3FS'!K17 -> 3624 | E17: ='3FS'!L17 -> 3280 | F17: ='3FS'!M17 -> 3330 | G17: ='3FS'!N17 -> 4341 | H17: ='3FS'!O17 -> 3268 | I17: ='3FS'!P17 -> 3667 | J17: ='3FS'!Q17 -> 4367 | K17: ='3FS'!R17 -> 5825 | ... AD17: ='3FS'!AK17 -> 4853 | AE17: =+'IS Drivers'!AE207 -> 6907.6944 | AF17: =+'IS Drivers'!AF207 -> 4862.4198 | AG17: =+'IS Drivers'!AG207 -> 5127.3165 | AH17: =+'IS Drivers'!AH207 -> 5178.2652 | AI17: =+'IS Drivers'!AI207 -> 7272.6497 | AK17: ='3FS'!D17 -> 11899 | AL17: ='3FS'!E17 -> 16388 | AM17: ='3FS'!F17 -> 22671 | AN17: ='3FS'!G17 -> 21540 | AO17: ='3FS'!H17 -> 18533 | AP17: ='3FS'!I17 -> 18882 | AQ17: =SUMIFS($F17:$AI17,$F$3:$AI$3,AQ$3) -> 21217.694 | AR17: =SUMIFS($F17:$AI17,$F$3:$AI$3,AR$3) -> 22440.651 | AS17: =+'IS Drivers'!AS207 -> 23173.982
B18: Selling, general and administrative | D18: ='3FS'!K18 -> 5010 | E18: ='3FS'!L18 -> 5177 | F18: ='3FS'!M18 -> 4979 | G18: ='3FS'!N18 -> 5028 | H18: ='3FS'!O18 -> 5280 | I18: ='3FS'!P18 -> 5604 | J18: ='3FS'!Q18 -> 4876 | K18: ='3FS'!R18 -> 4758 | ... AD18: ='3FS'!AK18 -> 6015 | AE18: =+'IS Drivers'!AE212 -> 6320.3537 | AF18: =+'IS Drivers'!AF212 -> 6186.0398 | AG18: =+'IS Drivers'!AG212 -> 6055.6418 | AH18: =+'IS Drivers'!AH212 -> 6542.3422 | AI18: =+'IS Drivers'!AI212 -> 6325.5909 | AK18: ='3FS'!D18 -> 14139 | AL18: ='3FS'!E18 -> 18926 | AM18: ='3FS'!F18 -> 20238 | AN18: ='3FS'!G18 -> 21607 | AO18: ='3FS'!H18 -> 21311 | AP18: ='3FS'!I18 -> 20818 | AQ18: =SUMIFS($F18:$AI18,$F$3:$AI$3,AQ$3) -> 23220.354 | AR18: =SUMIFS($F18:$AI18,$F$3:$AI$3,AR$3) -> 25109.615 | AS18: =+'IS Drivers'!AS212 -> 24975.525
B19: Impairment expense | D19: ='3FS'!K19 -> 2000 | E19: ='3FS'!L19 -> 0 | F19: ='3FS'!M19 -> 0 | G19: ='3FS'!N19 -> 0 | H19: ='3FS'!O19 -> 0 | I19: ='3FS'!P19 -> 418 | J19: ='3FS'!Q19 -> 0 | K19: ='3FS'!R19 -> 0 | ... AD19: ='3FS'!AK19 -> 278 | AK19: ='3FS'!D19 -> 0 | AL19: ='3FS'!E19 -> 418 | AM19: ='3FS'!F19 -> 0 | AN19: ='3FS'!G19 -> 477 | AO19: ='3FS'!H19 -> 0 | AP19: ='3FS'!I19 -> 0 | AQ19: =SUMIFS($F19:$AI19,$F$3:$AI$3,AQ$3) -> 278 | AR19: =SUMIFS($F19:$AI19,$F$3:$AI$3,AR$3) -> 0
B20: Loss (gain) on disposal group held for sale | D20: ='3FS'!K20 -> 0 | E20: ='3FS'!L20 -> 0 | F20: ='3FS'!M20 -> 0 | G20: ='3FS'!N20 -> 0 | H20: ='3FS'!O20 -> 0 | I20: ='3FS'!P20 -> 0 | J20: ='3FS'!Q20 -> 0 | K20: ='3FS'!R20 -> 0 | ... AD20: ='3FS'!AK20 -> 0 | AK20: ='3FS'!D20 -> 0 | AL20: ='3FS'!E20 -> 0 | AM20: ='3FS'!F20 -> 0 | AN20: ='3FS'!G20 -> 1087 | AO20: ='3FS'!H20 -> -25 | AP20: ='3FS'!I20 -> 0 | AQ20: =SUMIFS($F20:$AI20,$F$3:$AI$3,AQ$3) -> 0 | AR20: =SUMIFS($F20:$AI20,$F$3:$AI$3,AR$3) -> 0
B21: Depreciation and amortization | D21: ='3FS'!K21 -> 4015 | E21: ='3FS'!L21 -> 3972 | F21: ='3FS'!M21 -> 4084 | G21: ='3FS'!N21 -> 4122 | H21: ='3FS'!O21 -> 4014 | I21: ='3FS'!P21 -> 4064 | J21: ='3FS'!Q21 -> 4150 | K21: ='3FS'!R21 -> 4219 | ... AD21: ='3FS'!AK21 -> 3408 | AE21: =+AE122 -> 3670.0321 | AF21: =+AF122 -> 3720.8608 | AG21: =+AG122 -> 3615.6245 | AH21: =+AH122 -> 3525.2306 | AI21: =+AI122 -> 3446.8785 | AK21: ='3FS'!D21 -> 6616 | AL21: ='3FS'!E21 -> 14151 | AM21: ='3FS'!F21 -> 16383 | AN21: ='3FS'!G21 -> 13651 | AO21: ='3FS'!H21 -> 12818 | AP21: ='3FS'!I21 -> 12919 | AQ21: =SUMIFS($F21:$AI21,$F$3:$AI$3,AQ$3) -> 13422.032 | AR21: =SUMIFS($F21:$AI21,$F$3:$AI$3,AR$3) -> 14308.594 | AS21: =+AS122 -> 14771.983
B22: Total operating expenses | D22: =+SUM(D16:D21) -> 17991 | E22: =+SUM(E16:E21) -> 15648 | F22: =+SUM(F16:F21) -> 15759 | G22: =+SUM(G16:G21) -> 16788 | H22: =+SUM(H16:H21) -> 15762 | I22: =+SUM(I16:I21) -> 16851 | J22: =+SUM(J16:J21) -> 16707 | K22: =+SUM(K16:K21) -> 18629 | ... AI22: =+SUM(AI16:AI21) -> 20134.655 | AK22: =+SUM(AK16:AK21) -> 39276 | AL22: =+SUM(AL16:AL21) -> 61761 | AM22: =+SUM(AM16:AM21) -> 73226 | AN22: =+SUM(AN16:AN21) -> 73028 | AO22: =+SUM(AO16:AO21) -> 64292 | AP22: =+SUM(AP16:AP21) -> 63390 | AQ22: =+SUM(AQ16:AQ21) -> 69268.151 | AR22: =+SUM(AR16:AR21) -> 73788.638 | AS22: =+SUM(AS16:AS21) -> 75515.452
B23: Operating income | D23: =+D14-D22 -> -372 | E23: =+E14-E22 -> 1812 | F23: =+F14-F22 -> 1484 | G23: =+G14-G22 -> 1497 | H23: =+H14-H22 -> 1646 | I23: =+I14-I22 -> 820 | J23: =+J14-J22 -> 2565 | K23: =+K14-K22 -> 1712 | ... AI23: =+AI14-AI22 -> 5099.1664 | AK23: =+AK14-AK22 -> 5722 | AL23: =+AL14-AL22 -> 6636 | AM23: =+AM14-AM22 -> 6892 | AN23: =+AN14-AN22 -> 6543 | AO23: =+AO14-AO22 -> 14266 | AP23: =+AP14-AP22 -> 18010 | AQ23: =+AQ14-AQ22 -> 18579.344 | AR23: =+AR14-AR22 -> 20628.685 | AS23: =+AS14-AS22 -> 23736.335
B24: Other expense, net
B25: Interest expense, net | D25: ='3FS'!K25 -> -828 | E25: ='3FS'!L25 -> -819 | F25: ='3FS'!M25 -> -830 | G25: ='3FS'!N25 -> -827 | H25: ='3FS'!O25 -> -804 | I25: ='3FS'!P25 -> -833 | J25: ='3FS'!Q25 -> -806 | K25: ='3FS'!R25 -> -790 | ... AD25: ='3FS'!AK25 -> -924 | AE25: =+'BS Drivers'!AE107 -> -1014.6249 | AF25: =+'BS Drivers'!AF107 -> -957.77248 | AG25: =+'BS Drivers'!AG107 -> -968.96249 | AH25: =+'BS Drivers'!AH107 -> -998.72284 | AI25: =+'BS Drivers'!AI107 -> -1024.3197 | AK25: ='3FS'!D25 -> -1111 | AL25: ='3FS'!E25 -> -2701 | AM25: ='3FS'!F25 -> -3342 | AN25: ='3FS'!G25 -> -3364 | AO25: ='3FS'!H25 -> -3335 | AP25: ='3FS'!I25 -> -3411 | AQ25: =SUMIFS($F25:$AI25,$F$3:$AI$3,AQ$3) -> -3776.6249 | AR25: =SUMIFS($F25:$AI25,$F$3:$AI$3,AR$3) -> -3949.7775 | AS25: =+'BS Drivers'!AS107 -> -4240.0517
B26: Other (expense) income, net | D26: ='3FS'!K26 -> 1 | E26: ='3FS'!L26 -> -24 | F26: ='3FS'!M26 -> 1 | G26: ='3FS'!N26 -> -20 | H26: ='3FS'!O26 -> -19 | I26: ='3FS'!P26 -> -195 | J26: ='3FS'!Q26 -> -99 | K26: ='3FS'!R26 -> -101 | ... AD26: ='3FS'!AK26 -> -78 | AE26: =AD26 -> -78 | AF26: =AVERAGE(AB26:AE26) -> -53.25 | AG26: =AF26 -> -53.25 | AH26: =AG26 -> -53.25 | AI26: =AH26 -> -53.25 | AK26: ='3FS'!D26 -> -8 | AL26: ='3FS'!E26 -> -405 | AM26: ='3FS'!F26 -> -199 | AN26: ='3FS'!G26 -> -33 | AO26: ='3FS'!H26 -> 68 | AP26: ='3FS'!I26 -> 113 | AQ26: =SUMIFS($F26:$AI26,$F$3:$AI$3,AQ$3) -> -213 | AR26: =SUMIFS($F26:$AI26,$F$3:$AI$3,AR$3) -> -213 | AS26: =AR26 -> -213
B27: Total other expense, net | D27: =+SUM(D25:D26) -> -827 | E27: =+SUM(E25:E26) -> -843 | F27: =+SUM(F25:F26) -> -829 | G27: =+SUM(G25:G26) -> -847 | H27: =+SUM(H25:H26) -> -823 | I27: =+SUM(I25:I26) -> -1028 | J27: =+SUM(J25:J26) -> -905 | K27: =+SUM(K25:K26) -> -891 | ... AI27: =+SUM(AI25:AI26) -> -1077.5697 | AK27: =+SUM(AK25:AK26) -> -1119 | AL27: =+SUM(AL25:AL26) -> -3106 | AM27: =+SUM(AM25:AM26) -> -3541 | AN27: =+SUM(AN25:AN26) -> -3397 | AO27: =+SUM(AO25:AO26) -> -3267 | AP27: =+SUM(AP25:AP26) -> -3298 | AQ27: =+SUM(AQ25:AQ26) -> -3989.6249 | AR27: =+SUM(AR25:AR26) -> -4162.7775 | AS27: =+SUM(AS25:AS26) -> -4453.0517
B28: Income (loss) before income taxes | D28: =+D27+D23 -> -1199 | E28: =+E27+E23 -> 969 | F28: =+F27+F23 -> 655 | G28: =+G27+G23 -> 650 | H28: =+H27+H23 -> 823 | I28: =+I27+I23 -> -208 | J28: =+J27+J23 -> 1660 | K28: =+K27+K23 -> 821 | ... AI28: =+AI27+AI23 -> 4021.5968 | AK28: =+AK27+AK23 -> 4603 | AL28: =+AL27+AL23 -> 3530 | AM28: =+AM27+AM23 -> 3351 | AN28: =+AN27+AN23 -> 3146 | AO28: =+AO27+AO23 -> 10999 | AP28: =+AP27+AP23 -> 14712 | AQ28: =+AQ27+AQ23 -> 14589.719 | AR28: =+AR27+AR23 -> 16465.907 | AS28: =+AS27+AS23 -> 19283.283
B29: Income tax (expense) benefit | D29: ='3FS'!K29 -> -164 | E29: ='3FS'!L29 -> -241 | F29: ='3FS'!M29 -> -204 | G29: ='3FS'!N29 -> 143 | H29: ='3FS'!O29 -> 282 | I29: ='3FS'!P29 -> -2 | J29: ='3FS'!Q29 -> -407 | K29: ='3FS'!R29 -> -71 | ... AD29: ='3FS'!AK29 -> -814 | AE29: ='BS Drivers'!AE123 -> -679.19148 | AF29: ='BS Drivers'!AF123 -> -908.88543 | AG29: ='BS Drivers'!AG123 -> -1011.3869 | AH29: ='BS Drivers'!AH123 -> -950.94892 | AI29: ='BS Drivers'!AI123 -> -927.88543 | AK29: ='3FS'!D29 -> -1135 | AL29: ='3FS'!E29 -> -786 | AM29: ='3FS'!F29 -> -327 | AN29: ='3FS'!G29 -> -556 | AO29: ='3FS'!H29 -> -2682 | AP29: ='3FS'!I29 -> -3373 | AQ29: =SUMIFS($F29:$AI29,$F$3:$AI$3,AQ$3) -> -3436.1915 | AR29: =SUMIFS($F29:$AI29,$F$3:$AI$3,AR$3) -> -3799.1067 | AS29: ='BS Drivers'!AS123 -> -4449.1475
B30: Income from continuing operations | D30: =+D29+D28 -> -1363 | E30: =+E29+E28 -> 728 | F30: =+F29+F28 -> 451 | G30: =+G29+G28 -> 793 | H30: =+H29+H28 -> 1105 | I30: =+I29+I28 -> -210 | J30: =+J29+J28 -> 1253 | K30: =+K29+K28 -> 750 | ... AI30: =+AI29+AI28 -> 3093.7114 | AK30: =+AK29+AK28 -> 3468 | AL30: =+AL29+AL28 -> 2744 | AM30: =+AM29+AM28 -> 3024 | AN30: =+AN29+AN28 -> 2590 | AO30: =+AO29+AO28 -> 8317 | AP30: =+AP29+AP28 -> 11339 | AQ30: =+AQ29+AQ28 -> 11153.528 | AR30: =+AR29+AR28 -> 12666.801 | AS30: =+AS29+AS28 -> 14834.136
B31: Income from discontinued operations, net of tax | D31: ='3FS'!K31 -> 423 | E31: ='3FS'!L31 -> 423 | F31: ='3FS'!M31 -> 393 | G31: ='3FS'!N31 -> 355 | H31: ='3FS'!O31 -> 357 | I31: ='3FS'!P31 -> 320 | J31: ='3FS'!Q31 -> 0 | K31: ='3FS'!R31 -> 0 | ... AD31: ='3FS'!AK31 -> 0 | AE31: 0 | AF31: 0 | AG31: 0 | AH31: 0 | AI31: 0 | AK31: ='3FS'!D31 -> 0 | AL31: ='3FS'!E31 -> 320 | AM31: ='3FS'!F31 -> 0 | AN31: ='3FS'!G31 -> 0 | AO31: ='3FS'!H31 -> 0 | AP31: ='3FS'!I31 -> 0 | AQ31: =SUMIFS($F31:$AI31,$F$3:$AI$3,AQ$3) -> 0 | AR31: =SUMIFS($F31:$AI31,$F$3:$AI$3,AR$3) -> 0 | AS31: 0
B32: Net income (loss) | D32: =+D31+D30 -> -940 | E32: =+E31+E30 -> 1151 | F32: =+F31+F30 -> 844 | G32: =+G31+G30 -> 1148 | H32: =+H31+H30 -> 1462 | I32: =+I31+I30 -> 110 | J32: =+J31+J30 -> 1253 | K32: =+K31+K30 -> 750 | ... AI32: =+AI31+AI30 -> 3093.7114 | AK32: =+AK31+AK30 -> 3468 | AL32: =+AL31+AL30 -> 3064 | AM32: =+AM31+AM30 -> 3024 | AN32: =+AN31+AN30 -> 2590 | AO32: =+AO31+AO30 -> 8317 | AP32: =+AP31+AP30 -> 11339 | AQ32: =+AQ31+AQ30 -> 11153.528 | AR32: =+AR31+AR30 -> 12666.801 | AS32: =+AS31+AS30 -> 14834.136
B34: Earnings (loss) per share
B35: Basic | I35: =+I$32/I38 -> 0.08895873 | J35: =+J$32/J38 -> 1.011748 | K35: =+K$32/K38 -> 0.60406968 | L35: =+L$32/L38 -> 0.75028949 | M35: =+M$32/M38 -> 0.78392814 | N35: =+N$32/N38 -> 0.55360174 | O35: =+O$32/O38 -> 0.33779665 | P35: =+P$32/P38 -> 0.5701692 | ... AI35: =+AI$32/AI38 -> 2.7897559 | AK35: =+AK$32/AK38 -> 4.0602065 | AL35: =+AL$32/AL38 -> 2.6778387 | AM35: =+AM$32/AM38 -> 2.4247187 | AN35: =+AN$32/AN38 -> 2.0723914 | AO35: =+AO$32/AO38 -> 7.0178455 | AP35: =+AP$32/AP38 -> 9.6981225 | AQ35: =SUMIFS($F35:$AI35,$F$3:$AI$3,AQ$3) -> 9.8498256 | AR35: =SUMIFS($F35:$AI35,$F$3:$AI$3,AR$3) -> 11.417619 | AS35: =+AS$32/AS38 -> 13.647816
B36: Diluted | I36: =+I$32/I39 -> 0.08895873 | J36: =+J$32/J39 -> 1.0025614 | K36: =+K$32/K39 -> 0.59924883 | L36: =+L$32/L39 -> 0.74474157 | M36: =+M$32/M39 -> 0.78007965 | N36: =+N$32/N39 -> 0.55118558 | O36: =+O$32/O39 -> 0.33644554 | P36: =+P$32/P39 -> 0.56796068 | ... AI36: =+AI$32/AI39 -> 2.7826403 | AK36: =+AK$32/AK39 -> 4.0165224 | AL36: =+AL$32/AL39 -> 2.6533895 | AM36: =+AM$32/AM39 -> 2.4100036 | AN36: =+AN$32/AN39 -> 2.0631256 | AO36: =+AO$32/AO39 -> 6.9291804 | AP36: =+AP$32/AP39 -> 9.6649043 | AQ36: =SUMIFS($F36:$AI36,$F$3:$AI$3,AQ$3) -> 9.8240185 | AR36: =SUMIFS($F36:$AI36,$F$3:$AI$3,AR$3) -> 11.388496 | AS36: =+AS$32/AS39 -> 13.613006
B37: Weighted-average shares outstanding
B38: Basic | I38: ='3FS'!P42 -> 1236.5284 | J38: ='3FS'!Q42 -> 1238.4507 | K38: ='3FS'!R42 -> 1241.5786 | L38: ='3FS'!S42 -> 1243.52 | M38: ='3FS'!T42 -> 1247.5633 | N38: ='3FS'!U42 -> 1248.1897 | O38: ='3FS'!V42 -> 1249.2723 | P38: ='3FS'!W42 -> 1250.506 | ... AD38: ='3FS'!AK42 -> 1123.7541 | AE38: =+'BS Drivers'!AE151 -> 1131.5859 | AF38: =+'BS Drivers'!AF151 -> 1117.7272 | AG38: =+'BS Drivers'!AG151 -> 1110.1053 | AH38: =+'BS Drivers'!AH151 -> 1101.279 | AI38: =+'BS Drivers'!AI151 -> 1108.9541 | AK38: ='3FS'!D42 -> 854.14375 | AL38: ='3FS'!E42 -> 1144.2063 | AM38: ='3FS'!F42 -> 1247.155 | AN38: ='3FS'!G42 -> 1249.7639 | AO38: ='3FS'!H42 -> 1185.1216 | AP38: ='3FS'!I42 -> 1169.1954 | AQ38: =+AQ$32/AQ35 -> 1132.3579 | AR38: =+AR$32/AR35 -> 1109.4083 | AS38: =+'BS Drivers'!AS151 -> 1086.9238
B39: Diluted | I39: ='3FS'!P43 -> 1236.5284 | J39: ='3FS'!Q43 -> 1249.7987 | K39: ='3FS'!R43 -> 1251.5669 | L39: ='3FS'!S43 -> 1252.7836 | M39: ='3FS'!T43 -> 1253.7181 | N39: ='3FS'!U43 -> 1253.6612 | O39: ='3FS'!V43 -> 1254.2892 | P39: ='3FS'!W43 -> 1255.3686 | ... AD39: ='3FS'!AK43 -> 1126.6277 | AE39: =+'BS Drivers'!AE154 -> 1134.4795 | AF39: =+'BS Drivers'!AF154 -> 1120.5854 | AG39: =+'BS Drivers'!AG154 -> 1112.944 | AH39: =+'BS Drivers'!AH154 -> 1104.0952 | AI39: =+'BS Drivers'!AI154 -> 1111.7899 | AK39: ='3FS'!D43 -> 863.43351 | AL39: ='3FS'!E43 -> 1154.7494 | AM39: ='3FS'!F43 -> 1254.7699 | AN39: ='3FS'!G43 -> 1255.3768 | AO39: ='3FS'!H43 -> 1200.2863 | AP39: ='3FS'!I43 -> 1173.2139 | AQ39: =+AQ$32/AQ36 -> 1135.3325 | AR39: =+AR$32/AR36 -> 1112.2452 | AS39: =+'BS Drivers'!AS154 -> 1089.7032
B41: Gross margin - services | D41: =1-D16/D11 -> 0.74095031 | E41: =1-E16/E11 -> 0.7525369 | F41: =1-F16/F11 -> 0.73927188 | G41: =1-G16/G11 -> 0.75037856 | H41: =1-H16/H11 -> 0.75752065 | I41: =1-I16/I11 -> 0.76583522 | J41: =1-J16/J11 -> 0.76561284 | K41: =1-K16/K11 -> 0.73011283 | ... AI41: =1-AI16/AI11 -> 0.84267817 | AK41: =1-AK16/AK11 -> 0.80805797 | AL41: =1-AL16/AL11 -> 0.76430201 | AM41: =1-AM16/AM11 -> 0.76127739 | AN41: =1-AN16/AN11 -> 0.76084014 | AO41: =1-AO16/AO11 -> 0.815705 | AP41: =1-AP16/AP11 -> 0.83724198 | AQ41: =1-AQ16/AQ11 -> 0.84359439 | AR41: =1-AR16/AR11 -> 0.84461812 | AS41: =1-AS16/AS11 -> 0.84461812
B42: Gross margin - equipment | D42: =1-D17/D12 -> 0.17051957 | E42: =1-E17/E12 -> 0.19980483 | F42: =1-F17/F12 -> 0.16205335 | G42: =1-G17/G12 -> 0.077168367 | H42: =1-H17/H12 -> 0.15686275 | I42: =1-I17/I12 -> 0.14101663 | J42: =1-J17/J12 -> 0.11831213 | K42: =1-K17/K12 -> 0.024778168 | ... AI42: =1-AI17/AI12 -> -0.36760534 | AK42: =1-AK17/AK12 -> -0.20924797 | AL42: =1-AL17/AL12 -> 0.053373383 | AM42: =1-AM17/AM12 -> -0.093790708 | AN42: =1-AN17/AN12 -> -0.25744308 | AO42: =1-AO17/AO12 -> -0.31086434 | AP42: =1-AP17/AP12 -> -0.32384491 | AQ42: =1-AQ17/AQ12 -> -0.3549717 | AR42: =1-AR17/AR12 -> -0.35563853 | AS42: =1-AS17/AS12 -> -0.3569501
B43: Operating Margin | D43: =D23/D14 -> -0.021113571 | E43: =E23/E14 -> 0.10378007 | F43: =F23/F14 -> 0.08606391 | G43: =G23/G14 -> 0.081870386 | H43: =H23/H14 -> 0.094554228 | I43: =I23/I14 -> 0.046403712 | J43: =J23/J14 -> 0.13309465 | K43: =K23/K14 -> 0.084164987 | ... AI43: =AI23/AI14 -> 0.20207666 | AK43: =AK23/AK14 -> 0.12716121 | AL43: =AL23/AL14 -> 0.097021799 | AM43: =AM23/AM14 -> 0.086023116 | AN43: =AN23/AN14 -> 0.08222845 | AO43: =AO23/AO14 -> 0.18159831 | AP43: =AP23/AP14 -> 0.22125307 | AQ43: =AQ23/AQ14 -> 0.21149544 | AR43: =AR23/AR14 -> 0.21848411 | AS43: =AS23/AS14 -> 0.23915272
B45: Adjusted EBITDA
B46: Operating income | D46: =D23 -> -372 | E46: =E23 -> 1812 | F46: =F23 -> 1484 | G46: =G23 -> 1497 | H46: =H23 -> 1646 | I46: =I23 -> 820 | J46: =J23 -> 2565 | K46: =K23 -> 1712 | ... AI46: =AI23 -> 5099.1664 | AK46: =AK23 -> 5722 | AL46: =AL23 -> 6636 | AM46: =AM23 -> 6892 | AN46: =AN23 -> 6543 | AO46: =AO23 -> 14266 | AP46: =AP23 -> 18010 | AQ46: =SUMIFS($F46:$AI46,$F$3:$AI$3,AQ$3) -> 18579.344 | AR46: =SUMIFS($F46:$AI46,$F$3:$AI$3,AR$3) -> 20628.685 | AS46: =AS23 -> 23736.335
B47: Depreciation and amortization | D47: =+D21 -> 4015 | E47: =+E21 -> 3972 | F47: =+F21 -> 4084 | G47: =+G21 -> 4122 | H47: =+H21 -> 4014 | I47: =+I21 -> 4064 | J47: =+J21 -> 4150 | K47: =+K21 -> 4219 | ... AI47: =+AI21 -> 3446.8785 | AK47: =+AK21 -> 6616 | AL47: =+AL21 -> 14151 | AM47: =+AM21 -> 16383 | AN47: =+AN21 -> 13651 | AO47: =+AO21 -> 12818 | AP47: =+AP21 -> 12919 | AQ47: =SUMIFS($F47:$AI47,$F$3:$AI$3,AQ$3) -> 13422.032 | AR47: =SUMIFS($F47:$AI47,$F$3:$AI$3,AR$3) -> 14308.594 | AS47: =+AS21 -> 14771.983
B48: Operating income from discontinued operations | D48: =+'3FS'!K48 -> 571 | E48: =+'3FS'!L48 -> 572 | F48: =+'3FS'!M48 -> 531 | G48: =+'3FS'!N48 -> 480 | H48: =+'3FS'!O48 -> 482 | I48: =+'3FS'!P48 -> 432 | J48: =+'3FS'!Q48 -> 0 | K48: =+'3FS'!R48 -> 0 | ... AD48: =+'3FS'!AK48 -> 0 | AK48: =+'3FS'!D48 -> 0 | AL48: =+'3FS'!E48 -> 914 | AM48: =+'3FS'!F48 -> 0 | AN48: =+'3FS'!G48 -> 0 | AO48: =+'3FS'!H48 -> 0 | AP48: =+'3FS'!I48 -> 0 | AQ48: =SUMIFS($F48:$AI48,$F$3:$AI$3,AQ$3) -> 0 | AR48: =SUMIFS($F48:$AI48,$F$3:$AI$3,AR$3) -> 0
B49: Stock-based compensation | D49: =+'3FS'!K49 -> 183 | E49: =+'3FS'!L49 -> 133 | F49: =+'3FS'!M49 -> 117 | G49: =+'3FS'!N49 -> 119 | H49: =+'3FS'!O49 -> 124 | I49: =+'3FS'!P49 -> 139 | J49: =+'3FS'!Q49 -> 125 | K49: =+'3FS'!R49 -> 129 | ... AD49: =+'3FS'!AK49 -> 217 | AE49: =AD49*AE123/AD123 -> 228.01609 | AF49: =AE49*AF123/AE123 -> 223.17051 | AG49: =AF49*AG123/AF123 -> 218.46621 | AH49: =AG49*AH123/AG123 -> 236.02465 | AI49: =AH49*AI123/AH123 -> 228.20503 | AK49: =+'3FS'!D49 -> 423 | AL49: =+'3FS'!E49 -> 517 | AM49: =+'3FS'!F49 -> 521 | AN49: =+'3FS'!G49 -> 576 | AO49: =+'3FS'!H49 -> 644 | AP49: =+'3FS'!I49 -> 586 | AQ49: =SUMIFS($F49:$AI49,$F$3:$AI$3,AQ$3) -> 791.01609 | AR49: =SUMIFS($F49:$AI49,$F$3:$AI$3,AR$3) -> 905.8664 | AS49: =AR49*AS123/AR123 -> 901.02893
B50: Merger-related costs | D50: =+'3FS'!K50 -> 123 | E50: =+'3FS'!L50 -> 235 | F50: =+'3FS'!M50 -> 165 | G50: =+'3FS'!N50 -> 117 | H50: =+'3FS'!O50 -> 136 | I50: =+'3FS'!P50 -> 798 | J50: =+'3FS'!Q50 -> 288 | K50: =+'3FS'!R50 -> 686 | ... AD50: =+'3FS'!AK50 -> 73 | AK50: =+'3FS'!D50 -> 620 | AL50: =+'3FS'!E50 -> 1908 | AM50: =+'3FS'!F50 -> 3107 | AN50: =+'3FS'!G50 -> 4969 | AO50: =+'3FS'!H50 -> 1034 | AP50: =+'3FS'!I50 -> 121 | AQ50: =SUMIFS($F50:$AI50,$F$3:$AI$3,AQ$3) -> 120 | AR50: =SUMIFS($F50:$AI50,$F$3:$AI$3,AR$3) -> 0
B51: Impairment expense | D51: =+D19 -> 2000 | E51: =+E19 -> 0 | F51: =+F19 -> 0 | G51: =+G19 -> 0 | H51: =+H19 -> 0 | I51: =+I19 -> 418 | J51: =+J19 -> 0 | K51: =+K19 -> 0 | ... AI51: =+AI19 -> 0 | AK51: =+AK19 -> 0 | AL51: =+AL19 -> 418 | AM51: =+AM19 -> 0 | AN51: =+AN19 -> 477 | AO51: =+AO19 -> 0 | AP51: =+AP19 -> 0 | AQ51: =SUMIFS($F51:$AI51,$F$3:$AI$3,AQ$3) -> 278 | AR51: =SUMIFS($F51:$AI51,$F$3:$AI$3,AR$3) -> 0 | AS51: =+AS19 -> 0
B52: Legal-related expenses (recoveries), net | D52: ='3FS'!K53 -> 0 | E52: ='3FS'!L53 -> 0 | F52: ='3FS'!M53 -> 0 | G52: ='3FS'!N53 -> 0 | H52: ='3FS'!O53 -> 0 | I52: ='3FS'!P53 -> 0 | J52: ='3FS'!Q53 -> 0 | K52: ='3FS'!R53 -> 0 | ... AD52: ='3FS'!AK53 -> 8 | AK52: ='3FS'!D53 -> 0 | AL52: ='3FS'!E53 -> 0 | AM52: ='3FS'!F53 -> 0 | AN52: ='3FS'!G53 -> 391 | AO52: ='3FS'!H53 -> -42 | AP52: ='3FS'!I53 -> -89 | AQ52: =SUMIFS($F52:$AI52,$F$3:$AI$3,AQ$3) -> 10 | AR52: =SUMIFS($F52:$AI52,$F$3:$AI$3,AR$3) -> 0
B53: Loss (gain) on disposal group held for sale | D53: =+D20 -> 0 | E53: =+E20 -> 0 | F53: =+F20 -> 0 | G53: =+G20 -> 0 | H53: =+H20 -> 0 | I53: =+I20 -> 0 | J53: =+J20 -> 0 | K53: =+K20 -> 0 | ... AI53: =+AI20 -> 0 | AK53: =+AK20 -> 0 | AL53: =+AL20 -> 0 | AM53: =+AM20 -> 0 | AN53: =+AN20 -> 1087 | AO53: =+AO20 -> -25 | AP53: =+AP20 -> 0 | AQ53: =SUMIFS($F53:$AI53,$F$3:$AI$3,AQ$3) -> 0 | AR53: =SUMIFS($F53:$AI53,$F$3:$AI$3,AR$3) -> 0 | AS53: =+AS20 -> 0
B54: Other, net | D54: =+'3FS'!K55 -> 352 | E54: =+'3FS'!L55 -> 239 | F54: =+'3FS'!M55 -> 24 | G54: =+'3FS'!N55 -> -157 | H54: =+'3FS'!O55 -> 249 | I54: =+'3FS'!P55 -> 346 | J54: =+'3FS'!Q55 -> 1 | K54: =+'3FS'!R55 -> 0 | ... AD54: =+'3FS'!AK55 -> 170 | AE54: 0 | AF54: 0 | AG54: 0 | AH54: 0 | AI54: 0 | AK54: =+'3FS'!D55 -> 2 | AL54: =+'3FS'!E55 -> 596 | AM54: =+'3FS'!F55 -> 21 | AN54: =+'3FS'!G55 -> 127 | AO54: =+'3FS'!H55 -> 733 | AP54: =+'3FS'!I55 -> 317 | AQ54: =SUMIFS($F54:$AI54,$F$3:$AI$3,AQ$3) -> 224 | AR54: =SUMIFS($F54:$AI54,$F$3:$AI$3,AR$3) -> 0 | AS54: 0
B55: Cost to Achieve | AE55: ='IS Drivers'!AE218 -> 460 | AF55: ='IS Drivers'!AF218 -> 385 | AG55: ='IS Drivers'!AG218 -> 385 | AH55: ='IS Drivers'!AH218 -> 385 | AI55: ='IS Drivers'!AI218 -> 385 | AQ55: =SUMIFS($F55:$AI55,$F$3:$AI$3,AQ$3) -> 460 | AR55: =SUMIFS($F55:$AI55,$F$3:$AI$3,AR$3) -> 1540 | AS55: ='IS Drivers'!AS218 -> 660
B56: Adjusted EBITDA | D56: =+SUM(D46:D54) -> 6872 | E56: =+SUM(E46:E54) -> 6963 | F56: =+SUM(F46:F54) -> 6405 | G56: =+SUM(G46:G54) -> 6178 | H56: =+SUM(H46:H54) -> 6651 | I56: =+SUM(I46:I54) -> 7017 | J56: =+SUM(J46:J54) -> 7129 | K56: =+SUM(K46:K54) -> 6746 | ... AD56: =+SUM(AD46:AD54) -> 8684 | AE56: =+SUM(AE46:AE55) -> 8394.3925 | AF56: =+SUM(AF46:AF55) -> 9279.3016 | AG56: =+SUM(AG46:AG55) -> 9624.8083 | AH56: =+SUM(AH46:AH55) -> 9319.7855 | AI56: =+SUM(AI46:AI55) -> 9159.25 | AK56: =+SUM(AK46:AK54) -> 13383 | AL56: =+SUM(AL46:AL54) -> 25140 | AM56: =+SUM(AM46:AM54) -> 26924 | AN56: =+SUM(AN46:AN54) -> 27821 | AO56: =+SUM(AO46:AO54) -> 29428 | AP56: =+SUM(AP46:AP54) -> 31864 | AQ56: =+SUM(AQ46:AQ55) -> 33884.392 | AR56: =+SUM(AR46:AR55) -> 37383.145 | AS56: =+SUM(AS46:AS55) -> 40069.347
B57: Lease revenues | F57: =+'3FS'!M57 -> -1472 | G57: =+'3FS'!N57 -> -1445 | H57: =+'3FS'!O57 -> -1402 | I57: =+'3FS'!P57 -> -1421 | J57: =+'3FS'!Q57 -> -1350 | K57: =+'3FS'!R57 -> -1245 | L57: =+'3FS'!S57 -> -1041 | M57: =+'3FS'!T57 -> -914 | ... AD57: =+'3FS'!AK57 -> -4 | AE57: =-'IS Drivers'!AE14 -> -4 | AF57: =-'IS Drivers'!AF14 -> -4 | AG57: =-'IS Drivers'!AG14 -> -4 | AH57: =-'IS Drivers'!AH14 -> -4 | AI57: =-'IS Drivers'!AI14 -> -4 | AK57: =+'3FS'!D57 -> 0 | AL57: =+'3FS'!E57 -> -5418 | AM57: =+'3FS'!F57 -> -3348 | AN57: =+'3FS'!G57 -> -1430 | AO57: =+'3FS'!H57 -> -312 | AP57: =+'3FS'!I57 -> -93 | AQ57: =SUMIFS($F57:$AI57,$F$3:$AI$3,AQ$3) -> -15 | AR57: =SUMIFS($F57:$AI57,$F$3:$AI$3,AR$3) -> -16 | AS57: =-'IS Drivers'!AS14 -> 0
B58: Core Adjusted EBITDA | D58: =+D57+D56 -> 6872 | E58: =+E57+E56 -> 6963 | F58: =+F57+F56 -> 4933 | G58: =+G57+G56 -> 4733 | H58: =+H57+H56 -> 5249 | I58: =+I57+I56 -> 5596 | J58: =+J57+J56 -> 5779 | K58: =+K57+K56 -> 5501 | ... AI58: =+AI57+AI56 -> 9155.25 | AK58: =+AK57+AK56 -> 13383 | AL58: =+AL57+AL56 -> 19722 | AM58: =+AM57+AM56 -> 23576 | AN58: =+AN57+AN56 -> 26391 | AO58: =+AO57+AO56 -> 29116 | AP58: =+AP57+AP56 -> 31771 | AQ58: =+AQ57+AQ56 -> 33869.392 | AR58: =+AR57+AR56 -> 37367.145 | AS58: =+AS57+AS56 -> 40069.347
B59: Adjusted EBITDA margin (Adj. EBITDA / Service revenues) | D59: =+D56/D11 -> 0.53267189 | E59: =+E56/E11 -> 0.53528598 | F59: =+F56/F11 -> 0.49612703 | G59: =+G56/G11 -> 0.46774682 | H59: =+H56/H11 -> 0.50397818 | I59: =+I56/I11 -> 0.53038549 | J59: =+J56/J11 -> 0.50420822 | K59: =+K56/K11 -> 0.47574048 | ... AI59: =+AI56/AI11 -> 0.46639686 | AK59: =+AK56/AK11 -> 0.38791304 | AL59: =+AL56/AL11 -> 0.49885901 | AM59: =+AM56/AM11 -> 0.46127225 | AN59: =+AN56/AN11 -> 0.4536797 | AO59: =+AO56/AO11 -> 0.46533104 | AP59: =+AP56/AP11 -> 0.48148932 | AQ59: =+AQ56/AQ11 -> 0.4761613 | AR59: =+AR56/AR11 -> 0.4869046 | AS59: =+AS56/AS11 -> 0.4943679
B60: Core adj. EBITDA margin (Core Adj. EBITDA / Service revenues) | F60: =+F58/F11 -> 0.38210689 | G60: =+G58/G11 -> 0.35834343 | H60: =+H58/H11 -> 0.39774191 | I60: =+I58/I11 -> 0.42297808 | J60: =+J58/J11 -> 0.40872763 | K60: =+K58/K11 -> 0.38794076 | L60: =+L58/L11 -> 0.41319053 | M60: =+M58/M11 -> 0.4134695 | ... AI60: =+AI58/AI11 -> 0.46619317 | AK60: =+AK58/AK11 -> 0.38791304 | AL60: =+AL58/AL11 -> 0.39134835 | AM60: =+AM58/AM11 -> 0.40391304 | AN60: =+AN58/AN11 -> 0.43036055 | AO60: =+AO58/AO11 -> 0.46039753 | AP60: =+AP58/AP11 -> 0.48008402 | AQ60: =+AQ58/AQ11 -> 0.47595051 | AR60: =+AR58/AR11 -> 0.4866962 | AS60: =+AS58/AS11 -> 0.4943679
B61: Operating Income Margin | F61: =+F23/F14 -> 0.08606391 | G61: =+G23/G14 -> 0.081870386 | H61: =+H23/H14 -> 0.094554228 | I61: =+I23/I14 -> 0.046403712 | J61: =+J23/J14 -> 0.13309465 | K61: =+K23/K14 -> 0.084164987 | L61: =+L23/L14 -> 0.10825447 | M61: =+M23/M14 -> 0.10556391 | ... AI61: =+AI23/AI14 -> 0.20207666 | AK61: =+AK23/AK14 -> 0.12716121 | AL61: =+AL23/AL14 -> 0.097021799 | AM61: =+AM23/AM14 -> 0.086023116 | AN61: =+AN23/AN14 -> 0.08222845 | AO61: =+AO23/AO14 -> 0.18159831 | AP61: =+AP23/AP14 -> 0.22125307 | AQ61: =+AQ23/AQ14 -> 0.21149544 | AR61: =+AR23/AR14 -> 0.21848411 | AS61: =+AS23/AS14 -> 0.23915272
B63: YoY growth in Adj. EBITDA | H63: =H56/D56-1 -> -0.032159488 | I63: =I56/E56-1 -> 0.0077552779 | J63: =J56/F56-1 -> 0.11303669 | K63: =K56/G56-1 -> 0.091939139 | L63: =L56/H56-1 -> 0.038189746 | M63: =M56/I56-1 -> -0.015818726 | N63: =N56/J56-1 -> -0.044606537 | O63: =O56/K56-1 -> -0.06581678 | ... AI63: =AI56/AE56-1 -> 0.091115285 | AM63: =AM56/AL56-1 -> 0.070962609 | AN63: =AN56/AM56-1 -> 0.033316001 | AO63: =AO56/AN56-1 -> 0.057762122 | AP63: =AP56/AO56-1 -> 0.082778306 | AQ63: =AQ56/AP56-1 -> 0.063406744 | AR63: =AR56/AQ56-1 -> 0.10325559 | AS63: =AS56/AR56-1 -> 0.071855951
B64: YoY growth in Core Adj. EBITDA | H64: =H58/D58-1 -> -0.23617579 | I64: =I58/E58-1 -> -0.19632342 | J64: =J58/F58-1 -> 0.17149807 | K64: =K58/G58-1 -> 0.16226495 | L64: =L58/H58-1 -> 0.11716517 | M64: =M58/I58-1 -> 0.070764832 | N64: =N58/J58-1 -> 0.045336563 | O64: =O58/K58-1 -> 0.032357753 | ... AI64: =AI58/AE58-1 -> 0.091158723 | AM64: =AM58/AL58-1 -> 0.19541629 | AN64: =AN58/AM58-1 -> 0.11940109 | AO64: =AO58/AN58-1 -> 0.1032549 | AP64: =AP58/AO58-1 -> 0.091186976 | AQ64: =AQ58/AP58-1 -> 0.066047417 | AR64: =AR58/AQ58-1 -> 0.10327179 | AS64: =AS58/AR58-1 -> 0.072314902
A66: x | B66: Balance Sheet
B67: Assets | D67: Pre Merger Non Pro Forma
B68: Current assets
B69: Cash and cash equivalents | D69: ='3FS'!K66 -> 1439 | E69: ='3FS'!L66 -> 1105 | F69: ='3FS'!M66 -> 1653 | G69: ='3FS'!N66 -> 1528 | H69: ='3FS'!O66 -> 1112 | I69: ='3FS'!P66 -> 11076 | J69: ='3FS'!Q66 -> 6571 | K69: ='3FS'!R66 -> 10385 | ... AD69: ='3FS'!AK66 -> 3310 | AE69: =+AE165-AE166 -> 1858.3843 | AF69: =+AF165-AF166 -> 2175.0272 | AG69: =+AG165-AG166 -> 3602.8934 | AH69: =+AH165-AH166 -> 5883.6863 | AI69: =+AI165-AI166 -> 7040.4039 | AK69: ='3FS'!D66 -> 1528 | AL69: ='3FS'!E66 -> 10385 | AM69: ='3FS'!F66 -> 6631 | AN69: ='3FS'!G66 -> 4507 | AO69: ='3FS'!H66 -> 5135 | AP69: ='3FS'!I66 -> 5409 | AQ69: =SUMIFS($F69:$AI69,$F$3:$AI$3,AQ$3,$F$2:$AI$2,4) -> 1858.3843 | AR69: =SUMIFS($F69:$AI69,$F$3:$AI$3,AR$3,$F$2:$AI$2,4) -> 7040.4039 | AS69: =+AS165-AS166 -> 10264.348
B70: Accounts receivable | D70: ='3FS'!K67 -> 1765 | E70: ='3FS'!L67 -> 1835 | F70: ='3FS'!M67 -> 1842 | G70: ='3FS'!N67 -> 1908 | H70: ='3FS'!O67 -> 1862 | I70: ='3FS'!P67 -> 3379 | J70: ='3FS'!Q67 -> 4332 | K70: ='3FS'!R67 -> 4276 | ... AD70: ='3FS'!AK67 -> 5084 | AE70: ='BS Drivers'!AE9 -> 5096.0477 | AF70: ='BS Drivers'!AF9 -> 5244.6928 | AG70: ='BS Drivers'!AG9 -> 5509.2534 | AH70: ='BS Drivers'!AH9 -> 6020.8244 | AI70: ='BS Drivers'!AI9 -> 5994.5196 | AK70: ='3FS'!D67 -> 1908 | AL70: ='3FS'!E67 -> 4276 | AM70: ='3FS'!F67 -> 4194 | AN70: ='3FS'!G67 -> 4445 | AO70: ='3FS'!H67 -> 4692 | AP70: ='3FS'!I67 -> 4276 | AQ70: =SUMIFS($F70:$AI70,$F$3:$AI$3,AQ$3,$F$2:$AI$2,4) -> 5096.0477 | AR70: =SUMIFS($F70:$AI70,$F$3:$AI$3,AR$3,$F$2:$AI$2,4) -> 5994.5196 | AS70: ='BS Drivers'!AS9 -> 6573.3806
B71: Equipment installment plan receivables | D71: ='3FS'!K68 -> 2466 | E71: ='3FS'!L68 -> 2446 | F71: ='3FS'!M68 -> 2425 | G71: ='3FS'!N68 -> 2600 | H71: ='3FS'!O68 -> 2406 | I71: ='3FS'!P68 -> 3194 | J71: ='3FS'!Q68 -> 3083 | K71: ='3FS'!R68 -> 3577 | ... AD71: ='3FS'!AK68 -> 4599 | AE71: ='BS Drivers'!AE15 -> 4823.322 | AF71: ='BS Drivers'!AF15 -> 4838.6508 | AG71: ='BS Drivers'!AG15 -> 4945.0443 | AH71: ='BS Drivers'!AH15 -> 5016.5636 | AI71: ='BS Drivers'!AI15 -> 5098.7777 | AK71: ='3FS'!D68 -> 2600 | AL71: ='3FS'!E68 -> 3577 | AM71: ='3FS'!F68 -> 4748 | AN71: ='3FS'!G68 -> 5123 | AO71: ='3FS'!H68 -> 4456 | AP71: ='3FS'!I68 -> 4379 | AQ71: =SUMIFS($F71:$AI71,$F$3:$AI$3,AQ$3,$F$2:$AI$2,4) -> 4823.322 | AR71: =SUMIFS($F71:$AI71,$F$3:$AI$3,AR$3,$F$2:$AI$2,4) -> 5098.7777 | AS71: ='BS Drivers'!AS15 -> 5265.3989
B72: Inventory | D72: ='3FS'!K69 -> 1261 | E72: ='3FS'!L69 -> 998 | F72: ='3FS'!M69 -> 801 | G72: ='3FS'!N69 -> 964 | H72: ='3FS'!O69 -> 1225 | I72: ='3FS'!P69 -> 1549 | J72: ='3FS'!Q69 -> 1931 | K72: ='3FS'!R69 -> 2527 | ... AD72: ='3FS'!AK69 -> 2370 | AE72: =+'BS Drivers'!AE19 -> 2141.1954 | AF72: =+'BS Drivers'!AF19 -> 2181.7607 | AG72: =+'BS Drivers'!AG19 -> 2231.2123 | AH72: =+'BS Drivers'!AH19 -> 2268.1474 | AI72: =+'BS Drivers'!AI19 -> 2301.3284 | AK72: ='3FS'!D69 -> 964 | AL72: ='3FS'!E69 -> 2527 | AM72: ='3FS'!F69 -> 2567 | AN72: ='3FS'!G69 -> 1884 | AO72: ='3FS'!H69 -> 1678 | AP72: ='3FS'!I69 -> 1607 | AQ72: =SUMIFS($F72:$AI72,$F$3:$AI$3,AQ$3,$F$2:$AI$2,4) -> 2141.1954 | AR72: =SUMIFS($F72:$AI72,$F$3:$AI$3,AR$3,$F$2:$AI$2,4) -> 2301.3284 | AS72: =+'BS Drivers'!AS19 -> 2419.1636
B73: Prepaid expenses | D73: ='3FS'!K70 -> 0 | E73: ='3FS'!L70 -> 0 | F73: ='3FS'!M70 -> 0 | G73: ='3FS'!N70 -> 0 | H73: ='3FS'!O70 -> 0 | I73: ='3FS'!P70 -> 627 | J73: ='3FS'!Q70 -> 659 | K73: ='3FS'!R70 -> 624 | ... AD73: ='3FS'!AK70 -> 1128 | AE73: =+'BS Drivers'!AE23 -> 1154.2858 | AF73: =+'BS Drivers'!AF23 -> 1176.1539 | AG73: =+'BS Drivers'!AG23 -> 1202.8126 | AH73: =+'BS Drivers'!AH23 -> 1222.7237 | AI73: =+'BS Drivers'!AI23 -> 1240.6111 | AK73: ='3FS'!D70 -> 0 | AL73: ='3FS'!E70 -> 624 | AM73: ='3FS'!F70 -> 746 | AN73: ='3FS'!G70 -> 673 | AO73: ='3FS'!H70 -> 702 | AP73: ='3FS'!I70 -> 880 | AQ73: =SUMIFS($F73:$AI73,$F$3:$AI$3,AQ$3,$F$2:$AI$2,4) -> 1154.2858 | AR73: =SUMIFS($F73:$AI73,$F$3:$AI$3,AR$3,$F$2:$AI$2,4) -> 1240.6111 | AS73: =+'BS Drivers'!AS23 -> 1304.1343
B74: Other current assets | D74: ='3FS'!K71 -> 1814 | E74: ='3FS'!L71 -> 1730 | F74: ='3FS'!M71 -> 1737 | G74: ='3FS'!N71 -> 2305 | H74: ='3FS'!O71 -> 2882 | I74: ='3FS'!P71 -> 4496 | J74: ='3FS'!Q71 -> 2889 | K74: ='3FS'!R71 -> 2496 | ... AD74: ='3FS'!AK71 -> 5212 | AE74: ='BS Drivers'!AE66 -> 5212 | AF74: ='BS Drivers'!AF66 -> 5212 | AG74: ='BS Drivers'!AG66 -> 5212 | AH74: ='BS Drivers'!AH66 -> 5212 | AI74: ='BS Drivers'!AI66 -> 5212 | AK74: ='3FS'!D71 -> 2305 | AL74: ='3FS'!E71 -> 2496 | AM74: ='3FS'!F71 -> 2005 | AN74: ='3FS'!G71 -> 2435 | AO74: ='3FS'!H71 -> 2352 | AP74: ='3FS'!I71 -> 1853 | AQ74: =SUMIFS($F74:$AI74,$F$3:$AI$3,AQ$3,$F$2:$AI$2,4) -> 5212 | AR74: =SUMIFS($F74:$AI74,$F$3:$AI$3,AR$3,$F$2:$AI$2,4) -> 5212 | AS74: ='BS Drivers'!AS66 -> 5212
B75: Total current assets | D75: =+SUM(D69:D74) -> 8745 | E75: =+SUM(E69:E74) -> 8114 | F75: =+SUM(F69:F74) -> 8458 | G75: =+SUM(G69:G74) -> 9305 | H75: =+SUM(H69:H74) -> 9487 | I75: =+SUM(I69:I74) -> 24321 | J75: =+SUM(J69:J74) -> 19465 | K75: =+SUM(K69:K74) -> 23885 | ... AI75: =+SUM(AI69:AI74) -> 26887.641 | AK75: =+SUM(AK69:AK74) -> 9305 | AL75: =+SUM(AL69:AL74) -> 23885 | AM75: =+SUM(AM69:AM74) -> 20891 | AN75: =+SUM(AN69:AN74) -> 19067 | AO75: =+SUM(AO69:AO74) -> 19015 | AP75: =+SUM(AP69:AP74) -> 18404 | AQ75: =+SUM(AQ69:AQ74) -> 20285.235 | AR75: =+SUM(AR69:AR74) -> 26887.641 | AS75: =+SUM(AS69:AS74) -> 31038.426
B76: Property and equipment, net | D76: ='3FS'!K73 -> 21464 | E76: ='3FS'!L73 -> 21847 | F76: ='3FS'!M73 -> 22098 | G76: ='3FS'!N73 -> 21984 | H76: ='3FS'!O73 -> 22149 | I76: ='3FS'!P73 -> 38801 | J76: ='3FS'!Q73 -> 38567 | K76: ='3FS'!R73 -> 41175 | ... AD76: ='3FS'!AK73 -> 38718 | AE76: =+'BS Drivers'!AE47 -> 37585.235 | AF76: =+'BS Drivers'!AF47 -> 36439.382 | AG76: =+'BS Drivers'!AG47 -> 35450.659 | AH76: =+'BS Drivers'!AH47 -> 34589.33 | AI76: =+'BS Drivers'!AI47 -> 33838.887 | AK76: ='3FS'!D73 -> 21984 | AL76: ='3FS'!E73 -> 41175 | AM76: ='3FS'!F73 -> 39803 | AN76: ='3FS'!G73 -> 42086 | AO76: ='3FS'!H73 -> 40432 | AP76: ='3FS'!I73 -> 38533 | AQ76: =SUMIFS($F76:$AI76,$F$3:$AI$3,AQ$3,$F$2:$AI$2,4) -> 37585.235 | AR76: =SUMIFS($F76:$AI76,$F$3:$AI$3,AR$3,$F$2:$AI$2,4) -> 33838.887 | AS76: =+'BS Drivers'!AS47 -> 30007.908
B77: Operating lease right-of-use assets | D77: ='3FS'!K74 -> 9509 | E77: ='3FS'!L74 -> 10439 | F77: ='3FS'!M74 -> 10914 | G77: ='3FS'!N74 -> 10933 | H77: ='3FS'!O74 -> 10956 | I77: ='3FS'!P74 -> 17246 | J77: ='3FS'!Q74 -> 27999 | K77: ='3FS'!R74 -> 28021 | ... AD77: ='3FS'!AK74 -> 26070 | AE77: =+'BS Drivers'!AE119 -> 26969.97 | AF77: =+'BS Drivers'!AF119 -> 25801.608 | AG77: =+'BS Drivers'!AG119 -> 24589.387 | AH77: =+'BS Drivers'!AH119 -> 26020.107 | AI77: =+'BS Drivers'!AI119 -> 26996.866 | AK77: ='3FS'!D74 -> 10933 | AL77: ='3FS'!E74 -> 28021 | AM77: ='3FS'!F74 -> 26959 | AN77: ='3FS'!G74 -> 28715 | AO77: ='3FS'!H74 -> 27135 | AP77: ='3FS'!I74 -> 25398 | AQ77: =SUMIFS($F77:$AI77,$F$3:$AI$3,AQ$3,$F$2:$AI$2,4) -> 26969.97 | AR77: =SUMIFS($F77:$AI77,$F$3:$AI$3,AR$3,$F$2:$AI$2,4) -> 26996.866 | AS77: =+'BS Drivers'!AS119 -> 26289.657
B78: Financing lease right-of-use assets | D78: ='3FS'!K75 -> 2339 | E78: ='3FS'!L75 -> 2589 | F78: ='3FS'!M75 -> 2855 | G78: ='3FS'!N75 -> 2715 | H78: ='3FS'!O75 -> 2749 | I78: ='3FS'!P75 -> 3288 | J78: ='3FS'!Q75 -> 3038 | K78: ='3FS'!R75 -> 3028 | ... AD78: ='3FS'!AK75 -> 2955 | AE78: =+'BS Drivers'!AE49 -> 2962.1068 | AF78: =+'BS Drivers'!AF49 -> 2975.9763 | AG78: =+'BS Drivers'!AG49 -> 2997.3839 | AH78: =+'BS Drivers'!AH49 -> 3022.9234 | AI78: =+'BS Drivers'!AI49 -> 3051.3194 | AK78: ='3FS'!D75 -> 2715 | AL78: ='3FS'!E75 -> 3028 | AM78: ='3FS'!F75 -> 3322 | AN78: ='3FS'!G75 -> 3257 | AO78: ='3FS'!H75 -> 3270 | AP78: ='3FS'!I75 -> 3091 | AQ78: =SUMIFS($F78:$AI78,$F$3:$AI$3,AQ$3,$F$2:$AI$2,4) -> 2962.1068 | AR78: =SUMIFS($F78:$AI78,$F$3:$AI$3,AR$3,$F$2:$AI$2,4) -> 3051.3194 | AS78: =+'BS Drivers'!AS49 -> 3179.2927
B79: Goodwill | D79: ='3FS'!K76 -> 1901 | E79: ='3FS'!L76 -> 1901 | F79: ='3FS'!M76 -> 1930 | G79: ='3FS'!N76 -> 1930 | H79: ='3FS'!O76 -> 1930 | I79: ='3FS'!P76 -> 10910 | J79: ='3FS'!Q76 -> 10906 | K79: ='3FS'!R76 -> 11117 | ... AD79: ='3FS'!AK76 -> 13690 | AE79: =+AD79 -> 13690 | AF79: =+AE79 -> 13690 | AG79: =+AF79 -> 13690 | AH79: =+AG79 -> 13690 | AI79: =+AH79 -> 13690 | AK79: ='3FS'!D76 -> 1930 | AL79: ='3FS'!E76 -> 11117 | AM79: ='3FS'!F76 -> 12188 | AN79: ='3FS'!G76 -> 12234 | AO79: ='3FS'!H76 -> 12234 | AP79: ='3FS'!I76 -> 13005 | AQ79: =SUMIFS($F79:$AI79,$F$3:$AI$3,AQ$3,$F$2:$AI$2,4) -> 13690 | AR79: =SUMIFS($F79:$AI79,$F$3:$AI$3,AR$3,$F$2:$AI$2,4) -> 13690 | AS79: =+AR79 -> 13690
B80: Spectrum licenses | D80: ='3FS'!K77 -> 35618 | E80: ='3FS'!L77 -> 36430 | F80: ='3FS'!M77 -> 36442 | G80: ='3FS'!N77 -> 36465 | H80: ='3FS'!O77 -> 36471 | I80: ='3FS'!P77 -> 82870 | J80: ='3FS'!Q77 -> 82891 | K80: ='3FS'!R77 -> 82828 | ... AD80: ='3FS'!AK77 -> 97749 | AE80: =+'BS Drivers'!AE61 -> 99303.702 | AF80: =+'BS Drivers'!AF61 -> 100883.13 | AG80: =+'BS Drivers'!AG61 -> 102487.68 | AH80: =+'BS Drivers'!AH61 -> 104117.75 | AI80: =+'BS Drivers'!AI61 -> 105773.75 | AK80: ='3FS'!D77 -> 36465 | AL80: ='3FS'!E77 -> 82828 | AM80: ='3FS'!F77 -> 92606 | AN80: ='3FS'!G77 -> 95798 | AO80: ='3FS'!H77 -> 96707 | AP80: ='3FS'!I77 -> 100558 | AQ80: =SUMIFS($F80:$AI80,$F$3:$AI$3,AQ$3,$F$2:$AI$2,4) -> 99303.702 | AR80: =SUMIFS($F80:$AI80,$F$3:$AI$3,AR$3,$F$2:$AI$2,4) -> 105773.75 | AS80: =+'BS Drivers'!AS61 -> 112665.35
B81: Other intangible assets, net | D81: ='3FS'!K78 -> 174 | E81: ='3FS'!L78 -> 157 | F81: ='3FS'!M78 -> 144 | G81: ='3FS'!N78 -> 115 | H81: ='3FS'!O78 -> 91 | I81: ='3FS'!P78 -> 6038 | J81: ='3FS'!Q78 -> 5660 | K81: ='3FS'!R78 -> 5298 | ... AD81: ='3FS'!AK78 -> 4117 | AE81: =+'BS Drivers'!AE63 -> 4182.4811 | AF81: =+'BS Drivers'!AF63 -> 4249.0036 | AG81: =+'BS Drivers'!AG63 -> 4316.5842 | AH81: =+'BS Drivers'!AH63 -> 4385.2396 | AI81: =+'BS Drivers'!AI63 -> 4454.987 | AK81: ='3FS'!D78 -> 115 | AL81: ='3FS'!E78 -> 5298 | AM81: ='3FS'!F78 -> 4733 | AN81: ='3FS'!G78 -> 3508 | AO81: ='3FS'!H78 -> 2618 | AP81: ='3FS'!I78 -> 2512 | AQ81: =SUMIFS($F81:$AI81,$F$3:$AI$3,AQ$3,$F$2:$AI$2,4) -> 4182.4811 | AR81: =SUMIFS($F81:$AI81,$F$3:$AI$3,AR$3,$F$2:$AI$2,4) -> 4454.987 | AS81: =+'BS Drivers'!AS63 -> 4745.2479
