Workbook

Sheet Domestic 2025
A1: Rank | B1: Movie | C1: Release Date | D1: Distributor | E1: Genre | F1: 2025 Gross ($M) | G1: Tickets Sold | H1: Title (base) | I1: Row Labels | J1: Sum of 2025 Gross ($M) | K1: NormTitle | L1: Studio | M1: 2025 Box Office Gross ($M) | N1: StudioClean
A2: 1 | B2: A Minecraft Movie | C2: 45751 | D2: Warner Bros. | E2: Adventure | F2: 424087780 | G2: 35458844 | H2: =IFERROR(TRIM(LEFT(B2,FIND("(",B2)-1)),TRIM(B2)) -> A Minecraft Movie | I2: Walt Disney | J2: 1965890585 | K2: =SUBSTITUTE(SUBSTITUTE(SUBSTITUTE(SUBSTITUTE(SUBSTITUTE(SUBSTITUTE(SUBSTITUTE(SUBSTITUTE(SUBSTITUTE(SUBSTITUTE(SUBSTITUTE(SUBSTITUTE(LOWER(LEFT(SUBSTITUTE(H2,"…",""),25)),":",""),",",""),".",""),"'",""),"’",""),"!",""),"*",""),"—",""),"–",""),"-",""),"&","")," ","") -> aminecraftmovie | L2: =I2 -> Walt Disney | M2: =J2 -> 1965890585 | N2: =IF(D2="","Other",D2) -> Warner Bros.
A3: 2 | B3: Lilo & Stitch | C3: 45800 | D3: Walt Disney | E3: Adventure | F3: 423778855 | G3: 35433015 | H3: =IFERROR(TRIM(LEFT(B3,FIND("(",B3)-1)),TRIM(B3)) -> Lilo & Stitch | I3: Warner Bros. | J3: 1891341005 | K3: =SUBSTITUTE(SUBSTITUTE(SUBSTITUTE(SUBSTITUTE(SUBSTITUTE(SUBSTITUTE(SUBSTITUTE(SUBSTITUTE(SUBSTITUTE(SUBSTITUTE(SUBSTITUTE(SUBSTITUTE(LOWER(LEFT(SUBSTITUTE(H3,"…",""),25)),":",""),",",""),".",""),"'",""),"’",""),"!",""),"*",""),"—",""),"–",""),"-",""),"&","")," ","") -> lilostitch | L3: =I3 -> Warner Bros. | M3: =J3 -> 1891341005 | N3: =IF(D3="","Other",D3) -> Walt Disney
A4: 3 | B4: Superman | C4: 45849 | D4: Warner Bros. | E4: Action | F4: 354223803 | G4: 29617375 | H4: =IFERROR(TRIM(LEFT(B4,FIND("(",B4)-1)),TRIM(B4)) -> Superman | I4: Universal | J4: 1571343617 | K4: =SUBSTITUTE(SUBSTITUTE(SUBSTITUTE(SUBSTITUTE(SUBSTITUTE(SUBSTITUTE(SUBSTITUTE(SUBSTITUTE(SUBSTITUTE(SUBSTITUTE(SUBSTITUTE(SUBSTITUTE(LOWER(LEFT(SUBSTITUTE(H4,"…",""),25)),":",""),",",""),".",""),"'",""),"’",""),"!",""),"*",""),"—",""),"–",""),"-",""),"&","")," ","") -> superman | L4: =I4 -> Universal | M4: =J4 -> 1571343617 | N4: =IF(D4="","Other",D4) -> Warner Bros.
A5: 4 | B5: Jurassic World Rebirth | C5: 45840 | D5: Universal | E5: Action | F5: 339640400 | G5: 28398027 | H5: =IFERROR(TRIM(LEFT(B5,FIND("(",B5)-1)),TRIM(B5)) -> Jurassic World Rebirth | I5: Paramount Pictures | J5: 563517149 | K5: =SUBSTITUTE(SUBSTITUTE(SUBSTITUTE(SUBSTITUTE(SUBSTITUTE(SUBSTITUTE(SUBSTITUTE(SUBSTITUTE(SUBSTITUTE(SUBSTITUTE(SUBSTITUTE(SUBSTITUTE(LOWER(LEFT(SUBSTITUTE(H5,"…",""),25)),":",""),",",""),".",""),"'",""),"’",""),"!",""),"*",""),"—",""),"–",""),"-",""),"&","")," ","") -> jurassicworldrebirth | L5: =I5 -> Paramount Pictures | M5: =J5 -> 563517149 | N5: =IF(D5="","Other",D5) -> Universal
A6: 5 | B6: Zootopia 2 | C6: 45987 | D6: Walt Disney | E6: Adventure | F6: 337903155 | G6: 28252772 | H6: =IFERROR(TRIM(LEFT(B6,FIND("(",B6)-1)),TRIM(B6)) -> Zootopia 2 | I6: Sony Pictures | J6: 556796407 | K6: =SUBSTITUTE(SUBSTITUTE(SUBSTITUTE(SUBSTITUTE(SUBSTITUTE(SUBSTITUTE(SUBSTITUTE(SUBSTITUTE(SUBSTITUTE(SUBSTITUTE(SUBSTITUTE(SUBSTITUTE(LOWER(LEFT(SUBSTITUTE(H6,"…",""),25)),":",""),",",""),".",""),"'",""),"’",""),"!",""),"*",""),"—",""),"–",""),"-",""),"&","")," ","") -> zootopia2 | L6: =I6 -> Sony Pictures | M6: =J6 -> 556796407 | N6: =IF(D6="","Other",D6) -> Walt Disney
A7: 6 | B7: Wicked: For Good | C7: 45982 | D7: Universal | E7: Musical | F7: 335438675 | G7: 28046712 | H7: =IFERROR(TRIM(LEFT(B7,FIND("(",B7)-1)),TRIM(B7)) -> Wicked: For Good | I7: 20th Century Stud… | J7: 452223943 | K7: =SUBSTITUTE(SUBSTITUTE(SUBSTITUTE(SUBSTITUTE(SUBSTITUTE(SUBSTITUTE(SUBSTITUTE(SUBSTITUTE(SUBSTITUTE(SUBSTITUTE(SUBSTITUTE(SUBSTITUTE(LOWER(LEFT(SUBSTITUTE(H7,"…",""),25)),":",""),",",""),".",""),"'",""),"’",""),"!",""),"*",""),"—",""),"–",""),"-",""),"&","")," ","") -> wickedforgood | L7: =I7 -> 20th Century Stud… | M7: =J7 -> 452223943 | N7: =IF(D7="","Other",D7) -> Universal
A8: 7 | B8: Sinners | C8: 45765 | D8: Warner Bros. | E8: Horror | F8: 279989632 | G8: 23410504 | H8: =IFERROR(TRIM(LEFT(B8,FIND("(",B8)-1)),TRIM(B8)) -> Sinners | I8: Lionsgate | J8: 331288139 | K8: =SUBSTITUTE(SUBSTITUTE(SUBSTITUTE(SUBSTITUTE(SUBSTITUTE(SUBSTITUTE(SUBSTITUTE(SUBSTITUTE(SUBSTITUTE(SUBSTITUTE(SUBSTITUTE(SUBSTITUTE(LOWER(LEFT(SUBSTITUTE(H8,"…",""),25)),":",""),",",""),".",""),"'",""),"’",""),"!",""),"*",""),"—",""),"–",""),"-",""),"&","")," ","") -> sinners | L8: =I8 -> Lionsgate | M8: =J8 -> 331288139 | N8: =IF(D8="","Other",D8) -> Warner Bros.
A9: 8 | B9: The Fantastic Four: First Ste… | C9: 45863 | D9: Walt Disney | E9: Action | F9: 274286610 | G9: 22933663 | H9: =IFERROR(TRIM(LEFT(B9,FIND("(",B9)-1)),TRIM(B9)) -> The Fantastic Four: First Ste… | I9: A24 | J9: 231026707 | K9: =SUBSTITUTE(SUBSTITUTE(SUBSTITUTE(SUBSTITUTE(SUBSTITUTE(SUBSTITUTE(SUBSTITUTE(SUBSTITUTE(SUBSTITUTE(SUBSTITUTE(SUBSTITUTE(SUBSTITUTE(LOWER(LEFT(SUBSTITUTE(H9,"…",""),25)),":",""),",",""),".",""),"'",""),"’",""),"!",""),"*",""),"—",""),"–",""),"-",""),"&","")," ","") -> thefantasticfourfirst | L9: =I9 -> A24 | M9: =J9 -> 231026707 | N9: =IF(D9="","Other",D9) -> Walt Disney
A10: 9 | B10: How to Train Your Dragon | C10: 45821 | D10: Universal | E10: Adventure | F10: 262958100 | G10: 21986463 | H10: =IFERROR(TRIM(LEFT(B10,FIND("(",B10)-1)),TRIM(B10)) -> How to Train Your Dragon | I10: Focus Features | J10: 217958718 | K10: =SUBSTITUTE(SUBSTITUTE(SUBSTITUTE(SUBSTITUTE(SUBSTITUTE(SUBSTITUTE(SUBSTITUTE(SUBSTITUTE(SUBSTITUTE(SUBSTITUTE(SUBSTITUTE(SUBSTITUTE(LOWER(LEFT(SUBSTITUTE(H10,"…",""),25)),":",""),",",""),".",""),"'",""),"’",""),"!",""),"*",""),"—",""),"–",""),"-",""),"&","")," ","") -> howtotrainyourdragon | L10: Other | M10: =J132-SUM(M2:M9) -> 1152634501 | N10: =IF(D10="","Other",D10) -> Universal
A11: 10 | B11: Avatar: Fire and Ash | C11: 46010 | D11: 20th Century Stud… | E11: Action | F11: 250353869 | G11: 20932598 | H11: =IFERROR(TRIM(LEFT(B11,FIND("(",B11)-1)),TRIM(B11)) -> Avatar: Fire and Ash | I11: Angel Studios | J11: 167944327 | K11: =SUBSTITUTE(SUBSTITUTE(SUBSTITUTE(SUBSTITUTE(SUBSTITUTE(SUBSTITUTE(SUBSTITUTE(SUBSTITUTE(SUBSTITUTE(SUBSTITUTE(SUBSTITUTE(SUBSTITUTE(LOWER(LEFT(SUBSTITUTE(H11,"…",""),25)),":",""),",",""),".",""),"'",""),"’",""),"!",""),"*",""),"—",""),"–",""),"-",""),"&","")," ","") -> avatarfireandash | L11: Grand Total | M11: =SUM(M2:M10) -> 8716062053 | N11: =IF(D11="","Other",D11) -> 20th Century Stud…
A12: 11 | B12: Captain America: Brave New Wo… | C12: 45702 | D12: Walt Disney | E12: Action | F12: 200500001 | G12: 16764214 | H12: =IFERROR(TRIM(LEFT(B12,FIND("(",B12)-1)),TRIM(B12)) -> Captain America: Brave New Wo… | I12: Amazon MGM Studios | J12: 123549330 | K12: =SUBSTITUTE(SUBSTITUTE(SUBSTITUTE(SUBSTITUTE(SUBSTITUTE(SUBSTITUTE(SUBSTITUTE(SUBSTITUTE(SUBSTITUTE(SUBSTITUTE(SUBSTITUTE(SUBSTITUTE(LOWER(LEFT(SUBSTITUTE(H12,"…",""),25)),":",""),",",""),".",""),"'",""),"’",""),"!",""),"*",""),"—",""),"–",""),"-",""),"&","")," ","") -> captainamericabravene | N12: =IF(D12="","Other",D12) -> Walt Disney
A13: 12 | B13: Mission: Impossible—The Final… | C13: 45800 | D13: Paramount Pictures | E13: Action | F13: 197413515 | G13: 16506147 | H13: =IFERROR(TRIM(LEFT(B13,FIND("(",B13)-1)),TRIM(B13)) -> Mission: Impossible—The Final… | I13: Neon | J13: 104352652 | K13: =SUBSTITUTE(SUBSTITUTE(SUBSTITUTE(SUBSTITUTE(SUBSTITUTE(SUBSTITUTE(SUBSTITUTE(SUBSTITUTE(SUBSTITUTE(SUBSTITUTE(SUBSTITUTE(SUBSTITUTE(LOWER(LEFT(SUBSTITUTE(H13,"…",""),25)),":",""),",",""),".",""),"'",""),"’",""),"!",""),"*",""),"—",""),"–",""),"-",""),"&","")," ","") -> missionimpossiblethef | N13: =IF(D13="","Other",D13) -> Paramount Pictures
A14: 13 | B14: Thunderbolts* | C14: 45779 | D14: Walt Disney | E14: Action | F14: 190274328 | G14: 15909225 | H14: =IFERROR(TRIM(LEFT(B14,FIND("(",B14)-1)),TRIM(B14)) -> Thunderbolts* | I14: Searchlight Pictu… | J14: 73377390 | K14: =SUBSTITUTE(SUBSTITUTE(SUBSTITUTE(SUBSTITUTE(SUBSTITUTE(SUBSTITUTE(SUBSTITUTE(SUBSTITUTE(SUBSTITUTE(SUBSTITUTE(SUBSTITUTE(SUBSTITUTE(LOWER(LEFT(SUBSTITUTE(H14,"…",""),25)),":",""),",",""),".",""),"'",""),"’",""),"!",""),"*",""),"—",""),"–",""),"-",""),"&","")," ","") -> thunderbolts | N14: =IF(D14="","Other",D14) -> Walt Disney
A15: 14 | B15: F1: The Movie | C15: 45835 | D15: Warner Bros. | E15: Action | F15: 189642436 | G15: 15856391 | H15: =IFERROR(TRIM(LEFT(B15,FIND("(",B15)-1)),TRIM(B15)) -> F1: The Movie | I15: Fathom Entertainm… | J15: 52321724 | K15: =SUBSTITUTE(SUBSTITUTE(SUBSTITUTE(SUBSTITUTE(SUBSTITUTE(SUBSTITUTE(SUBSTITUTE(SUBSTITUTE(SUBSTITUTE(SUBSTITUTE(SUBSTITUTE(SUBSTITUTE(LOWER(LEFT(SUBSTITUTE(H15,"…",""),25)),":",""),",",""),".",""),"'",""),"’",""),"!",""),"*",""),"—",""),"–",""),"-",""),"&","")," ","") -> f1themovie | N15: =IF(D15="","Other",D15) -> Warner Bros.
A16: 15 | B16: The Conjuring: Last Rites | C16: 45905 | D16: Warner Bros. | E16: Horror | F16: 177756445 | G16: 14862579 | H16: =IFERROR(TRIM(LEFT(B16,FIND("(",B16)-1)),TRIM(B16)) -> The Conjuring: Last Rites | I16: Sony Pictures Cla… | J16: 49945605 | K16: =SUBSTITUTE(SUBSTITUTE(SUBSTITUTE(SUBSTITUTE(SUBSTITUTE(SUBSTITUTE(SUBSTITUTE(SUBSTITUTE(SUBSTITUTE(SUBSTITUTE(SUBSTITUTE(SUBSTITUTE(LOWER(LEFT(SUBSTITUTE(H16,"…",""),25)),":",""),",",""),".",""),"'",""),"’",""),"!",""),"*",""),"—",""),"–",""),"-",""),"&","")," ","") -> theconjuringlastrites | N16: =IF(D16="","Other",D16) -> Warner Bros.
A17: 16 | B17: Weapons | C17: 45877 | D17: Warner Bros. | E17: Horror | F17: 151572492 | G17: 12673285 | H17: =IFERROR(TRIM(LEFT(B17,FIND("(",B17)-1)),TRIM(B17)) -> Weapons | I17: GKIDS | J17: 45341684 | K17: =SUBSTITUTE(SUBSTITUTE(SUBSTITUTE(SUBSTITUTE(SUBSTITUTE(SUBSTITUTE(SUBSTITUTE(SUBSTITUTE(SUBSTITUTE(SUBSTITUTE(SUBSTITUTE(SUBSTITUTE(LOWER(LEFT(SUBSTITUTE(H17,"…",""),25)),":",""),",",""),".",""),"'",""),"’",""),"!",""),"*",""),"—",""),"–",""),"-",""),"&","")," ","") -> weapons | N17: =IF(D17="","Other",D17) -> Warner Bros.
A18: 17 | B18: Final Destination: Bloodlines | C18: 45793 | D18: Warner Bros. | E18: Horror | F18: 138254739 | G18: 11559761 | H18: =IFERROR(TRIM(LEFT(B18,FIND("(",B18)-1)),TRIM(B18)) -> Final Destination: Bloodlines | I18: AMC Theatres Dist… | J18: 34062774 | K18: =SUBSTITUTE(SUBSTITUTE(SUBSTITUTE(SUBSTITUTE(SUBSTITUTE(SUBSTITUTE(SUBSTITUTE(SUBSTITUTE(SUBSTITUTE(SUBSTITUTE(SUBSTITUTE(SUBSTITUTE(LOWER(LEFT(SUBSTITUTE(H18,"…",""),25)),":",""),",",""),".",""),"'",""),"’",""),"!",""),"*",""),"—",""),"–",""),"-",""),"&","")," ","") -> finaldestinationbloodl | N18: =IF(D18="","Other",D18) -> Warner Bros.
A19: 18 | B19: Demon Slayer -Kimetsu no Yaib… | C19: 45912 | D19: Sony Pictures | E19: Action | F19: 134487320 | G19: 11244759 | H19: =IFERROR(TRIM(LEFT(B19,FIND("(",B19)-1)),TRIM(B19)) -> Demon Slayer -Kimetsu no Yaib… | I19: Netflix | J19: 26800000 | K19: =SUBSTITUTE(SUBSTITUTE(SUBSTITUTE(SUBSTITUTE(SUBSTITUTE(SUBSTITUTE(SUBSTITUTE(SUBSTITUTE(SUBSTITUTE(SUBSTITUTE(SUBSTITUTE(SUBSTITUTE(LOWER(LEFT(SUBSTITUTE(H19,"…",""),25)),":",""),",",""),".",""),"'",""),"’",""),"!",""),"*",""),"—",""),"–",""),"-",""),"&","")," ","") -> demonslayerkimetsuno | N19: =IF(D19="","Other",D19) -> Sony Pictures
A20: 19 | B20: Mufasa: The Lion King | C20: 45646 | D20: Walt Disney | E20: Musical | F20: 126423748 | G20: 10570547 | H20: =IFERROR(TRIM(LEFT(B20,FIND("(",B20)-1)),TRIM(B20)) -> Mufasa: The Lion King | I20: (blank) | J20: 25925670 | K20: =SUBSTITUTE(SUBSTITUTE(SUBSTITUTE(SUBSTITUTE(SUBSTITUTE(SUBSTITUTE(SUBSTITUTE(SUBSTITUTE(SUBSTITUTE(SUBSTITUTE(SUBSTITUTE(SUBSTITUTE(LOWER(LEFT(SUBSTITUTE(H20,"…",""),25)),":",""),",",""),".",""),"'",""),"’",""),"!",""),"*",""),"—",""),"–",""),"-",""),"&","")," ","") -> mufasathelionking | N20: =IF(D20="","Other",D20) -> Walt Disney
A21: 20 | B21: Five Nights at Freddy’s 2 | C21: 45996 | D21: Universal | E21: Horror | F21: 121680315 | G21: 10173939 | H21: =IFERROR(TRIM(LEFT(B21,FIND("(",B21)-1)),TRIM(B21)) -> Five Nights at Freddy’s 2 | I21: Yash Raj Films | J21: 25359370 | K21: =SUBSTITUTE(SUBSTITUTE(SUBSTITUTE(SUBSTITUTE(SUBSTITUTE(SUBSTITUTE(SUBSTITUTE(SUBSTITUTE(SUBSTITUTE(SUBSTITUTE(SUBSTITUTE(SUBSTITUTE(LOWER(LEFT(SUBSTITUTE(H21,"…",""),25)),":",""),",",""),".",""),"'",""),"’",""),"!",""),"*",""),"—",""),"–",""),"-",""),"&","")," ","") -> fivenightsatfreddys2 | N21: =IF(D21="","Other",D21) -> Universal
A22: 21 | B22: Dog Man | C22: 45688 | D22: Universal | E22: Adventure | F22: 97970355 | G22: 8191501 | H22: =IFERROR(TRIM(LEFT(B22,FIND("(",B22)-1)),TRIM(B22)) -> Dog Man | I22: Roadside Attracti… | J22: 15690190 | K22: =SUBSTITUTE(SUBSTITUTE(SUBSTITUTE(SUBSTITUTE(SUBSTITUTE(SUBSTITUTE(SUBSTITUTE(SUBSTITUTE(SUBSTITUTE(SUBSTITUTE(SUBSTITUTE(SUBSTITUTE(LOWER(LEFT(SUBSTITUTE(H22,"…",""),25)),":",""),",",""),".",""),"'",""),"’",""),"!",""),"*",""),"—",""),"–",""),"-",""),"&","")," ","") -> dogman | N22: =IF(D22="","Other",D22) -> Universal
A23: 22 | B23: Freakier Friday | C23: 45877 | D23: Walt Disney | E23: Comedy | F23: 94186236 | G23: 7875103 | H23: =IFERROR(TRIM(LEFT(B23,FIND("(",B23)-1)),TRIM(B23)) -> Freakier Friday | I23: Bleecker Street | J23: 15424862 | K23: =SUBSTITUTE(SUBSTITUTE(SUBSTITUTE(SUBSTITUTE(SUBSTITUTE(SUBSTITUTE(SUBSTITUTE(SUBSTITUTE(SUBSTITUTE(SUBSTITUTE(SUBSTITUTE(SUBSTITUTE(LOWER(LEFT(SUBSTITUTE(H23,"…",""),25)),":",""),",",""),".",""),"'",""),"’",""),"!",""),"*",""),"—",""),"–",""),"-",""),"&","")," ","") -> freakierfriday | N23: =IF(D23="","Other",D23) -> Walt Disney
... A71: 70 | B71: M3GAN 2.0 | C71: 45835 | D71: Universal | E71: Horror | F71: 24101280 | G71: 2015157 | H71: =IFERROR(TRIM(LEFT(B71,FIND("(",B71)-1)),TRIM(B71)) -> M3GAN 2.0 | I71: Samuel Goldwyn Fi… | J71: 508403 | K71: =SUBSTITUTE(SUBSTITUTE(SUBSTITUTE(SUBSTITUTE(SUBSTITUTE(SUBSTITUTE(SUBSTITUTE(SUBSTITUTE(SUBSTITUTE(SUBSTITUTE(SUBSTITUTE(SUBSTITUTE(LOWER(LEFT(SUBSTITUTE(H71,"…",""),25)),":",""),",",""),".",""),"'",""),"’",""),"!",""),"*",""),"—",""),"–",""),"-",""),"&","")," ","") -> m3gan20 | N71: =IF(D71="","Other",D71) -> Universal
A72: 71 | B72: Ne Zha 2 (哪吒之魔童闹海) | C72: 45702 | E72: Action | F72: 23251218 | G72: 1944082 | H72: =IFERROR(TRIM(LEFT(B72,FIND("(",B72)-1)),TRIM(B72)) -> Ne Zha 2 | I72: Indican Pictures | J72: 444656 | K72: =SUBSTITUTE(SUBSTITUTE(SUBSTITUTE(SUBSTITUTE(SUBSTITUTE(SUBSTITUTE(SUBSTITUTE(SUBSTITUTE(SUBSTITUTE(SUBSTITUTE(SUBSTITUTE(SUBSTITUTE(LOWER(LEFT(SUBSTITUTE(H72,"…",""),25)),":",""),",",""),".",""),"'",""),"’",""),"!",""),"*",""),"—",""),"–",""),"-",""),"&","")," ","") -> nezha2 | N72: =IF(D72="","Other",D72) -> Other
A73: 72 | B73: Roofman | C73: 45940 | D73: Paramount Pictures | E73: Black Comedy | F73: 22739882 | G73: 1901328 | H73: =IFERROR(TRIM(LEFT(B73,FIND("(",B73)-1)),TRIM(B73)) -> Roofman | I73: 8 Above | J73: 388141 | K73: =SUBSTITUTE(SUBSTITUTE(SUBSTITUTE(SUBSTITUTE(SUBSTITUTE(SUBSTITUTE(SUBSTITUTE(SUBSTITUTE(SUBSTITUTE(SUBSTITUTE(SUBSTITUTE(SUBSTITUTE(LOWER(LEFT(SUBSTITUTE(H73,"…",""),25)),":",""),",",""),".",""),"'",""),"’",""),"!",""),"*",""),"—",""),"–",""),"-",""),"&","")," ","") -> roofman | N73: =IF(D73="","Other",D73) -> Paramount Pictures
A74: 73 | B74: Springsteen: Deliver Me From … | C74: 45954 | D74: 20th Century Stud… | E74: Drama | F74: 22638297 | G74: 1892834 | H74: =IFERROR(TRIM(LEFT(B74,FIND("(",B74)-1)),TRIM(B74)) -> Springsteen: Deliver Me From … | I74: FUNimation | J74: 383542 | K74: =SUBSTITUTE(SUBSTITUTE(SUBSTITUTE(SUBSTITUTE(SUBSTITUTE(SUBSTITUTE(SUBSTITUTE(SUBSTITUTE(SUBSTITUTE(SUBSTITUTE(SUBSTITUTE(SUBSTITUTE(LOWER(LEFT(SUBSTITUTE(H74,"…",""),25)),":",""),",",""),".",""),"'",""),"’",""),"!",""),"*",""),"—",""),"–",""),"-",""),"&","")," ","") -> springsteendelivermef | N74: =IF(D74="","Other",D74) -> 20th Century Stud…
A75: 74 | B75: The Woman in the Yard | C75: 45744 | D75: Universal | E75: Horror | F75: 22405985 | G75: 1873410 | H75: =IFERROR(TRIM(LEFT(B75,FIND("(",B75)-1)),TRIM(B75)) -> The Woman in the Yard | I75: Republic Pictures | J75: 368186 | K75: =SUBSTITUTE(SUBSTITUTE(SUBSTITUTE(SUBSTITUTE(SUBSTITUTE(SUBSTITUTE(SUBSTITUTE(SUBSTITUTE(SUBSTITUTE(SUBSTITUTE(SUBSTITUTE(SUBSTITUTE(LOWER(LEFT(SUBSTITUTE(H75,"…",""),25)),":",""),",",""),".",""),"'",""),"’",""),"!",""),"*",""),"—",""),"–",""),"-",""),"&","")," ","") -> thewomanintheyard | N75: =IF(D75="","Other",D75) -> Universal
A76: 75 | B76: Nobody 2 | C76: 45884 | D76: Universal | E76: Thriller/Suspense | F76: 21604985 | G76: 1806437 | H76: =IFERROR(TRIM(LEFT(B76,FIND("(",B76)-1)),TRIM(B76)) -> Nobody 2 | I76: Shudder | J76: 308555 | K76: =SUBSTITUTE(SUBSTITUTE(SUBSTITUTE(SUBSTITUTE(SUBSTITUTE(SUBSTITUTE(SUBSTITUTE(SUBSTITUTE(SUBSTITUTE(SUBSTITUTE(SUBSTITUTE(SUBSTITUTE(LOWER(LEFT(SUBSTITUTE(H76,"…",""),25)),":",""),",",""),".",""),"'",""),"’",""),"!",""),"*",""),"—",""),"–",""),"-",""),"&","")," ","") -> nobody2 | N76: =IF(D76="","Other",D76) -> Universal
A77: 76 | B77: Black Bag | C77: 45730 | D77: Focus Features | E77: Thriller/Suspense | F77: 21474035 | G77: 1795488 | H77: =IFERROR(TRIM(LEFT(B77,FIND("(",B77)-1)),TRIM(B77)) -> Black Bag | I77: Miramax | J77: 272559 | K77: =SUBSTITUTE(SUBSTITUTE(SUBSTITUTE(SUBSTITUTE(SUBSTITUTE(SUBSTITUTE(SUBSTITUTE(SUBSTITUTE(SUBSTITUTE(SUBSTITUTE(SUBSTITUTE(SUBSTITUTE(LOWER(LEFT(SUBSTITUTE(H77,"…",""),25)),":",""),",",""),".",""),"'",""),"’",""),"!",""),"*",""),"—",""),"–",""),"-",""),"&","")," ","") -> blackbag | N77: =IF(D77="","Other",D77) -> Focus Features
A78: 77 | B78: Together | C78: 45868 | D78: Neon | E78: Horror | F78: 21273161 | G78: 1778692 | H78: =IFERROR(TRIM(LEFT(B78,FIND("(",B78)-1)),TRIM(B78)) -> Together | I78: SRH | J78: 243844 | K78: =SUBSTITUTE(SUBSTITUTE(SUBSTITUTE(SUBSTITUTE(SUBSTITUTE(SUBSTITUTE(SUBSTITUTE(SUBSTITUTE(SUBSTITUTE(SUBSTITUTE(SUBSTITUTE(SUBSTITUTE(LOWER(LEFT(SUBSTITUTE(H78,"…",""),25)),":",""),",",""),".",""),"'",""),"’",""),"!",""),"*",""),"—",""),"–",""),"-",""),"&","")," ","") -> together | N78: =IF(D78="","Other",D78) -> Neon
A79: 78 | B79: Last Breath | C79: 45716 | D79: Focus Features | E79: Thriller/Suspense | F79: 21051180 | G79: 1760132 | H79: =IFERROR(TRIM(LEFT(B79,FIND("(",B79)-1)),TRIM(B79)) -> Last Breath | I79: 1-2 Special | J79: 231031 | K79: =SUBSTITUTE(SUBSTITUTE(SUBSTITUTE(SUBSTITUTE(SUBSTITUTE(SUBSTITUTE(SUBSTITUTE(SUBSTITUTE(SUBSTITUTE(SUBSTITUTE(SUBSTITUTE(SUBSTITUTE(LOWER(LEFT(SUBSTITUTE(H79,"…",""),25)),":",""),",",""),".",""),"'",""),"’",""),"!",""),"*",""),"—",""),"–",""),"-",""),"&","")," ","") -> lastbreath | N79: =IF(D79="","Other",D79) -> Focus Features
A80: 79 | B80: Companion | C80: 45688 | D80: Warner Bros. | E80: Black Comedy | F80: 20869122 | G80: 1744910 | H80: =IFERROR(TRIM(LEFT(B80,FIND("(",B80)-1)),TRIM(B80)) -> Companion | I80: Cartuna | J80: 205882 | K80: =SUBSTITUTE(SUBSTITUTE(SUBSTITUTE(SUBSTITUTE(SUBSTITUTE(SUBSTITUTE(SUBSTITUTE(SUBSTITUTE(SUBSTITUTE(SUBSTITUTE(SUBSTITUTE(SUBSTITUTE(LOWER(LEFT(SUBSTITUTE(H80,"…",""),25)),":",""),",",""),".",""),"'",""),"’",""),"!",""),"*",""),"—",""),"–",""),"-",""),"&","")," ","") -> companion | N80: =IF(D80="","Other",D80) -> Warner Bros.
A81: 80 | B81: Wolf Man | C81: 45674 | D81: Universal | E81: Horror | F81: 20707280 | G81: 1731378 | H81: =IFERROR(TRIM(LEFT(B81,FIND("(",B81)-1)),TRIM(B81)) -> Wolf Man | I81: Atlas Distribution | J81: 197000 | K81: =SUBSTITUTE(SUBSTITUTE(SUBSTITUTE(SUBSTITUTE(SUBSTITUTE(SUBSTITUTE(SUBSTITUTE(SUBSTITUTE(SUBSTITUTE(SUBSTITUTE(SUBSTITUTE(SUBSTITUTE(LOWER(LEFT(SUBSTITUTE(H81,"…",""),25)),":",""),",",""),".",""),"'",""),"’",""),"!",""),"*",""),"—",""),"–",""),"-",""),"&","")," ","") -> wolfman | N81: =IF(D81="","Other",D81) -> Universal
A82: 81 | B82: The Chosen: Last Supper — Par… | C82: 45743 | D82: Fathom Entertainm… | E82: Drama | F82: 20257290 | G82: 1693753 | H82: =IFERROR(TRIM(LEFT(B82,FIND("(",B82)-1)),TRIM(B82)) -> The Chosen: Last Supper — Par… | I82: SDG Releasing | J82: 174932 | K82: =SUBSTITUTE(SUBSTITUTE(SUBSTITUTE(SUBSTITUTE(SUBSTITUTE(SUBSTITUTE(SUBSTITUTE(SUBSTITUTE(SUBSTITUTE(SUBSTITUTE(SUBSTITUTE(SUBSTITUTE(LOWER(LEFT(SUBSTITUTE(H82,"…",""),25)),":",""),",",""),".",""),"'",""),"’",""),"!",""),"*",""),"—",""),"–",""),"-",""),"&","")," ","") -> thechosenlastsupper | N82: =IF(D82="","Other",D82) -> Fathom Entertainm…
A83: 82 | B83: Until Dawn | C83: 45772 | D83: Sony Pictures | E83: Horror | F83: 20172192 | G83: 1686638 | H83: =IFERROR(TRIM(LEFT(B83,FIND("(",B83)-1)),TRIM(B83)) -> Until Dawn | I83: Seismic Releasing | J83: 172187 | K83: =SUBSTITUTE(SUBSTITUTE(SUBSTITUTE(SUBSTITUTE(SUBSTITUTE(SUBSTITUTE(SUBSTITUTE(SUBSTITUTE(SUBSTITUTE(SUBSTITUTE(SUBSTITUTE(SUBSTITUTE(LOWER(LEFT(SUBSTITUTE(H83,"…",""),25)),":",""),",",""),".",""),"'",""),"’",""),"!",""),"*",""),"—",""),"–",""),"-",""),"&","")," ","") -> untildawn | N83: =IF(D83="","Other",D83) -> Sony Pictures
A84: 83 | B84: Novocaine | C84: 45730 | D84: Paramount Pictures | E84: Action | F84: 19861854 | G84: 1660690 | H84: =IFERROR(TRIM(LEFT(B84,FIND("(",B84)-1)),TRIM(B84)) -> Novocaine | I84: Abramorama Films | J84: 163200 | K84: =SUBSTITUTE(SUBSTITUTE(SUBSTITUTE(SUBSTITUTE(SUBSTITUTE(SUBSTITUTE(SUBSTITUTE(SUBSTITUTE(SUBSTITUTE(SUBSTITUTE(SUBSTITUTE(SUBSTITUTE(LOWER(LEFT(SUBSTITUTE(H84,"…",""),25)),":",""),",",""),".",""),"'",""),"’",""),"!",""),"*",""),"—",""),"–",""),"-",""),"&","")," ","") -> novocaine | N84: =IF(D84="","Other",D84) -> Paramount Pictures
... A101: 100 | B101: The Strangers: Chapter 2 | C101: 45926 | D101: Lionsgate | E101: Horror | F101: 15153346 | G101: 1267002 | H101: =IFERROR(TRIM(LEFT(B101,FIND("(",B101)-1)),TRIM(B101)) -> The Strangers: Chapter 2 | I101: Lost and Found Fi… | J101: 67407 | K101: =SUBSTITUTE(SUBSTITUTE(SUBSTITUTE(SUBSTITUTE(SUBSTITUTE(SUBSTITUTE(SUBSTITUTE(SUBSTITUTE(SUBSTITUTE(SUBSTITUTE(SUBSTITUTE(SUBSTITUTE(LOWER(LEFT(SUBSTITUTE(H101,"…",""),25)),":",""),",",""),".",""),"'",""),"’",""),"!",""),"*",""),"—",""),"–",""),"-",""),"&","")," ","") -> thestrangerschapter2 | N101: =IF(D101="","Other",D101) -> Lionsgate
A102: 101 | B102: Warner Bros. Other Catalog | C102: 46022 | D102: Warner Bros. | F102: 14889055 | G102: 1244904 | H102: =IFERROR(TRIM(LEFT(B102,FIND("(",B102)-1)),TRIM(B102)) -> Warner Bros. Other Catalog | I102: Falling Forward F… | J102: 65182 | K102: =SUBSTITUTE(SUBSTITUTE(SUBSTITUTE(SUBSTITUTE(SUBSTITUTE(SUBSTITUTE(SUBSTITUTE(SUBSTITUTE(SUBSTITUTE(SUBSTITUTE(SUBSTITUTE(SUBSTITUTE(LOWER(LEFT(SUBSTITUTE(H102,"…",""),25)),":",""),",",""),".",""),"'",""),"’",""),"!",""),"*",""),"—",""),"–",""),"-",""),"&","")," ","") -> warnerbrosothercatalo | N102: =IF(D102="","Other",D102) -> Warner Bros.
A103: 102 | B103: Nuremberg | C103: 45968 | D103: Sony Pictures Cla… | E103: Drama | F103: 14296489 | G103: 1195359 | H103: =IFERROR(TRIM(LEFT(B103,FIND("(",B103)-1)),TRIM(B103)) -> Nuremberg | I103: MTV Documentary F… | J103: 60970 | K103: =SUBSTITUTE(SUBSTITUTE(SUBSTITUTE(SUBSTITUTE(SUBSTITUTE(SUBSTITUTE(SUBSTITUTE(SUBSTITUTE(SUBSTITUTE(SUBSTITUTE(SUBSTITUTE(SUBSTITUTE(LOWER(LEFT(SUBSTITUTE(H103,"…",""),25)),":",""),",",""),".",""),"'",""),"’",""),"!",""),"*",""),"—",""),"–",""),"-",""),"&","")," ","") -> nuremberg | N103: =IF(D103="","Other",D103) -> Sony Pictures Cla…
A104: 103 | B104: Jaws | C104: 27565 | D104: Universal | E104: Thriller/Suspense | F104: 13555185 | G104: 1133377 | H104: =IFERROR(TRIM(LEFT(B104,FIND("(",B104)-1)),TRIM(B104)) -> Jaws | I104: Circle Collective | J104: 53478 | K104: =SUBSTITUTE(SUBSTITUTE(SUBSTITUTE(SUBSTITUTE(SUBSTITUTE(SUBSTITUTE(SUBSTITUTE(SUBSTITUTE(SUBSTITUTE(SUBSTITUTE(SUBSTITUTE(SUBSTITUTE(LOWER(LEFT(SUBSTITUTE(H104,"…",""),25)),":",""),",",""),".",""),"'",""),"’",""),"!",""),"*",""),"—",""),"–",""),"-",""),"&","")," ","") -> jaws | N104: =IF(D104="","Other",D104) -> Universal
A105: 104 | B105: Death of a Unicorn | C105: 45744 | D105: A24 | E105: Black Comedy | F105: 12519487 | G105: 1046780 | H105: =IFERROR(TRIM(LEFT(B105,FIND("(",B105)-1)),TRIM(B105)) -> Death of a Unicorn | I105: Strand Releasing | J105: 49707 | K105: =SUBSTITUTE(SUBSTITUTE(SUBSTITUTE(SUBSTITUTE(SUBSTITUTE(SUBSTITUTE(SUBSTITUTE(SUBSTITUTE(SUBSTITUTE(SUBSTITUTE(SUBSTITUTE(SUBSTITUTE(LOWER(LEFT(SUBSTITUTE(H105,"…",""),25)),":",""),",",""),".",""),"'",""),"’",""),"!",""),"*",""),"—",""),"–",""),"-",""),"&","")," ","") -> deathofaunicorn | N105: =IF(D105="","Other",D105) -> A24
A106: 105 | B106: Dhurandhar | C106: 45996 | D106: Yash Raj Films | E106: Action | F106: 12400000 | G106: 1036789 | H106: =IFERROR(TRIM(LEFT(B106,FIND("(",B106)-1)),TRIM(B106)) -> Dhurandhar | I106: Picturehouse | J106: 49703 | K106: =SUBSTITUTE(SUBSTITUTE(SUBSTITUTE(SUBSTITUTE(SUBSTITUTE(SUBSTITUTE(SUBSTITUTE(SUBSTITUTE(SUBSTITUTE(SUBSTITUTE(SUBSTITUTE(SUBSTITUTE(LOWER(LEFT(SUBSTITUTE(H106,"…",""),25)),":",""),",",""),".",""),"'",""),"’",""),"!",""),"*",""),"—",""),"–",""),"-",""),"&","")," ","") -> dhurandhar | N106: =IF(D106="","Other",D106) -> Yash Raj Films
A107: 106 | B107: The Chosen: Last Supper — Par… | C107: 45751 | D107: Fathom Entertainm… | E107: Drama | F107: 12360095 | G107: 1033453 | H107: =IFERROR(TRIM(LEFT(B107,FIND("(",B107)-1)),TRIM(B107)) -> The Chosen: Last Supper — Par… | I107: Orion Pictures | J107: 46810 | K107: =SUBSTITUTE(SUBSTITUTE(SUBSTITUTE(SUBSTITUTE(SUBSTITUTE(SUBSTITUTE(SUBSTITUTE(SUBSTITUTE(SUBSTITUTE(SUBSTITUTE(SUBSTITUTE(SUBSTITUTE(LOWER(LEFT(SUBSTITUTE(H107,"…",""),25)),":",""),",",""),".",""),"'",""),"’",""),"!",""),"*",""),"—",""),"–",""),"-",""),"&","")," ","") -> thechosenlastsupper | N107: =IF(D107="","Other",D107) -> Fathom Entertainm…
A108: 107 | B108: The Chosen: Last Supper — Par… | C108: 45758 | D108: Fathom Entertainm… | E108: Drama | F108: 11686132 | G108: 977101 | H108: =IFERROR(TRIM(LEFT(B108,FIND("(",B108)-1)),TRIM(B108)) -> The Chosen: Last Supper — Par… | I108: My Teez Productio… | J108: 37729 | K108: =SUBSTITUTE(SUBSTITUTE(SUBSTITUTE(SUBSTITUTE(SUBSTITUTE(SUBSTITUTE(SUBSTITUTE(SUBSTITUTE(SUBSTITUTE(SUBSTITUTE(SUBSTITUTE(SUBSTITUTE(LOWER(LEFT(SUBSTITUTE(H108,"…",""),25)),":",""),",",""),".",""),"'",""),"’",""),"!",""),"*",""),"—",""),"–",""),"-",""),"&","")," ","") -> thechosenlastsupper | N108: =IF(D108="","Other",D108) -> Fathom Entertainm…
A109: 108 | B109: Sarah’s Oil | C109: 45968 | D109: Amazon MGM Studios | E109: Drama | F109: 11675627 | G109: 976223 | H109: =IFERROR(TRIM(LEFT(B109,FIND("(",B109)-1)),TRIM(B109)) -> Sarah’s Oil | I109: Atlantic | J109: 33630 | K109: =SUBSTITUTE(SUBSTITUTE(SUBSTITUTE(SUBSTITUTE(SUBSTITUTE(SUBSTITUTE(SUBSTITUTE(SUBSTITUTE(SUBSTITUTE(SUBSTITUTE(SUBSTITUTE(SUBSTITUTE(LOWER(LEFT(SUBSTITUTE(H109,"…",""),25)),":",""),",",""),".",""),"'",""),"’",""),"!",""),"*",""),"—",""),"–",""),"-",""),"&","")," ","") -> sarahsoil | N109: =IF(D109="","Other",D109) -> Amazon MGM Studios
A110: 109 | B110: The Smashing Machine | C110: 45933 | D110: A24 | E110: Drama | F110: 11411388 | G110: 954129 | H110: =IFERROR(TRIM(LEFT(B110,FIND("(",B110)-1)),TRIM(B110)) -> The Smashing Machine | I110: The Forge | J110: 30755 | K110: =SUBSTITUTE(SUBSTITUTE(SUBSTITUTE(SUBSTITUTE(SUBSTITUTE(SUBSTITUTE(SUBSTITUTE(SUBSTITUTE(SUBSTITUTE(SUBSTITUTE(SUBSTITUTE(SUBSTITUTE(LOWER(LEFT(SUBSTITUTE(H110,"…",""),25)),":",""),",",""),".",""),"'",""),"’",""),"!",""),"*",""),"—",""),"–",""),"-",""),"&","")," ","") -> thesmashingmachine | N110: =IF(D110="","Other",D110) -> A24
A111: 110 | B111: Hamnet | C111: 45987 | D111: Focus Features | E111: Drama | F111: 10898125 | G111: 911214 | H111: =IFERROR(TRIM(LEFT(B111,FIND("(",B111)-1)),TRIM(B111)) -> Hamnet | I111: Gathr Films | J111: 29694 | K111: =SUBSTITUTE(SUBSTITUTE(SUBSTITUTE(SUBSTITUTE(SUBSTITUTE(SUBSTITUTE(SUBSTITUTE(SUBSTITUTE(SUBSTITUTE(SUBSTITUTE(SUBSTITUTE(SUBSTITUTE(LOWER(LEFT(SUBSTITUTE(H111,"…",""),25)),":",""),",",""),".",""),"'",""),"’",""),"!",""),"*",""),"—",""),"–",""),"-",""),"&","")," ","") -> hamnet | N111: =IF(D111="","Other",D111) -> Focus Features
A112: 111 | B112: Becoming Led Zeppelin | C112: 45695 | D112: Sony Pictures Cla… | E112: Documentary | F112: 10403808 | G112: 869884 | H112: =IFERROR(TRIM(LEFT(B112,FIND("(",B112)-1)),TRIM(B112)) -> Becoming Led Zeppelin | I112: Yellow Veil Pictu… | J112: 26762 | K112: =SUBSTITUTE(SUBSTITUTE(SUBSTITUTE(SUBSTITUTE(SUBSTITUTE(SUBSTITUTE(SUBSTITUTE(SUBSTITUTE(SUBSTITUTE(SUBSTITUTE(SUBSTITUTE(SUBSTITUTE(LOWER(LEFT(SUBSTITUTE(H112,"…",""),25)),":",""),",",""),".",""),"'",""),"’",""),"!",""),"*",""),"—",""),"–",""),"-",""),"&","")," ","") -> becomingledzeppelin | N112: =IF(D112="","Other",D112) -> Sony Pictures Cla…
A113: 112 | B113: Eddington | C113: 45856 | D113: A24 | E113: Black Comedy | F113: 10109484 | G113: 845275 | H113: =IFERROR(TRIM(LEFT(B113,FIND("(",B113)-1)),TRIM(B113)) -> Eddington | I113: Panorama Studios | J113: 25185 | K113: =SUBSTITUTE(SUBSTITUTE(SUBSTITUTE(SUBSTITUTE(SUBSTITUTE(SUBSTITUTE(SUBSTITUTE(SUBSTITUTE(SUBSTITUTE(SUBSTITUTE(SUBSTITUTE(SUBSTITUTE(LOWER(LEFT(SUBSTITUTE(H113,"…",""),25)),":",""),",",""),".",""),"'",""),"’",""),"!",""),"*",""),"—",""),"–",""),"-",""),"&","")," ","") -> eddington | N113: =IF(D113="","Other",D113) -> A24
A114: 113 | B114: Rental Family | C114: 45982 | D114: Searchlight Pictu… | E114: Comedy | F114: 10047429 | G114: 840086 | H114: =IFERROR(TRIM(LEFT(B114,FIND("(",B114)-1)),TRIM(B114)) -> Rental Family | I114: VRC | J114: 17310 | K114: =SUBSTITUTE(SUBSTITUTE(SUBSTITUTE(SUBSTITUTE(SUBSTITUTE(SUBSTITUTE(SUBSTITUTE(SUBSTITUTE(SUBSTITUTE(SUBSTITUTE(SUBSTITUTE(SUBSTITUTE(LOWER(LEFT(SUBSTITUTE(H114,"…",""),25)),":",""),",",""),".",""),"'",""),"’",""),"!",""),"*",""),"—",""),"–",""),"-",""),"&","")," ","") -> rentalfamily | N114: =IF(D114="","Other",D114) -> Searchlight Pictu…
... A118: 117 | B118: Gladiator II | C118: 45618 | D118: Paramount Pictures | E118: Action | F118: 7883095 | G118: 659122 | H118: =IFERROR(TRIM(LEFT(B118,FIND("(",B118)-1)),TRIM(B118)) -> Gladiator II | I118: Vertigo Releasing | J118: 12000 | K118: =SUBSTITUTE(SUBSTITUTE(SUBSTITUTE(SUBSTITUTE(SUBSTITUTE(SUBSTITUTE(SUBSTITUTE(SUBSTITUTE(SUBSTITUTE(SUBSTITUTE(SUBSTITUTE(SUBSTITUTE(LOWER(LEFT(SUBSTITUTE(H118,"…",""),25)),":",""),",",""),".",""),"'",""),"’",""),"!",""),"*",""),"—",""),"–",""),"-",""),"&","")," ","") -> gladiatorii | N118: =IF(D118="","Other",D118) -> Paramount Pictures
A119: 118 | B119: Paramount Pictures Other Cata… | C119: 46022 | D119: Paramount Pictures | F119: 7868518 | G119: 657903 | H119: =IFERROR(TRIM(LEFT(B119,FIND("(",B119)-1)),TRIM(B119)) -> Paramount Pictures Other Cata… | I119: Red Splat Product… | J119: 11943 | K119: =SUBSTITUTE(SUBSTITUTE(SUBSTITUTE(SUBSTITUTE(SUBSTITUTE(SUBSTITUTE(SUBSTITUTE(SUBSTITUTE(SUBSTITUTE(SUBSTITUTE(SUBSTITUTE(SUBSTITUTE(LOWER(LEFT(SUBSTITUTE(H119,"…",""),25)),":",""),",",""),".",""),"'",""),"’",""),"!",""),"*",""),"—",""),"–",""),"-",""),"&","")," ","") -> paramountpicturesother | N119: =IF(D119="","Other",D119) -> Paramount Pictures
A120: 119 | B120: Soul on Fire | C120: 45940 | D120: Sony Pictures | E120: Drama | F120: 7448606 | G120: 622793 | H120: =IFERROR(TRIM(LEFT(B120,FIND("(",B120)-1)),TRIM(B120)) -> Soul on Fire | I120: Chapter Two Films | J120: 11797 | K120: =SUBSTITUTE(SUBSTITUTE(SUBSTITUTE(SUBSTITUTE(SUBSTITUTE(SUBSTITUTE(SUBSTITUTE(SUBSTITUTE(SUBSTITUTE(SUBSTITUTE(SUBSTITUTE(SUBSTITUTE(LOWER(LEFT(SUBSTITUTE(H120,"…",""),25)),":",""),",",""),".",""),"'",""),"’",""),"!",""),"*",""),"—",""),"–",""),"-",""),"&","")," ","") -> soulonfire | N120: =IF(D120="","Other",D120) -> Sony Pictures
A121: 120 | B121: Clown in a Cornfield | C121: 45786 | D121: RLJ Entertainment | E121: Horror | F121: 7251799 | G121: 606338 | H121: =IFERROR(TRIM(LEFT(B121,FIND("(",B121)-1)),TRIM(B121)) -> Clown in a Cornfield | I121: Big World Pictures | J121: 8325 | K121: =SUBSTITUTE(SUBSTITUTE(SUBSTITUTE(SUBSTITUTE(SUBSTITUTE(SUBSTITUTE(SUBSTITUTE(SUBSTITUTE(SUBSTITUTE(SUBSTITUTE(SUBSTITUTE(SUBSTITUTE(LOWER(LEFT(SUBSTITUTE(H121,"…",""),25)),":",""),",",""),".",""),"'",""),"’",""),"!",""),"*",""),"—",""),"–",""),"-",""),"&","")," ","") -> clowninacornfield | N121: =IF(D121="","Other",D121) -> RLJ Entertainment
A122: 121 | B122: Presence | C122: 45681 | D122: Neon | E122: Horror | F122: 6900045 | G122: 576927 | H122: =IFERROR(TRIM(LEFT(B122,FIND("(",B122)-1)),TRIM(B122)) -> Presence | I122: Altitude Film Dis… | J122: 7200 | K122: =SUBSTITUTE(SUBSTITUTE(SUBSTITUTE(SUBSTITUTE(SUBSTITUTE(SUBSTITUTE(SUBSTITUTE(SUBSTITUTE(SUBSTITUTE(SUBSTITUTE(SUBSTITUTE(SUBSTITUTE(LOWER(LEFT(SUBSTITUTE(H122,"…",""),25)),":",""),",",""),".",""),"'",""),"’",""),"!",""),"*",""),"—",""),"–",""),"-",""),"&","")," ","") -> presence | N122: =IF(D122="","Other",D122) -> Neon
A123: 122 | B123: Princess Mononoke (もののけ姫) | C123: 36462 | D123: GKIDS | E123: Action | F123: 6851368 | G123: 572857 | H123: =IFERROR(TRIM(LEFT(B123,FIND("(",B123)-1)),TRIM(B123)) -> Princess Mononoke | I123: Film Forum | J123: 7066 | K123: =SUBSTITUTE(SUBSTITUTE(SUBSTITUTE(SUBSTITUTE(SUBSTITUTE(SUBSTITUTE(SUBSTITUTE(SUBSTITUTE(SUBSTITUTE(SUBSTITUTE(SUBSTITUTE(SUBSTITUTE(LOWER(LEFT(SUBSTITUTE(H123,"…",""),25)),":",""),",",""),".",""),"'",""),"’",""),"!",""),"*",""),"—",""),"–",""),"-",""),"&","")," ","") -> princessmononoke | N123: =IF(D123="","Other",D123) -> GKIDS
A124: 123 | B124: Homestead | C124: 45646 | D124: Angel Studios | E124: Drama | F124: 6823043 | G124: 570489 | H124: =IFERROR(TRIM(LEFT(B124,FIND("(",B124)-1)),TRIM(B124)) -> Homestead | I124: Mountain Park Med… | J124: 6318 | K124: =SUBSTITUTE(SUBSTITUTE(SUBSTITUTE(SUBSTITUTE(SUBSTITUTE(SUBSTITUTE(SUBSTITUTE(SUBSTITUTE(SUBSTITUTE(SUBSTITUTE(SUBSTITUTE(SUBSTITUTE(LOWER(LEFT(SUBSTITUTE(H124,"…",""),25)),":",""),",",""),".",""),"'",""),"’",""),"!",""),"*",""),"—",""),"–",""),"-",""),"&","")," ","") -> homestead | N124: =IF(D124="","Other",D124) -> Angel Studios
A125: 124 | B125: Toy Story | C125: 35025 | D125: Walt Disney | E125: Adventure | F125: 6721383 | G125: 561989 | H125: =IFERROR(TRIM(LEFT(B125,FIND("(",B125)-1)),TRIM(B125)) -> Toy Story | I125: Disrupt Entertain… | J125: 5438 | K125: =SUBSTITUTE(SUBSTITUTE(SUBSTITUTE(SUBSTITUTE(SUBSTITUTE(SUBSTITUTE(SUBSTITUTE(SUBSTITUTE(SUBSTITUTE(SUBSTITUTE(SUBSTITUTE(SUBSTITUTE(LOWER(LEFT(SUBSTITUTE(H125,"…",""),25)),":",""),",",""),".",""),"'",""),"’",""),"!",""),"*",""),"—",""),"–",""),"-",""),"&","")," ","") -> toystory | N125: =IF(D125="","Other",D125) -> Walt Disney
A126: 125 | B126: The Life of Chuck | C126: 45814 | D126: Neon | E126: Drama | F126: 6712602 | G126: 561254 | H126: =IFERROR(TRIM(LEFT(B126,FIND("(",B126)-1)),TRIM(B126)) -> The Life of Chuck | I126: Uncia Films | J126: 5283 | K126: =SUBSTITUTE(SUBSTITUTE(SUBSTITUTE(SUBSTITUTE(SUBSTITUTE(SUBSTITUTE(SUBSTITUTE(SUBSTITUTE(SUBSTITUTE(SUBSTITUTE(SUBSTITUTE(SUBSTITUTE(LOWER(LEFT(SUBSTITUTE(H126,"…",""),25)),":",""),",",""),".",""),"'",""),"’",""),"!",""),"*",""),"—",""),"–",""),"-",""),"&","")," ","") -> thelifeofchuck | N126: =IF(D126="","Other",D126) -> Neon
A127: 126 | B127: A Big Bold Beautiful Journey | C127: 45919 | D127: Sony Pictures | E127: Drama | F127: 6671082 | G127: 557783 | H127: =IFERROR(TRIM(LEFT(B127,FIND("(",B127)-1)),TRIM(B127)) -> A Big Bold Beautiful Journey | I127: October Films | J127: 4665 | K127: =SUBSTITUTE(SUBSTITUTE(SUBSTITUTE(SUBSTITUTE(SUBSTITUTE(SUBSTITUTE(SUBSTITUTE(SUBSTITUTE(SUBSTITUTE(SUBSTITUTE(SUBSTITUTE(SUBSTITUTE(LOWER(LEFT(SUBSTITUTE(H127,"…",""),25)),":",""),",",""),".",""),"'",""),"’",""),"!",""),"*",""),"—",""),"–",""),"-",""),"&","")," ","") -> abigboldbeautifuljour | N127: =IF(D127="","Other",D127) -> Sony Pictures
A128: 127 | B128: Good Boy | C128: 45933 | D128: IFC Entertainment… | E128: Horror | F128: 6624062 | G128: 553851 | H128: =IFERROR(TRIM(LEFT(B128,FIND("(",B128)-1)),TRIM(B128)) -> Good Boy | I128: Kani Releasing | J128: 4472 | K128: =SUBSTITUTE(SUBSTITUTE(SUBSTITUTE(SUBSTITUTE(SUBSTITUTE(SUBSTITUTE(SUBSTITUTE(SUBSTITUTE(SUBSTITUTE(SUBSTITUTE(SUBSTITUTE(SUBSTITUTE(LOWER(LEFT(SUBSTITUTE(H128,"…",""),25)),":",""),",",""),".",""),"'",""),"’",""),"!",""),"*",""),"—",""),"–",""),"-",""),"&","")," ","") -> goodboy | N128: =IF(D128="","Other",D128) -> IFC Entertainment…
A129: 128 | B129: The Last Supper | C129: 45730 | D129: Pinnacle Peak | E129: Drama | F129: 6564857 | G129: 548901 | H129: =IFERROR(TRIM(LEFT(B129,FIND("(",B129)-1)),TRIM(B129)) -> The Last Supper | I129: Lion Heart Distri… | J129: 3136 | K129: =SUBSTITUTE(SUBSTITUTE(SUBSTITUTE(SUBSTITUTE(SUBSTITUTE(SUBSTITUTE(SUBSTITUTE(SUBSTITUTE(SUBSTITUTE(SUBSTITUTE(SUBSTITUTE(SUBSTITUTE(LOWER(LEFT(SUBSTITUTE(H129,"…",""),25)),":",""),",",""),".",""),"'",""),"’",""),"!",""),"*",""),"—",""),"–",""),"-",""),"&","")," ","") -> thelastsupper | N129: =IF(D129="","Other",D129) -> Pinnacle Peak
A130: 129 | B130: The Unbreakable Boy | C130: 45709 | D130: Lionsgate | E130: Drama | F130: 6443813 | G130: 538780 | H130: =IFERROR(TRIM(LEFT(B130,FIND("(",B130)-1)),TRIM(B130)) -> The Unbreakable Boy | I130: Kismet Circle | J130: 2999 | K130: =SUBSTITUTE(SUBSTITUTE(SUBSTITUTE(SUBSTITUTE(SUBSTITUTE(SUBSTITUTE(SUBSTITUTE(SUBSTITUTE(SUBSTITUTE(SUBSTITUTE(SUBSTITUTE(SUBSTITUTE(LOWER(LEFT(SUBSTITUTE(H130,"…",""),25)),":",""),",",""),".",""),"'",""),"’",""),"!",""),"*",""),"—",""),"–",""),"-",""),"&","")," ","") -> theunbreakableboy | N130: =IF(D130="","Other",D130) -> Lionsgate
A131: 130 | B131: Anora | C131: 45583 | D131: Neon | E131: Comedy | F131: 6327494 | G131: 529055 | H131: =IFERROR(TRIM(LEFT(B131,FIND("(",B131)-1)),TRIM(B131)) -> Anora | I131: Buffalo 8 | J131: 1755 | K131: =SUBSTITUTE(SUBSTITUTE(SUBSTITUTE(SUBSTITUTE(SUBSTITUTE(SUBSTITUTE(SUBSTITUTE(SUBSTITUTE(SUBSTITUTE(SUBSTITUTE(SUBSTITUTE(SUBSTITUTE(LOWER(LEFT(SUBSTITUTE(H131,"…",""),25)),":",""),",",""),".",""),"'",""),"’",""),"!",""),"*",""),"—",""),"–",""),"-",""),"&","")," ","") -> anora | N131: =IF(D131="","Other",D131) -> Neon
A132: 131 | B132: Ainda Estou Aqui | C132: 45674 | D132: Sony Pictures Cla… | E132: Drama | F132: 6233517 | G132: 521197 | H132: =IFERROR(TRIM(LEFT(B132,FIND("(",B132)-1)),TRIM(B132)) -> Ainda Estou Aqui | I132: Grand Total | J132: 8716062053 | K132: =SUBSTITUTE(SUBSTITUTE(SUBSTITUTE(SUBSTITUTE(SUBSTITUTE(SUBSTITUTE(SUBSTITUTE(SUBSTITUTE(SUBSTITUTE(SUBSTITUTE(SUBSTITUTE(SUBSTITUTE(LOWER(LEFT(SUBSTITUTE(H132,"…",""),25)),":",""),",",""),".",""),"'",""),"’",""),"!",""),"*",""),"—",""),"–",""),"-",""),"&","")," ","") -> aindaestouaqui | N132: =IF(D132="","Other",D132) -> Sony Pictures Cla…
A133: 132 | B133: Pride & Prejudice | C133: 38667 | D133: Focus Features | E133: Drama | F133: 6221133 | G133: 520162 | H133: =IFERROR(TRIM(LEFT(B133,FIND("(",B133)-1)),TRIM(B133)) -> Pride & Prejudice | K133: =SUBSTITUTE(SUBSTITUTE(SUBSTITUTE(SUBSTITUTE(SUBSTITUTE(SUBSTITUTE(SUBSTITUTE(SUBSTITUTE(SUBSTITUTE(SUBSTITUTE(SUBSTITUTE(SUBSTITUTE(LOWER(LEFT(SUBSTITUTE(H133,"…",""),25)),":",""),",",""),".",""),"'",""),"’",""),"!",""),"*",""),"—",""),"–",""),"-",""),"&","")," ","") -> prideprejudice | N133: =IF(D133="","Other",D133) -> Focus Features
A134: 133 | B134: The Alto Knights | C134: 45737 | D134: Warner Bros. | E134: Drama | F134: 6125566 | G134: 512171 | H134: =IFERROR(TRIM(LEFT(B134,FIND("(",B134)-1)),TRIM(B134)) -> The Alto Knights | K134: =SUBSTITUTE(SUBSTITUTE(SUBSTITUTE(SUBSTITUTE(SUBSTITUTE(SUBSTITUTE(SUBSTITUTE(SUBSTITUTE(SUBSTITUTE(SUBSTITUTE(SUBSTITUTE(SUBSTITUTE(LOWER(LEFT(SUBSTITUTE(H134,"…",""),25)),":",""),",",""),".",""),"'",""),"’",""),"!",""),"*",""),"—",""),"–",""),"-",""),"&","")," ","") -> thealtoknights | N134: =IF(D134="","Other",D134) -> Warner Bros.
A135: 134 | B135: Truth & Treason | C135: 45947 | D135: Angel Studios | E135: Thriller/Suspense | F135: 6044364 | G135: 505382 | H135: =IFERROR(TRIM(LEFT(B135,FIND("(",B135)-1)),TRIM(B135)) -> Truth & Treason | K135: =SUBSTITUTE(SUBSTITUTE(SUBSTITUTE(SUBSTITUTE(SUBSTITUTE(SUBSTITUTE(SUBSTITUTE(SUBSTITUTE(SUBSTITUTE(SUBSTITUTE(SUBSTITUTE(SUBSTITUTE(LOWER(LEFT(SUBSTITUTE(H135,"…",""),25)),":",""),",",""),".",""),"'",""),"’",""),"!",""),"*",""),"—",""),"–",""),"-",""),"&","")," ","") -> truthtreason | N135: =IF(D135="","Other",D135) -> Angel Studios
A136: 135 | B136: Kill Bill: The Whole Bloody A… | C136: 45996 | D136: Lionsgate | E136: Action | F136: 6002538 | G136: 501884 | H136: =IFERROR(TRIM(LEFT(B136,FIND("(",B136)-1)),TRIM(B136)) -> Kill Bill: The Whole Bloody A… | K136: =SUBSTITUTE(SUBSTITUTE(SUBSTITUTE(SUBSTITUTE(SUBSTITUTE(SUBSTITUTE(SUBSTITUTE(SUBSTITUTE(SUBSTITUTE(SUBSTITUTE(SUBSTITUTE(SUBSTITUTE(LOWER(LEFT(SUBSTITUTE(H136,"…",""),25)),":",""),",",""),".",""),"'",""),"’",""),"!",""),"*",""),"—",""),"–",""),"-",""),"&","")," ","") -> killbillthewholebloo | N136: =IF(D136="","Other",D136) -> Lionsgate
A137: 136 | B137: Honey Don’t | C137: 45891 | D137: Focus Features | E137: Black Comedy | F137: 5810510 | G137: 485829 | H137: =IFERROR(TRIM(LEFT(B137,FIND("(",B137)-1)),TRIM(B137)) -> Honey Don’t | K137: =SUBSTITUTE(SUBSTITUTE(SUBSTITUTE(SUBSTITUTE(SUBSTITUTE(SUBSTITUTE(SUBSTITUTE(SUBSTITUTE(SUBSTITUTE(SUBSTITUTE(SUBSTITUTE(SUBSTITUTE(LOWER(LEFT(SUBSTITUTE(H137,"…",""),25)),":",""),",",""),".",""),"'",""),"’",""),"!",""),"*",""),"—",""),"–",""),"-",""),"&","")," ","") -> honeydont | N137: =IF(D137="","Other",D137) -> Focus Features
A138: 137 | B138: Dan Da Dan: Evil Eye | C138: 45814 | D138: GKIDS | E138: Action | F138: 5637079 | G138: 471328 | H138: =IFERROR(TRIM(LEFT(B138,FIND("(",B138)-1)),TRIM(B138)) -> Dan Da Dan: Evil Eye | K138: =SUBSTITUTE(SUBSTITUTE(SUBSTITUTE(SUBSTITUTE(SUBSTITUTE(SUBSTITUTE(SUBSTITUTE(SUBSTITUTE(SUBSTITUTE(SUBSTITUTE(SUBSTITUTE(SUBSTITUTE(LOWER(LEFT(SUBSTITUTE(H138,"…",""),25)),":",""),",",""),".",""),"'",""),"’",""),"!",""),"*",""),"—",""),"–",""),"-",""),"&","")," ","") -> dandadanevileye | N138: =IF(D138="","Other",D138) -> GKIDS
A139: 138 | B139: Die, My Love | C139: 45968 | D139: MUBI | E139: Thriller/Suspense | F139: 5515263 | G139: 461142 | H139: =IFERROR(TRIM(LEFT(B139,FIND("(",B139)-1)),TRIM(B139)) -> Die, My Love | K139: =SUBSTITUTE(SUBSTITUTE(SUBSTITUTE(SUBSTITUTE(SUBSTITUTE(SUBSTITUTE(SUBSTITUTE(SUBSTITUTE(SUBSTITUTE(SUBSTITUTE(SUBSTITUTE(SUBSTITUTE(LOWER(LEFT(SUBSTITUTE(H139,"…",""),25)),":",""),",",""),".",""),"'",""),"’",""),"!",""),"*",""),"—",""),"–",""),"-",""),"&","")," ","") -> diemylove | N139: =IF(D139="","Other",D139) -> MUBI
A140: 139 | B140: The Matrix | C140: 36250 | D140: Warner Bros. | E140: Action | F140: 5482077 | G140: 458368 | H140: =IFERROR(TRIM(LEFT(B140,FIND("(",B140)-1)),TRIM(B140)) -> The Matrix | K140: =SUBSTITUTE(SUBSTITUTE(SUBSTITUTE(SUBSTITUTE(SUBSTITUTE(SUBSTITUTE(SUBSTITUTE(SUBSTITUTE(SUBSTITUTE(SUBSTITUTE(SUBSTITUTE(SUBSTITUTE(LOWER(LEFT(SUBSTITUTE(H140,"…",""),25)),":",""),",",""),".",""),"'",""),"’",""),"!",""),"*",""),"—",""),"–",""),"-",""),"&","")," ","") -> thematrix | N140: =IF(D140="","Other",D140) -> Warner Bros.
A141: 140 | B141: The Senior | C141: 45919 | D141: Angel Studios | E141: Drama | F141: 5295949 | G141: 442805 | H141: =IFERROR(TRIM(LEFT(B141,FIND("(",B141)-1)),TRIM(B141)) -> The Senior | K141: =SUBSTITUTE(SUBSTITUTE(SUBSTITUTE(SUBSTITUTE(SUBSTITUTE(SUBSTITUTE(SUBSTITUTE(SUBSTITUTE(SUBSTITUTE(SUBSTITUTE(SUBSTITUTE(SUBSTITUTE(LOWER(LEFT(SUBSTITUTE(H141,"…",""),25)),":",""),",",""),".",""),"'",""),"’",""),"!",""),"*",""),"—",""),"–",""),"-",""),"&","")," ","") -> thesenior | N141: =IF(D141="","Other",D141) -> Angel Studios
A142: 141 | B142: Hurry Up Tomorrow | C142: 45793 | D142: Lionsgate | E142: Thriller/Suspense | F142: 5215357 | G142: 436067 | H142: =IFERROR(TRIM(LEFT(B142,FIND("(",B142)-1)),TRIM(B142)) -> Hurry Up Tomorrow | K142: =SUBSTITUTE(SUBSTITUTE(SUBSTITUTE(SUBSTITUTE(SUBSTITUTE(SUBSTITUTE(SUBSTITUTE(SUBSTITUTE(SUBSTITUTE(SUBSTITUTE(SUBSTITUTE(SUBSTITUTE(LOWER(LEFT(SUBSTITUTE(H142,"…",""),25)),":",""),",",""),".",""),"'",""),"’",""),"!",""),"*",""),"—",""),"–",""),"-",""),"&","")," ","") -> hurryuptomorrow | N142: =IF(D142="","Other",D142) -> Lionsgate
A143: 142 | B143: Light of the World | C143: 45905 | D143: Salvation Poem Pr… | E143: Drama | F143: 5213377 | G143: 435901 | H143: =IFERROR(TRIM(LEFT(B143,FIND("(",B143)-1)),TRIM(B143)) -> Light of the World | K143: =SUBSTITUTE(SUBSTITUTE(SUBSTITUTE(SUBSTITUTE(SUBSTITUTE(SUBSTITUTE(SUBSTITUTE(SUBSTITUTE(SUBSTITUTE(SUBSTITUTE(SUBSTITUTE(SUBSTITUTE(LOWER(LEFT(SUBSTITUTE(H143,"…",""),25)),":",""),",",""),".",""),"'",""),"’",""),"!",""),"*",""),"—",""),"–",""),"-",""),"&","")," ","") -> lightoftheworld | N143: =IF(D143="","Other",D143) -> Salvation Poem Pr…
A144: 143 | B144: They Call Him OG | C144: 45925 | D144: Prathyangira Cine… | E144: Action | F144: 5200000 | G144: 434783 | H144: =IFERROR(TRIM(LEFT(B144,FIND("(",B144)-1)),TRIM(B144)) -> They Call Him OG | K144: =SUBSTITUTE(SUBSTITUTE(SUBSTITUTE(SUBSTITUTE(SUBSTITUTE(SUBSTITUTE(SUBSTITUTE(SUBSTITUTE(SUBSTITUTE(SUBSTITUTE(SUBSTITUTE(SUBSTITUTE(LOWER(LEFT(SUBSTITUTE(H144,"…",""),25)),":",""),",",""),".",""),"'",""),"’",""),"!",""),"*",""),"—",""),"–",""),"-",""),"&","")," ","") -> theycallhimog | N144: =IF(D144="","Other",D144) -> Prathyangira Cine…
... A152: 151 | B152: Keeper | C152: 45975 | D152: Neon | E152: Horror | F152: 4200167 | G152: 351185 | H152: =IFERROR(TRIM(LEFT(B152,FIND("(",B152)-1)),TRIM(B152)) -> Keeper | K152: =SUBSTITUTE(SUBSTITUTE(SUBSTITUTE(SUBSTITUTE(SUBSTITUTE(SUBSTITUTE(SUBSTITUTE(SUBSTITUTE(SUBSTITUTE(SUBSTITUTE(SUBSTITUTE(SUBSTITUTE(LOWER(LEFT(SUBSTITUTE(H152,"…",""),25)),":",""),",",""),".",""),"'",""),"’",""),"!",""),"*",""),"—",""),"–",""),"-",""),"&","")," ","") -> keeper | N152: =IF(D152="","Other",D152) -> Neon
A153: 152 | B153: Walt Disney Other Catalog | C153: 46022 | D153: Walt Disney | F153: 4167547 | G153: 348457 | H153: =IFERROR(TRIM(LEFT(B153,FIND("(",B153)-1)),TRIM(B153)) -> Walt Disney Other Catalog | K153: =SUBSTITUTE(SUBSTITUTE(SUBSTITUTE(SUBSTITUTE(SUBSTITUTE(SUBSTITUTE(SUBSTITUTE(SUBSTITUTE(SUBSTITUTE(SUBSTITUTE(SUBSTITUTE(SUBSTITUTE(LOWER(LEFT(SUBSTITUTE(H153,"…",""),25)),":",""),",",""),".",""),"'",""),"’",""),"!",""),"*",""),"—",""),"–",""),"-",""),"&","")," ","") -> waltdisneyothercatalog | N153: =IF(D153="","Other",D153) -> Walt Disney
A154: 153 | B154: Shin Godjira | C154: 42654 | D154: GKIDS | E154: Action | F154: 4042146 | G154: 337972 | H154: =IFERROR(TRIM(LEFT(B154,FIND("(",B154)-1)),TRIM(B154)) -> Shin Godjira | K154: =SUBSTITUTE(SUBSTITUTE(SUBSTITUTE(SUBSTITUTE(SUBSTITUTE(SUBSTITUTE(SUBSTITUTE(SUBSTITUTE(SUBSTITUTE(SUBSTITUTE(SUBSTITUTE(SUBSTITUTE(LOWER(LEFT(SUBSTITUTE(H154,"…",""),25)),":",""),",",""),".",""),"'",""),"’",""),"!",""),"*",""),"—",""),"–",""),"-",""),"&","")," ","") -> shingodjira | N154: =IF(D154="","Other",D154) -> GKIDS
A155: 154 | B155: Ella McCay | C155: 46003 | D155: 20th Century Stud… | E155: Drama | F155: 3950824 | G155: 330336 | H155: =IFERROR(TRIM(LEFT(B155,FIND("(",B155)-1)),TRIM(B155)) -> Ella McCay | K155: =SUBSTITUTE(SUBSTITUTE(SUBSTITUTE(SUBSTITUTE(SUBSTITUTE(SUBSTITUTE(SUBSTITUTE(SUBSTITUTE(SUBSTITUTE(SUBSTITUTE(SUBSTITUTE(SUBSTITUTE(LOWER(LEFT(SUBSTITUTE(H155,"…",""),25)),":",""),",",""),".",""),"'",""),"’",""),"!",""),"*",""),"—",""),"–",""),"-",""),"&","")," ","") -> ellamccay | N155: =IF(D155="","Other",D155) -> 20th Century Stud…
A156: 155 | B156: The Friend | C156: 45744 | D156: Bleecker Street | E156: Drama | F156: 3942783 | G156: 329664 | H156: =IFERROR(TRIM(LEFT(B156,FIND("(",B156)-1)),TRIM(B156)) -> The Friend | K156: =SUBSTITUTE(SUBSTITUTE(SUBSTITUTE(SUBSTITUTE(SUBSTITUTE(SUBSTITUTE(SUBSTITUTE(SUBSTITUTE(SUBSTITUTE(SUBSTITUTE(SUBSTITUTE(SUBSTITUTE(LOWER(LEFT(SUBSTITUTE(H156,"…",""),25)),":",""),",",""),".",""),"'",""),"’",""),"!",""),"*",""),"—",""),"–",""),"-",""),"&","")," ","") -> thefriend | N156: =IF(D156="","Other",D156) -> Bleecker Street
A157: 156 | B157: Shadow Force | C157: 45786 | D157: Lionsgate | E157: Action | F157: 3933484 | G157: 328887 | H157: =IFERROR(TRIM(LEFT(B157,FIND("(",B157)-1)),TRIM(B157)) -> Shadow Force | K157: =SUBSTITUTE(SUBSTITUTE(SUBSTITUTE(SUBSTITUTE(SUBSTITUTE(SUBSTITUTE(SUBSTITUTE(SUBSTITUTE(SUBSTITUTE(SUBSTITUTE(SUBSTITUTE(SUBSTITUTE(LOWER(LEFT(SUBSTITUTE(H157,"…",""),25)),":",""),",",""),".",""),"'",""),"’",""),"!",""),"*",""),"—",""),"–",""),"-",""),"&","")," ","") -> shadowforce | N157: =IF(D157="","Other",D157) -> Lionsgate
A158: 157 | B158: Sentimental Value | C158: 45968 | D158: Neon | E158: Comedy | F158: 3916460 | G158: 327463 | H158: =IFERROR(TRIM(LEFT(B158,FIND("(",B158)-1)),TRIM(B158)) -> Sentimental Value | K158: =SUBSTITUTE(SUBSTITUTE(SUBSTITUTE(SUBSTITUTE(SUBSTITUTE(SUBSTITUTE(SUBSTITUTE(SUBSTITUTE(SUBSTITUTE(SUBSTITUTE(SUBSTITUTE(SUBSTITUTE(LOWER(LEFT(SUBSTITUTE(H158,"…",""),25)),":",""),",",""),".",""),"'",""),"’",""),"!",""),"*",""),"—",""),"–",""),"-",""),"&","")," ","") -> sentimentalvalue | N158: =IF(D158="","Other",D158) -> Neon
A159: 158 | B159: War 2 | C159: 45883 | D159: Yash Raj Films | E159: Action | F159: 3733779 | G159: 312189 | H159: =IFERROR(TRIM(LEFT(B159,FIND("(",B159)-1)),TRIM(B159)) -> War 2 | K159: =SUBSTITUTE(SUBSTITUTE(SUBSTITUTE(SUBSTITUTE(SUBSTITUTE(SUBSTITUTE(SUBSTITUTE(SUBSTITUTE(SUBSTITUTE(SUBSTITUTE(SUBSTITUTE(SUBSTITUTE(LOWER(LEFT(SUBSTITUTE(H159,"…",""),25)),":",""),",",""),".",""),"'",""),"’",""),"!",""),"*",""),"—",""),"–",""),"-",""),"&","")," ","") -> war2 | N159: =IF(D159="","Other",D159) -> Yash Raj Films
A160: 159 | B160: COLORFUL STAGE! The Movie: A … | C160: 45765 | D160: GKIDS | E160: Musical | F160: 3659632 | G160: 305989 | H160: =IFERROR(TRIM(LEFT(B160,FIND("(",B160)-1)),TRIM(B160)) -> COLORFUL STAGE! The Movie: A … | K160: =SUBSTITUTE(SUBSTITUTE(SUBSTITUTE(SUBSTITUTE(SUBSTITUTE(SUBSTITUTE(SUBSTITUTE(SUBSTITUTE(SUBSTITUTE(SUBSTITUTE(SUBSTITUTE(SUBSTITUTE(LOWER(LEFT(SUBSTITUTE(H160,"…",""),25)),":",""),",",""),".",""),"'",""),"’",""),"!",""),"*",""),"—",""),"–",""),"-",""),"&","")," ","") -> colorfulstagethemovie | N160: =IF(D160="","Other",D160) -> GKIDS
A161: 160 | B161: Fight or Flight | C161: 45786 | D161: Vertical Entertai… | E161: Action | F161: 3522025 | G161: 294484 | H161: =IFERROR(TRIM(LEFT(B161,FIND("(",B161)-1)),TRIM(B161)) -> Fight or Flight | K161: =SUBSTITUTE(SUBSTITUTE(SUBSTITUTE(SUBSTITUTE(SUBSTITUTE(SUBSTITUTE(SUBSTITUTE(SUBSTITUTE(SUBSTITUTE(SUBSTITUTE(SUBSTITUTE(SUBSTITUTE(LOWER(LEFT(SUBSTITUTE(H161,"…",""),25)),":",""),",",""),".",""),"'",""),"’",""),"!",""),"*",""),"—",""),"–",""),"-",""),"&","")," ","") -> fightorflight | N161: =IF(D161="","Other",D161) -> Vertical Entertai…
A162: 161 | B162: Saiyaara | C162: 45856 | D162: Yash Raj Films | E162: Drama | F162: 3359480 | G162: 280893 | H162: =IFERROR(TRIM(LEFT(B162,FIND("(",B162)-1)),TRIM(B162)) -> Saiyaara | K162: =SUBSTITUTE(SUBSTITUTE(SUBSTITUTE(SUBSTITUTE(SUBSTITUTE(SUBSTITUTE(SUBSTITUTE(SUBSTITUTE(SUBSTITUTE(SUBSTITUTE(SUBSTITUTE(SUBSTITUTE(LOWER(LEFT(SUBSTITUTE(H162,"…",""),25)),":",""),",",""),".",""),"'",""),"’",""),"!",""),"*",""),"—",""),"–",""),"-",""),"&","")," ","") -> saiyaara | N162: =IF(D162="","Other",D162) -> Yash Raj Films
A163: 162 | B163: The Penguin Lessons | C163: 45744 | D163: Sony Pictures Cla… | E163: Drama | F163: 3294991 | G163: 275501 | H163: =IFERROR(TRIM(LEFT(B163,FIND("(",B163)-1)),TRIM(B163)) -> The Penguin Lessons | K163: =SUBSTITUTE(SUBSTITUTE(SUBSTITUTE(SUBSTITUTE(SUBSTITUTE(SUBSTITUTE(SUBSTITUTE(SUBSTITUTE(SUBSTITUTE(SUBSTITUTE(SUBSTITUTE(SUBSTITUTE(LOWER(LEFT(SUBSTITUTE(H163,"…",""),25)),":",""),",",""),".",""),"'",""),"’",""),"!",""),"*",""),"—",""),"–",""),"-",""),"&","")," ","") -> thepenguinlessons | N163: =IF(D163="","Other",D163) -> Sony Pictures Cla…
A164: 163 | B164: 2025 Oscar Shorts | C164: 45702 | D164: ShortsHD | E164: Multiple Genres | F164: 3275177 | G164: 273844 | H164: =IFERROR(TRIM(LEFT(B164,FIND("(",B164)-1)),TRIM(B164)) -> 2025 Oscar Shorts | K164: =SUBSTITUTE(SUBSTITUTE(SUBSTITUTE(SUBSTITUTE(SUBSTITUTE(SUBSTITUTE(SUBSTITUTE(SUBSTITUTE(SUBSTITUTE(SUBSTITUTE(SUBSTITUTE(SUBSTITUTE(LOWER(LEFT(SUBSTITUTE(H164,"…",""),25)),":",""),",",""),".",""),"'",""),"’",""),"!",""),"*",""),"—",""),"–",""),"-",""),"&","")," ","") -> 2025oscarshorts | N164: =IF(D164="","Other",D164) -> ShortsHD
A165: 164 | B165: After the Hunt | C165: 45940 | D165: Amazon MGM Studios | E165: Thriller/Suspense | F165: 3258830 | G165: 272477 | H165: =IFERROR(TRIM(LEFT(B165,FIND("(",B165)-1)),TRIM(B165)) -> After the Hunt | K165: =SUBSTITUTE(SUBSTITUTE(SUBSTITUTE(SUBSTITUTE(SUBSTITUTE(SUBSTITUTE(SUBSTITUTE(SUBSTITUTE(SUBSTITUTE(SUBSTITUTE(SUBSTITUTE(SUBSTITUTE(LOWER(LEFT(SUBSTITUTE(H165,"…",""),25)),":",""),",",""),".",""),"'",""),"’",""),"!",""),"*",""),"—",""),"–",""),"-",""),"&","")," ","") -> afterthehunt | N165: =IF(D165="","Other",D165) -> Amazon MGM Studios
... A187: 186 | B187: Sorry, Baby | C187: 45835 | D187: A24 | E187: Drama | F187: 2346819 | G187: 196222 | H187: =IFERROR(TRIM(LEFT(B187,FIND("(",B187)-1)),TRIM(B187)) -> Sorry, Baby | K187: =SUBSTITUTE(SUBSTITUTE(SUBSTITUTE(SUBSTITUTE(SUBSTITUTE(SUBSTITUTE(SUBSTITUTE(SUBSTITUTE(SUBSTITUTE(SUBSTITUTE(SUBSTITUTE(SUBSTITUTE(LOWER(LEFT(SUBSTITUTE(H187,"…",""),25)),":",""),",",""),".",""),"'",""),"’",""),"!",""),"*",""),"—",""),"–",""),"-",""),"&","")," ","") -> sorrybaby | N187: =IF(D187="","Other",D187) -> A24
A188: 187 | B188: 46270 | C188: 45639 | D188: Paramount Pictures | E188: Drama | F188: 2291572 | G188: 191603 | H188: =IFERROR(TRIM(LEFT(B188,FIND("(",B188)-1)),TRIM(B188)) -> 46270 | K188: =SUBSTITUTE(SUBSTITUTE(SUBSTITUTE(SUBSTITUTE(SUBSTITUTE(SUBSTITUTE(SUBSTITUTE(SUBSTITUTE(SUBSTITUTE(SUBSTITUTE(SUBSTITUTE(SUBSTITUTE(LOWER(LEFT(SUBSTITUTE(H188,"…",""),25)),":",""),",",""),".",""),"'",""),"’",""),"!",""),"*",""),"—",""),"–",""),"-",""),"&","")," ","") -> 46270 | N188: =IF(D188="","Other",D188) -> Paramount Pictures
A189: 188 | B189: The Room Next Door | C189: 45646 | D189: Sony Pictures Cla… | E189: Drama | F189: 2274578 | G189: 190182 | H189: =IFERROR(TRIM(LEFT(B189,FIND("(",B189)-1)),TRIM(B189)) -> The Room Next Door | K189: =SUBSTITUTE(SUBSTITUTE(SUBSTITUTE(SUBSTITUTE(SUBSTITUTE(SUBSTITUTE(SUBSTITUTE(SUBSTITUTE(SUBSTITUTE(SUBSTITUTE(SUBSTITUTE(SUBSTITUTE(LOWER(LEFT(SUBSTITUTE(H189,"…",""),25)),":",""),",",""),".",""),"'",""),"’",""),"!",""),"*",""),"—",""),"–",""),"-",""),"&","")," ","") -> theroomnextdoor | N189: =IF(D189="","Other",D189) -> Sony Pictures Cla…
A190: 189 | B190: L2: Empuraan | C190: 45743 | E190: Action | F190: 2210556 | G190: 184829 | H190: =IFERROR(TRIM(LEFT(B190,FIND("(",B190)-1)),TRIM(B190)) -> L2: Empuraan | K190: =SUBSTITUTE(SUBSTITUTE(SUBSTITUTE(SUBSTITUTE(SUBSTITUTE(SUBSTITUTE(SUBSTITUTE(SUBSTITUTE(SUBSTITUTE(SUBSTITUTE(SUBSTITUTE(SUBSTITUTE(LOWER(LEFT(SUBSTITUTE(H190,"…",""),25)),":",""),",",""),".",""),"'",""),"’",""),"!",""),"*",""),"—",""),"–",""),"-",""),"&","")," ","") -> l2empuraan | N190: =IF(D190="","Other",D190) -> Other
A191: 190 | B191: The Sound of Music | C191: 23803 | D191: 20th Century Stud… | E191: Musical | F191: 2163488 | G191: 180894 | H191: =IFERROR(TRIM(LEFT(B191,FIND("(",B191)-1)),TRIM(B191)) -> The Sound of Music | K191: =SUBSTITUTE(SUBSTITUTE(SUBSTITUTE(SUBSTITUTE(SUBSTITUTE(SUBSTITUTE(SUBSTITUTE(SUBSTITUTE(SUBSTITUTE(SUBSTITUTE(SUBSTITUTE(SUBSTITUTE(LOWER(LEFT(SUBSTITUTE(H191,"…",""),25)),":",""),",",""),".",""),"'",""),"’",""),"!",""),"*",""),"—",""),"–",""),"-",""),"&","")," ","") -> thesoundofmusic | N191: =IF(D191="","Other",D191) -> 20th Century Stud…
A192: 191 | B192: Night of the Zoopocalypse | C192: 45716 | D192: Viva Pictures | E192: Comedy | F192: 2108907 | G192: 176330 | H192: =IFERROR(TRIM(LEFT(B192,FIND("(",B192)-1)),TRIM(B192)) -> Night of the Zoopocalypse | K192: =SUBSTITUTE(SUBSTITUTE(SUBSTITUTE(SUBSTITUTE(SUBSTITUTE(SUBSTITUTE(SUBSTITUTE(SUBSTITUTE(SUBSTITUTE(SUBSTITUTE(SUBSTITUTE(SUBSTITUTE(LOWER(LEFT(SUBSTITUTE(H192,"…",""),25)),":",""),",",""),".",""),"'",""),"’",""),"!",""),"*",""),"—",""),"–",""),"-",""),"&","")," ","") -> nightofthezoopocalypse | N192: =IF(D192="","Other",D192) -> Viva Pictures
A193: 192 | B193: The Wedding Banquet | C193: 45765 | D193: Bleecker Street | E193: Romantic Comedy | F193: 2090229 | G193: 174768 | H193: =IFERROR(TRIM(LEFT(B193,FIND("(",B193)-1)),TRIM(B193)) -> The Wedding Banquet | K193: =SUBSTITUTE(SUBSTITUTE(SUBSTITUTE(SUBSTITUTE(SUBSTITUTE(SUBSTITUTE(SUBSTITUTE(SUBSTITUTE(SUBSTITUTE(SUBSTITUTE(SUBSTITUTE(SUBSTITUTE(LOWER(LEFT(SUBSTITUTE(H193,"…",""),25)),":",""),",",""),".",""),"'",""),"’",""),"!",""),"*",""),"—",""),"–",""),"-",""),"&","")," ","") -> theweddingbanquet | N193: =IF(D193="","Other",D193) -> Bleecker Street
A194: 193 | B194: Oh, Hi! | C194: 45863 | D194: Sony Pictures Cla… | E194: Romantic Comedy | F194: 2082114 | G194: 174090 | H194: =IFERROR(TRIM(LEFT(B194,FIND("(",B194)-1)),TRIM(B194)) -> Oh, Hi! | K194: =SUBSTITUTE(SUBSTITUTE(SUBSTITUTE(SUBSTITUTE(SUBSTITUTE(SUBSTITUTE(SUBSTITUTE(SUBSTITUTE(SUBSTITUTE(SUBSTITUTE(SUBSTITUTE(SUBSTITUTE(LOWER(LEFT(SUBSTITUTE(H194,"…",""),25)),":",""),",",""),".",""),"'",""),"’",""),"!",""),"*",""),"—",""),"–",""),"-",""),"&","")," ","") -> ohhi | N194: =IF(D194="","Other",D194) -> Sony Pictures Cla…
...

Sheet Global 2025
A1: Rank | B1: Release Group | C1: Worldwide | D1: Domestic | E1: % | F1: Foreign | G1: % | H1: Title (base) | I1: NormTitle | J1: Studio
A2: 1 | B2: Ne Zha 2 | C2: 2267446370 | D2: 23308176 | E2: 0.01 | F2: 2244138194 | G2: 0.99 | H2: =IFERROR(TRIM(LEFT(B2,FIND("(",B2)-1)),TRIM(B2)) -> Ne Zha 2 | I2: =SUBSTITUTE(SUBSTITUTE(SUBSTITUTE(SUBSTITUTE(SUBSTITUTE(SUBSTITUTE(SUBSTITUTE(SUBSTITUTE(SUBSTITUTE(SUBSTITUTE(SUBSTITUTE(SUBSTITUTE(LOWER(LEFT(SUBSTITUTE(H2,"…",""),25)),":",""),",",""),".",""),"'",""),"’",""),"!",""),"*",""),"—",""),"–",""),"-",""),"&","")," ","") -> nezha2 | J2: =IFERROR(INDEX('Domestic 2025'!$N:$N,MATCH($I2,'Domestic 2025'!$K:$K,0)),IFERROR(INDEX('Domestic 2025'!$N:$N,MATCH($D2,'Domestic 2025'!$F:$F,0)),"Other")) -> Other
A3: 2 | B3: Zootopia 2 | C3: 1866647950 | D3: 428130160 | E3: 0.229 | F3: 1438517790 | G3: 0.771 | H3: =IFERROR(TRIM(LEFT(B3,FIND("(",B3)-1)),TRIM(B3)) -> Zootopia 2 | I3: =SUBSTITUTE(SUBSTITUTE(SUBSTITUTE(SUBSTITUTE(SUBSTITUTE(SUBSTITUTE(SUBSTITUTE(SUBSTITUTE(SUBSTITUTE(SUBSTITUTE(SUBSTITUTE(SUBSTITUTE(LOWER(LEFT(SUBSTITUTE(H3,"…",""),25)),":",""),",",""),".",""),"'",""),"’",""),"!",""),"*",""),"—",""),"–",""),"-",""),"&","")," ","") -> zootopia2 | J3: =IFERROR(INDEX('Domestic 2025'!$N:$N,MATCH($I3,'Domestic 2025'!$K:$K,0)),IFERROR(INDEX('Domestic 2025'!$N:$N,MATCH($D3,'Domestic 2025'!$F:$F,0)),"Other")) -> Walt Disney
A4: 3 | B4: Avatar: Fire and Ash | C4: 1485999890 | D4: 404340010 | E4: 0.272 | F4: 1081659880 | G4: 0.728 | H4: =IFERROR(TRIM(LEFT(B4,FIND("(",B4)-1)),TRIM(B4)) -> Avatar: Fire and Ash | I4: =SUBSTITUTE(SUBSTITUTE(SUBSTITUTE(SUBSTITUTE(SUBSTITUTE(SUBSTITUTE(SUBSTITUTE(SUBSTITUTE(SUBSTITUTE(SUBSTITUTE(SUBSTITUTE(SUBSTITUTE(LOWER(LEFT(SUBSTITUTE(H4,"…",""),25)),":",""),",",""),".",""),"'",""),"’",""),"!",""),"*",""),"—",""),"–",""),"-",""),"&","")," ","") -> avatarfireandash | J4: =IFERROR(INDEX('Domestic 2025'!$N:$N,MATCH($I4,'Domestic 2025'!$K:$K,0)),IFERROR(INDEX('Domestic 2025'!$N:$N,MATCH($D4,'Domestic 2025'!$F:$F,0)),"Other")) -> 20th Century Stud…
A5: 4 | B5: Lilo & Stitch | C5: 1038027526 | D5: 423778855 | E5: 0.408 | F5: 614248671 | G5: 0.592 | H5: =IFERROR(TRIM(LEFT(B5,FIND("(",B5)-1)),TRIM(B5)) -> Lilo & Stitch | I5: =SUBSTITUTE(SUBSTITUTE(SUBSTITUTE(SUBSTITUTE(SUBSTITUTE(SUBSTITUTE(SUBSTITUTE(SUBSTITUTE(SUBSTITUTE(SUBSTITUTE(SUBSTITUTE(SUBSTITUTE(LOWER(LEFT(SUBSTITUTE(H5,"…",""),25)),":",""),",",""),".",""),"'",""),"’",""),"!",""),"*",""),"—",""),"–",""),"-",""),"&","")," ","") -> lilostitch | J5: =IFERROR(INDEX('Domestic 2025'!$N:$N,MATCH($I5,'Domestic 2025'!$K:$K,0)),IFERROR(INDEX('Domestic 2025'!$N:$N,MATCH($D5,'Domestic 2025'!$F:$F,0)),"Other")) -> Walt Disney
A6: 5 | B6: A Minecraft Movie | C6: 960387780 | D6: 424087780 | E6: 0.442 | F6: 536300000 | G6: 0.558 | H6: =IFERROR(TRIM(LEFT(B6,FIND("(",B6)-1)),TRIM(B6)) -> A Minecraft Movie | I6: =SUBSTITUTE(SUBSTITUTE(SUBSTITUTE(SUBSTITUTE(SUBSTITUTE(SUBSTITUTE(SUBSTITUTE(SUBSTITUTE(SUBSTITUTE(SUBSTITUTE(SUBSTITUTE(SUBSTITUTE(LOWER(LEFT(SUBSTITUTE(H6,"…",""),25)),":",""),",",""),".",""),"'",""),"’",""),"!",""),"*",""),"—",""),"–",""),"-",""),"&","")," ","") -> aminecraftmovie | J6: =IFERROR(INDEX('Domestic 2025'!$N:$N,MATCH($I6,'Domestic 2025'!$K:$K,0)),IFERROR(INDEX('Domestic 2025'!$N:$N,MATCH($D6,'Domestic 2025'!$F:$F,0)),"Other")) -> Warner Bros.
A7: 6 | B7: Jurassic World: Rebirth | C7: 869146189 | D7: 339640400 | E7: 0.391 | F7: 529505789 | G7: 0.609 | H7: =IFERROR(TRIM(LEFT(B7,FIND("(",B7)-1)),TRIM(B7)) -> Jurassic World: Rebirth | I7: =SUBSTITUTE(SUBSTITUTE(SUBSTITUTE(SUBSTITUTE(SUBSTITUTE(SUBSTITUTE(SUBSTITUTE(SUBSTITUTE(SUBSTITUTE(SUBSTITUTE(SUBSTITUTE(SUBSTITUTE(LOWER(LEFT(SUBSTITUTE(H7,"…",""),25)),":",""),",",""),".",""),"'",""),"’",""),"!",""),"*",""),"—",""),"–",""),"-",""),"&","")," ","") -> jurassicworldrebirth | J7: =IFERROR(INDEX('Domestic 2025'!$N:$N,MATCH($I7,'Domestic 2025'!$K:$K,0)),IFERROR(INDEX('Domestic 2025'!$N:$N,MATCH($D7,'Domestic 2025'!$F:$F,0)),"Other")) -> Universal
A8: 7 | B8: Demon Slayer: Kimetsu No Yaiba Infinity Castle | C8: 793498985 | D8: 136950340 | E8: 0.173 | F8: 656548645 | G8: 0.827 | H8: =IFERROR(TRIM(LEFT(B8,FIND("(",B8)-1)),TRIM(B8)) -> Demon Slayer: Kimetsu No Yaiba Infinity Castle | I8: =SUBSTITUTE(SUBSTITUTE(SUBSTITUTE(SUBSTITUTE(SUBSTITUTE(SUBSTITUTE(SUBSTITUTE(SUBSTITUTE(SUBSTITUTE(SUBSTITUTE(SUBSTITUTE(SUBSTITUTE(LOWER(LEFT(SUBSTITUTE(H8,"…",""),25)),":",""),",",""),".",""),"'",""),"’",""),"!",""),"*",""),"—",""),"–",""),"-",""),"&","")," ","") -> demonslayerkimetsuno | J8: =IFERROR(INDEX('Domestic 2025'!$N:$N,MATCH($I8,'Domestic 2025'!$K:$K,0)),IFERROR(INDEX('Domestic 2025'!$N:$N,MATCH($D8,'Domestic 2025'!$F:$F,0)),"Other")) -> Sony Pictures
A9: 8 | B9: How to Train Your Dragon | C9: 636596299 | D9: 262958100 | E9: 0.413 | F9: 373638199 | G9: 0.587 | H9: =IFERROR(TRIM(LEFT(B9,FIND("(",B9)-1)),TRIM(B9)) -> How to Train Your Dragon | I9: =SUBSTITUTE(SUBSTITUTE(SUBSTITUTE(SUBSTITUTE(SUBSTITUTE(SUBSTITUTE(SUBSTITUTE(SUBSTITUTE(SUBSTITUTE(SUBSTITUTE(SUBSTITUTE(SUBSTITUTE(LOWER(LEFT(SUBSTITUTE(H9,"…",""),25)),":",""),",",""),".",""),"'",""),"’",""),"!",""),"*",""),"—",""),"–",""),"-",""),"&","")," ","") -> howtotrainyourdragon | J9: =IFERROR(INDEX('Domestic 2025'!$N:$N,MATCH($I9,'Domestic 2025'!$K:$K,0)),IFERROR(INDEX('Domestic 2025'!$N:$N,MATCH($D9,'Domestic 2025'!$F:$F,0)),"Other")) -> Universal
A10: 9 | B10: F1: The Movie | C10: 634142436 | D10: 189642436 | E10: 0.299 | F10: 444500000 | G10: 0.701 | H10: =IFERROR(TRIM(LEFT(B10,FIND("(",B10)-1)),TRIM(B10)) -> F1: The Movie | I10: =SUBSTITUTE(SUBSTITUTE(SUBSTITUTE(SUBSTITUTE(SUBSTITUTE(SUBSTITUTE(SUBSTITUTE(SUBSTITUTE(SUBSTITUTE(SUBSTITUTE(SUBSTITUTE(SUBSTITUTE(LOWER(LEFT(SUBSTITUTE(H10,"…",""),25)),":",""),",",""),".",""),"'",""),"’",""),"!",""),"*",""),"—",""),"–",""),"-",""),"&","")," ","") -> f1themovie | J10: =IFERROR(INDEX('Domestic 2025'!$N:$N,MATCH($I10,'Domestic 2025'!$K:$K,0)),IFERROR(INDEX('Domestic 2025'!$N:$N,MATCH($D10,'Domestic 2025'!$F:$F,0)),"Other")) -> Warner Bros.
A11: 10 | B11: Superman | C11: 618723803 | D11: 354223803 | E11: 0.573 | F11: 264500000 | G11: 0.427 | H11: =IFERROR(TRIM(LEFT(B11,FIND("(",B11)-1)),TRIM(B11)) -> Superman | I11: =SUBSTITUTE(SUBSTITUTE(SUBSTITUTE(SUBSTITUTE(SUBSTITUTE(SUBSTITUTE(SUBSTITUTE(SUBSTITUTE(SUBSTITUTE(SUBSTITUTE(SUBSTITUTE(SUBSTITUTE(LOWER(LEFT(SUBSTITUTE(H11,"…",""),25)),":",""),",",""),".",""),"'",""),"’",""),"!",""),"*",""),"—",""),"–",""),"-",""),"&","")," ","") -> superman | J11: =IFERROR(INDEX('Domestic 2025'!$N:$N,MATCH($I11,'Domestic 2025'!$K:$K,0)),IFERROR(INDEX('Domestic 2025'!$N:$N,MATCH($D11,'Domestic 2025'!$F:$F,0)),"Other")) -> Warner Bros.
A12: 11 | B12: Mission: Impossible - The Final Reckoning | C12: 598767057 | D12: 197413515 | E12: 0.33 | F12: 401353542 | G12: 0.67 | H12: =IFERROR(TRIM(LEFT(B12,FIND("(",B12)-1)),TRIM(B12)) -> Mission: Impossible - The Final Reckoning | I12: =SUBSTITUTE(SUBSTITUTE(SUBSTITUTE(SUBSTITUTE(SUBSTITUTE(SUBSTITUTE(SUBSTITUTE(SUBSTITUTE(SUBSTITUTE(SUBSTITUTE(SUBSTITUTE(SUBSTITUTE(LOWER(LEFT(SUBSTITUTE(H12,"…",""),25)),":",""),",",""),".",""),"'",""),"’",""),"!",""),"*",""),"—",""),"–",""),"-",""),"&","")," ","") -> missionimpossiblethe | J12: =IFERROR(INDEX('Domestic 2025'!$N:$N,MATCH($I12,'Domestic 2025'!$K:$K,0)),IFERROR(INDEX('Domestic 2025'!$N:$N,MATCH($D12,'Domestic 2025'!$F:$F,0)),"Other")) -> Paramount Pictures
A13: 12 | B13: Wicked: For Good | C13: 540807925 | D13: 342915090 | E13: 0.634 | F13: 197892835 | G13: 0.366 | H13: =IFERROR(TRIM(LEFT(B13,FIND("(",B13)-1)),TRIM(B13)) -> Wicked: For Good | I13: =SUBSTITUTE(SUBSTITUTE(SUBSTITUTE(SUBSTITUTE(SUBSTITUTE(SUBSTITUTE(SUBSTITUTE(SUBSTITUTE(SUBSTITUTE(SUBSTITUTE(SUBSTITUTE(SUBSTITUTE(LOWER(LEFT(SUBSTITUTE(H13,"…",""),25)),":",""),",",""),".",""),"'",""),"’",""),"!",""),"*",""),"—",""),"–",""),"-",""),"&","")," ","") -> wickedforgood | J13: =IFERROR(INDEX('Domestic 2025'!$N:$N,MATCH($I13,'Domestic 2025'!$K:$K,0)),IFERROR(INDEX('Domestic 2025'!$N:$N,MATCH($D13,'Domestic 2025'!$F:$F,0)),"Other")) -> Universal
... A16: 15 | B16: The Conjuring: Last Rites | C16: 499256445 | D16: 177756445 | E16: 0.356 | F16: 321500000 | G16: 0.644 | H16: =IFERROR(TRIM(LEFT(B16,FIND("(",B16)-1)),TRIM(B16)) -> The Conjuring: Last Rites | I16: =SUBSTITUTE(SUBSTITUTE(SUBSTITUTE(SUBSTITUTE(SUBSTITUTE(SUBSTITUTE(SUBSTITUTE(SUBSTITUTE(SUBSTITUTE(SUBSTITUTE(SUBSTITUTE(SUBSTITUTE(LOWER(LEFT(SUBSTITUTE(H16,"…",""),25)),":",""),",",""),".",""),"'",""),"’",""),"!",""),"*",""),"—",""),"–",""),"-",""),"&","")," ","") -> theconjuringlastrites | J16: =IFERROR(INDEX('Domestic 2025'!$N:$N,MATCH($I16,'Domestic 2025'!$K:$K,0)),IFERROR(INDEX('Domestic 2025'!$N:$N,MATCH($D16,'Domestic 2025'!$F:$F,0)),"Other")) -> Warner Bros.
A17: 16 | B17: Dead to Rights | C17: 422789550 | D17: - | E17: - | F17: 422789550 | G17: 1 | H17: =IFERROR(TRIM(LEFT(B17,FIND("(",B17)-1)),TRIM(B17)) -> Dead to Rights | I17: =SUBSTITUTE(SUBSTITUTE(SUBSTITUTE(SUBSTITUTE(SUBSTITUTE(SUBSTITUTE(SUBSTITUTE(SUBSTITUTE(SUBSTITUTE(SUBSTITUTE(SUBSTITUTE(SUBSTITUTE(LOWER(LEFT(SUBSTITUTE(H17,"…",""),25)),":",""),",",""),".",""),"'",""),"’",""),"!",""),"*",""),"—",""),"–",""),"-",""),"&","")," ","") -> deadtorights | J17: =IFERROR(INDEX('Domestic 2025'!$N:$N,MATCH($I17,'Domestic 2025'!$K:$K,0)),IFERROR(INDEX('Domestic 2025'!$N:$N,MATCH($D17,'Domestic 2025'!$F:$F,0)),"Other")) -> Other
A18: 17 | B18: Captain America: Brave New World | C18: 415101577 | D18: 200500001 | E18: 0.483 | F18: 214601576 | G18: 0.517 | H18: =IFERROR(TRIM(LEFT(B18,FIND("(",B18)-1)),TRIM(B18)) -> Captain America: Brave New World | I18: =SUBSTITUTE(SUBSTITUTE(SUBSTITUTE(SUBSTITUTE(SUBSTITUTE(SUBSTITUTE(SUBSTITUTE(SUBSTITUTE(SUBSTITUTE(SUBSTITUTE(SUBSTITUTE(SUBSTITUTE(LOWER(LEFT(SUBSTITUTE(H18,"…",""),25)),":",""),",",""),".",""),"'",""),"’",""),"!",""),"*",""),"—",""),"–",""),"-",""),"&","")," ","") -> captainamericabravene | J18: =IFERROR(INDEX('Domestic 2025'!$N:$N,MATCH($I18,'Domestic 2025'!$K:$K,0)),IFERROR(INDEX('Domestic 2025'!$N:$N,MATCH($D18,'Domestic 2025'!$F:$F,0)),"Other")) -> Walt Disney
A19: 18 | B19: The Housemaid | C19: 400530884 | D19: 126432462 | E19: 0.316 | F19: 274098422 | G19: 0.684 | H19: =IFERROR(TRIM(LEFT(B19,FIND("(",B19)-1)),TRIM(B19)) -> The Housemaid | I19: =SUBSTITUTE(SUBSTITUTE(SUBSTITUTE(SUBSTITUTE(SUBSTITUTE(SUBSTITUTE(SUBSTITUTE(SUBSTITUTE(SUBSTITUTE(SUBSTITUTE(SUBSTITUTE(SUBSTITUTE(LOWER(LEFT(SUBSTITUTE(H19,"…",""),25)),":",""),",",""),".",""),"'",""),"’",""),"!",""),"*",""),"—",""),"–",""),"-",""),"&","")," ","") -> thehousemaid | J19: =IFERROR(INDEX('Domestic 2025'!$N:$N,MATCH($I19,'Domestic 2025'!$K:$K,0)),IFERROR(INDEX('Domestic 2025'!$N:$N,MATCH($D19,'Domestic 2025'!$F:$F,0)),"Other")) -> Lionsgate
A20: 19 | B20: Thunderbolts* | C20: 382436917 | D20: 190274328 | E20: 0.498 | F20: 192162589 | G20: 0.502 | H20: =IFERROR(TRIM(LEFT(B20,FIND("(",B20)-1)),TRIM(B20)) -> Thunderbolts* | I20: =SUBSTITUTE(SUBSTITUTE(SUBSTITUTE(SUBSTITUTE(SUBSTITUTE(SUBSTITUTE(SUBSTITUTE(SUBSTITUTE(SUBSTITUTE(SUBSTITUTE(SUBSTITUTE(SUBSTITUTE(LOWER(LEFT(SUBSTITUTE(H20,"…",""),25)),":",""),",",""),".",""),"'",""),"’",""),"!",""),"*",""),"—",""),"–",""),"-",""),"&","")," ","") -> thunderbolts | J20: =IFERROR(INDEX('Domestic 2025'!$N:$N,MATCH($I20,'Domestic 2025'!$K:$K,0)),IFERROR(INDEX('Domestic 2025'!$N:$N,MATCH($D20,'Domestic 2025'!$F:$F,0)),"Other")) -> Walt Disney
A21: 20 | B21: Sinners | C21: 370289632 | D21: 279989632 | E21: 0.756 | F21: 90300000 | G21: 0.244 | H21: =IFERROR(TRIM(LEFT(B21,FIND("(",B21)-1)),TRIM(B21)) -> Sinners | I21: =SUBSTITUTE(SUBSTITUTE(SUBSTITUTE(SUBSTITUTE(SUBSTITUTE(SUBSTITUTE(SUBSTITUTE(SUBSTITUTE(SUBSTITUTE(SUBSTITUTE(SUBSTITUTE(SUBSTITUTE(LOWER(LEFT(SUBSTITUTE(H21,"…",""),25)),":",""),",",""),".",""),"'",""),"’",""),"!",""),"*",""),"—",""),"–",""),"-",""),"&","")," ","") -> sinners | J21: =IFERROR(INDEX('Domestic 2025'!$N:$N,MATCH($I21,'Domestic 2025'!$K:$K,0)),IFERROR(INDEX('Domestic 2025'!$N:$N,MATCH($D21,'Domestic 2025'!$F:$F,0)),"Other")) -> Warner Bros.
A22: 21 | B22: Final Destination: Bloodlines | C22: 317854739 | D22: 138254739 | E22: 0.435 | F22: 179600000 | G22: 0.565 | H22: =IFERROR(TRIM(LEFT(B22,FIND("(",B22)-1)),TRIM(B22)) -> Final Destination: Bloodlines | I22: =SUBSTITUTE(SUBSTITUTE(SUBSTITUTE(SUBSTITUTE(SUBSTITUTE(SUBSTITUTE(SUBSTITUTE(SUBSTITUTE(SUBSTITUTE(SUBSTITUTE(SUBSTITUTE(SUBSTITUTE(LOWER(LEFT(SUBSTITUTE(H22,"…",""),25)),":",""),",",""),".",""),"'",""),"’",""),"!",""),"*",""),"—",""),"–",""),"-",""),"&","")," ","") -> finaldestinationbloodl | J22: =IFERROR(INDEX('Domestic 2025'!$N:$N,MATCH($I22,'Domestic 2025'!$K:$K,0)),IFERROR(INDEX('Domestic 2025'!$N:$N,MATCH($D22,'Domestic 2025'!$F:$F,0)),"Other")) -> Warner Bros.
A23: 22 | B23: 731 | C23: 274090081 | D23: 410904 | E23: 0.001 | F23: 273679177 | G23: 0.999 | H23: =IFERROR(TRIM(LEFT(B23,FIND("(",B23)-1)),TRIM(B23)) -> 731 | I23: =SUBSTITUTE(SUBSTITUTE(SUBSTITUTE(SUBSTITUTE(SUBSTITUTE(SUBSTITUTE(SUBSTITUTE(SUBSTITUTE(SUBSTITUTE(SUBSTITUTE(SUBSTITUTE(SUBSTITUTE(LOWER(LEFT(SUBSTITUTE(H23,"…",""),25)),":",""),",",""),".",""),"'",""),"’",""),"!",""),"*",""),"—",""),"–",""),"-",""),"&","")," ","") -> 731 | J23: =IFERROR(INDEX('Domestic 2025'!$N:$N,MATCH($I23,'Domestic 2025'!$K:$K,0)),IFERROR(INDEX('Domestic 2025'!$N:$N,MATCH($D23,'Domestic 2025'!$F:$F,0)),"Other")) -> Well Go USA
A24: 23 | B24: Weapons | C24: 270072492 | D24: 151572492 | E24: 0.561 | F24: 118500000 | G24: 0.439 | H24: =IFERROR(TRIM(LEFT(B24,FIND("(",B24)-1)),TRIM(B24)) -> Weapons | I24: =SUBSTITUTE(SUBSTITUTE(SUBSTITUTE(SUBSTITUTE(SUBSTITUTE(SUBSTITUTE(SUBSTITUTE(SUBSTITUTE(SUBSTITUTE(SUBSTITUTE(SUBSTITUTE(SUBSTITUTE(LOWER(LEFT(SUBSTITUTE(H24,"…",""),25)),":",""),",",""),".",""),"'",""),"’",""),"!",""),"*",""),"—",""),"–",""),"-",""),"&","")," ","") -> weapons | J24: =IFERROR(INDEX('Domestic 2025'!$N:$N,MATCH($I24,'Domestic 2025'!$K:$K,0)),IFERROR(INDEX('Domestic 2025'!$N:$N,MATCH($D24,'Domestic 2025'!$F:$F,0)),"Other")) -> Warner Bros.
A25: 24 | B25: Now You See Me: Now You Don't | C25: 246602999 | D25: 61882396 | E25: 0.251 | F25: 184720603 | G25: 0.749 | H25: =IFERROR(TRIM(LEFT(B25,FIND("(",B25)-1)),TRIM(B25)) -> Now You See Me: Now You Don't | I25: =SUBSTITUTE(SUBSTITUTE(SUBSTITUTE(SUBSTITUTE(SUBSTITUTE(SUBSTITUTE(SUBSTITUTE(SUBSTITUTE(SUBSTITUTE(SUBSTITUTE(SUBSTITUTE(SUBSTITUTE(LOWER(LEFT(SUBSTITUTE(H25,"…",""),25)),":",""),",",""),".",""),"'",""),"’",""),"!",""),"*",""),"—",""),"–",""),"-",""),"&","")," ","") -> nowyouseemenowyoud | J25: =IFERROR(INDEX('Domestic 2025'!$N:$N,MATCH($I25,'Domestic 2025'!$K:$K,0)),IFERROR(INDEX('Domestic 2025'!$N:$N,MATCH($D25,'Domestic 2025'!$F:$F,0)),"Other")) -> Lionsgate
A26: 25 | B26: The Bad Guys 2 | C26: 239753615 | D26: 82593605 | E26: 0.344 | F26: 157160010 | G26: 0.656 | H26: =IFERROR(TRIM(LEFT(B26,FIND("(",B26)-1)),TRIM(B26)) -> The Bad Guys 2 | I26: =SUBSTITUTE(SUBSTITUTE(SUBSTITUTE(SUBSTITUTE(SUBSTITUTE(SUBSTITUTE(SUBSTITUTE(SUBSTITUTE(SUBSTITUTE(SUBSTITUTE(SUBSTITUTE(SUBSTITUTE(LOWER(LEFT(SUBSTITUTE(H26,"…",""),25)),":",""),",",""),".",""),"'",""),"’",""),"!",""),"*",""),"—",""),"–",""),"-",""),"&","")," ","") -> thebadguys2 | J26: =IFERROR(INDEX('Domestic 2025'!$N:$N,MATCH($I26,'Domestic 2025'!$K:$K,0)),IFERROR(INDEX('Domestic 2025'!$N:$N,MATCH($D26,'Domestic 2025'!$F:$F,0)),"Other")) -> Universal
A27: 26 | B27: Five Nights at Freddy's 2 | C27: 238569800 | D27: 127730290 | E27: 0.535 | F27: 110839510 | G27: 0.465 | H27: =IFERROR(TRIM(LEFT(B27,FIND("(",B27)-1)),TRIM(B27)) -> Five Nights at Freddy's 2 | I27: =SUBSTITUTE(SUBSTITUTE(SUBSTITUTE(SUBSTITUTE(SUBSTITUTE(SUBSTITUTE(SUBSTITUTE(SUBSTITUTE(SUBSTITUTE(SUBSTITUTE(SUBSTITUTE(SUBSTITUTE(LOWER(LEFT(SUBSTITUTE(H27,"…",""),25)),":",""),",",""),".",""),"'",""),"’",""),"!",""),"*",""),"—",""),"–",""),"-",""),"&","")," ","") -> fivenightsatfreddys2 | J27: =IFERROR(INDEX('Domestic 2025'!$N:$N,MATCH($I27,'Domestic 2025'!$K:$K,0)),IFERROR(INDEX('Domestic 2025'!$N:$N,MATCH($D27,'Domestic 2025'!$F:$F,0)),"Other")) -> Universal
A28: 27 | B28: One Battle After Another | C28: 213121406 | D28: 72918884 | E28: 0.342 | F28: 140202522 | G28: 0.658 | H28: =IFERROR(TRIM(LEFT(B28,FIND("(",B28)-1)),TRIM(B28)) -> One Battle After Another | I28: =SUBSTITUTE(SUBSTITUTE(SUBSTITUTE(SUBSTITUTE(SUBSTITUTE(SUBSTITUTE(SUBSTITUTE(SUBSTITUTE(SUBSTITUTE(SUBSTITUTE(SUBSTITUTE(SUBSTITUTE(LOWER(LEFT(SUBSTITUTE(H28,"…",""),25)),":",""),",",""),".",""),"'",""),"’",""),"!",""),"*",""),"—",""),"–",""),"-",""),"&","")," ","") -> onebattleafteranother | J28: =IFERROR(INDEX('Domestic 2025'!$N:$N,MATCH($I28,'Domestic 2025'!$K:$K,0)),IFERROR(INDEX('Domestic 2025'!$N:$N,MATCH($D28,'Domestic 2025'!$F:$F,0)),"Other")) -> Warner Bros.
A29: 28 | B29: Snow White | C29: 205679463 | D29: 87203963 | E29: 0.424 | F29: 118475500 | G29: 0.576 | H29: =IFERROR(TRIM(LEFT(B29,FIND("(",B29)-1)),TRIM(B29)) -> Snow White | I29: =SUBSTITUTE(SUBSTITUTE(SUBSTITUTE(SUBSTITUTE(SUBSTITUTE(SUBSTITUTE(SUBSTITUTE(SUBSTITUTE(SUBSTITUTE(SUBSTITUTE(SUBSTITUTE(SUBSTITUTE(LOWER(LEFT(SUBSTITUTE(H29,"…",""),25)),":",""),",",""),".",""),"'",""),"’",""),"!",""),"*",""),"—",""),"–",""),"-",""),"&","")," ","") -> snowwhite | J29: =IFERROR(INDEX('Domestic 2025'!$N:$N,MATCH($I29,'Domestic 2025'!$K:$K,0)),IFERROR(INDEX('Domestic 2025'!$N:$N,MATCH($D29,'Domestic 2025'!$F:$F,0)),"Other")) -> Walt Disney
A30: 29 | B30: Marty Supreme | C30: 191886340 | D30: 96040064 | E30: 0.501 | F30: 95846276 | G30: 0.499 | H30: =IFERROR(TRIM(LEFT(B30,FIND("(",B30)-1)),TRIM(B30)) -> Marty Supreme | I30: =SUBSTITUTE(SUBSTITUTE(SUBSTITUTE(SUBSTITUTE(SUBSTITUTE(SUBSTITUTE(SUBSTITUTE(SUBSTITUTE(SUBSTITUTE(SUBSTITUTE(SUBSTITUTE(SUBSTITUTE(LOWER(LEFT(SUBSTITUTE(H30,"…",""),25)),":",""),",",""),".",""),"'",""),"’",""),"!",""),"*",""),"—",""),"–",""),"-",""),"&","")," ","") -> martysupreme | J30: =IFERROR(INDEX('Domestic 2025'!$N:$N,MATCH($I30,'Domestic 2025'!$K:$K,0)),IFERROR(INDEX('Domestic 2025'!$N:$N,MATCH($D30,'Domestic 2025'!$F:$F,0)),"Other")) -> A24
A31: 30 | B31: Predator: Badlands | C31: 184561056 | D31: 91083631 | E31: 0.494 | F31: 93477425 | G31: 0.506 | H31: =IFERROR(TRIM(LEFT(B31,FIND("(",B31)-1)),TRIM(B31)) -> Predator: Badlands | I31: =SUBSTITUTE(SUBSTITUTE(SUBSTITUTE(SUBSTITUTE(SUBSTITUTE(SUBSTITUTE(SUBSTITUTE(SUBSTITUTE(SUBSTITUTE(SUBSTITUTE(SUBSTITUTE(SUBSTITUTE(LOWER(LEFT(SUBSTITUTE(H31,"…",""),25)),":",""),",",""),".",""),"'",""),"’",""),"!",""),"*",""),"—",""),"–",""),"-",""),"&","")," ","") -> predatorbadlands | J31: =IFERROR(INDEX('Domestic 2025'!$N:$N,MATCH($I31,'Domestic 2025'!$K:$K,0)),IFERROR(INDEX('Domestic 2025'!$N:$N,MATCH($D31,'Domestic 2025'!$F:$F,0)),"Other")) -> 20th Century Stud…
A32: 31 | B32: The SpongeBob Movie: Search for SquarePants | C32: 169269936 | D32: 71068170 | E32: 0.42 | F32: 98201766 | G32: 0.58 | H32: =IFERROR(TRIM(LEFT(B32,FIND("(",B32)-1)),TRIM(B32)) -> The SpongeBob Movie: Search for SquarePants | I32: =SUBSTITUTE(SUBSTITUTE(SUBSTITUTE(SUBSTITUTE(SUBSTITUTE(SUBSTITUTE(SUBSTITUTE(SUBSTITUTE(SUBSTITUTE(SUBSTITUTE(SUBSTITUTE(SUBSTITUTE(LOWER(LEFT(SUBSTITUTE(H32,"…",""),25)),":",""),",",""),".",""),"'",""),"’",""),"!",""),"*",""),"—",""),"–",""),"-",""),"&","")," ","") -> thespongebobmoviesear | J32: =IFERROR(INDEX('Domestic 2025'!$N:$N,MATCH($I32,'Domestic 2025'!$K:$K,0)),IFERROR(INDEX('Domestic 2025'!$N:$N,MATCH($D32,'Domestic 2025'!$F:$F,0)),"Other")) -> Paramount Pictures
A33: 32 | B33: Detective Conan: One-Eyed Flashback | C33: 166061012 | D33: - | E33: - | F33: 166061012 | G33: 1 | H33: =IFERROR(TRIM(LEFT(B33,FIND("(",B33)-1)),TRIM(B33)) -> Detective Conan: One-Eyed Flashback | I33: =SUBSTITUTE(SUBSTITUTE(SUBSTITUTE(SUBSTITUTE(SUBSTITUTE(SUBSTITUTE(SUBSTITUTE(SUBSTITUTE(SUBSTITUTE(SUBSTITUTE(SUBSTITUTE(SUBSTITUTE(LOWER(LEFT(SUBSTITUTE(H33,"…",""),25)),":",""),",",""),".",""),"'",""),"’",""),"!",""),"*",""),"—",""),"–",""),"-",""),"&","")," ","") -> detectiveconanoneeyed | J33: =IFERROR(INDEX('Domestic 2025'!$N:$N,MATCH($I33,'Domestic 2025'!$K:$K,0)),IFERROR(INDEX('Domestic 2025'!$N:$N,MATCH($D33,'Domestic 2025'!$F:$F,0)),"Other")) -> Other
A34: 33 | B34: Chainsaw Man - The Movie: Reze Arc | C34: 162440471 | D34: 43438461 | E34: 0.267 | F34: 119002010 | G34: 0.733 | H34: =IFERROR(TRIM(LEFT(B34,FIND("(",B34)-1)),TRIM(B34)) -> Chainsaw Man - The Movie: Reze Arc | I34: =SUBSTITUTE(SUBSTITUTE(SUBSTITUTE(SUBSTITUTE(SUBSTITUTE(SUBSTITUTE(SUBSTITUTE(SUBSTITUTE(SUBSTITUTE(SUBSTITUTE(SUBSTITUTE(SUBSTITUTE(LOWER(LEFT(SUBSTITUTE(H34,"…",""),25)),":",""),",",""),".",""),"'",""),"’",""),"!",""),"*",""),"—",""),"–",""),"-",""),"&","")," ","") -> chainsawmanthemovie | J34: =IFERROR(INDEX('Domestic 2025'!$N:$N,MATCH($I34,'Domestic 2025'!$K:$K,0)),IFERROR(INDEX('Domestic 2025'!$N:$N,MATCH($D34,'Domestic 2025'!$F:$F,0)),"Other")) -> Sony Pictures
A35: 34 | B35: Elio | C35: 154291182 | D35: 72987454 | E35: 0.473 | F35: 81303728 | G35: 0.527 | H35: =IFERROR(TRIM(LEFT(B35,FIND("(",B35)-1)),TRIM(B35)) -> Elio | I35: =SUBSTITUTE(SUBSTITUTE(SUBSTITUTE(SUBSTITUTE(SUBSTITUTE(SUBSTITUTE(SUBSTITUTE(SUBSTITUTE(SUBSTITUTE(SUBSTITUTE(SUBSTITUTE(SUBSTITUTE(LOWER(LEFT(SUBSTITUTE(H35,"…",""),25)),":",""),",",""),".",""),"'",""),"’",""),"!",""),"*",""),"—",""),"–",""),"-",""),"&","")," ","") -> elio | J35: =IFERROR(INDEX('Domestic 2025'!$N:$N,MATCH($I35,'Domestic 2025'!$K:$K,0)),IFERROR(INDEX('Domestic 2025'!$N:$N,MATCH($D35,'Domestic 2025'!$F:$F,0)),"Other")) -> Walt Disney
A36: 35 | B36: Freakier Friday | C36: 153176952 | D36: 94186236 | E36: 0.615 | F36: 58990716 | G36: 0.385 | H36: =IFERROR(TRIM(LEFT(B36,FIND("(",B36)-1)),TRIM(B36)) -> Freakier Friday | I36: =SUBSTITUTE(SUBSTITUTE(SUBSTITUTE(SUBSTITUTE(SUBSTITUTE(SUBSTITUTE(SUBSTITUTE(SUBSTITUTE(SUBSTITUTE(SUBSTITUTE(SUBSTITUTE(SUBSTITUTE(LOWER(LEFT(SUBSTITUTE(H36,"…",""),25)),":",""),",",""),".",""),"'",""),"’",""),"!",""),"*",""),"—",""),"–",""),"-",""),"&","")," ","") -> freakierfriday | J36: =IFERROR(INDEX('Domestic 2025'!$N:$N,MATCH($I36,'Domestic 2025'!$K:$K,0)),IFERROR(INDEX('Domestic 2025'!$N:$N,MATCH($D36,'Domestic 2025'!$F:$F,0)),"Other")) -> Walt Disney
A37: 36 | B37: 28 Years Later | C37: 151329249 | D37: 70446897 | E37: 0.466 | F37: 80882352 | G37: 0.534 | H37: =IFERROR(TRIM(LEFT(B37,FIND("(",B37)-1)),TRIM(B37)) -> 28 Years Later | I37: =SUBSTITUTE(SUBSTITUTE(SUBSTITUTE(SUBSTITUTE(SUBSTITUTE(SUBSTITUTE(SUBSTITUTE(SUBSTITUTE(SUBSTITUTE(SUBSTITUTE(SUBSTITUTE(SUBSTITUTE(LOWER(LEFT(SUBSTITUTE(H37,"…",""),25)),":",""),",",""),".",""),"'",""),"’",""),"!",""),"*",""),"—",""),"–",""),"-",""),"&","")," ","") -> 28yearslater | J37: =IFERROR(INDEX('Domestic 2025'!$N:$N,MATCH($I37,'Domestic 2025'!$K:$K,0)),IFERROR(INDEX('Domestic 2025'!$N:$N,MATCH($D37,'Domestic 2025'!$F:$F,0)),"Other")) -> Sony Pictures
A38: 37 | B38: Dog Man | C38: 146076772 | D38: 97970355 | E38: 0.671 | F38: 48106417 | G38: 0.329 | H38: =IFERROR(TRIM(LEFT(B38,FIND("(",B38)-1)),TRIM(B38)) -> Dog Man | I38: =SUBSTITUTE(SUBSTITUTE(SUBSTITUTE(SUBSTITUTE(SUBSTITUTE(SUBSTITUTE(SUBSTITUTE(SUBSTITUTE(SUBSTITUTE(SUBSTITUTE(SUBSTITUTE(SUBSTITUTE(LOWER(LEFT(SUBSTITUTE(H38,"…",""),25)),":",""),",",""),".",""),"'",""),"’",""),"!",""),"*",""),"—",""),"–",""),"-",""),"&","")," ","") -> dogman | J38: =IFERROR(INDEX('Domestic 2025'!$N:$N,MATCH($I38,'Domestic 2025'!$K:$K,0)),IFERROR(INDEX('Domestic 2025'!$N:$N,MATCH($D38,'Domestic 2025'!$F:$F,0)),"Other")) -> Universal
A39: 38 | B39: Tron: Ares | C39: 142249983 | D39: 73161014 | E39: 0.514 | F39: 69088969 | G39: 0.486 | H39: =IFERROR(TRIM(LEFT(B39,FIND("(",B39)-1)),TRIM(B39)) -> Tron: Ares | I39: =SUBSTITUTE(SUBSTITUTE(SUBSTITUTE(SUBSTITUTE(SUBSTITUTE(SUBSTITUTE(SUBSTITUTE(SUBSTITUTE(SUBSTITUTE(SUBSTITUTE(SUBSTITUTE(SUBSTITUTE(LOWER(LEFT(SUBSTITUTE(H39,"…",""),25)),":",""),",",""),".",""),"'",""),"’",""),"!",""),"*",""),"—",""),"–",""),"-",""),"&","")," ","") -> tronares | J39: =IFERROR(INDEX('Domestic 2025'!$N:$N,MATCH($I39,'Domestic 2025'!$K:$K,0)),IFERROR(INDEX('Domestic 2025'!$N:$N,MATCH($D39,'Domestic 2025'!$F:$F,0)),"Other")) -> Walt Disney
A40: 39 | B40: Bridget Jones: Mad About the Boy | C40: 140433351 | D40: - | E40: - | F40: 140433351 | G40: 1 | H40: =IFERROR(TRIM(LEFT(B40,FIND("(",B40)-1)),TRIM(B40)) -> Bridget Jones: Mad About the Boy | I40: =SUBSTITUTE(SUBSTITUTE(SUBSTITUTE(SUBSTITUTE(SUBSTITUTE(SUBSTITUTE(SUBSTITUTE(SUBSTITUTE(SUBSTITUTE(SUBSTITUTE(SUBSTITUTE(SUBSTITUTE(LOWER(LEFT(SUBSTITUTE(H40,"…",""),25)),":",""),",",""),".",""),"'",""),"’",""),"!",""),"*",""),"—",""),"–",""),"-",""),"&","")," ","") -> bridgetjonesmadabout | J40: =IFERROR(INDEX('Domestic 2025'!$N:$N,MATCH($I40,'Domestic 2025'!$K:$K,0)),IFERROR(INDEX('Domestic 2025'!$N:$N,MATCH($D40,'Domestic 2025'!$F:$F,0)),"Other")) -> Other
A41: 40 | B41: Ballerina | C41: 140201236 | D41: 58051327 | E41: 0.414 | F41: 82149909 | G41: 0.586 | H41: =IFERROR(TRIM(LEFT(B41,FIND("(",B41)-1)),TRIM(B41)) -> Ballerina | I41: =SUBSTITUTE(SUBSTITUTE(SUBSTITUTE(SUBSTITUTE(SUBSTITUTE(SUBSTITUTE(SUBSTITUTE(SUBSTITUTE(SUBSTITUTE(SUBSTITUTE(SUBSTITUTE(SUBSTITUTE(LOWER(LEFT(SUBSTITUTE(H41,"…",""),25)),":",""),",",""),".",""),"'",""),"’",""),"!",""),"*",""),"—",""),"–",""),"-",""),"&","")," ","") -> ballerina | J41: =IFERROR(INDEX('Domestic 2025'!$N:$N,MATCH($I41,'Domestic 2025'!$K:$K,0)),IFERROR(INDEX('Domestic 2025'!$N:$N,MATCH($D41,'Domestic 2025'!$F:$F,0)),"Other")) -> Lionsgate
A42: 41 | B42: Dhurandhar | C42: 137246897 | D42: 19702994 | E42: 0.144 | F42: 117543903 | G42: 0.856 | H42: =IFERROR(TRIM(LEFT(B42,FIND("(",B42)-1)),TRIM(B42)) -> Dhurandhar | I42: =SUBSTITUTE(SUBSTITUTE(SUBSTITUTE(SUBSTITUTE(SUBSTITUTE(SUBSTITUTE(SUBSTITUTE(SUBSTITUTE(SUBSTITUTE(SUBSTITUTE(SUBSTITUTE(SUBSTITUTE(LOWER(LEFT(SUBSTITUTE(H42,"…",""),25)),":",""),",",""),".",""),"'",""),"’",""),"!",""),"*",""),"—",""),"–",""),"-",""),"&","")," ","") -> dhurandhar | J42: =IFERROR(INDEX('Domestic 2025'!$N:$N,MATCH($I42,'Domestic 2025'!$K:$K,0)),IFERROR(INDEX('Domestic 2025'!$N:$N,MATCH($D42,'Domestic 2025'!$F:$F,0)),"Other")) -> Yash Raj Films
A43: 42 | B43: Anaconda | C43: 135390406 | D43: 65098148 | E43: 0.481 | F43: 70292258 | G43: 0.519 | H43: =IFERROR(TRIM(LEFT(B43,FIND("(",B43)-1)),TRIM(B43)) -> Anaconda | I43: =SUBSTITUTE(SUBSTITUTE(SUBSTITUTE(SUBSTITUTE(SUBSTITUTE(SUBSTITUTE(SUBSTITUTE(SUBSTITUTE(SUBSTITUTE(SUBSTITUTE(SUBSTITUTE(SUBSTITUTE(LOWER(LEFT(SUBSTITUTE(H43,"…",""),25)),":",""),",",""),".",""),"'",""),"’",""),"!",""),"*",""),"—",""),"–",""),"-",""),"&","")," ","") -> anaconda | J43: =IFERROR(INDEX('Domestic 2025'!$N:$N,MATCH($I43,'Domestic 2025'!$K:$K,0)),IFERROR(INDEX('Domestic 2025'!$N:$N,MATCH($D43,'Domestic 2025'!$F:$F,0)),"Other")) -> Sony Pictures
A44: 43 | B44: Kokuho | C44: 134555814 | D44: 1119136 | E44: 0.008 | F44: 133436678 | G44: 0.992 | H44: =IFERROR(TRIM(LEFT(B44,FIND("(",B44)-1)),TRIM(B44)) -> Kokuho | I44: =SUBSTITUTE(SUBSTITUTE(SUBSTITUTE(SUBSTITUTE(SUBSTITUTE(SUBSTITUTE(SUBSTITUTE(SUBSTITUTE(SUBSTITUTE(SUBSTITUTE(SUBSTITUTE(SUBSTITUTE(LOWER(LEFT(SUBSTITUTE(H44,"…",""),25)),":",""),",",""),".",""),"'",""),"’",""),"!",""),"*",""),"—",""),"–",""),"-",""),"&","")," ","") -> kokuho | J44: =IFERROR(INDEX('Domestic 2025'!$N:$N,MATCH($I44,'Domestic 2025'!$K:$K,0)),IFERROR(INDEX('Domestic 2025'!$N:$N,MATCH($D44,'Domestic 2025'!$F:$F,0)),"Other")) -> GKIDS
A45: 44 | B45: Mickey 17 | C45: 133542263 | D45: 46142263 | E45: 0.346 | F45: 87400000 | G45: 0.654 | H45: =IFERROR(TRIM(LEFT(B45,FIND("(",B45)-1)),TRIM(B45)) -> Mickey 17 | I45: =SUBSTITUTE(SUBSTITUTE(SUBSTITUTE(SUBSTITUTE(SUBSTITUTE(SUBSTITUTE(SUBSTITUTE(SUBSTITUTE(SUBSTITUTE(SUBSTITUTE(SUBSTITUTE(SUBSTITUTE(LOWER(LEFT(SUBSTITUTE(H45,"…",""),25)),":",""),",",""),".",""),"'",""),"’",""),"!",""),"*",""),"—",""),"–",""),"-",""),"&","")," ","") -> mickey17 | J45: =IFERROR(INDEX('Domestic 2025'!$N:$N,MATCH($I45,'Domestic 2025'!$K:$K,0)),IFERROR(INDEX('Domestic 2025'!$N:$N,MATCH($D45,'Domestic 2025'!$F:$F,0)),"Other")) -> Warner Bros.
A46: 45 | B46: Black Phone 2 | C46: 132248152 | D46: 77378880 | E46: 0.585 | F46: 54869272 | G46: 0.415 | H46: =IFERROR(TRIM(LEFT(B46,FIND("(",B46)-1)),TRIM(B46)) -> Black Phone 2 | I46: =SUBSTITUTE(SUBSTITUTE(SUBSTITUTE(SUBSTITUTE(SUBSTITUTE(SUBSTITUTE(SUBSTITUTE(SUBSTITUTE(SUBSTITUTE(SUBSTITUTE(SUBSTITUTE(SUBSTITUTE(LOWER(LEFT(SUBSTITUTE(H46,"…",""),25)),":",""),",",""),".",""),"'",""),"’",""),"!",""),"*",""),"—",""),"–",""),"-",""),"&","")," ","") -> blackphone2 | J46: =IFERROR(INDEX('Domestic 2025'!$N:$N,MATCH($I46,'Domestic 2025'!$K:$K,0)),IFERROR(INDEX('Domestic 2025'!$N:$N,MATCH($D46,'Domestic 2025'!$F:$F,0)),"Other")) -> Universal
A47: 46 | B47: Smurfs | C47: 124157356 | D47: 31075170 | E47: 0.25 | F47: 93082186 | G47: 0.75 | H47: =IFERROR(TRIM(LEFT(B47,FIND("(",B47)-1)),TRIM(B47)) -> Smurfs | I47: =SUBSTITUTE(SUBSTITUTE(SUBSTITUTE(SUBSTITUTE(SUBSTITUTE(SUBSTITUTE(SUBSTITUTE(SUBSTITUTE(SUBSTITUTE(SUBSTITUTE(SUBSTITUTE(SUBSTITUTE(LOWER(LEFT(SUBSTITUTE(H47,"…",""),25)),":",""),",",""),".",""),"'",""),"’",""),"!",""),"*",""),"—",""),"–",""),"-",""),"&","")," ","") -> smurfs | J47: =IFERROR(INDEX('Domestic 2025'!$N:$N,MATCH($I47,'Domestic 2025'!$K:$K,0)),IFERROR(INDEX('Domestic 2025'!$N:$N,MATCH($D47,'Domestic 2025'!$F:$F,0)),"Other")) -> Paramount Pictures
A48: 47 | B48: Karate Kid: Legends | C48: 117105466 | D48: 52547391 | E48: 0.449 | F48: 64558075 | G48: 0.551 | H48: =IFERROR(TRIM(LEFT(B48,FIND("(",B48)-1)),TRIM(B48)) -> Karate Kid: Legends | I48: =SUBSTITUTE(SUBSTITUTE(SUBSTITUTE(SUBSTITUTE(SUBSTITUTE(SUBSTITUTE(SUBSTITUTE(SUBSTITUTE(SUBSTITUTE(SUBSTITUTE(SUBSTITUTE(SUBSTITUTE(LOWER(LEFT(SUBSTITUTE(H48,"…",""),25)),":",""),",",""),".",""),"'",""),"’",""),"!",""),"*",""),"—",""),"–",""),"-",""),"&","")," ","") -> karatekidlegends | J48: =IFERROR(INDEX('Domestic 2025'!$N:$N,MATCH($I48,'Domestic 2025'!$K:$K,0)),IFERROR(INDEX('Domestic 2025'!$N:$N,MATCH($D48,'Domestic 2025'!$F:$F,0)),"Other")) -> Sony Pictures
A49: 48 | B49: Hamnet | C49: 108954968 | D49: 24208900 | E49: 0.222 | F49: 84746068 | G49: 0.778 | H49: =IFERROR(TRIM(LEFT(B49,FIND("(",B49)-1)),TRIM(B49)) -> Hamnet | I49: =SUBSTITUTE(SUBSTITUTE(SUBSTITUTE(SUBSTITUTE(SUBSTITUTE(SUBSTITUTE(SUBSTITUTE(SUBSTITUTE(SUBSTITUTE(SUBSTITUTE(SUBSTITUTE(SUBSTITUTE(LOWER(LEFT(SUBSTITUTE(H49,"…",""),25)),":",""),",",""),".",""),"'",""),"’",""),"!",""),"*",""),"—",""),"–",""),"-",""),"&","")," ","") -> hamnet | J49: =IFERROR(INDEX('Domestic 2025'!$N:$N,MATCH($I49,'Domestic 2025'!$K:$K,0)),IFERROR(INDEX('Domestic 2025'!$N:$N,MATCH($D49,'Domestic 2025'!$F:$F,0)),"Other")) -> Focus Features
A50: 49 | B50: Materialists | C50: 105649413 | D50: 36521973 | E50: 0.346 | F50: 69127440 | G50: 0.654 | H50: =IFERROR(TRIM(LEFT(B50,FIND("(",B50)-1)),TRIM(B50)) -> Materialists | I50: =SUBSTITUTE(SUBSTITUTE(SUBSTITUTE(SUBSTITUTE(SUBSTITUTE(SUBSTITUTE(SUBSTITUTE(SUBSTITUTE(SUBSTITUTE(SUBSTITUTE(SUBSTITUTE(SUBSTITUTE(LOWER(LEFT(SUBSTITUTE(H50,"…",""),25)),":",""),",",""),".",""),"'",""),"’",""),"!",""),"*",""),"—",""),"–",""),"-",""),"&","")," ","") -> materialists | J50: =IFERROR(INDEX('Domestic 2025'!$N:$N,MATCH($I50,'Domestic 2025'!$K:$K,0)),IFERROR(INDEX('Domestic 2025'!$N:$N,MATCH($D50,'Domestic 2025'!$F:$F,0)),"Other")) -> A24
A51: 50 | B51: Downton Abbey: The Grand Finale | C51: 103546113 | D51: 44996590 | E51: 0.435 | F51: 58549523 | G51: 0.565 | H51: =IFERROR(TRIM(LEFT(B51,FIND("(",B51)-1)),TRIM(B51)) -> Downton Abbey: The Grand Finale | I51: =SUBSTITUTE(SUBSTITUTE(SUBSTITUTE(SUBSTITUTE(SUBSTITUTE(SUBSTITUTE(SUBSTITUTE(SUBSTITUTE(SUBSTITUTE(SUBSTITUTE(SUBSTITUTE(SUBSTITUTE(LOWER(LEFT(SUBSTITUTE(H51,"…",""),25)),":",""),",",""),".",""),"'",""),"’",""),"!",""),"*",""),"—",""),"–",""),"-",""),"&","")," ","") -> downtonabbeythegrand | J51: =IFERROR(INDEX('Domestic 2025'!$N:$N,MATCH($I51,'Domestic 2025'!$K:$K,0)),IFERROR(INDEX('Domestic 2025'!$N:$N,MATCH($D51,'Domestic 2025'!$F:$F,0)),"Other")) -> Focus Features
A52: 51 | B52: The Accountant 2 | C52: 103323366 | D52: 65523366 | E52: 0.634 | F52: 37800000 | G52: 0.366 | H52: =IFERROR(TRIM(LEFT(B52,FIND("(",B52)-1)),TRIM(B52)) -> The Accountant 2 | I52: =SUBSTITUTE(SUBSTITUTE(SUBSTITUTE(SUBSTITUTE(SUBSTITUTE(SUBSTITUTE(SUBSTITUTE(SUBSTITUTE(SUBSTITUTE(SUBSTITUTE(SUBSTITUTE(SUBSTITUTE(LOWER(LEFT(SUBSTITUTE(H52,"…",""),25)),":",""),",",""),".",""),"'",""),"’",""),"!",""),"*",""),"—",""),"–",""),"-",""),"&","")," ","") -> theaccountant2 | J52: =IFERROR(INDEX('Domestic 2025'!$N:$N,MATCH($I52,'Domestic 2025'!$K:$K,0)),IFERROR(INDEX('Domestic 2025'!$N:$N,MATCH($D52,'Domestic 2025'!$F:$F,0)),"Other")) -> Amazon MGM Studios
... A57: 56 | B57: David | C57: 88344394 | D57: 80382774 | E57: 0.91 | F57: 7961620 | G57: 0.09 | H57: =IFERROR(TRIM(LEFT(B57,FIND("(",B57)-1)),TRIM(B57)) -> David | I57: =SUBSTITUTE(SUBSTITUTE(SUBSTITUTE(SUBSTITUTE(SUBSTITUTE(SUBSTITUTE(SUBSTITUTE(SUBSTITUTE(SUBSTITUTE(SUBSTITUTE(SUBSTITUTE(SUBSTITUTE(LOWER(LEFT(SUBSTITUTE(H57,"…",""),25)),":",""),",",""),".",""),"'",""),"’",""),"!",""),"*",""),"—",""),"–",""),"-",""),"&","")," ","") -> david | J57: =IFERROR(INDEX('Domestic 2025'!$N:$N,MATCH($I57,'Domestic 2025'!$K:$K,0)),IFERROR(INDEX('Domestic 2025'!$N:$N,MATCH($D57,'Domestic 2025'!$F:$F,0)),"Other")) -> Angel Studios
A58: 57 | B58: Buen Camino | C58: 87529797 | D58: - | E58: - | F58: 87529797 | G58: 1 | H58: =IFERROR(TRIM(LEFT(B58,FIND("(",B58)-1)),TRIM(B58)) -> Buen Camino | I58: =SUBSTITUTE(SUBSTITUTE(SUBSTITUTE(SUBSTITUTE(SUBSTITUTE(SUBSTITUTE(SUBSTITUTE(SUBSTITUTE(SUBSTITUTE(SUBSTITUTE(SUBSTITUTE(SUBSTITUTE(LOWER(LEFT(SUBSTITUTE(H58,"…",""),25)),":",""),",",""),".",""),"'",""),"’",""),"!",""),"*",""),"—",""),"–",""),"-",""),"&","")," ","") -> buencamino | J58: =IFERROR(INDEX('Domestic 2025'!$N:$N,MATCH($I58,'Domestic 2025'!$K:$K,0)),IFERROR(INDEX('Domestic 2025'!$N:$N,MATCH($D58,'Domestic 2025'!$F:$F,0)),"Other")) -> Other
A59: 58 | B59: The King of Kings | C59: 83612781 | D59: 60270106 | E59: 0.721 | F59: 23342675 | G59: 0.279 | H59: =IFERROR(TRIM(LEFT(B59,FIND("(",B59)-1)),TRIM(B59)) -> The King of Kings | I59: =SUBSTITUTE(SUBSTITUTE(SUBSTITUTE(SUBSTITUTE(SUBSTITUTE(SUBSTITUTE(SUBSTITUTE(SUBSTITUTE(SUBSTITUTE(SUBSTITUTE(SUBSTITUTE(SUBSTITUTE(LOWER(LEFT(SUBSTITUTE(H59,"…",""),25)),":",""),",",""),".",""),"'",""),"’",""),"!",""),"*",""),"—",""),"–",""),"-",""),"&","")," ","") -> thekingofkings | J59: =IFERROR(INDEX('Domestic 2025'!$N:$N,MATCH($I59,'Domestic 2025'!$K:$K,0)),IFERROR(INDEX('Domestic 2025'!$N:$N,MATCH($D59,'Domestic 2025'!$F:$F,0)),"Other")) -> Angel Studios
A60: 59 | B60: Gabby's Dollhouse: The Movie | C60: 80832387 | D60: 32011820 | E60: 0.396 | F60: 48820567 | G60: 0.604 | H60: =IFERROR(TRIM(LEFT(B60,FIND("(",B60)-1)),TRIM(B60)) -> Gabby's Dollhouse: The Movie | I60: =SUBSTITUTE(SUBSTITUTE(SUBSTITUTE(SUBSTITUTE(SUBSTITUTE(SUBSTITUTE(SUBSTITUTE(SUBSTITUTE(SUBSTITUTE(SUBSTITUTE(SUBSTITUTE(SUBSTITUTE(LOWER(LEFT(SUBSTITUTE(H60,"…",""),25)),":",""),",",""),".",""),"'",""),"’",""),"!",""),"*",""),"—",""),"–",""),"-",""),"&","")," ","") -> gabbysdollhousethemo | J60: =IFERROR(INDEX('Domestic 2025'!$N:$N,MATCH($I60,'Domestic 2025'!$K:$K,0)),IFERROR(INDEX('Domestic 2025'!$N:$N,MATCH($D60,'Domestic 2025'!$F:$F,0)),"Other")) -> Universal
A61: 60 | B61: Cheburashka 2 | C61: 79178509 | D61: - | E61: - | F61: 79178509 | G61: 1 | H61: =IFERROR(TRIM(LEFT(B61,FIND("(",B61)-1)),TRIM(B61)) -> Cheburashka 2 | I61: =SUBSTITUTE(SUBSTITUTE(SUBSTITUTE(SUBSTITUTE(SUBSTITUTE(SUBSTITUTE(SUBSTITUTE(SUBSTITUTE(SUBSTITUTE(SUBSTITUTE(SUBSTITUTE(SUBSTITUTE(LOWER(LEFT(SUBSTITUTE(H61,"…",""),25)),":",""),",",""),".",""),"'",""),"’",""),"!",""),"*",""),"—",""),"–",""),"-",""),"&","")," ","") -> cheburashka2 | J61: =IFERROR(INDEX('Domestic 2025'!$N:$N,MATCH($I61,'Domestic 2025'!$K:$K,0)),IFERROR(INDEX('Domestic 2025'!$N:$N,MATCH($D61,'Domestic 2025'!$F:$F,0)),"Other")) -> Other
A62: 61 | B62: Nuremberg | C62: 70531391 | D62: 14524693 | E62: 0.206 | F62: 56006698 | G62: 0.794 | H62: =IFERROR(TRIM(LEFT(B62,FIND("(",B62)-1)),TRIM(B62)) -> Nuremberg | I62: =SUBSTITUTE(SUBSTITUTE(SUBSTITUTE(SUBSTITUTE(SUBSTITUTE(SUBSTITUTE(SUBSTITUTE(SUBSTITUTE(SUBSTITUTE(SUBSTITUTE(SUBSTITUTE(SUBSTITUTE(LOWER(LEFT(SUBSTITUTE(H62,"…",""),25)),":",""),",",""),".",""),"'",""),"’",""),"!",""),"*",""),"—",""),"–",""),"-",""),"&","")," ","") -> nuremberg | J62: =IFERROR(INDEX('Domestic 2025'!$N:$N,MATCH($I62,'Domestic 2025'!$K:$K,0)),IFERROR(INDEX('Domestic 2025'!$N:$N,MATCH($D62,'Domestic 2025'!$F:$F,0)),"Other")) -> Sony Pictures Cla…
A63: 62 | B63: The Running Man | C63: 69486523 | D63: 37815641 | E63: 0.544 | F63: 31670882 | G63: 0.456 | H63: =IFERROR(TRIM(LEFT(B63,FIND("(",B63)-1)),TRIM(B63)) -> The Running Man | I63: =SUBSTITUTE(SUBSTITUTE(SUBSTITUTE(SUBSTITUTE(SUBSTITUTE(SUBSTITUTE(SUBSTITUTE(SUBSTITUTE(SUBSTITUTE(SUBSTITUTE(SUBSTITUTE(SUBSTITUTE(LOWER(LEFT(SUBSTITUTE(H63,"…",""),25)),":",""),",",""),".",""),"'",""),"’",""),"!",""),"*",""),"—",""),"–",""),"-",""),"&","")," ","") -> therunningman | J63: =IFERROR(INDEX('Domestic 2025'!$N:$N,MATCH($I63,'Domestic 2025'!$K:$K,0)),IFERROR(INDEX('Domestic 2025'!$N:$N,MATCH($D63,'Domestic 2025'!$F:$F,0)),"Other")) -> Paramount Pictures
A64: 63 | B64: The Monkey | C64: 68871071 | D64: 39724909 | E64: 0.577 | F64: 29146162 | G64: 0.423 | H64: =IFERROR(TRIM(LEFT(B64,FIND("(",B64)-1)),TRIM(B64)) -> The Monkey | I64: =SUBSTITUTE(SUBSTITUTE(SUBSTITUTE(SUBSTITUTE(SUBSTITUTE(SUBSTITUTE(SUBSTITUTE(SUBSTITUTE(SUBSTITUTE(SUBSTITUTE(SUBSTITUTE(SUBSTITUTE(LOWER(LEFT(SUBSTITUTE(H64,"…",""),25)),":",""),",",""),".",""),"'",""),"’",""),"!",""),"*",""),"—",""),"–",""),"-",""),"&","")," ","") -> themonkey | J64: =IFERROR(INDEX('Domestic 2025'!$N:$N,MATCH($I64,'Domestic 2025'!$K:$K,0)),IFERROR(INDEX('Domestic 2025'!$N:$N,MATCH($D64,'Domestic 2025'!$F:$F,0)),"Other")) -> Neon
A65: 64 | B65: I Know What You Did Last Summer | C65: 64808120 | D65: 32165634 | E65: 0.496 | F65: 32642486 | G65: 0.504 | H65: =IFERROR(TRIM(LEFT(B65,FIND("(",B65)-1)),TRIM(B65)) -> I Know What You Did Last Summer | I65: =SUBSTITUTE(SUBSTITUTE(SUBSTITUTE(SUBSTITUTE(SUBSTITUTE(SUBSTITUTE(SUBSTITUTE(SUBSTITUTE(SUBSTITUTE(SUBSTITUTE(SUBSTITUTE(SUBSTITUTE(LOWER(LEFT(SUBSTITUTE(H65,"…",""),25)),":",""),",",""),".",""),"'",""),"’",""),"!",""),"*",""),"—",""),"–",""),"-",""),"&","")," ","") -> iknowwhatyoudidlast | J65: =IFERROR(INDEX('Domestic 2025'!$N:$N,MATCH($I65,'Domestic 2025'!$K:$K,0)),IFERROR(INDEX('Domestic 2025'!$N:$N,MATCH($D65,'Domestic 2025'!$F:$F,0)),"Other")) -> Sony Pictures
A66: 65 | B66: The Long Walk | C66: 63249525 | D66: 35163573 | E66: 0.556 | F66: 28085952 | G66: 0.444 | H66: =IFERROR(TRIM(LEFT(B66,FIND("(",B66)-1)),TRIM(B66)) -> The Long Walk | I66: =SUBSTITUTE(SUBSTITUTE(SUBSTITUTE(SUBSTITUTE(SUBSTITUTE(SUBSTITUTE(SUBSTITUTE(SUBSTITUTE(SUBSTITUTE(SUBSTITUTE(SUBSTITUTE(SUBSTITUTE(LOWER(LEFT(SUBSTITUTE(H66,"…",""),25)),":",""),",",""),".",""),"'",""),"’",""),"!",""),"*",""),"—",""),"–",""),"-",""),"&","")," ","") -> thelongwalk | J66: =IFERROR(INDEX('Domestic 2025'!$N:$N,MATCH($I66,'Domestic 2025'!$K:$K,0)),IFERROR(INDEX('Domestic 2025'!$N:$N,MATCH($D66,'Domestic 2025'!$F:$F,0)),"Other")) -> Lionsgate
A67: 66 | B67: Den of Thieves: Pantera | C67: 58371508 | D67: 36015016 | E67: 0.617 | F67: 22356492 | G67: 0.383 | H67: =IFERROR(TRIM(LEFT(B67,FIND("(",B67)-1)),TRIM(B67)) -> Den of Thieves: Pantera | I67: =SUBSTITUTE(SUBSTITUTE(SUBSTITUTE(SUBSTITUTE(SUBSTITUTE(SUBSTITUTE(SUBSTITUTE(SUBSTITUTE(SUBSTITUTE(SUBSTITUTE(SUBSTITUTE(SUBSTITUTE(LOWER(LEFT(SUBSTITUTE(H67,"…",""),25)),":",""),",",""),".",""),"'",""),"’",""),"!",""),"*",""),"—",""),"–",""),"-",""),"&","")," ","") -> denofthievespantera | J67: =IFERROR(INDEX('Domestic 2025'!$N:$N,MATCH($I67,'Domestic 2025'!$K:$K,0)),IFERROR(INDEX('Domestic 2025'!$N:$N,MATCH($D67,'Domestic 2025'!$F:$F,0)),"Other")) -> Lionsgate
A68: 67 | B68: Song Sung Blue | C68: 58290126 | D68: 39185290 | E68: 0.672 | F68: 19104836 | G68: 0.328 | H68: =IFERROR(TRIM(LEFT(B68,FIND("(",B68)-1)),TRIM(B68)) -> Song Sung Blue | I68: =SUBSTITUTE(SUBSTITUTE(SUBSTITUTE(SUBSTITUTE(SUBSTITUTE(SUBSTITUTE(SUBSTITUTE(SUBSTITUTE(SUBSTITUTE(SUBSTITUTE(SUBSTITUTE(SUBSTITUTE(LOWER(LEFT(SUBSTITUTE(H68,"…",""),25)),":",""),",",""),".",""),"'",""),"’",""),"!",""),"*",""),"—",""),"–",""),"-",""),"&","")," ","") -> songsungblue | J68: =IFERROR(INDEX('Domestic 2025'!$N:$N,MATCH($I68,'Domestic 2025'!$K:$K,0)),IFERROR(INDEX('Domestic 2025'!$N:$N,MATCH($D68,'Domestic 2025'!$F:$F,0)),"Other")) -> Focus Features
A69: 68 | B69: Manitou's Canoe | C69: 57840726 | D69: - | E69: - | F69: 57840726 | G69: 1 | H69: =IFERROR(TRIM(LEFT(B69,FIND("(",B69)-1)),TRIM(B69)) -> Manitou's Canoe | I69: =SUBSTITUTE(SUBSTITUTE(SUBSTITUTE(SUBSTITUTE(SUBSTITUTE(SUBSTITUTE(SUBSTITUTE(SUBSTITUTE(SUBSTITUTE(SUBSTITUTE(SUBSTITUTE(SUBSTITUTE(LOWER(LEFT(SUBSTITUTE(H69,"…",""),25)),":",""),",",""),".",""),"'",""),"’",""),"!",""),"*",""),"—",""),"–",""),"-",""),"&","")," ","") -> manitouscanoe | J69: =IFERROR(INDEX('Domestic 2025'!$N:$N,MATCH($I69,'Domestic 2025'!$K:$K,0)),IFERROR(INDEX('Domestic 2025'!$N:$N,MATCH($D69,'Domestic 2025'!$F:$F,0)),"Other")) -> Other
A70: 69 | B70: Star Wars: Episode III - Revenge of the Sith 20th anniversary | C70: 55560312 | D70: 34107714 | E70: 0.614 | F70: 21452598 | G70: 0.386 | H70: =IFERROR(TRIM(LEFT(B70,FIND("(",B70)-1)),TRIM(B70)) -> Star Wars: Episode III - Revenge of the Sith 20th anniversary | I70: =SUBSTITUTE(SUBSTITUTE(SUBSTITUTE(SUBSTITUTE(SUBSTITUTE(SUBSTITUTE(SUBSTITUTE(SUBSTITUTE(SUBSTITUTE(SUBSTITUTE(SUBSTITUTE(SUBSTITUTE(LOWER(LEFT(SUBSTITUTE(H70,"…",""),25)),":",""),",",""),".",""),"'",""),"’",""),"!",""),"*",""),"—",""),"–",""),"-",""),"&","")," ","") -> starwarsepisodeiii | J70: =IFERROR(INDEX('Domestic 2025'!$N:$N,MATCH($I70,'Domestic 2025'!$K:$K,0)),IFERROR(INDEX('Domestic 2025'!$N:$N,MATCH($D70,'Domestic 2025'!$F:$F,0)),"Other")) -> 20th Century Stud…
A71: 70 | B71: Until Dawn | C71: 54105064 | D71: 20172192 | E71: 0.373 | F71: 33932872 | G71: 0.627 | H71: =IFERROR(TRIM(LEFT(B71,FIND("(",B71)-1)),TRIM(B71)) -> Until Dawn | I71: =SUBSTITUTE(SUBSTITUTE(SUBSTITUTE(SUBSTITUTE(SUBSTITUTE(SUBSTITUTE(SUBSTITUTE(SUBSTITUTE(SUBSTITUTE(SUBSTITUTE(SUBSTITUTE(SUBSTITUTE(LOWER(LEFT(SUBSTITUTE(H71,"…",""),25)),":",""),",",""),".",""),"'",""),"’",""),"!",""),"*",""),"—",""),"–",""),"-",""),"&","")," ","") -> untildawn | J71: =IFERROR(INDEX('Domestic 2025'!$N:$N,MATCH($I71,'Domestic 2025'!$K:$K,0)),IFERROR(INDEX('Domestic 2025'!$N:$N,MATCH($D71,'Domestic 2025'!$F:$F,0)),"Other")) -> Sony Pictures
A72: 71 | B72: The Roses | C72: 51989385 | D72: 15298844 | E72: 0.294 | F72: 36690541 | G72: 0.706 | H72: =IFERROR(TRIM(LEFT(B72,FIND("(",B72)-1)),TRIM(B72)) -> The Roses | I72: =SUBSTITUTE(SUBSTITUTE(SUBSTITUTE(SUBSTITUTE(SUBSTITUTE(SUBSTITUTE(SUBSTITUTE(SUBSTITUTE(SUBSTITUTE(SUBSTITUTE(SUBSTITUTE(SUBSTITUTE(LOWER(LEFT(SUBSTITUTE(H72,"…",""),25)),":",""),",",""),".",""),"'",""),"’",""),"!",""),"*",""),"—",""),"–",""),"-",""),"&","")," ","") -> theroses | J72: =IFERROR(INDEX('Domestic 2025'!$N:$N,MATCH($I72,'Domestic 2025'!$K:$K,0)),IFERROR(INDEX('Domestic 2025'!$N:$N,MATCH($D72,'Domestic 2025'!$F:$F,0)),"Other")) -> Searchlight Pictu…
A73: 72 | B73: One of Them Days | C73: 51896264 | D73: 50054690 | E73: 0.965 | F73: 1841574 | G73: 0.035 | H73: =IFERROR(TRIM(LEFT(B73,FIND("(",B73)-1)),TRIM(B73)) -> One of Them Days | I73: =SUBSTITUTE(SUBSTITUTE(SUBSTITUTE(SUBSTITUTE(SUBSTITUTE(SUBSTITUTE(SUBSTITUTE(SUBSTITUTE(SUBSTITUTE(SUBSTITUTE(SUBSTITUTE(SUBSTITUTE(LOWER(LEFT(SUBSTITUTE(H73,"…",""),25)),":",""),",",""),".",""),"'",""),"’",""),"!",""),"*",""),"—",""),"–",""),"-",""),"&","")," ","") -> oneofthemdays | J73: =IFERROR(INDEX('Domestic 2025'!$N:$N,MATCH($I73,'Domestic 2025'!$K:$K,0)),IFERROR(INDEX('Domestic 2025'!$N:$N,MATCH($D73,'Domestic 2025'!$F:$F,0)),"Other")) -> Sony Pictures
A74: 73 | B74: Taylor Swift: The Official Release Party of a Showgirl | C74: 50062774 | D74: 34062774 | E74: 0.68 | F74: 16000000 | G74: 0.32 | H74: =IFERROR(TRIM(LEFT(B74,FIND("(",B74)-1)),TRIM(B74)) -> Taylor Swift: The Official Release Party of a Showgirl | I74: =SUBSTITUTE(SUBSTITUTE(SUBSTITUTE(SUBSTITUTE(SUBSTITUTE(SUBSTITUTE(SUBSTITUTE(SUBSTITUTE(SUBSTITUTE(SUBSTITUTE(SUBSTITUTE(SUBSTITUTE(LOWER(LEFT(SUBSTITUTE(H74,"…",""),25)),":",""),",",""),".",""),"'",""),"’",""),"!",""),"*",""),"—",""),"–",""),"-",""),"&","")," ","") -> taylorswifttheofficia | J74: =IFERROR(INDEX('Domestic 2025'!$N:$N,MATCH($I74,'Domestic 2025'!$K:$K,0)),IFERROR(INDEX('Domestic 2025'!$N:$N,MATCH($D74,'Domestic 2025'!$F:$F,0)),"Other")) -> AMC Theatres Dist…
A75: 74 | B75: Flight Risk | C75: 48701987 | D75: 29783527 | E75: 0.612 | F75: 18918460 | G75: 0.388 | H75: =IFERROR(TRIM(LEFT(B75,FIND("(",B75)-1)),TRIM(B75)) -> Flight Risk | I75: =SUBSTITUTE(SUBSTITUTE(SUBSTITUTE(SUBSTITUTE(SUBSTITUTE(SUBSTITUTE(SUBSTITUTE(SUBSTITUTE(SUBSTITUTE(SUBSTITUTE(SUBSTITUTE(SUBSTITUTE(LOWER(LEFT(SUBSTITUTE(H75,"…",""),25)),":",""),",",""),".",""),"'",""),"’",""),"!",""),"*",""),"—",""),"–",""),"-",""),"&","")," ","") -> flightrisk | J75: =IFERROR(INDEX('Domestic 2025'!$N:$N,MATCH($I75,'Domestic 2025'!$K:$K,0)),IFERROR(INDEX('Domestic 2025'!$N:$N,MATCH($D75,'Domestic 2025'!$F:$F,0)),"Other")) -> Lionsgate
A76: 75 | B76: Springsteen: Deliver Me from Nowhere | C76: 45240624 | D76: 22638297 | E76: 0.5 | F76: 22602327 | G76: 0.5 | H76: =IFERROR(TRIM(LEFT(B76,FIND("(",B76)-1)),TRIM(B76)) -> Springsteen: Deliver Me from Nowhere | I76: =SUBSTITUTE(SUBSTITUTE(SUBSTITUTE(SUBSTITUTE(SUBSTITUTE(SUBSTITUTE(SUBSTITUTE(SUBSTITUTE(SUBSTITUTE(SUBSTITUTE(SUBSTITUTE(SUBSTITUTE(LOWER(LEFT(SUBSTITUTE(H76,"…",""),25)),":",""),",",""),".",""),"'",""),"’",""),"!",""),"*",""),"—",""),"–",""),"-",""),"&","")," ","") -> springsteendelivermef | J76: =IFERROR(INDEX('Domestic 2025'!$N:$N,MATCH($I76,'Domestic 2025'!$K:$K,0)),IFERROR(INDEX('Domestic 2025'!$N:$N,MATCH($D76,'Domestic 2025'!$F:$F,0)),"Other")) -> 20th Century Stud…
A77: 76 | B77: Jujutsu Kaisen: Execution | C77: 44457030 | D77: 16583133 | E77: 0.373 | F77: 27873897 | G77: 0.627 | H77: =IFERROR(TRIM(LEFT(B77,FIND("(",B77)-1)),TRIM(B77)) -> Jujutsu Kaisen: Execution | I77: =SUBSTITUTE(SUBSTITUTE(SUBSTITUTE(SUBSTITUTE(SUBSTITUTE(SUBSTITUTE(SUBSTITUTE(SUBSTITUTE(SUBSTITUTE(SUBSTITUTE(SUBSTITUTE(SUBSTITUTE(LOWER(LEFT(SUBSTITUTE(H77,"…",""),25)),":",""),",",""),".",""),"'",""),"’",""),"!",""),"*",""),"—",""),"–",""),"-",""),"&","")," ","") -> jujutsukaisenexecution | J77: =IFERROR(INDEX('Domestic 2025'!$N:$N,MATCH($I77,'Domestic 2025'!$K:$K,0)),IFERROR(INDEX('Domestic 2025'!$N:$N,MATCH($D77,'Domestic 2025'!$F:$F,0)),"Other")) -> GKIDS
A78: 77 | B78: Exit 8 | C78: 43892680 | D78: 3735090 | E78: 0.085 | F78: 40157590 | G78: 0.915 | H78: =IFERROR(TRIM(LEFT(B78,FIND("(",B78)-1)),TRIM(B78)) -> Exit 8 | I78: =SUBSTITUTE(SUBSTITUTE(SUBSTITUTE(SUBSTITUTE(SUBSTITUTE(SUBSTITUTE(SUBSTITUTE(SUBSTITUTE(SUBSTITUTE(SUBSTITUTE(SUBSTITUTE(SUBSTITUTE(LOWER(LEFT(SUBSTITUTE(H78,"…",""),25)),":",""),",",""),".",""),"'",""),"’",""),"!",""),"*",""),"—",""),"–",""),"-",""),"&","")," ","") -> exit8 | J78: =IFERROR(INDEX('Domestic 2025'!$N:$N,MATCH($I78,'Domestic 2025'!$K:$K,0)),IFERROR(INDEX('Domestic 2025'!$N:$N,MATCH($D78,'Domestic 2025'!$F:$F,0)),"Other")) -> Other
A79: 78 | B79: Black Bag | C79: 43887905 | D79: 21474035 | E79: 0.489 | F79: 22413870 | G79: 0.511 | H79: =IFERROR(TRIM(LEFT(B79,FIND("(",B79)-1)),TRIM(B79)) -> Black Bag | I79: =SUBSTITUTE(SUBSTITUTE(SUBSTITUTE(SUBSTITUTE(SUBSTITUTE(SUBSTITUTE(SUBSTITUTE(SUBSTITUTE(SUBSTITUTE(SUBSTITUTE(SUBSTITUTE(SUBSTITUTE(LOWER(LEFT(SUBSTITUTE(H79,"…",""),25)),":",""),",",""),".",""),"'",""),"’",""),"!",""),"*",""),"—",""),"–",""),"-",""),"&","")," ","") -> blackbag | J79: =IFERROR(INDEX('Domestic 2025'!$N:$N,MATCH($I79,'Domestic 2025'!$K:$K,0)),IFERROR(INDEX('Domestic 2025'!$N:$N,MATCH($D79,'Domestic 2025'!$F:$F,0)),"Other")) -> Focus Features
A80: 79 | B80: Bugonia | C80: 43523384 | D80: 17692390 | E80: 0.407 | F80: 25830994 | G80: 0.593 | H80: =IFERROR(TRIM(LEFT(B80,FIND("(",B80)-1)),TRIM(B80)) -> Bugonia | I80: =SUBSTITUTE(SUBSTITUTE(SUBSTITUTE(SUBSTITUTE(SUBSTITUTE(SUBSTITUTE(SUBSTITUTE(SUBSTITUTE(SUBSTITUTE(SUBSTITUTE(SUBSTITUTE(SUBSTITUTE(LOWER(LEFT(SUBSTITUTE(H80,"…",""),25)),":",""),",",""),".",""),"'",""),"’",""),"!",""),"*",""),"—",""),"–",""),"-",""),"&","")," ","") -> bugonia | J80: =IFERROR(INDEX('Domestic 2025'!$N:$N,MATCH($I80,'Domestic 2025'!$K:$K,0)),IFERROR(INDEX('Domestic 2025'!$N:$N,MATCH($D80,'Domestic 2025'!$F:$F,0)),"Other")) -> Focus Features
A81: 80 | B81: The Wizard of the Emerald City | C81: 43514205 | D81: - | E81: - | F81: 43514205 | G81: 1 | H81: =IFERROR(TRIM(LEFT(B81,FIND("(",B81)-1)),TRIM(B81)) -> The Wizard of the Emerald City | I81: =SUBSTITUTE(SUBSTITUTE(SUBSTITUTE(SUBSTITUTE(SUBSTITUTE(SUBSTITUTE(SUBSTITUTE(SUBSTITUTE(SUBSTITUTE(SUBSTITUTE(SUBSTITUTE(SUBSTITUTE(LOWER(LEFT(SUBSTITUTE(H81,"…",""),25)),":",""),",",""),".",""),"'",""),"’",""),"!",""),"*",""),"—",""),"–",""),"-",""),"&","")," ","") -> thewizardoftheemerald | J81: =IFERROR(INDEX('Domestic 2025'!$N:$N,MATCH($I81,'Domestic 2025'!$K:$K,0)),IFERROR(INDEX('Domestic 2025'!$N:$N,MATCH($D81,'Domestic 2025'!$F:$F,0)),"Other")) -> Other
A82: 81 | B82: Nobody 2 | C82: 43285109 | D82: 21604985 | E82: 0.499 | F82: 21680124 | G82: 0.501 | H82: =IFERROR(TRIM(LEFT(B82,FIND("(",B82)-1)),TRIM(B82)) -> Nobody 2 | I82: =SUBSTITUTE(SUBSTITUTE(SUBSTITUTE(SUBSTITUTE(SUBSTITUTE(SUBSTITUTE(SUBSTITUTE(SUBSTITUTE(SUBSTITUTE(SUBSTITUTE(SUBSTITUTE(SUBSTITUTE(LOWER(LEFT(SUBSTITUTE(H82,"…",""),25)),":",""),",",""),".",""),"'",""),"’",""),"!",""),"*",""),"—",""),"–",""),"-",""),"&","")," ","") -> nobody2 | J82: =IFERROR(INDEX('Domestic 2025'!$N:$N,MATCH($I82,'Domestic 2025'!$K:$K,0)),IFERROR(INDEX('Domestic 2025'!$N:$N,MATCH($D82,'Domestic 2025'!$F:$F,0)),"Other")) -> Universal
A83: 82 | B83: Dracula | C83: 42415061 | D83: 13053400 | E83: 0.308 | F83: 29361661 | G83: 0.692 | H83: =IFERROR(TRIM(LEFT(B83,FIND("(",B83)-1)),TRIM(B83)) -> Dracula | I83: =SUBSTITUTE(SUBSTITUTE(SUBSTITUTE(SUBSTITUTE(SUBSTITUTE(SUBSTITUTE(SUBSTITUTE(SUBSTITUTE(SUBSTITUTE(SUBSTITUTE(SUBSTITUTE(SUBSTITUTE(LOWER(LEFT(SUBSTITUTE(H83,"…",""),25)),":",""),",",""),".",""),"'",""),"’",""),"!",""),"*",""),"—",""),"–",""),"-",""),"&","")," ","") -> dracula | J83: =IFERROR(INDEX('Domestic 2025'!$N:$N,MATCH($I83,'Domestic 2025'!$K:$K,0)),IFERROR(INDEX('Domestic 2025'!$N:$N,MATCH($D83,'Domestic 2025'!$F:$F,0)),"Other")) -> 1-2 Special
A84: 83 | B84: The Phoenician Scheme | C84: 40566381 | D84: 19555015 | E84: 0.482 | F84: 21011366 | G84: 0.518 | H84: =IFERROR(TRIM(LEFT(B84,FIND("(",B84)-1)),TRIM(B84)) -> The Phoenician Scheme | I84: =SUBSTITUTE(SUBSTITUTE(SUBSTITUTE(SUBSTITUTE(SUBSTITUTE(SUBSTITUTE(SUBSTITUTE(SUBSTITUTE(SUBSTITUTE(SUBSTITUTE(SUBSTITUTE(SUBSTITUTE(LOWER(LEFT(SUBSTITUTE(H84,"…",""),25)),":",""),",",""),".",""),"'",""),"’",""),"!",""),"*",""),"—",""),"–",""),"-",""),"&","")," ","") -> thephoenicianscheme | J84: =IFERROR(INDEX('Domestic 2025'!$N:$N,MATCH($I84,'Domestic 2025'!$K:$K,0)),IFERROR(INDEX('Domestic 2025'!$N:$N,MATCH($D84,'Domestic 2025'!$F:$F,0)),"Other")) -> Focus Features
A85: 84 | B85: No Other Choice | C85: 40215145 | D85: 10011860 | E85: 0.249 | F85: 30203285 | G85: 0.751 | H85: =IFERROR(TRIM(LEFT(B85,FIND("(",B85)-1)),TRIM(B85)) -> No Other Choice | I85: =SUBSTITUTE(SUBSTITUTE(SUBSTITUTE(SUBSTITUTE(SUBSTITUTE(SUBSTITUTE(SUBSTITUTE(SUBSTITUTE(SUBSTITUTE(SUBSTITUTE(SUBSTITUTE(SUBSTITUTE(LOWER(LEFT(SUBSTITUTE(H85,"…",""),25)),":",""),",",""),".",""),"'",""),"’",""),"!",""),"*",""),"—",""),"–",""),"-",""),"&","")," ","") -> nootherchoice | J85: =IFERROR(INDEX('Domestic 2025'!$N:$N,MATCH($I85,'Domestic 2025'!$K:$K,0)),IFERROR(INDEX('Domestic 2025'!$N:$N,MATCH($D85,'Domestic 2025'!$F:$F,0)),"Other")) -> Neon
A86: 85 | B86: Doraemon: Nobita's Art World Tales | C86: 40180353 | D86: - | E86: - | F86: 40180353 | G86: 1 | H86: =IFERROR(TRIM(LEFT(B86,FIND("(",B86)-1)),TRIM(B86)) -> Doraemon: Nobita's Art World Tales | I86: =SUBSTITUTE(SUBSTITUTE(SUBSTITUTE(SUBSTITUTE(SUBSTITUTE(SUBSTITUTE(SUBSTITUTE(SUBSTITUTE(SUBSTITUTE(SUBSTITUTE(SUBSTITUTE(SUBSTITUTE(LOWER(LEFT(SUBSTITUTE(H86,"…",""),25)),":",""),",",""),".",""),"'",""),"’",""),"!",""),"*",""),"—",""),"–",""),"-",""),"&","")," ","") -> doraemonnobitasartwo | J86: =IFERROR(INDEX('Domestic 2025'!$N:$N,MATCH($I86,'Domestic 2025'!$K:$K,0)),IFERROR(INDEX('Domestic 2025'!$N:$N,MATCH($D86,'Domestic 2025'!$F:$F,0)),"Other")) -> Other
A87: 86 | B87: Bring Her Back | C87: 39410222 | D87: 19333305 | E87: 0.491 | F87: 20076917 | G87: 0.509 | H87: =IFERROR(TRIM(LEFT(B87,FIND("(",B87)-1)),TRIM(B87)) -> Bring Her Back | I87: =SUBSTITUTE(SUBSTITUTE(SUBSTITUTE(SUBSTITUTE(SUBSTITUTE(SUBSTITUTE(SUBSTITUTE(SUBSTITUTE(SUBSTITUTE(SUBSTITUTE(SUBSTITUTE(SUBSTITUTE(LOWER(LEFT(SUBSTITUTE(H87,"…",""),25)),":",""),",",""),".",""),"'",""),"’",""),"!",""),"*",""),"—",""),"–",""),"-",""),"&","")," ","") -> bringherback | J87: =IFERROR(INDEX('Domestic 2025'!$N:$N,MATCH($I87,'Domestic 2025'!$K:$K,0)),IFERROR(INDEX('Domestic 2025'!$N:$N,MATCH($D87,'Domestic 2025'!$F:$F,0)),"Other")) -> A24
A88: 87 | B88: M3GAN 2.0 | C88: 39083707 | D88: 24101280 | E88: 0.617 | F88: 14982427 | G88: 0.383 | H88: =IFERROR(TRIM(LEFT(B88,FIND("(",B88)-1)),TRIM(B88)) -> M3GAN 2.0 | I88: =SUBSTITUTE(SUBSTITUTE(SUBSTITUTE(SUBSTITUTE(SUBSTITUTE(SUBSTITUTE(SUBSTITUTE(SUBSTITUTE(SUBSTITUTE(SUBSTITUTE(SUBSTITUTE(SUBSTITUTE(LOWER(LEFT(SUBSTITUTE(H88,"…",""),25)),":",""),",",""),".",""),"'",""),"’",""),"!",""),"*",""),"—",""),"–",""),"-",""),"&","")," ","") -> m3gan20 | J88: =IFERROR(INDEX('Domestic 2025'!$N:$N,MATCH($I88,'Domestic 2025'!$K:$K,0)),IFERROR(INDEX('Domestic 2025'!$N:$N,MATCH($D88,'Domestic 2025'!$F:$F,0)),"Other")) -> Universal
A89: 88 | B89: Companion | C89: 36969122 | D89: 20869122 | E89: 0.565 | F89: 16100000 | G89: 0.435 | H89: =IFERROR(TRIM(LEFT(B89,FIND("(",B89)-1)),TRIM(B89)) -> Companion | I89: =SUBSTITUTE(SUBSTITUTE(SUBSTITUTE(SUBSTITUTE(SUBSTITUTE(SUBSTITUTE(SUBSTITUTE(SUBSTITUTE(SUBSTITUTE(SUBSTITUTE(SUBSTITUTE(SUBSTITUTE(LOWER(LEFT(SUBSTITUTE(H89,"…",""),25)),":",""),",",""),".",""),"'",""),"’",""),"!",""),"*",""),"—",""),"–",""),"-",""),"&","")," ","") -> companion | J89: =IFERROR(INDEX('Domestic 2025'!$N:$N,MATCH($I89,'Domestic 2025'!$K:$K,0)),IFERROR(INDEX('Domestic 2025'!$N:$N,MATCH($D89,'Domestic 2025'!$F:$F,0)),"Other")) -> Warner Bros.
A90: 89 | B90: My Daughter Is a Zombie | C90: 36966774 | D90: - | E90: - | F90: 36966774 | G90: 1 | H90: =IFERROR(TRIM(LEFT(B90,FIND("(",B90)-1)),TRIM(B90)) -> My Daughter Is a Zombie | I90: =SUBSTITUTE(SUBSTITUTE(SUBSTITUTE(SUBSTITUTE(SUBSTITUTE(SUBSTITUTE(SUBSTITUTE(SUBSTITUTE(SUBSTITUTE(SUBSTITUTE(SUBSTITUTE(SUBSTITUTE(LOWER(LEFT(SUBSTITUTE(H90,"…",""),25)),":",""),",",""),".",""),"'",""),"’",""),"!",""),"*",""),"—",""),"–",""),"-",""),"&","")," ","") -> mydaughterisazombie | J90: =IFERROR(INDEX('Domestic 2025'!$N:$N,MATCH($I90,'Domestic 2025'!$K:$K,0)),IFERROR(INDEX('Domestic 2025'!$N:$N,MATCH($D90,'Domestic 2025'!$F:$F,0)),"Other")) -> Other
A91: 90 | B91: Eternity | C91: 35858277 | D91: 16210244 | E91: 0.452 | F91: 19648033 | G91: 0.548 | H91: =IFERROR(TRIM(LEFT(B91,FIND("(",B91)-1)),TRIM(B91)) -> Eternity | I91: =SUBSTITUTE(SUBSTITUTE(SUBSTITUTE(SUBSTITUTE(SUBSTITUTE(SUBSTITUTE(SUBSTITUTE(SUBSTITUTE(SUBSTITUTE(SUBSTITUTE(SUBSTITUTE(SUBSTITUTE(LOWER(LEFT(SUBSTITUTE(H91,"…",""),25)),":",""),",",""),".",""),"'",""),"’",""),"!",""),"*",""),"—",""),"–",""),"-",""),"&","")," ","") -> eternity | J91: =IFERROR(INDEX('Domestic 2025'!$N:$N,MATCH($I91,'Domestic 2025'!$K:$K,0)),IFERROR(INDEX('Domestic 2025'!$N:$N,MATCH($D91,'Domestic 2025'!$F:$F,0)),"Other")) -> A24
A92: 91 | B92: Warfare | C92: 34902602 | D92: 26000309 | E92: 0.745 | F92: 8902293 | G92: 0.255 | H92: =IFERROR(TRIM(LEFT(B92,FIND("(",B92)-1)),TRIM(B92)) -> Warfare | I92: =SUBSTITUTE(SUBSTITUTE(SUBSTITUTE(SUBSTITUTE(SUBSTITUTE(SUBSTITUTE(SUBSTITUTE(SUBSTITUTE(SUBSTITUTE(SUBSTITUTE(SUBSTITUTE(SUBSTITUTE(LOWER(LEFT(SUBSTITUTE(H92,"…",""),25)),":",""),",",""),".",""),"'",""),"’",""),"!",""),"*",""),"—",""),"–",""),"-",""),"&","")," ","") -> warfare | J92: =IFERROR(INDEX('Domestic 2025'!$N:$N,MATCH($I92,'Domestic 2025'!$K:$K,0)),IFERROR(INDEX('Domestic 2025'!$N:$N,MATCH($D92,'Domestic 2025'!$F:$F,0)),"Other")) -> A24
A93: 92 | B93: Roofman | C93: 34852212 | D93: 22739882 | E93: 0.652 | F93: 12112330 | G93: 0.348 | H93: =IFERROR(TRIM(LEFT(B93,FIND("(",B93)-1)),TRIM(B93)) -> Roofman | I93: =SUBSTITUTE(SUBSTITUTE(SUBSTITUTE(SUBSTITUTE(SUBSTITUTE(SUBSTITUTE(SUBSTITUTE(SUBSTITUTE(SUBSTITUTE(SUBSTITUTE(SUBSTITUTE(SUBSTITUTE(LOWER(LEFT(SUBSTITUTE(H93,"…",""),25)),":",""),",",""),".",""),"'",""),"’",""),"!",""),"*",""),"—",""),"–",""),"-",""),"&","")," ","") -> roofman | J93: =IFERROR(INDEX('Domestic 2025'!$N:$N,MATCH($I93,'Domestic 2025'!$K:$K,0)),IFERROR(INDEX('Domestic 2025'!$N:$N,MATCH($D93,'Domestic 2025'!$F:$F,0)),"Other")) -> Paramount Pictures
A94: 93 | B94: Together | C94: 34747399 | D94: 21273159 | E94: 0.612 | F94: 13474240 | G94: 0.388 | H94: =IFERROR(TRIM(LEFT(B94,FIND("(",B94)-1)),TRIM(B94)) -> Together | I94: =SUBSTITUTE(SUBSTITUTE(SUBSTITUTE(SUBSTITUTE(SUBSTITUTE(SUBSTITUTE(SUBSTITUTE(SUBSTITUTE(SUBSTITUTE(SUBSTITUTE(SUBSTITUTE(SUBSTITUTE(LOWER(LEFT(SUBSTITUTE(H94,"…",""),25)),":",""),",",""),".",""),"'",""),"’",""),"!",""),"*",""),"—",""),"–",""),"-",""),"&","")," ","") -> together | J94: =IFERROR(INDEX('Domestic 2025'!$N:$N,MATCH($I94,'Domestic 2025'!$K:$K,0)),IFERROR(INDEX('Domestic 2025'!$N:$N,MATCH($D94,'Domestic 2025'!$F:$F,0)),"Other")) -> Neon
A95: 94 | B95: Novocaine | C95: 34536061 | D95: 19861854 | E95: 0.575 | F95: 14674207 | G95: 0.425 | H95: =IFERROR(TRIM(LEFT(B95,FIND("(",B95)-1)),TRIM(B95)) -> Novocaine | I95: =SUBSTITUTE(SUBSTITUTE(SUBSTITUTE(SUBSTITUTE(SUBSTITUTE(SUBSTITUTE(SUBSTITUTE(SUBSTITUTE(SUBSTITUTE(SUBSTITUTE(SUBSTITUTE(SUBSTITUTE(LOWER(LEFT(SUBSTITUTE(H95,"…",""),25)),":",""),",",""),".",""),"'",""),"’",""),"!",""),"*",""),"—",""),"–",""),"-",""),"&","")," ","") -> novocaine | J95: =IFERROR(INDEX('Domestic 2025'!$N:$N,MATCH($I95,'Domestic 2025'!$K:$K,0)),IFERROR(INDEX('Domestic 2025'!$N:$N,MATCH($D95,'Domestic 2025'!$F:$F,0)),"Other")) -> Paramount Pictures
A96: 95 | B96: Wolf Man | C96: 34154366 | D96: 20707280 | E96: 0.606 | F96: 13447086 | G96: 0.394 | H96: =IFERROR(TRIM(LEFT(B96,FIND("(",B96)-1)),TRIM(B96)) -> Wolf Man | I96: =SUBSTITUTE(SUBSTITUTE(SUBSTITUTE(SUBSTITUTE(SUBSTITUTE(SUBSTITUTE(SUBSTITUTE(SUBSTITUTE(SUBSTITUTE(SUBSTITUTE(SUBSTITUTE(SUBSTITUTE(LOWER(LEFT(SUBSTITUTE(H96,"…",""),25)),":",""),",",""),".",""),"'",""),"’",""),"!",""),"*",""),"—",""),"–",""),"-",""),"&","")," ","") -> wolfman | J96: =IFERROR(INDEX('Domestic 2025'!$N:$N,MATCH($I96,'Domestic 2025'!$K:$K,0)),IFERROR(INDEX('Domestic 2025'!$N:$N,MATCH($D96,'Domestic 2025'!$F:$F,0)),"Other")) -> Universal
A97: 96 | B97: Tokyo Mer the Movie: Nankai Mission | C97: 33931597 | D97: - | E97: - | F97: 33931597 | G97: 1 | H97: =IFERROR(TRIM(LEFT(B97,FIND("(",B97)-1)),TRIM(B97)) -> Tokyo Mer the Movie: Nankai Mission | I97: =SUBSTITUTE(SUBSTITUTE(SUBSTITUTE(SUBSTITUTE(SUBSTITUTE(SUBSTITUTE(SUBSTITUTE(SUBSTITUTE(SUBSTITUTE(SUBSTITUTE(SUBSTITUTE(SUBSTITUTE(LOWER(LEFT(SUBSTITUTE(H97,"…",""),25)),":",""),",",""),".",""),"'",""),"’",""),"!",""),"*",""),"—",""),"–",""),"-",""),"&","")," ","") -> tokyomerthemovienank | J97: =IFERROR(INDEX('Domestic 2025'!$N:$N,MATCH($I97,'Domestic 2025'!$K:$K,0)),IFERROR(INDEX('Domestic 2025'!$N:$N,MATCH($D97,'Domestic 2025'!$F:$F,0)),"Other")) -> Other
A98: 97 | B98: Caught Stealing | C98: 33251665 | D98: 19005242 | E98: 0.572 | F98: 14246423 | G98: 0.428 | H98: =IFERROR(TRIM(LEFT(B98,FIND("(",B98)-1)),TRIM(B98)) -> Caught Stealing | I98: =SUBSTITUTE(SUBSTITUTE(SUBSTITUTE(SUBSTITUTE(SUBSTITUTE(SUBSTITUTE(SUBSTITUTE(SUBSTITUTE(SUBSTITUTE(SUBSTITUTE(SUBSTITUTE(SUBSTITUTE(LOWER(LEFT(SUBSTITUTE(H98,"…",""),25)),":",""),",",""),".",""),"'",""),"’",""),"!",""),"*",""),"—",""),"–",""),"-",""),"&","")," ","") -> caughtstealing | J98: =IFERROR(INDEX('Domestic 2025'!$N:$N,MATCH($I98,'Domestic 2025'!$K:$K,0)),IFERROR(INDEX('Domestic 2025'!$N:$N,MATCH($D98,'Domestic 2025'!$F:$F,0)),"Other")) -> Sony Pictures
A99: 98 | B99: Heart Eyes | C99: 33129099 | D99: 30415738 | E99: 0.918 | F99: 2713361 | G99: 0.082 | H99: =IFERROR(TRIM(LEFT(B99,FIND("(",B99)-1)),TRIM(B99)) -> Heart Eyes | I99: =SUBSTITUTE(SUBSTITUTE(SUBSTITUTE(SUBSTITUTE(SUBSTITUTE(SUBSTITUTE(SUBSTITUTE(SUBSTITUTE(SUBSTITUTE(SUBSTITUTE(SUBSTITUTE(SUBSTITUTE(LOWER(LEFT(SUBSTITUTE(H99,"…",""),25)),":",""),",",""),".",""),"'",""),"’",""),"!",""),"*",""),"—",""),"–",""),"-",""),"&","")," ","") -> hearteyes | J99: =IFERROR(INDEX('Domestic 2025'!$N:$N,MATCH($I99,'Domestic 2025'!$K:$K,0)),IFERROR(INDEX('Domestic 2025'!$N:$N,MATCH($D99,'Domestic 2025'!$F:$F,0)),"Other")) -> Sony Pictures
A100: 99 | B100: Fredonia: The Movie | C100: 31114453 | D100: - | E100: - | F100: 31114453 | G100: 1 | H100: =IFERROR(TRIM(LEFT(B100,FIND("(",B100)-1)),TRIM(B100)) -> Fredonia: The Movie | I100: =SUBSTITUTE(SUBSTITUTE(SUBSTITUTE(SUBSTITUTE(SUBSTITUTE(SUBSTITUTE(SUBSTITUTE(SUBSTITUTE(SUBSTITUTE(SUBSTITUTE(SUBSTITUTE(SUBSTITUTE(LOWER(LEFT(SUBSTITUTE(H100,"…",""),25)),":",""),",",""),".",""),"'",""),"’",""),"!",""),"*",""),"—",""),"–",""),"-",""),"&","")," ","") -> fredoniathemovie | J100: =IFERROR(INDEX('Domestic 2025'!$N:$N,MATCH($I100,'Domestic 2025'!$K:$K,0)),IFERROR(INDEX('Domestic 2025'!$N:$N,MATCH($D100,'Domestic 2025'!$F:$F,0)),"Other")) -> Other
A101: 100 | B101: Pinocchio | C101: 30846911 | D101: - | E101: - | F101: 30846911 | G101: 1 | H101: =IFERROR(TRIM(LEFT(B101,FIND("(",B101)-1)),TRIM(B101)) -> Pinocchio | I101: =SUBSTITUTE(SUBSTITUTE(SUBSTITUTE(SUBSTITUTE(SUBSTITUTE(SUBSTITUTE(SUBSTITUTE(SUBSTITUTE(SUBSTITUTE(SUBSTITUTE(SUBSTITUTE(SUBSTITUTE(LOWER(LEFT(SUBSTITUTE(H101,"…",""),25)),":",""),",",""),".",""),"'",""),"’",""),"!",""),"*",""),"—",""),"–",""),"-",""),"&","")," ","") -> pinocchio | J101: =IFERROR(INDEX('Domestic 2025'!$N:$N,MATCH($I101,'Domestic 2025'!$K:$K,0)),IFERROR(INDEX('Domestic 2025'!$N:$N,MATCH($D101,'Domestic 2025'!$F:$F,0)),"Other")) -> Other
A102: 101 | B102: Drop | C102: 28744167 | D102: 16600805 | E102: 0.578 | F102: 12143362 | G102: 0.422 | H102: =IFERROR(TRIM(LEFT(B102,FIND("(",B102)-1)),TRIM(B102)) -> Drop | I102: =SUBSTITUTE(SUBSTITUTE(SUBSTITUTE(SUBSTITUTE(SUBSTITUTE(SUBSTITUTE(SUBSTITUTE(SUBSTITUTE(SUBSTITUTE(SUBSTITUTE(SUBSTITUTE(SUBSTITUTE(LOWER(LEFT(SUBSTITUTE(H102,"…",""),25)),":",""),",",""),".",""),"'",""),"’",""),"!",""),"*",""),"—",""),"–",""),"-",""),"&","")," ","") -> drop | J102: =IFERROR(INDEX('Domestic 2025'!$N:$N,MATCH($I102,'Domestic 2025'!$K:$K,0)),IFERROR(INDEX('Domestic 2025'!$N:$N,MATCH($D102,'Domestic 2025'!$F:$F,0)),"Other")) -> Universal
A103: 102 | B103: School of Magical Animals 4 | C103: 27968598 | D103: - | E103: - | F103: 27968598 | G103: 1 | H103: =IFERROR(TRIM(LEFT(B103,FIND("(",B103)-1)),TRIM(B103)) -> School of Magical Animals 4 | I103: =SUBSTITUTE(SUBSTITUTE(SUBSTITUTE(SUBSTITUTE(SUBSTITUTE(SUBSTITUTE(SUBSTITUTE(SUBSTITUTE(SUBSTITUTE(SUBSTITUTE(SUBSTITUTE(SUBSTITUTE(LOWER(LEFT(SUBSTITUTE(H103,"…",""),25)),":",""),",",""),".",""),"'",""),"’",""),"!",""),"*",""),"—",""),"–",""),"-",""),"&","")," ","") -> schoolofmagicalanimals | J103: =IFERROR(INDEX('Domestic 2025'!$N:$N,MATCH($I103,'Domestic 2025'!$K:$K,0)),IFERROR(INDEX('Domestic 2025'!$N:$N,MATCH($D103,'Domestic 2025'!$F:$F,0)),"Other")) -> Other
A104: 103 | B104: Him | C104: 27834512 | D104: 25009605 | E104: 0.899 | F104: 2824907 | G104: 0.101 | H104: =IFERROR(TRIM(LEFT(B104,FIND("(",B104)-1)),TRIM(B104)) -> Him | I104: =SUBSTITUTE(SUBSTITUTE(SUBSTITUTE(SUBSTITUTE(SUBSTITUTE(SUBSTITUTE(SUBSTITUTE(SUBSTITUTE(SUBSTITUTE(SUBSTITUTE(SUBSTITUTE(SUBSTITUTE(LOWER(LEFT(SUBSTITUTE(H104,"…",""),25)),":",""),",",""),".",""),"'",""),"’",""),"!",""),"*",""),"—",""),"–",""),"-",""),"&","")," ","") -> him | J104: =IFERROR(INDEX('Domestic 2025'!$N:$N,MATCH($I104,'Domestic 2025'!$K:$K,0)),IFERROR(INDEX('Domestic 2025'!$N:$N,MATCH($D104,'Domestic 2025'!$F:$F,0)),"Other")) -> Universal
A105: 104 | B105: Red Rain | C105: 27028224 | D105: - | E105: - | F105: 27028224 | G105: 1 | H105: =IFERROR(TRIM(LEFT(B105,FIND("(",B105)-1)),TRIM(B105)) -> Red Rain | I105: =SUBSTITUTE(SUBSTITUTE(SUBSTITUTE(SUBSTITUTE(SUBSTITUTE(SUBSTITUTE(SUBSTITUTE(SUBSTITUTE(SUBSTITUTE(SUBSTITUTE(SUBSTITUTE(SUBSTITUTE(LOWER(LEFT(SUBSTITUTE(H105,"…",""),25)),":",""),",",""),".",""),"'",""),"’",""),"!",""),"*",""),"—",""),"–",""),"-",""),"&","")," ","") -> redrain | J105: =IFERROR(INDEX('Domestic 2025'!$N:$N,MATCH($I105,'Domestic 2025'!$K:$K,0)),IFERROR(INDEX('Domestic 2025'!$N:$N,MATCH($D105,'Domestic 2025'!$F:$F,0)),"Other")) -> Other
A106: 105 | B106: Rental Family | C106: 26758365 | D106: 10047429 | E106: 0.375 | F106: 16710936 | G106: 0.625 | H106: =IFERROR(TRIM(LEFT(B106,FIND("(",B106)-1)),TRIM(B106)) -> Rental Family | I106: =SUBSTITUTE(SUBSTITUTE(SUBSTITUTE(SUBSTITUTE(SUBSTITUTE(SUBSTITUTE(SUBSTITUTE(SUBSTITUTE(SUBSTITUTE(SUBSTITUTE(SUBSTITUTE(SUBSTITUTE(LOWER(LEFT(SUBSTITUTE(H106,"…",""),25)),":",""),",",""),".",""),"'",""),"’",""),"!",""),"*",""),"—",""),"–",""),"-",""),"&","")," ","") -> rentalfamily | J106: =IFERROR(INDEX('Domestic 2025'!$N:$N,MATCH($I106,'Domestic 2025'!$K:$K,0)),IFERROR(INDEX('Domestic 2025'!$N:$N,MATCH($D106,'Domestic 2025'!$F:$F,0)),"Other")) -> Searchlight Pictu…
...

Sheet Domestic 2024
A1: 1 | B1: Inside Out 2 | C1: 45457 | D1: Walt Disney | E1: Adventure | F1: 652980194 | G1: 57734765 | H1: =IFERROR(TRIM(LEFT(B1,FIND("(",B1)-1)),TRIM(B1)) -> Inside Out 2 | I1: =SUBSTITUTE(SUBSTITUTE(SUBSTITUTE(SUBSTITUTE(SUBSTITUTE(SUBSTITUTE(SUBSTITUTE(SUBSTITUTE(SUBSTITUTE(SUBSTITUTE(SUBSTITUTE(SUBSTITUTE(LOWER(LEFT(SUBSTITUTE(H1,"…",""),25)),":",""),",",""),".",""),"'",""),"’",""),"!",""),"*",""),"—",""),"–",""),"-",""),"&","")," ","") -> insideout2 | J1: =IF(D1="","Other",D1) -> Walt Disney
A2: 2 | B2: Deadpool & Wolverine | C2: 45499 | D2: Walt Disney | E2: Action | F2: 636745858 | G2: 56299369 | H2: =IFERROR(TRIM(LEFT(B2,FIND("(",B2)-1)),TRIM(B2)) -> Deadpool & Wolverine | I2: =SUBSTITUTE(SUBSTITUTE(SUBSTITUTE(SUBSTITUTE(SUBSTITUTE(SUBSTITUTE(SUBSTITUTE(SUBSTITUTE(SUBSTITUTE(SUBSTITUTE(SUBSTITUTE(SUBSTITUTE(LOWER(LEFT(SUBSTITUTE(H2,"…",""),25)),":",""),",",""),".",""),"'",""),"’",""),"!",""),"*",""),"—",""),"–",""),"-",""),"&","")," ","") -> deadpoolwolverine | J2: =IF(D2="","Other",D2) -> Walt Disney
A3: 3 | B3: Wicked | C3: 45618 | D3: Universal | E3: Musical | F3: 432943285 | G3: 38279689 | H3: =IFERROR(TRIM(LEFT(B3,FIND("(",B3)-1)),TRIM(B3)) -> Wicked | I3: =SUBSTITUTE(SUBSTITUTE(SUBSTITUTE(SUBSTITUTE(SUBSTITUTE(SUBSTITUTE(SUBSTITUTE(SUBSTITUTE(SUBSTITUTE(SUBSTITUTE(SUBSTITUTE(SUBSTITUTE(LOWER(LEFT(SUBSTITUTE(H3,"…",""),25)),":",""),",",""),".",""),"'",""),"’",""),"!",""),"*",""),"—",""),"–",""),"-",""),"&","")," ","") -> wicked | J3: =IF(D3="","Other",D3) -> Universal
A4: 4 | B4: Moana 2 | C4: 45623 | D4: Walt Disney | E4: Musical | F4: 404017489 | G4: 35722148 | H4: =IFERROR(TRIM(LEFT(B4,FIND("(",B4)-1)),TRIM(B4)) -> Moana 2 | I4: =SUBSTITUTE(SUBSTITUTE(SUBSTITUTE(SUBSTITUTE(SUBSTITUTE(SUBSTITUTE(SUBSTITUTE(SUBSTITUTE(SUBSTITUTE(SUBSTITUTE(SUBSTITUTE(SUBSTITUTE(LOWER(LEFT(SUBSTITUTE(H4,"…",""),25)),":",""),",",""),".",""),"'",""),"’",""),"!",""),"*",""),"—",""),"–",""),"-",""),"&","")," ","") -> moana2 | J4: =IF(D4="","Other",D4) -> Walt Disney
A5: 5 | B5: Despicable Me 4 | C5: 45476 | D5: Universal | E5: Adventure | F5: 361004205 | G5: 31919028 | H5: =IFERROR(TRIM(LEFT(B5,FIND("(",B5)-1)),TRIM(B5)) -> Despicable Me 4 | I5: =SUBSTITUTE(SUBSTITUTE(SUBSTITUTE(SUBSTITUTE(SUBSTITUTE(SUBSTITUTE(SUBSTITUTE(SUBSTITUTE(SUBSTITUTE(SUBSTITUTE(SUBSTITUTE(SUBSTITUTE(LOWER(LEFT(SUBSTITUTE(H5,"…",""),25)),":",""),",",""),".",""),"'",""),"’",""),"!",""),"*",""),"—",""),"–",""),"-",""),"&","")," ","") -> despicableme4 | J5: =IF(D5="","Other",D5) -> Universal
A6: 6 | B6: Beetlejuice Beetlejuice | C6: 45541 | D6: Warner Bros. | E6: Comedy | F6: 294100435 | G6: 26003575 | H6: =IFERROR(TRIM(LEFT(B6,FIND("(",B6)-1)),TRIM(B6)) -> Beetlejuice Beetlejuice | I6: =SUBSTITUTE(SUBSTITUTE(SUBSTITUTE(SUBSTITUTE(SUBSTITUTE(SUBSTITUTE(SUBSTITUTE(SUBSTITUTE(SUBSTITUTE(SUBSTITUTE(SUBSTITUTE(SUBSTITUTE(LOWER(LEFT(SUBSTITUTE(H6,"…",""),25)),":",""),",",""),".",""),"'",""),"’",""),"!",""),"*",""),"—",""),"–",""),"-",""),"&","")," ","") -> beetlejuicebeetlejuice | J6: =IF(D6="","Other",D6) -> Warner Bros.
A7: 7 | B7: Dune: Part Two | C7: 45352 | D7: Warner Bros. | E7: Action | F7: 282709065 | G7: 24996381 | H7: =IFERROR(TRIM(LEFT(B7,FIND("(",B7)-1)),TRIM(B7)) -> Dune: Part Two | I7: =SUBSTITUTE(SUBSTITUTE(SUBSTITUTE(SUBSTITUTE(SUBSTITUTE(SUBSTITUTE(SUBSTITUTE(SUBSTITUTE(SUBSTITUTE(SUBSTITUTE(SUBSTITUTE(SUBSTITUTE(LOWER(LEFT(SUBSTITUTE(H7,"…",""),25)),":",""),",",""),".",""),"'",""),"’",""),"!",""),"*",""),"—",""),"–",""),"-",""),"&","")," ","") -> duneparttwo | J7: =IF(D7="","Other",D7) -> Warner Bros.
A8: 8 | B8: Twisters | C8: 45492 | D8: Universal | E8: Thriller/Suspense | F8: 267762265 | G8: 23674824 | H8: =IFERROR(TRIM(LEFT(B8,FIND("(",B8)-1)),TRIM(B8)) -> Twisters | I8: =SUBSTITUTE(SUBSTITUTE(SUBSTITUTE(SUBSTITUTE(SUBSTITUTE(SUBSTITUTE(SUBSTITUTE(SUBSTITUTE(SUBSTITUTE(SUBSTITUTE(SUBSTITUTE(SUBSTITUTE(LOWER(LEFT(SUBSTITUTE(H8,"…",""),25)),":",""),",",""),".",""),"'",""),"’",""),"!",""),"*",""),"—",""),"–",""),"-",""),"&","")," ","") -> twisters | J8: =IF(D8="","Other",D8) -> Universal
A9: 9 | B9: Godzilla x Kong: The New Empi… | C9: 45380 | D9: Warner Bros. | E9: Action | F9: 196805338 | G9: 17401002 | H9: =IFERROR(TRIM(LEFT(B9,FIND("(",B9)-1)),TRIM(B9)) -> Godzilla x Kong: The New Empi… | I9: =SUBSTITUTE(SUBSTITUTE(SUBSTITUTE(SUBSTITUTE(SUBSTITUTE(SUBSTITUTE(SUBSTITUTE(SUBSTITUTE(SUBSTITUTE(SUBSTITUTE(SUBSTITUTE(SUBSTITUTE(LOWER(LEFT(SUBSTITUTE(H9,"…",""),25)),":",""),",",""),".",""),"'",""),"’",""),"!",""),"*",""),"—",""),"–",""),"-",""),"&","")," ","") -> godzillaxkongthenew | J9: =IF(D9="","Other",D9) -> Warner Bros.
A10: 10 | B10: Kung Fu Panda 4 | C10: 45359 | D10: Universal | E10: Comedy | F10: 193590620 | G10: 17116766 | H10: =IFERROR(TRIM(LEFT(B10,FIND("(",B10)-1)),TRIM(B10)) -> Kung Fu Panda 4 | I10: =SUBSTITUTE(SUBSTITUTE(SUBSTITUTE(SUBSTITUTE(SUBSTITUTE(SUBSTITUTE(SUBSTITUTE(SUBSTITUTE(SUBSTITUTE(SUBSTITUTE(SUBSTITUTE(SUBSTITUTE(LOWER(LEFT(SUBSTITUTE(H10,"…",""),25)),":",""),",",""),".",""),"'",""),"’",""),"!",""),"*",""),"—",""),"–",""),"-",""),"&","")," ","") -> kungfupanda4 | J10: =IF(D10="","Other",D10) -> Universal
A11: 11 | B11: Bad Boys: Ride or Die | C11: 45450 | D11: Sony Pictures | E11: Action | F11: 193573217 | G11: 17115227 | H11: =IFERROR(TRIM(LEFT(B11,FIND("(",B11)-1)),TRIM(B11)) -> Bad Boys: Ride or Die | I11: =SUBSTITUTE(SUBSTITUTE(SUBSTITUTE(SUBSTITUTE(SUBSTITUTE(SUBSTITUTE(SUBSTITUTE(SUBSTITUTE(SUBSTITUTE(SUBSTITUTE(SUBSTITUTE(SUBSTITUTE(LOWER(LEFT(SUBSTITUTE(H11,"…",""),25)),":",""),",",""),".",""),"'",""),"’",""),"!",""),"*",""),"—",""),"–",""),"-",""),"&","")," ","") -> badboysrideordie | J11: =IF(D11="","Other",D11) -> Sony Pictures
A12: 12 | B12: Kingdom of the Planet of the … | C12: 45422 | D12: 20th Century Stud… | E12: Action | F12: 171130165 | G12: 15130872 | H12: =IFERROR(TRIM(LEFT(B12,FIND("(",B12)-1)),TRIM(B12)) -> Kingdom of the Planet of the … | I12: =SUBSTITUTE(SUBSTITUTE(SUBSTITUTE(SUBSTITUTE(SUBSTITUTE(SUBSTITUTE(SUBSTITUTE(SUBSTITUTE(SUBSTITUTE(SUBSTITUTE(SUBSTITUTE(SUBSTITUTE(LOWER(LEFT(SUBSTITUTE(H12,"…",""),25)),":",""),",",""),".",""),"'",""),"’",""),"!",""),"*",""),"—",""),"–",""),"-",""),"&","")," ","") -> kingdomoftheplanetof | J12: =IF(D12="","Other",D12) -> 20th Century Stud…
... A158: 158 | B158: Jesus Thirsts: The Miracle of… | C158: 45447 | D158: Fathom Events | E158: Documentary | F158: 2927121 | G158: 258808 | H158: =IFERROR(TRIM(LEFT(B158,FIND("(",B158)-1)),TRIM(B158)) -> Jesus Thirsts: The Miracle of… | I158: =SUBSTITUTE(SUBSTITUTE(SUBSTITUTE(SUBSTITUTE(SUBSTITUTE(SUBSTITUTE(SUBSTITUTE(SUBSTITUTE(SUBSTITUTE(SUBSTITUTE(SUBSTITUTE(SUBSTITUTE(LOWER(LEFT(SUBSTITUTE(H158,"…",""),25)),":",""),",",""),".",""),"'",""),"’",""),"!",""),"*",""),"—",""),"–",""),"-",""),"&","")," ","") -> jesusthirststhemiracl | J158: =IF(D158="","Other",D158) -> Fathom Events
A159: 159 | B159: 1992 | C159: 45534 | D159: Lionsgate | E159: Thriller/Suspense | F159: 2906073 | G159: 256947 | H159: =IFERROR(TRIM(LEFT(B159,FIND("(",B159)-1)),TRIM(B159)) -> 1992 | I159: =SUBSTITUTE(SUBSTITUTE(SUBSTITUTE(SUBSTITUTE(SUBSTITUTE(SUBSTITUTE(SUBSTITUTE(SUBSTITUTE(SUBSTITUTE(SUBSTITUTE(SUBSTITUTE(SUBSTITUTE(LOWER(LEFT(SUBSTITUTE(H159,"…",""),25)),":",""),",",""),".",""),"'",""),"’",""),"!",""),"*",""),"—",""),"–",""),"-",""),"&","")," ","") -> 1992 | J159: =IF(D159="","Other",D159) -> Lionsgate
A160: 160 | B160: The Fabulous Four | C160: 45499 | D160: Bleecker Street | E160: Comedy | F160: 2854289 | G160: 252369 | H160: =IFERROR(TRIM(LEFT(B160,FIND("(",B160)-1)),TRIM(B160)) -> The Fabulous Four | I160: =SUBSTITUTE(SUBSTITUTE(SUBSTITUTE(SUBSTITUTE(SUBSTITUTE(SUBSTITUTE(SUBSTITUTE(SUBSTITUTE(SUBSTITUTE(SUBSTITUTE(SUBSTITUTE(SUBSTITUTE(LOWER(LEFT(SUBSTITUTE(H160,"…",""),25)),":",""),",",""),".",""),"'",""),"’",""),"!",""),"*",""),"—",""),"–",""),"-",""),"&","")," ","") -> thefabulousfour | J160: =IF(D160="","Other",D160) -> Bleecker Street
A161: 161 | B161: Queer | C161: 45623 | D161: A24 | E161: Drama | F161: 2837173 | G161: 250855 | H161: =IFERROR(TRIM(LEFT(B161,FIND("(",B161)-1)),TRIM(B161)) -> Queer | I161: =SUBSTITUTE(SUBSTITUTE(SUBSTITUTE(SUBSTITUTE(SUBSTITUTE(SUBSTITUTE(SUBSTITUTE(SUBSTITUTE(SUBSTITUTE(SUBSTITUTE(SUBSTITUTE(SUBSTITUTE(LOWER(LEFT(SUBSTITUTE(H161,"…",""),25)),":",""),",",""),".",""),"'",""),"’",""),"!",""),"*",""),"—",""),"–",""),"-",""),"&","")," ","") -> queer | J161: =IF(D161="","Other",D161) -> A24
A162: 162 | B162: For King + Country: A Drummer… | C162: 45631 | D162: Fathom Events | E162: Concert/Performance | F162: 2827417 | G162: 249993 | H162: =IFERROR(TRIM(LEFT(B162,FIND("(",B162)-1)),TRIM(B162)) -> For King + Country: A Drummer… | I162: =SUBSTITUTE(SUBSTITUTE(SUBSTITUTE(SUBSTITUTE(SUBSTITUTE(SUBSTITUTE(SUBSTITUTE(SUBSTITUTE(SUBSTITUTE(SUBSTITUTE(SUBSTITUTE(SUBSTITUTE(LOWER(LEFT(SUBSTITUTE(H162,"…",""),25)),":",""),",",""),".",""),"'",""),"’",""),"!",""),"*",""),"—",""),"–",""),"-",""),"&","")," ","") -> forking+countryadru | J162: =IF(D162="","Other",D162) -> Fathom Events
A163: 163 | B163: White Christmas | C163: 19841 | D163: Fathom Events | E163: Musical | F163: 2800094 | G163: 247577 | H163: =IFERROR(TRIM(LEFT(B163,FIND("(",B163)-1)),TRIM(B163)) -> White Christmas | I163: =SUBSTITUTE(SUBSTITUTE(SUBSTITUTE(SUBSTITUTE(SUBSTITUTE(SUBSTITUTE(SUBSTITUTE(SUBSTITUTE(SUBSTITUTE(SUBSTITUTE(SUBSTITUTE(SUBSTITUTE(LOWER(LEFT(SUBSTITUTE(H163,"…",""),25)),":",""),",",""),".",""),"'",""),"’",""),"!",""),"*",""),"—",""),"–",""),"-",""),"&","")," ","") -> whitechristmas | J163: =IF(D163="","Other",D163) -> Fathom Events
A164: 164 | B164: Sing Sing | C164: 45485 | D164: A24 | E164: Drama | F164: 2778745 | G164: 245689 | H164: =IFERROR(TRIM(LEFT(B164,FIND("(",B164)-1)),TRIM(B164)) -> Sing Sing | I164: =SUBSTITUTE(SUBSTITUTE(SUBSTITUTE(SUBSTITUTE(SUBSTITUTE(SUBSTITUTE(SUBSTITUTE(SUBSTITUTE(SUBSTITUTE(SUBSTITUTE(SUBSTITUTE(SUBSTITUTE(LOWER(LEFT(SUBSTITUTE(H164,"…",""),25)),":",""),",",""),".",""),"'",""),"’",""),"!",""),"*",""),"—",""),"–",""),"-",""),"&","")," ","") -> singsing | J164: =IF(D164="","Other",D164) -> A24
A165: 165 | B165: My Penguin Friend | C165: 45520 | D165: Roadside Attracti… | E165: Drama | F165: 2769460 | G165: 244868 | H165: =IFERROR(TRIM(LEFT(B165,FIND("(",B165)-1)),TRIM(B165)) -> My Penguin Friend | I165: =SUBSTITUTE(SUBSTITUTE(SUBSTITUTE(SUBSTITUTE(SUBSTITUTE(SUBSTITUTE(SUBSTITUTE(SUBSTITUTE(SUBSTITUTE(SUBSTITUTE(SUBSTITUTE(SUBSTITUTE(LOWER(LEFT(SUBSTITUTE(H165,"…",""),25)),":",""),",",""),".",""),"'",""),"’",""),"!",""),"*",""),"—",""),"–",""),"-",""),"&","")," ","") -> mypenguinfriend | J165: =IF(D165="","Other",D165) -> Roadside Attracti…
A166: 166 | B166: Absolution | C166: 45597 | D166: Samuel Goldwyn Fi… | E166: Drama | F166: 2715727 | G166: 240117 | H166: =IFERROR(TRIM(LEFT(B166,FIND("(",B166)-1)),TRIM(B166)) -> Absolution | I166: =SUBSTITUTE(SUBSTITUTE(SUBSTITUTE(SUBSTITUTE(SUBSTITUTE(SUBSTITUTE(SUBSTITUTE(SUBSTITUTE(SUBSTITUTE(SUBSTITUTE(SUBSTITUTE(SUBSTITUTE(LOWER(LEFT(SUBSTITUTE(H166,"…",""),25)),":",""),",",""),".",""),"'",""),"’",""),"!",""),"*",""),"—",""),"–",""),"-",""),"&","")," ","") -> absolution | J166: =IF(D166="","Other",D166) -> Samuel Goldwyn Fi…
A167: 167 | B167: Dune | C167: 44491 | D167: Warner Bros. | E167: Action | F167: 2703437 | G167: 239031 | H167: =IFERROR(TRIM(LEFT(B167,FIND("(",B167)-1)),TRIM(B167)) -> Dune | I167: =SUBSTITUTE(SUBSTITUTE(SUBSTITUTE(SUBSTITUTE(SUBSTITUTE(SUBSTITUTE(SUBSTITUTE(SUBSTITUTE(SUBSTITUTE(SUBSTITUTE(SUBSTITUTE(SUBSTITUTE(LOWER(LEFT(SUBSTITUTE(H167,"…",""),25)),":",""),",",""),".",""),"'",""),"’",""),"!",""),"*",""),"—",""),"–",""),"-",""),"&","")," ","") -> dune | J167: =IF(D167="","Other",D167) -> Warner Bros.
A168: 168 | B168: Ezra | C168: 45443 | D168: Bleecker Street | E168: Comedy | F168: 2631451 | G168: 232666 | H168: =IFERROR(TRIM(LEFT(B168,FIND("(",B168)-1)),TRIM(B168)) -> Ezra | I168: =SUBSTITUTE(SUBSTITUTE(SUBSTITUTE(SUBSTITUTE(SUBSTITUTE(SUBSTITUTE(SUBSTITUTE(SUBSTITUTE(SUBSTITUTE(SUBSTITUTE(SUBSTITUTE(SUBSTITUTE(LOWER(LEFT(SUBSTITUTE(H168,"…",""),25)),":",""),",",""),".",""),"'",""),"’",""),"!",""),"*",""),"—",""),"–",""),"-",""),"&","")," ","") -> ezra | J168: =IF(D168="","Other",D168) -> Bleecker Street
A169: 169 | B169: Sight & Sound Presents: Danie… | C169: 45534 | D169: Fathom Events | E169: Concert/Performance | F169: 2629933 | G169: 232532 | H169: =IFERROR(TRIM(LEFT(B169,FIND("(",B169)-1)),TRIM(B169)) -> Sight & Sound Presents: Danie… | I169: =SUBSTITUTE(SUBSTITUTE(SUBSTITUTE(SUBSTITUTE(SUBSTITUTE(SUBSTITUTE(SUBSTITUTE(SUBSTITUTE(SUBSTITUTE(SUBSTITUTE(SUBSTITUTE(SUBSTITUTE(LOWER(LEFT(SUBSTITUTE(H169,"…",""),25)),":",""),",",""),".",""),"'",""),"’",""),"!",""),"*",""),"—",""),"–",""),"-",""),"&","")," ","") -> sightsoundpresentsd | J169: =IF(D169="","Other",D169) -> Fathom Events
A170: 170 | B170: Boy Kills World | C170: 45408 | D170: Roadside Attracti… | E170: Action | F170: 2626127 | G170: 232195 | H170: =IFERROR(TRIM(LEFT(B170,FIND("(",B170)-1)),TRIM(B170)) -> Boy Kills World | I170: =SUBSTITUTE(SUBSTITUTE(SUBSTITUTE(SUBSTITUTE(SUBSTITUTE(SUBSTITUTE(SUBSTITUTE(SUBSTITUTE(SUBSTITUTE(SUBSTITUTE(SUBSTITUTE(SUBSTITUTE(LOWER(LEFT(SUBSTITUTE(H170,"…",""),25)),":",""),",",""),".",""),"'",""),"’",""),"!",""),"*",""),"—",""),"–",""),"-",""),"&","")," ","") -> boykillsworld | J170: =IF(D170="","Other",D170) -> Roadside Attracti…
A171: 171 | B171: The Lord of the Rings: The Tw… | C171: 37608 | D171: Fathom Events | E171: Adventure | F171: 2566412 | G171: 226915 | H171: =IFERROR(TRIM(LEFT(B171,FIND("(",B171)-1)),TRIM(B171)) -> The Lord of the Rings: The Tw… | I171: =SUBSTITUTE(SUBSTITUTE(SUBSTITUTE(SUBSTITUTE(SUBSTITUTE(SUBSTITUTE(SUBSTITUTE(SUBSTITUTE(SUBSTITUTE(SUBSTITUTE(SUBSTITUTE(SUBSTITUTE(LOWER(LEFT(SUBSTITUTE(H171,"…",""),25)),":",""),",",""),".",""),"'",""),"’",""),"!",""),"*",""),"—",""),"–",""),"-",""),"&","")," ","") -> thelordoftheringsth | J171: =IF(D171="","Other",D171) -> Fathom Events
... A373: 373 | B373: Ghost Cat Anzu (化け猫あんず… | C373: 45611 | D373: GKIDS | E373: Drama | F373: 218261 | G373: 19298 | H373: =IFERROR(TRIM(LEFT(B373,FIND("(",B373)-1)),TRIM(B373)) -> Ghost Cat Anzu | I373: =SUBSTITUTE(SUBSTITUTE(SUBSTITUTE(SUBSTITUTE(SUBSTITUTE(SUBSTITUTE(SUBSTITUTE(SUBSTITUTE(SUBSTITUTE(SUBSTITUTE(SUBSTITUTE(SUBSTITUTE(LOWER(LEFT(SUBSTITUTE(H373,"…",""),25)),":",""),",",""),".",""),"'",""),"’",""),"!",""),"*",""),"—",""),"–",""),"-",""),"&","")," ","") -> ghostcatanzu | J373: =IF(D373="","Other",D373) -> GKIDS
A374: 374 | B374: 46270 | C374: 45639 | D374: Paramount Pictures | E374: Drama | F374: 217151 | G374: 19200 | H374: =IFERROR(TRIM(LEFT(B374,FIND("(",B374)-1)),TRIM(B374)) -> 46270 | I374: =SUBSTITUTE(SUBSTITUTE(SUBSTITUTE(SUBSTITUTE(SUBSTITUTE(SUBSTITUTE(SUBSTITUTE(SUBSTITUTE(SUBSTITUTE(SUBSTITUTE(SUBSTITUTE(SUBSTITUTE(LOWER(LEFT(SUBSTITUTE(H374,"…",""),25)),":",""),",",""),".",""),"'",""),"’",""),"!",""),"*",""),"—",""),"–",""),"-",""),"&","")," ","") -> 46270 | J374: =IF(D374="","Other",D374) -> Paramount Pictures
A375: 375 | B375: Pandas | C375: 43196 | D375: IMAX Films | E375: Documentary | F375: 215347 | G375: 19040 | H375: =IFERROR(TRIM(LEFT(B375,FIND("(",B375)-1)),TRIM(B375)) -> Pandas | I375: =SUBSTITUTE(SUBSTITUTE(SUBSTITUTE(SUBSTITUTE(SUBSTITUTE(SUBSTITUTE(SUBSTITUTE(SUBSTITUTE(SUBSTITUTE(SUBSTITUTE(SUBSTITUTE(SUBSTITUTE(LOWER(LEFT(SUBSTITUTE(H375,"…",""),25)),":",""),",",""),".",""),"'",""),"’",""),"!",""),"*",""),"—",""),"–",""),"-",""),"&","")," ","") -> pandas | J375: =IF(D375="","Other",D375) -> IMAX Films
A376: 376 | B376: The People’s Joker | C376: 45387 | D376: Altered Innocence | E376: Comedy | F376: 213555 | G376: 18882 | H376: =IFERROR(TRIM(LEFT(B376,FIND("(",B376)-1)),TRIM(B376)) -> The People’s Joker | I376: =SUBSTITUTE(SUBSTITUTE(SUBSTITUTE(SUBSTITUTE(SUBSTITUTE(SUBSTITUTE(SUBSTITUTE(SUBSTITUTE(SUBSTITUTE(SUBSTITUTE(SUBSTITUTE(SUBSTITUTE(LOWER(LEFT(SUBSTITUTE(H376,"…",""),25)),":",""),",",""),".",""),"'",""),"’",""),"!",""),"*",""),"—",""),"–",""),"-",""),"&","")," ","") -> thepeoplesjoker | J376: =IF(D376="","Other",D376) -> Altered Innocence
A377: 377 | B377: The Dark Knight | C377: 39647 | D377: Warner Bros. | E377: Action | F377: 211676 | G377: 18716 | H377: =IFERROR(TRIM(LEFT(B377,FIND("(",B377)-1)),TRIM(B377)) -> The Dark Knight | I377: =SUBSTITUTE(SUBSTITUTE(SUBSTITUTE(SUBSTITUTE(SUBSTITUTE(SUBSTITUTE(SUBSTITUTE(SUBSTITUTE(SUBSTITUTE(SUBSTITUTE(SUBSTITUTE(SUBSTITUTE(LOWER(LEFT(SUBSTITUTE(H377,"…",""),25)),":",""),",",""),".",""),"'",""),"’",""),"!",""),"*",""),"—",""),"–",""),"-",""),"&","")," ","") -> thedarkknight | J377: =IF(D377="","Other",D377) -> Warner Bros.
A378: 378 | B378: Trailer Park Boys Presents: S… | C378: 45632 | D378: Blue Fox Entertai… | E378: Comedy | F378: 210000 | G378: 18568 | H378: =IFERROR(TRIM(LEFT(B378,FIND("(",B378)-1)),TRIM(B378)) -> Trailer Park Boys Presents: S… | I378: =SUBSTITUTE(SUBSTITUTE(SUBSTITUTE(SUBSTITUTE(SUBSTITUTE(SUBSTITUTE(SUBSTITUTE(SUBSTITUTE(SUBSTITUTE(SUBSTITUTE(SUBSTITUTE(SUBSTITUTE(LOWER(LEFT(SUBSTITUTE(H378,"…",""),25)),":",""),",",""),".",""),"'",""),"’",""),"!",""),"*",""),"—",""),"–",""),"-",""),"&","")," ","") -> trailerparkboyspresent | J378: =IF(D378="","Other",D378) -> Blue Fox Entertai…
A379: 379 | B379: The Thing | C379: 30127 | D379: Universal | E379: Horror | F379: 206355 | G379: 18245 | H379: =IFERROR(TRIM(LEFT(B379,FIND("(",B379)-1)),TRIM(B379)) -> The Thing | I379: =SUBSTITUTE(SUBSTITUTE(SUBSTITUTE(SUBSTITUTE(SUBSTITUTE(SUBSTITUTE(SUBSTITUTE(SUBSTITUTE(SUBSTITUTE(SUBSTITUTE(SUBSTITUTE(SUBSTITUTE(LOWER(LEFT(SUBSTITUTE(H379,"…",""),25)),":",""),",",""),".",""),"'",""),"’",""),"!",""),"*",""),"—",""),"–",""),"-",""),"&","")," ","") -> thething | J379: =IF(D379="","Other",D379) -> Universal
A380: 380 | B380: The Lego Movie | C380: 41677 | D380: Warner Bros. | E380: Adventure | F380: 205354 | G380: 18157 | H380: =IFERROR(TRIM(LEFT(B380,FIND("(",B380)-1)),TRIM(B380)) -> The Lego Movie | I380: =SUBSTITUTE(SUBSTITUTE(SUBSTITUTE(SUBSTITUTE(SUBSTITUTE(SUBSTITUTE(SUBSTITUTE(SUBSTITUTE(SUBSTITUTE(SUBSTITUTE(SUBSTITUTE(SUBSTITUTE(LOWER(LEFT(SUBSTITUTE(H380,"…",""),25)),":",""),",",""),".",""),"'",""),"’",""),"!",""),"*",""),"—",""),"–",""),"-",""),"&","")," ","") -> thelegomovie | J380: =IF(D380="","Other",D380) -> Warner Bros.
A381: 381 | B381: Luther: Never Too Much | C381: 45597 | D381: Giant Pictures | E381: Documentary | F381: 202796 | G381: 17931 | H381: =IFERROR(TRIM(LEFT(B381,FIND("(",B381)-1)),TRIM(B381)) -> Luther: Never Too Much | I381: =SUBSTITUTE(SUBSTITUTE(SUBSTITUTE(SUBSTITUTE(SUBSTITUTE(SUBSTITUTE(SUBSTITUTE(SUBSTITUTE(SUBSTITUTE(SUBSTITUTE(SUBSTITUTE(SUBSTITUTE(LOWER(LEFT(SUBSTITUTE(H381,"…",""),25)),":",""),",",""),".",""),"'",""),"’",""),"!",""),"*",""),"—",""),"–",""),"-",""),"&","")," ","") -> luthernevertoomuch | J381: =IF(D381="","Other",D381) -> Giant Pictures
A382: 382 | B382: Aggro Dr1ft | C382: 45331 | D382: EDGLRD | E382: Action | F382: 201351 | G382: 17803 | H382: =IFERROR(TRIM(LEFT(B382,FIND("(",B382)-1)),TRIM(B382)) -> Aggro Dr1ft | I382: =SUBSTITUTE(SUBSTITUTE(SUBSTITUTE(SUBSTITUTE(SUBSTITUTE(SUBSTITUTE(SUBSTITUTE(SUBSTITUTE(SUBSTITUTE(SUBSTITUTE(SUBSTITUTE(SUBSTITUTE(LOWER(LEFT(SUBSTITUTE(H382,"…",""),25)),":",""),",",""),".",""),"'",""),"’",""),"!",""),"*",""),"—",""),"–",""),"-",""),"&","")," ","") -> aggrodr1ft | J382: =IF(D382="","Other",D382) -> EDGLRD
A383: 383 | B383: TAYLOR SWIFT | THE ERAS TOUR | C383: 45212 | D383: AMC Theatres Dist… | E383: Concert/Performance | F383: 199943 | G383: 17678 | H383: =IFERROR(TRIM(LEFT(B383,FIND("(",B383)-1)),TRIM(B383)) -> TAYLOR SWIFT | THE ERAS TOUR | I383: =SUBSTITUTE(SUBSTITUTE(SUBSTITUTE(SUBSTITUTE(SUBSTITUTE(SUBSTITUTE(SUBSTITUTE(SUBSTITUTE(SUBSTITUTE(SUBSTITUTE(SUBSTITUTE(SUBSTITUTE(LOWER(LEFT(SUBSTITUTE(H383,"…",""),25)),":",""),",",""),".",""),"'",""),"’",""),"!",""),"*",""),"—",""),"–",""),"-",""),"&","")," ","") -> taylorswift|theerast | J383: =IF(D383="","Other",D383) -> AMC Theatres Dist…
A384: 384 | B384: Mars Express | C384: 45415 | D384: GKIDS | E384: Thriller/Suspense | F384: 199289 | G384: 17621 | H384: =IFERROR(TRIM(LEFT(B384,FIND("(",B384)-1)),TRIM(B384)) -> Mars Express | I384: =SUBSTITUTE(SUBSTITUTE(SUBSTITUTE(SUBSTITUTE(SUBSTITUTE(SUBSTITUTE(SUBSTITUTE(SUBSTITUTE(SUBSTITUTE(SUBSTITUTE(SUBSTITUTE(SUBSTITUTE(LOWER(LEFT(SUBSTITUTE(H384,"…",""),25)),":",""),",",""),".",""),"'",""),"’",""),"!",""),"*",""),"—",""),"–",""),"-",""),"&","")," ","") -> marsexpress | J384: =IF(D384="","Other",D384) -> GKIDS
A385: 385 | B385: Beetlejuice | C385: 32232 | D385: Warner Bros. | E385: Comedy | F385: 195469 | G385: 17283 | H385: =IFERROR(TRIM(LEFT(B385,FIND("(",B385)-1)),TRIM(B385)) -> Beetlejuice | I385: =SUBSTITUTE(SUBSTITUTE(SUBSTITUTE(SUBSTITUTE(SUBSTITUTE(SUBSTITUTE(SUBSTITUTE(SUBSTITUTE(SUBSTITUTE(SUBSTITUTE(SUBSTITUTE(SUBSTITUTE(LOWER(LEFT(SUBSTITUTE(H385,"…",""),25)),":",""),",",""),".",""),"'",""),"’",""),"!",""),"*",""),"—",""),"–",""),"-",""),"&","")," ","") -> beetlejuice | J385: =IF(D385="","Other",D385) -> Warner Bros.
A386: 386 | B386: The Shift | C386: 45261 | D386: Angel Studios | E386: Thriller/Suspense | F386: 192985 | G386: 17063 | H386: =IFERROR(TRIM(LEFT(B386,FIND("(",B386)-1)),TRIM(B386)) -> The Shift | I386: =SUBSTITUTE(SUBSTITUTE(SUBSTITUTE(SUBSTITUTE(SUBSTITUTE(SUBSTITUTE(SUBSTITUTE(SUBSTITUTE(SUBSTITUTE(SUBSTITUTE(SUBSTITUTE(SUBSTITUTE(LOWER(LEFT(SUBSTITUTE(H386,"…",""),25)),":",""),",",""),".",""),"'",""),"’",""),"!",""),"*",""),"—",""),"–",""),"-",""),"&","")," ","") -> theshift | J386: =IF(D386="","Other",D386) -> Angel Studios
... A397: 397 | B397: How to Have Sex | C397: 45324 | D397: MUBI | E397: Drama | F397: 177380 | G397: 15683 | H397: =IFERROR(TRIM(LEFT(B397,FIND("(",B397)-1)),TRIM(B397)) -> How to Have Sex | I397: =SUBSTITUTE(SUBSTITUTE(SUBSTITUTE(SUBSTITUTE(SUBSTITUTE(SUBSTITUTE(SUBSTITUTE(SUBSTITUTE(SUBSTITUTE(SUBSTITUTE(SUBSTITUTE(SUBSTITUTE(LOWER(LEFT(SUBSTITUTE(H397,"…",""),25)),":",""),",",""),".",""),"'",""),"’",""),"!",""),"*",""),"—",""),"–",""),"-",""),"&","")," ","") -> howtohavesex | J397: =IF(D397="","Other",D397) -> MUBI
A398: 398 | B398: Le Samourï | C398: 26492 | E398: Thriller/Suspense | F398: 177215 | G398: 15669 | H398: =IFERROR(TRIM(LEFT(B398,FIND("(",B398)-1)),TRIM(B398)) -> Le Samourï | I398: =SUBSTITUTE(SUBSTITUTE(SUBSTITUTE(SUBSTITUTE(SUBSTITUTE(SUBSTITUTE(SUBSTITUTE(SUBSTITUTE(SUBSTITUTE(SUBSTITUTE(SUBSTITUTE(SUBSTITUTE(LOWER(LEFT(SUBSTITUTE(H398,"…",""),25)),":",""),",",""),".",""),"'",""),"’",""),"!",""),"*",""),"—",""),"–",""),"-",""),"&","")," ","") -> lesamourï | J398: =IF(D398="","Other",D398) -> Other
A399: 399 | B399: L'été dernier | C399: 45471 | D399: Janus Films | E399: Drama | F399: 174977 | G399: 15471 | H399: =IFERROR(TRIM(LEFT(B399,FIND("(",B399)-1)),TRIM(B399)) -> L'été dernier | I399: =SUBSTITUTE(SUBSTITUTE(SUBSTITUTE(SUBSTITUTE(SUBSTITUTE(SUBSTITUTE(SUBSTITUTE(SUBSTITUTE(SUBSTITUTE(SUBSTITUTE(SUBSTITUTE(SUBSTITUTE(LOWER(LEFT(SUBSTITUTE(H399,"…",""),25)),":",""),",",""),".",""),"'",""),"’",""),"!",""),"*",""),"—",""),"–",""),"-",""),"&","")," ","") -> létédernier | J399: =IF(D399="","Other",D399) -> Janus Films
A400: 400 | B400: I Used to Be Funny | C400: 45450 | D400: Utopia | E400: Comedy | F400: 171756 | G400: 15186 | H400: =IFERROR(TRIM(LEFT(B400,FIND("(",B400)-1)),TRIM(B400)) -> I Used to Be Funny | I400: =SUBSTITUTE(SUBSTITUTE(SUBSTITUTE(SUBSTITUTE(SUBSTITUTE(SUBSTITUTE(SUBSTITUTE(SUBSTITUTE(SUBSTITUTE(SUBSTITUTE(SUBSTITUTE(SUBSTITUTE(LOWER(LEFT(SUBSTITUTE(H400,"…",""),25)),":",""),",",""),".",""),"'",""),"’",""),"!",""),"*",""),"—",""),"–",""),"-",""),"&","")," ","") -> iusedtobefunny | J400: =IF(D400="","Other",D400) -> Utopia
A401: 401 | B401: Saltburn | C401: 45247 | D401: Amazon MGM Studios | E401: Thriller/Suspense | F401: 169317 | G401: 14971 | H401: =IFERROR(TRIM(LEFT(B401,FIND("(",B401)-1)),TRIM(B401)) -> Saltburn | I401: =SUBSTITUTE(SUBSTITUTE(SUBSTITUTE(SUBSTITUTE(SUBSTITUTE(SUBSTITUTE(SUBSTITUTE(SUBSTITUTE(SUBSTITUTE(SUBSTITUTE(SUBSTITUTE(SUBSTITUTE(LOWER(LEFT(SUBSTITUTE(H401,"…",""),25)),":",""),",",""),".",""),"'",""),"’",""),"!",""),"*",""),"—",""),"–",""),"-",""),"&","")," ","") -> saltburn | J401: =IF(D401="","Other",D401) -> Amazon MGM Studios
A402: 402 | B402: Bocchi The Rock! Recap Part 1… | C402: 45569 | D402: Crunchyroll | F402: 167948 | G402: 14850 | H402: =IFERROR(TRIM(LEFT(B402,FIND("(",B402)-1)),TRIM(B402)) -> Bocchi The Rock! Recap Part 1… | I402: =SUBSTITUTE(SUBSTITUTE(SUBSTITUTE(SUBSTITUTE(SUBSTITUTE(SUBSTITUTE(SUBSTITUTE(SUBSTITUTE(SUBSTITUTE(SUBSTITUTE(SUBSTITUTE(SUBSTITUTE(LOWER(LEFT(SUBSTITUTE(H402,"…",""),25)),":",""),",",""),".",""),"'",""),"’",""),"!",""),"*",""),"—",""),"–",""),"-",""),"&","")," ","") -> bocchitherockrecappa | J402: =IF(D402="","Other",D402) -> Crunchyroll
A403: 403 | B403: Coup! | C403: 45506 | D403: Greenwich | E403: Comedy | F403: 166559 | G403: 14727 | H403: =IFERROR(TRIM(LEFT(B403,FIND("(",B403)-1)),TRIM(B403)) -> Coup! | I403: =SUBSTITUTE(SUBSTITUTE(SUBSTITUTE(SUBSTITUTE(SUBSTITUTE(SUBSTITUTE(SUBSTITUTE(SUBSTITUTE(SUBSTITUTE(SUBSTITUTE(SUBSTITUTE(SUBSTITUTE(LOWER(LEFT(SUBSTITUTE(H403,"…",""),25)),":",""),",",""),".",""),"'",""),"’",""),"!",""),"*",""),"—",""),"–",""),"-",""),"&","")," ","") -> coup | J403: =IF(D403="","Other",D403) -> Greenwich
A404: 404 | B404: Remembering Gene Wilder | C404: 45366 | D404: Kino Lorber | E404: Documentary | F404: 166233 | G404: 14698 | H404: =IFERROR(TRIM(LEFT(B404,FIND("(",B404)-1)),TRIM(B404)) -> Remembering Gene Wilder | I404: =SUBSTITUTE(SUBSTITUTE(SUBSTITUTE(SUBSTITUTE(SUBSTITUTE(SUBSTITUTE(SUBSTITUTE(SUBSTITUTE(SUBSTITUTE(SUBSTITUTE(SUBSTITUTE(SUBSTITUTE(LOWER(LEFT(SUBSTITUTE(H404,"…",""),25)),":",""),",",""),".",""),"'",""),"’",""),"!",""),"*",""),"—",""),"–",""),"-",""),"&","")," ","") -> rememberinggenewilder | J404: =IF(D404="","Other",D404) -> Kino Lorber
A405: 405 | B405: The Monk and the Gun | C405: 45331 | D405: Roadside Attracti… | E405: Drama | F405: 165470 | G405: 14630 | H405: =IFERROR(TRIM(LEFT(B405,FIND("(",B405)-1)),TRIM(B405)) -> The Monk and the Gun | I405: =SUBSTITUTE(SUBSTITUTE(SUBSTITUTE(SUBSTITUTE(SUBSTITUTE(SUBSTITUTE(SUBSTITUTE(SUBSTITUTE(SUBSTITUTE(SUBSTITUTE(SUBSTITUTE(SUBSTITUTE(LOWER(LEFT(SUBSTITUTE(H405,"…",""),25)),":",""),",",""),".",""),"'",""),"’",""),"!",""),"*",""),"—",""),"–",""),"-",""),"&","")," ","") -> themonkandthegun | J405: =IF(D405="","Other",D405) -> Roadside Attracti…
A406: 406 | B406: No Way Up | C406: 45338 | D406: IFC Films | E406: Adventure | F406: 163756 | G406: 14479 | H406: =IFERROR(TRIM(LEFT(B406,FIND("(",B406)-1)),TRIM(B406)) -> No Way Up | I406: =SUBSTITUTE(SUBSTITUTE(SUBSTITUTE(SUBSTITUTE(SUBSTITUTE(SUBSTITUTE(SUBSTITUTE(SUBSTITUTE(SUBSTITUTE(SUBSTITUTE(SUBSTITUTE(SUBSTITUTE(LOWER(LEFT(SUBSTITUTE(H406,"…",""),25)),":",""),",",""),".",""),"'",""),"’",""),"!",""),"*",""),"—",""),"–",""),"-",""),"&","")," ","") -> nowayup | J406: =IF(D406="","Other",D406) -> IFC Films
A407: 407 | B407: Mon chat et moi, la grande av… | C407: 45380 | D407: Blue Fox Entertai… | E407: Adventure | F407: 162363 | G407: 14356 | H407: =IFERROR(TRIM(LEFT(B407,FIND("(",B407)-1)),TRIM(B407)) -> Mon chat et moi, la grande av… | I407: =SUBSTITUTE(SUBSTITUTE(SUBSTITUTE(SUBSTITUTE(SUBSTITUTE(SUBSTITUTE(SUBSTITUTE(SUBSTITUTE(SUBSTITUTE(SUBSTITUTE(SUBSTITUTE(SUBSTITUTE(LOWER(LEFT(SUBSTITUTE(H407,"…",""),25)),":",""),",",""),".",""),"'",""),"’",""),"!",""),"*",""),"—",""),"–",""),"-",""),"&","")," ","") -> monchatetmoilagrand | J407: =IF(D407="","Other",D407) -> Blue Fox Entertai…
A408: 408 | B408: The Iron Giant | C408: 36376 | D408: Warner Bros. / Fa… | E408: Adventure | F408: 159179 | G408: 14074 | H408: =IFERROR(TRIM(LEFT(B408,FIND("(",B408)-1)),TRIM(B408)) -> The Iron Giant | I408: =SUBSTITUTE(SUBSTITUTE(SUBSTITUTE(SUBSTITUTE(SUBSTITUTE(SUBSTITUTE(SUBSTITUTE(SUBSTITUTE(SUBSTITUTE(SUBSTITUTE(SUBSTITUTE(SUBSTITUTE(LOWER(LEFT(SUBSTITUTE(H408,"…",""),25)),":",""),",",""),".",""),"'",""),"’",""),"!",""),"*",""),"—",""),"–",""),"-",""),"&","")," ","") -> theirongiant | J408: =IF(D408="","Other",D408) -> Warner Bros. / Fa…
A409: 409 | B409: Vertigo | C409: 21314 | D409: Paramount Pictures | E409: Thriller/Suspense | F409: 158085 | G409: 13977 | H409: =IFERROR(TRIM(LEFT(B409,FIND("(",B409)-1)),TRIM(B409)) -> Vertigo | I409: =SUBSTITUTE(SUBSTITUTE(SUBSTITUTE(SUBSTITUTE(SUBSTITUTE(SUBSTITUTE(SUBSTITUTE(SUBSTITUTE(SUBSTITUTE(SUBSTITUTE(SUBSTITUTE(SUBSTITUTE(LOWER(LEFT(SUBSTITUTE(H409,"…",""),25)),":",""),",",""),".",""),"'",""),"’",""),"!",""),"*",""),"—",""),"–",""),"-",""),"&","")," ","") -> vertigo | J409: =IF(D409="","Other",D409) -> Paramount Pictures
A410: 410 | B410: Christmas Eve in Miller’s Poi… | C410: 45604 | D410: IFC Films | E410: Comedy | F410: 157305 | G410: 13908 | H410: =IFERROR(TRIM(LEFT(B410,FIND("(",B410)-1)),TRIM(B410)) -> Christmas Eve in Miller’s Poi… | I410: =SUBSTITUTE(SUBSTITUTE(SUBSTITUTE(SUBSTITUTE(SUBSTITUTE(SUBSTITUTE(SUBSTITUTE(SUBSTITUTE(SUBSTITUTE(SUBSTITUTE(SUBSTITUTE(SUBSTITUTE(LOWER(LEFT(SUBSTITUTE(H410,"…",""),25)),":",""),",",""),".",""),"'",""),"’",""),"!",""),"*",""),"—",""),"–",""),"-",""),"&","")," ","") -> christmaseveinmillers | J410: =IF(D410="","Other",D410) -> IFC Films
A411: 411 | B411: Chłopi | C411: 45317 | D411: Sony Pictures Cla… | E411: Drama | F411: 155188 | G411: 13721 | H411: =IFERROR(TRIM(LEFT(B411,FIND("(",B411)-1)),TRIM(B411)) -> Chłopi | I411: =SUBSTITUTE(SUBSTITUTE(SUBSTITUTE(SUBSTITUTE(SUBSTITUTE(SUBSTITUTE(SUBSTITUTE(SUBSTITUTE(SUBSTITUTE(SUBSTITUTE(SUBSTITUTE(SUBSTITUTE(LOWER(LEFT(SUBSTITUTE(H411,"…",""),25)),":",""),",",""),".",""),"'",""),"’",""),"!",""),"*",""),"—",""),"–",""),"-",""),"&","")," ","") -> chłopi | J411: =IF(D411="","Other",D411) -> Sony Pictures Cla…
A412: 412 | B412: Weak Layers | C412: 45296 | D412: Greenwich | E412: Comedy | F412: 154445 | G412: 13656 | H412: =IFERROR(TRIM(LEFT(B412,FIND("(",B412)-1)),TRIM(B412)) -> Weak Layers | I412: =SUBSTITUTE(SUBSTITUTE(SUBSTITUTE(SUBSTITUTE(SUBSTITUTE(SUBSTITUTE(SUBSTITUTE(SUBSTITUTE(SUBSTITUTE(SUBSTITUTE(SUBSTITUTE(SUBSTITUTE(LOWER(LEFT(SUBSTITUTE(H412,"…",""),25)),":",""),",",""),".",""),"'",""),"’",""),"!",""),"*",""),"—",""),"–",""),"-",""),"&","")," ","") -> weaklayers | J412: =IF(D412="","Other",D412) -> Greenwich
A413: 413 | B413: The Good Half | C413: 45496 | D413: Utopia | E413: Comedy | F413: 151894 | G413: 13430 | H413: =IFERROR(TRIM(LEFT(B413,FIND("(",B413)-1)),TRIM(B413)) -> The Good Half | I413: =SUBSTITUTE(SUBSTITUTE(SUBSTITUTE(SUBSTITUTE(SUBSTITUTE(SUBSTITUTE(SUBSTITUTE(SUBSTITUTE(SUBSTITUTE(SUBSTITUTE(SUBSTITUTE(SUBSTITUTE(LOWER(LEFT(SUBSTITUTE(H413,"…",""),25)),":",""),",",""),".",""),"'",""),"’",""),"!",""),"*",""),"—",""),"–",""),"-",""),"&","")," ","") -> thegoodhalf | J413: =IF(D413="","Other",D413) -> Utopia
A414: 414 | B414: North by Northwest | C414: 21734 | D414: Fathom Events | E414: Thriller/Suspense | F414: 151019 | G414: 13353 | H414: =IFERROR(TRIM(LEFT(B414,FIND("(",B414)-1)),TRIM(B414)) -> North by Northwest | I414: =SUBSTITUTE(SUBSTITUTE(SUBSTITUTE(SUBSTITUTE(SUBSTITUTE(SUBSTITUTE(SUBSTITUTE(SUBSTITUTE(SUBSTITUTE(SUBSTITUTE(SUBSTITUTE(SUBSTITUTE(LOWER(LEFT(SUBSTITUTE(H414,"…",""),25)),":",""),",",""),".",""),"'",""),"’",""),"!",""),"*",""),"—",""),"–",""),"-",""),"&","")," ","") -> northbynorthwest | J414: =IF(D414="","Other",D414) -> Fathom Events
... A424: 424 | B424: The End | C424: 45632 | D424: Neon | E424: Musical | F424: 141660 | G424: 12525 | H424: =IFERROR(TRIM(LEFT(B424,FIND("(",B424)-1)),TRIM(B424)) -> The End | I424: =SUBSTITUTE(SUBSTITUTE(SUBSTITUTE(SUBSTITUTE(SUBSTITUTE(SUBSTITUTE(SUBSTITUTE(SUBSTITUTE(SUBSTITUTE(SUBSTITUTE(SUBSTITUTE(SUBSTITUTE(LOWER(LEFT(SUBSTITUTE(H424,"…",""),25)),":",""),",",""),".",""),"'",""),"’",""),"!",""),"*",""),"—",""),"–",""),"-",""),"&","")," ","") -> theend | J424: =IF(D424="","Other",D424) -> Neon
A425: 425 | B425: Raayan | C425: 45499 | E425: Action | F425: 140000 | G425: 12378 | H425: =IFERROR(TRIM(LEFT(B425,FIND("(",B425)-1)),TRIM(B425)) -> Raayan | I425: =SUBSTITUTE(SUBSTITUTE(SUBSTITUTE(SUBSTITUTE(SUBSTITUTE(SUBSTITUTE(SUBSTITUTE(SUBSTITUTE(SUBSTITUTE(SUBSTITUTE(SUBSTITUTE(SUBSTITUTE(LOWER(LEFT(SUBSTITUTE(H425,"…",""),25)),":",""),",",""),".",""),"'",""),"’",""),"!",""),"*",""),"—",""),"–",""),"-",""),"&","")," ","") -> raayan | J425: =IF(D425="","Other",D425) -> Other
A426: 426 | B426: Scott Pilgrim vs. The World | C426: 40403 | D426: Universal | E426: Comedy | F426: 133705 | G426: 11822 | H426: =IFERROR(TRIM(LEFT(B426,FIND("(",B426)-1)),TRIM(B426)) -> Scott Pilgrim vs. The World | I426: =SUBSTITUTE(SUBSTITUTE(SUBSTITUTE(SUBSTITUTE(SUBSTITUTE(SUBSTITUTE(SUBSTITUTE(SUBSTITUTE(SUBSTITUTE(SUBSTITUTE(SUBSTITUTE(SUBSTITUTE(LOWER(LEFT(SUBSTITUTE(H426,"…",""),25)),":",""),",",""),".",""),"'",""),"’",""),"!",""),"*",""),"—",""),"–",""),"-",""),"&","")," ","") -> scottpilgrimvsthewor | J426: =IF(D426="","Other",D426) -> Universal
A427: 427 | B427: Poolman | C427: 45422 | D427: Vertical Entertai… | E427: Comedy | F427: 131000 | G427: 11583 | H427: =IFERROR(TRIM(LEFT(B427,FIND("(",B427)-1)),TRIM(B427)) -> Poolman | I427: =SUBSTITUTE(SUBSTITUTE(SUBSTITUTE(SUBSTITUTE(SUBSTITUTE(SUBSTITUTE(SUBSTITUTE(SUBSTITUTE(SUBSTITUTE(SUBSTITUTE(SUBSTITUTE(SUBSTITUTE(LOWER(LEFT(SUBSTITUTE(H427,"…",""),25)),":",""),",",""),".",""),"'",""),"’",""),"!",""),"*",""),"—",""),"–",""),"-",""),"&","")," ","") -> poolman | J427: =IF(D427="","Other",D427) -> Vertical Entertai…
A428: 428 | B428: Love Actually | C428: 37932 | D428: Universal | E428: Romantic Comedy | F428: 130875 | G428: 11572 | H428: =IFERROR(TRIM(LEFT(B428,FIND("(",B428)-1)),TRIM(B428)) -> Love Actually | I428: =SUBSTITUTE(SUBSTITUTE(SUBSTITUTE(SUBSTITUTE(SUBSTITUTE(SUBSTITUTE(SUBSTITUTE(SUBSTITUTE(SUBSTITUTE(SUBSTITUTE(SUBSTITUTE(SUBSTITUTE(LOWER(LEFT(SUBSTITUTE(H428,"…",""),25)),":",""),",",""),".",""),"'",""),"’",""),"!",""),"*",""),"—",""),"–",""),"-",""),"&","")," ","") -> loveactually | J428: =IF(D428="","Other",D428) -> Universal
A429: 429 | B429: Sometimes I Think About Dying | C429: 45317 | D429: Oscilloscope Pict… | E429: Comedy | F429: 130457 | G429: 11535 | H429: =IFERROR(TRIM(LEFT(B429,FIND("(",B429)-1)),TRIM(B429)) -> Sometimes I Think About Dying | I429: =SUBSTITUTE(SUBSTITUTE(SUBSTITUTE(SUBSTITUTE(SUBSTITUTE(SUBSTITUTE(SUBSTITUTE(SUBSTITUTE(SUBSTITUTE(SUBSTITUTE(SUBSTITUTE(SUBSTITUTE(LOWER(LEFT(SUBSTITUTE(H429,"…",""),25)),":",""),",",""),".",""),"'",""),"’",""),"!",""),"*",""),"—",""),"–",""),"-",""),"&","")," ","") -> sometimesithinkaboutd | J429: =IF(D429="","Other",D429) -> Oscilloscope Pict…
A430: 430 | B430: Shaun of the Dead | C430: 38254 | D430: Focus Features | E430: Comedy | F430: 128790 | G430: 11387 | H430: =IFERROR(TRIM(LEFT(B430,FIND("(",B430)-1)),TRIM(B430)) -> Shaun of the Dead | I430: =SUBSTITUTE(SUBSTITUTE(SUBSTITUTE(SUBSTITUTE(SUBSTITUTE(SUBSTITUTE(SUBSTITUTE(SUBSTITUTE(SUBSTITUTE(SUBSTITUTE(SUBSTITUTE(SUBSTITUTE(LOWER(LEFT(SUBSTITUTE(H430,"…",""),25)),":",""),",",""),".",""),"'",""),"’",""),"!",""),"*",""),"—",""),"–",""),"-",""),"&","")," ","") -> shaunofthedead | J430: =IF(D430="","Other",D430) -> Focus Features
A431: 431 | B431: ¡Casa Bonita Mi Amor! | C431: 45541 | D431: MTV Documentary F… | E431: Documentary | F431: 128531 | G431: 11364 | H431: =IFERROR(TRIM(LEFT(B431,FIND("(",B431)-1)),TRIM(B431)) -> ¡Casa Bonita Mi Amor! | I431: =SUBSTITUTE(SUBSTITUTE(SUBSTITUTE(SUBSTITUTE(SUBSTITUTE(SUBSTITUTE(SUBSTITUTE(SUBSTITUTE(SUBSTITUTE(SUBSTITUTE(SUBSTITUTE(SUBSTITUTE(LOWER(LEFT(SUBSTITUTE(H431,"…",""),25)),":",""),",",""),".",""),"'",""),"’",""),"!",""),"*",""),"—",""),"–",""),"-",""),"&","")," ","") -> ¡casabonitamiamor | J431: =IF(D431="","Other",D431) -> MTV Documentary F…
A432: 432 | B432: Across the River and Into the… | C432: 45534 | D432: Level 33 | E432: Drama | F432: 128342 | G432: 11348 | H432: =IFERROR(TRIM(LEFT(B432,FIND("(",B432)-1)),TRIM(B432)) -> Across the River and Into the… | I432: =SUBSTITUTE(SUBSTITUTE(SUBSTITUTE(SUBSTITUTE(SUBSTITUTE(SUBSTITUTE(SUBSTITUTE(SUBSTITUTE(SUBSTITUTE(SUBSTITUTE(SUBSTITUTE(SUBSTITUTE(LOWER(LEFT(SUBSTITUTE(H432,"…",""),25)),":",""),",",""),".",""),"'",""),"’",""),"!",""),"*",""),"—",""),"–",""),"-",""),"&","")," ","") -> acrosstheriverandinto | J432: =IF(D432="","Other",D432) -> Level 33
A433: 433 | B433: Shrek 2 | C433: 38126 | D433: Universal | E433: Adventure | F433: 123485 | G433: 10918 | H433: =IFERROR(TRIM(LEFT(B433,FIND("(",B433)-1)),TRIM(B433)) -> Shrek 2 | I433: =SUBSTITUTE(SUBSTITUTE(SUBSTITUTE(SUBSTITUTE(SUBSTITUTE(SUBSTITUTE(SUBSTITUTE(SUBSTITUTE(SUBSTITUTE(SUBSTITUTE(SUBSTITUTE(SUBSTITUTE(LOWER(LEFT(SUBSTITUTE(H433,"…",""),25)),":",""),",",""),".",""),"'",""),"’",""),"!",""),"*",""),"—",""),"–",""),"-",""),"&","")," ","") -> shrek2 | J433: =IF(D433="","Other",D433) -> Universal
A434: 434 | B434: Customs Frontline | C434: 45492 | D434: Well Go USA | E434: Action | F434: 122095 | G434: 10795 | H434: =IFERROR(TRIM(LEFT(B434,FIND("(",B434)-1)),TRIM(B434)) -> Customs Frontline | I434: =SUBSTITUTE(SUBSTITUTE(SUBSTITUTE(SUBSTITUTE(SUBSTITUTE(SUBSTITUTE(SUBSTITUTE(SUBSTITUTE(SUBSTITUTE(SUBSTITUTE(SUBSTITUTE(SUBSTITUTE(LOWER(LEFT(SUBSTITUTE(H434,"…",""),25)),":",""),",",""),".",""),"'",""),"’",""),"!",""),"*",""),"—",""),"–",""),"-",""),"&","")," ","") -> customsfrontline | J434: =IF(D434="","Other",D434) -> Well Go USA
A435: 435 | B435: Eyes Wide Shut | C435: 36357 | D435: Warner Bros. | E435: Drama | F435: 121174 | G435: 10714 | H435: =IFERROR(TRIM(LEFT(B435,FIND("(",B435)-1)),TRIM(B435)) -> Eyes Wide Shut | I435: =SUBSTITUTE(SUBSTITUTE(SUBSTITUTE(SUBSTITUTE(SUBSTITUTE(SUBSTITUTE(SUBSTITUTE(SUBSTITUTE(SUBSTITUTE(SUBSTITUTE(SUBSTITUTE(SUBSTITUTE(LOWER(LEFT(SUBSTITUTE(H435,"…",""),25)),":",""),",",""),".",""),"'",""),"’",""),"!",""),"*",""),"—",""),"–",""),"-",""),"&","")," ","") -> eyeswideshut | J435: =IF(D435="","Other",D435) -> Warner Bros.
A436: 436 | B436: Kuru Otlar Üstüne | C436: 45345 | D436: Janus Films | E436: Drama | F436: 118988 | G436: 10521 | H436: =IFERROR(TRIM(LEFT(B436,FIND("(",B436)-1)),TRIM(B436)) -> Kuru Otlar Üstüne | I436: =SUBSTITUTE(SUBSTITUTE(SUBSTITUTE(SUBSTITUTE(SUBSTITUTE(SUBSTITUTE(SUBSTITUTE(SUBSTITUTE(SUBSTITUTE(SUBSTITUTE(SUBSTITUTE(SUBSTITUTE(LOWER(LEFT(SUBSTITUTE(H436,"…",""),25)),":",""),",",""),".",""),"'",""),"’",""),"!",""),"*",""),"—",""),"–",""),"-",""),"&","")," ","") -> kuruotlarüstüne | J436: =IF(D436="","Other",D436) -> Janus Films
A437: 437 | B437: Dazed and Confused | C437: 34236 | D437: Focus Features | E437: Comedy | F437: 117625 | G437: 10400 | H437: =IFERROR(TRIM(LEFT(B437,FIND("(",B437)-1)),TRIM(B437)) -> Dazed and Confused | I437: =SUBSTITUTE(SUBSTITUTE(SUBSTITUTE(SUBSTITUTE(SUBSTITUTE(SUBSTITUTE(SUBSTITUTE(SUBSTITUTE(SUBSTITUTE(SUBSTITUTE(SUBSTITUTE(SUBSTITUTE(LOWER(LEFT(SUBSTITUTE(H437,"…",""),25)),":",""),",",""),".",""),"'",""),"’",""),"!",""),"*",""),"—",""),"–",""),"-",""),"&","")," ","") -> dazedandconfused | J437: =IF(D437="","Other",D437) -> Focus Features
... A545: 545 | B545: Les Maîtres du temps | C545: 30883 | D545: Janus Films | E545: Adventure | F545: 43686 | G545: 3863 | H545: =IFERROR(TRIM(LEFT(B545,FIND("(",B545)-1)),TRIM(B545)) -> Les Maîtres du temps | I545: =SUBSTITUTE(SUBSTITUTE(SUBSTITUTE(SUBSTITUTE(SUBSTITUTE(SUBSTITUTE(SUBSTITUTE(SUBSTITUTE(SUBSTITUTE(SUBSTITUTE(SUBSTITUTE(SUBSTITUTE(LOWER(LEFT(SUBSTITUTE(H545,"…",""),25)),":",""),",",""),".",""),"'",""),"’",""),"!",""),"*",""),"—",""),"–",""),"-",""),"&","")," ","") -> lesmaîtresdutemps | J545: =IF(D545="","Other",D545) -> Janus Films
A546: 546 | B546: Nurse Unseen | C546: 45569 | E546: Documentary | F546: 42778 | G546: 3782 | H546: =IFERROR(TRIM(LEFT(B546,FIND("(",B546)-1)),TRIM(B546)) -> Nurse Unseen | I546: =SUBSTITUTE(SUBSTITUTE(SUBSTITUTE(SUBSTITUTE(SUBSTITUTE(SUBSTITUTE(SUBSTITUTE(SUBSTITUTE(SUBSTITUTE(SUBSTITUTE(SUBSTITUTE(SUBSTITUTE(LOWER(LEFT(SUBSTITUTE(H546,"…",""),25)),":",""),",",""),".",""),"'",""),"’",""),"!",""),"*",""),"—",""),"–",""),"-",""),"&","")," ","") -> nurseunseen | J546: =IF(D546="","Other",D546) -> Other
A547: 547 | B547: The Oath | C547: 45268 | D547: Freestyle Releasi… | E547: Action | F547: 41443 | G547: 3664 | H547: =IFERROR(TRIM(LEFT(B547,FIND("(",B547)-1)),TRIM(B547)) -> The Oath | I547: =SUBSTITUTE(SUBSTITUTE(SUBSTITUTE(SUBSTITUTE(SUBSTITUTE(SUBSTITUTE(SUBSTITUTE(SUBSTITUTE(SUBSTITUTE(SUBSTITUTE(SUBSTITUTE(SUBSTITUTE(LOWER(LEFT(SUBSTITUTE(H547,"…",""),25)),":",""),",",""),".",""),"'",""),"’",""),"!",""),"*",""),"—",""),"–",""),"-",""),"&","")," ","") -> theoath | J547: =IF(D547="","Other",D547) -> Freestyle Releasi…
A548: 548 | B548: Omni Loop | C548: 45555 | D548: Magnolia Pictures | E548: Drama | F548: 40269 | G548: 3560 | H548: =IFERROR(TRIM(LEFT(B548,FIND("(",B548)-1)),TRIM(B548)) -> Omni Loop | I548: =SUBSTITUTE(SUBSTITUTE(SUBSTITUTE(SUBSTITUTE(SUBSTITUTE(SUBSTITUTE(SUBSTITUTE(SUBSTITUTE(SUBSTITUTE(SUBSTITUTE(SUBSTITUTE(SUBSTITUTE(LOWER(LEFT(SUBSTITUTE(H548,"…",""),25)),":",""),",",""),".",""),"'",""),"’",""),"!",""),"*",""),"—",""),"–",""),"-",""),"&","")," ","") -> omniloop | J548: =IF(D548="","Other",D548) -> Magnolia Pictures
A549: 549 | B549: Panda Plan (熊猫计划) | C549: 45583 | D549: Well Go USA | E549: Comedy | F549: 40110 | G549: 3546 | H549: =IFERROR(TRIM(LEFT(B549,FIND("(",B549)-1)),TRIM(B549)) -> Panda Plan | I549: =SUBSTITUTE(SUBSTITUTE(SUBSTITUTE(SUBSTITUTE(SUBSTITUTE(SUBSTITUTE(SUBSTITUTE(SUBSTITUTE(SUBSTITUTE(SUBSTITUTE(SUBSTITUTE(SUBSTITUTE(LOWER(LEFT(SUBSTITUTE(H549,"…",""),25)),":",""),",",""),".",""),"'",""),"’",""),"!",""),"*",""),"—",""),"–",""),"-",""),"&","")," ","") -> pandaplan | J549: =IF(D549="","Other",D549) -> Well Go USA
A550: 550 | B550: Crumb Catcher | C550: 45492 | D550: Music Box Films | E550: Thriller/Suspense | F550: 39660 | G550: 3507 | H550: =IFERROR(TRIM(LEFT(B550,FIND("(",B550)-1)),TRIM(B550)) -> Crumb Catcher | I550: =SUBSTITUTE(SUBSTITUTE(SUBSTITUTE(SUBSTITUTE(SUBSTITUTE(SUBSTITUTE(SUBSTITUTE(SUBSTITUTE(SUBSTITUTE(SUBSTITUTE(SUBSTITUTE(SUBSTITUTE(LOWER(LEFT(SUBSTITUTE(H550,"…",""),25)),":",""),",",""),".",""),"'",""),"’",""),"!",""),"*",""),"—",""),"–",""),"-",""),"&","")," ","") -> crumbcatcher | J550: =IF(D550="","Other",D550) -> Music Box Films
A551: 551 | B551: Leap of Faith | C551: 45569 | D551: Picturehouse | E551: Documentary | F551: 39083 | G551: 3456 | H551: =IFERROR(TRIM(LEFT(B551,FIND("(",B551)-1)),TRIM(B551)) -> Leap of Faith | I551: =SUBSTITUTE(SUBSTITUTE(SUBSTITUTE(SUBSTITUTE(SUBSTITUTE(SUBSTITUTE(SUBSTITUTE(SUBSTITUTE(SUBSTITUTE(SUBSTITUTE(SUBSTITUTE(SUBSTITUTE(LOWER(LEFT(SUBSTITUTE(H551,"…",""),25)),":",""),",",""),".",""),"'",""),"’",""),"!",""),"*",""),"—",""),"–",""),"-",""),"&","")," ","") -> leapoffaith | J551: =IF(D551="","Other",D551) -> Picturehouse
A552: 552 | B552: The Stolen Valley | C552: 45345 | D552: Blue Fox Entertai… | E552: Western | F552: 38909 | G552: 3440 | H552: =IFERROR(TRIM(LEFT(B552,FIND("(",B552)-1)),TRIM(B552)) -> The Stolen Valley | I552: =SUBSTITUTE(SUBSTITUTE(SUBSTITUTE(SUBSTITUTE(SUBSTITUTE(SUBSTITUTE(SUBSTITUTE(SUBSTITUTE(SUBSTITUTE(SUBSTITUTE(SUBSTITUTE(SUBSTITUTE(LOWER(LEFT(SUBSTITUTE(H552,"…",""),25)),":",""),",",""),".",""),"'",""),"’",""),"!",""),"*",""),"—",""),"–",""),"-",""),"&","")," ","") -> thestolenvalley | J552: =IF(D552="","Other",D552) -> Blue Fox Entertai…
A553: 553 | B553: Household Saints | C553: 34227 | D553: Kino Lorber | E553: Drama | F553: 38814 | G553: 3432 | H553: =IFERROR(TRIM(LEFT(B553,FIND("(",B553)-1)),TRIM(B553)) -> Household Saints | I553: =SUBSTITUTE(SUBSTITUTE(SUBSTITUTE(SUBSTITUTE(SUBSTITUTE(SUBSTITUTE(SUBSTITUTE(SUBSTITUTE(SUBSTITUTE(SUBSTITUTE(SUBSTITUTE(SUBSTITUTE(LOWER(LEFT(SUBSTITUTE(H553,"…",""),25)),":",""),",",""),".",""),"'",""),"’",""),"!",""),"*",""),"—",""),"–",""),"-",""),"&","")," ","") -> householdsaints | J553: =IF(D553="","Other",D553) -> Kino Lorber
A554: 554 | B554: Popular Theory | C554: 45331 | D554: Blue Fox Entertai… | E554: Comedy | F554: 38781 | G554: 3429 | H554: =IFERROR(TRIM(LEFT(B554,FIND("(",B554)-1)),TRIM(B554)) -> Popular Theory | I554: =SUBSTITUTE(SUBSTITUTE(SUBSTITUTE(SUBSTITUTE(SUBSTITUTE(SUBSTITUTE(SUBSTITUTE(SUBSTITUTE(SUBSTITUTE(SUBSTITUTE(SUBSTITUTE(SUBSTITUTE(LOWER(LEFT(SUBSTITUTE(H554,"…",""),25)),":",""),",",""),".",""),"'",""),"’",""),"!",""),"*",""),"—",""),"–",""),"-",""),"&","")," ","") -> populartheory | J554: =IF(D554="","Other",D554) -> Blue Fox Entertai…
A555: 555 | B555: Dark Feathers: Dance Of The G… | C555: 45506 | D555: Hannover House | E555: Thriller/Suspense | F555: 38254 | G555: 3382 | H555: =IFERROR(TRIM(LEFT(B555,FIND("(",B555)-1)),TRIM(B555)) -> Dark Feathers: Dance Of The G… | I555: =SUBSTITUTE(SUBSTITUTE(SUBSTITUTE(SUBSTITUTE(SUBSTITUTE(SUBSTITUTE(SUBSTITUTE(SUBSTITUTE(SUBSTITUTE(SUBSTITUTE(SUBSTITUTE(SUBSTITUTE(LOWER(LEFT(SUBSTITUTE(H555,"…",""),25)),":",""),",",""),".",""),"'",""),"’",""),"!",""),"*",""),"—",""),"–",""),"-",""),"&","")," ","") -> darkfeathersdanceoft | J555: =IF(D555="","Other",D555) -> Hannover House
A556: 556 | B556: The Line | C556: 45583 | D556: Utopia | E556: Thriller/Suspense | F556: 37774 | G556: 3340 | H556: =IFERROR(TRIM(LEFT(B556,FIND("(",B556)-1)),TRIM(B556)) -> The Line | I556: =SUBSTITUTE(SUBSTITUTE(SUBSTITUTE(SUBSTITUTE(SUBSTITUTE(SUBSTITUTE(SUBSTITUTE(SUBSTITUTE(SUBSTITUTE(SUBSTITUTE(SUBSTITUTE(SUBSTITUTE(LOWER(LEFT(SUBSTITUTE(H556,"…",""),25)),":",""),",",""),".",""),"'",""),"’",""),"!",""),"*",""),"—",""),"–",""),"-",""),"&","")," ","") -> theline | J556: =IF(D556="","Other",D556) -> Utopia
A557: 557 | B557: Little Girl Blue | C557: 45597 | D557: Indican Pictures | E557: Documentary | F557: 37340 | G557: 3302 | H557: =IFERROR(TRIM(LEFT(B557,FIND("(",B557)-1)),TRIM(B557)) -> Little Girl Blue | I557: =SUBSTITUTE(SUBSTITUTE(SUBSTITUTE(SUBSTITUTE(SUBSTITUTE(SUBSTITUTE(SUBSTITUTE(SUBSTITUTE(SUBSTITUTE(SUBSTITUTE(SUBSTITUTE(SUBSTITUTE(LOWER(LEFT(SUBSTITUTE(H557,"…",""),25)),":",""),",",""),".",""),"'",""),"’",""),"!",""),"*",""),"—",""),"–",""),"-",""),"&","")," ","") -> littlegirlblue | J557: =IF(D557="","Other",D557) -> Indican Pictures
A558: 558 | B558: The Absence of Eden | C558: 45394 | D558: Roadside Attracti… | E558: Drama | F558: 37265 | G558: 3295 | H558: =IFERROR(TRIM(LEFT(B558,FIND("(",B558)-1)),TRIM(B558)) -> The Absence of Eden | I558: =SUBSTITUTE(SUBSTITUTE(SUBSTITUTE(SUBSTITUTE(SUBSTITUTE(SUBSTITUTE(SUBSTITUTE(SUBSTITUTE(SUBSTITUTE(SUBSTITUTE(SUBSTITUTE(SUBSTITUTE(LOWER(LEFT(SUBSTITUTE(H558,"…",""),25)),":",""),",",""),".",""),"'",""),"’",""),"!",""),"*",""),"—",""),"–",""),"-",""),"&","")," ","") -> theabsenceofeden | J558: =IF(D558="","Other",D558) -> Roadside Attracti…
... A566: 566 | B566: Cora Bora | C566: 45457 | D566: Brainstorm Media | E566: Comedy | F566: 35040 | G566: 3098 | H566: =IFERROR(TRIM(LEFT(B566,FIND("(",B566)-1)),TRIM(B566)) -> Cora Bora | I566: =SUBSTITUTE(SUBSTITUTE(SUBSTITUTE(SUBSTITUTE(SUBSTITUTE(SUBSTITUTE(SUBSTITUTE(SUBSTITUTE(SUBSTITUTE(SUBSTITUTE(SUBSTITUTE(SUBSTITUTE(LOWER(LEFT(SUBSTITUTE(H566,"…",""),25)),":",""),",",""),".",""),"'",""),"’",""),"!",""),"*",""),"—",""),"–",""),"-",""),"&","")," ","") -> corabora | J566: =IF(D566="","Other",D566) -> Brainstorm Media
A567: 567 | B567: Fighting Spirit: A Combat Cha… | C567: 45604 | E567: Documentary | F567: 35007 | G567: 3095 | H567: =IFERROR(TRIM(LEFT(B567,FIND("(",B567)-1)),TRIM(B567)) -> Fighting Spirit: A Combat Cha… | I567: =SUBSTITUTE(SUBSTITUTE(SUBSTITUTE(SUBSTITUTE(SUBSTITUTE(SUBSTITUTE(SUBSTITUTE(SUBSTITUTE(SUBSTITUTE(SUBSTITUTE(SUBSTITUTE(SUBSTITUTE(LOWER(LEFT(SUBSTITUTE(H567,"…",""),25)),":",""),",",""),".",""),"'",""),"’",""),"!",""),"*",""),"—",""),"–",""),"-",""),"&","")," ","") -> fightingspiritacombat | J567: =IF(D567="","Other",D567) -> Other
A568: 568 | B568: Sciuscia | C568: 45457 | D568: Janus Films | E568: Drama | F568: 34677 | G568: 3066 | H568: =IFERROR(TRIM(LEFT(B568,FIND("(",B568)-1)),TRIM(B568)) -> Sciuscia | I568: =SUBSTITUTE(SUBSTITUTE(SUBSTITUTE(SUBSTITUTE(SUBSTITUTE(SUBSTITUTE(SUBSTITUTE(SUBSTITUTE(SUBSTITUTE(SUBSTITUTE(SUBSTITUTE(SUBSTITUTE(LOWER(LEFT(SUBSTITUTE(H568,"…",""),25)),":",""),",",""),".",""),"'",""),"’",""),"!",""),"*",""),"—",""),"–",""),"-",""),"&","")," ","") -> sciuscia | J568: =IF(D568="","Other",D568) -> Janus Films
A569: 569 | B569: Sleep (잠) | C569: 45562 | D569: Magnet Releasing | E569: Thriller/Suspense | F569: 34221 | G569: 3026 | H569: =IFERROR(TRIM(LEFT(B569,FIND("(",B569)-1)),TRIM(B569)) -> Sleep | I569: =SUBSTITUTE(SUBSTITUTE(SUBSTITUTE(SUBSTITUTE(SUBSTITUTE(SUBSTITUTE(SUBSTITUTE(SUBSTITUTE(SUBSTITUTE(SUBSTITUTE(SUBSTITUTE(SUBSTITUTE(LOWER(LEFT(SUBSTITUTE(H569,"…",""),25)),":",""),",",""),".",""),"'",""),"’",""),"!",""),"*",""),"—",""),"–",""),"-",""),"&","")," ","") -> sleep | J569: =IF(D569="","Other",D569) -> Magnet Releasing
A570: 570 | B570: Trapezium (トラペジウム) | C570: 45553 | D570: Crunchyroll | E570: Musical | F570: 32541 | G570: 2877 | H570: =IFERROR(TRIM(LEFT(B570,FIND("(",B570)-1)),TRIM(B570)) -> Trapezium | I570: =SUBSTITUTE(SUBSTITUTE(SUBSTITUTE(SUBSTITUTE(SUBSTITUTE(SUBSTITUTE(SUBSTITUTE(SUBSTITUTE(SUBSTITUTE(SUBSTITUTE(SUBSTITUTE(SUBSTITUTE(LOWER(LEFT(SUBSTITUTE(H570,"…",""),25)),":",""),",",""),".",""),"'",""),"’",""),"!",""),"*",""),"—",""),"–",""),"-",""),"&","")," ","") -> trapezium | J570: =IF(D570="","Other",D570) -> Crunchyroll
A571: 571 | B571: Bushman | C571: 45324 | D571: Kino Lorber | E571: Drama | F571: 31380 | G571: 2775 | H571: =IFERROR(TRIM(LEFT(B571,FIND("(",B571)-1)),TRIM(B571)) -> Bushman | I571: =SUBSTITUTE(SUBSTITUTE(SUBSTITUTE(SUBSTITUTE(SUBSTITUTE(SUBSTITUTE(SUBSTITUTE(SUBSTITUTE(SUBSTITUTE(SUBSTITUTE(SUBSTITUTE(SUBSTITUTE(LOWER(LEFT(SUBSTITUTE(H571,"…",""),25)),":",""),",",""),".",""),"'",""),"’",""),"!",""),"*",""),"—",""),"–",""),"-",""),"&","")," ","") -> bushman | J571: =IF(D571="","Other",D571) -> Kino Lorber
A572: 572 | B572: Caligula | C572: 29252 | D572: Drafthouse Films | E572: Drama | F572: 30815 | G572: 2725 | H572: =IFERROR(TRIM(LEFT(B572,FIND("(",B572)-1)),TRIM(B572)) -> Caligula | I572: =SUBSTITUTE(SUBSTITUTE(SUBSTITUTE(SUBSTITUTE(SUBSTITUTE(SUBSTITUTE(SUBSTITUTE(SUBSTITUTE(SUBSTITUTE(SUBSTITUTE(SUBSTITUTE(SUBSTITUTE(LOWER(LEFT(SUBSTITUTE(H572,"…",""),25)),":",""),",",""),".",""),"'",""),"’",""),"!",""),"*",""),"—",""),"–",""),"-",""),"&","")," ","") -> caligula | J572: =IF(D572="","Other",D572) -> Drafthouse Films
A573: 573 | B573: To the Arctic 3D | C573: 41019 | D573: Warner Bros. | E573: Documentary | F573: 30630 | G573: 2708 | H573: =IFERROR(TRIM(LEFT(B573,FIND("(",B573)-1)),TRIM(B573)) -> To the Arctic 3D | I573: =SUBSTITUTE(SUBSTITUTE(SUBSTITUTE(SUBSTITUTE(SUBSTITUTE(SUBSTITUTE(SUBSTITUTE(SUBSTITUTE(SUBSTITUTE(SUBSTITUTE(SUBSTITUTE(SUBSTITUTE(LOWER(LEFT(SUBSTITUTE(H573,"…",""),25)),":",""),",",""),".",""),"'",""),"’",""),"!",""),"*",""),"—",""),"–",""),"-",""),"&","")," ","") -> tothearctic3d | J573: =IF(D573="","Other",D573) -> Warner Bros.
A574: 574 | B574: Once Again (For The Very Firs… | C574: 45583 | D574: Indican Pictures | E574: Drama | F574: 30092 | G574: 2661 | H574: =IFERROR(TRIM(LEFT(B574,FIND("(",B574)-1)),TRIM(B574)) -> Once Again | I574: =SUBSTITUTE(SUBSTITUTE(SUBSTITUTE(SUBSTITUTE(SUBSTITUTE(SUBSTITUTE(SUBSTITUTE(SUBSTITUTE(SUBSTITUTE(SUBSTITUTE(SUBSTITUTE(SUBSTITUTE(LOWER(LEFT(SUBSTITUTE(H574,"…",""),25)),":",""),",",""),".",""),"'",""),"’",""),"!",""),"*",""),"—",""),"–",""),"-",""),"&","")," ","") -> onceagain | J574: =IF(D574="","Other",D574) -> Indican Pictures
A575: 575 | B575: Make Me Famous | C575: 45099 | D575: Red Splat Product… | E575: Documentary | F575: 30007 | G575: 2653 | H575: =IFERROR(TRIM(LEFT(B575,FIND("(",B575)-1)),TRIM(B575)) -> Make Me Famous | I575: =SUBSTITUTE(SUBSTITUTE(SUBSTITUTE(SUBSTITUTE(SUBSTITUTE(SUBSTITUTE(SUBSTITUTE(SUBSTITUTE(SUBSTITUTE(SUBSTITUTE(SUBSTITUTE(SUBSTITUTE(LOWER(LEFT(SUBSTITUTE(H575,"…",""),25)),":",""),",",""),".",""),"'",""),"’",""),"!",""),"*",""),"—",""),"–",""),"-",""),"&","")," ","") -> makemefamous | J575: =IF(D575="","Other",D575) -> Red Splat Product…
A576: 576 | B576: The World According to Allee … | C576: 45611 | D576: Magnolia Pictures | E576: Documentary | F576: 29689 | G576: 2625 | H576: =IFERROR(TRIM(LEFT(B576,FIND("(",B576)-1)),TRIM(B576)) -> The World According to Allee … | I576: =SUBSTITUTE(SUBSTITUTE(SUBSTITUTE(SUBSTITUTE(SUBSTITUTE(SUBSTITUTE(SUBSTITUTE(SUBSTITUTE(SUBSTITUTE(SUBSTITUTE(SUBSTITUTE(SUBSTITUTE(LOWER(LEFT(SUBSTITUTE(H576,"…",""),25)),":",""),",",""),".",""),"'",""),"’",""),"!",""),"*",""),"—",""),"–",""),"-",""),"&","")," ","") -> theworldaccordingtoal | J576: =IF(D576="","Other",D576) -> Magnolia Pictures
A577: 577 | B577: Killer Raccoons 2: Dark Chris… | C577: 44043 | D577: Indican Pictures | E577: Comedy | F577: 29175 | G577: 2580 | H577: =IFERROR(TRIM(LEFT(B577,FIND("(",B577)-1)),TRIM(B577)) -> Killer Raccoons 2: Dark Chris… | I577: =SUBSTITUTE(SUBSTITUTE(SUBSTITUTE(SUBSTITUTE(SUBSTITUTE(SUBSTITUTE(SUBSTITUTE(SUBSTITUTE(SUBSTITUTE(SUBSTITUTE(SUBSTITUTE(SUBSTITUTE(LOWER(LEFT(SUBSTITUTE(H577,"…",""),25)),":",""),",",""),".",""),"'",""),"’",""),"!",""),"*",""),"—",""),"–",""),"-",""),"&","")," ","") -> killerraccoons2darkc | J577: =IF(D577="","Other",D577) -> Indican Pictures
A578: 578 | B578: Gasoline Rainbow | C578: 45422 | D578: MUBI | E578: Adventure | F578: 29068 | G578: 2570 | H578: =IFERROR(TRIM(LEFT(B578,FIND("(",B578)-1)),TRIM(B578)) -> Gasoline Rainbow | I578: =SUBSTITUTE(SUBSTITUTE(SUBSTITUTE(SUBSTITUTE(SUBSTITUTE(SUBSTITUTE(SUBSTITUTE(SUBSTITUTE(SUBSTITUTE(SUBSTITUTE(SUBSTITUTE(SUBSTITUTE(LOWER(LEFT(SUBSTITUTE(H578,"…",""),25)),":",""),",",""),".",""),"'",""),"’",""),"!",""),"*",""),"—",""),"–",""),"-",""),"&","")," ","") -> gasolinerainbow | J578: =IF(D578="","Other",D578) -> MUBI
A579: 579 | B579: Let’s Get Lost | C579: 32619 | D579: Kino Lorber | E579: Documentary | F579: 28339 | G579: 2506 | H579: =IFERROR(TRIM(LEFT(B579,FIND("(",B579)-1)),TRIM(B579)) -> Let’s Get Lost | I579: =SUBSTITUTE(SUBSTITUTE(SUBSTITUTE(SUBSTITUTE(SUBSTITUTE(SUBSTITUTE(SUBSTITUTE(SUBSTITUTE(SUBSTITUTE(SUBSTITUTE(SUBSTITUTE(SUBSTITUTE(LOWER(LEFT(SUBSTITUTE(H579,"…",""),25)),":",""),",",""),".",""),"'",""),"’",""),"!",""),"*",""),"—",""),"–",""),"-",""),"&","")," ","") -> letsgetlost | J579: =IF(D579="","Other",D579) -> Kino Lorber
...

Sheet Global 2024
A1: 1 | B1: Inside Out 2 | C1: 1698863816 | D1: 652980194 | E1: 0.384 | F1: 1045883622 | G1: 0.616 | H1: =IFERROR(TRIM(LEFT(B1,FIND("(",B1)-1)),TRIM(B1)) -> Inside Out 2 | I1: =SUBSTITUTE(SUBSTITUTE(SUBSTITUTE(SUBSTITUTE(SUBSTITUTE(SUBSTITUTE(SUBSTITUTE(SUBSTITUTE(SUBSTITUTE(SUBSTITUTE(SUBSTITUTE(SUBSTITUTE(LOWER(LEFT(SUBSTITUTE(H1,"…",""),25)),":",""),",",""),".",""),"'",""),"’",""),"!",""),"*",""),"—",""),"–",""),"-",""),"&","")," ","") -> insideout2 | J1: =IFERROR(INDEX('Domestic 2024'!$J:$J,MATCH($I1,'Domestic 2024'!$I:$I,0)),IFERROR(INDEX('Domestic 2024'!$J:$J,MATCH($D1,'Domestic 2024'!$F:$F,0)),"Other")) -> Walt Disney
A2: 2 | B2: Deadpool & Wolverine | C2: 1338073645 | D2: 636745858 | E2: 0.476 | F2: 701327787 | G2: 0.524 | H2: =IFERROR(TRIM(LEFT(B2,FIND("(",B2)-1)),TRIM(B2)) -> Deadpool & Wolverine | I2: =SUBSTITUTE(SUBSTITUTE(SUBSTITUTE(SUBSTITUTE(SUBSTITUTE(SUBSTITUTE(SUBSTITUTE(SUBSTITUTE(SUBSTITUTE(SUBSTITUTE(SUBSTITUTE(SUBSTITUTE(LOWER(LEFT(SUBSTITUTE(H2,"…",""),25)),":",""),",",""),".",""),"'",""),"’",""),"!",""),"*",""),"—",""),"–",""),"-",""),"&","")," ","") -> deadpoolwolverine | J2: =IFERROR(INDEX('Domestic 2024'!$J:$J,MATCH($I2,'Domestic 2024'!$I:$I,0)),IFERROR(INDEX('Domestic 2024'!$J:$J,MATCH($D2,'Domestic 2024'!$F:$F,0)),"Other")) -> Walt Disney
A3: 3 | B3: Moana 2 | C3: 1059242164 | D3: 460405297 | E3: 0.435 | F3: 598836867 | G3: 0.565 | H3: =IFERROR(TRIM(LEFT(B3,FIND("(",B3)-1)),TRIM(B3)) -> Moana 2 | I3: =SUBSTITUTE(SUBSTITUTE(SUBSTITUTE(SUBSTITUTE(SUBSTITUTE(SUBSTITUTE(SUBSTITUTE(SUBSTITUTE(SUBSTITUTE(SUBSTITUTE(SUBSTITUTE(SUBSTITUTE(LOWER(LEFT(SUBSTITUTE(H3,"…",""),25)),":",""),",",""),".",""),"'",""),"’",""),"!",""),"*",""),"—",""),"–",""),"-",""),"&","")," ","") -> moana2 | J3: =IFERROR(INDEX('Domestic 2024'!$J:$J,MATCH($I3,'Domestic 2024'!$I:$I,0)),IFERROR(INDEX('Domestic 2024'!$J:$J,MATCH($D3,'Domestic 2024'!$F:$F,0)),"Other")) -> Walt Disney
A4: 4 | B4: Despicable Me 4 | C4: 972021410 | D4: 361004205 | E4: 0.371 | F4: 611017205 | G4: 0.629 | H4: =IFERROR(TRIM(LEFT(B4,FIND("(",B4)-1)),TRIM(B4)) -> Despicable Me 4 | I4: =SUBSTITUTE(SUBSTITUTE(SUBSTITUTE(SUBSTITUTE(SUBSTITUTE(SUBSTITUTE(SUBSTITUTE(SUBSTITUTE(SUBSTITUTE(SUBSTITUTE(SUBSTITUTE(SUBSTITUTE(LOWER(LEFT(SUBSTITUTE(H4,"…",""),25)),":",""),",",""),".",""),"'",""),"’",""),"!",""),"*",""),"—",""),"–",""),"-",""),"&","")," ","") -> despicableme4 | J4: =IFERROR(INDEX('Domestic 2024'!$J:$J,MATCH($I4,'Domestic 2024'!$I:$I,0)),IFERROR(INDEX('Domestic 2024'!$J:$J,MATCH($D4,'Domestic 2024'!$F:$F,0)),"Other")) -> Universal
A5: 5 | B5: Wicked | C5: 763963597 | D5: 474983975 | E5: 0.622 | F5: 288979622 | G5: 0.378 | H5: =IFERROR(TRIM(LEFT(B5,FIND("(",B5)-1)),TRIM(B5)) -> Wicked | I5: =SUBSTITUTE(SUBSTITUTE(SUBSTITUTE(SUBSTITUTE(SUBSTITUTE(SUBSTITUTE(SUBSTITUTE(SUBSTITUTE(SUBSTITUTE(SUBSTITUTE(SUBSTITUTE(SUBSTITUTE(LOWER(LEFT(SUBSTITUTE(H5,"…",""),25)),":",""),",",""),".",""),"'",""),"’",""),"!",""),"*",""),"—",""),"–",""),"-",""),"&","")," ","") -> wicked | J5: =IFERROR(INDEX('Domestic 2024'!$J:$J,MATCH($I5,'Domestic 2024'!$I:$I,0)),IFERROR(INDEX('Domestic 2024'!$J:$J,MATCH($D5,'Domestic 2024'!$F:$F,0)),"Other")) -> Universal
A6: 6 | B6: Mufasa: The Lion King | C6: 722631756 | D6: 254567693 | E6: 0.352 | F6: 468064063 | G6: 0.648 | H6: =IFERROR(TRIM(LEFT(B6,FIND("(",B6)-1)),TRIM(B6)) -> Mufasa: The Lion King | I6: =SUBSTITUTE(SUBSTITUTE(SUBSTITUTE(SUBSTITUTE(SUBSTITUTE(SUBSTITUTE(SUBSTITUTE(SUBSTITUTE(SUBSTITUTE(SUBSTITUTE(SUBSTITUTE(SUBSTITUTE(LOWER(LEFT(SUBSTITUTE(H6,"…",""),25)),":",""),",",""),".",""),"'",""),"’",""),"!",""),"*",""),"—",""),"–",""),"-",""),"&","")," ","") -> mufasathelionking | J6: =IFERROR(INDEX('Domestic 2024'!$J:$J,MATCH($I6,'Domestic 2024'!$I:$I,0)),IFERROR(INDEX('Domestic 2024'!$J:$J,MATCH($D6,'Domestic 2024'!$F:$F,0)),"Other")) -> Walt Disney
A7: 7 | B7: Dune: Part Two | C7: 714844358 | D7: 282144358 | E7: 0.395 | F7: 432700000 | G7: 0.605 | H7: =IFERROR(TRIM(LEFT(B7,FIND("(",B7)-1)),TRIM(B7)) -> Dune: Part Two | I7: =SUBSTITUTE(SUBSTITUTE(SUBSTITUTE(SUBSTITUTE(SUBSTITUTE(SUBSTITUTE(SUBSTITUTE(SUBSTITUTE(SUBSTITUTE(SUBSTITUTE(SUBSTITUTE(SUBSTITUTE(LOWER(LEFT(SUBSTITUTE(H7,"…",""),25)),":",""),",",""),".",""),"'",""),"’",""),"!",""),"*",""),"—",""),"–",""),"-",""),"&","")," ","") -> duneparttwo | J7: =IFERROR(INDEX('Domestic 2024'!$J:$J,MATCH($I7,'Domestic 2024'!$I:$I,0)),IFERROR(INDEX('Domestic 2024'!$J:$J,MATCH($D7,'Domestic 2024'!$F:$F,0)),"Other")) -> Warner Bros.
A8: 8 | B8: Godzilla X Kong: The New Empire | C8: 572050016 | D8: 196350016 | E8: 0.343 | F8: 375700000 | G8: 0.657 | H8: =IFERROR(TRIM(LEFT(B8,FIND("(",B8)-1)),TRIM(B8)) -> Godzilla X Kong: The New Empire | I8: =SUBSTITUTE(SUBSTITUTE(SUBSTITUTE(SUBSTITUTE(SUBSTITUTE(SUBSTITUTE(SUBSTITUTE(SUBSTITUTE(SUBSTITUTE(SUBSTITUTE(SUBSTITUTE(SUBSTITUTE(LOWER(LEFT(SUBSTITUTE(H8,"…",""),25)),":",""),",",""),".",""),"'",""),"’",""),"!",""),"*",""),"—",""),"–",""),"-",""),"&","")," ","") -> godzillaxkongthenew | J8: =IFERROR(INDEX('Domestic 2024'!$J:$J,MATCH($I8,'Domestic 2024'!$I:$I,0)),IFERROR(INDEX('Domestic 2024'!$J:$J,MATCH($D8,'Domestic 2024'!$F:$F,0)),"Other")) -> Warner Bros.
A9: 9 | B9: Kung Fu Panda 4 | C9: 547946428 | D9: 193590620 | E9: 0.353 | F9: 354355808 | G9: 0.647 | H9: =IFERROR(TRIM(LEFT(B9,FIND("(",B9)-1)),TRIM(B9)) -> Kung Fu Panda 4 | I9: =SUBSTITUTE(SUBSTITUTE(SUBSTITUTE(SUBSTITUTE(SUBSTITUTE(SUBSTITUTE(SUBSTITUTE(SUBSTITUTE(SUBSTITUTE(SUBSTITUTE(SUBSTITUTE(SUBSTITUTE(LOWER(LEFT(SUBSTITUTE(H9,"…",""),25)),":",""),",",""),".",""),"'",""),"’",""),"!",""),"*",""),"—",""),"–",""),"-",""),"&","")," ","") -> kungfupanda4 | J9: =IFERROR(INDEX('Domestic 2024'!$J:$J,MATCH($I9,'Domestic 2024'!$I:$I,0)),IFERROR(INDEX('Domestic 2024'!$J:$J,MATCH($D9,'Domestic 2024'!$F:$F,0)),"Other")) -> Universal
A10: 10 | B10: Sonic the Hedgehog 3 | C10: 492162604 | D10: 236115100 | E10: 0.48 | F10: 256047504 | G10: 0.52 | H10: =IFERROR(TRIM(LEFT(B10,FIND("(",B10)-1)),TRIM(B10)) -> Sonic the Hedgehog 3 | I10: =SUBSTITUTE(SUBSTITUTE(SUBSTITUTE(SUBSTITUTE(SUBSTITUTE(SUBSTITUTE(SUBSTITUTE(SUBSTITUTE(SUBSTITUTE(SUBSTITUTE(SUBSTITUTE(SUBSTITUTE(LOWER(LEFT(SUBSTITUTE(H10,"…",""),25)),":",""),",",""),".",""),"'",""),"’",""),"!",""),"*",""),"—",""),"–",""),"-",""),"&","")," ","") -> sonicthehedgehog3 | J10: =IFERROR(INDEX('Domestic 2024'!$J:$J,MATCH($I10,'Domestic 2024'!$I:$I,0)),IFERROR(INDEX('Domestic 2024'!$J:$J,MATCH($D10,'Domestic 2024'!$F:$F,0)),"Other")) -> Paramount Pictures
A11: 11 | B11: Venom: The Last Dance | C11: 478937618 | D11: 139755882 | E11: 0.292 | F11: 339181736 | G11: 0.708 | H11: =IFERROR(TRIM(LEFT(B11,FIND("(",B11)-1)),TRIM(B11)) -> Venom: The Last Dance | I11: =SUBSTITUTE(SUBSTITUTE(SUBSTITUTE(SUBSTITUTE(SUBSTITUTE(SUBSTITUTE(SUBSTITUTE(SUBSTITUTE(SUBSTITUTE(SUBSTITUTE(SUBSTITUTE(SUBSTITUTE(LOWER(LEFT(SUBSTITUTE(H11,"…",""),25)),":",""),",",""),".",""),"'",""),"’",""),"!",""),"*",""),"—",""),"–",""),"-",""),"&","")," ","") -> venomthelastdance | J11: =IFERROR(INDEX('Domestic 2024'!$J:$J,MATCH($I11,'Domestic 2024'!$I:$I,0)),IFERROR(INDEX('Domestic 2024'!$J:$J,MATCH($D11,'Domestic 2024'!$F:$F,0)),"Other")) -> Sony Pictures
A12: 12 | B12: Gladiator II | C12: 462180717 | D12: 172438016 | E12: 0.373 | F12: 289742701 | G12: 0.627 | H12: =IFERROR(TRIM(LEFT(B12,FIND("(",B12)-1)),TRIM(B12)) -> Gladiator II | I12: =SUBSTITUTE(SUBSTITUTE(SUBSTITUTE(SUBSTITUTE(SUBSTITUTE(SUBSTITUTE(SUBSTITUTE(SUBSTITUTE(SUBSTITUTE(SUBSTITUTE(SUBSTITUTE(SUBSTITUTE(LOWER(LEFT(SUBSTITUTE(H12,"…",""),25)),":",""),",",""),".",""),"'",""),"’",""),"!",""),"*",""),"—",""),"–",""),"-",""),"&","")," ","") -> gladiatorii | J12: =IFERROR(INDEX('Domestic 2024'!$J:$J,MATCH($I12,'Domestic 2024'!$I:$I,0)),IFERROR(INDEX('Domestic 2024'!$J:$J,MATCH($D12,'Domestic 2024'!$F:$F,0)),"Other")) -> Paramount Pictures
... A14: 14 | B14: Yolo | C14: 433606094 | D14: 2001584 | E14: 0.005 | F14: 431604510 | G14: 0.995 | H14: =IFERROR(TRIM(LEFT(B14,FIND("(",B14)-1)),TRIM(B14)) -> Yolo | I14: =SUBSTITUTE(SUBSTITUTE(SUBSTITUTE(SUBSTITUTE(SUBSTITUTE(SUBSTITUTE(SUBSTITUTE(SUBSTITUTE(SUBSTITUTE(SUBSTITUTE(SUBSTITUTE(SUBSTITUTE(LOWER(LEFT(SUBSTITUTE(H14,"…",""),25)),":",""),",",""),".",""),"'",""),"’",""),"!",""),"*",""),"—",""),"–",""),"-",""),"&","")," ","") -> yolo | J14: =IFERROR(INDEX('Domestic 2024'!$J:$J,MATCH($I14,'Domestic 2024'!$I:$I,0)),IFERROR(INDEX('Domestic 2024'!$J:$J,MATCH($D14,'Domestic 2024'!$F:$F,0)),"Other")) -> Sony Pictures
A15: 15 | B15: Pegasus 2 | C15: 422878491 | D15: - | E15: - | F15: 422878491 | G15: 1 | H15: =IFERROR(TRIM(LEFT(B15,FIND("(",B15)-1)),TRIM(B15)) -> Pegasus 2 | I15: =SUBSTITUTE(SUBSTITUTE(SUBSTITUTE(SUBSTITUTE(SUBSTITUTE(SUBSTITUTE(SUBSTITUTE(SUBSTITUTE(SUBSTITUTE(SUBSTITUTE(SUBSTITUTE(SUBSTITUTE(LOWER(LEFT(SUBSTITUTE(H15,"…",""),25)),":",""),",",""),".",""),"'",""),"’",""),"!",""),"*",""),"—",""),"–",""),"-",""),"&","")," ","") -> pegasus2 | J15: =IFERROR(INDEX('Domestic 2024'!$J:$J,MATCH($I15,'Domestic 2024'!$I:$I,0)),IFERROR(INDEX('Domestic 2024'!$J:$J,MATCH($D15,'Domestic 2024'!$F:$F,0)),"Other")) -> Other
A16: 16 | B16: Successor | C16: 422307398 | D16: - | E16: - | F16: 422307398 | G16: 1 | H16: =IFERROR(TRIM(LEFT(B16,FIND("(",B16)-1)),TRIM(B16)) -> Successor | I16: =SUBSTITUTE(SUBSTITUTE(SUBSTITUTE(SUBSTITUTE(SUBSTITUTE(SUBSTITUTE(SUBSTITUTE(SUBSTITUTE(SUBSTITUTE(SUBSTITUTE(SUBSTITUTE(SUBSTITUTE(LOWER(LEFT(SUBSTITUTE(H16,"…",""),25)),":",""),",",""),".",""),"'",""),"’",""),"!",""),"*",""),"—",""),"–",""),"-",""),"&","")," ","") -> successor | J16: =IFERROR(INDEX('Domestic 2024'!$J:$J,MATCH($I16,'Domestic 2024'!$I:$I,0)),IFERROR(INDEX('Domestic 2024'!$J:$J,MATCH($D16,'Domestic 2024'!$F:$F,0)),"Other")) -> Other
A17: 17 | B17: Bad Boys: Ride or Die | C17: 404550184 | D17: 193573217 | E17: 0.478 | F17: 210976967 | G17: 0.522 | H17: =IFERROR(TRIM(LEFT(B17,FIND("(",B17)-1)),TRIM(B17)) -> Bad Boys: Ride or Die | I17: =SUBSTITUTE(SUBSTITUTE(SUBSTITUTE(SUBSTITUTE(SUBSTITUTE(SUBSTITUTE(SUBSTITUTE(SUBSTITUTE(SUBSTITUTE(SUBSTITUTE(SUBSTITUTE(SUBSTITUTE(LOWER(LEFT(SUBSTITUTE(H17,"…",""),25)),":",""),",",""),".",""),"'",""),"’",""),"!",""),"*",""),"—",""),"–",""),"-",""),"&","")," ","") -> badboysrideordie | J17: =IFERROR(INDEX('Domestic 2024'!$J:$J,MATCH($I17,'Domestic 2024'!$I:$I,0)),IFERROR(INDEX('Domestic 2024'!$J:$J,MATCH($D17,'Domestic 2024'!$F:$F,0)),"Other")) -> Sony Pictures
A18: 18 | B18: Kingdom of the Planet of the Apes | C18: 397378150 | D18: 171130165 | E18: 0.431 | F18: 226247985 | G18: 0.569 | H18: =IFERROR(TRIM(LEFT(B18,FIND("(",B18)-1)),TRIM(B18)) -> Kingdom of the Planet of the Apes | I18: =SUBSTITUTE(SUBSTITUTE(SUBSTITUTE(SUBSTITUTE(SUBSTITUTE(SUBSTITUTE(SUBSTITUTE(SUBSTITUTE(SUBSTITUTE(SUBSTITUTE(SUBSTITUTE(SUBSTITUTE(LOWER(LEFT(SUBSTITUTE(H18,"…",""),25)),":",""),",",""),".",""),"'",""),"’",""),"!",""),"*",""),"—",""),"–",""),"-",""),"&","")," ","") -> kingdomoftheplanetof | J18: =IFERROR(INDEX('Domestic 2024'!$J:$J,MATCH($I18,'Domestic 2024'!$I:$I,0)),IFERROR(INDEX('Domestic 2024'!$J:$J,MATCH($D18,'Domestic 2024'!$F:$F,0)),"Other")) -> 20th Century Stud…
A19: 19 | B19: Twisters | C19: 372262265 | D19: 267762265 | E19: 0.719 | F19: 104500000 | G19: 0.281 | H19: =IFERROR(TRIM(LEFT(B19,FIND("(",B19)-1)),TRIM(B19)) -> Twisters | I19: =SUBSTITUTE(SUBSTITUTE(SUBSTITUTE(SUBSTITUTE(SUBSTITUTE(SUBSTITUTE(SUBSTITUTE(SUBSTITUTE(SUBSTITUTE(SUBSTITUTE(SUBSTITUTE(SUBSTITUTE(LOWER(LEFT(SUBSTITUTE(H19,"…",""),25)),":",""),",",""),".",""),"'",""),"’",""),"!",""),"*",""),"—",""),"–",""),"-",""),"&","")," ","") -> twisters | J19: =IFERROR(INDEX('Domestic 2024'!$J:$J,MATCH($I19,'Domestic 2024'!$I:$I,0)),IFERROR(INDEX('Domestic 2024'!$J:$J,MATCH($D19,'Domestic 2024'!$F:$F,0)),"Other")) -> Universal
A20: 20 | B20: It Ends with Us | C20: 351441044 | D20: 148518266 | E20: 0.423 | F20: 202922778 | G20: 0.577 | H20: =IFERROR(TRIM(LEFT(B20,FIND("(",B20)-1)),TRIM(B20)) -> It Ends with Us | I20: =SUBSTITUTE(SUBSTITUTE(SUBSTITUTE(SUBSTITUTE(SUBSTITUTE(SUBSTITUTE(SUBSTITUTE(SUBSTITUTE(SUBSTITUTE(SUBSTITUTE(SUBSTITUTE(SUBSTITUTE(LOWER(LEFT(SUBSTITUTE(H20,"…",""),25)),":",""),",",""),".",""),"'",""),"’",""),"!",""),"*",""),"—",""),"–",""),"-",""),"&","")," ","") -> itendswithus | J20: =IFERROR(INDEX('Domestic 2024'!$J:$J,MATCH($I20,'Domestic 2024'!$I:$I,0)),IFERROR(INDEX('Domestic 2024'!$J:$J,MATCH($D20,'Domestic 2024'!$F:$F,0)),"Other")) -> Sony Pictures
A21: 21 | B21: Alien: Romulus | C21: 350865342 | D21: 105313091 | E21: 0.3 | F21: 245552251 | G21: 0.7 | H21: =IFERROR(TRIM(LEFT(B21,FIND("(",B21)-1)),TRIM(B21)) -> Alien: Romulus | I21: =SUBSTITUTE(SUBSTITUTE(SUBSTITUTE(SUBSTITUTE(SUBSTITUTE(SUBSTITUTE(SUBSTITUTE(SUBSTITUTE(SUBSTITUTE(SUBSTITUTE(SUBSTITUTE(SUBSTITUTE(LOWER(LEFT(SUBSTITUTE(H21,"…",""),25)),":",""),",",""),".",""),"'",""),"’",""),"!",""),"*",""),"—",""),"–",""),"-",""),"&","")," ","") -> alienromulus | J21: =IFERROR(INDEX('Domestic 2024'!$J:$J,MATCH($I21,'Domestic 2024'!$I:$I,0)),IFERROR(INDEX('Domestic 2024'!$J:$J,MATCH($D21,'Domestic 2024'!$F:$F,0)),"Other")) -> 20th Century Stud…
A22: 22 | B22: The Wild Robot | C22: 334509500 | D22: 143901945 | E22: 0.43 | F22: 190607555 | G22: 0.57 | H22: =IFERROR(TRIM(LEFT(B22,FIND("(",B22)-1)),TRIM(B22)) -> The Wild Robot | I22: =SUBSTITUTE(SUBSTITUTE(SUBSTITUTE(SUBSTITUTE(SUBSTITUTE(SUBSTITUTE(SUBSTITUTE(SUBSTITUTE(SUBSTITUTE(SUBSTITUTE(SUBSTITUTE(SUBSTITUTE(LOWER(LEFT(SUBSTITUTE(H22,"…",""),25)),":",""),",",""),".",""),"'",""),"’",""),"!",""),"*",""),"—",""),"–",""),"-",""),"&","")," ","") -> thewildrobot | J22: =IFERROR(INDEX('Domestic 2024'!$J:$J,MATCH($I22,'Domestic 2024'!$I:$I,0)),IFERROR(INDEX('Domestic 2024'!$J:$J,MATCH($D22,'Domestic 2024'!$F:$F,0)),"Other")) -> Universal
A23: 23 | B23: Article 20 | C23: 306899794 | D23: - | E23: - | F23: 306899794 | G23: 1 | H23: =IFERROR(TRIM(LEFT(B23,FIND("(",B23)-1)),TRIM(B23)) -> Article 20 | I23: =SUBSTITUTE(SUBSTITUTE(SUBSTITUTE(SUBSTITUTE(SUBSTITUTE(SUBSTITUTE(SUBSTITUTE(SUBSTITUTE(SUBSTITUTE(SUBSTITUTE(SUBSTITUTE(SUBSTITUTE(LOWER(LEFT(SUBSTITUTE(H23,"…",""),25)),":",""),",",""),".",""),"'",""),"’",""),"!",""),"*",""),"—",""),"–",""),"-",""),"&","")," ","") -> article20 | J23: =IFERROR(INDEX('Domestic 2024'!$J:$J,MATCH($I23,'Domestic 2024'!$I:$I,0)),IFERROR(INDEX('Domestic 2024'!$J:$J,MATCH($D23,'Domestic 2024'!$F:$F,0)),"Other")) -> Other
A24: 24 | B24: A Quiet Place: Day One | C24: 261907653 | D24: 139051884 | E24: 0.531 | F24: 122855769 | G24: 0.469 | H24: =IFERROR(TRIM(LEFT(B24,FIND("(",B24)-1)),TRIM(B24)) -> A Quiet Place: Day One | I24: =SUBSTITUTE(SUBSTITUTE(SUBSTITUTE(SUBSTITUTE(SUBSTITUTE(SUBSTITUTE(SUBSTITUTE(SUBSTITUTE(SUBSTITUTE(SUBSTITUTE(SUBSTITUTE(SUBSTITUTE(LOWER(LEFT(SUBSTITUTE(H24,"…",""),25)),":",""),",",""),".",""),"'",""),"’",""),"!",""),"*",""),"—",""),"–",""),"-",""),"&","")," ","") -> aquietplacedayone | J24: =IFERROR(INDEX('Domestic 2024'!$J:$J,MATCH($I24,'Domestic 2024'!$I:$I,0)),IFERROR(INDEX('Domestic 2024'!$J:$J,MATCH($D24,'Domestic 2024'!$F:$F,0)),"Other")) -> Paramount Pictures
A25: 25 | B25: Boonie Bears: Time Twist | C25: 250921235 | D25: - | E25: - | F25: 250921235 | G25: 1 | H25: =IFERROR(TRIM(LEFT(B25,FIND("(",B25)-1)),TRIM(B25)) -> Boonie Bears: Time Twist | I25: =SUBSTITUTE(SUBSTITUTE(SUBSTITUTE(SUBSTITUTE(SUBSTITUTE(SUBSTITUTE(SUBSTITUTE(SUBSTITUTE(SUBSTITUTE(SUBSTITUTE(SUBSTITUTE(SUBSTITUTE(LOWER(LEFT(SUBSTITUTE(H25,"…",""),25)),":",""),",",""),".",""),"'",""),"’",""),"!",""),"*",""),"—",""),"–",""),"-",""),"&","")," ","") -> booniebearstimetwist | J25: =IFERROR(INDEX('Domestic 2024'!$J:$J,MATCH($I25,'Domestic 2024'!$I:$I,0)),IFERROR(INDEX('Domestic 2024'!$J:$J,MATCH($D25,'Domestic 2024'!$F:$F,0)),"Other")) -> Other
A26: 26 | B26: The Garfield Movie | C26: 234748692 | D26: 91956547 | E26: 0.392 | F26: 142792145 | G26: 0.608 | H26: =IFERROR(TRIM(LEFT(B26,FIND("(",B26)-1)),TRIM(B26)) -> The Garfield Movie | I26: =SUBSTITUTE(SUBSTITUTE(SUBSTITUTE(SUBSTITUTE(SUBSTITUTE(SUBSTITUTE(SUBSTITUTE(SUBSTITUTE(SUBSTITUTE(SUBSTITUTE(SUBSTITUTE(SUBSTITUTE(LOWER(LEFT(SUBSTITUTE(H26,"…",""),25)),":",""),",",""),".",""),"'",""),"’",""),"!",""),"*",""),"—",""),"–",""),"-",""),"&","")," ","") -> thegarfieldmovie | J26: =IFERROR(INDEX('Domestic 2024'!$J:$J,MATCH($I26,'Domestic 2024'!$I:$I,0)),IFERROR(INDEX('Domestic 2024'!$J:$J,MATCH($D26,'Domestic 2024'!$F:$F,0)),"Other")) -> Sony Pictures
A27: 27 | B27: Paddington in Peru | C27: 211000000 | D27: 45800000 | E27: 0.217 | F27: 165200000 | G27: 0.783 | H27: =IFERROR(TRIM(LEFT(B27,FIND("(",B27)-1)),TRIM(B27)) -> Paddington in Peru | I27: =SUBSTITUTE(SUBSTITUTE(SUBSTITUTE(SUBSTITUTE(SUBSTITUTE(SUBSTITUTE(SUBSTITUTE(SUBSTITUTE(SUBSTITUTE(SUBSTITUTE(SUBSTITUTE(SUBSTITUTE(LOWER(LEFT(SUBSTITUTE(H27,"…",""),25)),":",""),",",""),".",""),"'",""),"’",""),"!",""),"*",""),"—",""),"–",""),"-",""),"&","")," ","") -> paddingtoninperu | J27: =IFERROR(INDEX('Domestic 2024'!$J:$J,MATCH($I27,'Domestic 2024'!$I:$I,0)),IFERROR(INDEX('Domestic 2024'!$J:$J,MATCH($D27,'Domestic 2024'!$F:$F,0)),"Other")) -> Other
A28: 28 | B28: Joker: Folie à Deux | C28: 207500287 | D28: 58300287 | E28: 0.281 | F28: 149200000 | G28: 0.719 | H28: =IFERROR(TRIM(LEFT(B28,FIND("(",B28)-1)),TRIM(B28)) -> Joker: Folie à Deux | I28: =SUBSTITUTE(SUBSTITUTE(SUBSTITUTE(SUBSTITUTE(SUBSTITUTE(SUBSTITUTE(SUBSTITUTE(SUBSTITUTE(SUBSTITUTE(SUBSTITUTE(SUBSTITUTE(SUBSTITUTE(LOWER(LEFT(SUBSTITUTE(H28,"…",""),25)),":",""),",",""),".",""),"'",""),"’",""),"!",""),"*",""),"—",""),"–",""),"-",""),"&","")," ","") -> jokerfolieàdeux | J28: =IFERROR(INDEX('Domestic 2024'!$J:$J,MATCH($I28,'Domestic 2024'!$I:$I,0)),IFERROR(INDEX('Domestic 2024'!$J:$J,MATCH($D28,'Domestic 2024'!$F:$F,0)),"Other")) -> Warner Bros.
A29: 29 | B29: Ghostbusters: Frozen Empire | C29: 201967521 | D29: 113376590 | E29: 0.561 | F29: 88590931 | G29: 0.439 | H29: =IFERROR(TRIM(LEFT(B29,FIND("(",B29)-1)),TRIM(B29)) -> Ghostbusters: Frozen Empire | I29: =SUBSTITUTE(SUBSTITUTE(SUBSTITUTE(SUBSTITUTE(SUBSTITUTE(SUBSTITUTE(SUBSTITUTE(SUBSTITUTE(SUBSTITUTE(SUBSTITUTE(SUBSTITUTE(SUBSTITUTE(LOWER(LEFT(SUBSTITUTE(H29,"…",""),25)),":",""),",",""),".",""),"'",""),"’",""),"!",""),"*",""),"—",""),"–",""),"-",""),"&","")," ","") -> ghostbustersfrozenempi | J29: =IFERROR(INDEX('Domestic 2024'!$J:$J,MATCH($I29,'Domestic 2024'!$I:$I,0)),IFERROR(INDEX('Domestic 2024'!$J:$J,MATCH($D29,'Domestic 2024'!$F:$F,0)),"Other")) -> Sony Pictures
A30: 30 | B30: IF | C30: 190535708 | D30: 111375918 | E30: 0.585 | F30: 79159790 | G30: 0.415 | H30: =IFERROR(TRIM(LEFT(B30,FIND("(",B30)-1)),TRIM(B30)) -> IF | I30: =SUBSTITUTE(SUBSTITUTE(SUBSTITUTE(SUBSTITUTE(SUBSTITUTE(SUBSTITUTE(SUBSTITUTE(SUBSTITUTE(SUBSTITUTE(SUBSTITUTE(SUBSTITUTE(SUBSTITUTE(LOWER(LEFT(SUBSTITUTE(H30,"…",""),25)),":",""),",",""),".",""),"'",""),"’",""),"!",""),"*",""),"—",""),"–",""),"-",""),"&","")," ","") -> if | J30: =IFERROR(INDEX('Domestic 2024'!$J:$J,MATCH($I30,'Domestic 2024'!$I:$I,0)),IFERROR(INDEX('Domestic 2024'!$J:$J,MATCH($D30,'Domestic 2024'!$F:$F,0)),"Other")) -> Paramount Pictures
A31: 31 | B31: Red One | C31: 186000759 | D31: 97000759 | E31: 0.522 | F31: 89000000 | G31: 0.478 | H31: =IFERROR(TRIM(LEFT(B31,FIND("(",B31)-1)),TRIM(B31)) -> Red One | I31: =SUBSTITUTE(SUBSTITUTE(SUBSTITUTE(SUBSTITUTE(SUBSTITUTE(SUBSTITUTE(SUBSTITUTE(SUBSTITUTE(SUBSTITUTE(SUBSTITUTE(SUBSTITUTE(SUBSTITUTE(LOWER(LEFT(SUBSTITUTE(H31,"…",""),25)),":",""),",",""),".",""),"'",""),"’",""),"!",""),"*",""),"—",""),"–",""),"-",""),"&","")," ","") -> redone | J31: =IFERROR(INDEX('Domestic 2024'!$J:$J,MATCH($I31,'Domestic 2024'!$I:$I,0)),IFERROR(INDEX('Domestic 2024'!$J:$J,MATCH($D31,'Domestic 2024'!$F:$F,0)),"Other")) -> Amazon MGM Studios
A32: 32 | B32: Nosferatu | C32: 181954339 | D32: 95608235 | E32: 0.525 | F32: 86346104 | G32: 0.475 | H32: =IFERROR(TRIM(LEFT(B32,FIND("(",B32)-1)),TRIM(B32)) -> Nosferatu | I32: =SUBSTITUTE(SUBSTITUTE(SUBSTITUTE(SUBSTITUTE(SUBSTITUTE(SUBSTITUTE(SUBSTITUTE(SUBSTITUTE(SUBSTITUTE(SUBSTITUTE(SUBSTITUTE(SUBSTITUTE(LOWER(LEFT(SUBSTITUTE(H32,"…",""),25)),":",""),",",""),".",""),"'",""),"’",""),"!",""),"*",""),"—",""),"–",""),"-",""),"&","")," ","") -> nosferatu | J32: =IFERROR(INDEX('Domestic 2024'!$J:$J,MATCH($I32,'Domestic 2024'!$I:$I,0)),IFERROR(INDEX('Domestic 2024'!$J:$J,MATCH($D32,'Domestic 2024'!$F:$F,0)),"Other")) -> Focus Features
A33: 33 | B33: The Fall Guy | C33: 181073291 | D33: 92900355 | E33: 0.513 | F33: 88172936 | G33: 0.487 | H33: =IFERROR(TRIM(LEFT(B33,FIND("(",B33)-1)),TRIM(B33)) -> The Fall Guy | I33: =SUBSTITUTE(SUBSTITUTE(SUBSTITUTE(SUBSTITUTE(SUBSTITUTE(SUBSTITUTE(SUBSTITUTE(SUBSTITUTE(SUBSTITUTE(SUBSTITUTE(SUBSTITUTE(SUBSTITUTE(LOWER(LEFT(SUBSTITUTE(H33,"…",""),25)),":",""),",",""),".",""),"'",""),"’",""),"!",""),"*",""),"—",""),"–",""),"-",""),"&","")," ","") -> thefallguy | J33: =IFERROR(INDEX('Domestic 2024'!$J:$J,MATCH($I33,'Domestic 2024'!$I:$I,0)),IFERROR(INDEX('Domestic 2024'!$J:$J,MATCH($D33,'Domestic 2024'!$F:$F,0)),"Other")) -> Universal
A34: 34 | B34: Bob Marley: One Love | C34: 180971146 | D34: 96981216 | E34: 0.536 | F34: 83989930 | G34: 0.464 | H34: =IFERROR(TRIM(LEFT(B34,FIND("(",B34)-1)),TRIM(B34)) -> Bob Marley: One Love | I34: =SUBSTITUTE(SUBSTITUTE(SUBSTITUTE(SUBSTITUTE(SUBSTITUTE(SUBSTITUTE(SUBSTITUTE(SUBSTITUTE(SUBSTITUTE(SUBSTITUTE(SUBSTITUTE(SUBSTITUTE(LOWER(LEFT(SUBSTITUTE(H34,"…",""),25)),":",""),",",""),".",""),"'",""),"’",""),"!",""),"*",""),"—",""),"–",""),"-",""),"&","")," ","") -> bobmarleyonelove | J34: =IFERROR(INDEX('Domestic 2024'!$J:$J,MATCH($I34,'Domestic 2024'!$I:$I,0)),IFERROR(INDEX('Domestic 2024'!$J:$J,MATCH($D34,'Domestic 2024'!$F:$F,0)),"Other")) -> Paramount Pictures
A35: 35 | B35: Pushpa: The Rule - Part 2 | C35: 175399684 | D35: 13000000 | E35: 0.074 | F35: 162399684 | G35: 0.926 | H35: =IFERROR(TRIM(LEFT(B35,FIND("(",B35)-1)),TRIM(B35)) -> Pushpa: The Rule - Part 2 | I35: =SUBSTITUTE(SUBSTITUTE(SUBSTITUTE(SUBSTITUTE(SUBSTITUTE(SUBSTITUTE(SUBSTITUTE(SUBSTITUTE(SUBSTITUTE(SUBSTITUTE(SUBSTITUTE(SUBSTITUTE(LOWER(LEFT(SUBSTITUTE(H35,"…",""),25)),":",""),",",""),".",""),"'",""),"’",""),"!",""),"*",""),"—",""),"–",""),"-",""),"&","")," ","") -> pushpatherulepart2 | J35: =IFERROR(INDEX('Domestic 2024'!$J:$J,MATCH($I35,'Domestic 2024'!$I:$I,0)),IFERROR(INDEX('Domestic 2024'!$J:$J,MATCH($D35,'Domestic 2024'!$F:$F,0)),"Other")) -> Prathyangira Cine…
A36: 36 | B36: Furiosa: A Mad Max Saga | C36: 174375791 | D36: 67475791 | E36: 0.387 | F36: 106900000 | G36: 0.613 | H36: =IFERROR(TRIM(LEFT(B36,FIND("(",B36)-1)),TRIM(B36)) -> Furiosa: A Mad Max Saga | I36: =SUBSTITUTE(SUBSTITUTE(SUBSTITUTE(SUBSTITUTE(SUBSTITUTE(SUBSTITUTE(SUBSTITUTE(SUBSTITUTE(SUBSTITUTE(SUBSTITUTE(SUBSTITUTE(SUBSTITUTE(LOWER(LEFT(SUBSTITUTE(H36,"…",""),25)),":",""),",",""),".",""),"'",""),"’",""),"!",""),"*",""),"—",""),"–",""),"-",""),"&","")," ","") -> furiosaamadmaxsaga | J36: =IFERROR(INDEX('Domestic 2024'!$J:$J,MATCH($I36,'Domestic 2024'!$I:$I,0)),IFERROR(INDEX('Domestic 2024'!$J:$J,MATCH($D36,'Domestic 2024'!$F:$F,0)),"Other")) -> Warner Bros.
A37: 37 | B37: A Place Called Silence | C37: 174308156 | D37: - | E37: - | F37: 174308156 | G37: 1 | H37: =IFERROR(TRIM(LEFT(B37,FIND("(",B37)-1)),TRIM(B37)) -> A Place Called Silence | I37: =SUBSTITUTE(SUBSTITUTE(SUBSTITUTE(SUBSTITUTE(SUBSTITUTE(SUBSTITUTE(SUBSTITUTE(SUBSTITUTE(SUBSTITUTE(SUBSTITUTE(SUBSTITUTE(SUBSTITUTE(LOWER(LEFT(SUBSTITUTE(H37,"…",""),25)),":",""),",",""),".",""),"'",""),"’",""),"!",""),"*",""),"—",""),"–",""),"-",""),"&","")," ","") -> aplacecalledsilence | J37: =IFERROR(INDEX('Domestic 2024'!$J:$J,MATCH($I37,'Domestic 2024'!$I:$I,0)),IFERROR(INDEX('Domestic 2024'!$J:$J,MATCH($D37,'Domestic 2024'!$F:$F,0)),"Other")) -> Other
A38: 38 | B38: The Beekeeper | C38: 162619535 | D38: 66220535 | E38: 0.407 | F38: 96399000 | G38: 0.593 | H38: =IFERROR(TRIM(LEFT(B38,FIND("(",B38)-1)),TRIM(B38)) -> The Beekeeper | I38: =SUBSTITUTE(SUBSTITUTE(SUBSTITUTE(SUBSTITUTE(SUBSTITUTE(SUBSTITUTE(SUBSTITUTE(SUBSTITUTE(SUBSTITUTE(SUBSTITUTE(SUBSTITUTE(SUBSTITUTE(LOWER(LEFT(SUBSTITUTE(H38,"…",""),25)),":",""),",",""),".",""),"'",""),"’",""),"!",""),"*",""),"—",""),"–",""),"-",""),"&","")," ","") -> thebeekeeper | J38: =IFERROR(INDEX('Domestic 2024'!$J:$J,MATCH($I38,'Domestic 2024'!$I:$I,0)),IFERROR(INDEX('Domestic 2024'!$J:$J,MATCH($D38,'Domestic 2024'!$F:$F,0)),"Other")) -> Amazon MGM Studios
