Workbook
Name __FDS_UNIQUE_RANGE_ID_GENERATOR_COUNTER: 1
Name is: #REF!
Name is: #REF!
Name sh: #REF!
Name sh: #REF!

Sheet DIS Experience
B1: 2022 | C1: 2022 | D1: 2022 | E1: 2022 | F1: 2023 | G1: 2023 | H1: 2023 | I1: 2023 | J1: =+F1+1 -> 2024 | K1: =+G1+1 -> 2024 | L1: =+H1+1 -> 2024 | M1: =+I1+1 -> 2024 | N1: =+J1+1 -> 2025 | O1: =+K1+1 -> 2025 | P1: =+L1+1 -> 2025 | Q1: 2025 | R1: 2026 | S1: 2026 | T1: 2026 | U1: 2026 | V1: =+R1+1 -> 2027 | W1: =+S1+1 -> 2027 | X1: =+T1+1 -> 2027 | Y1: =+U1+1 -> 2027 | AB1: 2022 | AC1: 2023 | AD1: 2024 | AE1: 2025 | AF1: 2026 | AG1: 2027
A2: Experiences | B2: 1Q22 | C2: 2Q22 | D2: 3Q22 | E2: 4Q22 | F2: 1Q23 | G2: 2Q23 | H2: 3Q23 | I2: 4Q23 | J2: 1Q24 | K2: 2Q24 | L2: 3Q24 | M2: 4Q24 | N2: 1Q25 | O2: 2Q25 | P2: 3Q25 | Q2: 4Q25 | R2: 1Q26 | S2: 2Q26 | T2: 3Q26E | U2: 4Q26E | V2: 1Q27E | W2: 2Q27E | X2: 3Q27E | Y2: 4Q27E | AB2: 2022 | AC2: 2023 | AD2: 2024 | AE2: 2025 | AF2: 2026E | AG2: 2027E
A3: Theme park admissions | B3: =[2]Segment!F280 -> 2152 | C3: =[2]Segment!G280 -> 1973 | D3: =[2]Segment!H280 -> 2312 | E3: =[2]Segment!I280 -> 2165 | F3: =[2]Segment!J280 -> 2641 | G3: =[2]Segment!K280 -> 2428 | H3: =[2]Segment!L280 -> 2731 | I3: =[2]Segment!M280 -> 2623 | ... S3: =[2]Segment!W280 -> 3092 | T3: =P3*(1+T21) -> 3145.8 | U3: =Q3*(1+U21) -> 3056.65 | V3: =R3*(1+V21) -> 3466.05 | W3: =S3*(1+W21) -> 3246.6 | X3: =T3*(1+X21) -> 3303.09 | Y3: =U3*(1+Y21) -> 2980.2337 | AB3: =+[2]Segment!Z280 -> 8602 | AC3: =+[2]Segment!AA280 -> 10423 | AD3: =+[2]Segment!AB280 -> 11171 | AE3: =+[2]Segment!AC280 -> 11707 | AF3: =SUMIF($B$1:$Y$1,AF$1,$B3:$Y3) -> 12595.45 | AG3: =SUMIF($B$1:$Y$1,AG$1,$B3:$Y3) -> 12995.974
A4: Resorts and vacations | B4: =[2]Segment!F281 -> 1445 | C4: =[2]Segment!G281 -> 1451 | D4: =[2]Segment!H281 -> 1805 | E4: =[2]Segment!I281 -> 1709 | F4: =[2]Segment!J281 -> 1980 | G4: =[2]Segment!K281 -> 1903 | H4: =[2]Segment!L281 -> 1963 | I4: =[2]Segment!M281 -> 2103 | ... S4: =[2]Segment!W281 -> 2564 | T4: =T63 -> 2779.1153 | U4: =U63 -> 2849.9047 | V4: =V63 -> 2856.0863 | W4: =W63 -> 2901.4606 | X4: =X63 -> 2973.7504 | Y4: =Y63 -> 2759.5313 | AB4: =+[2]Segment!Z281 -> 6410 | AC4: =+[2]Segment!AA281 -> 7949 | AD4: =+[2]Segment!AB281 -> 8375 | AE4: =+[2]Segment!AC281 -> 9210 | AF4: =SUMIF($B$1:$U$1,AF$1,B4:U4) -> 10603.02 | AG4: =SUMIF($B$1:$Y$1,AG$1,$B4:$Y4) -> 11490.829
A5: Parks & Experiences merchandise, food and beverage | B5: =[2]Segment!F282 -> 1626 | C5: =[2]Segment!G282 -> 1515 | D5: =[2]Segment!H282 -> 1688 | E5: =[2]Segment!I282 -> 1750 | F5: =[2]Segment!J282 -> 1980 | G5: =[2]Segment!K282 -> 1949 | H5: =[2]Segment!L282 -> 1990 | I5: =[2]Segment!M282 -> 1793 | ... S5: =[2]Segment!W282 -> 2199 | T5: =T32*T3 -> 2250.15 | U5: =U32*U3 -> 2334.58 | V5: =V32*V3 -> 2465.4 | W5: =W32*W3 -> 2308.95 | X5: =X32*X3 -> 2362.6575 | Y5: =Y32*Y3 -> 2276.2155 | AB5: =+[2]Segment!Z282 -> 6579 | AC5: =+[2]Segment!AA282 -> 7712 | AD5: =+[2]Segment!AB282 -> 8039 | AE5: =+[2]Segment!AC282 -> 8491 | AF5: =SUMIF($B$1:$U$1,AF$1,B5:U5) -> 9131.73 | AG5: =SUMIF($B$1:$Y$1,AG$1,$B5:$Y5) -> 9413.223
A6: Merchandise licensing and retail | B6: =[2]Segment!F283 -> 1411 | C6: =[2]Segment!G283 -> 1017 | D6: =[2]Segment!H283 -> 1026 | E6: =[2]Segment!I283 -> 1155 | F6: =[2]Segment!J283 -> 1355 | G6: =[2]Segment!K283 -> 881 | H6: =[2]Segment!L283 -> 1010 | I6: =[2]Segment!M283 -> 1112 | ... S6: =[2]Segment!W283 -> 962 | T6: =T33*T3 -> 1027.95 | U6: =U33*U3 -> 1302.89 | V6: =V33*V3 -> 1403.85 | W6: =W33*W3 -> 1010.1 | X6: =X33*X3 -> 1079.3475 | Y6: =Y33*Y3 -> 1270.3177 | AB6: =+[2]Segment!Z283 -> 4609 | AC6: =+[2]Segment!AA283 -> 4358 | AD6: =+[2]Segment!AB283 -> 4307 | AE6: =+[2]Segment!AC283 -> 4387 | AF6: =SUMIF($B$1:$U$1,AF$1,B6:U6) -> 4629.84 | AG6: =SUMIF($B$1:$Y$1,AG$1,$B6:$Y6) -> 4763.6153
A7: Parks licensing and other | B7: =[2]Segment!F284 -> 448 | C7: =[2]Segment!G284 -> 549 | D7: =[2]Segment!H284 -> 414 | E7: =[2]Segment!I284 -> 474 | F7: =[2]Segment!J284 -> 589 | G7: =[2]Segment!K284 -> 485 | H7: =[2]Segment!L284 -> 504 | I7: =[2]Segment!M284 -> 529 | ... S7: =[2]Segment!W284 -> 670 | T7: =T34*T3 -> 681.65783 | U7: =U34*U3 -> 662.34007 | V7: =V34*V3 -> 751.05223 | W7: =W34*W3 -> 703.5 | X7: =X34*X3 -> 715.74072 | Y7: =Y34*Y3 -> 645.78157 | AB7: =+[2]Segment!Z284 -> 1885 | AC7: =+[2]Segment!AA284 -> 2107 | AD7: =+[2]Segment!AB284 -> 2259 | AE7: =+[2]Segment!AC284 -> 2361 | AF7: =SUMIF($B$1:$U$1,AF$1,B7:U7) -> 2623.9979 | AG7: =SUMIF($B$1:$Y$1,AG$1,$B7:$Y7) -> 2816.0745
A8: Total revenue ($M) | B8: =[2]Segment!F285 -> 7082 | C8: =[2]Segment!G285 -> 6505 | D8: =[2]Segment!H285 -> 7245 | E8: =[2]Segment!I285 -> 7253 | F8: =[2]Segment!J285 -> 8545 | G8: =[2]Segment!K285 -> 7646 | H8: =[2]Segment!L285 -> 8198 | I8: =[2]Segment!M285 -> 8160 | J8: =SUM(J3:J7) -> 9132 | K8: =SUM(K3:K7) -> 8393 | L8: =SUM(L3:L7) -> 8386 | M8: =SUM(M3:M7) -> 8240 | N8: =SUM(N3:N7) -> 9415 | O8: =SUM(O3:O7) -> 8889 | P8: =SUM(P3:P7) -> 9086 | Q8: =SUM(Q3:Q7) -> 8766 | ... Y8: =SUM(Y3:Y7) -> 9932.0799 | AB8: =SUM(AB3:AB7) -> 28085 | AC8: =SUM(AC3:AC7) -> 32549 | AD8: =SUM(AD3:AD7) -> 34151 | AE8: =SUM(AE3:AE7) -> 36156 | AF8: =SUM(AF3:AF7) -> 39584.038 | AG8: =SUM(AG3:AG7) -> 41479.715
A9: Operating expenses | B9: =[2]Segment!F286 -> -3451 | C9: =[2]Segment!G286 -> -3485 | D9: =[2]Segment!H286 -> -3729 | E9: =[2]Segment!I286 -> -4271 | F9: =[2]Segment!J286 -> -4139 | G9: =[2]Segment!K286 -> -4106 | H9: =[2]Segment!L286 -> -4279 | I9: =[2]Segment!M286 -> -4605 | ... S9: =[2]Segment!W286 -> -4969 | T9: =T$8*T38 -> -5230.6304 | U9: =U$8*U38 -> -5901.9009 | V9: =V$8*V38 -> -5332.268 | W9: =W$8*W38 -> -5225.3482 | X9: =X$8*X38 -> -5417.2797 | Y9: =Y$8*Y38 -> -5643.9729 | AB9: =+[2]Segment!Z286 -> -14936 | AC9: =+[2]Segment!AA286 -> -17129 | AD9: =+[2]Segment!AB286 -> -18356 | AE9: =+[2]Segment!AC286 -> -19224 | AF9: =SUMIF($B$1:$U$1,AF$1,B9:U9) -> -21077.531 | AG9: =SUMIF($B$1:$Y$1,AG$1,$B9:$Y9) -> -21618.869
A10: SG&A | B10: =[2]Segment!F287 -> -737 | C10: =[2]Segment!G287 -> -809 | D10: =[2]Segment!H287 -> -855 | E10: =[2]Segment!I287 -> -1002 | F10: =[2]Segment!J287 -> -899 | G10: =[2]Segment!K287 -> -853 | H10: =[2]Segment!L287 -> -900 | I10: =[2]Segment!M287 -> -1023 | ... S10: =[2]Segment!W287 -> -1115 | T10: =T8*T39 -> -1093.9611 | U10: =U8*U39 -> -1066.1378 | V10: =V8*V39 -> -1106.7436 | W10: =W8*W39 -> -1246.1973 | X10: =X8*X39 -> -1206.9943 | Y10: =Y8*Y39 -> -1087.1469 | AB10: =+[2]Segment!Z287 -> -3403 | AC10: =+[2]Segment!AA287 -> -3675 | AD10: =+[2]Segment!AB287 -> -3944 | AE10: =+[2]Segment!AC287 -> -4114 | AF10: =SUMIF($B$1:$U$1,AF$1,B10:U10) -> -4237.0989 | AG10: =SUMIF($B$1:$Y$1,AG$1,$B10:$Y10) -> -4647.0821
A11: D&A | B11: =[2]Segment!F288 -> -593 | C11: =[2]Segment!G288 -> -598 | D11: =[2]Segment!H288 -> -622 | E11: =[2]Segment!I288 -> -638 | F11: =[2]Segment!J288 -> -643 | G11: =[2]Segment!K288 -> -651 | H11: =[2]Segment!L288 -> -722 | I11: =[2]Segment!M288 -> -773 | ... S11: =[2]Segment!W288 -> -788 | T11: =T8*T40 -> -770.59027 | U11: =U8*U40 -> -795.66874 | V11: =V8*V40 -> -880.40775 | W11: =W8*W40 -> -843.73447 | X11: =X8*X40 -> -891.71983 | Y11: =Y8*Y40 -> -873.60681 | AB11: =+[2]Segment!Z288 -> -2451 | AC11: =+[2]Segment!AA288 -> -2789 | AD11: =+[2]Segment!AB288 -> -2579 | AE11: =+[2]Segment!AC288 -> -2823 | AF11: =SUMIF($B$1:$U$1,AF$1,B11:U11) -> -3113.259 | AG11: =SUMIF($B$1:$Y$1,AG$1,$B11:$Y11) -> -3489.4689
A12: Equity in income(loss) of investees | B12: =[2]Segment!F289 -> -3 | C12: =[2]Segment!G289 -> -5 | D12: =[2]Segment!H289 -> -2 | E12: =[2]Segment!I289 -> 0 | F12: =[2]Segment!J289 -> -2 | G12: =[2]Segment!K289 -> 0 | H12: =[2]Segment!L289 -> 0 | I12: =[2]Segment!M289 -> 0 | ... P12: =[2]Segment!T289 -> 0 | AB12: =+[2]Segment!Z289 -> -10 | AC12: =+[2]Segment!AA289 -> -2 | AD12: =+[2]Segment!AB289 -> 0 | AE12: =+[2]Segment!AC289 -> 0 | AF12: =SUMIF($B$1:$U$1,AF$1,B12:U12) -> 0 | AG12: =SUMIF($B$1:$Y$1,AG$1,$B12:$Y12) -> 0
A13: OI ($M) | B13: =[2]Segment!F290 -> 2298 | C13: =[2]Segment!G290 -> 1608 | D13: =[2]Segment!H290 -> 2037 | E13: =[2]Segment!I290 -> 1342 | F13: =[2]Segment!J290 -> 2862 | G13: =[2]Segment!K290 -> 2036 | H13: =[2]Segment!L290 -> 2297 | I13: =[2]Segment!M290 -> 1759 | J13: =SUM(J8:J12) -> 3105 | K13: =SUM(K8:K12) -> 2286 | L13: =SUM(L8:L12) -> 2222 | M13: =SUM(M8:M12) -> 1659 | N13: =SUM(N8:N12) -> 3110 | O13: =SUM(O8:O12) -> 2491 | P13: =SUM(P8:P12) -> 2516 | Q13: =SUM(Q8:Q12) -> 1878 | ... Y13: =SUM(Y8:Y12) -> 2327.3532 | AB13: =SUM(AB8:AB12) -> 7285 | AC13: =SUM(AC8:AC12) -> 8954 | AD13: =SUM(AD8:AD12) -> 9272 | AE13: =SUM(AE8:AE12) -> 9995 | AF13: =SUM(AF8:AF12) -> 11156.149 | AG13: =SUM(AG8:AG12) -> 11724.295
A14: OI Margin (%) | B14: =B13/B8 -> 0.32448461 | C14: =C13/C8 -> 0.24719447 | D14: =D13/D8 -> 0.28115942 | E14: =E13/E8 -> 0.18502689 | F14: =F13/F8 -> 0.33493271 | G14: =G13/G8 -> 0.26628302 | H14: =H13/H8 -> 0.28019029 | I14: =I13/I8 -> 0.21556373 | ... Y14: =Y13/Y8 -> 0.23432687 | AB14: =AB13/AB8 -> 0.25939113 | AC14: =AC13/AC8 -> 0.27509294 | AD14: =AD13/AD8 -> 0.2715001 | AE14: =AE13/AE8 -> 0.27644098 | AF14: =AF13/AF8 -> 0.28183453 | AG14: =AG13/AG8 -> 0.2826513
A15: YoY | F15: =F13/B13-1 -> 0.24543081 | G15: =G13/C13-1 -> 0.26616915 | H15: =H13/D13-1 -> 0.12763868 | I15: =I13/E13-1 -> 0.31073025 | J15: =J13/F13-1 -> 0.08490566 | K15: =K13/G13-1 -> 0.12278978 | L15: =L13/H13-1 -> -0.032651284 | M15: =M13/I13-1 -> -0.056850483 | ... Y15: =Y13/U13-1 -> -0.047204393 | AC15: =AC13/AB13-1 -> 0.22910089 | AD15: =AD13/AC13-1 -> 0.035514854 | AE15: =AE13/AD13-1 -> 0.077976704 | AF15: =AF13/AE13-1 -> 0.11617295 | AG15: =AG13/AF13-1 -> 0.050926781
A16: EBITDA | B16: =B13-B11 -> 2891 | C16: =C13-C11 -> 2206 | D16: =D13-D11 -> 2659 | E16: =E13-E11 -> 1980 | F16: =F13-F11 -> 3505 | G16: =G13-G11 -> 2687 | H16: =H13-H11 -> 3019 | I16: =I13-I11 -> 2532 | ... Y16: =Y13-Y11 -> 3200.96 | AB16: =AB13-AB11 -> 9736 | AC16: =AC13-AC11 -> 11743 | AD16: =AD13-AD11 -> 11851 | AE16: =AE13-AE11 -> 12818 | AF16: =AF13-AF11 -> 14269.408 | AG16: =AG13-AG11 -> 15213.764
A17: EBITDA margin | B17: =B16/B8 -> 0.40821802 | C17: =C16/C8 -> 0.33912375 | D17: =D16/D8 -> 0.36701173 | E17: =E16/E8 -> 0.27299049 | F17: =F16/F8 -> 0.41018139 | G17: =G16/G8 -> 0.35142558 | H17: =H16/H8 -> 0.36826055 | I17: =I16/I8 -> 0.31029412 | ... Y17: =Y16/Y8 -> 0.32228496 | AB17: =AB16/AB8 -> 0.34666192 | AC17: =AC16/AC8 -> 0.36077913 | AD17: =AD16/AD8 -> 0.34701766 | AE17: =AE16/AE8 -> 0.35451931 | AF17: =AF16/AF8 -> 0.36048388 | AG17: =AG16/AG8 -> 0.36677601
A19: YoY
A20: Total revenue | F20: =F8/B8-1 -> 0.20658006 | G20: =G8/C8-1 -> 0.17540354 | H20: =H8/D8-1 -> 0.13153899 | I20: =I8/E8-1 -> 0.1250517 | J20: =J8/F8-1 -> 0.068695143 | K20: =K8/G8-1 -> 0.097698143 | L20: =L8/H8-1 -> 0.022932423 | M20: =M8/I8-1 -> 0.0098039216 | ... Y20: =Y8/U8-1 -> -0.026873912 | AC20: =AC8/AB8-1 -> 0.15894606 | AD20: =AD8/AC8-1 -> 0.049218102 | AE20: =AE8/AD8-1 -> 0.058709847 | AF20: =AF8/AE8-1 -> 0.094812421 | AG20: =AG8/AF8-1 -> 0.04788994
A21: Theme park admissions | F21: =F3/B3-1 -> 0.22723048 | G21: =G3/C3-1 -> 0.23061328 | H21: =H3/D3-1 -> 0.18122837 | I21: =I3/E3-1 -> 0.21154734 | J21: =J3/F3-1 -> 0.12911776 | K21: =K3/G3-1 -> 0.15568369 | L21: =L3/H3-1 -> 0.017942146 | M21: =M3/I3-1 -> -0.007624857 | ... S21: =S3/O3-1 -> 0.059266872 | T21: 0.05 | U21: 0.13 | V21: =T21 -> 0.05 | W21: =V21 -> 0.05 | X21: =W21 -> 0.05 | Y21: -0.025 | AC21: =AC3/AB3-1 -> 0.21169495 | AD21: =AD3/AC3-1 -> 0.071764367 | AE21: =AE3/AD3-1 -> 0.04798138 | AF21: =AF3/AE3-1 -> 0.075890493 | AG21: =AG3/AF3-1 -> 0.031799082
A22: Resorts and vacations | F22: =F4/B4-1 -> 0.37024221 | G22: =G4/C4-1 -> 0.3115093 | H22: =H4/D4-1 -> 0.087534626 | I22: =I4/E4-1 -> 0.23054418 | J22: =J4/F4-1 -> 0.06969697 | K22: =K4/G4-1 -> 0.10404624 | L22: =L4/H4-1 -> 0.077432501 | M22: =M4/I4-1 -> -0.029481693 | ... Y22: =Y4/U4-1 -> -0.031711041 | AC22: =AC4/AB4-1 -> 0.2400936 | AD22: =AD4/AC4-1 -> 0.053591647 | AE22: =AE4/AD4-1 -> 0.099701493 | AF22: =AF4/AE4-1 -> 0.15125081 | AG22: =AG4/AF4-1 -> 0.083731672
A23: Parks & Experiences merchandise, food and beverage | F23: =F5/B5-1 -> 0.21771218 | G23: =G5/C5-1 -> 0.28646865 | H23: =H5/D5-1 -> 0.17890995 | I23: =I5/E5-1 -> 0.024571429 | J23: =J5/F5-1 -> 0.062121212 | K23: =K5/G5-1 -> 0.041046691 | L23: =L5/H5-1 -> 0.0020100503 | M23: =M5/I5-1 -> 0.066926938 | ... Y23: =Y5/U5-1 -> -0.025 | AC23: =AC5/AB5-1 -> 0.17221462 | AD23: =AD5/AC5-1 -> 0.042401452 | AE23: =AE5/AD5-1 -> 0.056225899 | AF23: =AF5/AE5-1 -> 0.075459899 | AG23: =AG5/AF5-1 -> 0.030825813
A24: Merchandise licensing and retail | F24: =F6/B6-1 -> -0.039688164 | G24: =G6/C6-1 -> -0.13372665 | H24: =H6/D6-1 -> -0.015594542 | I24: =I6/E6-1 -> -0.037229437 | J24: =J6/F6-1 -> -0.010332103 | K24: =K6/G6-1 -> 0.0090805902 | L24: =L6/H6-1 -> -0.055445545 | M24: =M6/I6-1 -> 0.0098920863 | ... Y24: =Y6/U6-1 -> -0.025 | AC24: =AC6/AB6-1 -> -0.054458668 | AD24: =AD6/AC6-1 -> -0.011702616 | AE24: =AE6/AD6-1 -> 0.018574414 | AF24: =AF6/AE6-1 -> 0.055354456 | AG24: =AG6/AF6-1 -> 0.028894141
A25: Parks licensing and other | F25: =F7/B7-1 -> 0.31473214 | G25: =G7/C7-1 -> -0.11657559 | H25: =H7/D7-1 -> 0.2173913 | I25: =I7/E7-1 -> 0.11603376 | J25: =J7/F7-1 -> -0.0016977929 | K25: =K7/G7-1 -> 0.17113402 | L25: =L7/H7-1 -> 0.077380952 | M25: =M7/I7-1 -> 0.058601134 | ... Y25: =Y7/U7-1 -> -0.025 | AC25: =AC7/AB7-1 -> 0.11777188 | AD25: =AD7/AC7-1 -> 0.072140484 | AE25: =AE7/AD7-1 -> 0.045152722 | AF25: =AF7/AE7-1 -> 0.11139259 | AG25: =AG7/AF7-1 -> 0.07319999
A26: Operating expenses | F26: =(-F9)/(-B9)-1 -> 0.1993625 | G26: =(-G9)/(-C9)-1 -> 0.17819225 | H26: =(-H9)/(-D9)-1 -> 0.14749263 | I26: =(-I9)/(-E9)-1 -> 0.078201826 | J26: =(-J9)/(-F9)-1 -> 0.08238705 | K26: =(-K9)/(-G9)-1 -> 0.09814905 | L26: =(-L9)/(-H9)-1 -> 0.068707642 | M26: =(-M9)/(-I9)-1 -> 0.041042345 | ... Y26: =(-Y9)/(-U9)-1 -> -0.043702524 | AC26: =(-AC9)/(-AB9)-1 -> 0.14682646 | AD26: =(-AD9)/(-AC9)-1 -> 0.071632903 | AE26: =(-AE9)/(-AD9)-1 -> 0.047286991 | AF26: =(-AF9)/(-AE9)-1 -> 0.096417568 | AG26: =(-AG9)/(-AF9)-1 -> 0.025683155
A27: SG&A | F27: =(-F10)/(-B10)-1 -> 0.21981004 | G27: =(-G10)/(-C10)-1 -> 0.054388133 | H27: =(-H10)/(-D10)-1 -> 0.052631579 | I27: =(-I10)/(-E10)-1 -> 0.020958084 | J27: =(-J10)/(-F10)-1 -> 0.028921023 | K27: =(-K10)/(-G10)-1 -> 0.12895662 | L27: =(-L10)/(-H10)-1 -> 0.046666667 | M27: =(-M10)/(-I10)-1 -> 0.088954057 | ... Y27: =(-Y10)/(-U10)-1 -> 0.019705806 | AC27: =(-AC10)/(-AB10)-1 -> 0.079929474 | AD27: =(-AD10)/(-AC10)-1 -> 0.073197279 | AE27: =(-AE10)/(-AD10)-1 -> 0.043103448 | AF27: =(-AF10)/(-AE10)-1 -> 0.029921959 | AG27: =(-AG10)/(-AF10)-1 -> 0.096760337
A28: D&A | F28: =(-F11)/(-B11)-1 -> 0.084317032 | G28: =(-G11)/(-C11)-1 -> 0.088628763 | H28: =(-H11)/(-D11)-1 -> 0.1607717 | I28: =(-I11)/(-E11)-1 -> 0.21159875 | J28: =(-J11)/(-F11)-1 -> -0.032659409 | K28: =(-K11)/(-G11)-1 -> -0.024577573 | L28: =(-L11)/(-H11)-1 -> -0.10110803 | M28: =(-M11)/(-I11)-1 -> -0.12936611 | ... Y28: =(-Y11)/(-U11)-1 -> 0.097952907 | AC28: =(-AC11)/(-AB11)-1 -> 0.1379029 | AD28: =(-AD11)/(-AC11)-1 -> -0.075295805 | AE28: =(-AE11)/(-AD11)-1 -> 0.094610314 | AF28: =(-AF11)/(-AE11)-1 -> 0.10281935 | AG28: =(-AG11)/(-AF11)-1 -> 0.12084116
A30: % of theme park admissions
A31: Resorts and vacations | B31: =B4/B3 -> 0.6714684 | C31: =C4/C3 -> 0.73542828 | D31: =D4/D3 -> 0.78070934 | E31: =E4/E3 -> 0.78937644 | F31: =F4/F3 -> 0.74971602 | G31: =G4/G3 -> 0.78377265 | H31: =H4/H3 -> 0.71878433 | I31: =I4/I3 -> 0.80175372 | ... N31: =N4/N3 -> 0.71946874 | O31: =(O4-SUM(O59:O61))/O3 -> 0.7665125 | P31: =(P4-SUM(P59:P61))/P3 -> 0.74779706 | Q31: =(Q4-SUM(Q59:Q61))/Q3 -> 0.78127542 | R31: =(R4-SUM(R59:R61))/R3 -> 0.66846865 | S31: =(S4-SUM(S59:S61))/S3 -> 0.71842982 | AB31: =AB4/AB3 -> 0.74517554 | AC31: =AC4/AC3 -> 0.76264031 | AD31: =AD4/AD3 -> 0.74970907 | AE31: =AE4/AE3 -> 0.78670881 | AF31: =AF4/AF3 -> 0.84181351 | AG31: =AG4/AG3 -> 0.88418373
A32: Parks & Experiences merchandise, food and beverage | B32: =B5/B3 -> 0.75557621 | C32: =C5/C3 -> 0.76786619 | D32: =D5/D3 -> 0.73010381 | E32: =E5/E3 -> 0.80831409 | F32: =F5/F3 -> 0.74971602 | G32: =G5/G3 -> 0.80271829 | H32: =H5/H3 -> 0.72867082 | I32: =I5/I3 -> 0.68356843 | ... S32: =S5/S3 -> 0.71119017 | T32: =+P32 -> 0.71528705 | U32: =+Q32 -> 0.76377079 | V32: =+R32 -> 0.71129961 | W32: =+S32 -> 0.71119017 | X32: =+T32 -> 0.71528705 | Y32: =+U32 -> 0.76377079 | AB32: =AB5/AB3 -> 0.76482213 | AC32: =AC5/AC3 -> 0.73990214 | AD32: =AD5/AD3 -> 0.71963119 | AE32: =AE5/AE3 -> 0.72529256 | AF32: =AF5/AF3 -> 0.72500228 | AG32: =AG5/AG3 -> 0.72431841
A33: Merchandise licensing and retail | B33: =B6/B3 -> 0.65566914 | C33: =C6/C3 -> 0.51545869 | D33: =D6/D3 -> 0.44377163 | E33: =E6/E3 -> 0.5334873 | F33: =F6/F3 -> 0.51306323 | G33: =G6/G3 -> 0.36285008 | H33: =H6/H3 -> 0.3698279 | I33: =I6/I3 -> 0.42394205 | ... S33: =S6/S3 -> 0.31112549 | T33: =+P33 -> 0.32676903 | U33: =+Q33 -> 0.42624769 | V33: =+R33 -> 0.40502878 | W33: =+S33 -> 0.31112549 | X33: =+T33 -> 0.32676903 | Y33: =+U33 -> 0.42624769 | AB33: =AB6/AB3 -> 0.53580563 | AC33: =AC6/AC3 -> 0.41811379 | AD33: =AD6/AD3 -> 0.38555188 | AE33: =AE6/AE3 -> 0.37473307 | AF33: =AF6/AF3 -> 0.36758036 | AG33: =AG6/AG3 -> 0.36654547
A34: Parks licensing and other | B34: =B7/B3 -> 0.20817844 | C34: =C7/C3 -> 0.27825646 | D34: =D7/D3 -> 0.17906574 | E34: =E7/E3 -> 0.21893764 | F34: =F7/F3 -> 0.22302158 | G34: =G7/G3 -> 0.19975288 | H34: =H7/H3 -> 0.18454778 | I34: =I7/I3 -> 0.20167747 | ... S34: =S7/S3 -> 0.21668823 | T34: =S34 -> 0.21668823 | U34: =T34 -> 0.21668823 | V34: =U34 -> 0.21668823 | W34: =V34 -> 0.21668823 | X34: =W34 -> 0.21668823 | Y34: =X34 -> 0.21668823 | AB34: =AB7/AB3 -> 0.21913508 | AC34: =AC7/AC3 -> 0.20214909 | AD34: =AD7/AD3 -> 0.20222003 | AE34: =AE7/AE3 -> 0.20167421 | AF34: =AF7/AF3 -> 0.20832903 | AG34: =AG7/AG3 -> 0.21668823
A36: Cost drivers
A37: % of Revenue
A38: Operating expenses | B38: =B9/B8 -> -0.48729173 | C38: =C9/C8 -> -0.53574174 | D38: =D9/D8 -> -0.51469979 | E38: =E9/E8 -> -0.58885978 | F38: =F9/F8 -> -0.48437683 | G38: =G9/G8 -> -0.53701282 | H38: =H9/H8 -> -0.52195657 | I38: =I9/I8 -> -0.56433824 | ... S38: =S9/S8 -> -0.52376937 | T38: =P38 -> -0.52916575 | U38: =Q38 -> -0.5782569 | V38: =R38+1% -> -0.48730162 | W38: =S38+1% -> -0.51376937 | X38: =T38+1% -> -0.51916575 | Y38: =U38+1% -> -0.5682569 | AB38: =AB9/AB8 -> -0.53181414 | AC38: =AC9/AC8 -> -0.52625273 | AD38: =AD9/AD8 -> -0.53749524 | AE38: =AE9/AE8 -> -0.53169598 | AF38: =AF9/AF8 -> -0.53247552 | AG38: =AG9/AG8 -> -0.52119135
A39: SG&A | B39: =B10/B8 -> -0.10406665 | C39: =C10/C8 -> -0.12436587 | D39: =D10/D8 -> -0.11801242 | E39: =E10/E8 -> -0.13814973 | F39: =F10/F8 -> -0.10520772 | G39: =G10/G8 -> -0.1115616 | H39: =H10/H8 -> -0.10978287 | I39: =I10/I8 -> -0.12536765 | ... S39: =S10/S8 -> -0.11752925 | T39: =+P39+0.5% -> -0.11067246 | U39: =+Q39+2% -> -0.10445813 | V39: =+R39-0.5% -> -0.10114231 | W39: =+S39-0.5% -> -0.12252925 | X39: =+T39-0.5% -> -0.11567246 | Y39: =+U39-0.5% -> -0.10945813 | AB39: =AB10/AB8 -> -0.12116788 | AC39: =AC10/AC8 -> -0.11290669 | AD39: =AD10/AD8 -> -0.1154871 | AE39: =AE10/AE8 -> -0.11378471 | AF39: =AF10/AF8 -> -0.10704059 | AG39: =AG10/AG8 -> -0.11203264
A40: D&A | B40: =B11/B8 -> -0.083733409 | C40: =C11/C8 -> -0.091929285 | D40: =D11/D8 -> -0.085852312 | E40: =E11/E8 -> -0.087963601 | F40: =F11/F8 -> -0.075248683 | G40: =G11/G8 -> -0.085142558 | H40: =H11/H8 -> -0.088070261 | I40: =I11/I8 -> -0.094730392 | ... S40: =S11/S8 -> -0.083061031 | T40: -0.077958094 | U40: -0.077958094 | V40: -0.080458094 | W40: -0.082958094 | X40: -0.085458094 | Y40: -0.087958094 | AB40: =AB11/AB8 -> -0.087270785 | AC40: =AC11/AC8 -> -0.085686196 | AD40: =AD11/AD8 -> -0.075517554 | AE40: =AE11/AE8 -> -0.078078327 | AF40: =AF11/AF8 -> -0.078649354 | AG40: =AG11/AG8 -> -0.084124707
A44: Supplemental
A45: Revenue
A46: Parks & Experiences | B46: =[2]Segment!F294 -> 7082 | C46: =[2]Segment!G294 -> 6505 | D46: =[2]Segment!H294 -> 7245 | E46: =[2]Segment!I294 -> 7253 | F46: =[2]Segment!J294 -> 8545 | G46: =[2]Segment!K294 -> 7776 | H46: =[2]Segment!L294 -> 8326 | I46: =[2]Segment!M294 -> 8160 | ... S46: =[2]Segment!W294 -> 9487 | AB46: =SUM(AB47:AB49) -> 28085 | AC46: =SUM(AC47:AC49) -> 32549 | AD46: =SUM(AD47:AD49) -> 34151 | AE46: =SUM(AE47:AE49) -> 36156
A47: Domestic | B47: =[2]Segment!F295 -> 4800 | C47: =[2]Segment!G295 -> 4898 | D47: =[2]Segment!H295 -> 5423 | E47: =[2]Segment!I295 -> 5010 | F47: =[2]Segment!J295 -> 6072 | G47: =[2]Segment!K295 -> 5572 | H47: =[2]Segment!L295 -> 5649 | I47: =[2]Segment!M295 -> 5384 | ... S47: =[2]Segment!W295 -> 6917 | AB47: =[2]Segment!Z295 -> 20131 | AC47: =[2]Segment!AA295 -> 22677 | AD47: =[2]Segment!AB295 -> 23596 | AE47: =[2]Segment!AC295 -> 25191
A48: International | B48: =[2]Segment!F296 -> 861 | C48: =[2]Segment!G296 -> 574 | D48: =[2]Segment!H296 -> 788 | E48: =[2]Segment!I296 -> 1074 | F48: =[2]Segment!J296 -> 1094 | G48: =[2]Segment!K296 -> 1184 | H48: =[2]Segment!L296 -> 1532 | I48: =[2]Segment!M296 -> 1665 | ... S48: =[2]Segment!W296 -> 1596 | AB48: =[2]Segment!Z296 -> 3297 | AC48: =[2]Segment!AA296 -> 5475 | AD48: =[2]Segment!AB296 -> 6183 | AE48: =[2]Segment!AC296 -> 6520
A49: Consumer products | B49: =[2]Segment!F297 -> 1421 | C49: =[2]Segment!G297 -> 1033 | D49: =[2]Segment!H297 -> 1034 | E49: =[2]Segment!I297 -> 1169 | F49: =[2]Segment!J297 -> 1379 | G49: =[2]Segment!K297 -> 1020 | H49: =[2]Segment!L297 -> 1145 | I49: =[2]Segment!M297 -> 1111 | ... S49: =[2]Segment!W297 -> 974 | AB49: =[2]Segment!Z297 -> 4657 | AC49: =[2]Segment!AA297 -> 4397 | AD49: =[2]Segment!AB297 -> 4372 | AE49: =[2]Segment!AC297 -> 4445
A51: OI
A52: Parks & Experiences | B52: =SUM(B53:B55) -> 2298 | C52: =SUM(C53:C55) -> 1608 | D52: =SUM(D53:D55) -> 2037 | E52: =SUM(E53:E55) -> 1342 | F52: =SUM(F53:F55) -> 1498 | G52: =SUM(G53:G55) -> 2036 | H52: =SUM(H53:H55) -> 2297 | I52: =SUM(I53:I55) -> 1759 | ... S52: =SUM(S53:S55) -> 2615 | AB52: =SUM(AB53:AB55) -> 7285 | AC52: =SUM(AC53:AC55) -> 8954 | AD52: =SUM(AD53:AD55) -> 9272 | AE52: =SUM(AE53:AE55) -> 9995
A53: Domestic | B53: =[2]Segment!F301 -> 1555 | C53: =[2]Segment!G301 -> 1385 | D53: =[2]Segment!H301 -> 1651 | E53: =[2]Segment!I301 -> 741 | F53: =[2]Segment!J301 -> 79 | G53: =[2]Segment!K301 -> 1519 | H53: =[2]Segment!L301 -> 1436 | I53: =[2]Segment!M301 -> 808 | ... S53: =[2]Segment!W301 -> 1909 | AB53: =[2]Segment!Z301 -> 5332 | AC53: =[2]Segment!AA301 -> 5876 | AD53: =[2]Segment!AB301 -> 5878 | AE53: =[2]Segment!AC301 -> 6375
A54: International | B54: =[2]Segment!F302 -> 21 | C54: =[2]Segment!G302 -> -268 | D54: =[2]Segment!H302 -> -64 | E54: =[2]Segment!I302 -> 74 | F54: =[2]Segment!J302 -> 670 | G54: =[2]Segment!K302 -> 156 | H54: =[2]Segment!L302 -> 428 | I54: =[2]Segment!M302 -> 441 | ... S54: =[2]Segment!W302 -> 227 | AB54: =[2]Segment!Z302 -> -237 | AC54: =[2]Segment!AA302 -> 1104 | AD54: =[2]Segment!AB302 -> 1354 | AE54: =[2]Segment!AC302 -> 1442
A55: Consumer products | B55: =[2]Segment!F303 -> 722 | C55: =[2]Segment!G303 -> 491 | D55: =[2]Segment!H303 -> 450 | E55: =[2]Segment!I303 -> 527 | F55: =[2]Segment!J303 -> 749 | G55: =[2]Segment!K303 -> 361 | H55: =[2]Segment!L303 -> 433 | I55: =[2]Segment!M303 -> 510 | ... S55: =[2]Segment!W303 -> 479 | AB55: =[2]Segment!Z303 -> 2190 | AC55: =[2]Segment!AA303 -> 1974 | AD55: =[2]Segment!AB303 -> 2040 | AE55: =[2]Segment!AC303 -> 2178
A57: Base resorts and vacations revenue | B57: =+B4 -> 1445 | C57: =+C4 -> 1451 | D57: =+D4 -> 1805 | E57: =+E4 -> 1709 | F57: =+F4 -> 1980 | G57: =+G4 -> 1903 | H57: =+H4 -> 1963 | I57: =+I4 -> 2103 | ... N57: =+N4 -> 2221 | O57: =O4-O62 -> 2237.45 | P57: =P4-P62 -> 2240.4 | Q57: =Q4-Q62 -> 2113.35 | R57: =R4-R62 -> 2206.615 | S57: =S4-S62 -> 2221.385 | T57: =P57*(1+T58) -> 2262.804 | U57: =Q57*(1+U58) -> 2292.9847 | V57: =R57*(1+V58) -> 2228.6811 | W57: =S57*(1+W58) -> 2243.5988 | X57: =T57*(1+X58) -> 2285.432 | Y57: =U57*(1+Y58) -> 2040.7564 | AB57: =SUMIF($B$1:$U$1,AB$1,$B57:$U57) -> 6410 | AC57: =SUMIF($B$1:$U$1,AC$1,$B57:$U57) -> 7949 | AD57: =SUMIF($B$1:$U$1,AD$1,$B57:$U57) -> 8375 | AE57: =SUMIF($B$1:$U$1,AE$1,$B57:$U57) -> 8812.2 | AF57: =SUMIF($B$1:$Y$1,AF$1,$B57:$Y57) -> 8983.7887 | AG57: =SUMIF($B$1:$Y$1,AG$1,$B57:$Y57) -> 8798.4685
A58: YoY growth % | F58: =+F57/B57-1 -> 0.37024221 | G58: =+G57/C57-1 -> 0.3115093 | H58: =+H57/D57-1 -> 0.087534626 | I58: =+I57/E57-1 -> 0.23054418 | J58: =+J57/F57-1 -> 0.06969697 | K58: =+K57/G57-1 -> 0.10404624 | L58: =+L57/H57-1 -> 0.077432501 | M58: =+M57/I57-1 -> -0.029481693 | ... S58: =+S57/O57-1 -> -0.0071800487 | T58: 0.01 | U58: 0.085 | V58: =T58 -> 0.01 | W58: =V58 -> 0.01 | X58: =W58 -> 0.01 | Y58: -0.11 | AC58: =+AC57/AB57-1 -> 0.2400936 | AD58: =+AD57/AC57-1 -> 0.053591647 | AE58: =+AE57/AD57-1 -> 0.052202985 | AF58: =+AF57/AE57-1 -> 0.019471727 | AG58: =+AG57/AF57-1 -> -0.020628299
A59: Treasure (Dec 2024) | M59: from our side analysis | O59: 121.55 | P59: 132.6 | Q59: 143.65 | R59: 162.435 | S59: 174.0375 | T59: 185.64 | U59: 197.2425 | V59: 219.28725 | W59: 219.28725 | X59: 219.28725 | Y59: 219.28725 | AE59: =SUMIF($B$1:$U$1,AE$1,$B59:$U59) -> 397.8 | AF59: =SUMIF($B$1:$U$1,AF$1,$B59:$U59) -> 719.355 | AG59: =SUMIF($B$1:$Y$1,AG$1,$B59:$Y59) -> 877.149
A60: Destiny (Nov 2025) | R60: 40.95 | S60: 127.6275 | T60: 139.23 | U60: 150.8325 | V60: 170.55675 | W60: 182.73938 | X60: 194.922 | Y60: 207.10463 | AE60: =SUMIF($B$1:$U$1,AE$1,$B60:$U60) -> 0 | AF60: =SUMIF($B$1:$U$1,AF$1,$B60:$U60) -> 458.64 | AG60: =SUMIF($B$1:$Y$1,AG$1,$B60:$Y60) -> 755.32275
A61: Adventure (March 2026) | S61: 40.95 | T61: 191.44125 | U61: 208.845 | V61: 237.56119 | W61: 255.83513 | X61: 274.10906 | Y61: 292.383 | AE61: =SUMIF($B$1:$U$1,AE$1,$B61:$U61) -> 0 | AF61: =SUMIF($B$1:$U$1,AF$1,$B61:$U61) -> 441.23625 | AG61: =SUMIF($B$1:$Y$1,AG$1,$B61:$Y61) -> 1059.8884
A62: Incremental cruise revenue | O62: =+SUM(O59:O61) -> 121.55 | P62: =+SUM(P59:P61) -> 132.6 | Q62: =+SUM(Q59:Q61) -> 143.65 | R62: =+SUM(R59:R61) -> 203.385 | S62: =+SUM(S59:S61) -> 342.615 | T62: =+SUM(T59:T61) -> 516.31125 | U62: =+SUM(U59:U61) -> 556.92 | V62: =+SUM(V59:V61) -> 627.40519 | ... Y62: =+SUM(Y59:Y61) -> 718.77488 | AE62: =SUMIF($B$1:$U$1,AE$1,$B62:$U62) -> 397.8 | AF62: =SUMIF($B$1:$U$1,AF$1,$B62:$U62) -> 1619.2313 | AG62: =SUMIF($B$1:$Y$1,AG$1,$B62:$Y62) -> 2692.3601
A63: Total Resorts and Vacations Revenue | B63: =+B62+B57 -> 1445 | C63: =+C62+C57 -> 1451 | D63: =+D62+D57 -> 1805 | E63: =+E62+E57 -> 1709 | F63: =+F62+F57 -> 1980 | G63: =+G62+G57 -> 1903 | H63: =+H62+H57 -> 1963 | I63: =+I62+I57 -> 2103 | ... Y63: =+Y62+Y57 -> 2759.5313 | AB63: =SUMIF($B$1:$U$1,AB$1,$B63:$U63) -> 6410 | AC63: =SUMIF($B$1:$U$1,AC$1,$B63:$U63) -> 7949 | AD63: =SUMIF($B$1:$U$1,AD$1,$B63:$U63) -> 8375 | AE63: =SUMIF($B$1:$U$1,AE$1,$B63:$U63) -> 9210 | AF63: =SUMIF($B$1:$U$1,AF$1,$B63:$U63) -> 10603.02 | AG63: =SUMIF($B$1:$Y$1,AG$1,$B63:$Y63) -> 11490.829
A64: YoY growth % | F64: =+F63/B63-1 -> 0.37024221 | G64: =+G63/C63-1 -> 0.3115093 | H64: =+H63/D63-1 -> 0.087534626 | I64: =+I63/E63-1 -> 0.23054418 | J64: =+J63/F63-1 -> 0.06969697 | K64: =+K63/G63-1 -> 0.10404624 | L64: =+L63/H63-1 -> 0.077432501 | M64: =+M63/I63-1 -> -0.029481693 | ... Y64: =+Y63/U63-1 -> -0.031711041 | AC64: =+AC63/AB63-1 -> 0.2400936 | AD64: =+AD63/AC63-1 -> 0.053591647 | AE64: =+AE63/AD63-1 -> 0.099701493 | AF64: =+AF63/AE63-1 -> 0.15125081 | AG64: =+AG63/AF63-1 -> 0.083731672
A66: Operating margin for cruise | O66: 0.25 | P66: 0.25 | Q66: 0.25 | R66: =Q66-2% -> 0.23 | S66: =R66-2% -> 0.21 | T66: =S66-2% -> 0.19 | U66: =T66-2% -> 0.17 | V66: =U66-0.5% -> 0.165 | W66: =V66-0.5% -> 0.16 | X66: =W66-0.5% -> 0.155 | Y66: =X66-0.5% -> 0.15
A67: Operating Income from incremental cruise lines | O67: =+O66*O62 -> 30.3875 | P67: =+P66*P62 -> 33.15 | Q67: =+Q66*Q62 -> 35.9125 | R67: =+R66*R62 -> 46.77855 | S67: =+S66*S62 -> 71.94915 | T67: =+T66*T62 -> 98.099138 | U67: =+U66*U62 -> 94.6764 | V67: =+V66*V62 -> 103.52186 | ... Y67: =+Y66*Y62 -> 107.81623 | AE67: =SUMIF($B$1:$U$1,AE$1,$B67:$U67) -> 99.45 | AF67: =SUMIF($B$1:$U$1,AF$1,$B67:$U67) -> 311.50324 | AG67: =SUMIF($B$1:$Y$1,AG$1,$B67:$Y67) -> 423.28531
A68: Base line Operating Income | B68: =+B13-B67 -> 2298 | C68: =+C13-C67 -> 1608 | D68: =+D13-D67 -> 2037 | E68: =+E13-E67 -> 1342 | F68: =+F13-F67 -> 2862 | G68: =+G13-G67 -> 2036 | H68: =+H13-H67 -> 2297 | I68: =+I13-I67 -> 1759 | ... Y68: =+Y13-Y67 -> 2219.537 | AB68: =+AB13-AB67 -> 7285 | AC68: =+AC13-AC67 -> 8954 | AD68: =+AD13-AD67 -> 9272 | AE68: =+AE13-AE67 -> 9895.55 | AF68: =+AF13-AF67 -> 10844.645 | AG68: =+AG13-AG67 -> 11301.01
A69: YoY growth % | F69: =+F68/B68-1 -> 0.24543081 | G69: =+G68/C68-1 -> 0.26616915 | H69: =+H68/D68-1 -> 0.12763868 | I69: =+I68/E68-1 -> 0.31073025 | J69: =+J68/F68-1 -> 0.08490566 | K69: =+K68/G68-1 -> 0.12278978 | L69: =+L68/H68-1 -> -0.032651284 | M69: =+M68/I68-1 -> -0.056850483 | ... Y69: =+Y68/U68-1 -> -0.054704017 | AC69: =+AC68/AB68-1 -> 0.22910089 | AD69: =+AD68/AC68-1 -> 0.035514854 | AE69: =+AE68/AD68-1 -> 0.067250863 | AF69: =+AF68/AE68-1 -> 0.095911331 | AG69: =+AG68/AF68-1 -> 0.042082028
A71: Operating expenses
A72: Operating labor | B72: =-[2]Segment!F306 -> 0 | C72: =-[2]Segment!G306 -> 0 | D72: =-[2]Segment!H306 -> 0 | E72: =-[2]Segment!I306 -> 0 | F72: =-[2]Segment!J306 -> 1789 | G72: =-[2]Segment!K306 -> 1826 | H72: =-[2]Segment!L306 -> 1938 | I72: =-[2]Segment!M306 -> 2839 | ... S72: =-[2]Segment!W306 -> 2355
A73: Infrastructure costs | B73: =-[2]Segment!F307 -> 0 | C73: =-[2]Segment!G307 -> 0 | D73: =-[2]Segment!H307 -> 0 | E73: =-[2]Segment!I307 -> 0 | F73: =-[2]Segment!J307 -> 722 | G73: =-[2]Segment!K307 -> 750 | H73: =-[2]Segment!L307 -> 754 | I73: =-[2]Segment!M307 -> 1137 | ... S73: =-[2]Segment!W307 -> 856
A74: COGS and distributon costs | B74: =-[2]Segment!F308 -> 0 | C74: =-[2]Segment!G308 -> 0 | D74: =-[2]Segment!H308 -> 0 | E74: =-[2]Segment!I308 -> 0 | F74: =-[2]Segment!J308 -> 912 | G74: =-[2]Segment!K308 -> 767 | H74: =-[2]Segment!L308 -> 811 | I74: =-[2]Segment!M308 -> 829 | ... S74: =-[2]Segment!W308 -> 773
A75: Other operating expenses | B75: =-[2]Segment!F309 -> 0 | C75: =-[2]Segment!G309 -> 0 | D75: =-[2]Segment!H309 -> 0 | E75: =-[2]Segment!I309 -> 0 | F75: =-[2]Segment!J309 -> 716 | G75: =-[2]Segment!K309 -> 763 | H75: =-[2]Segment!L309 -> 776 | I75: =-[2]Segment!M309 -> 1027 | ... S75: =-[2]Segment!W309 -> 985
A76: Total | F76: =+SUM(F72:F75) -> 4139 | G76: =+SUM(G72:G75) -> 4106 | H76: =+SUM(H72:H75) -> 4279 | I76: =+SUM(I72:I75) -> 5832 | J76: =+SUM(J72:J75) -> 4480 | K76: =+SUM(K72:K75) -> 4509 | L76: =+SUM(L72:L75) -> 4573 | M76: =+SUM(M72:M75) -> 4794 | ... S76: =+SUM(S72:S75) -> 4969
A78: YoY growth %
A79: Operating labor | J79: =+J72/F72-1 -> 0.11794298 | K79: =+K72/G72-1 -> 0.13253012 | L79: =+L72/H72-1 -> 0.11145511 | M79: =+M72/I72-1 -> -0.23564635 | N79: =+N72/J72-1 -> 0.082 | O79: =+O72/K72-1 -> 0.070116054 | P79: =+P72/L72-1 -> 0.060352832 | Q79: =+Q72/M72-1 -> 0.053917051 | ... S79: =+S72/O72-1 -> 0.06416629
A80: Infrastructure costs | J80: =+J73/F73-1 -> 0.10387812 | K80: =+K73/G73-1 -> 0.082666667 | L80: =+L73/H73-1 -> 0.091511936 | M80: =+M73/I73-1 -> -0.18117854 | N80: =+N73/J73-1 -> 0.0050188206 | O80: =+O73/K73-1 -> 0.054187192 | P80: =+P73/L73-1 -> 0.057108141 | Q80: =+Q73/M73-1 -> 0.056928034 | ... S80: =+S73/O73-1 -> 0
A81: COGS and distributon costs | J81: =+J74/F74-1 -> -0.0087719298 | K81: =+K74/G74-1 -> 0.04041721 | L81: =+L74/H74-1 -> -0.038224414 | M81: =+M74/I74-1 -> 0.0096501809 | N81: =+N74/J74-1 -> 0.027654867 | O81: =+O74/K74-1 -> -0.093984962 | P81: =+P74/L74-1 -> -0.0012820513 | Q81: =+Q74/M74-1 -> -0.017921147 | ... S81: =+S74/O74-1 -> 0.069156293
A82: Other operating expenses | J82: =+J75/F75-1 -> 0.087988827 | K82: =+K75/G75-1 -> 0.089121887 | L82: =+L75/H75-1 -> 0.051546392 | M82: =+M75/I75-1 -> -0.16650438 | N82: =+N75/J75-1 -> 0.0064184852 | O82: =+O75/K75-1 -> 0.055354994 | P82: =+P75/L75-1 -> 0.072303922 | Q82: =+Q75/M75-1 -> 0.14018692 | ... S82: =+S75/O75-1 -> 0.12314709

Sheet CMCSA Segments
C1: 2021 | D1: =C1 -> 2021 | E1: =D1 -> 2021 | F1: =E1 -> 2021 | G1: =C1+1 -> 2022 | H1: =D1+1 -> 2022 | I1: =E1+1 -> 2022 | J1: =F1+1 -> 2022 | K1: =G1+1 -> 2023 | L1: =H1+1 -> 2023 | M1: =I1+1 -> 2023 | N1: =J1+1 -> 2023 | O1: 2024 | P1: 2024 | Q1: 2024 | R1: 2024 | S1: 2025 | T1: 2025 | U1: 2025 | V1: 2025 | W1: 2026 | X1: 2026 | AA1: 2021 | AB1: 2022 | AC1: 2023 | AD1: 2024 | AE1: 2025
C2: 1 | D2: =C2+1 -> 2 | E2: =D2+1 -> 3 | F2: =E2+1 -> 4 | G2: =C2 -> 1 | H2: =D2 -> 2 | I2: =E2 -> 3 | J2: =F2 -> 4 | K2: =G2 -> 1 | L2: =H2 -> 2 | M2: =I2 -> 3 | N2: =J2 -> 4 | O2: 1 | P2: 2 | Q2: 3 | R2: 4 | S2: 1 | T2: 2 | U2: 3 | V2: 4 | W2: 1 | X2: 2
C3: Q | D3: Q | E3: Q | F3: Q | G3: Q | H3: Q | I3: Q | J3: Q | K3: Q | L3: Q | M3: Q | N3: Q
C4: 1 | D4: =C4+1 -> 2 | E4: =D4+1 -> 3 | F4: =E4+1 -> 4 | G4: 1 | H4: =G4+1 -> 2 | I4: =H4+1 -> 3 | J4: =I4+1 -> 4 | K4: 1 | L4: =K4+1 -> 2 | M4: =L4+1 -> 3 | N4: =M4+1 -> 4
B5: in million $ | C5: =_xlfn.CONCAT(C4,C3,21) -> 1Q21 | D5: =_xlfn.CONCAT(D4,D3,21) -> 2Q21 | E5: =_xlfn.CONCAT(E4,E3,21) -> 3Q21 | F5: =_xlfn.CONCAT(F4,F3,21) -> 4Q21 | G5: =_xlfn.CONCAT(G4,G3,22) -> 1Q22 | H5: =_xlfn.CONCAT(H4,H3,22) -> 2Q22 | I5: =_xlfn.CONCAT(I4,I3,22) -> 3Q22 | J5: =_xlfn.CONCAT(J4,J3,22) -> 4Q22 | K5: =_xlfn.CONCAT(K4,K3,23) -> 1Q23 | L5: =_xlfn.CONCAT(L4,L3,23) -> 2Q23 | M5: =_xlfn.CONCAT(M4,M3,23) -> 3Q23 | N5: =_xlfn.CONCAT(N4,N3,23) -> 4Q23 | O5: 1Q24 | P5: 2Q24 | Q5: 3Q24 | R5: 4Q24 | S5: 1Q25 | T5: 2Q25 | U5: 3Q25 | V5: 4Q25 | W5: 1Q26 | X5: 2Q26 | AA5: 2021 | AB5: 2022 | AC5: 2023 | AD5: 2024 | AE5: 2025
B6: Consolidated revenue | C6: =C23+C86+C187+C191 -> 27203 | D6: =D23+D86+D187+D191 -> 28547 | E6: =E23+E86+E187+E191 -> 30297 | F6: =F23+F86+F187+F191 -> 30335 | G6: =G23+G86+G187+G191 -> 31011 | H6: =H23+H86+H187+H191 -> 30016 | I6: =I23+I86+I187+I191 -> 29850 | J6: =J23+J86+J187+J191 -> 30552 | ... N6: =N23+N86+N187+N191 -> 31252 | O6: =O23+O86+O187+O191-1 -> 28013 | P6: =P23+P86+P187+P191 -> 27582 | Q6: =Q23+Q86+Q187+Q191 -> 30014 | R6: =R23+R86+R187+R191 -> 29851 | S6: =S23+S86+S187+S191-1 -> 27865 | T6: =T23+T86+T187+T191+1 -> 28249 | U6: =U23+U86+U187+U191-1 -> 29151 | V6: =V23+V86+V187+V191 -> 30287 | W6: =W23+W86+W187+W191-1 -> 30892 | X6: =X23+X86+X187+X191+1 -> 29568 | AA6: =SUMIF($C$1:$M$1,AA$1,$C6:$M6) -> 116382 | AB6: =SUMIF($C$1:$M$1,AB$1,$C6:$M6) -> 121429 | AC6: =SUMIF($C$1:$N$1,AC$1,$C6:$N6) -> 121575 | AD6: =SUMIF($C$1:$R$1,AD$1,$C6:$R6)-1 -> 115459 | AE6: =SUMIF($C$1:$V$1,AE$1,$C6:$V6) -> 115552
B8: Previous Reporting (Changed in 2Q26, Sky Germany Sale)
B9: Consolidated revenue | C9: 27203 | D9: 28547 | E9: 30297 | F9: 30335 | G9: 31011 | H9: 30016 | I9: 29850 | J9: 30552 | K9: 29692 | L9: 30516 | M9: 30115 | N9: 31252 | O9: 28461 | P9: 28098 | Q9: 30532 | R9: 30372 | S9: 28369 | T9: 28790 | U9: 29704 | V9: 30877 | AA9: 116382 | AB9: 121429 | AC9: 121575 | AD9: 117463 | AE9: 117740
A11: x | B11: C&P Revenue
B12: Residential Connectivity | C12: =SUM(C13:C17) -> 6875 | D12: =SUM(D13:D17) -> 7067 | E12: =SUM(E13:E17) -> 7244 | F12: =SUM(F13:F17) -> 7466 | G12: =SUM(G13:G17) -> 7567 | H12: =SUM(H13:H17) -> 7620 | I12: =SUM(I13:I17) -> 7766 | J12: =SUM(J13:J17) -> 8013 | ... L12: =SUM(L13:L17) -> 8065 | M12: =SUM(M13:M17)+1 -> 8179 | N12: =SUM(N13:N17) -> 8392 | O12: =SUM(O15:O17) -> 8578 | P12: =SUM(P15:P17)+1 -> 8625 | Q12: =SUM(Q15:Q17)+1 -> 8762 | R12: =SUM(R15:R17) -> 8961 | S12: =SUM(S15:S17) -> 8934 | T12: =SUM(T15:T17) -> 9063 | U12: =SUM(U15:U17) -> 9071 | V12: =SUM(V15:V17) -> 9150 | W12: =SUM(W15:W17) -> 8973 | X12: =SUM(X15:X17) -> 8937 | AA12: =SUMIF($C$1:$M$1,AA$1,$C12:$M12) -> 28652 | AB12: =SUMIF($C$1:$M$1,AB$1,$C12:$M12) -> 30966 | AC12: =SUMIF($C$1:$N$1,AC$1,$C12:$N12) -> 32581 | AD12: =SUMIF($C$1:$R$1,AD$1,$C12:$R12)-1 -> 34925 | AE12: =SUMIF($C$1:$V$1,AE$1,$C12:$V12) -> 36218
B13: Domestic BB | C13: 5600 | D13: 5717 | E13: 5801 | F13: 5861 | G13: 6050 | H13: 6107 | I13: 6135 | J13: 6177 | K13: 6246 | L13: 6270 | M13: 6229 | N13: 6254 | O13: ='[1]pro-forma'!B8 -> 6573 | P13: ='[1]pro-forma'!C8 -> 6549 | Q13: ='[1]pro-forma'!D8 -> 6518 | R13: ='[1]pro-forma'!E8 -> 6509 | S13: ='[1]pro-forma'!F8 -> 6679 | T13: ='[1]pro-forma'!G8 -> 6649 | U13: ='[1]pro-forma'!H8 -> 6550 | V13: ='[1]pro-forma'!I8 -> 6410 | W13: ='[1]pro-forma'!J8 -> 6338 | X13: 6280 | AA13: =SUMIF($C$1:$M$1,AA$1,$C13:$M13) -> 22979 | AB13: =SUMIF($C$1:$M$1,AB$1,$C13:$M13) -> 24469 | AC13: =SUMIF($C$1:$N$1,AC$1,$C13:$N13) -> 24999 | AD13: =SUMIF($C$1:$R$1,AD$1,$C13:$R13) -> 26149 | AE13: =SUMIF($C$1:$V$1,AE$1,$C13:$V13) -> 26288
B14: Domestic Wireless | C14: 513 | D14: 556 | E14: 603 | F14: 709 | G14: 677 | H14: 722 | I14: 789 | J14: 883 | K14: 858 | L14: 869 | M14: 917 | N14: 1020 | O14: 733 | P14: 774 | Q14: 823 | R14: 836 | S14: 850 | T14: 882 | U14: 915 | V14: 965 | W14: 977 | X14: 1007 | AA14: =SUMIF($C$1:$M$1,AA$1,$C14:$M14) -> 2381 | AB14: =SUMIF($C$1:$M$1,AB$1,$C14:$M14) -> 3071 | AC14: =SUMIF($C$1:$N$1,AC$1,$C14:$N14) -> 3664 | AD14: =SUMIF($C$1:$R$1,AD$1,$C14:$R14) -> 3166 | AE14: =SUMIF($C$1:$V$1,AE$1,$C14:$V14) -> 3612
B15: Domestic Convergence Revenue | O15: =SUM(O13:O14) -> 7306 | P15: =SUM(P13:P14) -> 7323 | Q15: =SUM(Q13:Q14) -> 7341 | R15: =SUM(R13:R14) -> 7345 | S15: =SUM(S13:S14) -> 7529 | T15: =SUM(T13:T14) -> 7531 | U15: =SUM(U13:U14) -> 7465 | V15: =SUM(V13:V14) -> 7375 | ... X15: =SUM(X13:X14) -> 7287 | AD15: =SUMIF($C$1:$R$1,AD$1,$C15:$R15) -> 29315 | AE15: =SUMIF($C$1:$V$1,AE$1,$C15:$V15) -> 29900
B16: Domestic Wireless Equipment4 | O16: 239 | P16: 245 | Q16: 270 | R16: 353 | S16: 273 | T16: 313 | U16: 331 | V16: 438 | W16: 418 | X16: 404 | AD16: =SUMIF($C$1:$R$1,AD$1,$C16:$R16) -> 1107 | AE16: =SUMIF($C$1:$V$1,AE$1,$C16:$V16) -> 1355
B17: International Connectivity | C17: 762 | D17: 794 | E17: 840 | F17: 896 | G17: 840 | H17: 791 | I17: 842 | J17: 953 | K17: 841 | L17: 926 | M17: 1032 | N17: 1118 | O17: 1033 | P17: 1056 | Q17: 1150 | R17: 1263 | S17: 1132 | T17: 1219 | U17: 1275 | V17: 1337 | W17: 1240 | X17: 1246 | AA17: =SUMIF($C$1:$M$1,AA$1,$C17:$M17) -> 3292 | AB17: =SUMIF($C$1:$M$1,AB$1,$C17:$M17) -> 3426 | AC17: =SUMIF($C$1:$N$1,AC$1,$C17:$N17) -> 3917 | AD17: =SUMIF($C$1:$R$1,AD$1,$C17:$R17) -> 4502 | AE17: =SUMIF($C$1:$V$1,AE$1,$C17:$V17) -> 4963
B18: Video | C18: 8191 | D18: 8232 | E18: 8080 | F18: 7936 | G18: 8002 | H18: 7793 | I18: 7428 | J18: 7273 | K18: 7537 | L18: 7542 | M18: 7368 | N18: 7131 | O18: ='[1]pro-forma'!B14 -> 6977 | P18: ='[1]pro-forma'!C14 -> 6894 | Q18: ='[1]pro-forma'!D14 -> 6821 | R18: ='[1]pro-forma'!E14 -> 6615 | S18: ='[1]pro-forma'!F14 -> 6600 | T18: ='[1]pro-forma'!G14 -> 6605 | U18: ='[1]pro-forma'!H14 -> 6475 | V18: ='[1]pro-forma'!I14 -> 6266 | W18: 6256 | X18: 6092 | AA18: =SUMIF($C$1:$M$1,AA$1,$C18:$M18) -> 32439 | AB18: =SUMIF($C$1:$M$1,AB$1,$C18:$M18) -> 30496 | AC18: =SUMIF($C$1:$N$1,AC$1,$C18:$N18) -> 29578 | AD18: =SUMIF($C$1:$R$1,AD$1,$C18:$R18)+1 -> 27308 | AE18: =SUMIF($C$1:$V$1,AE$1,$C18:$V18) -> 25946
B19: Advertising | C19: 1001 | D19: 1128 | E19: 1097 | F19: 1282 | G19: 1073 | H19: 1112 | I19: 1078 | J19: 1283 | K19: 907 | L19: 993 | M19: 960 | N19: 1109 | O19: 973 | P19: 1012 | Q19: 1012 | R19: 1188 | S19: 899 | T19: 951 | U19: 893 | V19: 1067 | W19: 951 | X19: 962 | AA19: =SUMIF($C$1:$M$1,AA$1,$C19:$M19) -> 4508 | AB19: =SUMIF($C$1:$M$1,AB$1,$C19:$M19) -> 4546 | AC19: =SUMIF($C$1:$N$1,AC$1,$C19:$N19) -> 3969 | AD19: =SUMIF($C$1:$R$1,AD$1,$C19:$R19) -> 4185 | AE19: =SUMIF($C$1:$V$1,AE$1,$C19:$V19) -> 3810
B20: Other | C20: 1785 | D20: 1805 | E20: 1759 | F20: 1747 | G20: 1698 | H20: 1607 | I20: 1561 | J20: 1512 | K20: 1482 | L20: 1469 | M20: 1444 | N20: 1426 | O20: 1367 | P20: 1319 | Q20: 1301 | R20: 1290 | S20: 1233 | T20: 1219 | U20: 1197 | V20: 1209 | W20: 1143 | X20: 1133 | AA20: =SUMIF($C$1:$M$1,AA$1,$C20:$M20) -> 7096 | AB20: =SUMIF($C$1:$M$1,AB$1,$C20:$M20) -> 6378 | AC20: =SUMIF($C$1:$N$1,AC$1,$C20:$N20) -> 5821 | AD20: =SUMIF($C$1:$R$1,AD$1,$C20:$R20) -> 5277 | AE20: =SUMIF($C$1:$V$1,AE$1,$C20:$V20) -> 4858
B21: Residential C&P | C21: =C12+SUM(C18:C20)-1 -> 17851 | D21: =D12+SUM(D18:D20) -> 18232 | E21: =E12+SUM(E18:E20) -> 18180 | F21: =F12+SUM(F18:F20) -> 18431 | G21: =G12+SUM(G18:G20) -> 18340 | H21: =H12+SUM(H18:H20) -> 18132 | I21: =I12+SUM(I18:I20) -> 17833 | J21: =J12+SUM(J18:J20) -> 18081 | K21: =K12+SUM(K18:K20) -> 17871 | ... R21: =R12+SUM(R18:R20) -> 18054 | S21: =S12+SUM(S18:S20)-1 -> 17665 | T21: =T12+SUM(T18:T20) -> 17838 | U21: =U12+SUM(U18:U20) -> 17636 | V21: =V12+SUM(V18:V20) -> 17692 | W21: =W12+SUM(W18:W20) -> 17323 | X21: =X12+SUM(X18:X20) -> 17124 | AA21: =SUMIF($C$1:$M$1,AA$1,$C21:$M21) -> 72694 | AB21: =SUMIF($C$1:$M$1,AB$1,$C21:$M21) -> 72386 | AC21: =SUMIF($C$1:$N$1,AC$1,$C21:$N21) -> 71949 | AD21: =SUMIF($C$1:$R$1,AD$1,$C21:$R21) -> 71695 | AE21: =SUMIF($C$1:$V$1,AE$1,$C21:$V21) -> 70831
B22: Business service connectivity | C22: =1946 -> 1946 | D22: 1983 | E22: 2008 | F22: 2119 | G22: 2172 | H22: 2203 | I22: 2215 | J22: 2230 | K22: 2283 | L22: 2292 | M22: 2320 | N22: 2361 | O22: 2407 | P22: 2421 | Q22: 2425 | R22: 2448 | S22: 2496 | T22: 2575 | U22: 2576 | V22: 2590 | W22: 2640 | X22: 2671 | AA22: =SUMIF($C$1:$M$1,AA$1,$C22:$M22) -> 8056 | AB22: =SUMIF($C$1:$M$1,AB$1,$C22:$M22) -> 8820 | AC22: =SUMIF($C$1:$N$1,AC$1,$C22:$N22) -> 9256 | AD22: =SUMIF($C$1:$R$1,AD$1,$C22:$R22) -> 9701 | AE22: =SUMIF($C$1:$V$1,AE$1,$C22:$V22) -> 10237
B23: Total C&P | C23: =C21+C22 -> 19797 | D23: =D21+D22 -> 20215 | E23: =E21+E22 -> 20188 | F23: =F21+F22 -> 20550 | G23: =G21+G22 -> 20512 | H23: =H21+H22 -> 20335 | I23: =I21+I22 -> 20048 | J23: =J21+J22 -> 20311 | ... N23: =N21+N22 -> 20419 | O23: =O21+O22+1 -> 20303 | P23: =P21+P22+1 -> 20272 | Q23: =Q21+Q22-1 -> 20320 | R23: =R21+R22 -> 20502 | S23: =S21+S22 -> 20161 | T23: =T21+T22 -> 20413 | U23: =U21+U22 -> 20212 | V23: =V21+V22 -> 20282 | W23: =W21+W22 -> 19963 | X23: =X21+X22 -> 19795 | AA23: =SUMIF($C$1:$M$1,AA$1,$C23:$M23) -> 80750 | AB23: =SUMIF($C$1:$M$1,AB$1,$C23:$M23) -> 81206 | AC23: =SUMIF($C$1:$N$1,AC$1,$C23:$N23) -> 81205 | AD23: =SUMIF($C$1:$R$1,AD$1,$C23:$R23)-1 -> 81396 | AE23: =SUMIF($C$1:$V$1,AE$1,$C23:$V23) -> 81068
B25: Previous Reporting (Changed after 1Q26, Pre VSNT Spin)
B26: C&P Revenue
B27: Residential Connectivity | C27: =SUM(C28:C30) -> 6875 | D27: =SUM(D28:D30) -> 7067 | E27: =SUM(E28:E30) -> 7244 | F27: =SUM(F28:F30) -> 7466 | G27: =SUM(G28:G30) -> 7567 | H27: =SUM(H28:H30) -> 7620 | I27: =SUM(I28:I30) -> 7766 | J27: =SUM(J28:J30) -> 8013 | ... L27: =SUM(L28:L30) -> 8065 | M27: =SUM(M28:M30)+1 -> 8179 | N27: =SUM(N28:N30) -> 8392 | O27: =SUM(O28:O30) -> 8451 | P27: =SUM(P28:P30) -> 8504 | Q27: =SUM(Q28:Q30) -> 8643 | R27: =SUM(R28:R30) -> 8836 | S27: =SUM(S28:S30) -> 8813 | T27: =SUM(T28:T30) -> 8944 | U27: =SUM(U28:U30) -> 8954 | V27: =SUM(V28:V30) -> 9056 | AA27: =SUMIF($C$1:$M$1,AA$1,$C27:$M27) -> 28652 | AB27: =SUMIF($C$1:$M$1,AB$1,$C27:$M27) -> 30966 | AC27: =SUMIF($C$1:$N$1,AC$1,$C27:$N27) -> 32581 | AD27: =SUMIF($C$1:$R$1,AD$1,$C27:$R27) -> 34434 | AE27: =SUMIF($C$1:$V$1,AE$1,$C27:$V27) -> 35767
B28: Domestic BB | C28: 5600 | D28: 5717 | E28: 5801 | F28: 5861 | G28: 6050 | H28: 6107 | I28: 6135 | J28: 6177 | K28: 6246 | L28: 6270 | M28: 6229 | N28: 6254 | O28: 6446 | P28: 6429 | Q28: 6400 | R28: 6384 | S28: 6558 | T28: 6530 | U28: 6433 | V28: 6316 | AA28: =SUMIF($C$1:$M$1,AA$1,$C28:$M28) -> 22979 | AB28: =SUMIF($C$1:$M$1,AB$1,$C28:$M28) -> 24469 | AC28: =SUMIF($C$1:$N$1,AC$1,$C28:$N28) -> 24999 | AD28: =SUMIF($C$1:$R$1,AD$1,$C28:$R28) -> 25659 | AE28: =SUMIF($C$1:$V$1,AE$1,$C28:$V28) -> 25837
B29: Domestic Wireless | C29: 513 | D29: 556 | E29: 603 | F29: 709 | G29: 677 | H29: 722 | I29: 789 | J29: 883 | K29: 858 | L29: 869 | M29: 917 | N29: 1020 | O29: 972 | P29: 1019 | Q29: 1093 | R29: 1189 | S29: 1123 | T29: 1195 | U29: 1246 | V29: 1403 | AA29: =SUMIF($C$1:$M$1,AA$1,$C29:$M29) -> 2381 | AB29: =SUMIF($C$1:$M$1,AB$1,$C29:$M29) -> 3071 | AC29: =SUMIF($C$1:$N$1,AC$1,$C29:$N29) -> 3664 | AD29: =SUMIF($C$1:$R$1,AD$1,$C29:$R29) -> 4273 | AE29: =SUMIF($C$1:$V$1,AE$1,$C29:$V29) -> 4967
B30: International Connectivity | C30: 762 | D30: 794 | E30: 840 | F30: 896 | G30: 840 | H30: 791 | I30: 842 | J30: 953 | K30: 841 | L30: 926 | M30: 1032 | N30: 1118 | O30: 1033 | P30: 1056 | Q30: 1150 | R30: 1263 | S30: 1132 | T30: 1219 | U30: 1275 | V30: 1337 | AA30: =SUMIF($C$1:$M$1,AA$1,$C30:$M30) -> 3292 | AB30: =SUMIF($C$1:$M$1,AB$1,$C30:$M30) -> 3426 | AC30: =SUMIF($C$1:$N$1,AC$1,$C30:$N30) -> 3917 | AD30: =SUMIF($C$1:$R$1,AD$1,$C30:$R30) -> 4502 | AE30: =SUMIF($C$1:$V$1,AE$1,$C30:$V30) -> 4963
B31: Video | C31: 8191 | D31: 8232 | E31: 8080 | F31: 7936 | G31: 8002 | H31: 7793 | I31: 7428 | J31: 7273 | K31: 7537 | L31: 7542 | M31: 7368 | N31: 7131 | O31: 7104 | P31: 7013 | Q31: 6938 | R31: 6736 | S31: 6718 | T31: 6722 | U31: 6591 | V31: 6356 | AA31: =SUMIF($C$1:$M$1,AA$1,$C31:$M31) -> 32439 | AB31: =SUMIF($C$1:$M$1,AB$1,$C31:$M31) -> 30496 | AC31: =SUMIF($C$1:$N$1,AC$1,$C31:$N31) -> 29578 | AD31: =SUMIF($C$1:$R$1,AD$1,$C31:$R31) -> 27791 | AE31: =SUMIF($C$1:$V$1,AE$1,$C31:$V31) -> 26387
B32: Advertising | C32: 1001 | D32: 1128 | E32: 1097 | F32: 1282 | G32: 1073 | H32: 1112 | I32: 1078 | J32: 1283 | K32: 907 | L32: 993 | M32: 960 | N32: 1109 | O32: 951 | P32: 993 | Q32: 987 | R32: 1158 | S32: 881 | T32: 935 | U32: 864 | V32: 1033 | AA32: =SUMIF($C$1:$M$1,AA$1,$C32:$M32) -> 4508 | AB32: =SUMIF($C$1:$M$1,AB$1,$C32:$M32) -> 4546 | AC32: =SUMIF($C$1:$N$1,AC$1,$C32:$N32) -> 3969 | AD32: =SUMIF($C$1:$R$1,AD$1,$C32:$R32) -> 4089 | AE32: =SUMIF($C$1:$V$1,AE$1,$C32:$V32) -> 3713
B33: Other | C33: 1785 | D33: 1805 | E33: 1759 | F33: 1747 | G33: 1698 | H33: 1607 | I33: 1561 | J33: 1512 | K33: 1482 | L33: 1469 | M33: 1444 | N33: 1426 | O33: 1362 | P33: 1313 | Q33: 1298 | R33: 1286 | S33: 1230 | T33: 1213 | U33: 1192 | V33: 1203 | AA33: =SUMIF($C$1:$M$1,AA$1,$C33:$M33) -> 7096 | AB33: =SUMIF($C$1:$M$1,AB$1,$C33:$M33) -> 6378 | AC33: =SUMIF($C$1:$N$1,AC$1,$C33:$N33) -> 5821 | AD33: =SUMIF($C$1:$R$1,AD$1,$C33:$R33) -> 5259 | AE33: =SUMIF($C$1:$V$1,AE$1,$C33:$V33) -> 4838
B34: Residential C&P | C34: =C27+SUM(C31:C33)-1 -> 17851 | D34: =D27+SUM(D31:D33) -> 18232 | E34: =E27+SUM(E31:E33) -> 18180 | F34: =F27+SUM(F31:F33) -> 18431 | G34: =G27+SUM(G31:G33) -> 18340 | H34: =H27+SUM(H31:H33) -> 18132 | I34: =I27+SUM(I31:I33) -> 17833 | J34: =J27+SUM(J31:J33) -> 18081 | K34: =K27+SUM(K31:K33) -> 17871 | ... Q34: =Q27+SUM(Q31:Q33) -> 17866 | R34: 18016 | S34: =S27+SUM(S31:S33) -> 17642 | T34: =T27+SUM(T31:T33) -> 17814 | U34: =U27+SUM(U31:U33) -> 17601 | V34: =V27+SUM(V31:V33) -> 17648 | AA34: =SUMIF($C$1:$M$1,AA$1,$C34:$M34) -> 72694 | AB34: =SUMIF($C$1:$M$1,AB$1,$C34:$M34) -> 72386 | AC34: =SUMIF($C$1:$N$1,AC$1,$C34:$N34) -> 71949 | AD34: =SUMIF($C$1:$R$1,AD$1,$C34:$R34) -> 71573 | AE34: =SUMIF($C$1:$V$1,AE$1,$C34:$V34) -> 70705
B35: Business service connectivity | C35: =1946 -> 1946 | D35: 1983 | E35: 2008 | F35: 2119 | G35: 2172 | H35: 2203 | I35: 2215 | J35: 2230 | K35: 2283 | L35: 2292 | M35: 2320 | N35: 2361 | O35: 2407 | P35: 2421 | Q35: 2425 | R35: 2448 | S35: 2496 | T35: 2575 | U35: 2576 | V35: 2590 | AA35: =SUMIF($C$1:$M$1,AA$1,$C35:$M35) -> 8056 | AB35: =SUMIF($C$1:$M$1,AB$1,$C35:$M35) -> 8820 | AC35: =SUMIF($C$1:$N$1,AC$1,$C35:$N35) -> 9256 | AD35: =SUMIF($C$1:$R$1,AD$1,$C35:$R35) -> 9701 | AE35: =SUMIF($C$1:$V$1,AE$1,$C35:$V35) -> 10237
B36: Total C&P | C36: =C34+C35 -> 19797 | D36: =D34+D35 -> 20215 | E36: =E34+E35 -> 20188 | F36: =F34+F35 -> 20550 | G36: =G34+G35 -> 20512 | H36: =H34+H35 -> 20335 | I36: =I34+I35 -> 20048 | J36: =J34+J35 -> 20311 | ... V36: =V34+V35 -> 20238 | AA36: =SUMIF($C$1:$M$1,AA$1,$C36:$M36) -> 80750 | AB36: =SUMIF($C$1:$M$1,AB$1,$C36:$M36) -> 81206 | AC36: =SUMIF($C$1:$N$1,AC$1,$C36:$N36) -> 81205 | AD36: =SUMIF($C$1:$R$1,AD$1,$C36:$R36) -> 81274 | AE36: =SUMIF($C$1:$V$1,AE$1,$C36:$V36) -> 80942
B38: Previous Reporting (Changed in 1Q25)
B39: C&P Revenue
B40: Residential Connectivity | C40: =SUM(C41:C43) -> 6875 | D40: =SUM(D41:D43) -> 7067 | E40: =SUM(E41:E43) -> 7244 | F40: =SUM(F41:F43) -> 7466 | G40: =SUM(G41:G43) -> 7567 | H40: =SUM(H41:H43) -> 7620 | I40: =SUM(I41:I43) -> 7766 | J40: =SUM(J41:J43) -> 8013 | ... L40: =SUM(L41:L43) -> 8248 | M40: =SUM(M41:M43)+1 -> 8393 | N40: =SUM(N41:N43) -> 8620 | O40: =SUM(O41:O43) -> 8679 | P40: =SUM(P41:P43) -> 8736 | Q40: =SUM(Q41:Q43) -> 8868 | R40: =SUM(R41:R43) -> 9071 | S40: =SUM(S41:S43) -> 8813 | AA40: =SUMIF($C$1:$M$1,AA$1,$C40:$M40) -> 28652 | AB40: =SUMIF($C$1:$M$1,AB$1,$C40:$M40) -> 30966 | AC40: =SUMIF($C$1:$N$1,AC$1,$C40:$N40) -> 33359 | AD40: =SUMIF($C$1:$R$1,AD$1,$C40:$R40) -> 35354
B41: Domestic BB | C41: 5600 | D41: 5717 | E41: 5801 | F41: 5861 | G41: 6050 | H41: 6107 | I41: 6135 | J41: 6177 | K41: 6343 | L41: 6377 | M41: 6366 | N41: 6403 | O41: 6591 | P41: 6569 | Q41: 6539 | R41: 6528 | S41: 6558 | AA41: =SUMIF($C$1:$M$1,AA$1,$C41:$M41) -> 22979 | AB41: =SUMIF($C$1:$M$1,AB$1,$C41:$M41) -> 24469 | AC41: =SUMIF($C$1:$N$1,AC$1,$C41:$N41) -> 25489 | AD41: =SUMIF($C$1:$R$1,AD$1,$C41:$R41) -> 26227
B42: Domestic Wireless | C42: 513 | D42: 556 | E42: 603 | F42: 709 | G42: 677 | H42: 722 | I42: 789 | J42: 883 | K42: 858 | L42: 869 | M42: 917 | N42: 1020 | O42: 972 | P42: 1019 | Q42: 1093 | R42: 1189 | S42: 1123 | AA42: =SUMIF($C$1:$M$1,AA$1,$C42:$M42) -> 2381 | AB42: =SUMIF($C$1:$M$1,AB$1,$C42:$M42) -> 3071 | AC42: =SUMIF($C$1:$N$1,AC$1,$C42:$N42) -> 3664 | AD42: =SUMIF($C$1:$R$1,AD$1,$C42:$R42) -> 4273
B43: International Connectivity | C43: 762 | D43: 794 | E43: 840 | F43: 896 | G43: 840 | H43: 791 | I43: 842 | J43: 953 | K43: 897 | L43: 1002 | M43: 1109 | N43: 1197 | O43: 1116 | P43: 1148 | Q43: 1236 | R43: 1354 | S43: 1132 | AA43: =SUMIF($C$1:$M$1,AA$1,$C43:$M43) -> 3292 | AB43: =SUMIF($C$1:$M$1,AB$1,$C43:$M43) -> 3426 | AC43: =SUMIF($C$1:$N$1,AC$1,$C43:$N43) -> 4205 | AD43: =SUMIF($C$1:$R$1,AD$1,$C43:$R43) -> 4854
B44: Video | C44: 8191 | D44: 8232 | E44: 8080 | F44: 7936 | G44: 8002 | H44: 7793 | I44: 7428 | J44: 7273 | K44: 7382 | L44: 7358 | M44: 7154 | N44: 6903 | O44: 6876 | P44: 6781 | Q44: 6713 | R44: 6502 | S44: 6718 | AA44: =SUMIF($C$1:$M$1,AA$1,$C44:$M44) -> 32439 | AB44: =SUMIF($C$1:$M$1,AB$1,$C44:$M44) -> 30496 | AC44: =SUMIF($C$1:$N$1,AC$1,$C44:$N44) -> 28797 | AD44: =SUMIF($C$1:$R$1,AD$1,$C44:$R44) -> 26872
B45: Advertising | C45: 1001 | D45: 1128 | E45: 1097 | F45: 1282 | G45: 1073 | H45: 1112 | I45: 1078 | J45: 1283 | K45: 907 | L45: 993 | M45: 960 | N45: 1109 | O45: 951 | P45: 993 | Q45: 987 | R45: 1158 | S45: 881 | AA45: =SUMIF($C$1:$M$1,AA$1,$C45:$M45) -> 4508 | AB45: =SUMIF($C$1:$M$1,AB$1,$C45:$M45) -> 4546 | AC45: =SUMIF($C$1:$N$1,AC$1,$C45:$N45) -> 3969 | AD45: =SUMIF($C$1:$R$1,AD$1,$C45:$R45) -> 4089
B46: Other | C46: 1785 | D46: 1805 | E46: 1759 | F46: 1747 | G46: 1698 | H46: 1607 | I46: 1561 | J46: 1512 | K46: 1482 | L46: 1469 | M46: 1444 | N46: 1426 | O46: 1362 | P46: 1313 | Q46: 1298 | R46: 1286 | S46: 1230 | AA46: =SUMIF($C$1:$M$1,AA$1,$C46:$M46) -> 7096 | AB46: =SUMIF($C$1:$M$1,AB$1,$C46:$M46) -> 6378 | AC46: =SUMIF($C$1:$N$1,AC$1,$C46:$N46) -> 5821 | AD46: =SUMIF($C$1:$R$1,AD$1,$C46:$R46) -> 5259
B47: Residential C&P | C47: =C40+SUM(C44:C46)-1 -> 17851 | D47: =D40+SUM(D44:D46) -> 18232 | E47: =E40+SUM(E44:E46) -> 18180 | F47: =F40+SUM(F44:F46) -> 18431 | G47: =G40+SUM(G44:G46) -> 18340 | H47: =H40+SUM(H44:H46) -> 18132 | I47: =I40+SUM(I44:I46) -> 17833 | J47: =J40+SUM(J44:J46) -> 18081 | K47: =K40+SUM(K44:K46) -> 17869 | ... Q47: =Q40+SUM(Q44:Q46) -> 17866 | R47: 18016 | S47: =S40+SUM(S44:S46) -> 17642 | AA47: =SUMIF($C$1:$M$1,AA$1,$C47:$M47) -> 72694 | AB47: =SUMIF($C$1:$M$1,AB$1,$C47:$M47) -> 72386 | AC47: =SUMIF($C$1:$N$1,AC$1,$C47:$N47) -> 71946 | AD47: =SUMIF($C$1:$R$1,AD$1,$C47:$R47) -> 71573
B48: Business service connectivity | C48: =1946 -> 1946 | D48: 1983 | E48: 2008 | F48: 2119 | G48: 2172 | H48: 2203 | I48: 2215 | J48: 2230 | K48: 2283 | L48: 2292 | M48: 2320 | N48: 2361 | O48: 2407 | P48: 2421 | Q48: 2425 | R48: 2448 | S48: 2496 | AA48: =SUMIF($C$1:$M$1,AA$1,$C48:$M48) -> 8056 | AB48: =SUMIF($C$1:$M$1,AB$1,$C48:$M48) -> 8820 | AC48: =SUMIF($C$1:$N$1,AC$1,$C48:$N48) -> 9256 | AD48: =SUMIF($C$1:$R$1,AD$1,$C48:$R48) -> 9701
B49: Total C&P | C49: =C47+C48 -> 19797 | D49: =D47+D48 -> 20215 | E49: =E47+E48 -> 20188 | F49: =F47+F48 -> 20550 | G49: =G47+G48 -> 20512 | H49: =H47+H48 -> 20335 | I49: =I47+I48 -> 20048 | J49: =J47+J48 -> 20311 | ... S49: =S47+S48 -> 20138 | AA49: =SUMIF($C$1:$M$1,AA$1,$C49:$M49) -> 80750 | AB49: =SUMIF($C$1:$M$1,AB$1,$C49:$M49) -> 81206 | AC49: =SUMIF($C$1:$N$1,AC$1,$C49:$N49) -> 81202 | AD49: =SUMIF($C$1:$R$1,AD$1,$C49:$R49) -> 81274
A51: x | B51: C&P Cost excluding D&A | C51: =C52+C53 -> 12466 | D51: =D52+D53 -> 12537 | E51: =E52+E53 -> 12632 | F51: =F52+F53 -> 13245 | G51: =G52+G53 -> 12667 | H51: =H52+H53 -> 12340 | I51: =I52+I53 -> 12065 | J51: =J52+J53 -> 12962 | ... X51: =X52+X53 -> 11831 | AA51: =SUMIF($C$1:$M$1,AA$1,$C51:$M51) -> 50880 | AB51: =SUMIF($C$1:$M$1,AB$1,$C51:$M51) -> 50034 | AC51: =SUMIF($C$1:$N$1,AC$1,$C51:$N51) -> 48963 | AD51: =SUMIF($C$1:$R$1,AD$1,$C51:$R51) -> 48834 | AE51: =SUMIF($C$1:$V$1,AE$1,$C51:$V51) -> 48982
B52: Residential C&P | C52: 11674 | D52: 11707 | E52: 11805 | F52: 12320 | G52: 11729 | H52: 11399 | I52: 11138 | J52: 12009 | K52: 11108 | L52: 11044 | M52: 11065 | N52: 11782 | O52: 11104 | P52: 10820 | Q52: 11058 | R52: 11651 | S52: 10823 | T52: 10834 | U52: 11152 | V52: 11660 | W52: 10889 | X52: 10676 | AA52: =SUMIF($C$1:$M$1,AA$1,$C52:$M52) -> 47506 | AB52: =SUMIF($C$1:$M$1,AB$1,$C52:$M52) -> 46275 | AC52: =SUMIF($C$1:$N$1,AC$1,$C52:$N52) -> 44999 | AD52: =SUMIF($C$1:$R$1,AD$1,$C52:$R52) -> 44633 | AE52: =SUMIF($C$1:$V$1,AE$1,$C52:$V52)-1 -> 44468
B53: Business C&P | C53: 792 | D53: 830 | E53: 827 | F53: 925 | G53: 938 | H53: 941 | I53: 927 | J53: 953 | K53: 952 | L53: 970 | M53: 985 | N53: 1057 | O53: 1041 | P53: 1041 | Q53: 1034 | R53: 1085 | S53: 1074 | T53: 1131 | U53: 1122 | V53: 1186 | W53: 1163 | X53: 1155 | AA53: =SUMIF($C$1:$M$1,AA$1,$C53:$M53) -> 3374 | AB53: =SUMIF($C$1:$M$1,AB$1,$C53:$M53) -> 3759 | AC53: =SUMIF($C$1:$N$1,AC$1,$C53:$N53) -> 3964 | AD53: =SUMIF($C$1:$R$1,AD$1,$C53:$R53) -> 4201 | AE53: =SUMIF($C$1:$V$1,AE$1,$C53:$V53)-1 -> 4512
B55: Supplemental C&P Cost
B56: Programming | C56: 5199 | D56: 5176 | E56: 5069 | F56: 5098 | G56: 4884 | H56: 4679 | I56: 4464 | J56: 4473 | K56: 4600 | L56: 4579 | M56: 4460 | N56: 4429 | O56: 4405 | P56: 4248 | Q56: 4102 | R56: 4125 | S56: 4107 | T56: 3998 | U56: 3952 | V56: 3950 | W56: 3787 | X56: 3698 | AA56: =SUMIF($C$1:$M$1,AA$1,$C56:$M56) -> 20542 | AB56: =SUMIF($C$1:$M$1,AB$1,$C56:$M56) -> 18500 | AC56: =SUMIF($C$1:$N$1,AC$1,$C56:$N56) -> 18068 | AD56: =SUMIF($C$1:$R$1,AD$1,$C56:$R56)+1 -> 16881 | AE56: =SUMIF($C$1:$V$1,AE$1,$C56:$V56) -> 16007
B57: Marketing & Promotion | C57: 1213 | D57: 1274 | E57: 1309 | F57: 1384 | G57: 1332 | H57: 1296 | I57: 1246 | J57: 1227 | K57: 1202 | L57: 1213 | M57: 1169 | N57: 1135 | O57: 1180 | P57: 1150 | Q57: 1244 | R57: 1250 | S57: 1242 | T57: 1249 | U57: 1332 | V57: 1323 | W57: 1337 | X57: 1311 | AA57: =SUMIF($C$1:$M$1,AA$1,$C57:$M57) -> 5180 | AB57: =SUMIF($C$1:$M$1,AB$1,$C57:$M57) -> 5101 | AC57: =SUMIF($C$1:$N$1,AC$1,$C57:$N57) -> 4719 | AD57: =SUMIF($C$1:$R$1,AD$1,$C57:$R57)-1 -> 4823 | AE57: =SUMIF($C$1:$V$1,AE$1,$C57:$V57)-1 -> 5145
B58: Direct product costs | C58: 1122 | D58: 1152 | E58: 1200 | F58: 1427 | G58: 1339 | H58: 1329 | I58: 1377 | J58: 1553 | K58: 1401 | L58: 1408 | M58: 1554 | N58: 1784 | O58: 1514 | P58: 1515 | Q58: 1676 | R58: 1902 | S58: 1625 | T58: 1829 | U58: 1911 | V58: 2210 | W58: 1962 | X58: 1992 | AA58: =SUMIF($C$1:$M$1,AA$1,$C58:$M58) -> 4901 | AB58: =SUMIF($C$1:$M$1,AB$1,$C58:$M58) -> 5598 | AC58: =SUMIF($C$1:$N$1,AC$1,$C58:$N58) -> 6147 | AD58: =SUMIF($C$1:$R$1,AD$1,$C58:$R58) -> 6607 | AE58: =SUMIF($C$1:$V$1,AE$1,$C58:$V58)+1 -> 7576
B59: Tech & Support | C59: 1855 | D59: 1873 | E59: 1951 | F59: 2003 | G59: 1949 | H59: 1916 | I59: 1911 | J59: 1945 | K59: 1830 | L59: 1828 | M59: 1867 | N59: 1891 | O59: 2012 | P59: 1907 | Q59: 1963 | R59: 1963 | S59: 1935 | T59: 1918 | U59: 2019 | V59: 1981 | W59: 1968 | X59: 1913 | AA59: =SUMIF($C$1:$M$1,AA$1,$C59:$M59) -> 7682 | AB59: =SUMIF($C$1:$M$1,AB$1,$C59:$M59) -> 7721 | AC59: =SUMIF($C$1:$N$1,AC$1,$C59:$N59) -> 7416 | AD59: =SUMIF($C$1:$R$1,AD$1,$C59:$R59) -> 7845 | AE59: =SUMIF($C$1:$V$1,AE$1,$C59:$V59)+1 -> 7854
B60: Customer service | C60: 776 | D60: 759 | E60: 748 | F60: 735 | G60: 736 | H60: 720 | I60: 712 | J60: 702 | K60: 709 | L60: 696 | M60: 692 | N60: 686 | O60: 712 | P60: 685 | Q60: 683 | R60: 662 | S60: 682 | T60: 677 | U60: 707 | V60: 699 | W60: 676 | X60: 671 | AA60: =SUMIF($C$1:$M$1,AA$1,$C60:$M60) -> 3018 | AB60: =SUMIF($C$1:$M$1,AB$1,$C60:$M60) -> 2870 | AC60: =SUMIF($C$1:$N$1,AC$1,$C60:$N60) -> 2783 | AD60: =SUMIF($C$1:$R$1,AD$1,$C60:$R60) -> 2742 | AE60: =SUMIF($C$1:$V$1,AE$1,$C60:$V60) -> 2765
B61: Other | C61: 2301 | D61: 2303 | E61: 2354 | F61: 2598 | G61: 2429 | H61: 2399 | I61: 2354 | J61: 3062 | K61: 2317 | L61: 2290 | M61: 2308 | N61: 2914 | O61: 2322 | P61: 2356 | Q61: 2424 | R61: 2833 | S61: 2305 | T61: 2293 | U61: 2353 | V61: 2683 | W61: 2323 | X61: 2245 | AA61: =SUMIF($C$1:$M$1,AA$1,$C61:$M61) -> 9556 | AB61: =SUMIF($C$1:$M$1,AB$1,$C61:$M61) -> 10244 | AC61: =SUMIF($C$1:$N$1,AC$1,$C61:$N61) -> 9829 | AD61: =SUMIF($C$1:$R$1,AD$1,$C61:$R61) -> 9935 | AE61: =SUMIF($C$1:$V$1,AE$1,$C61:$V61) -> 9634
B62: Total C&P | C62: =SUM(C56:C61) -> 12466 | D62: =SUM(D56:D61) -> 12537 | E62: =SUM(E56:E61) -> 12631 | F62: =SUM(F56:F61) -> 13245 | G62: =SUM(G56:G61) -> 12669 | H62: =SUM(H56:H61) -> 12339 | I62: =SUM(I56:I61) -> 12064 | J62: =SUM(J56:J61) -> 12962 | ... O62: =SUM(O56:O61) -> 12145 | P62: =SUM(P56:P61)+1 -> 11862 | Q62: =SUM(Q56:Q61) -> 12092 | R62: =SUM(R56:R61)+1 -> 12736 | S62: =SUM(S56:S61)+1 -> 11897 | T62: =SUM(T56:T61)+1 -> 11965 | U62: =SUM(U56:U61) -> 12274 | V62: =SUM(V56:V61)-1 -> 12845 | W62: =SUM(W56:W61)-1 -> 12052 | X62: =SUM(X56:X61)+1 -> 11831 | AA62: =SUMIF($C$1:$M$1,AA$1,$C62:$M62) -> 50879 | AB62: =SUMIF($C$1:$M$1,AB$1,$C62:$M62) -> 50034 | AC62: =SUMIF($C$1:$N$1,AC$1,$C62:$N62) -> 48962 | AD62: =SUMIF($C$1:$R$1,AD$1,$C62:$R62) -> 48835 | AE62: =SUMIF($C$1:$V$1,AE$1,$C62:$V62)-1 -> 48980
B64: Adjusted EBITDA | C64: =C65+C66 -> 7331 | D64: =D65+D66 -> 7678 | E64: =E65+E66 -> 7556 | F64: =F65+F66 -> 7306 | G64: =G65+G66 -> 7844 | H64: =H65+H66 -> 7996 | I64: =I65+I66 -> 7983 | J64: =J65+J66 -> 7349 | ... N64: =N65+N66 -> 7579 | O64: =O65+O66+1 -> 8158 | P64: =P65+P66 -> 8410 | Q64: =Q65+Q66 -> 8228 | R64: =R65+R66 -> 7765 | S64: =S65+S66 -> 8264 | T64: =T65+T66 -> 8450 | U64: =U65+U66 -> 7938 | V64: =V65+V66 -> 7437 | W64: =W65+W66 -> 7910 | X64: =X65+X66 -> 7964 | AA64: =SUMIF($C$1:$M$1,AA$1,$C64:$M64) -> 29871 | AB64: =SUMIF($C$1:$M$1,AB$1,$C64:$M64) -> 31172 | AC64: =SUMIF($C$1:$N$1,AC$1,$C64:$N64) -> 32240 | AD64: =SUMIF($C$1:$R$1,AD$1,$C64:$R64) -> 32561 | AE64: =SUMIF($C$1:$V$1,AE$1,$C64:$V64) -> 32089
B65: Residential C&P | C65: 6177 | D65: 6525 | E65: 6375 | F65: 6111 | G65: 6611 | H65: 6733 | I65: 6695 | J65: 6073 | K65: 6762 | L65: 7024 | M65: 6886 | N65: 6276 | O65: 6791 | P65: 7030 | Q65: 6837 | R65: 6402 | S65: 6842 | T65: 7006 | U65: 6484 | V65: 6032 | W65: 6434 | X65: 6448 | AA65: =SUMIF($C$1:$M$1,AA$1,$C65:$M65) -> 25188 | AB65: =SUMIF($C$1:$M$1,AB$1,$C65:$M65) -> 26112 | AC65: =SUMIF($C$1:$N$1,AC$1,$C65:$N65) -> 26948 | AD65: =SUMIF($C$1:$R$1,AD$1,$C65:$R65) -> 27060 | AE65: =SUMIF($C$1:$V$1,AE$1,$C65:$V65) -> 26364
B66: Business service connectivity | C66: 1154 | D66: 1153 | E66: 1181 | F66: 1195 | G66: 1233 | H66: 1263 | I66: 1288 | J66: 1276 | K66: 1332 | L66: 1322 | M66: 1335 | N66: 1303 | O66: 1366 | P66: 1380 | Q66: 1391 | R66: 1363 | S66: 1422 | T66: 1444 | U66: 1454 | V66: 1405 | W66: 1476 | X66: 1516 | AA66: =SUMIF($C$1:$M$1,AA$1,$C66:$M66) -> 4683 | AB66: =SUMIF($C$1:$M$1,AB$1,$C66:$M66) -> 5060 | AC66: =SUMIF($C$1:$N$1,AC$1,$C66:$N66) -> 5292 | AD66: =SUMIF($C$1:$R$1,AD$1,$C66:$R66) -> 5500 | AE66: =SUMIF($C$1:$V$1,AE$1,$C66:$V66) -> 5725
B68: Previous Reporting (Changed after 1Q26, Pre VSNT Spin)
B69: C&P Cost excluding D&A | C69: =C70+C71 -> 12466 | D69: =D70+D71 -> 12537 | E69: =E70+E71 -> 12632 | F69: =F70+F71 -> 13245 | G69: =G70+G71 -> 12667 | H69: =H70+H71 -> 12340 | I69: =I70+I71 -> 12065 | J69: =J70+J71 -> 12962 | ... V69: =V70+V71 -> 12734 | AA69: =SUMIF($C$1:$M$1,AA$1,$C69:$M69) -> 50880 | AB69: =SUMIF($C$1:$M$1,AB$1,$C69:$M69) -> 50034 | AC69: =SUMIF($C$1:$N$1,AC$1,$C69:$N69) -> 48963 | AD69: =SUMIF($C$1:$R$1,AD$1,$C69:$R69) -> 48437 | AE69: =SUMIF($C$1:$V$1,AE$1,$C69:$V69) -> 48565
B70: Residential C&P | C70: 11674 | D70: 11707 | E70: 11805 | F70: 12320 | G70: 11729 | H70: 11399 | I70: 11138 | J70: 12009 | K70: 11108 | L70: 11044 | M70: 11065 | N70: 11782 | O70: 11016 | P70: 10721 | Q70: 10962 | R70: 11537 | S70: 10724 | T70: 10733 | U70: 11047 | V70: 11548 | AA70: =SUMIF($C$1:$M$1,AA$1,$C70:$M70) -> 47506 | AB70: =SUMIF($C$1:$M$1,AB$1,$C70:$M70) -> 46275 | AC70: =SUMIF($C$1:$N$1,AC$1,$C70:$N70) -> 44999 | AD70: =SUMIF($C$1:$R$1,AD$1,$C70:$R70) -> 44236 | AE70: =SUMIF($C$1:$V$1,AE$1,$C70:$V70) -> 44052
B71: Business C&P | C71: 792 | D71: 830 | E71: 827 | F71: 925 | G71: 938 | H71: 941 | I71: 927 | J71: 953 | K71: 952 | L71: 970 | M71: 985 | N71: 1057 | O71: 1041 | P71: 1041 | Q71: 1034 | R71: 1085 | S71: 1074 | T71: 1131 | U71: 1122 | V71: 1186 | AA71: =SUMIF($C$1:$M$1,AA$1,$C71:$M71) -> 3374 | AB71: =SUMIF($C$1:$M$1,AB$1,$C71:$M71) -> 3759 | AC71: =SUMIF($C$1:$N$1,AC$1,$C71:$N71) -> 3964 | AD71: =SUMIF($C$1:$R$1,AD$1,$C71:$R71) -> 4201 | AE71: =SUMIF($C$1:$V$1,AE$1,$C71:$V71) -> 4513
B73: Supplemental C&P Cost
B74: Programming | C74: 5199 | D74: 5176 | E74: 5069 | F74: 5098 | G74: 4884 | H74: 4679 | I74: 4464 | J74: 4473 | K74: 4600 | L74: 4579 | M74: 4460 | N74: 4429 | O74: 4405 | P74: 4248 | Q74: 4102 | R74: 4125 | S74: 4107 | T74: 3998 | U74: 3952 | V74: 3950 | AA74: =SUMIF($C$1:$M$1,AA$1,$C74:$M74) -> 20542 | AB74: =SUMIF($C$1:$M$1,AB$1,$C74:$M74) -> 18500 | AC74: =SUMIF($C$1:$N$1,AC$1,$C74:$N74) -> 18068 | AD74: =SUMIF($C$1:$R$1,AD$1,$C74:$R74) -> 16880 | AE74: =SUMIF($C$1:$V$1,AE$1,$C74:$V74) -> 16007
B75: Marketing & Promotion | C75: 1213 | D75: 1274 | E75: 1309 | F75: 1384 | G75: 1332 | H75: 1296 | I75: 1246 | J75: 1227 | K75: 1202 | L75: 1213 | M75: 1169 | N75: 1135 | O75: 1173 | P75: 1140 | Q75: 1234 | R75: 1225 | S75: 1227 | T75: 1234 | U75: 1318 | V75: 1306 | AA75: =SUMIF($C$1:$M$1,AA$1,$C75:$M75) -> 5180 | AB75: =SUMIF($C$1:$M$1,AB$1,$C75:$M75) -> 5101 | AC75: =SUMIF($C$1:$N$1,AC$1,$C75:$N75) -> 4719 | AD75: =SUMIF($C$1:$R$1,AD$1,$C75:$R75) -> 4772 | AE75: =SUMIF($C$1:$V$1,AE$1,$C75:$V75) -> 5085
B76: Direct product costs | C76: 1122 | D76: 1152 | E76: 1200 | F76: 1427 | G76: 1339 | H76: 1329 | I76: 1377 | J76: 1553 | K76: 1401 | L76: 1408 | M76: 1554 | N76: 1784 | O76: 1514 | P76: 1515 | Q76: 1675 | R76: 1902 | S76: 1625 | T76: 1829 | U76: 1911 | V76: 2210 | AA76: =SUMIF($C$1:$M$1,AA$1,$C76:$M76) -> 4901 | AB76: =SUMIF($C$1:$M$1,AB$1,$C76:$M76) -> 5598 | AC76: =SUMIF($C$1:$N$1,AC$1,$C76:$N76) -> 6147 | AD76: =SUMIF($C$1:$R$1,AD$1,$C76:$R76) -> 6606 | AE76: =SUMIF($C$1:$V$1,AE$1,$C76:$V76) -> 7575
B77: Tech & Support | C77: 1855 | D77: 1873 | E77: 1951 | F77: 2003 | G77: 1949 | H77: 1916 | I77: 1911 | J77: 1945 | K77: 1830 | L77: 1828 | M77: 1867 | N77: 1891 | O77: 1959 | P77: 1845 | Q77: 1908 | R77: 1905 | S77: 1874 | T77: 1855 | U77: 1959 | V77: 1921 | AA77: =SUMIF($C$1:$M$1,AA$1,$C77:$M77) -> 7682 | AB77: =SUMIF($C$1:$M$1,AB$1,$C77:$M77) -> 7721 | AC77: =SUMIF($C$1:$N$1,AC$1,$C77:$N77) -> 7416 | AD77: =SUMIF($C$1:$R$1,AD$1,$C77:$R77) -> 7617 | AE77: =SUMIF($C$1:$V$1,AE$1,$C77:$V77) -> 7609
B78: Customer service | C78: 776 | D78: 759 | E78: 748 | F78: 735 | G78: 736 | H78: 720 | I78: 712 | J78: 702 | K78: 709 | L78: 696 | M78: 692 | N78: 686 | O78: 709 | P78: 682 | Q78: 680 | R78: 660 | S78: 680 | T78: 675 | U78: 704 | V78: 696 | AA78: =SUMIF($C$1:$M$1,AA$1,$C78:$M78) -> 3018 | AB78: =SUMIF($C$1:$M$1,AB$1,$C78:$M78) -> 2870 | AC78: =SUMIF($C$1:$N$1,AC$1,$C78:$N78) -> 2783 | AD78: =SUMIF($C$1:$R$1,AD$1,$C78:$R78) -> 2731 | AE78: =SUMIF($C$1:$V$1,AE$1,$C78:$V78) -> 2755
B79: Other | C79: 2301 | D79: 2303 | E79: 2354 | F79: 2598 | G79: 2429 | H79: 2399 | I79: 2354 | J79: 3062 | K79: 2317 | L79: 2290 | M79: 2308 | N79: 2914 | O79: 2297 | P79: 2331 | Q79: 2395 | R79: 2805 | S79: 2285 | T79: 2272 | U79: 2324 | V79: 2650 | AA79: =SUMIF($C$1:$M$1,AA$1,$C79:$M79) -> 9556 | AB79: =SUMIF($C$1:$M$1,AB$1,$C79:$M79) -> 10244 | AC79: =SUMIF($C$1:$N$1,AC$1,$C79:$N79) -> 9829 | AD79: =SUMIF($C$1:$R$1,AD$1,$C79:$R79) -> 9828 | AE79: =SUMIF($C$1:$V$1,AE$1,$C79:$V79) -> 9531
B80: Total C&P | C80: =SUM(C74:C79) -> 12466 | D80: =SUM(D74:D79) -> 12537 | E80: =SUM(E74:E79) -> 12631 | F80: =SUM(F74:F79) -> 13245 | G80: =SUM(G74:G79) -> 12669 | H80: =SUM(H74:H79) -> 12339 | I80: =SUM(I74:I79) -> 12064 | J80: =SUM(J74:J79) -> 12962 | ... V80: =SUM(V74:V79) -> 12733 | AA80: =SUMIF($C$1:$M$1,AA$1,$C80:$M80) -> 50879 | AB80: =SUMIF($C$1:$M$1,AB$1,$C80:$M80) -> 50034 | AC80: =SUMIF($C$1:$N$1,AC$1,$C80:$N80) -> 48962 | AD80: =SUMIF($C$1:$R$1,AD$1,$C80:$R80) -> 48434 | AE80: =SUMIF($C$1:$V$1,AE$1,$C80:$V80) -> 48562
B82: Adjusted EBITDA | C82: =C83+C84 -> 7331 | D82: =D83+D84 -> 7678 | E82: =E83+E84 -> 7556 | F82: =F83+F84 -> 7306 | G82: =G83+G84 -> 7844 | H82: =H83+H84 -> 7996 | I82: =I83+I84 -> 7983 | J82: =J83+J84 -> 7349 | ... V82: =V83+V84 -> 7504 | AA82: =SUMIF($C$1:$M$1,AA$1,$C82:$M82) -> 29871 | AB82: =SUMIF($C$1:$M$1,AB$1,$C82:$M82) -> 31172 | AC82: =SUMIF($C$1:$N$1,AC$1,$C82:$N82) -> 32240 | AD82: =SUMIF($C$1:$R$1,AD$1,$C82:$R82) -> 32838 | AE82: =SUMIF($C$1:$V$1,AE$1,$C82:$V82) -> 32378
B83: Residential C&P | C83: 6177 | D83: 6525 | E83: 6375 | F83: 6111 | G83: 6611 | H83: 6733 | I83: 6695 | J83: 6073 | K83: 6762 | L83: 7024 | M83: 6886 | N83: 6276 | O83: 6852 | P83: 7103 | Q83: 6904 | R83: 6479 | S83: 6918 | T83: 7082 | U83: 6554 | V83: 6099 | AA83: =SUMIF($C$1:$M$1,AA$1,$C83:$M83) -> 25188 | AB83: =SUMIF($C$1:$M$1,AB$1,$C83:$M83) -> 26112 | AC83: =SUMIF($C$1:$N$1,AC$1,$C83:$N83) -> 26948 | AD83: =SUMIF($C$1:$R$1,AD$1,$C83:$R83) -> 27338 | AE83: =SUMIF($C$1:$V$1,AE$1,$C83:$V83) -> 26653
B84: Business service connectivity | C84: 1154 | D84: 1153 | E84: 1181 | F84: 1195 | G84: 1233 | H84: 1263 | I84: 1288 | J84: 1276 | K84: 1332 | L84: 1322 | M84: 1335 | N84: 1303 | O84: 1366 | P84: 1380 | Q84: 1391 | R84: 1363 | S84: 1422 | T84: 1444 | U84: 1454 | V84: 1405 | AA84: =SUMIF($C$1:$M$1,AA$1,$C84:$M84) -> 4683 | AB84: =SUMIF($C$1:$M$1,AB$1,$C84:$M84) -> 5060 | AC84: =SUMIF($C$1:$N$1,AC$1,$C84:$N84) -> 5292 | AD84: =SUMIF($C$1:$R$1,AD$1,$C84:$R84) -> 5500 | AE84: =SUMIF($C$1:$V$1,AE$1,$C84:$V84) -> 5725
A86: x | B86: C&E Revenue | C86: =C87+C92+C96+C97+C98 -> 8318 | D86: =D87+D92+D96+D97+D98 -> 9317 | E86: =E87+E92+E96+E97+E98 -> 11252 | F86: =F87+F92+F96+F97+F98 -> 10686 | G86: =G87+G92+G96+G97+G98 -> 11340 | H86: =H87+H92+H96+H97+H98 -> 10453 | I86: =I87+I92+I96+I97+I98 -> 10478 | J86: =J87+J92+J96+J97+J98 -> 10880 | ... N86: =N87+N92+N96+N97+N98 -> 11499 | O86: =O87+O92+O96+O97+O98-1 -> 8265 | P86: =P87+P92+P96+P97+P98-1 -> 7994 | Q86: =Q87+Q92+Q96+Q97+Q98+1 -> 10611 | R86: =R87+R92+R96+R97+R98+1 -> 10120 | S86: =S87+S92+S96+S97+S98 -> 8546 | T86: =T87+T92+T96+T97+T98+2 -> 8730 | U86: =U87+U92+U96+U97+U98+1 -> 9898 | V86: =V87+V92+V96+V97+V98+1 -> 10941 | W86: =W87+W92+W96+W97+W98 -> 11941 | X86: =X87+X92+X96+X97+X98+1 -> 10728 | AA86: =SUMIF($C$1:$M$1,AA$1,$C86:$M86) -> 39573 | AB86: =SUMIF($C$1:$M$1,AB$1,$C86:$M86) -> 43151 | AC86: =SUMIF($C$1:$N$1,AC$1,$C86:$N86) -> 43190 | AD86: =SUMIF($C$1:$R$1,AD$1,$C86:$R86) -> 36990 | AE86: =SUMIF($C$1:$V$1,AE$1,$C86:$V86)-1 -> 38114
B87: Total Media | C87: =SUM(C88:C91) -> 6201 | D87: =SUM(D88:D91) -> 6328 | E87: =SUM(E88:E91) -> 7889 | F87: =SUM(F88:F91) -> 6988 | G87: =SUM(G88:G91) -> 7758 | H87: =SUM(H88:H91) -> 6188 | I87: =SUM(I88:I91) -> 6005 | J87: =SUM(J88:J91) -> 6768 | ... W87: =SUM(W88:W91) -> 7280 | X87: =SUM(X88:X91)+1 -> 5691 | AA87: =SUMIF($C$1:$M$1,AA$1,$C87:$M87) -> 27406 | AB87: =SUMIF($C$1:$M$1,AB$1,$C87:$M87) -> 26719 | AC87: =SUMIF($C$1:$N$1,AC$1,$C87:$N87) -> 25355 | AD87: =SUMIF($C$1:$R$1,AD$1,$C87:$R87) -> 20024 | AE87: =SUMIF($C$1:$V$1,AE$1,$C87:$V87) -> 19637
B88: Domestic adverstising | C88: 2072 | D88: 2161 | E88: 3230 | F88: 2714 | G88: 3310 | H88: 2131 | I88: 2089 | J88: 2829 | K88: 2025 | L88: 2027 | M88: 1913 | N88: 2635 | O88: 1530 | P88: 1468 | Q88: 2917 | R88: 2208 | S88: 1468 | T88: 1395 | U88: 1556 | V88: 2294 | W88: 3453 | X88: 2163 | AA88: =SUMIF($C$1:$M$1,AA$1,$C88:$M88) -> 10177 | AB88: =SUMIF($C$1:$M$1,AB$1,$C88:$M88) -> 10359 | AC88: =SUMIF($C$1:$N$1,AC$1,$C88:$N88) -> 8600 | AD88: =SUMIF($C$1:$R$1,AD$1,$C88:$R88)-1 -> 8122 | AE88: =SUMIF($C$1:$V$1,AE$1,$C88:$V88)-1 -> 6712
B89: Domestic distribution | C89: 2403 | D89: 2358 | E89: 2896 | F89: 2423 | G89: 2938 | H89: 2558 | I89: 2497 | J89: 2532 | K89: 2709 | L89: 2615 | M89: 2591 | N89: 2747 | O89: 1499 | P89: 1463 | Q89: 1999 | R89: 1634 | S89: 1667 | T89: 1632 | U89: 1690 | V89: 1876 | W89: 2283 | X89: 1993 | AA89: =SUMIF($C$1:$M$1,AA$1,$C89:$M89) -> 10080 | AB89: =SUMIF($C$1:$M$1,AB$1,$C89:$M89) -> 10525 | AC89: =SUMIF($C$1:$N$1,AC$1,$C89:$N89) -> 10662 | AD89: =SUMIF($C$1:$R$1,AD$1,$C89:$R89) -> 6595 | AE89: =SUMIF($C$1:$V$1,AE$1,$C89:$V89)+1 -> 6866
B90: International networks | C90: 1268 | D90: 1288 | E90: 1221 | F90: 1282 | G90: 995 | H90: 970 | I90: 872 | J90: 893 | K90: 1008 | L90: 1035 | M90: 1019 | N90: 1047 | O90: 1009 | P90: 1090 | Q90: 1059 | R90: 1072 | S90: 1148 | T90: 1254 | U90: 1239 | V90: 1283 | W90: 1291 | X90: 1330 | AA90: =SUMIF($C$1:$M$1,AA$1,$C90:$M90) -> 5059 | AB90: =SUMIF($C$1:$M$1,AB$1,$C90:$M90) -> 3730 | AC90: =SUMIF($C$1:$N$1,AC$1,$C90:$N90) -> 4109 | AD90: =SUMIF($C$1:$R$1,AD$1,$C90:$R90)+1 -> 4231 | AE90: =SUMIF($C$1:$V$1,AE$1,$C90:$V90) -> 4924
B91: Other | C91: 458 | D91: 521 | E91: 542 | F91: 569 | G91: 515 | H91: 529 | I91: 547 | J91: 514 | K91: 410 | L91: 518 | M91: 506 | N91: 550 | O91: 223 | P91: 239 | Q91: 266 | R91: 348 | S91: 244 | T91: 261 | U91: 259 | V91: 371 | W91: 253 | X91: 204 | AA91: =SUMIF($C$1:$M$1,AA$1,$C91:$M91) -> 2090 | AB91: =SUMIF($C$1:$M$1,AB$1,$C91:$M91) -> 2105 | AC91: =SUMIF($C$1:$N$1,AC$1,$C91:$N91) -> 1984 | AD91: =SUMIF($C$1:$R$1,AD$1,$C91:$R91) -> 1076 | AE91: =SUMIF($C$1:$V$1,AE$1,$C91:$V91)+1 -> 1136
B92: Total Studios | C92: =SUM(C93:C95) -> 2525 | D92: =SUM(D93:D95) -> 2406 | E92: =SUM(E93:E95) -> 2540 | F92: =SUM(F93:F95) -> 2606 | G92: =SUM(G93:G95) -> 2907 | H92: =SUM(H93:H95) -> 3117 | I92: =SUM(I93:I95) -> 3296 | J92: =SUM(J93:J95) -> 2937 | ... L92: =SUM(L93:L95) -> 3088 | M92: =SUM(M93:M95)-1 -> 2518 | N92: =SUM(N93:N95) -> 3063 | O92: =SUM(O93:O95) -> 2743 | P92: =SUM(P93:P95) -> 2253 | Q92: =SUM(Q93:Q95) -> 2826 | R92: =SUM(R93:R95) -> 3269 | S92: =SUM(S93:S95) -> 2826 | T92: =SUM(T93:T95) -> 2432 | U92: =SUM(U93:U95) -> 3000 | ... X92: =SUM(X93:X95) -> 3040 | AA92: =SUMIF($C$1:$M$1,AA$1,$C92:$M92) -> 10077 | AB92: =SUMIF($C$1:$M$1,AB$1,$C92:$M92) -> 12257 | AC92: =SUMIF($C$1:$N$1,AC$1,$C92:$N92) -> 11624 | AD92: =SUMIF($C$1:$R$1,AD$1,$C92:$R92)+1 -> 11092 | AE92: =SUMIF($C$1:$V$1,AE$1,$C92:$V92)+1 -> 11286
B93: Content Licensing | C93: 2204 | D93: 1962 | E93: 1960 | F93: 2067 | G93: 2429 | H93: 2269 | I93: 2267 | J93: 2382 | K93: 2344 | L93: 1821 | M93: 1691 | N93: 2375 | O93: 2101 | P93: 1714 | Q93: 1865 | R93: 2383 | S93: 2174 | T93: 1805 | U93: 2035 | V93: 2186 | W93: 2973 | X93: 1799 | AA93: =SUMIF($C$1:$M$1,AA$1,$C93:$M93) -> 8193 | AB93: =SUMIF($C$1:$M$1,AB$1,$C93:$M93) -> 9347 | AC93: =SUMIF($C$1:$N$1,AC$1,$C93:$N93) -> 8231 | AD93: =SUMIF($C$1:$R$1,AD$1,$C93:$R93) -> 8063 | AE93: =SUMIF($C$1:$V$1,AE$1,$C93:$V93)-1 -> 8199
B94: Theatrical | C94: 39 | D94: 198 | E94: 307 | F94: 147 | G94: 168 | H94: 550 | I94: 673 | J94: 216 | K94: 319 | L94: 913 | M94: 504 | N94: 343 | O94: 330 | P94: 237 | Q94: 611 | R94: 515 | S94: 286 | T94: 284 | U94: 639 | V94: 411 | W94: 117 | X94: 972 | AA94: =SUMIF($C$1:$M$1,AA$1,$C94:$M94) -> 691 | AB94: =SUMIF($C$1:$M$1,AB$1,$C94:$M94) -> 1607 | AC94: =SUMIF($C$1:$N$1,AC$1,$C94:$N94) -> 2079 | AD94: =SUMIF($C$1:$R$1,AD$1,$C94:$R94) -> 1693 | AE94: =SUMIF($C$1:$V$1,AE$1,$C94:$V94)+1 -> 1621
B95: Other | C95: 282 | D95: 246 | E95: 273 | F95: 392 | G95: 310 | H95: 298 | I95: 356 | J95: 339 | K95: 292 | L95: 354 | M95: 324 | N95: 345 | O95: 312 | P95: 302 | Q95: 350 | R95: 371 | S95: 366 | T95: 343 | U95: 326 | V95: 430 | W95: 336 | X95: 269 | AA95: =SUMIF($C$1:$M$1,AA$1,$C95:$M95) -> 1193 | AB95: =SUMIF($C$1:$M$1,AB$1,$C95:$M95) -> 1303 | AC95: =SUMIF($C$1:$N$1,AC$1,$C95:$N95) -> 1315 | AD95: =SUMIF($C$1:$R$1,AD$1,$C95:$R95) -> 1335 | AE95: =SUMIF($C$1:$V$1,AE$1,$C95:$V95) -> 1465
B96: Theme parks | C96: 619 | D96: 1095 | E96: 1449 | F96: 1887 | G96: 1560 | H96: 1804 | I96: 2064 | J96: 2114 | K96: 1949 | L96: 2209 | M96: 2418 | N96: 2371 | O96: 1979 | P96: 1975 | Q96: 2289 | R96: 2374 | S96: 1876 | T96: 2349 | U96: 2717 | V96: 2893 | W96: 2331 | X96: 2413 | AA96: =SUMIF($C$1:$M$1,AA$1,$C96:$M96) -> 5050 | AB96: =SUMIF($C$1:$M$1,AB$1,$C96:$M96) -> 7542 | AC96: =SUMIF($C$1:$N$1,AC$1,$C96:$N96) -> 8947 | AD96: =SUMIF($C$1:$R$1,AD$1,$C96:$R96) -> 8617 | AE96: =SUMIF($C$1:$V$1,AE$1,$C96:$V96)+1 -> 9836
B97: Headquarters & Other | C97: 16 | D97: 22 | E97: 28 | F97: 22 | G97: 16 | H97: 8 | I97: 22 | J97: 29 | K97: 19 | L97: 13 | M97: 13 | N97: 19 | O97: 12 | P97: 10 | Q97: 11 | R97: 17 | S97: 11 | T97: 9 | U97: 15 | V97: 11 | W97: 15 | X97: 18 | AA97: =SUMIF($C$1:$M$1,AA$1,$C97:$M97) -> 88 | AB97: =SUMIF($C$1:$M$1,AB$1,$C97:$M97) -> 75 | AC97: =SUMIF($C$1:$N$1,AC$1,$C97:$N97) -> 64 | AD97: =SUMIF($C$1:$R$1,AD$1,$C97:$R97) -> 50 | AE97: =SUMIF($C$1:$V$1,AE$1,$C97:$V97) -> 46
B98: Eliminations | C98: -1043 | D98: -534 | E98: -654 | F98: -817 | G98: -901 | H98: -664 | I98: -909 | J98: -968 | K98: -817 | L98: -631 | M98: -419 | N98: -933 | O98: -729 | P98: -503 | Q98: -757 | R98: -803 | S98: -694 | T98: -604 | U98: -579 | V98: -815 | W98: -1111 | X98: -435 | AA98: =SUMIF($C$1:$M$1,AA$1,$C98:$M98) -> -3048 | AB98: =SUMIF($C$1:$M$1,AB$1,$C98:$M98) -> -3442 | AC98: =SUMIF($C$1:$N$1,AC$1,$C98:$N98) -> -2800 | AD98: =SUMIF($C$1:$R$1,AD$1,$C98:$R98) -> -2792 | AE98: =SUMIF($C$1:$V$1,AE$1,$C98:$V98) -> -2692
B100: Supplemental C&E Revenue
B101: Peacock Revenue | C101: =SUM(C102:C104) -> 91 | D101: =SUM(D102:D104) -> 122 | E101: =SUM(E102:E104) -> 230 | F101: =SUM(F102:F104) -> 335 | G101: =SUM(G102:G104) -> 472 | H101: =SUM(H102:H104) -> 444 | I101: =SUM(I102:I104) -> 506 | J101: =SUM(J102:J104) -> 660 | ... N101: =SUM(N102:N104) -> 1033 | O101: =SUM(O102:O104)+1 -> 1054 | P101: =SUM(P102:P104) -> 1046 | Q101: =SUM(Q102:Q104) -> 1513 | R101: =SUM(R102:R104) -> 1321 | S101: =SUM(S102:S104) -> 1226 | T101: =SUM(T102:T104) -> 1232 | U101: =SUM(U102:U104) -> 1363 | V101: =SUM(V102:V104) -> 1628 | W101: =SUM(W102:W104) -> 2099 | X101: =SUM(X102:X104) -> 1895 | AA101: =SUMIF($C$1:$M$1,AA$1,$C101:$M101) -> 778 | AB101: =SUMIF($C$1:$M$1,AB$1,$C101:$M101) -> 2082 | AC101: =SUMIF($C$1:$N$1,AC$1,$C101:$N101) -> 3368 | AD101: =SUMIF($C$1:$R$1,AD$1,$C101:$R101)-1 -> 4933 | AE101: =SUMIF($C$1:$V$1,AE$1,$C101:$V101)-1 -> 5448
B102: Advertising | C102: 55 | D102: 56 | E102: 109 | F102: 166 | G102: 242 | H102: 207 | I102: 255 | J102: 329 | K102: 304 | L102: 367 | M102: 355 | N102: 422 | O102: 404 | P102: 402 | Q102: 761 | R102: 476 | S102: 414 | T102: 427 | U102: 477 | V102: 564 | W102: 901 | X102: 717 | AA102: =SUMIF($C$1:$M$1,AA$1,$C102:$M102) -> 386 | AB102: =SUMIF($C$1:$M$1,AB$1,$C102:$M102) -> 1033 | AC102: =SUMIF($C$1:$N$1,AC$1,$C102:$N102) -> 1448 | AD102: =SUMIF($C$1:$R$1,AD$1,$C102:$R102)-1 -> 2042 | AE102: =SUMIF($C$1:$V$1,AE$1,$C102:$V102)+1 -> 1883
B103: Distribution | C103: 35 | D103: 61 | E103: 94 | F103: 139 | G103: 192 | H103: 214 | I103: 222 | J103: 278 | K103: 352 | L103: 361 | M103: 420 | N103: 522 | O103: 593 | P103: 581 | Q103: 677 | R103: 773 | S103: 763 | T103: 759 | U103: 843 | V103: 1013 | W103: 1151 | X103: 1155 | AA103: =SUMIF($C$1:$M$1,AA$1,$C103:$M103) -> 329 | AB103: =SUMIF($C$1:$M$1,AB$1,$C103:$M103) -> 906 | AC103: =SUMIF($C$1:$N$1,AC$1,$C103:$N103) -> 1655 | AD103: =SUMIF($C$1:$R$1,AD$1,$C103:$R103) -> 2624 | AE103: =SUMIF($C$1:$V$1,AE$1,$C103:$V103)-1 -> 3377
B104: Other | C104: 1 | D104: 5 | E104: 27 | F104: 30 | G104: 38 | H104: 23 | I104: 29 | J104: 53 | K104: 29 | L104: 92 | M104: 55 | N104: 89 | O104: 56 | P104: 63 | Q104: 75 | R104: 72 | S104: 49 | T104: 46 | U104: 43 | V104: 51 | W104: 47 | X104: 23 | AA104: =SUMIF($C$1:$M$1,AA$1,$C104:$M104) -> 63 | AB104: =SUMIF($C$1:$M$1,AB$1,$C104:$M104) -> 143 | AC104: =SUMIF($C$1:$N$1,AC$1,$C104:$N104) -> 265 | AD104: =SUMIF($C$1:$R$1,AD$1,$C104:$R104) -> 266 | AE104: =SUMIF($C$1:$V$1,AE$1,$C104:$V104) -> 189
B105: Peacock Paid Sub | C105: 3 | D105: 4 | E105: 6 | F105: 9 | G105: 13 | H105: 13 | I105: 16 | J105: 21 | K105: 22 | L105: 24 | M105: 28 | N105: 31 | O105: 34 | P105: 33 | Q105: 36 | R105: 36 | S105: 41 | T105: 41 | U105: 41 | V105: 44 | W105: 46 | X105: 48 | AA105: =SUMIFS($C105:$M105,$C$1:$M$1,AA$1,$C$2:$M$2,4) -> 9 | AB105: =SUMIFS($C105:$M105,$C$1:$M$1,AB$1,$C$2:$M$2,4) -> 21 | AC105: =SUMIFS($C105:$N105,$C$1:$N$1,AC$1,$C$2:$N$2,4) -> 31 | AD105: 36 | AE105: =V105 -> 44
B107: Previous Reporting (Changed after 1Q26, Pre VSNT Spin)
B108: C&E Revenue | C108: =C109+C114+C118+C119+C120 -> 8318 | D108: =D109+D114+D118+D119+D120 -> 9317 | E108: =E109+E114+E118+E119+E120 -> 11252 | F108: =F109+F114+F118+F119+F120 -> 10686 | G108: =G109+G114+G118+G119+G120 -> 11340 | H108: =H109+H114+H118+H119+H120 -> 10453 | I108: =I109+I114+I118+I119+I120 -> 10478 | J108: =J109+J114+J118+J119+J120 -> 10880 | ... R108: =R109+R114+R118+R119+R120 -> 12078 | S108: 10457 | T108: =T109+T114+T118+T119+T120 -> 10624 | U108: =U109+U114+U118+U119+U120 -> 11741 | V108: =V109+V114+V118+V119+V120 -> 12735 | AA108: =SUMIF($C$1:$M$1,AA$1,$C108:$M108) -> 39573 | AB108: =SUMIF($C$1:$M$1,AB$1,$C108:$M108) -> 43151 | AC108: =SUMIF($C$1:$N$1,AC$1,$C108:$N108) -> 43190 | AD108: =SUMIF($C$1:$R$1,AD$1,$C108:$R108) -> 45109 | AE108: =SUMIF($C$1:$V$1,AE$1,$C108:$V108) -> 45557
B109: Total Media | C109: =SUM(C110:C113) -> 6201 | D109: =SUM(D110:D113) -> 6328 | E109: =SUM(E110:E113) -> 7889 | F109: =SUM(F110:F113) -> 6988 | G109: =SUM(G110:G113) -> 7758 | H109: =SUM(H110:H113) -> 6188 | I109: =SUM(I110:I113) -> 6005 | J109: =SUM(J110:J113) -> 6768 | ... Q109: =SUM(Q110:Q113) -> 8231 | R109: 7222 | S109: =SUM(S110:S113) -> 6440 | T109: =SUM(T110:T113) -> 6440 | U109: =SUM(U110:U113) -> 6589 | V109: =SUM(V110:V113) -> 7621 | AA109: =SUMIF($C$1:$M$1,AA$1,$C109:$M109) -> 27406 | AB109: =SUMIF($C$1:$M$1,AB$1,$C109:$M109) -> 26719 | AC109: =SUMIF($C$1:$N$1,AC$1,$C109:$N109) -> 25355 | AD109: =SUMIF($C$1:$R$1,AD$1,$C109:$R109) -> 28149 | AE109: =SUMIF($C$1:$V$1,AE$1,$C109:$V109) -> 27090
B110: Domestic adverstising | C110: 2072 | D110: 2161 | E110: 3230 | F110: 2714 | G110: 3310 | H110: 2131 | I110: 2089 | J110: 2829 | K110: 2025 | L110: 2027 | M110: 1913 | N110: 2635 | O110: 2025 | P110: 1991 | Q110: 3347 | R110: 2645 | S110: 1886 | T110: 1848 | U110: 1964 | V110: 2684 | AA110: =SUMIF($C$1:$M$1,AA$1,$C110:$M110) -> 10177 | AB110: =SUMIF($C$1:$M$1,AB$1,$C110:$M110) -> 10359 | AC110: =SUMIF($C$1:$N$1,AC$1,$C110:$N110) -> 8600 | AD110: =SUMIF($C$1:$R$1,AD$1,$C110:$R110) -> 10008 | AE110: =SUMIF($C$1:$V$1,AE$1,$C110:$V110) -> 8382
B111: Domestic distribution | C111: 2403 | D111: 2358 | E111: 2896 | F111: 2423 | G111: 2938 | H111: 2558 | I111: 2497 | J111: 2532 | K111: 2709 | L111: 2615 | M111: 2591 | N111: 2747 | O111: 2906 | P111: 2764 | Q111: 3272 | R111: 2885 | S111: 2922 | T111: 2812 | U111: 2841 | V111: 3038 | AA111: =SUMIF($C$1:$M$1,AA$1,$C111:$M111) -> 10080 | AB111: =SUMIF($C$1:$M$1,AB$1,$C111:$M111) -> 10525 | AC111: =SUMIF($C$1:$N$1,AC$1,$C111:$N111) -> 10662 | AD111: =SUMIF($C$1:$R$1,AD$1,$C111:$R111) -> 11827 | AE111: =SUMIF($C$1:$V$1,AE$1,$C111:$V111) -> 11613
B112: International networks | C112: 1268 | D112: 1288 | E112: 1221 | F112: 1282 | G112: 995 | H112: 970 | I112: 872 | J112: 893 | K112: 1008 | L112: 1035 | M112: 1019 | N112: 1047 | O112: 1021 | P112: 1102 | Q112: 1070 | R112: 1090 | S112: 1162 | T112: 1266 | U112: 1252 | V112: 1297 | AA112: =SUMIF($C$1:$M$1,AA$1,$C112:$M112) -> 5059 | AB112: =SUMIF($C$1:$M$1,AB$1,$C112:$M112) -> 3730 | AC112: =SUMIF($C$1:$N$1,AC$1,$C112:$N112) -> 4109 | AD112: =SUMIF($C$1:$R$1,AD$1,$C112:$R112) -> 4283 | AE112: =SUMIF($C$1:$V$1,AE$1,$C112:$V112) -> 4977
B113: Other | C113: 458 | D113: 521 | E113: 542 | F113: 569 | G113: 515 | H113: 529 | I113: 547 | J113: 514 | K113: 410 | L113: 518 | M113: 506 | N113: 550 | O113: 420 | P113: 467 | Q113: 542 | R113: 603 | S113: 470 | T113: 514 | U113: 532 | V113: 602 | AA113: =SUMIF($C$1:$M$1,AA$1,$C113:$M113) -> 2090 | AB113: =SUMIF($C$1:$M$1,AB$1,$C113:$M113) -> 2105 | AC113: =SUMIF($C$1:$N$1,AC$1,$C113:$N113) -> 1984 | AD113: =SUMIF($C$1:$R$1,AD$1,$C113:$R113) -> 2032 | AE113: =SUMIF($C$1:$V$1,AE$1,$C113:$V113) -> 2118
...

Sheet CMCSA vs DIS Parks
A1: CMCSA Theme Parks vs. DIS Experiences — quarterly, aligned by calendar quarter
A2: Calendar quarter | B2: 4Q17 | C2: 1Q18 | D2: 2Q18 | E2: 3Q18 | F2: 4Q18 | G2: 1Q19 | H2: 2Q19 | I2: 3Q19 | J2: 4Q19 | K2: 1Q20 | L2: 2Q20 | M2: 3Q20 | N2: 4Q20 | O2: 1Q21 | P2: 2Q21 | Q2: 3Q21 | R2: 4Q21 | S2: 1Q22 | T2: 2Q22 | U2: 3Q22 | V2: 4Q22 | W2: 1Q23 | X2: 2Q23 | Y2: 3Q23 | Z2: 4Q23 | AA2: 1Q24 | AB2: 2Q24 | AC2: 3Q24 | AD2: 4Q24 | AE2: 1Q25 | AF2: 2Q25 | AG2: 3Q25 | AH2: 4Q25 | AI2: 1Q26
A3: DIS fiscal quarter | B3: 1Q18 | C3: 2Q18 | D3: 3Q18 | E3: 4Q18 | F3: 1Q19 | G3: 2Q19 | H3: 3Q19 | I3: 4Q19 | J3: 1Q20 | K3: 2Q20 | L3: 3Q20 | M3: 4Q20 | N3: 1Q21 | O3: 2Q21 | P3: 3Q21 | Q3: 4Q21 | R3: 1Q22 | S3: 2Q22 | T3: 3Q22 | U3: 4Q22 | V3: 1Q23 | W3: 2Q23 | X3: 3Q23 | Y3: 4Q23 | Z3: 1Q24 | AA3: 2Q24 | AB3: 3Q24 | AC3: 4Q24 | AD3: 1Q25 | AE3: 2Q25 | AF3: 3Q25 | AG3: 4Q25 | AH3: 1Q26 | AI3: 2Q26
A5: CMCSA Theme Parks revenue ($mm) | B5: 1461 | C5: 1281 | D5: 1361 | E5: 1528 | F5: 1513 | G5: 1276 | H5: 1464 | I5: 1631 | J5: 1562 | K5: 869 | L5: 87 | M5: 311 | N5: =L41-SUM(K5:M5) -> 579 | O5: ='CMCSA Segments'!C96 -> 619 | P5: ='CMCSA Segments'!D96 -> 1095 | Q5: ='CMCSA Segments'!E96 -> 1449 | R5: ='CMCSA Segments'!F96 -> 1887 | S5: ='CMCSA Segments'!G96 -> 1560 | T5: ='CMCSA Segments'!H96 -> 1804 | U5: ='CMCSA Segments'!I96 -> 2064 | V5: ='CMCSA Segments'!J96 -> 2114 | ... AI5: ='CMCSA Segments'!W96 -> 2331
A6: DIS Theme park admissions ($mm) | B6: =B37-C6 -> 1832 | C6: 1690 | D6: 1834 | E6: =D37-C37 -> 1827 | F6: =E37-G6 -> 1933 | G6: 1768 | H6: 1956 | I6: =G37-F37 -> 1883 | J6: 2067 | K6: 1554 | L6: 34 | M6: =I37-H37 -> 383 | N6: 549 | O6: 597 | P6: 1152 | Q6: =K37-J37 -> 1550 | R6: ='DIS Experience'!B3 -> 2152 | S6: ='DIS Experience'!C3 -> 1973 | T6: ='DIS Experience'!D3 -> 2312 | U6: ='DIS Experience'!E3 -> 2165 | V6: ='DIS Experience'!F3 -> 2641 | W6: ='DIS Experience'!G3 -> 2428 | X6: ='DIS Experience'!H3 -> 2731 | Y6: ='DIS Experience'!I3 -> 2623 | ... AI6: ='DIS Experience'!S3 -> 3092
A7: DIS Parks & Exp merchandise, food and beverage ($mm) | B7: =B38-C7 -> 1495 | C7: 1352 | D7: 1442 | E7: =D38-C38 -> 1385 | F7: =E38-G7 -> 1565 | G7: 1411 | H7: 1515 | I7: =G38-F38 -> 1472 | J7: 1691 | K7: 1276 | L7: 63 | M7: =I38-H38 -> 411 | N7: 553 | O7: 558 | P7: 914 | Q7: =K38-J38 -> 1274 | R7: ='DIS Experience'!B5 -> 1626 | S7: ='DIS Experience'!C5 -> 1515 | T7: ='DIS Experience'!D5 -> 1688 | U7: ='DIS Experience'!E5 -> 1750 | V7: ='DIS Experience'!F5 -> 1980 | W7: ='DIS Experience'!G5 -> 1949 | X7: ='DIS Experience'!H5 -> 1990 | Y7: ='DIS Experience'!I5 -> 1793 | ... AI7: ='DIS Experience'!S5 -> 2199
A8: DIS Experiences revenue ex. merch licensing & retail ($mm) | B8: =B10-B9 -> 5185 | C8: =C10-C9 -> 4923 | D8: =D10-D9 -> 5218 | E8: =E10-E9 -> 5126 | F8: =F10-F9 -> 5524 | G8: =G10-G9 -> 5177 | H8: =H10-H9 -> 5582 | I8: =I10-I9 -> 5421 | ... AI8: =AI10-AI9 -> 8525
A9: memo: DIS Merchandise licensing and retail ($mm) | B9: =B39-C9 -> 1342 | C9: 980 | D9: 918 | E9: =D39-C39 -> 1009 | F9: =E39-G9 -> 1300 | G9: 992 | H9: 993 | I9: =G39-F39 -> 1234 | J9: 1669 | K9: 1017 | L9: 721 | M9: =I39-H39 -> 1314 | N9: 1698 | O9: 1145 | P9: 1137 | Q9: =K39-J39 -> 1261 | R9: ='DIS Experience'!B6 -> 1411 | S9: ='DIS Experience'!C6 -> 1017 | T9: ='DIS Experience'!D6 -> 1026 | U9: ='DIS Experience'!E6 -> 1155 | V9: ='DIS Experience'!F6 -> 1355 | W9: ='DIS Experience'!G6 -> 881 | X9: ='DIS Experience'!H6 -> 1010 | Y9: ='DIS Experience'!I6 -> 1112 | ... AI9: ='DIS Experience'!S6 -> 962
A10: memo: DIS Experiences total revenue ($mm) | B10: =B40-C10 -> 6527 | C10: 5903 | D10: 6136 | E10: =D40-C40 -> 6135 | F10: =E40-G10 -> 6824 | G10: 6169 | H10: 6575 | I10: =G40-F40 -> 6655 | J10: 7580 | K10: 5660 | L10: 1065 | M10: =I40-H40 -> 2733 | N10: 3588 | O10: 3173 | P10: 4341 | Q10: =K40-J40 -> 5450 | R10: ='DIS Experience'!B8 -> 7082 | S10: ='DIS Experience'!C8 -> 6505 | T10: ='DIS Experience'!D8 -> 7245 | U10: ='DIS Experience'!E8 -> 7253 | V10: ='DIS Experience'!F8 -> 8545 | W10: ='DIS Experience'!G8 -> 7646 | X10: ='DIS Experience'!H8 -> 8198 | Y10: ='DIS Experience'!I8 -> 8160 | ... AI10: ='DIS Experience'!S8 -> 9487
A12: Ratio: CMCSA / DIS admissions | B12: =B5/B6 -> 0.79748908 | C12: =C5/C6 -> 0.75798817 | D12: =D5/D6 -> 0.74209378 | E12: =E5/E6 -> 0.83634373 | F12: =F5/F6 -> 0.78272116 | G12: =G5/G6 -> 0.72171946 | H12: =H5/H6 -> 0.74846626 | I12: =I5/I6 -> 0.866171 | ... AI12: =AI5/AI6 -> 0.75388098
A13: Ratio: CMCSA / DIS merch, food & bev | B13: =B5/(B7+B6) -> 0.43913436 | C13: =C5/(C7+C6) -> 0.42110454 | D13: =D5/(D7+D6) -> 0.41544567 | E13: =E5/(E7+E6) -> 0.47571606 | F13: =F5/(F7+F6) -> 0.43253288 | G13: =G5/(G7+G6) -> 0.40138408 | H13: =H5/(H7+H6) -> 0.42178047 | I13: =I5/(I7+I6) -> 0.48614009 | ... AI13: =AI5/(AI7+AI6) -> 0.44055944
A14: Ratio: CMCSA / DIS ex. merch licensing & retail | B14: =B5/B8 -> 0.28177435 | C14: =C5/C8 -> 0.26020719 | D14: =D5/D8 -> 0.2608279 | E14: =E5/E8 -> 0.29808818 | F14: =F5/F8 -> 0.27389573 | G14: =G5/G8 -> 0.24647479 | H14: =H5/H8 -> 0.26227159 | I14: =I5/I8 -> 0.300867 | ... AI14: =AI5/AI8 -> 0.27343109
A16: CMCSA Theme Parks YoY % | F16: =F5/B5-1 -> 0.03559206 | G16: =G5/C5-1 -> -0.0039032006 | H16: =H5/D5-1 -> 0.075679647 | I16: =I5/E5-1 -> 0.067408377 | J16: =J5/F5-1 -> 0.032385988 | K16: =K5/G5-1 -> -0.31896552 | L16: =L5/H5-1 -> -0.94057377 | M16: =M5/I5-1 -> -0.80931944 | ... AI16: =AI5/AE5-1 -> 0.24253731
A17: DIS admissions YoY % | F17: =F6/B6-1 -> 0.055131004 | G17: =G6/C6-1 -> 0.046153846 | H17: =H6/D6-1 -> 0.066521265 | I17: =I6/E6-1 -> 0.030651341 | J17: =J6/F6-1 -> 0.069322297 | K17: =K6/G6-1 -> -0.12104072 | L17: =L6/H6-1 -> -0.98261759 | M17: =M6/I6-1 -> -0.79660117 | ... AI17: =AI6/AE6-1 -> 0.059266872
A18: DIS merch, food & bev YoY % | F18: =F7/B7-1 -> 0.046822742 | G18: =G7/C7-1 -> 0.043639053 | H18: =H7/D7-1 -> 0.050624133 | I18: =I7/E7-1 -> 0.062815884 | J18: =J7/F7-1 -> 0.080511182 | K18: =K7/G7-1 -> -0.095676825 | L18: =L7/H7-1 -> -0.95841584 | M18: =M7/I7-1 -> -0.72078804 | ... AI18: =AI7/AE7-1 -> 0.046644455
A19: DIS ex. merch licensing & retail YoY % | F19: =F8/B8-1 -> 0.065380906 | G19: =G8/C8-1 -> 0.051594556 | H19: =H8/D8-1 -> 0.069758528 | I19: =I8/E8-1 -> 0.057549746 | J19: =J8/F8-1 -> 0.070057929 | K19: =K8/G8-1 -> -0.10314854 | L19: =L8/H8-1 -> -0.93837334 | M19: =M8/I8-1 -> -0.73824018 | ... AI19: =AI8/AE8-1 -> 0.072057344
A21: COVID flag — levels (1 = 1Q20–4Q21) | B21: 0 | C21: 0 | D21: 0 | E21: 0 | F21: 0 | G21: 0 | H21: 0 | I21: 0 | J21: 0 | K21: 1 | L21: 1 | M21: 1 | N21: 1 | O21: 1 | P21: 1 | Q21: 1 | R21: 1 | S21: 0 | T21: 0 | U21: 0 | V21: 0 | W21: 0 | X21: 0 | Y21: 0 | Z21: 0 | AA21: 0 | AB21: 0 | AC21: 0 | AD21: 0 | AE21: 0 | AF21: 0 | AG21: 0 | AH21: 0 | AI21: 0
A22: COVID flag — YoY (1 = 1Q20–4Q22) | B22: 0 | C22: 0 | D22: 0 | E22: 0 | F22: 0 | G22: 0 | H22: 0 | I22: 0 | J22: 0 | K22: 1 | L22: 1 | M22: 1 | N22: 1 | O22: 1 | P22: 1 | Q22: 1 | R22: 1 | S22: 1 | T22: 1 | U22: 1 | V22: 1 | W22: 0 | X22: 0 | Y22: 0 | Z22: 0 | AA22: 0 | AB22: 0 | AC22: 0 | AD22: 0 | AE22: 0 | AF22: 0 | AG22: 0 | AH22: 0 | AI22: 0
A24: Summary — CMCSA Theme Parks vs. DIS line | B24: vs. Admissions | C24: vs. Merch/Food/Bev | D24: vs. Ex-licensing
A25: Average ratio (all quarters) | B25: =AVERAGE(B12:AI12) -> 0.86974315 | C25: =AVERAGE(B13:AI13) -> 0.47211461 | D25: =AVERAGE(B14:AI14) -> 0.28892719
A26: Average ratio (ex-COVID) | B26: {=AVERAGE(_xlfn._xlws.FILTER(B12:AI12,B21:AI21=0))} -> 0.79951988 | C26: {=AVERAGE(_xlfn._xlws.FILTER(B13:AI13,B21:AI21=0))} -> 0.45585821 | D26: {=AVERAGE(_xlfn._xlws.FILTER(B14:AI14,B21:AI21=0))} -> 0.28970376
A27: Correlation — levels, all quarters | B27: =CORREL($B$5:$AI$5,$B$6:$AI$6) -> 0.95329524 | C27: =CORREL($B$5:$AI$5,$B$7:$AI$7) -> 0.94762355 | D27: =CORREL($B$5:$AI$5,$B$8:$AI$8) -> 0.94739907
A28: Correlation — levels, ex-COVID (excl. 1Q20–4Q21) | B28: {=CORREL(_xlfn._xlws.FILTER($B$5:$AI$5,$B$21:$AI$21=0),_xlfn._xlws.FILTER($B$6:$AI$6,$B$21:$AI$21=0))} -> 0.88805702 | C28: {=CORREL(_xlfn._xlws.FILTER($B$5:$AI$5,$B$21:$AI$21=0),_xlfn._xlws.FILTER($B$7:$AI$7,$B$21:$AI$21=0))} -> 0.88640855 | D28: {=CORREL(_xlfn._xlws.FILTER($B$5:$AI$5,$B$21:$AI$21=0),_xlfn._xlws.FILTER($B$8:$AI$8,$B$21:$AI$21=0))} -> 0.88867919
A29: Correlation — YoY %, all quarters | B29: =CORREL($F$16:$AI$16,$F$17:$AI$17) -> 0.96790199 | C29: =CORREL($F$16:$AI$16,$F$18:$AI$18) -> 0.98676567 | D29: =CORREL($F$16:$AI$16,$F$19:$AI$19) -> 0.98947604
A30: Correlation — YoY %, ex-COVID (excl. 1Q20–4Q22) | B30: {=CORREL(_xlfn._xlws.FILTER($F$16:$AI$16,$F$22:$AI$22=0),_xlfn._xlws.FILTER($F$17:$AI$17,$F$22:$AI$22=0))} -> 0.57736032 | C30: {=CORREL(_xlfn._xlws.FILTER($F$16:$AI$16,$F$22:$AI$22=0),_xlfn._xlws.FILTER($F$18:$AI$18,$F$22:$AI$22=0))} -> 0.57183136 | D30: {=CORREL(_xlfn._xlws.FILTER($F$16:$AI$16,$F$22:$AI$22=0),_xlfn._xlws.FILTER($F$19:$AI$19,$F$22:$AI$22=0))} -> 0.65892868
A32: Notes: Columns are calendar quarters; DIS fiscal quarters (FY ends late Sep) are mapped to the calendar quarter they cover (e.g., DIS 1Q FY22 = Oct–Dec 2021 = 4Q21). DIS FY18–FY21 = as-reported Parks, Experiences & Products (DPEP) segment; FY22 onward = recast Experiences segment per 'DIS Experience' tab (recast moved games licensing out of merchandise licensing & retail, so the memo rows have a small definitional seam at 4Q21/1Q22; admissions and merch/food/bev are unaffected). FY18 comparatives are pre-ASC 606. CMCSA 4Q17–4Q20 = as-reported Theme Parks segment; 1Q21 onward linked from 'CMCSA Segments' row 96. DIS fiscal Q1/Q4 are derived from H1/9M/FY filing totals (helper block, rows 36–41).
A35: Helper — DIS DPEP filing-period totals ($mm, as reported; used to derive fiscal Q1 = H1 − Q2 and Q4 = FY − 9M)
B36: H1 FY18 | C36: 9M FY18 | D36: FY2018 | E36: H1 FY19 | F36: 9M FY19 | G36: FY2019 | H36: 9M FY20 | I36: FY2020 | J36: 9M FY21 | K36: FY2021 | L36: CMCSA FY2020
A37: Theme park admissions | B37: 3522 | C37: 5356 | D37: 7183 | E37: 3701 | F37: 5657 | G37: 7540 | H37: 3655 | I37: 4038 | J37: 2298 | K37: 3848
A38: Parks & Exp merchandise, food and beverage | B38: 2847 | C38: 4289 | D38: 5674 | E38: 2976 | F38: 4491 | G38: 5963 | H38: 3030 | I38: 3441 | J38: 2025 | K38: 3299
A39: Merchandise licensing and retail | B39: 2322 | C39: 3240 | D39: 4249 | E39: 2292 | F39: 3285 | G39: 4519 | H39: 3407 | I39: 4721 | J39: 3980 | K39: 5241
A40: DPEP total segment revenue | B40: 12430 | C40: 18566 | D40: 24701 | E40: 12993 | F40: 19570 | G40: 26225 | H40: 14305 | I40: 17038 | J40: 11102 | K40: 16552
A41: CMCSA Theme Parks revenue | L41: 1846
