Workbook
Name _1_0_TV_TBL_DEALS: #REF!
Name a: #REF!
Name clean_spreads: #REF!
Name CommercialExAIGMetrics: [5]Appendix!#REF!
Name IQ_CH: 110000
Name IQ_CQ: 5000
Name IQ_CY: 10000
Name IQ_DAILY: 500000
Name IQ_FH: 100000
Name IQ_FQ: 500
Name IQ_FY: 1000
Name IQ_LTM: 2000
Name IQ_MONTH: 15000
Name IQ_NTM: 6000
Name IQ_WEEK: 50000
Name IQ_YTD: 3000
Name Market_Lookup: OFFSET([6]ParentCompanies!$BI$9,1,0,COUNTA(OFFSET([6]ParentCompanies!$BJ$9,1,0,65000,1)),2)
Name NIELSEN_2009_2010_AVG_TV_RATINGS_TOP_25_DMA_Query: #REF!
Name Nielsen_TV_Ranks_2009_2010_Query: #REF!
Name Options: '[7]Broadcast Stocks MTD'!$W$3:$W$4
Name RadioTVowners: #REF!
Name TV_Station_Revenues_Top_25_DMAs: #REF!

Sheet Starlink Subs & ARPU
B2: SpaceX / Starlink — Connectivity Segment: Subscribers & ARPU
B3: Compiled from SpaceX Form S-1 (filed 5/20/26) and SpaceX Q2 2026 Earnings Release (8/4/26)
B5: Table 1: Annual Subscriber & ARPU History (per S-1 Prospectus)
B6: Period | C6: Period End Date | D6: Starlink Subscribers (millions) | E6: Starlink ARPU ($/month) | F6: Source
B7: FY2023 | C7: 12/31/2023 | D7: 2.3 | E7: 99 | F7: SpaceX Form S-1, Connectivity segment historical data, p. (subscriber/ARPU disclosure)
B8: FY2024 | C8: 12/31/2024 | D8: 4.4 | E8: 81 | F8: SpaceX Form S-1, Connectivity segment historical data, p. (subscriber/ARPU disclosure)
B9: FY2025 | C9: 12/31/2025 | D9: 8.9 | E9: n/d | F9: SpaceX Form S-1 (subscribers); full-year FY2025 average ARPU not separately disclosed in S-1
B10: Q1 2026 | C10: 3/31/2026 | D10: 10.3 | E10: 66 | F10: SpaceX Form S-1, most recent quarter as of filing (5/20/26)
B12: FY24 vs FY23 subscriber growth | D12: =(D8/D7)-1 -> 0.91304348
B13: FY25 vs FY24 subscriber growth | D13: =(D9/D8)-1 -> 1.0227273
B15: Table 2: Quarterly Subscriber & ARPU Data (per Q2 2026 Earnings Release)
B16: Quarter | C16: Period End Date | D16: Starlink Subscribers (millions) | E16: Starlink ARPU ($/month) | F16: Source
B17: Q2 2025 | C17: 6/30/2025 | D17: 6 | E17: 85 | F17: SpaceX Q2 2026 Earnings Release, Connectivity Segment Operating Data (8/4/26), prior-year comp
B18: Q1 2026 | C18: 3/31/2026 | D18: 10.3 | E18: 66 | F18: SpaceX Q2 2026 Earnings Release, Connectivity Segment Operating Data (8/4/26), sequential comp
B19: Q2 2026 | C19: 6/30/2026 | D19: 12 | E19: 66 | F19: SpaceX Q2 2026 Earnings Release, Connectivity Segment Operating Data (8/4/26), current quarter
B21: Q2'26 vs Q1'26 subscriber growth (QoQ) | D21: =(D19/D18)-1 -> 0.16504854
B22: Q2'26 vs Q2'25 subscriber growth (YoY) | D22: =(D19/D17)-1 -> 1
B23: Q2'26 vs Q2'25 ARPU change (YoY) | D23: =(E19/E17)-1 -> -0.22352941
B26: Notes:
B27: 1. Subscriber figures represent paid Starlink subscriptions across Residential, Roam, and Business/Enterprise plans (per S-1), not unique individual customers.
B28: 2. Table 1 (annual) reflects year-end figures as disclosed in the S-1 prospectus filed 5/20/2026, ahead of SpaceX's 6/12/2026 Nasdaq listing (SPCX).
B29: 3. Table 2 (quarterly) reflects the Connectivity Segment Operating and Financial Data table from SpaceX's actual Q2 2026 earnings release (furnished 8/4/2026), which is the first quarter with true sequential + YoY quarterly comps as a reporting company.
B30: 4. Q1 2026 and FY2025 subscriber/ARPU figures are consistent between the S-1 and the Q2 2026 earnings release.
B31: 5. FY2025 full-year average ARPU was not separately broken out in the S-1; only point-in-time ARPU (Q1 2026: $66/mo) and prior year-end figures were given.
B32: 6. Going forward, quarterly subscriber/ARPU disclosure should continue each quarter now that SPCX is a public reporting company.

Sheet Introduction
B3: Starlink economics
B4: Starlink, Viasat and EchoStar global subscribers from 2014-2025, Starlink launch timeline by country and economic launch model for Starlink, including DIY model.
B6: Click here for MI analysis of the data
B8: Click here to contact product support via email
B12: About Kagan
B13: S&P Global Market Intelligence Kagan is the ultimate resource for complete financial intelligence and analytics on the broad and dynamic media & communications industry, including the broadcasting, cable, TV network, motion picture, wireline, wireless, satellite, and internet media sectors. The Kagan suite of products integrates comprehensive data, forecasts, expert analysis and breaking news into an electronic database and analytical tools that are available online and updated around the clock. Kagan combines the more than 40-year heritage of Kagan Research with parent company S&P Global's years of experience in providing essential guidance to companies, governments and individuals worldwide.
B15: About S&P Global Market Intelligence
B16: At S&P Global Market Intelligence, we understand the importance of accurate, deep and insightful information. Our team of experts delivers unrivaled insights and leading data and technology solutions, partnering with customers to expand their perspective, operate with confidence, and make decisions with conviction. S&P Global Market Intelligence is a division of S&P Global (NYSE: SPGI). S&P Global is the world’s foremost provider of credit ratings, benchmarks, analytics and workflow solutions in the global capital, commodity and automotive markets. With every one of our offerings, we help many of the world’s leading organizations navigate the economic landscape so they can plan for tomorrow, today. For more information, visit www.spglobal.com/marketintelligence.
B18: Disclosures
B19: Copyright © 2026 by S&P Global Market Intelligence, a division of S&P Global Inc. These materials have been prepared solely for information purposes based upon information generally available to the public and from sources believed to be reliable. S&P Global Market Intelligence, its affiliates, and third party providers (together, “S&P Global”) do not guarantee the accuracy, completeness or timeliness of any content provided, including model, software or application, and are not responsible for errors or omissions, or for results obtained in connection with use of content. S&P Global disclaims all express or implied warranties, including (but not limited to) any warranties of merchantability or fitness for a particular purpose or use.
B20: S&P Global Market Intelligence’s opinions, quotes and credit-related and other analyses are statements of opinion as of the date they are expressed and not statements of fact or recommendation to purchase, hold, or sell any securities or to make any investment decisions, and do not address the suitability of any security.
B21: S&P Global keeps certain activities of its divisions separate from each other in order to preserve the independence and objectivity of their respective activities. As a result, certain divisions of S&P Global may have information that is not available to other S&P Global divisions.
... B26: www.marketintelligence.spglobal.com

Sheet Satellite subscribers
B3: Satellite broadband subscribers, global, 2014–2025
C4: 2014 | D4: 2015 | H4: 2016 | L4: 2017 | P4: 2018 | T4: 2019 | X4: 2020 | AB4: 2021 | AF4: 2022 | AJ4: 2023 | AN4: 2024 | AR4: 2025
C5: Q4 | D5: Q1 | E5: Q2 | F5: Q3 | G5: Q4 | H5: Q1 | I5: Q2 | J5: Q3 | K5: Q4 | L5: Q1 | M5: Q2 | N5: Q3 | O5: Q4 | P5: Q1 | Q5: Q2 | R5: Q3 | S5: Q4 | T5: Q1 | U5: Q2 | V5: Q3 | W5: Q4 | X5: Q1 | Y5: Q2 | Z5: Q3 | AA5: Q4 | AB5: Q1 | AC5: Q2 | AD5: Q3 | AE5: Q4 | AF5: Q1 | AG5: Q2 | AH5: Q3 | AI5: Q4 | AJ5: Q1 | AK5: Q2 | AL5: Q3 | AM5: Q4 | AN5: Q1 | AO5: Q2 | AP5: Q3 | AQ5: Q4 | AR5: Q1 | AS5: Q2 | AT5: Q3
B6: EchoStar | C6: 977000 | D6: 998000 | E6: 1011500 | F6: 1025000 | G6: 1035000 | H6: 1038000 | I6: 1030000 | J6: 1018000 | K6: 1036000 | L6: 1043000 | M6: 1085000 | N6: 1140000 | O6: 1208000 | P6: 1267000 | Q6: 1298000 | R6: 1332000 | S6: 1361000 | T6: 1388000 | U6: 1415000 | V6: 1437000 | W6: 1477000 | X6: 1516000 | Y6: 1542000 | Z6: 1580000 | AA6: 1564000 | AB6: 1553000 | AC6: 1542000 | AD6: 1510000 | AE6: 1462000 | AF6: 1406000 | AG6: 1346000 | AH6: 1285000 | AI6: 1228000 | AJ6: 1177000 | AK6: 1122000 | AL6: 1063000 | AM6: 1004000 | AN6: 978000 | AO6: 955000 | AP6: 912000 | AQ6: 883000 | AR6: 853000 | AS6: 819000 | AT6: 783000
B7: ViaSat | C7: 675000 | D7: 686000 | E7: 685000 | F7: 687000 | G7: 687000 | H7: 697000 | I7: 696000 | J7: 686000 | K7: 675000 | L7: 659000 | M7: 625000 | N7: 589000 | O7: 577000 | P7: 576000 | Q7: 577000 | R7: 585000 | S7: 584000 | T7: 586000 | U7: 587000 | V7: 587000 | W7: 586000 | X7: 590000 | Y7: 599000 | Z7: 603000 | AA7: 596000 | AB7: 590000 | AC7: 585820.99 | AD7: 573663.88 | AE7: 555428.2 | AF7: 534153.25 | AG7: 530369.81 | AH7: 506333.73 | AI7: 494860.35 | AJ7: 472253.13 | AK7: 436944.48 | AL7: 393250.03 | AM7: 334262.53 | AN7: 294151.03 | AO7: 257000 | AP7: 228000 | AQ7: 205000 | AR7: 189000 | AS7: 172000 | AT7: 157000
B8: Starlink Global subscribers | AB8: 21779 | AC8: 70000 | AD8: 119674 | AE8: 145000 | AF8: 250000 | AG8: 500000 | AH8: 700000 | AI8: 1000000 | AJ8: 1400000 | AK8: 1626707.7 | AL8: 2000000 | AM8: 2300000 | AN8: 2700000 | AO8: 3100000 | AP8: 4000000 | AQ8: 4600000 | AR8: 5100000 | AS8: 6000000 | AT8: 7500000
B9: Total satellite broadband subscribers (global) | C9: 1652000 | D9: 1684000 | E9: 1620000 | F9: 1712000 | G9: 1722000 | H9: 1735000 | I9: 1726000 | J9: 1704000 | K9: 1711000 | L9: 1702000 | M9: 1710000 | N9: 1729000 | O9: 1785000 | P9: 1843000 | Q9: 1875000 | R9: 1917000 | S9: 1945000 | T9: 1974000 | U9: 2002000 | V9: 2024000 | W9: 2063000 | X9: 2106000 | Y9: 2141000 | Z9: 2183000 | AA9: 2160000 | AB9: 2164779 | AC9: 2197821 | AD9: 2203337.9 | AE9: 2162428.2 | AF9: 2190153.3 | AG9: 2376369.8 | AH9: 2491333.7 | AI9: 2722860.3 | AJ9: 3049253.1 | AK9: 3185652.1 | AL9: 3456250 | AM9: 3638262.5 | AN9: 3972151 | AO9: 4312000 | AP9: 5140000 | AQ9: 5688000 | AR9: 6142000 | AS9: 6991000 | AT9: 8440000
B11: Sequential percent change
B12: EchoStar | D12: 0.021494371 | E12: 0.013527054 | F12: 0.013346515 | G12: 0.0097560976 | H12: 0.0028985507 | I12: -0.0077071291 | J12: -0.011650485 | K12: 0.017681729 | L12: 0.0067567568 | M12: 0.040268456 | N12: 0.050691244 | O12: 0.059649123 | P12: 0.04884106 | Q12: 0.024467245 | R12: 0.026194145 | S12: 0.021771772 | T12: 0.019838354 | U12: 0.01945245 | V12: 0.015547703 | W12: 0.027835769 | X12: 0.026404875 | Y12: 0.017150396 | Z12: 0.02464332 | AA12: -0.010126582 | AB12: -0.0070332481 | AC12: -0.007083065 | AD12: -0.02075227 | AE12: -0.031788079 | AF12: -0.038303694 | AG12: -0.042674253 | AH12: -0.045319465 | AI12: -0.044357977 | AJ12: -0.041530945 | AK12: -0.046728972 | AL12: -0.05258467 | AM12: -0.055503293 | AN12: -0.025896414 | AO12: -0.023517382 | AP12: -0.045026178 | AQ12: -0.031798246 | AR12: -0.033975085 | AS12: -0.03985932 | AT12: -0.043956044
B13: ViaSat, Inc. | D13: 0.016296296 | E13: -0.0014577259 | F13: 0.002919708 | G13: 0 | H13: 0.014556041 | I13: -0.0014347202 | J13: -0.014367816 | K13: -0.016034985 | L13: -0.023703704 | M13: -0.051593323 | N13: -0.0576 | O13: -0.020373514 | P13: -0.0017331023 | Q13: 0.0017361111 | R13: 0.013864818 | S13: -0.0017094017 | T13: 0.0034246575 | U13: 0.0017064846 | V13: 0 | W13: -0.0017035775 | X13: 0.0068259386 | Y13: 0.015254237 | Z13: 0.0066777963 | AA13: -0.011608624 | AB13: -0.010067114 | AC13: -0.007083065 | AD13: -0.02075227 | AE13: -0.031788079 | AF13: -0.038303694 | AG13: -0.007083065 | AH13: -0.045319465 | AI13: -0.022659733 | AJ13: -0.045684039 | AK13: -0.074766355 | AL13: -0.1 | AM13: -0.15 | AN13: -0.12 | AO13: -0.12629915 | AP13: -0.11284047 | AQ13: -0.10087719 | AR13: -0.07804878 | AS13: -0.08994709 | AT13: -0.087209302
B14: Starlink Global subscribers | AC14: 2.2141053 | AD14: 0.70962857 | AE14: 0.21162491 | AF14: 0.72413793 | AG14: 1 | AH14: 0.4 | AI14: 0.42857143 | AJ14: 0.4 | AK14: 0.16193404 | AL14: 0.22947722 | AM14: 0.15 | AN14: 0.17391304 | AO14: 0.14814815 | AP14: 0.29032258 | AQ14: 0.15 | AR14: 0.10869565 | AS14: 0.17647059 | AT14: 0.25
B15: Total satellite broadband subscribers (global) | D15: 0.01937046 | E15: -0.038004751 | F15: 0.056790123 | G15: 0.0058411215 | H15: 0.0075493612 | I15: -0.0051873199 | J15: -0.012746234 | K15: 0.0041079812 | L15: -0.0052600818 | M15: 0.0047003525 | N15: 0.011111111 | O15: 0.032388664 | P15: 0.032492997 | Q15: 0.017362995 | R15: 0.0224 | S15: 0.014606155 | T15: 0.014910026 | U15: 0.014184397 | V15: 0.010989011 | W15: 0.019268775 | X15: 0.020843432 | Y15: 0.016619183 | Z15: 0.019617001 | AA15: -0.01053596 | AB15: 0.0022125 | AC15: 0.015263448 | AD15: 0.0025101611 | AE15: -0.018567135 | AF15: 0.012821257 | AG15: 0.085024442 | AH15: 0.04837796 | AI15: 0.092932797 | AJ15: 0.11987129 | AK15: 0.044731941 | AL15: 0.0849427 | AM15: 0.052661842 | AN15: 0.091771414 | AO15: 0.085557919 | AP15: 0.19202226 | AQ15: 0.10661479 | AR15: 0.079817159 | AS15: 0.13822859 | AT15: 0.20726649
B17: Annual percent change
B18: EchoStar | G18: 0.059365404 | H18: 0.04008016 | I18: 0.018289669 | J18: -0.0068292683 | K18: 0.00096618357 | L18: 0.0048169557 | M18: 0.053398058 | N18: 0.11984283 | O18: 0.16602317 | P18: 0.2147651 | Q18: 0.19631336 | R18: 0.16842105 | S18: 0.12665563 | T18: 0.095501184 | U18: 0.090138675 | V18: 0.078828829 | W18: 0.085231447 | X18: 0.09221902 | Y18: 0.08975265 | Z18: 0.099512874 | AA18: 0.058903182 | AB18: 0.024406332 | AC18: 0 | AD18: -0.044303797 | AE18: -0.065217391 | AF18: -0.094655505 | AG18: -0.12710765 | AH18: -0.14900662 | AI18: -0.16005472 | AJ18: -0.1628734 | AK18: -0.16641902 | AL18: -0.17276265 | AM18: -0.18241042 | AN18: -0.16907392 | AO18: -0.14884135 | AP18: -0.1420508 | AQ18: -0.12051793 | AR18: -0.12781186 | AS18: -0.14240838 | AT18: -0.14144737
B19: ViaSat, Inc. | G19: 0.017777778 | H19: 0.016034985 | I19: 0.016058394 | J19: -0.0014556041 | K19: -0.017467249 | L19: -0.054519369 | M19: -0.10201149 | N19: -0.14139942 | O19: -0.14518519 | P19: -0.12594841 | Q19: -0.0768 | R19: -0.0067911715 | S19: 0.012131716 | T19: 0.017361111 | U19: 0.017331023 | V19: 0.0034188034 | W19: 0.0034246575 | X19: 0.0068259386 | Y19: 0.02044293 | Z19: 0.02725724 | AA19: 0.017064846 | AB19: 0 | AC19: -0.022001683 | AD19: -0.048650288 | AE19: -0.068073484 | AF19: -0.094655505 | AG19: -0.094655505 | AH19: -0.11736863 | AI19: -0.10904714 | AJ19: -0.11588458 | AK19: -0.17615129 | AL19: -0.22333827 | AM19: -0.3245316 | AN19: -0.37713271 | AO19: -0.41182459 | AP19: -0.4202162 | AQ19: -0.3867096 | AR19: -0.35747292 | AS19: -0.3307393 | AT19: -0.31140351
B20: Starlink Global subscribers | AF20: 10.478948 | AG20: 6.1428571 | AH20: 4.8492237 | AI20: 5.8965517 | AJ20: 4.6 | AK20: 2.2534153 | AL20: 1.8571429 | AM20: 1.3 | AN20: 0.92857143 | AO20: 0.90568968 | AP20: 1 | AQ20: 1 | AR20: 0.88888889 | AS20: 0.93548387 | AT20: 0.875
B21: Total satellite broadband subscribers (global) | G21: 0.042372881 | H21: 0.030285036 | I21: 0.065432099 | J21: -0.0046728972 | K21: -0.006387921 | L21: -0.019020173 | M21: -0.0092699884 | N21: 0.014671362 | O21: 0.043249562 | P21: 0.082843713 | Q21: 0.096491228 | R21: 0.10873337 | S21: 0.089635854 | T21: 0.071079761 | U21: 0.067733333 | V21: 0.05581638 | W21: 0.06066838 | X21: 0.066869301 | Y21: 0.069430569 | Z21: 0.078557312 | AA21: 0.047018905 | AB21: 0.027910256 | AC21: 0.026539464 | AD21: 0.0093164802 | AE21: 0.0011241683 | AF21: 0.011721405 | AG21: 0.081239017 | AH21: 0.13070889 | AI21: 0.25916798 | AJ21: 0.3922556 | AK21: 0.34055404 | AL21: 0.38730913 | AM21: 0.33619138 | AN21: 0.30266359 | AO21: 0.35356901 | AP21: 0.48716093 | AQ21: 0.56338361 | AR21: 0.54626548 | AS21: 0.62128942 | AT21: 0.64202335
B23: Sources: Industry data; S&P Global Market Intelligence Kagan estimates.
B24: © 2026 S&P Global.

Sheet Starlink launches
B3: Starlink satellite broadband market launches, 2020–2025
C4: Q4'20 | D4: Q1'21 | E4: Q2'21 | F4: Q3'21 | G4: Q4'21 | H4: Q1'22 | I4: Q2'22 | J4: Q3'22 | K4: Q4'22 | L4: Q1'23 | M4: Q2'23 | N4: Q3'23 | O4: Q4'23 | P4: Q1'24 | Q4: Q2'24 | R4: Q3'24 | S4: Q4'24 | T4: Q1'25 | U4: Q2'25 | V4: Q3'25
B5: Starlink debut by country | C5: USA | D5: USA | E5: AU | F5: Ireland | G5: Sweden | H5: Spain | I5: Romania | J5: Luxembourg | K5: Japan | L5: Peru | M5: El Salvador | N5: Cyprus | O5: Zambia | P5: Mongolia | Q5: Albania | R5: Tonga | S5: Samoa | T5: Liberia | U5: Guyana | V5: Sri Lanka
D6: Canada | E6: NZ | F6: Denmark | G6: Mexico | H6: Slovakia | I6: Greece | J6: Dom. Republic | K6: Jamaica | L6: Nigeria | M6: Panama | N6: Guatemala | O6: Georgia | P6: Argentina | Q6: Micronesia | R6: South Sudan | S6: Vanuatu | T6: Tuvalu | U6: Jordan | V6: Chad
D7: UK | E7: France | F7: Portugal | G7: Croatia | H7: Slovenia | I7: Latvia | J7: Moldova | K7: Finland | L7: Colombia | M7: Mozambique | N7: Kenya | O7: Benin | Q7: Uruguay | R7: Botswana | S7: Qatar | T7: Bhutan | U7: St. Vincent and the Grenadines | V7: Somalia
D8: Germany | E8: Austria | F8: Switzerland | G8: Lithuania | H8: Tonga | I8: Hungary | J8: Estonia | L8: Iceland | M8: Trinidad and Tobago | N8: Malaysia | O8: Maldives | Q8: Indonesia | R8: Ghana | S8: Cape Verde | T8: Niger | U8: Bahrain | V8: Israel
E9: Netherlands | F9: Chile | H9: Brazil | I9: North Macedonia | J9: Colombia | L9: Rwanda | N9: Malawi | O9: Costa Rica | Q9: Fiji | R9: Solomon Islands | S9: Timor Leste | T9: Kiribati | U9: Bangladesh | V9: Antigua and Barbuda
E10: Belgium | F10: Poland | H10: Bulgaria | J10: Norway | L10: Philippines | N10: Bahamas | O10: Honduras | Q10: Sierra Leone | R10: Zimbabwe | S10: Nauru | T10: Armenia | U10: Democratic Republic of Congo | V10: Kazakhstan
F11: Italy | H11: Ukraine | J11: Malta | L11: Haiti | O11: Eswatini | Q11: Madagascar | R11: Yemen | S11: Kosovo | T11: Oman | U11: Dominica | V11: Liechtenstein
F12: Czech Republic | J12: Iran | L12: Ecuador | O12: Paraguay | T12: Azerbaijan | U12: Marshall Islands
U13: Guinea-Bissau
U14: Lesotho
B19: Sources: Industry data.
B20: © 2026 S&P Global.

Sheet Starlink economics
B3: Starlink economics
C4: Revenue only | D4: Revenue less overhead
B5: Starlink global subscribers, YE 2025e | C5: 9200000 | D5: 9200000
B6: Est. Starlink subscribers YE 2026e | C6: 12880000 | D6: 12880000
B7: Annual growth rate | C7: 0.4 | D7: 0.4
B8: Average subs 2026 | C8: 11040000 | D8: 11040000
B9: Estimated ARPU per month | C9: 80 | D9: 80
B10: TTM recurring revenue | C10: 10598400000 | D10: 10598400000
B12: Cost per rocket launch | C12: 10000000 | D12: 10000000
B13: Rocket launches per month | C13: 11 | D13: 7.5
B14: Annualized Starship launches full year 2026 | C14: 132 | D14: 90
B15: Starship cost next 12 months | C15: 1320000000 | D15: 900000000
B17: Satellites in each Starship | C17: 50 | D17: 50
B18: Total satellites in next 12 months | C18: 7700 | D18: 5400
... B22: New satellite launch cost | C22: 10560000000 | D22: 7380000000
B23: Other overhead as percentage revenue | D23: 0.3
B24: Other overhead | D24: 3179520000
B25: Net revenue | D25: 7418880000
B27: Check (negative numbers imply too many satellites) | C27: 38400000 | D27: 38880000
B29: Current Starlink satellites in orbit, Feb. 2026 | C29: 9347
B30: Subscribers per satellite, YE 2025 | C30: 984.27303
B32: US subscribers | C32: 2250000
B33: US subscribers as percentage total | C33: 0.24456522
B36: Sources: Industry data; S&P Global Market Intelligence Kagan estimates.
B37: © 2026 S&P Global.

Sheet EchoStar (Hughes)
B2: EchoStar Corporation — Hughes / HughesNet Broadband Subscribers
B3: Compiled from EchoStar quarterly earnings releases and Form 10-Qs/10-Ks, Q1 2020 - Q2 2026
B5: Quarterly Broadband Subscribers (thousands) — U.S. / Latin America / Total
B6: Quarter | C6: Period End | D6: US Subs (000s) | E6: LatAm Subs (000s) | F6: Total Subs (000s) | G6: Net Adds (000s) | H6: Source / Note
B7: Q1 2020 | C7: 3/31/2020 | D7: n/d | E7: 267 | F7: 1516 | H7: EchoStar Q1 2020 earnings release
B8: Q2 2020 | C8: 6/30/2020 | D8: 1221 | E8: 321 | F8: 1542 | G8: =F8-F7 -> 26 | H8: EchoStar Q2 2020 earnings release / 10-Q
B9: Q3 2020 | C9: 9/30/2020 | D9: 1216 | E9: 364 | F9: 1580 | G9: =F9-F8 -> 38 | H9: EchoStar Q3 2020 earnings release / 10-Q
B10: Q4 2020 | C10: 12/31/2020 | D10: 1189 | E10: 375 | F10: 1564 | G10: =F10-F9 -> -16 | H10: Backed out from Q1 2021 release (US -25k, LatAm +14k QoQ)
B11: Q1 2021 | C11: 3/31/2021 | D11: 1164 | E11: 389 | F11: 1553 | G11: =F11-F10 -> -11 | H11: EchoStar Q1 2021 earnings release
B12: Q2 2021 | C12: 6/30/2021 | D12: n/d | E12: n/d | F12: 1542 | G12: =F12-F11 -> -11 | H12: Backed out from Q3 2021 release (total -32k QoQ)
B13: Q3 2021 | C13: 9/30/2021 | D13: 1120 | E13: 390 | F13: 1510 | G13: =F13-F12 -> -32 | H13: EchoStar Q3 2021 earnings release / 10-Q
B14: Q4 2021 | C14: 12/31/2021 | D14: 1090 | E14: 372 | F14: 1462 | G14: =F14-F13 -> -48 | H14: EchoStar Q4 2021 earnings release
B15: Q1 2022 | C15: 3/31/2022 | D15: 1055 | E15: 351 | F15: 1406 | G15: =F15-F14 -> -56 | H15: EchoStar Q1 2022 earnings release
B16: Q2 2022 | C16: 6/30/2022 | D16: n/d | E16: n/d | F16: 1346 | G16: =F16-F15 -> -60 | H16: EchoStar Q2 2022 earnings release
B17: Q3 2022 | C17: 9/30/2022 | D17: n/d | E17: n/d | F17: 1285 | G17: =F17-F16 -> -61 | H17: EchoStar Q3 2022 earnings release
B18: Q4 2022 | C18: 12/31/2022 | D18: n/d | E18: n/d | F18: 1228 | G18: =F18-F17 -> -57 | H18: EchoStar Q4 2022 earnings release
B19: Q1 2023 | C19: 3/31/2023 | D19: n/d | E19: n/d | F19: 1177 | G19: =F19-F18 -> -51 | H19: EchoStar Q1 2023 earnings release
B20: Q2 2023 | C20: 6/30/2023 | D20: 846 | E20: 276 | F20: 1122 | G20: =F20-F19 -> -55 | H20: EchoStar Q2 2023 earnings release / 10-Q
B21: Q3 2023 | C21: 9/30/2023 | D21: 801 | E21: 262 | F21: 1063 | G21: =F21-F20 -> -59 | H21: EchoStar Q3 2023 earnings release / 10-Q
B22: Q4 2023 | C22: 12/31/2023 | D22: n/d | E22: n/d | F22: 1004 | G22: =F22-F21 -> -59 | H22: Backed out from Q4 2024 release (Q4'23 declined 59k from Q3'23's 1,063k)
B23: Q1 2024 | C23: 3/31/2024 | D23: n/d | E23: n/d | F23: 978 | G23: =F23-F22 -> -26 | H23: EchoStar Q1 2024 earnings release
B24: Q2 2024 | C24: 6/30/2024 | D24: n/d | E24: n/d | F24: 955 | G24: =F24-F23 -> -23 | H24: EchoStar Q2 2024 earnings call transcript
B25: Q3 2024 | C25: 9/30/2024 | D25: n/d | E25: n/d | F25: 912 | G25: =F25-F24 -> -43 | H25: Backed out from Q4 2024 release (Q4'24 declined 29k from Q3'24)
B26: Q4 2024 | C26: 12/31/2024 | D26: n/d | E26: n/d | F26: 883 | G26: =F26-F25 -> -29 | H26: EchoStar Q4 2024 / FY2024 earnings release & 10-K
B27: Q1 2025 | C27: 3/31/2025 | D27: n/d | E27: n/d | F27: 853 | G27: =F27-F26 -> -30 | H27: EchoStar Q1 2025 earnings release
B28: Q2 2025 | C28: 6/30/2025 | D28: n/d | E28: n/d | F28: 819 | G28: =F28-F27 -> -34 | H28: EchoStar Q2 2025 earnings release
B29: Q3 2025 | C29: 9/30/2025 | D29: n/d | E29: n/d | F29: 783 | G29: =F29-F28 -> -36 | H29: Backed out from Q4 2025 release (Q4'25 declined 44k from Q3'25)
B30: Q4 2025 | C30: 12/31/2025 | D30: n/d | E30: n/d | F30: 739 | G30: =F30-F29 -> -44 | H30: EchoStar Q4 2025 / FY2025 earnings release
B31: Q1 2026 | C31: 3/31/2026 | D31: n/d | E31: n/d | F31: 681 | G31: =F31-F30 -> -58 | H31: EchoStar Q1 2026 earnings release
B32: Q2 2026 | C32: 6/30/2026 | D32: n/d | E32: n/d | F32: 622 | G32: =F32-F31 -> -59 | H32: EchoStar Q2 2026 earnings release
B34: Total decline, Q1 2020 to Q2 2026 (subs, 000s) | F34: =F32-F7 -> -894
B35: % decline, Q1 2020 to Q2 2026 | F35: =(F32/F7)-1 -> -0.58970976
B38: Notes:
B39: 1. "Broadband subscribers" (branded HughesNet) include U.S. and Latin America consumer, retail, wholesale, and SME channels.
B40: 2. EchoStar reports total broadband subscribers every quarter without exception; the US/LatAm split was disclosed through 2023 but has not been broken out separately in releases since (total-only from 2024 onward).
B41: 3. Rows shaded yellow are back-calculated from adjacent quarters' disclosed net-subscriber-change commentary (e.g., "declined 29,000 from Q3"), not directly reported point-in-time figures — shown for time-series continuity, cited to the disclosing release.
B42: 4. EchoStar does not disclose a blended broadband ARPU figure in the same explicit $/month terms as SpaceX/Starlink; commentary references ARPU direction qualitatively in some quarters but doesn't provide a hard number.
B43: 5. Subscriber base has fallen from ~1.58 million (Q3 2020 peak) to 622,000 (Q2 2026), a decline of roughly 61%, coinciding with Starlink's consumer market expansion.

Sheet Viasat
B2: Viasat, Inc. — U.S. Fixed Broadband Subscribers & ARPU
B3: Compiled from Viasat Form 10-K filings and earnings releases (fiscal year ends March 31)
B5: Disclosed Subscriber & ARPU Data Points
B6: Period | C6: Period End Date | D6: US Subscribers | E6: ARPU ($/month) | F6: Source | G6: Note
B7: FY2012 | C7: 3/30/2012 | D7: 385000 | E7: n/d | F7: Viasat Form 10-K, FY2012 | G7: Retail + wholesale broadband subscribers (Exede/WildBlue brands)
B8: FY2019 | C8: 3/31/2019 | D8: 586000 | E8: n/d | F8: Viasat Form 10-K, FY2019
B9: Q2 FY2021 (Cal. Sept 2020) | C9: 9/30/2020 | D9: 603000 | E9: n/d | F9: Third-party estimate (CyberNews / TipRanks), not a primary Viasat disclosure | G9: Flagged: not sourced directly from a Viasat filing; included for approximate time-series continuity only
B10: FY2020 | C10: 3/31/2020 | D10: 590000 | E10: 93.06 | F10: Viasat Form 10-K, FY2020 | G10: Excludes subscribers retained under FCC Keep Americans Connected Pledge
B11: FY2021 | C11: 3/31/2021 | D11: n/d | E11: n/d | F11: Not disclosed | G11: Viasat's 10-K Item 1 Business section stopped stating a hard U.S. subscriber count after FY2020
B12: FY2022 | C12: 3/31/2022 | D12: n/d | E12: n/d | F12: Not disclosed | G12: No subscriber count found in FY2022 10-K Item 1 Business section
B13: FY2023 | C13: 3/31/2023 | D13: n/d | E13: n/d | F13: Not disclosed | G13: Per Light Reading (Nov 2023): "Viasat has not released residential subscriber figures for several quarters"
B14: FY2024 | C14: 3/31/2024 | D14: n/d | E14: n/d | F14: Not disclosed | G14: No subscriber count found in FY2024 10-K Item 1 Business section
B15: FY2025 | C15: 3/31/2025 | D15: 189000 | E15: 115 | F15: Viasat Form 10-K, FY2025 | G15: Disclosure resumed; "U.S. fixed broadband business had approximately 189,000 subscribers"
B16: Q3 FY2026 (Cal. Dec 2025) | C16: 46022 | D16: 143000 | E16: n/d | F16: Viasat quarterly disclosure, calendar Q4 2025 (per company reporting) | G16: Calendar Q4 2025 U.S. fixed broadband subscriber count
B17: FY2026 | C17: 3/31/2026 | D17: 130000 | E17: 113 | F17: Viasat Form 10-K, FY2026 | G17: "U.S. fixed broadband business had approximately 130,000 subscribers"
B19: FY2020 to FY2025 decline (subs) | D19: =D10-D15 -> 401000
B20: FY2020 to FY2025 % decline | D20: =(D15/D10)-1 -> -0.67966102
B21: FY2025 to FY2026 % decline | D21: =(D17/D15)-1 -> -0.31216931
B24: Notes:
B25: 1. Viasat's fiscal year ends March 31 (FY2026 = year ended 3/31/2026), unlike SpaceX and EchoStar which report on a calendar-year basis.
B26: 2. Unlike EchoStar and SpaceX/Starlink, Viasat does NOT disclose a hard subscriber count every quarter or even every year. Between FY2021 and FY2024 (four consecutive fiscal years), no specific subscriber figure could be located in Viasat's 10-K Item 1 Business disclosures — shaded rows above.
B27: 3. Viasat's shareholder letters during the gap years referenced subscriber trends qualitatively (e.g., "US fixed broadband subscribers continued to decrease," "approximately flat subscriber growth") without a specific headline number.
B28: 4. Disclosure of a specific subscriber count resumed in the FY2025 10-K (189,000) and continued in FY2026 (130,000).
B29: 5. The Sept-2020 (603,000) figure is a third-party estimate reported by CyberNews/TipRanks, not sourced to a Viasat filing — included only to illustrate the scale of decline commonly cited in the press, and should be treated with lower confidence than the 10-K-sourced figures.
B30: 6. Viasat's fixed broadband ARPU has risen even as subscriber count has fallen sharply (mix-shift toward higher-value plans), from $93/month in FY2020 to $113-115/month in FY2025-26.

Sheet Summary
B1: Global Satellite Broadband Subscribers by Carrier
B2: Year-End (Q4) Snapshot, in millions of subscribers
B4: Carrier | C4: 2020 | D4: 2021 | E4: 2022 | F4: 2023 | G4: 2024 | H4: 2025 | I4: Q2'26*
B5: EchoStar | C5: ='Satellite subscribers'!AA6/1000000 -> 1.564 | D5: ='Satellite subscribers'!AE6/1000000 -> 1.462 | E5: ='Satellite subscribers'!AI6/1000000 -> 1.228 | F5: ='Satellite subscribers'!AM6/1000000 -> 1.004 | G5: ='Satellite subscribers'!AQ6/1000000 -> 0.883 | H5: ='EchoStar (Hughes)'!F30/1000 -> 0.739 | I5: ='EchoStar (Hughes)'!F32/1000 -> 0.622
B6: ViaSat | C6: ='Satellite subscribers'!AA7/1000000 -> 0.596 | D6: ='Satellite subscribers'!AE7/1000000 -> 0.5554282 | E6: ='Satellite subscribers'!AI7/1000000 -> 0.49486035 | F6: ='Satellite subscribers'!AM7/1000000 -> 0.33426253 | G6: ='Satellite subscribers'!AQ7/1000000 -> 0.205 | H6: =Viasat!D16/1000000 -> 0.143 | I6: =Viasat!D17/1000000*(Viasat!D17/Viasat!D16) -> 0.11818182
B7: Starlink | C7: ='Satellite subscribers'!AA8/1000000 -> 0 | D7: ='Satellite subscribers'!AE8/1000000 -> 0.145 | E7: ='Satellite subscribers'!AI8/1000000 -> 1 | F7: ='Starlink Subs & ARPU'!D7 -> 2.3 | G7: ='Starlink Subs & ARPU'!D8 -> 4.4 | H7: ='Starlink Subs & ARPU'!D9 -> 8.9 | I7: ='Starlink Subs & ARPU'!D19 -> 12
B8: Total | C8: =SUM(C5:C7) -> 2.16 | D8: =SUM(D5:D7) -> 2.1624282 | E8: =SUM(E5:E7) -> 2.7228603 | F8: =SUM(F5:F7) -> 3.6382625 | G8: =SUM(G5:G7) -> 5.488 | H8: =SUM(H5:H7) -> 9.782 | I8: =SUM(I5:I7) -> 12.740182
B10: * Q2'26: EchoStar and Starlink are actual reported figures; ViaSat is estimated by applying the Q4'25→Q1'26 (FY2026) QoQ decline rate forward one quarter, since ViaSat has not yet reported a calendar Q2 2026 figure.
B11: Sources: EchoStar — actual (EchoStar (Hughes) tab) 2023 onward, S&P Kagan estimate 2020-2022 ('Satellite subscribers' tab). ViaSat — actual company-disclosed figures (Viasat tab) for Q1 2020, Q3 2020 (third-party est.), and Q4 2025 onward; S&P Kagan estimate for all other quarters. Starlink — S&P Kagan estimate 2020-2022; actual SpaceX data (Starlink Subs & ARPU tab) 2023 onward.
