Workbook

Sheet README
A1: Hotchkis & Wiley — Quant RA Excel Practice
A2: Built for Andrew · Live screen-share prep · Data is synthetic
A4: HOW TO USE
A5: 1. | B5: Work tab by tab. Each tab has numbered tasks at the top and the data below.
A6: 2. | B6: Type a formula (not a hardcoded number!) in the yellow 'Your Answer' cell. The 'Check' column grades it instantly (±0.1%).
A7: 3. | B7: Build helper columns in the green 'workspace' area next to the data — that's how you'd do it live.
A8: 4. | B8: Stuck? Use the Hint column first. Model solutions are on the hidden 'Answer Key' tab (right-click any tab → Unhide).
A9: 5. | B9: Practice NARRATING out loud as if Janvi and Sky are watching: what you're doing, why, and how you'll sanity-check it.
A10: LEGEND
A11: Yellow fill | B11: Your answer cells / inputs
A12: Blue text | B12: Hardcoded data
A13: Green fill | B13: Workspace for your helper columns
A14: SUGGESTED TIME BUDGET
A15: If you have ~60 min | B15: 3_Returns (R1–R11) → 4_Screening (S1–S9) → 2_Aggregation (A1–A8)
A16: If you have ~2 hrs | B16: All of the above, then 1_Lookups, 5_Regression (G1–G7), 6_Valuation (V1–V9)
A17: Timed run | B17: Aim for ~2–3 min per task. Most live tasks are shorter than these.
A19: TABS & SCORE | C19: Score
A20: 1_Lookups | B20: Cleaning, INDEX/MATCH, two-way & approximate lookups | C20: =COUNTIF(1_Lookups!I:I,"✓ Correct")&" / 13" -> 0 / 13
A21: 2_Aggregation | B21: SUMIFS/COUNTIFS/AVERAGEIFS/MAXIFS, weighted avgs, aggregate P/E, pivot | C21: =COUNTIF(2_Aggregation!I:I,"✓ Correct")&" / 14" -> 0 / 14
A22: 3_Returns | B22: Cumulative/CAGR, vol, Sharpe, Sortino, drawdown, beta, TE/IR, calendar returns | C22: =COUNTIF(3_Returns!I:I,"✓ Correct")&" / 19" -> 0 / 19
A23: 4_Screening | B23: Multiples, RANK/PERCENTRANK, z-scores, composite value score, quintiles, winsorizing | C23: =COUNTIF(4_Screening!I:I,"✓ Correct")&" / 13" -> 0 / 13
A24: 5_Regression | B24: CORREL, SLOPE, INTERCEPT, RSQ, covariance, 3-factor LINEST, t-stats | C24: =COUNTIF(5_Regression!I:I,"✓ Correct")&" / 13" -> 0 / 13
A25: 6_Valuation | B25: Mkt cap, EV bridge, margins, CAGR, FCF yield, leverage, implied price, mini-DCF | C25: =COUNTIF(6_Valuation!I:I,"✓ Correct")&" / 16" -> 0 / 16
A26: TOTAL | C26: =COUNTIF(1_Lookups!I:I,"✓ Correct")+COUNTIF(2_Aggregation!I:I,"✓ Correct")+COUNTIF(3_Returns!I:I,"✓ Correct")+COUNTIF(4_Screening!I:I,"✓ Correct")+COUNTIF(5_Regression!I:I,"✓ Correct")+COUNTIF(6_Valuation!I:I,"✓ Correct")&" / 88" -> 0 / 88

Sheet 1_Lookups
A1: 1 · Lookups & Data Cleaning
A2: Messy trade blotter + clean reference table + month-end price grid. Clean, match, and look up.
A4: # | B4: Task | H4: Your Answer | I4: Check | J4: Hint (functions to use)
A5: L1 | B5: What sector is FENX in? (Use the reference table.) | I5: =IF(H5="","",IFERROR(IF(ISNUMBER('Answer Key'!$D$5),IF(ABS(H5-'Answer Key'!$D$5)<=MAX(0.0001,ABS('Answer Key'!$D$5)*0.001),"✓ Correct","✗ Try again"),IF(TRIM(H5)=TRIM('Answer Key'!$D$5),"✓ Correct","✗ Try again")),"✗ Try again")) | J5: INDEX/MATCH or XLOOKUP
A6: L2 | B6: Reverse lookup: what is the ticker for 'Harbor Logistics'? (Ticker column is to the LEFT of company name.) | I6: =IF(H6="","",IFERROR(IF(ISNUMBER('Answer Key'!$D$6),IF(ABS(H6-'Answer Key'!$D$6)<=MAX(0.0001,ABS('Answer Key'!$D$6)*0.001),"✓ Correct","✗ Try again"),IF(TRIM(H6)=TRIM('Answer Key'!$D$6),"✓ Correct","✗ Try again")),"✗ Try again")) | J6: INDEX/MATCH (VLOOKUP can't look left)
A7: L3 | B7: How many rows in the raw blotter have a 'dirty' ticker (leading/trailing spaces or lowercase)? | I7: =IF(H7="","",IFERROR(IF(ISNUMBER('Answer Key'!$D$7),IF(ABS(H7-'Answer Key'!$D$7)<=MAX(0.0001,ABS('Answer Key'!$D$7)*0.001),"✓ Correct","✗ Try again"),IF(TRIM(H7)=TRIM('Answer Key'!$D$7),"✓ Correct","✗ Try again")),"✗ Try again")) | J7: EXACT, TRIM, UPPER, SUMPRODUCT
A8: L4 | B8: How many prices in the raw blotter are stored as TEXT rather than numbers? | I8: =IF(H8="","",IFERROR(IF(ISNUMBER('Answer Key'!$D$8),IF(ABS(H8-'Answer Key'!$D$8)<=MAX(0.0001,ABS('Answer Key'!$D$8)*0.001),"✓ Correct","✗ Try again"),IF(TRIM(H8)=TRIM('Answer Key'!$D$8),"✓ Correct","✗ Try again")),"✗ Try again")) | J8: ISTEXT, SUMPRODUCT
A9: L5 | B9: Total market value (price × shares) across ALL blotter rows, after converting text prices to numbers. Include duplicates and unknown tickers. | I9: =IF(H9="","",IFERROR(IF(ISNUMBER('Answer Key'!$D$9),IF(ABS(H9-'Answer Key'!$D$9)<=MAX(0.0001,ABS('Answer Key'!$D$9)*0.001),"✓ Correct","✗ Try again"),IF(TRIM(H9)=TRIM('Answer Key'!$D$9),"✓ Correct","✗ Try again")),"✗ Try again")) | J9: VALUE / TRIM helper column, then SUM
A10: L6 | B10: After cleaning tickers (TRIM + UPPER), how many blotter rows have a ticker NOT in the reference table? | I10: =IF(H10="","",IFERROR(IF(ISNUMBER('Answer Key'!$D$10),IF(ABS(H10-'Answer Key'!$D$10)<=MAX(0.0001,ABS('Answer Key'!$D$10)*0.001),"✓ Correct","✗ Try again"),IF(TRIM(H10)=TRIM('Answer Key'!$D$10),"✓ Correct","✗ Try again")),"✗ Try again")) | J10: ISNA/ISNUMBER + MATCH, or COUNTIF=0
A11: L7 | B11: Total market value of blotter rows in the Energy sector (look up each row's sector first; all rows incl. duplicates). | I11: =IF(H11="","",IFERROR(IF(ISNUMBER('Answer Key'!$D$11),IF(ABS(H11-'Answer Key'!$D$11)<=MAX(0.0001,ABS('Answer Key'!$D$11)*0.001),"✓ Correct","✗ Try again"),IF(TRIM(H11)=TRIM('Answer Key'!$D$11),"✓ Correct","✗ Try again")),"✗ Try again")) | J11: Helper sector column + SUMIFS
A12: L8 | B12: How many rows are duplicate copies (same Trade ID appearing again after its first occurrence)? | I12: =IF(H12="","",IFERROR(IF(ISNUMBER('Answer Key'!$D$12),IF(ABS(H12-'Answer Key'!$D$12)<=MAX(0.0001,ABS('Answer Key'!$D$12)*0.001),"✓ Correct","✗ Try again"),IF(TRIM(H12)=TRIM('Answer Key'!$D$12),"✓ Correct","✗ Try again")),"✗ Try again")) | J12: COUNTIF with an expanding range $F$x:F2
A13: L9 | B13: Two-way lookup: MRDN's closing price on 2026-06-30 from the month-end grid. | I13: =IF(H13="","",IFERROR(IF(ISNUMBER('Answer Key'!$D$13),IF(ABS(H13-'Answer Key'!$D$13)<=MAX(0.0001,ABS('Answer Key'!$D$13)*0.001),"✓ Correct","✗ Try again"),IF(TRIM(H13)=TRIM('Answer Key'!$D$13),"✓ Correct","✗ Try again")),"✗ Try again")) | J13: INDEX(grid, MATCH(row), MATCH(col))
A14: L10 | B14: Extract the plain ticker from the BBG ID of trade T1017 (e.g. 'ABC US Equity' → 'ABC'). | I14: =IF(H14="","",IFERROR(IF(ISNUMBER('Answer Key'!$D$14),IF(ABS(H14-'Answer Key'!$D$14)<=MAX(0.0001,ABS('Answer Key'!$D$14)*0.001),"✓ Correct","✗ Try again"),IF(TRIM(H14)=TRIM('Answer Key'!$D$14),"✓ Correct","✗ Try again")),"✗ Try again")) | J14: LEFT + FIND (or TEXTBEFORE)
A15: L11 | B15: What is the company name for trade T1033? (Its raw ticker is dirty — clean it inside the lookup.) | I15: =IF(H15="","",IFERROR(IF(ISNUMBER('Answer Key'!$D$15),IF(ABS(H15-'Answer Key'!$D$15)<=MAX(0.0001,ABS('Answer Key'!$D$15)*0.001),"✓ Correct","✗ Try again"),IF(TRIM(H15)=TRIM('Answer Key'!$D$15),"✓ Correct","✗ Try again")),"✗ Try again")) | J15: INDEX/MATCH on UPPER(TRIM(x))
A16: L12 | B16: Approximate match: for trade T1025, return its ticker's most recent month-end close ON OR BEFORE the trade date. | I16: =IF(H16="","",IFERROR(IF(ISNUMBER('Answer Key'!$D$16),IF(ABS(H16-'Answer Key'!$D$16)<=MAX(0.0001,ABS('Answer Key'!$D$16)*0.001),"✓ Correct","✗ Try again"),IF(TRIM(H16)=TRIM('Answer Key'!$D$16),"✓ Correct","✗ Try again")),"✗ Try again")) | J16: MATCH(date, header, 1) — header sorted ascending
A17: L13 | B17: Total market value EXCLUDING duplicate rows AND rows with tickers not in the reference table. | I17: =IF(H17="","",IFERROR(IF(ISNUMBER('Answer Key'!$D$17),IF(ABS(H17-'Answer Key'!$D$17)<=MAX(0.0001,ABS('Answer Key'!$D$17)*0.001),"✓ Correct","✗ Try again"),IF(TRIM(H17)=TRIM('Answer Key'!$D$17),"✓ Correct","✗ Try again")),"✗ Try again")) | J17: Combine your helper flags with SUMPRODUCT or SUMIFS
G18: Score: | H18: =COUNTIF(I5:I17,"✓ Correct")&" / 13" -> 0 / 13
A21: DATA
A22: Reference (A:D) · Raw trade blotter (F:K) · Month-end close grid (M:Y). Green columns AA:AH = your workspace for helper columns.
A24: Ticker | B24: Company | C24: Sector | D24: Country | F24: Trade ID | G24: Ticker (raw) | H24: Trade Date | I24: Price (raw) | J24: Shares | K24: BBG ID | M24: Ticker | N24: 45961 | O24: 45991 | P24: 46022 | Q24: 46053 | R24: 46081 | S24: 46112 | T24: 46142 | U24: 46173 | V24: 46203 | W24: 46234 | X24: 46265 | Y24: 46295 | AA24: workspace
A25: ALDR | B25: Alder Resources | C25: Energy | D25: Germany | F25: T1001 | G25: LMRA | H25: 46160 | I25: 244.07 | J25: 2600 | K25: LMRA US Equity | M25: ALDR | N25: 147.3 | O25: 134.92 | P25: 131.94 | Q25: 115.7 | R25: 106.42 | S25: 93.76 | T25: 93.16 | U25: 85.82 | V25: 88.31 | W25: 90.16 | X25: 89.88 | Y25: 74.95
A26: BRKN | B26: Brookline Bancorp | C26: Financials | D26: Japan | F26: T1002 | G26: HRBR | H26: 46265 | I26: 264.22 | J26: 2300 | K26: HRBR US Equity | M26: BRKN | N26: 230.95 | O26: 232.47 | P26: 236.64 | Q26: 213.66 | R26: 208.65 | S26: 196.45 | T26: 187.29 | U26: 203.07 | V26: 193.62 | W26: 195.12 | X26: 209.15 | Y26: 202.7
A27: CVLT | B27: Cobalt Systems | C27: Technology | D27: Japan | F27: T1003 | G27: DMNX | H27: 46213 | I27: 41.96 | J27: 4900 | K27: DMNX US Equity | M27: CVLT | N27: 81.55 | O27: 82.99 | P27: 84.19 | Q27: 77.82 | R27: 79.01 | S27: 87.31 | T27: 78.73 | U27: 84.26 | V27: 85.8 | W27: 82.81 | X27: 95.23 | Y27: 101.26
A28: DMNX | B28: Domino Semiconductor | C28: Health Care | D28: Germany | F28: T1004 | G28: ZNTH | H28: 46237 | I28: 133.18 | J28: 3500 | K28: ZNTH US Equity | M28: DMNX | N28: 33.63 | O28: 34.14 | P28: 35.86 | Q28: 35.74 | R28: 37.81 | S28: 38.01 | T28: 40.17 | U28: 44.61 | V28: 42.95 | W28: 43.99 | X28: 43 | Y28: 43.82
A29: ELMR | B29: Elmore Therapeutics | C29: Industrials | D29: Japan | F29: T1005 | G29: xera | H29: 46188 | I29: 152.39 | J29: 1700 | K29: XERA US Equity | M29: ELMR | N29: 121.27 | O29: 117.57 | P29: 117.13 | Q29: 125.67 | R29: 137 | S29: 125.68 | T29: 119.94 | U29: 126.57 | V29: 110.19 | W29: 107.72 | X29: 108.06 | Y29: 118.65
A30: FENX | B30: Fenwick Oil & Gas | C30: Energy | D30: Germany | F30: T1006 | G30: KSTL | H30: 46070 | I30: 154.72 | J30: 900 | K30: KSTL US Equity | M30: FENX | N30: 237.34 | O30: 234.28 | P30: 230.57 | Q30: 228.84 | R30: 255.53 | S30: 250.43 | T30: 247.61 | U30: 256.2 | V30: 256.6 | W30: 255.62 | X30: 238.24 | Y30: 240.43
A31: GRVL | B31: Gravel Industrial | C31: Energy | D31: Germany | F31: T1007 | G31: ABRV | H31: 46016 | I31: 173.91 | J31: 4200 | K31: ABRV US Equity | M31: GRVL | N31: 114.52 | O31: 125.01 | P31: 131.98 | Q31: 133.08 | R31: 140.63 | S31: 138.69 | T31: 150.29 | U31: 151.74 | V31: 159.45 | W31: 146.64 | X31: 151.66 | Y31: 135.26
A32: HRBR | B32: Harbor Logistics | C32: Financials | D32: US | F32: T1008 | G32: ULMN | H32: 46282 | I32: 34.3 | J32: 1700 | K32: ULMN US Equity | M32: HRBR | N32: 242.44 | O32: 239.7 | P32: 227 | Q32: 231.88 | R32: 270.63 | S32: 257.58 | T32: 248.9 | U32: 254.97 | V32: 266.32 | W32: 265.7 | X32: 264.52 | Y32: 280.18
A33: IRNW | B33: Ironwood Insurance | C33: Technology | D33: US | F33: T1009 | G33: TRVO | H33: 46013 | I33: 59.4 | J33: 1400 | K33: TRVO US Equity | M33: IRNW | N33: 54.74 | O33: 51.33 | P33: 51.56 | Q33: 52.2 | R33: 48.87 | S33: 50.25 | T33: 47.73 | U33: 51.46 | V33: 52.67 | W33: 53.52 | X33: 51.84 | Y33: 51.93
A34: KSTL | B34: Kestrel Software | C34: Health Care | D34: UK | F34: T1010 | G34: CVLT | H34: 46020 | I34: 81.69 | J34: 4800 | K34: CVLT US Equity | M34: KSTL | N34: 186.95 | O34: 174.01 | P34: 180.17 | Q34: 155.13 | R34: 165.87 | S34: 147.25 | T34: 156.53 | U34: 148.83 | V34: 158.43 | W34: 161.47 | X34: 145.71 | Y34: 159.91
A35: LMRA | B35: Lamarra Foods | C35: Industrials | D35: UK | F35: T1011 | G35: ZZZZ | H35: 46227 | I35: 31.4 | J35: 2900 | K35: ZZZZ US Equity | M35: LMRA | N35: 245.49 | O35: 246.81 | P35: 244.55 | Q35: 244.26 | R35: 230.03 | S35: 250.02 | T35: 243.02 | U35: 244.58 | V35: 233.44 | W35: 225.54 | X35: 207.63 | Y35: 227.97
A36: MRDN | B36: Meridian Health | C36: Consumer | D36: Germany | F36: T1012 | G36: ABRV | H36: 46114 | I36: 170.12 | J36: 3500 | K36: ABRV US Equity | M36: MRDN | N36: 139.49 | O36: 150.31 | P36: 151.96 | Q36: 146.09 | R36: 144.21 | S36: 140 | T36: 141.48 | U36: 139.17 | V36: 137.64 | W36: 125.74 | X36: 119.89 | Y36: 134.97
A37: NOVX | B37: Novex Pharma | C37: Energy | D37: Germany | F37: T1013 | G37: BLCK | H37: 46275 | I37: 64.3 | J37: 1200 | K37: BLCK US Equity | M37: NOVX | N37: 230.56 | O37: 215.85 | P37: 223.11 | Q37: 247.31 | R37: 224.62 | S37: 223.58 | T37: 215.93 | U37: 191.47 | V37: 203.23 | W37: 204.93 | X37: 208.01 | Y37: 199.13
A38: OKRA | B38: Okra Brands | C38: Financials | D38: US | F38: T1014 | G38: okra | H38: 45964 | I38: 32.93 | J38: 3400 | K38: OKRA US Equity | M38: OKRA | N38: 34.23 | O38: 33.28 | P38: 33.28 | Q38: 31.03 | R38: 28.7 | S38: 31.67 | T38: 30.86 | U38: 31.8 | V38: 32.04 | W38: 31.37 | X38: 30.57 | Y38: 32.23
A39: PLMT | B39: Palmetto Energy | C39: Technology | D39: UK | F39: T1015 | G39: YRLW | H39: 46072 | I39: 308.54 | J39: 2100 | K39: YRLW US Equity | M39: PLMT | N39: 26.97 | O39: 26.95 | P39: 27.26 | Q39: 29.78 | R39: 31.5 | S39: 32.65 | T39: 31.69 | U39: 28.94 | V39: 31.16 | W39: 33.58 | X39: 33.58 | Y39: 35.19
A40: QRSN | B40: Quorsan Capital | C40: Health Care | D40: Germany | F40: T1016 | G40: GRVL | H40: 45978 | I40: 113.84 | J40: 2800 | K40: GRVL US Equity | M40: QRSN | N40: 235.82 | O40: 251.9 | P40: 270.66 | Q40: 264.74 | R40: 295.46 | S40: 272.63 | T40: 291.8 | U40: 304.81 | V40: 326.5 | W40: 372.71 | X40: 415.16 | Y40: 386.04
A41: RDGE | B41: Ridgeline Machinery | C41: Industrials | D41: US | F41: T1017 | G41: BRKN | H41: 46204 | I41: 192.94 | J41: 3600 | K41: BRKN US Equity | M41: RDGE | N41: 97.89 | O41: 104.47 | P41: 98.09 | Q41: 98.99 | R41: 105.79 | S41: 94.68 | T41: 81.64 | U41: 83.94 | V41: 85.04 | W41: 84.43 | X41: 85.5 | Y41: 81.2
A42: SLTN | B42: Saltonstall Bank | C42: Consumer | D42: Germany | F42: T1018 | G42: VSTR | H42: 46279 | I42: 113.22 | J42: 2400 | K42: VSTR US Equity | M42: SLTN | N42: 151.94 | O42: 151.68 | P42: 142.88 | Q42: 127.87 | R42: 133.68 | S42: 134.44 | T42: 139.61 | U42: 131.34 | V42: 126.6 | W42: 119.02 | X42: 112.82 | Y42: 115.49
A43: TRVO | B43: Trevo Devices | C43: Energy | D43: US | F43: T1019 | G43: OKRA | H43: 45980 | I43: 33.97 | J43: 3600 | K43: OKRA US Equity | M43: TRVO | N43: 57.15 | O43: 59.14 | P43: 61.14 | Q43: 70.42 | R43: 64.26 | S43: 68.9 | T43: 69.15 | U43: 69.78 | V43: 63.39 | W43: 61.98 | X43: 65.83 | Y43: 66.11
A44: ULMN | B44: Ulman Retail | C44: Financials | D44: UK | F44: T1020 | G44: EVRG | H44: 46203 | I44: 37.19 | J44: 4700 | K44: EVRG US Equity | M44: ULMN | N44: 50.76 | O44: 50.23 | P44: 54.79 | Q44: 55.26 | R44: 47.3 | S44: 45.48 | T44: 39.67 | U44: 31.04 | V44: 30.19 | W44: 33.32 | X44: 33.76 | Y44: 31.33
A45: VSTR | B45: Vestra Networks | C45: Technology | D45: Germany | F45: T1021 | G45: ZZZZ | H45: 46094 | I45: 62.92 | J45: 2800 | K45: ZZZZ US Equity | M45: VSTR | N45: 88.93 | O45: 96.86 | P45: 98.89 | Q45: 100.22 | R45: 100.84 | S45: 102.12 | T45: 108.9 | U45: 114.2 | V45: 117.07 | W45: 109.69 | X45: 114.71 | Y45: 110.37
A46: WNDL | B46: Windle Aerospace | C46: Health Care | D46: UK | F46: T1022 | G46: VSTR | H46: 45975 | I46: 88.11 | J46: 600 | K46: VSTR US Equity | M46: WNDL | N46: 63.04 | O46: 58.06 | P46: 58.09 | Q46: 58.64 | R46: 53.79 | S46: 60.81 | T46: 67.63 | U46: 66.11 | V46: 70.35 | W46: 72.91 | X46: 60.3 | Y46: 61.96
A47: XERA | B47: Xera Biotech | C47: Industrials | D47: UK | F47: T1023 | G47: VSTR | H47: 45985 | I47: 87.46 | J47: 2700 | K47: VSTR US Equity | M47: XERA | N47: 139.32 | O47: 141.52 | P47: 132.27 | Q47: 131.1 | R47: 130.77 | S47: 142.96 | T47: 147.73 | U47: 149.15 | V47: 166.61 | W47: 161.8 | X47: 159.01 | Y47: 140.38
A48: YRLW | B48: Yarrow Lane Apparel | C48: Consumer | D48: UK | F48: T1024 | G48: ABRV | H48: 46157 | I48: 174.29 | J48: 100 | K48: ABRV US Equity | M48: YRLW | N48: 249.26 | O48: 268.58 | P48: 288.5 | Q48: 304.89 | R48: 310.29 | S48: 318.07 | T48: 315.64 | U48: 314.3 | V48: 318.64 | W48: 355.55 | X48: 372.93 | Y48: 375.14
A49: ZNTH | B49: Zenith Pipelines | C49: Energy | D49: Japan | F49: T1025 | G49: IRNW | H49: 46251 | I49: 54.47 | J49: 3700 | K49: IRNW US Equity | M49: ZNTH | N49: 116.55 | O49: 112.53 | P49: 126.28 | Q49: 132.02 | R49: 133.97 | S49: 132.06 | T49: 123.13 | U49: 123.79 | V49: 132.59 | W49: 130.28 | X49: 129.51 | Y49: 128.8
A50: ABRV | B50: Abrevia Health | C50: Financials | D50: UK | F50: T1026 | G50: PLMT | H50: 46237 | I50: 33.14 | J50: 3700 | K50: PLMT US Equity | M50: ABRV | N50: 194.89 | O50: 175.1 | P50: 173.97 | Q50: 165.3 | R50: 177.19 | S50: 169.41 | T50: 177.94 | U50: 198.71 | V50: 196.34 | W50: 190.03 | X50: 194.48 | Y50: 196.4
A51: BLCK | B51: Blackrock Mining Co | C51: Technology | D51: Germany | F51: T1027 | G51: dmnx | H51: 46146 | I51: 40.86 | J51: 800 | K51: DMNX US Equity | M51: BLCK | N51: 63.83 | O51: 66.53 | P51: 76.58 | Q51: 75.96 | R51: 75.64 | S51: 70.86 | T51: 73.16 | U51: 67.5 | V51: 62.95 | W51: 69.21 | X51: 65.52 | Y51: 71.13
A52: CRST | B52: Crestview Financial | C52: Health Care | D52: UK | F52: T1028 | G52: PLMT | H52: 46234 | I52: 33.06 | J52: 3100 | K52: PLMT US Equity | M52: CRST | N52: 248.93 | O52: 255.94 | P52: 268.42 | Q52: 307.78 | R52: 306.62 | S52: 296.96 | T52: 271.8 | U52: 275.31 | V52: 306.57 | W52: 330.23 | X52: 311.75 | Y52: 296.2
A53: DRFT | B53: Driftwood Hotels | C53: Industrials | D53: UK | F53: T1029 | G53: MRDN | H53: 46185 | I53: 138.54 | J53: 2100 | K53: MRDN US Equity | M53: DRFT | N53: 62.25 | O53: 64.15 | P53: 63.87 | Q53: 65.46 | R53: 67.48 | S53: 66.74 | T53: 67.22 | U53: 68.87 | V53: 69.15 | W53: 72.28 | X53: 82.47 | Y53: 86.71
A54: EVRG | B54: Evergreen Utilities Tech | C54: Consumer | D54: Japan | F54: T1030 | G54: NOVX | H54: 45995 | I54: 215.18 | J54: 2800 | K54: NOVX US Equity | M54: EVRG | N54: 51.35 | O54: 45.8 | P54: 47.51 | Q54: 41.51 | R54: 37.83 | S54: 40.47 | T54: 42.88 | U54: 42.85 | V54: 38.15 | W54: 37.54 | X54: 36.13 | Y54: 38.11
F55: T1031 | G55: FENX | H55: 46209 | I55: 256.36 | J55: 2100 | K55: FENX US Equity
F56: T1032 | G56: PLMT | H56: 45985 | I56: 27 | J56: 3800 | K56: PLMT US Equity
F57: T1033 | G57: lmra | H57: 46014 | I57: 246.62 | J57: 4100 | K57: LMRA US Equity
F58: T1034 | G58: NOVX | H58: 46240 | I58: 207.60 | J58: 4800 | K58: NOVX US Equity
F59: T1035 | G59: PLMT | H59: 46210 | I59: 31.12 | J59: 3500 | K59: PLMT US Equity
F60: T1036 | G60: CRST | H60: 46245 | I60: 320.16 | J60: 2500 | K60: CRST US Equity
F61: T1037 | G61: QQQQ | H61: 46237 | I61: 116.33 | J61: 3300 | K61: QQQQ US Equity
F62: T1038 | G62: irnw | H62: 46154 | I62: 46.96 | J62: 600 | K62: IRNW US Equity
F63: T1039 | G63: FENX | H63: 46076 | I63: 225.38 | J63: 1500 | K63: FENX US Equity
F64: T1040 | G64: HRBR | H64: 46104 | I64: 265.37 | J64: 1600 | K64: HRBR US Equity
F65: T1007 | G65: ABRV | H65: 46016 | I65: 173.91 | J65: 4200 | K65: ABRV US Equity
F66: T1016 | G66: GRVL | H66: 45978 | I66: 113.84 | J66: 2800 | K66: GRVL US Equity
F67: T1030 | G67: NOVX | H67: 45995 | I67: 215.18 | J67: 2800 | K67: NOVX US Equity

Sheet 2_Aggregation
A1: 2 · Conditional Aggregation & Pivots
A2: 60-stock global universe. SUMIFS / COUNTIFS / AVERAGEIFS / MAXIFS / SUMPRODUCT, plus a pivot-table check.
A4: # | B4: Task | H4: Your Answer | I4: Check | J4: Hint (functions to use)
A5: A1 | B5: Total market cap of the Financials sector ($bn). | I5: =IF(H5="","",IFERROR(IF(ISNUMBER('Answer Key'!$D$18),IF(ABS(H5-'Answer Key'!$D$18)<=MAX(0.0001,ABS('Answer Key'!$D$18)*0.001),"✓ Correct","✗ Try again"),IF(TRIM(H5)=TRIM('Answer Key'!$D$18),"✓ Correct","✗ Try again")),"✗ Try again")) | J5: SUMIFS
A6: A2 | B6: How many Technology stocks returned more than 10% over the past year? | I6: =IF(H6="","",IFERROR(IF(ISNUMBER('Answer Key'!$D$19),IF(ABS(H6-'Answer Key'!$D$19)<=MAX(0.0001,ABS('Answer Key'!$D$19)*0.001),"✓ Correct","✗ Try again"),IF(TRIM(H6)=TRIM('Answer Key'!$D$19),"✓ Correct","✗ Try again")),"✗ Try again")) | J6: COUNTIFS with ">0.1"
A7: A3 | B7: Average P/E of US Industrials (ignore NM). | I7: =IF(H7="","",IFERROR(IF(ISNUMBER('Answer Key'!$D$20),IF(ABS(H7-'Answer Key'!$D$20)<=MAX(0.0001,ABS('Answer Key'!$D$20)*0.001),"✓ Correct","✗ Try again"),IF(TRIM(H7)=TRIM('Answer Key'!$D$20),"✓ Correct","✗ Try again")),"✗ Try again")) | J7: AVERAGEIFS (text 'NM' is skipped automatically)
A8: A4 | B8: Market-cap-weighted average 1Y return of Health Care. | I8: =IF(H8="","",IFERROR(IF(ISNUMBER('Answer Key'!$D$21),IF(ABS(H8-'Answer Key'!$D$21)<=MAX(0.0001,ABS('Answer Key'!$D$21)*0.001),"✓ Correct","✗ Try again"),IF(TRIM(H8)=TRIM('Answer Key'!$D$21),"✓ Correct","✗ Try again")),"✗ Try again")) | J8: SUMPRODUCT((cond)*cap*ret)/SUMIFS(cap)
A9: A5 | B9: Highest dividend yield in Energy. | I9: =IF(H9="","",IFERROR(IF(ISNUMBER('Answer Key'!$D$22),IF(ABS(H9-'Answer Key'!$D$22)<=MAX(0.0001,ABS('Answer Key'!$D$22)*0.001),"✓ Correct","✗ Try again"),IF(TRIM(H9)=TRIM('Answer Key'!$D$22),"✓ Correct","✗ Try again")),"✗ Try again")) | J9: MAXIFS
A10: A6 | B10: Lowest P/E among UK stocks (ignore NM). | I10: =IF(H10="","",IFERROR(IF(ISNUMBER('Answer Key'!$D$23),IF(ABS(H10-'Answer Key'!$D$23)<=MAX(0.0001,ABS('Answer Key'!$D$23)*0.001),"✓ Correct","✗ Try again"),IF(TRIM(H10)=TRIM('Answer Key'!$D$23),"✓ Correct","✗ Try again")),"✗ Try again")) | J10: MINIFS
A11: A7 | B11: How many stocks have a market cap between $10bn and $50bn inclusive? | I11: =IF(H11="","",IFERROR(IF(ISNUMBER('Answer Key'!$D$24),IF(ABS(H11-'Answer Key'!$D$24)<=MAX(0.0001,ABS('Answer Key'!$D$24)*0.001),"✓ Correct","✗ Try again"),IF(TRIM(H11)=TRIM('Answer Key'!$D$24),"✓ Correct","✗ Try again")),"✗ Try again")) | J11: COUNTIFS on the same column twice
A12: A8 | B12: Combined market cap of Technology OR Health Care. | I12: =IF(H12="","",IFERROR(IF(ISNUMBER('Answer Key'!$D$25),IF(ABS(H12-'Answer Key'!$D$25)<=MAX(0.0001,ABS('Answer Key'!$D$25)*0.001),"✓ Correct","✗ Try again"),IF(TRIM(H12)=TRIM('Answer Key'!$D$25),"✓ Correct","✗ Try again")),"✗ Try again")) | J12: Two SUMIFS added, or SUM(SUMIFS(...,{"A","B"}))
A13: A9 | B13: Which sector has the largest total market cap? (text) | I13: =IF(H13="","",IFERROR(IF(ISNUMBER('Answer Key'!$D$26),IF(ABS(H13-'Answer Key'!$D$26)<=MAX(0.0001,ABS('Answer Key'!$D$26)*0.001),"✓ Correct","✗ Try again"),IF(TRIM(H13)=TRIM('Answer Key'!$D$26),"✓ Correct","✗ Try again")),"✗ Try again")) | J13: Build a small sector table with SUMIFS, then INDEX/MATCH on MAX
A14: A10 | B14: AGGREGATE P/E of Energy = total cap ÷ total net income (include loss-makers). Why is this better than averaging P/Es? | I14: =IF(H14="","",IFERROR(IF(ISNUMBER('Answer Key'!$D$27),IF(ABS(H14-'Answer Key'!$D$27)<=MAX(0.0001,ABS('Answer Key'!$D$27)*0.001),"✓ Correct","✗ Try again"),IF(TRIM(H14)=TRIM('Answer Key'!$D$27),"✓ Correct","✗ Try again")),"✗ Try again")) | J14: SUMIFS / SUMIFS
A15: A11 | B15: PIVOT: Build a PivotTable of average 1Y Return by Sector (rows) × Country (cols). What is Japan / Technology? | I15: =IF(H15="","",IFERROR(IF(ISNUMBER('Answer Key'!$D$28),IF(ABS(H15-'Answer Key'!$D$28)<=MAX(0.0001,ABS('Answer Key'!$D$28)*0.001),"✓ Correct","✗ Try again"),IF(TRIM(H15)=TRIM('Answer Key'!$D$28),"✓ Correct","✗ Try again")),"✗ Try again")) | J15: Insert → PivotTable; Values = Average. Verify with AVERAGEIFS
A16: A12 | B16: What % of total universe market cap is rated 'Buy'? | I16: =IF(H16="","",IFERROR(IF(ISNUMBER('Answer Key'!$D$29),IF(ABS(H16-'Answer Key'!$D$29)<=MAX(0.0001,ABS('Answer Key'!$D$29)*0.001),"✓ Correct","✗ Try again"),IF(TRIM(H16)=TRIM('Answer Key'!$D$29),"✓ Correct","✗ Try again")),"✗ Try again")) | J16: SUMIFS / SUM
A17: A13 | B17: How many stocks have a P/E of 'NM'? | I17: =IF(H17="","",IFERROR(IF(ISNUMBER('Answer Key'!$D$30),IF(ABS(H17-'Answer Key'!$D$30)<=MAX(0.0001,ABS('Answer Key'!$D$30)*0.001),"✓ Correct","✗ Try again"),IF(TRIM(H17)=TRIM('Answer Key'!$D$30),"✓ Correct","✗ Try again")),"✗ Try again")) | J17: COUNTIF
A18: A14 | B18: Average 1Y return of the 10 largest stocks by market cap. | I18: =IF(H18="","",IFERROR(IF(ISNUMBER('Answer Key'!$D$31),IF(ABS(H18-'Answer Key'!$D$31)<=MAX(0.0001,ABS('Answer Key'!$D$31)*0.001),"✓ Correct","✗ Try again"),IF(TRIM(H18)=TRIM('Answer Key'!$D$31),"✓ Correct","✗ Try again")),"✗ Try again")) | J18: AVERAGEIFS with ">="&LARGE(cap,10)
G19: Score: | H19: =COUNTIF(I5:I18,"✓ Correct")&" / 14" -> 0 / 14
A22: DATA
A23: Mkt Cap & Net Income in $bn. P/E shows 'NM' (not meaningful) when earnings ≤ 0. Then build a PivotTable (Insert → PivotTable) for A11.
A25: Ticker | B25: Sector | C25: Country | D25: Mkt Cap ($bn) | E25: Net Income ($bn) | F25: P/E | G25: Div Yield | H25: 1Y Return | I25: Rating
A26: ALDR | B26: Energy | C26: UK | D26: 16.42 | E26: -0.26 | F26: NM | G26: 0.0096 | H26: 0.0812 | I26: Buy
A27: BRKN | B27: Financials | C27: Germany | D27: 10.28 | E27: 0.89 | F27: 11.6 | G27: 0.042 | H27: 0.2894 | I27: Hold
A28: CVLT | B28: Technology | C28: UK | D28: 3.69 | E28: 0.44 | F28: 8.4 | G28: 0.0246 | H28: 0.5206 | I28: Buy
A29: DMNX | B29: Health Care | C29: US | D29: 16.55 | E29: 1.83 | F29: 9 | G29: 0.0139 | H29: 0.055 | I29: Buy
A30: ELMR | B30: Industrials | C30: Japan | D30: 23.79 | E30: 1.71 | F30: 13.9 | G30: 0.0197 | H30: 0.0794 | I30: Buy
A31: FENX | B31: Consumer | C31: Germany | D31: 22.55 | E31: -0.4 | F31: NM | G31: 0.0217 | H31: 0.1337 | I31: Hold
A32: GRVL | B32: Energy | C32: Germany | D32: 22.34 | E32: 2.39 | F32: 9.3 | G32: 0.0355 | H32: 0.3855 | I32: Buy
A33: HRBR | B33: Financials | C33: UK | D33: 7.99 | E33: 0.42 | F33: 19 | G33: 0.0011 | H33: 0.0833 | I33: Buy
A34: IRNW | B34: Technology | C34: Germany | D34: 22.96 | E34: -1.53 | F34: NM | G34: 0.0094 | H34: 0.4133 | I34: Hold
A35: KSTL | B35: Health Care | C35: Germany | D35: 23.6 | E35: 1.86 | F35: 12.7 | G35: 0.0193 | H35: -0.1227 | I35: Buy
A36: LMRA | B36: Industrials | C36: UK | D36: 89.17 | E36: -1.3 | F36: NM | G36: 0.063 | H36: 0.0491 | I36: Sell
A37: MRDN | B37: Consumer | C37: UK | D37: 158.66 | E37: -0.77 | F37: NM | G37: 0.0393 | H37: 0.0464 | I37: Sell
A38: NOVX | B38: Energy | C38: UK | D38: 21.39 | E38: 0.6 | F38: 35.7 | G38: 0.0233 | H38: 0.263 | I38: Buy
A39: OKRA | B39: Financials | C39: UK | D39: 11.4 | E39: 1.41 | F39: 8.1 | G39: 0.0357 | H39: 0.32 | I39: Hold
A40: PLMT | B40: Technology | C40: Germany | D40: 22.99 | E40: 0.95 | F40: 24.2 | G40: 0.0559 | H40: -0.2421 | I40: Buy
A41: QRSN | B41: Health Care | C41: UK | D41: 13.36 | E41: 0.98 | F41: 13.6 | G41: 0.0215 | H41: -0.1113 | I41: Buy
A42: RDGE | B42: Industrials | C42: UK | D42: 11.68 | E42: 1.72 | F42: 6.8 | G42: 0.0195 | H42: 0.1641 | I42: Buy
A43: SLTN | B43: Consumer | C43: Germany | D43: 23.14 | E43: 3.23 | F43: 7.2 | G43: 0.0432 | H43: -0.0549 | I43: Hold
A44: TRVO | B44: Energy | C44: Japan | D44: 8.64 | E44: 0.47 | F44: 18.4 | G44: 0.0324 | H44: -0.2449 | I44: Sell
A45: ULMN | B45: Financials | C45: US | D45: 44.97 | E45: 2.16 | F45: 20.8 | G45: 0.0351 | H45: 0.3185 | I45: Buy
A46: VSTR | B46: Technology | C46: US | D46: 22.11 | E46: -0.07 | F46: NM | G46: 0.0174 | H46: 0.1987 | I46: Hold
A47: WNDL | B47: Health Care | C47: US | D47: 31.5 | E47: 0.8 | F47: 39.4 | G47: 0.0539 | H47: 0.1985 | I47: Hold
A48: XERA | B48: Industrials | C48: Germany | D48: 20.43 | E48: 1.66 | F48: 12.3 | G48: 0.0506 | H48: -0.0146 | I48: Buy
A49: YRLW | B49: Consumer | C49: US | D49: 11.85 | E49: 0.95 | F49: 12.5 | G49: 0.0335 | H49: 0.3164 | I49: Sell
A50: ZNTH | B50: Energy | C50: UK | D50: 9.51 | E50: 0.62 | F50: 15.3 | G50: 0.0353 | H50: 0.0372 | I50: Hold
A51: ABRV | B51: Financials | C51: Japan | D51: 19.35 | E51: 2.12 | F51: 9.1 | G51: 0 | H51: 0.3312 | I51: Buy
A52: BLCK | B52: Technology | C52: UK | D52: 14.17 | E52: 0.3 | F52: 47.2 | G52: 0.0346 | H52: -0.1106 | I52: Sell
A53: CRST | B53: Health Care | C53: US | D53: 31 | E53: 1.77 | F53: 17.5 | G53: 0.0221 | H53: -0.0979 | I53: Buy
A54: DRFT | B54: Industrials | C54: US | D54: 24.42 | E54: 2.36 | F54: 10.3 | G54: 0.0315 | H54: 0.135 | I54: Buy
A55: EVRG | B55: Consumer | C55: Germany | D55: 6.28 | E55: 0.56 | F55: 11.2 | G55: 0.0352 | H55: -0.0645 | I55: Buy
A56: FLNT | B56: Energy | C56: UK | D56: 26.24 | E56: 2.98 | F56: 8.8 | G56: 0.0199 | H56: 0.2386 | I56: Sell
A57: GLDN | B57: Financials | C57: UK | D57: 6.41 | E57: 0.51 | F57: 12.6 | G57: 0 | H57: 0.1472 | I57: Buy
A58: HZLN | B58: Technology | C58: Germany | D58: 13.24 | E58: 0.59 | F58: 22.4 | G58: 0.0305 | H58: -0.1131 | I58: Sell
... A60: JSPR | B60: Industrials | C60: Germany | D60: 3.08 | E60: 0.03 | F60: 102.7 | G60: 0.02 | H60: 0.0127 | I60: Buy
A61: KLMN | B61: Consumer | C61: US | D61: 26.88 | E61: -0.59 | F61: NM | G61: 0.0159 | H61: 0.2915 | I61: Hold
A62: LTUS | B62: Energy | C62: UK | D62: 28.53 | E62: 2.54 | F62: 11.2 | G62: 0.0199 | H62: -0.0492 | I62: Hold
A63: MSTC | B63: Financials | C63: Germany | D63: 20.95 | E63: 1.2 | F63: 17.5 | G63: 0 | H63: -0.0066 | I63: Hold
A64: NRTH | B64: Technology | C64: Germany | D64: 16.05 | E64: 1.21 | F64: 13.3 | G64: 0.0433 | H64: 0.3565 | I64: Hold
A65: OPAL | B65: Health Care | C65: Japan | D65: 16.88 | E65: -0.42 | F65: NM | G65: 0.0288 | H65: 0.5825 | I65: Hold
A66: PRSM | B66: Industrials | C66: UK | D66: 9.24 | E66: 0.39 | F66: 23.7 | G66: 0.0417 | H66: 0.5298 | I66: Sell
A67: QUIL | B67: Consumer | C67: Germany | D67: 18.73 | E67: 0.56 | F67: 33.4 | G67: 0.0547 | H67: 0.1039 | I67: Buy
A68: RVNE | B68: Energy | C68: UK | D68: 14.12 | E68: 0.24 | F68: 58.8 | G68: 0.0253 | H68: 0.1381 | I68: Hold
A69: SPRC | B69: Financials | C69: Japan | D69: 26.89 | E69: -1.42 | F69: NM | G69: 0 | H69: 0.4274 | I69: Buy
A70: TMBR | B70: Technology | C70: Japan | D70: 7.36 | E70: 0.32 | F70: 23 | G70: 0.0116 | H70: 0.0626 | I70: Hold
A71: UMBR | B71: Health Care | C71: UK | D71: 31.05 | E71: 3.26 | F71: 9.5 | G71: 0.0069 | H71: -0.1248 | I71: Sell
A72: VLLY | B72: Industrials | C72: US | D72: 28.31 | E72: 2.24 | F72: 12.6 | G72: 0.0175 | H72: 0.1157 | I72: Sell
A73: WLOW | B73: Consumer | C73: Japan | D73: 21.29 | E73: 0.64 | F73: 33.3 | G73: 0.0262 | H73: 0.1893 | I73: Buy
A74: XNTH | B74: Energy | C74: UK | D74: 15.81 | E74: 0.94 | F74: 16.8 | G74: 0 | H74: -0.0924 | I74: Hold
A75: YUKN | B75: Financials | C75: Japan | D75: 42.62 | E75: 4.17 | F75: 10.2 | G75: 0.0301 | H75: -0.2722 | I75: Sell
A76: ZPHR | B76: Technology | C76: Japan | D76: 4.64 | E76: -0.36 | F76: NM | G76: 0.0023 | H76: -0.2261 | I76: Sell
A77: ARCD | B77: Health Care | C77: Germany | D77: 38.88 | E77: 2.09 | F77: 18.6 | G77: 0.0295 | H77: 0.2364 | I77: Buy
A78: BYRN | B78: Industrials | C78: Germany | D78: 31.28 | E78: 2.73 | F78: 11.5 | G78: 0.0234 | H78: -0.0768 | I78: Sell
A79: CDAR | B79: Consumer | C79: Japan | D79: 32.57 | E79: 3.07 | F79: 10.6 | G79: 0.0203 | H79: 0.0589 | I79: Buy
A80: DLTA | B80: Energy | C80: US | D80: 35.99 | E80: 5.22 | F80: 6.9 | G80: 0.0239 | H80: 0.1368 | I80: Buy
A81: EMBR | B81: Financials | C81: US | D81: 12.76 | E81: 1.49 | F81: 8.6 | G81: 0.0169 | H81: 0.2262 | I81: Hold
A82: FRST | B82: Technology | C82: Japan | D82: 18.93 | E82: 1.43 | F82: 13.2 | G82: 0.0158 | H82: 0.0163 | I82: Hold
A83: GRNT | B83: Health Care | C83: Japan | D83: 46.39 | E83: 3.48 | F83: 13.3 | G83: 0 | H83: 0.1997 | I83: Buy
A84: HLCN | B84: Industrials | C84: Germany | D84: 37.74 | E84: 3.75 | F84: 10.1 | G84: 0.0246 | H84: -0.1058 | I84: Buy
A85: IVRY | B85: Consumer | C85: UK | D85: 30.17 | E85: 1 | F85: 30.2 | G85: 0.0527 | H85: 0.0104 | I85: Buy

Sheet Key_Work
A1: Key_Work — helper columns used by the Answer Key (rows mirror each practice tab's data rows)
J4: S2 Sector | K4: Total Cap | AH4: S6 DCF
J5: Energy | K5: =SUMIFS(2_Aggregation!$D$26:$D$85,2_Aggregation!$B$26:$B$85,J5) -> 198.99 | AH5: FCF0 | AJ5: =6_Valuation!$F$34-6_Valuation!$F$35 -> 590
J6: Financials | K6: =SUMIFS(2_Aggregation!$D$26:$D$85,2_Aggregation!$B$26:$B$85,J6) -> 203.62 | AH6: FCF yr1 | AI6: 1 | AJ6: =$AJ$5*(1+6_Valuation!$B$47)^1 -> 619.5
J7: Technology | K7: =SUMIFS(2_Aggregation!$D$26:$D$85,2_Aggregation!$B$26:$B$85,J7) -> 146.14 | AH7: FCF yr2 | AI7: 2 | AJ7: =$AJ$5*(1+6_Valuation!$B$47)^2 -> 650.475
J8: Health Care | K8: =SUMIFS(2_Aggregation!$D$26:$D$85,2_Aggregation!$B$26:$B$85,J8) -> 267.49 | AH8: FCF yr3 | AI8: 3 | AJ8: =$AJ$5*(1+6_Valuation!$B$47)^3 -> 682.99875
J9: Industrials | K9: =SUMIFS(2_Aggregation!$D$26:$D$85,2_Aggregation!$B$26:$B$85,J9) -> 279.14 | AH9: FCF yr4 | AI9: 4 | AJ9: =$AJ$5*(1+6_Valuation!$B$47)^4 -> 717.14869
J10: Consumer | K10: =SUMIFS(2_Aggregation!$D$26:$D$85,2_Aggregation!$B$26:$B$85,J10) -> 352.12 | AH10: FCF yr5 | AI10: 5 | AJ10: =$AJ$5*(1+6_Valuation!$B$47)^5 -> 753.00612
AH11: EV (DCF) | AJ11: =NPV(6_Valuation!$B$46,AJ6:AJ10)+AJ10*(1+6_Valuation!$B$48)/(6_Valuation!$B$46-6_Valuation!$B$48)/(1+6_Valuation!$B$46)^5 -> 10358.187
AH12: Implied px | AJ12: =(AJ11-(6_Valuation!$B$41-6_Valuation!$B$42+6_Valuation!$B$43+6_Valuation!$B$44))/6_Valuation!$F$37 -> 36.371652
A24: S1 Clean Tkr | B24: Price# | C24: Mkt Val | D24: In Ref | E24: Sector | F24: Dup | G24: Dirty Tkr | H24: Text Px | V24: S4 P/B | W24: E/P | X24: EV/EBITDA | Y24: Rk PB | Z24: Rk EP | AA24: Rk EV | AB24: Composite | AC24: Comp Rk | AD24: Quintile | AE24: P/E pos | AF24: ROE wins
A25: =UPPER(TRIM(1_Lookups!G25)) -> LMRA | B25: =VALUE(TRIM(1_Lookups!I25)) -> 244.07 | C25: =B25*1_Lookups!J25 -> 634582 | D25: =IF(ISNUMBER(MATCH(A25,1_Lookups!$A$25:$A$54,0)),1,0) -> 1 | E25: =IFERROR(INDEX(1_Lookups!$C$25:$C$54,MATCH(A25,1_Lookups!$A$25:$A$54,0)),"Not Found") -> Industrials | F25: =IF(COUNTIF(1_Lookups!$F$25:F25,1_Lookups!F25)>1,1,0) -> 0 | G25: =IF(EXACT(1_Lookups!G25,A25),0,1) -> 0 | H25: =IF(ISTEXT(1_Lookups!I25),1,0) -> 0 | V25: =4_Screening!C25/4_Screening!D25 -> 1.5482032 | W25: =4_Screening!E25/4_Screening!C25 -> 0.10074627 | X25: =4_Screening!F25/4_Screening!G25 -> 6.9076923 | Y25: =RANK(V25,$V$25:$V$74,1) -> 20 | Z25: =RANK(W25,$W$25:$W$74,0) -> 6 | AA25: =RANK(X25,$X$25:$X$74,1) -> 9 | AB25: =AVERAGE(Y25:AA25) -> 11.666667 | AC25: =RANK(AB25,$AB$25:$AB$74,1) -> 1 | AD25: =ROUNDUP(5*AC25/COUNT($AB$25:$AB$74),0) -> 1 | AE25: =IF(4_Screening!E25>0,4_Screening!C25/4_Screening!E25,"") -> 9.9259259 | AF25: =MIN(MAX(4_Screening!H25,PERCENTILE(4_Screening!$H$25:$H$74,0.05)),PERCENTILE(4_Screening!$H$25:$H$74,0.95)) -> 0.1456
A26: =UPPER(TRIM(1_Lookups!G26)) -> HRBR | B26: =VALUE(TRIM(1_Lookups!I26)) -> 264.22 | C26: =B26*1_Lookups!J26 -> 607706 | D26: =IF(ISNUMBER(MATCH(A26,1_Lookups!$A$25:$A$54,0)),1,0) -> 1 | E26: =IFERROR(INDEX(1_Lookups!$C$25:$C$54,MATCH(A26,1_Lookups!$A$25:$A$54,0)),"Not Found") -> Financials | F26: =IF(COUNTIF(1_Lookups!$F$25:F26,1_Lookups!F26)>1,1,0) -> 0 | G26: =IF(EXACT(1_Lookups!G26,A26),0,1) -> 0 | H26: =IF(ISTEXT(1_Lookups!I26),1,0) -> 1 | V26: =4_Screening!C26/4_Screening!D26 -> 2.1747621 | W26: =4_Screening!E26/4_Screening!C26 -> 0.12653266 | X26: =4_Screening!F26/4_Screening!G26 -> 11.553191 | Y26: =RANK(V26,$V$25:$V$74,1) -> 33 | Z26: =RANK(W26,$W$25:$W$74,0) -> 3 | AA26: =RANK(X26,$X$25:$X$74,1) -> 33 | AB26: =AVERAGE(Y26:AA26) -> 23 | AC26: =RANK(AB26,$AB$25:$AB$74,1) -> 21 | AD26: =ROUNDUP(5*AC26/COUNT($AB$25:$AB$74),0) -> 3 | AE26: =IF(4_Screening!E26>0,4_Screening!C26/4_Screening!E26,"") -> 7.903098 | AF26: =MIN(MAX(4_Screening!H26,PERCENTILE(4_Screening!$H$25:$H$74,0.05)),PERCENTILE(4_Screening!$H$25:$H$74,0.95)) -> 0.1727
A27: =UPPER(TRIM(1_Lookups!G27)) -> DMNX | B27: =VALUE(TRIM(1_Lookups!I27)) -> 41.96 | C27: =B27*1_Lookups!J27 -> 205604 | D27: =IF(ISNUMBER(MATCH(A27,1_Lookups!$A$25:$A$54,0)),1,0) -> 1 | E27: =IFERROR(INDEX(1_Lookups!$C$25:$C$54,MATCH(A27,1_Lookups!$A$25:$A$54,0)),"Not Found") -> Health Care | F27: =IF(COUNTIF(1_Lookups!$F$25:F27,1_Lookups!F27)>1,1,0) -> 0 | G27: =IF(EXACT(1_Lookups!G27,A27),0,1) -> 1 | H27: =IF(ISTEXT(1_Lookups!I27),1,0) -> 0 | V27: =4_Screening!C27/4_Screening!D27 -> 1.4397487 | W27: =4_Screening!E27/4_Screening!C27 -> 0.1032659 | X27: =4_Screening!F27/4_Screening!G27 -> 8.654321 | Y27: =RANK(V27,$V$25:$V$74,1) -> 18 | Z27: =RANK(W27,$W$25:$W$74,0) -> 4 | AA27: =RANK(X27,$X$25:$X$74,1) -> 23 | AB27: =AVERAGE(Y27:AA27) -> 15 | AC27: =RANK(AB27,$AB$25:$AB$74,1) -> 7 | AD27: =ROUNDUP(5*AC27/COUNT($AB$25:$AB$74),0) -> 1 | AE27: =IF(4_Screening!E27>0,4_Screening!C27/4_Screening!E27,"") -> 9.6837388 | AF27: =MIN(MAX(4_Screening!H27,PERCENTILE(4_Screening!$H$25:$H$74,0.05)),PERCENTILE(4_Screening!$H$25:$H$74,0.95)) -> 0.1747
A28: =UPPER(TRIM(1_Lookups!G28)) -> ZNTH | B28: =VALUE(TRIM(1_Lookups!I28)) -> 133.18 | C28: =B28*1_Lookups!J28 -> 466130 | D28: =IF(ISNUMBER(MATCH(A28,1_Lookups!$A$25:$A$54,0)),1,0) -> 1 | E28: =IFERROR(INDEX(1_Lookups!$C$25:$C$54,MATCH(A28,1_Lookups!$A$25:$A$54,0)),"Not Found") -> Energy | F28: =IF(COUNTIF(1_Lookups!$F$25:F28,1_Lookups!F28)>1,1,0) -> 0 | G28: =IF(EXACT(1_Lookups!G28,A28),0,1) -> 0 | H28: =IF(ISTEXT(1_Lookups!I28),1,0) -> 0 | V28: =4_Screening!C28/4_Screening!D28 -> 0.7474555 | W28: =4_Screening!E28/4_Screening!C28 -> 0.055272337 | X28: =4_Screening!F28/4_Screening!G28 -> 6.7920904 | Y28: =RANK(V28,$V$25:$V$74,1) -> 3 | Z28: =RANK(W28,$W$25:$W$74,0) -> 28 | AA28: =RANK(X28,$X$25:$X$74,1) -> 8 | AB28: =AVERAGE(Y28:AA28) -> 13 | AC28: =RANK(AB28,$AB$25:$AB$74,1) -> 2 | AD28: =ROUNDUP(5*AC28/COUNT($AB$25:$AB$74),0) -> 1 | AE28: =IF(4_Screening!E28>0,4_Screening!C28/4_Screening!E28,"") -> 18.092233 | AF28: =MIN(MAX(4_Screening!H28,PERCENTILE(4_Screening!$H$25:$H$74,0.05)),PERCENTILE(4_Screening!$H$25:$H$74,0.95)) -> 0.29721
A29: =UPPER(TRIM(1_Lookups!G29)) -> XERA | B29: =VALUE(TRIM(1_Lookups!I29)) -> 152.39 | C29: =B29*1_Lookups!J29 -> 259063 | D29: =IF(ISNUMBER(MATCH(A29,1_Lookups!$A$25:$A$54,0)),1,0) -> 1 | E29: =IFERROR(INDEX(1_Lookups!$C$25:$C$54,MATCH(A29,1_Lookups!$A$25:$A$54,0)),"Not Found") -> Industrials | F29: =IF(COUNTIF(1_Lookups!$F$25:F29,1_Lookups!F29)>1,1,0) -> 0 | G29: =IF(EXACT(1_Lookups!G29,A29),0,1) -> 1 | H29: =IF(ISTEXT(1_Lookups!I29),1,0) -> 0 | V29: =4_Screening!C29/4_Screening!D29 -> 3.1378057 | W29: =4_Screening!E29/4_Screening!C29 -> 0.070352817 | X29: =4_Screening!F29/4_Screening!G29 -> 12.47561 | Y29: =RANK(V29,$V$25:$V$74,1) -> 46 | Z29: =RANK(W29,$W$25:$W$74,0) -> 16 | AA29: =RANK(X29,$X$25:$X$74,1) -> 38 | AB29: =AVERAGE(Y29:AA29) -> 33.333333 | AC29: =RANK(AB29,$AB$25:$AB$74,1) -> 41 | AD29: =ROUNDUP(5*AC29/COUNT($AB$25:$AB$74),0) -> 5 | AE29: =IF(4_Screening!E29>0,4_Screening!C29/4_Screening!E29,"") -> 14.214072 | AF29: =MIN(MAX(4_Screening!H29,PERCENTILE(4_Screening!$H$25:$H$74,0.05)),PERCENTILE(4_Screening!$H$25:$H$74,0.95)) -> 0.1075
A30: =UPPER(TRIM(1_Lookups!G30)) -> KSTL | B30: =VALUE(TRIM(1_Lookups!I30)) -> 154.72 | C30: =B30*1_Lookups!J30 -> 139248 | D30: =IF(ISNUMBER(MATCH(A30,1_Lookups!$A$25:$A$54,0)),1,0) -> 1 | E30: =IFERROR(INDEX(1_Lookups!$C$25:$C$54,MATCH(A30,1_Lookups!$A$25:$A$54,0)),"Not Found") -> Health Care | F30: =IF(COUNTIF(1_Lookups!$F$25:F30,1_Lookups!F30)>1,1,0) -> 0 | G30: =IF(EXACT(1_Lookups!G30,A30),0,1) -> 0 | H30: =IF(ISTEXT(1_Lookups!I30),1,0) -> 1 | M30: S3 rA | N30: rB | O30: rM | P30: RunMax A | Q30: DD A | R30: ln rA | S30: rA-rM | T30: A>M | V30: =4_Screening!C30/4_Screening!D30 -> 0.96569228 | W30: =4_Screening!E30/4_Screening!C30 -> 0.067156063 | X30: =4_Screening!F30/4_Screening!G30 -> 11.617021 | Y30: =RANK(V30,$V$25:$V$74,1) -> 7 | Z30: =RANK(W30,$W$25:$W$74,0) -> 18 | AA30: =RANK(X30,$X$25:$X$74,1) -> 34 | AB30: =AVERAGE(Y30:AA30) -> 19.666667 | AC30: =RANK(AB30,$AB$25:$AB$74,1) -> 13 | AD30: =ROUNDUP(5*AC30/COUNT($AB$25:$AB$74),0) -> 2 | AE30: =IF(4_Screening!E30>0,4_Screening!C30/4_Screening!E30,"") -> 14.890688 | AF30: =MIN(MAX(4_Screening!H30,PERCENTILE(4_Screening!$H$25:$H$74,0.05)),PERCENTILE(4_Screening!$H$25:$H$74,0.95)) -> 0.1399
A31: =UPPER(TRIM(1_Lookups!G31)) -> ABRV | B31: =VALUE(TRIM(1_Lookups!I31)) -> 173.91 | C31: =B31*1_Lookups!J31 -> 730422 | D31: =IF(ISNUMBER(MATCH(A31,1_Lookups!$A$25:$A$54,0)),1,0) -> 1 | E31: =IFERROR(INDEX(1_Lookups!$C$25:$C$54,MATCH(A31,1_Lookups!$A$25:$A$54,0)),"Not Found") -> Financials | F31: =IF(COUNTIF(1_Lookups!$F$25:F31,1_Lookups!F31)>1,1,0) -> 0 | G31: =IF(EXACT(1_Lookups!G31,A31),0,1) -> 0 | H31: =IF(ISTEXT(1_Lookups!I31),1,0) -> 0 | P31: =MAX(3_Returns!$B$31:B31) -> 48.2 | Q31: =3_Returns!B31/P31-1 -> 0 | V31: =4_Screening!C31/4_Screening!D31 -> 2.7388265 | W31: =4_Screening!E31/4_Screening!C31 -> -0.06837451 | X31: =4_Screening!F31/4_Screening!G31 -> 7.3333333 | Y31: =RANK(V31,$V$25:$V$74,1) -> 42 | Z31: =RANK(W31,$W$25:$W$74,0) -> 49 | AA31: =RANK(X31,$X$25:$X$74,1) -> 12 | AB31: =AVERAGE(Y31:AA31) -> 34.333333 | AC31: =RANK(AB31,$AB$25:$AB$74,1) -> 45 | AD31: =ROUNDUP(5*AC31/COUNT($AB$25:$AB$74),0) -> 5 | AE31: =IF(4_Screening!E31>0,4_Screening!C31/4_Screening!E31,"") | AF31: =MIN(MAX(4_Screening!H31,PERCENTILE(4_Screening!$H$25:$H$74,0.05)),PERCENTILE(4_Screening!$H$25:$H$74,0.95)) -> 0.186
A32: =UPPER(TRIM(1_Lookups!G32)) -> ULMN | B32: =VALUE(TRIM(1_Lookups!I32)) -> 34.3 | C32: =B32*1_Lookups!J32 -> 58310 | D32: =IF(ISNUMBER(MATCH(A32,1_Lookups!$A$25:$A$54,0)),1,0) -> 1 | E32: =IFERROR(INDEX(1_Lookups!$C$25:$C$54,MATCH(A32,1_Lookups!$A$25:$A$54,0)),"Not Found") -> Financials | F32: =IF(COUNTIF(1_Lookups!$F$25:F32,1_Lookups!F32)>1,1,0) -> 0 | G32: =IF(EXACT(1_Lookups!G32,A32),0,1) -> 1 | H32: =IF(ISTEXT(1_Lookups!I32),1,0) -> 0 | M32: =3_Returns!B32/3_Returns!B31-1 -> 0.010580913 | N32: =3_Returns!C32/3_Returns!C31-1 -> -0.0024681201 | O32: =3_Returns!D32/3_Returns!D31-1 -> 0.0066837056 | P32: =MAX(3_Returns!$B$31:B32) -> 48.71 | Q32: =3_Returns!B32/P32-1 -> 0 | R32: =LN(3_Returns!B32/3_Returns!B31) -> 0.010525327 | S32: =M32-O32 -> 0.0038972072 | T32: =IF(M32>O32,1,0) -> 1 | V32: =4_Screening!C32/4_Screening!D32 -> 2.3447154 | W32: =4_Screening!E32/4_Screening!C32 -> 0.067961165 | X32: =4_Screening!F32/4_Screening!G32 -> 13.558333 | Y32: =RANK(V32,$V$25:$V$74,1) -> 39 | Z32: =RANK(W32,$W$25:$W$74,0) -> 17 | AA32: =RANK(X32,$X$25:$X$74,1) -> 43 | AB32: =AVERAGE(Y32:AA32) -> 33 | AC32: =RANK(AB32,$AB$25:$AB$74,1) -> 40 | AD32: =ROUNDUP(5*AC32/COUNT($AB$25:$AB$74),0) -> 4 | AE32: =IF(4_Screening!E32>0,4_Screening!C32/4_Screening!E32,"") -> 14.714286 | AF32: =MIN(MAX(4_Screening!H32,PERCENTILE(4_Screening!$H$25:$H$74,0.05)),PERCENTILE(4_Screening!$H$25:$H$74,0.95)) -> 0.0849
A33: =UPPER(TRIM(1_Lookups!G33)) -> TRVO | B33: =VALUE(TRIM(1_Lookups!I33)) -> 59.4 | C33: =B33*1_Lookups!J33 -> 83160 | D33: =IF(ISNUMBER(MATCH(A33,1_Lookups!$A$25:$A$54,0)),1,0) -> 1 | E33: =IFERROR(INDEX(1_Lookups!$C$25:$C$54,MATCH(A33,1_Lookups!$A$25:$A$54,0)),"Not Found") -> Energy | F33: =IF(COUNTIF(1_Lookups!$F$25:F33,1_Lookups!F33)>1,1,0) -> 0 | G33: =IF(EXACT(1_Lookups!G33,A33),0,1) -> 0 | H33: =IF(ISTEXT(1_Lookups!I33),1,0) -> 0 | M33: =3_Returns!B33/3_Returns!B32-1 -> 0.011701909 | N33: =3_Returns!C33/3_Returns!C32-1 -> -0.0028041237 | O33: =3_Returns!D33/3_Returns!D32-1 -> 0.00070079888 | P33: =MAX(3_Returns!$B$31:B33) -> 49.28 | Q33: =3_Returns!B33/P33-1 -> 0 | R33: =LN(3_Returns!B33/3_Returns!B32) -> 0.011633971 | S33: =M33-O33 -> 0.01100111 | T33: =IF(M33>O33,1,0) -> 1 | V33: =4_Screening!C33/4_Screening!D33 -> 0.67463432 | W33: =4_Screening!E33/4_Screening!C33 -> 0.028556319 | X33: =4_Screening!F33/4_Screening!G33 -> 8.1295812 | Y33: =RANK(V33,$V$25:$V$74,1) -> 2 | Z33: =RANK(W33,$W$25:$W$74,0) -> 37 | AA33: =RANK(X33,$X$25:$X$74,1) -> 19 | AB33: =AVERAGE(Y33:AA33) -> 19.333333 | AC33: =RANK(AB33,$AB$25:$AB$74,1) -> 11 | AD33: =ROUNDUP(5*AC33/COUNT($AB$25:$AB$74),0) -> 2 | AE33: =IF(4_Screening!E33>0,4_Screening!C33/4_Screening!E33,"") -> 35.018519 | AF33: =MIN(MAX(4_Screening!H33,PERCENTILE(4_Screening!$H$25:$H$74,0.05)),PERCENTILE(4_Screening!$H$25:$H$74,0.95)) -> 0.0486
A34: =UPPER(TRIM(1_Lookups!G34)) -> CVLT | B34: =VALUE(TRIM(1_Lookups!I34)) -> 81.69 | C34: =B34*1_Lookups!J34 -> 392112 | D34: =IF(ISNUMBER(MATCH(A34,1_Lookups!$A$25:$A$54,0)),1,0) -> 1 | E34: =IFERROR(INDEX(1_Lookups!$C$25:$C$54,MATCH(A34,1_Lookups!$A$25:$A$54,0)),"Not Found") -> Technology | F34: =IF(COUNTIF(1_Lookups!$F$25:F34,1_Lookups!F34)>1,1,0) -> 0 | G34: =IF(EXACT(1_Lookups!G34,A34),0,1) -> 0 | H34: =IF(ISTEXT(1_Lookups!I34),1,0) -> 1 | M34: =3_Returns!B34/3_Returns!B33-1 -> 0.014813312 | N34: =3_Returns!C34/3_Returns!C33-1 -> 0.026962203 | O34: =3_Returns!D34/3_Returns!D33-1 -> 0.012777582 | P34: =MAX(3_Returns!$B$31:B34) -> 50.01 | Q34: =3_Returns!B34/P34-1 -> 0 | R34: =LN(3_Returns!B34/3_Returns!B33) -> 0.014704666 | S34: =M34-O34 -> 0.0020357299 | T34: =IF(M34>O34,1,0) -> 1 | V34: =4_Screening!C34/4_Screening!D34 -> 1.0337497 | W34: =4_Screening!E34/4_Screening!C34 -> -0.024166376 | X34: =4_Screening!F34/4_Screening!G34 -> 8.0985915 | Y34: =RANK(V34,$V$25:$V$74,1) -> 8 | Z34: =RANK(W34,$W$25:$W$74,0) -> 44 | AA34: =RANK(X34,$X$25:$X$74,1) -> 17 | AB34: =AVERAGE(Y34:AA34) -> 23 | AC34: =RANK(AB34,$AB$25:$AB$74,1) -> 21 | AD34: =ROUNDUP(5*AC34/COUNT($AB$25:$AB$74),0) -> 3 | AE34: =IF(4_Screening!E34>0,4_Screening!C34/4_Screening!E34,"") | AF34: =MIN(MAX(4_Screening!H34,PERCENTILE(4_Screening!$H$25:$H$74,0.05)),PERCENTILE(4_Screening!$H$25:$H$74,0.95)) -> 0.2002
A35: =UPPER(TRIM(1_Lookups!G35)) -> ZZZZ | B35: =VALUE(TRIM(1_Lookups!I35)) -> 31.4 | C35: =B35*1_Lookups!J35 -> 91060 | D35: =IF(ISNUMBER(MATCH(A35,1_Lookups!$A$25:$A$54,0)),1,0) -> 0 | E35: =IFERROR(INDEX(1_Lookups!$C$25:$C$54,MATCH(A35,1_Lookups!$A$25:$A$54,0)),"Not Found") -> Not Found | F35: =IF(COUNTIF(1_Lookups!$F$25:F35,1_Lookups!F35)>1,1,0) -> 0 | G35: =IF(EXACT(1_Lookups!G35,A35),0,1) -> 0 | H35: =IF(ISTEXT(1_Lookups!I35),1,0) -> 0 | M35: =3_Returns!B35/3_Returns!B34-1 -> 0.015396921 | N35: =3_Returns!C35/3_Returns!C34-1 -> 0.0063622453 | O35: =3_Returns!D35/3_Returns!D34-1 -> 0.0046000954 | P35: =MAX(3_Returns!$B$31:B35) -> 50.78 | Q35: =3_Returns!B35/P35-1 -> 0 | R35: =LN(3_Returns!B35/3_Returns!B34) -> 0.015279591 | S35: =M35-O35 -> 0.010796825 | T35: =IF(M35>O35,1,0) -> 1 | V35: =4_Screening!C35/4_Screening!D35 -> 1.338455 | W35: =4_Screening!E35/4_Screening!C35 -> 0.033107122 | X35: =4_Screening!F35/4_Screening!G35 -> 9.4074074 | Y35: =RANK(V35,$V$25:$V$74,1) -> 15 | Z35: =RANK(W35,$W$25:$W$74,0) -> 33 | AA35: =RANK(X35,$X$25:$X$74,1) -> 26 | AB35: =AVERAGE(Y35:AA35) -> 24.666667 | AC35: =RANK(AB35,$AB$25:$AB$74,1) -> 24 | AD35: =ROUNDUP(5*AC35/COUNT($AB$25:$AB$74),0) -> 3 | AE35: =IF(4_Screening!E35>0,4_Screening!C35/4_Screening!E35,"") -> 30.204981 | AF35: =MIN(MAX(4_Screening!H35,PERCENTILE(4_Screening!$H$25:$H$74,0.05)),PERCENTILE(4_Screening!$H$25:$H$74,0.95)) -> 0.2074
A36: =UPPER(TRIM(1_Lookups!G36)) -> ABRV | B36: =VALUE(TRIM(1_Lookups!I36)) -> 170.12 | C36: =B36*1_Lookups!J36 -> 595420 | D36: =IF(ISNUMBER(MATCH(A36,1_Lookups!$A$25:$A$54,0)),1,0) -> 1 | E36: =IFERROR(INDEX(1_Lookups!$C$25:$C$54,MATCH(A36,1_Lookups!$A$25:$A$54,0)),"Not Found") -> Financials | F36: =IF(COUNTIF(1_Lookups!$F$25:F36,1_Lookups!F36)>1,1,0) -> 0 | G36: =IF(EXACT(1_Lookups!G36,A36),0,1) -> 1 | H36: =IF(ISTEXT(1_Lookups!I36),1,0) -> 0 | M36: =3_Returns!B36/3_Returns!B35-1 -> -0.014769594 | N36: =3_Returns!C36/3_Returns!C35-1 -> 0.004081306 | O36: =3_Returns!D36/3_Returns!D35-1 -> 0.0042698913 | P36: =MAX(3_Returns!$B$31:B36) -> 50.78 | Q36: =3_Returns!B36/P36-1 -> -0.014769594 | R36: =LN(3_Returns!B36/3_Returns!B35) -> -0.014879751 | S36: =M36-O36 -> -0.019039486 | T36: =IF(M36>O36,1,0) -> 0 | V36: =4_Screening!C36/4_Screening!D36 -> 1.1135418 | W36: =4_Screening!E36/4_Screening!C36 -> -0.021033526 | X36: =4_Screening!F36/4_Screening!G36 -> 6.9367816 | Y36: =RANK(V36,$V$25:$V$74,1) -> 9 | Z36: =RANK(W36,$W$25:$W$74,0) -> 43 | AA36: =RANK(X36,$X$25:$X$74,1) -> 10 | AB36: =AVERAGE(Y36:AA36) -> 20.666667 | AC36: =RANK(AB36,$AB$25:$AB$74,1) -> 15 | AD36: =ROUNDUP(5*AC36/COUNT($AB$25:$AB$74),0) -> 2 | AE36: =IF(4_Screening!E36>0,4_Screening!C36/4_Screening!E36,"") | AF36: =MIN(MAX(4_Screening!H36,PERCENTILE(4_Screening!$H$25:$H$74,0.05)),PERCENTILE(4_Screening!$H$25:$H$74,0.95)) -> 0.1559
A37: =UPPER(TRIM(1_Lookups!G37)) -> BLCK | B37: =VALUE(TRIM(1_Lookups!I37)) -> 64.3 | C37: =B37*1_Lookups!J37 -> 77160 | D37: =IF(ISNUMBER(MATCH(A37,1_Lookups!$A$25:$A$54,0)),1,0) -> 1 | E37: =IFERROR(INDEX(1_Lookups!$C$25:$C$54,MATCH(A37,1_Lookups!$A$25:$A$54,0)),"Not Found") -> Technology | F37: =IF(COUNTIF(1_Lookups!$F$25:F37,1_Lookups!F37)>1,1,0) -> 0 | G37: =IF(EXACT(1_Lookups!G37,A37),0,1) -> 0 | H37: =IF(ISTEXT(1_Lookups!I37),1,0) -> 0 | M37: =3_Returns!B37/3_Returns!B36-1 -> 0.019588247 | N37: =3_Returns!C37/3_Returns!C36-1 -> 0.0243883 | O37: =3_Returns!D37/3_Returns!D36-1 -> 0.0044490174 | P37: =MAX(3_Returns!$B$31:B37) -> 51.01 | Q37: =3_Returns!B37/P37-1 -> 0 | R37: =LN(3_Returns!B37/3_Returns!B36) -> 0.019398866 | S37: =M37-O37 -> 0.01513923 | T37: =IF(M37>O37,1,0) -> 1 | V37: =4_Screening!C37/4_Screening!D37 -> 0.89650512 | W37: =4_Screening!E37/4_Screening!C37 -> 0.062674995 | X37: =4_Screening!F37/4_Screening!G37 -> 7.736 | Y37: =RANK(V37,$V$25:$V$74,1) -> 5 | Z37: =RANK(W37,$W$25:$W$74,0) -> 21 | AA37: =RANK(X37,$X$25:$X$74,1) -> 13 | AB37: =AVERAGE(Y37:AA37) -> 13 | AC37: =RANK(AB37,$AB$25:$AB$74,1) -> 2 | AD37: =ROUNDUP(5*AC37/COUNT($AB$25:$AB$74),0) -> 1 | AE37: =IF(4_Screening!E37>0,4_Screening!C37/4_Screening!E37,"") -> 15.955326 | AF37: =MIN(MAX(4_Screening!H37,PERCENTILE(4_Screening!$H$25:$H$74,0.05)),PERCENTILE(4_Screening!$H$25:$H$74,0.95)) -> 0.0874
A38: =UPPER(TRIM(1_Lookups!G38)) -> OKRA | B38: =VALUE(TRIM(1_Lookups!I38)) -> 32.93 | C38: =B38*1_Lookups!J38 -> 111962 | D38: =IF(ISNUMBER(MATCH(A38,1_Lookups!$A$25:$A$54,0)),1,0) -> 1 | E38: =IFERROR(INDEX(1_Lookups!$C$25:$C$54,MATCH(A38,1_Lookups!$A$25:$A$54,0)),"Not Found") -> Financials | F38: =IF(COUNTIF(1_Lookups!$F$25:F38,1_Lookups!F38)>1,1,0) -> 0 | G38: =IF(EXACT(1_Lookups!G38,A38),0,1) -> 1 | H38: =IF(ISTEXT(1_Lookups!I38),1,0) -> 0 | M38: =3_Returns!B38/3_Returns!B37-1 -> -0.024701039 | N38: =3_Returns!C38/3_Returns!C37-1 -> -0.0065354392 | O38: =3_Returns!D38/3_Returns!D37-1 -> -0.014364785 | P38: =MAX(3_Returns!$B$31:B38) -> 51.01 | Q38: =3_Returns!B38/P38-1 -> -0.024701039 | R38: =LN(3_Returns!B38/3_Returns!B37) -> -0.025011228 | S38: =M38-O38 -> -0.010336254 | T38: =IF(M38>O38,1,0) -> 0 | V38: =4_Screening!C38/4_Screening!D38 -> 2.8401072 | W38: =4_Screening!E38/4_Screening!C38 -> 0.060229596 | X38: =4_Screening!F38/4_Screening!G38 -> 8.5338983 | Y38: =RANK(V38,$V$25:$V$74,1) -> 44 | Z38: =RANK(W38,$W$25:$W$74,0) -> 24 | AA38: =RANK(X38,$X$25:$X$74,1) -> 22 | AB38: =AVERAGE(Y38:AA38) -> 30 | AC38: =RANK(AB38,$AB$25:$AB$74,1) -> 33 | AD38: =ROUNDUP(5*AC38/COUNT($AB$25:$AB$74),0) -> 4 | AE38: =IF(4_Screening!E38>0,4_Screening!C38/4_Screening!E38,"") -> 16.603133 | AF38: =MIN(MAX(4_Screening!H38,PERCENTILE(4_Screening!$H$25:$H$74,0.05)),PERCENTILE(4_Screening!$H$25:$H$74,0.95)) -> 0.1585
A39: =UPPER(TRIM(1_Lookups!G39)) -> YRLW | B39: =VALUE(TRIM(1_Lookups!I39)) -> 308.54 | C39: =B39*1_Lookups!J39 -> 647934 | D39: =IF(ISNUMBER(MATCH(A39,1_Lookups!$A$25:$A$54,0)),1,0) -> 1 | E39: =IFERROR(INDEX(1_Lookups!$C$25:$C$54,MATCH(A39,1_Lookups!$A$25:$A$54,0)),"Not Found") -> Consumer | F39: =IF(COUNTIF(1_Lookups!$F$25:F39,1_Lookups!F39)>1,1,0) -> 0 | G39: =IF(EXACT(1_Lookups!G39,A39),0,1) -> 0 | H39: =IF(ISTEXT(1_Lookups!I39),1,0) -> 1 | M39: =3_Returns!B39/3_Returns!B38-1 -> 0.0064321608 | N39: =3_Returns!C39/3_Returns!C38-1 -> -0.0085362988 | O39: =3_Returns!D39/3_Returns!D38-1 -> -0.0013416316 | P39: =MAX(3_Returns!$B$31:B39) -> 51.01 | Q39: =3_Returns!B39/P39-1 -> -0.018427759 | R39: =LN(3_Returns!B39/3_Returns!B38) -> 0.0064115627 | S39: =M39-O39 -> 0.0077737924 | T39: =IF(M39>O39,1,0) -> 1 | V39: =4_Screening!C39/4_Screening!D39 -> 1.5782149 | W39: =4_Screening!E39/4_Screening!C39 -> -0.0069965746 | X39: =4_Screening!F39/4_Screening!G39 -> 15.433333 | Y39: =RANK(V39,$V$25:$V$74,1) -> 23 | Z39: =RANK(W39,$W$25:$W$74,0) -> 41 | AA39: =RANK(X39,$X$25:$X$74,1) -> 46 | AB39: =AVERAGE(Y39:AA39) -> 36.666667 | AC39: =RANK(AB39,$AB$25:$AB$74,1) -> 47 | AD39: =ROUNDUP(5*AC39/COUNT($AB$25:$AB$74),0) -> 5 | AE39: =IF(4_Screening!E39>0,4_Screening!C39/4_Screening!E39,"") | AF39: =MIN(MAX(4_Screening!H39,PERCENTILE(4_Screening!$H$25:$H$74,0.05)),PERCENTILE(4_Screening!$H$25:$H$74,0.95)) -> 0.1377
A40: =UPPER(TRIM(1_Lookups!G40)) -> GRVL | B40: =VALUE(TRIM(1_Lookups!I40)) -> 113.84 | C40: =B40*1_Lookups!J40 -> 318752 | D40: =IF(ISNUMBER(MATCH(A40,1_Lookups!$A$25:$A$54,0)),1,0) -> 1 | E40: =IFERROR(INDEX(1_Lookups!$C$25:$C$54,MATCH(A40,1_Lookups!$A$25:$A$54,0)),"Not Found") -> Energy | F40: =IF(COUNTIF(1_Lookups!$F$25:F40,1_Lookups!F40)>1,1,0) -> 0 | G40: =IF(EXACT(1_Lookups!G40,A40),0,1) -> 0 | H40: =IF(ISTEXT(1_Lookups!I40),1,0) -> 0 | M40: =3_Returns!B40/3_Returns!B39-1 -> -0.00019972039 | N40: =3_Returns!C40/3_Returns!C39-1 -> 0.005450237 | O40: =3_Returns!D40/3_Returns!D39-1 -> -0.0022963949 | P40: =MAX(3_Returns!$B$31:B40) -> 51.01 | Q40: =3_Returns!B40/P40-1 -> -0.018623799 | R40: =LN(3_Returns!B40/3_Returns!B39) -> -0.00019974034 | S40: =M40-O40 -> 0.0020966745 | T40: =IF(M40>O40,1,0) -> 1 | V40: =4_Screening!C40/4_Screening!D40 -> 2.2965387 | W40: =4_Screening!E40/4_Screening!C40 -> 0.087532003 | X40: =4_Screening!F40/4_Screening!G40 -> 15.25431 | Y40: =RANK(V40,$V$25:$V$74,1) -> 38 | Z40: =RANK(W40,$W$25:$W$74,0) -> 11 | AA40: =RANK(X40,$X$25:$X$74,1) -> 45 | AB40: =AVERAGE(Y40:AA40) -> 31.333333 | AC40: =RANK(AB40,$AB$25:$AB$74,1) -> 34 | AD40: =ROUNDUP(5*AC40/COUNT($AB$25:$AB$74),0) -> 4 | AE40: =IF(4_Screening!E40>0,4_Screening!C40/4_Screening!E40,"") -> 11.424393 | AF40: =MIN(MAX(4_Screening!H40,PERCENTILE(4_Screening!$H$25:$H$74,0.05)),PERCENTILE(4_Screening!$H$25:$H$74,0.95)) -> 0.1886
A41: =UPPER(TRIM(1_Lookups!G41)) -> BRKN | B41: =VALUE(TRIM(1_Lookups!I41)) -> 192.94 | C41: =B41*1_Lookups!J41 -> 694584 | D41: =IF(ISNUMBER(MATCH(A41,1_Lookups!$A$25:$A$54,0)),1,0) -> 1 | E41: =IFERROR(INDEX(1_Lookups!$C$25:$C$54,MATCH(A41,1_Lookups!$A$25:$A$54,0)),"Not Found") -> Financials | F41: =IF(COUNTIF(1_Lookups!$F$25:F41,1_Lookups!F41)>1,1,0) -> 0 | G41: =IF(EXACT(1_Lookups!G41,A41),0,1) -> 0 | H41: =IF(ISTEXT(1_Lookups!I41),1,0) -> 0 | M41: =3_Returns!B41/3_Returns!B40-1 -> -0.029564523 | N41: =3_Returns!C41/3_Returns!C40-1 -> -0.009427292 | O41: =3_Returns!D41/3_Returns!D40-1 -> 0.002408575 | P41: =MAX(3_Returns!$B$31:B41) -> 51.01 | Q41: =3_Returns!B41/P41-1 -> -0.047637718 | R41: =LN(3_Returns!B41/3_Returns!B40) -> -0.030010362 | S41: =M41-O41 -> -0.031973098 | T41: =IF(M41>O41,1,0) -> 0 | V41: =4_Screening!C41/4_Screening!D41 -> 1.4072814 | W41: =4_Screening!E41/4_Screening!C41 -> 0.094709516 | X41: =4_Screening!F41/4_Screening!G41 -> 8.2432432 | Y41: =RANK(V41,$V$25:$V$74,1) -> 17 | Z41: =RANK(W41,$W$25:$W$74,0) -> 9 | AA41: =RANK(X41,$X$25:$X$74,1) -> 20 | AB41: =AVERAGE(Y41:AA41) -> 15.333333 | AC41: =RANK(AB41,$AB$25:$AB$74,1) -> 8 | AD41: =ROUNDUP(5*AC41/COUNT($AB$25:$AB$74),0) -> 1 | AE41: =IF(4_Screening!E41>0,4_Screening!C41/4_Screening!E41,"") -> 10.558601 | AF41: =MIN(MAX(4_Screening!H41,PERCENTILE(4_Screening!$H$25:$H$74,0.05)),PERCENTILE(4_Screening!$H$25:$H$74,0.95)) -> 0.0426
A42: =UPPER(TRIM(1_Lookups!G42)) -> VSTR | B42: =VALUE(TRIM(1_Lookups!I42)) -> 113.22 | C42: =B42*1_Lookups!J42 -> 271728 | D42: =IF(ISNUMBER(MATCH(A42,1_Lookups!$A$25:$A$54,0)),1,0) -> 1 | E42: =IFERROR(INDEX(1_Lookups!$C$25:$C$54,MATCH(A42,1_Lookups!$A$25:$A$54,0)),"Not Found") -> Technology | F42: =IF(COUNTIF(1_Lookups!$F$25:F42,1_Lookups!F42)>1,1,0) -> 0 | G42: =IF(EXACT(1_Lookups!G42,A42),0,1) -> 0 | H42: =IF(ISTEXT(1_Lookups!I42),1,0) -> 0 | M42: =3_Returns!B42/3_Returns!B41-1 -> -0.025319061 | N42: =3_Returns!C42/3_Returns!C41-1 -> 0.0014275517 | O42: =3_Returns!D42/3_Returns!D41-1 -> -0.013376149 | P42: =MAX(3_Returns!$B$31:B42) -> 51.01 | Q42: =3_Returns!B42/P42-1 -> -0.071750637 | R42: =LN(3_Returns!B42/3_Returns!B41) -> -0.025645104 | S42: =M42-O42 -> -0.011942912 | T42: =IF(M42>O42,1,0) -> 0 | V42: =4_Screening!C42/4_Screening!D42 -> 2.1881574 | W42: =4_Screening!E42/4_Screening!C42 -> 0.063913121 | X42: =4_Screening!F42/4_Screening!G42 -> 15.861111 | Y42: =RANK(V42,$V$25:$V$74,1) -> 34 | Z42: =RANK(W42,$W$25:$W$74,0) -> 20 | AA42: =RANK(X42,$X$25:$X$74,1) -> 47 | AB42: =AVERAGE(Y42:AA42) -> 33.666667 | AC42: =RANK(AB42,$AB$25:$AB$74,1) -> 44 | AD42: =ROUNDUP(5*AC42/COUNT($AB$25:$AB$74),0) -> 5 | AE42: =IF(4_Screening!E42>0,4_Screening!C42/4_Screening!E42,"") -> 15.64624 | AF42: =MIN(MAX(4_Screening!H42,PERCENTILE(4_Screening!$H$25:$H$74,0.05)),PERCENTILE(4_Screening!$H$25:$H$74,0.95)) -> 0.03151
A43: =UPPER(TRIM(1_Lookups!G43)) -> OKRA | B43: =VALUE(TRIM(1_Lookups!I43)) -> 33.97 | C43: =B43*1_Lookups!J43 -> 122292 | D43: =IF(ISNUMBER(MATCH(A43,1_Lookups!$A$25:$A$54,0)),1,0) -> 1 | E43: =IFERROR(INDEX(1_Lookups!$C$25:$C$54,MATCH(A43,1_Lookups!$A$25:$A$54,0)),"Not Found") -> Financials | F43: =IF(COUNTIF(1_Lookups!$F$25:F43,1_Lookups!F43)>1,1,0) -> 0 | G43: =IF(EXACT(1_Lookups!G43,A43),0,1) -> 0 | H43: =IF(ISTEXT(1_Lookups!I43),1,0) -> 1 | M43: =3_Returns!B43/3_Returns!B42-1 -> 0.023020063 | N43: =3_Returns!C43/3_Returns!C42-1 -> 0.02328344 | O43: =3_Returns!D43/3_Returns!D42-1 -> 0.016787796 | P43: =MAX(3_Returns!$B$31:B43) -> 51.01 | Q43: =3_Returns!B43/P43-1 -> -0.050382278 | R43: =LN(3_Returns!B43/3_Returns!B42) -> 0.022759099 | S43: =M43-O43 -> 0.0062322677 | T43: =IF(M43>O43,1,0) -> 1 | V43: =4_Screening!C43/4_Screening!D43 -> 1.1610414 | W43: =4_Screening!E43/4_Screening!C43 -> 0.12672559 | X43: =4_Screening!F43/4_Screening!G43 -> 8.888361 | Y43: =RANK(V43,$V$25:$V$74,1) -> 12 | Z43: =RANK(W43,$W$25:$W$74,0) -> 2 | AA43: =RANK(X43,$X$25:$X$74,1) -> 25 | AB43: =AVERAGE(Y43:AA43) -> 13 | AC43: =RANK(AB43,$AB$25:$AB$74,1) -> 2 | AD43: =ROUNDUP(5*AC43/COUNT($AB$25:$AB$74),0) -> 1 | AE43: =IF(4_Screening!E43>0,4_Screening!C43/4_Screening!E43,"") -> 7.8910663 | AF43: =MIN(MAX(4_Screening!H43,PERCENTILE(4_Screening!$H$25:$H$74,0.05)),PERCENTILE(4_Screening!$H$25:$H$74,0.95)) -> 0.1189
... A67: =UPPER(TRIM(1_Lookups!G67)) -> NOVX | B67: =VALUE(TRIM(1_Lookups!I67)) -> 215.18 | C67: =B67*1_Lookups!J67 -> 602504 | D67: =IF(ISNUMBER(MATCH(A67,1_Lookups!$A$25:$A$54,0)),1,0) -> 1 | E67: =IFERROR(INDEX(1_Lookups!$C$25:$C$54,MATCH(A67,1_Lookups!$A$25:$A$54,0)),"Not Found") -> Energy | F67: =IF(COUNTIF(1_Lookups!$F$25:F67,1_Lookups!F67)>1,1,0) -> 1 | G67: =IF(EXACT(1_Lookups!G67,A67),0,1) -> 0 | H67: =IF(ISTEXT(1_Lookups!I67),1,0) -> 0 | M67: =3_Returns!B67/3_Returns!B66-1 -> -0.041117764 | N67: =3_Returns!C67/3_Returns!C66-1 -> -0.017359641 | O67: =3_Returns!D67/3_Returns!D66-1 -> -0.020853805 | P67: =MAX(3_Returns!$B$31:B67) -> 52.89 | Q67: =3_Returns!B67/P67-1 -> -0.091699754 | R67: =LN(3_Returns!B67/3_Returns!B66) -> -0.041987011 | S67: =M67-O67 -> -0.02026396 | T67: =IF(M67>O67,1,0) -> 0 | V67: =4_Screening!C67/4_Screening!D67 -> 1.765873 | W67: =4_Screening!E67/4_Screening!C67 -> -0.066292135 | X67: =4_Screening!F67/4_Screening!G67 -> 8.4637681 | Y67: =RANK(V67,$V$25:$V$74,1) -> 26 | Z67: =RANK(W67,$W$25:$W$74,0) -> 48 | AA67: =RANK(X67,$X$25:$X$74,1) -> 21 | AB67: =AVERAGE(Y67:AA67) -> 31.666667 | AC67: =RANK(AB67,$AB$25:$AB$74,1) -> 36 | AD67: =ROUNDUP(5*AC67/COUNT($AB$25:$AB$74),0) -> 4 | AE67: =IF(4_Screening!E67>0,4_Screening!C67/4_Screening!E67,"") | AF67: =MIN(MAX(4_Screening!H67,PERCENTILE(4_Screening!$H$25:$H$74,0.05)),PERCENTILE(4_Screening!$H$25:$H$74,0.95)) -> 0.1694
M68: =3_Returns!B68/3_Returns!B67-1 -> -0.01602831 | N68: =3_Returns!C68/3_Returns!C67-1 -> -0.020079283 | O68: =3_Returns!D68/3_Returns!D67-1 -> -0.014250764 | P68: =MAX(3_Returns!$B$31:B68) -> 52.89 | Q68: =3_Returns!B68/P68-1 -> -0.10625827 | R68: =LN(3_Returns!B68/3_Returns!B67) -> -0.016158152 | S68: =M68-O68 -> -0.0017775454 | T68: =IF(M68>O68,1,0) -> 0 | V68: =4_Screening!C68/4_Screening!D68 -> 0.80855783 | W68: =4_Screening!E68/4_Screening!C68 -> -0.051263001 | X68: =4_Screening!F68/4_Screening!G68 -> 6.7777778 | Y68: =RANK(V68,$V$25:$V$74,1) -> 4 | Z68: =RANK(W68,$W$25:$W$74,0) -> 46 | AA68: =RANK(X68,$X$25:$X$74,1) -> 7 | AB68: =AVERAGE(Y68:AA68) -> 19 | AC68: =RANK(AB68,$AB$25:$AB$74,1) -> 10 | AD68: =ROUNDUP(5*AC68/COUNT($AB$25:$AB$74),0) -> 1 | AE68: =IF(4_Screening!E68>0,4_Screening!C68/4_Screening!E68,"") | AF68: =MIN(MAX(4_Screening!H68,PERCENTILE(4_Screening!$H$25:$H$74,0.05)),PERCENTILE(4_Screening!$H$25:$H$74,0.95)) -> 0.2568
M69: =3_Returns!B69/3_Returns!B68-1 -> -0.013327692 | N69: =3_Returns!C69/3_Returns!C68-1 -> 0.007035441 | O69: =3_Returns!D69/3_Returns!D68-1 -> -0.0038455727 | P69: =MAX(3_Returns!$B$31:B69) -> 52.89 | Q69: =3_Returns!B69/P69-1 -> -0.11816979 | R69: =LN(3_Returns!B69/3_Returns!B68) -> -0.013417303 | S69: =M69-O69 -> -0.0094821193 | T69: =IF(M69>O69,1,0) -> 0 | V69: =4_Screening!C69/4_Screening!D69 -> 1.5919198 | W69: =4_Screening!E69/4_Screening!C69 -> 0.088333661 | X69: =4_Screening!F69/4_Screening!G69 -> 10.512821 | Y69: =RANK(V69,$V$25:$V$74,1) -> 24 | Z69: =RANK(W69,$W$25:$W$74,0) -> 10 | AA69: =RANK(X69,$X$25:$X$74,1) -> 32 | AB69: =AVERAGE(Y69:AA69) -> 22 | AC69: =RANK(AB69,$AB$25:$AB$74,1) -> 17 | AD69: =ROUNDUP(5*AC69/COUNT($AB$25:$AB$74),0) -> 2 | AE69: =IF(4_Screening!E69>0,4_Screening!C69/4_Screening!E69,"") -> 11.320713 | AF69: =MIN(MAX(4_Screening!H69,PERCENTILE(4_Screening!$H$25:$H$74,0.05)),PERCENTILE(4_Screening!$H$25:$H$74,0.95)) -> 0.1499
M70: =3_Returns!B70/3_Returns!B69-1 -> -0.014150943 | N70: =3_Returns!C70/3_Returns!C69-1 -> 0.0042791023 | O70: =3_Returns!D70/3_Returns!D69-1 -> 0.0018107561 | P70: =MAX(3_Returns!$B$31:B70) -> 52.89 | Q70: =3_Returns!B70/P70-1 -> -0.13064852 | R70: =LN(3_Returns!B70/3_Returns!B69) -> -0.014252023 | S70: =M70-O70 -> -0.015961699 | T70: =IF(M70>O70,1,0) -> 0 | V70: =4_Screening!C70/4_Screening!D70 -> 2.9019984 | W70: =4_Screening!E70/4_Screening!C70 -> 0.041128195 | X70: =4_Screening!F70/4_Screening!G70 -> 7.8341969 | Y70: =RANK(V70,$V$25:$V$74,1) -> 45 | Z70: =RANK(W70,$W$25:$W$74,0) -> 29 | AA70: =RANK(X70,$X$25:$X$74,1) -> 15 | AB70: =AVERAGE(Y70:AA70) -> 29.666667 | AC70: =RANK(AB70,$AB$25:$AB$74,1) -> 31 | AD70: =ROUNDUP(5*AC70/COUNT($AB$25:$AB$74),0) -> 4 | AE70: =IF(4_Screening!E70>0,4_Screening!C70/4_Screening!E70,"") -> 24.31422 | AF70: =MIN(MAX(4_Screening!H70,PERCENTILE(4_Screening!$H$25:$H$74,0.05)),PERCENTILE(4_Screening!$H$25:$H$74,0.95)) -> 0.2152
M71: =3_Returns!B71/3_Returns!B70-1 -> -0.017616355 | N71: =3_Returns!C71/3_Returns!C70-1 -> 0.0096521739 | O71: =3_Returns!D71/3_Returns!D70-1 -> -0.0015538677 | P71: =MAX(3_Returns!$B$31:B71) -> 52.89 | Q71: =3_Returns!B71/P71-1 -> -0.14596332 | R71: =LN(3_Returns!B71/3_Returns!B70) -> -0.01777337 | S71: =M71-O71 -> -0.016062487 | T71: =IF(M71>O71,1,0) -> 0 | V71: =4_Screening!C71/4_Screening!D71 -> 5.9388169 | W71: =4_Screening!E71/4_Screening!C71 -> -0.043528689 | X71: =4_Screening!F71/4_Screening!G71 -> 5.2067511 | Y71: =RANK(V71,$V$25:$V$74,1) -> 49 | Z71: =RANK(W71,$W$25:$W$74,0) -> 45 | AA71: =RANK(X71,$X$25:$X$74,1) -> 2 | AB71: =AVERAGE(Y71:AA71) -> 32 | AC71: =RANK(AB71,$AB$25:$AB$74,1) -> 39 | AD71: =ROUNDUP(5*AC71/COUNT($AB$25:$AB$74),0) -> 4 | AE71: =IF(4_Screening!E71>0,4_Screening!C71/4_Screening!E71,"") | AF71: =MIN(MAX(4_Screening!H71,PERCENTILE(4_Screening!$H$25:$H$74,0.05)),PERCENTILE(4_Screening!$H$25:$H$74,0.95)) -> 0.0581
M72: =3_Returns!B72/3_Returns!B71-1 -> -0.027009077 | N72: =3_Returns!C72/3_Returns!C71-1 -> -0.012057532 | O72: =3_Returns!D72/3_Returns!D71-1 -> -0.017562716 | P72: =MAX(3_Returns!$B$31:B72) -> 52.89 | Q72: =3_Returns!B72/P72-1 -> -0.16903006 | R72: =LN(3_Returns!B72/3_Returns!B71) -> -0.027380526 | S72: =M72-O72 -> -0.009446361 | T72: =IF(M72>O72,1,0) -> 0 | V72: =4_Screening!C72/4_Screening!D72 -> 2.7839228 | W72: =4_Screening!E72/4_Screening!C72 -> 0.078309078 | X72: =4_Screening!F72/4_Screening!G72 -> 6.1197605 | Y72: =RANK(V72,$V$25:$V$74,1) -> 43 | Z72: =RANK(W72,$W$25:$W$74,0) -> 13 | AA72: =RANK(X72,$X$25:$X$74,1) -> 6 | AB72: =AVERAGE(Y72:AA72) -> 20.666667 | AC72: =RANK(AB72,$AB$25:$AB$74,1) -> 15 | AD72: =ROUNDUP(5*AC72/COUNT($AB$25:$AB$74),0) -> 2 | AE72: =IF(4_Screening!E72>0,4_Screening!C72/4_Screening!E72,"") -> 12.769912 | AF72: =MIN(MAX(4_Screening!H72,PERCENTILE(4_Screening!$H$25:$H$74,0.05)),PERCENTILE(4_Screening!$H$25:$H$74,0.95)) -> 0.0325
M73: =3_Returns!B73/3_Returns!B72-1 -> -0.028441411 | N73: =3_Returns!C73/3_Returns!C72-1 -> 0.008281754 | O73: =3_Returns!D73/3_Returns!D72-1 -> -0.0043567772 | P73: =MAX(3_Returns!$B$31:B73) -> 52.89 | Q73: =3_Returns!B73/P73-1 -> -0.19266402 | R73: =LN(3_Returns!B73/3_Returns!B72) -> -0.028853704 | S73: =M73-O73 -> -0.024084633 | T73: =IF(M73>O73,1,0) -> 0 | V73: =4_Screening!C73/4_Screening!D73 -> 2.1449024 | W73: =4_Screening!E73/4_Screening!C73 -> 0.066140777 | X73: =4_Screening!F73/4_Screening!G73 -> 16.767857 | Y73: =RANK(V73,$V$25:$V$74,1) -> 32 | Z73: =RANK(W73,$W$25:$W$74,0) -> 19 | AA73: =RANK(X73,$X$25:$X$74,1) -> 49 | AB73: =AVERAGE(Y73:AA73) -> 33.333333 | AC73: =RANK(AB73,$AB$25:$AB$74,1) -> 41 | AD73: =ROUNDUP(5*AC73/COUNT($AB$25:$AB$74),0) -> 5 | AE73: =IF(4_Screening!E73>0,4_Screening!C73/4_Screening!E73,"") -> 15.119266 | AF73: =MIN(MAX(4_Screening!H73,PERCENTILE(4_Screening!$H$25:$H$74,0.05)),PERCENTILE(4_Screening!$H$25:$H$74,0.95)) -> 0.2299
M74: =3_Returns!B74/3_Returns!B73-1 -> -0.0067915691 | N74: =3_Returns!C74/3_Returns!C73-1 -> 0.014006571 | O74: =3_Returns!D74/3_Returns!D73-1 -> 0.0083640979 | P74: =MAX(3_Returns!$B$31:B74) -> 52.89 | Q74: =3_Returns!B74/P74-1 -> -0.1981471 | R74: =LN(3_Returns!B74/3_Returns!B73) -> -0.0068147367 | S74: =M74-O74 -> -0.015155667 | T74: =IF(M74>O74,1,0) -> 0 | V74: =4_Screening!C74/4_Screening!D74 -> 3.707019 | W74: =4_Screening!E74/4_Screening!C74 -> 0.06163281 | X74: =4_Screening!F74/4_Screening!G74 -> 5.3093923 | Y74: =RANK(V74,$V$25:$V$74,1) -> 47 | Z74: =RANK(W74,$W$25:$W$74,0) -> 22 | AA74: =RANK(X74,$X$25:$X$74,1) -> 3 | AB74: =AVERAGE(Y74:AA74) -> 24 | AC74: =RANK(AB74,$AB$25:$AB$74,1) -> 23 | AD74: =ROUNDUP(5*AC74/COUNT($AB$25:$AB$74),0) -> 3 | AE74: =IF(4_Screening!E74>0,4_Screening!C74/4_Screening!E74,"") -> 16.225124 | AF74: =MIN(MAX(4_Screening!H74,PERCENTILE(4_Screening!$H$25:$H$74,0.05)),PERCENTILE(4_Screening!$H$25:$H$74,0.95)) -> 0.2332
M75: =3_Returns!B75/3_Returns!B74-1 -> -0.013204433 | N75: =3_Returns!C75/3_Returns!C74-1 -> 0.010999318 | O75: =3_Returns!D75/3_Returns!D74-1 -> 0.0059212309 | P75: =MAX(3_Returns!$B$31:B75) -> 52.89 | Q75: =3_Returns!B75/P75-1 -> -0.20873511 | R75: =LN(3_Returns!B75/3_Returns!B74) -> -0.013292387 | S75: =M75-O75 -> -0.019125664 | T75: =IF(M75>O75,1,0) -> 0
M76: =3_Returns!B76/3_Returns!B75-1 -> 0.001911589 | N76: =3_Returns!C76/3_Returns!C75-1 -> 0.0045542717 | O76: =3_Returns!D76/3_Returns!D75-1 -> -0.00047763521 | P76: =MAX(3_Returns!$B$31:B76) -> 52.89 | Q76: =3_Returns!B76/P76-1 -> -0.20722254 | R76: =LN(3_Returns!B76/3_Returns!B75) -> 0.0019097642 | S76: =M76-O76 -> 0.0023892242 | T76: =IF(M76>O76,1,0) -> 1
M77: =3_Returns!B77/3_Returns!B76-1 -> -0.0050083472 | N77: =3_Returns!C77/3_Returns!C76-1 -> -0.0021828562 | O77: =3_Returns!D77/3_Returns!D76-1 -> -0.0086263911 | P77: =MAX(3_Returns!$B$31:B77) -> 52.89 | Q77: =3_Returns!B77/P77-1 -> -0.21119304 | R77: =LN(3_Returns!B77/3_Returns!B76) -> -0.0050209311 | S77: =M77-O77 -> 0.0036180438 | T77: =IF(M77>O77,1,0) -> 1
M78: =3_Returns!B78/3_Returns!B77-1 -> 0.033557047 | N78: =3_Returns!C78/3_Returns!C77-1 -> 0.0068994531 | O78: =3_Returns!D78/3_Returns!D77-1 -> 0.0066808188 | P78: =MAX(3_Returns!$B$31:B78) -> 52.89 | Q78: =3_Returns!B78/P78-1 -> -0.18472301 | R78: =LN(3_Returns!B78/3_Returns!B77) -> 0.033006296 | S78: =M78-O78 -> 0.026876228 | T78: =IF(M78>O78,1,0) -> 1
M79: =3_Returns!B79/3_Returns!B78-1 -> -0.025278293 | N79: =3_Returns!C79/3_Returns!C78-1 -> -0.0015876995 | O79: =3_Returns!D79/3_Returns!D78-1 -> -0.005517952 | P79: =MAX(3_Returns!$B$31:B79) -> 52.89 | Q79: =3_Returns!B79/P79-1 -> -0.20533182 | R79: =LN(3_Returns!B79/3_Returns!B78) -> -0.025603278 | S79: =M79-O79 -> -0.019760341 | T79: =IF(M79>O79,1,0) -> 0
M80: =3_Returns!B80/3_Returns!B79-1 -> -0.022127052 | N80: =3_Returns!C80/3_Returns!C79-1 -> 0.0014228323 | O80: =3_Returns!D80/3_Returns!D79-1 -> -0.011466914 | P80: =MAX(3_Returns!$B$31:B80) -> 52.89 | Q80: =3_Returns!B80/P80-1 -> -0.22291548 | R80: =LN(3_Returns!B80/3_Returns!B79) -> -0.022375528 | S80: =M80-O80 -> -0.010660138 | T80: =IF(M80>O80,1,0) -> 0
M81: =3_Returns!B81/3_Returns!B80-1 -> 0.002189781 | N81: =3_Returns!C81/3_Returns!C80-1 -> -0.010196406 | O81: =3_Returns!D81/3_Returns!D80-1 -> -0.0077696535 | P81: =MAX(3_Returns!$B$31:B81) -> 52.89 | Q81: =3_Returns!B81/P81-1 -> -0.22121384 | R81: =LN(3_Returns!B81/3_Returns!B80) -> 0.0021873869 | S81: =M81-O81 -> 0.0099594346 | T81: =IF(M81>O81,1,0) -> 1
M82: =3_Returns!B82/3_Returns!B81-1 -> 0.015537752 | N82: =3_Returns!C82/3_Returns!C81-1 -> 0.026935743 | O82: =3_Returns!D82/3_Returns!D81-1 -> 0.014916816 | P82: =MAX(3_Returns!$B$31:B82) -> 52.89 | Q82: =3_Returns!B82/P82-1 -> -0.20911325 | R82: =LN(3_Returns!B82/3_Returns!B81) -> 0.015418277 | S82: =M82-O82 -> 0.00062093615 | T82: =IF(M82>O82,1,0) -> 1
M83: =3_Returns!B83/3_Returns!B82-1 -> -0.00095625149 | N83: =3_Returns!C83/3_Returns!C82-1 -> 0.0009044565 | O83: =3_Returns!D83/3_Returns!D82-1 -> 0.0025363328 | P83: =MAX(3_Returns!$B$31:B83) -> 52.89 | Q83: =3_Returns!B83/P83-1 -> -0.20986954 | R83: =LN(3_Returns!B83/3_Returns!B82) -> -0.00095670899 | S83: =M83-O83 -> -0.0034925843 | T83: =IF(M83>O83,1,0) -> 0
M84: =3_Returns!B84/3_Returns!B83-1 -> 0.036133046 | N84: =3_Returns!C84/3_Returns!C83-1 -> 0.017826337 | O84: =3_Returns!D84/3_Returns!D83-1 -> 0.012001181 | P84: =MAX(3_Returns!$B$31:B84) -> 52.89 | Q84: =3_Returns!B84/P84-1 -> -0.18131972 | R84: =LN(3_Returns!B84/3_Returns!B83) -> 0.035495559 | S84: =M84-O84 -> 0.024131865 | T84: =IF(M84>O84,1,0) -> 1
M85: =3_Returns!B85/3_Returns!B84-1 -> -0.0094688222 | N85: =3_Returns!C85/3_Returns!C84-1 -> -0.0039548023 | O85: =3_Returns!D85/3_Returns!D84-1 -> -0.004513575 | P85: =MAX(3_Returns!$B$31:B85) -> 52.89 | Q85: =3_Returns!B85/P85-1 -> -0.18907166 | R85: =LN(3_Returns!B85/3_Returns!B84) -> -0.0095139365 | S85: =M85-O85 -> -0.0049552471 | T85: =IF(M85>O85,1,0) -> 0
M86: =3_Returns!B86/3_Returns!B85-1 -> -0.0025647004 | N86: =3_Returns!C86/3_Returns!C85-1 -> 0.0046187505 | O86: =3_Returns!D86/3_Returns!D85-1 -> 0.0097729915 | P86: =MAX(3_Returns!$B$31:B86) -> 52.89 | Q86: =3_Returns!B86/P86-1 -> -0.19115145 | R86: =LN(3_Returns!B86/3_Returns!B85) -> -0.0025679949 | S86: =M86-O86 -> -0.012337692 | T86: =IF(M86>O86,1,0) -> 0
... M534: =3_Returns!B534/3_Returns!B533-1 -> -0.0058015858 | N534: =3_Returns!C534/3_Returns!C533-1 -> 0.0044069745 | O534: =3_Returns!D534/3_Returns!D533-1 -> 0.0029237495 | P534: =MAX(3_Returns!$B$31:B534) -> 69.88 | Q534: =3_Returns!B534/P534-1 -> -0.26431025 | R534: =LN(3_Returns!B534/3_Returns!B533) -> -0.0058184803 | S534: =M534-O534 -> -0.0087253353 | T534: =IF(M534>O534,1,0) -> 0

Sheet 3_Returns
A1: 3 · Returns, Risk & Performance Math
A2: ~2 years of daily closes for two stocks and a benchmark. Build return columns to the right (E onward), then answer.
A4: # | B4: Task | H4: Your Answer | I4: Check | J4: Hint (functions to use)
A5: R1 | B5: Total (cumulative) return of Stock A over the full period. | I5: =IF(H5="","",IFERROR(IF(ISNUMBER('Answer Key'!$D$32),IF(ABS(H5-'Answer Key'!$D$32)<=MAX(0.0001,ABS('Answer Key'!$D$32)*0.001),"✓ Correct","✗ Try again"),IF(TRIM(H5)=TRIM('Answer Key'!$D$32),"✓ Correct","✗ Try again")),"✗ Try again")) | J5: last / first − 1
A6: R2 | B6: Total return of Stock B — compute it by compounding daily returns: PRODUCT(1+r)−1. Confirm it equals last/first−1. | I6: =IF(H6="","",IFERROR(IF(ISNUMBER('Answer Key'!$D$33),IF(ABS(H6-'Answer Key'!$D$33)<=MAX(0.0001,ABS('Answer Key'!$D$33)*0.001),"✓ Correct","✗ Try again"),IF(TRIM(H6)=TRIM('Answer Key'!$D$33),"✓ Correct","✗ Try again")),"✗ Try again")) | J6: Daily return column, then PRODUCT(1+range)-1 (Ctrl+Shift+Enter in old Excel)
A7: R3 | B7: Annualized return (CAGR) of Stock A. Use 252 trading days/yr and N = number of daily return observations. | I7: =IF(H7="","",IFERROR(IF(ISNUMBER('Answer Key'!$D$34),IF(ABS(H7-'Answer Key'!$D$34)<=MAX(0.0001,ABS('Answer Key'!$D$34)*0.001),"✓ Correct","✗ Try again"),IF(TRIM(H7)=TRIM('Answer Key'!$D$34),"✓ Correct","✗ Try again")),"✗ Try again")) | J7: (1+cum)^(252/N) − 1; N = COUNT(returns)
A8: R4 | B8: Annualized volatility of Stock A (sample std dev of daily returns). | I8: =IF(H8="","",IFERROR(IF(ISNUMBER('Answer Key'!$D$35),IF(ABS(H8-'Answer Key'!$D$35)<=MAX(0.0001,ABS('Answer Key'!$D$35)*0.001),"✓ Correct","✗ Try again"),IF(TRIM(H8)=TRIM('Answer Key'!$D$35),"✓ Correct","✗ Try again")),"✗ Try again")) | J8: STDEV.S × SQRT(252)
A9: R5 | B9: Sharpe ratio of Stock A = (AVERAGE(daily r)×252 − rf) ÷ annualized vol. | I9: =IF(H9="","",IFERROR(IF(ISNUMBER('Answer Key'!$D$36),IF(ABS(H9-'Answer Key'!$D$36)<=MAX(0.0001,ABS('Answer Key'!$D$36)*0.001),"✓ Correct","✗ Try again"),IF(TRIM(H9)=TRIM('Answer Key'!$D$36),"✓ Correct","✗ Try again")),"✗ Try again")) | J9: Arithmetic annualized mean; rf in G
A10: R6 | B10: Maximum drawdown of Stock A (peak-to-trough, as a negative %). | I10: =IF(H10="","",IFERROR(IF(ISNUMBER('Answer Key'!$D$37),IF(ABS(H10-'Answer Key'!$D$37)<=MAX(0.0001,ABS('Answer Key'!$D$37)*0.001),"✓ Correct","✗ Try again"),IF(TRIM(H10)=TRIM('Answer Key'!$D$37),"✓ Correct","✗ Try again")),"✗ Try again")) | J10: Running max: MAX($B$first:B2); DD = B/runmax − 1; MIN(DD)
A11: R7 | B11: On what date did Stock A hit its max-drawdown trough? | I11: =IF(H11="","",IFERROR(IF(ISNUMBER('Answer Key'!$D$38),IF(ABS(H11-'Answer Key'!$D$38)<=MAX(0.0001,ABS('Answer Key'!$D$38)*0.001),"✓ Correct","✗ Try again"),IF(TRIM(H11)=TRIM('Answer Key'!$D$38),"✓ Correct","✗ Try again")),"✗ Try again")) | J11: INDEX/MATCH on MIN of drawdown column
A12: R8 | B12: Beta of Stock A vs the Benchmark (daily returns). | I12: =IF(H12="","",IFERROR(IF(ISNUMBER('Answer Key'!$D$39),IF(ABS(H12-'Answer Key'!$D$39)<=MAX(0.0001,ABS('Answer Key'!$D$39)*0.001),"✓ Correct","✗ Try again"),IF(TRIM(H12)=TRIM('Answer Key'!$D$39),"✓ Correct","✗ Try again")),"✗ Try again")) | J12: SLOPE(stock, market) — y first!
A13: R9 | B13: Correlation of daily returns: Stock A vs Stock B. | I13: =IF(H13="","",IFERROR(IF(ISNUMBER('Answer Key'!$D$40),IF(ABS(H13-'Answer Key'!$D$40)<=MAX(0.0001,ABS('Answer Key'!$D$40)*0.001),"✓ Correct","✗ Try again"),IF(TRIM(H13)=TRIM('Answer Key'!$D$40),"✓ Correct","✗ Try again")),"✗ Try again")) | J13: CORREL
A14: R10 | B14: Annualized tracking error of Stock A vs Benchmark (std dev of daily active return × √252). | I14: =IF(H14="","",IFERROR(IF(ISNUMBER('Answer Key'!$D$41),IF(ABS(H14-'Answer Key'!$D$41)<=MAX(0.0001,ABS('Answer Key'!$D$41)*0.001),"✓ Correct","✗ Try again"),IF(TRIM(H14)=TRIM('Answer Key'!$D$41),"✓ Correct","✗ Try again")),"✗ Try again")) | J14: Helper: rA − rM
A15: R11 | B15: Information ratio of Stock A = (AVERAGE(active r)×252) ÷ tracking error. | I15: =IF(H15="","",IFERROR(IF(ISNUMBER('Answer Key'!$D$42),IF(ABS(H15-'Answer Key'!$D$42)<=MAX(0.0001,ABS('Answer Key'!$D$42)*0.001),"✓ Correct","✗ Try again"),IF(TRIM(H15)=TRIM('Answer Key'!$D$42),"✓ Correct","✗ Try again")),"✗ Try again")) | J15: Active return / TE
A16: R12 | B16: Sum of Stock A's daily LOG returns. (Should equal LN(last/first) — why?) | I16: =IF(H16="","",IFERROR(IF(ISNUMBER('Answer Key'!$D$43),IF(ABS(H16-'Answer Key'!$D$43)<=MAX(0.0001,ABS('Answer Key'!$D$43)*0.001),"✓ Correct","✗ Try again"),IF(TRIM(H16)=TRIM('Answer Key'!$D$43),"✓ Correct","✗ Try again")),"✗ Try again")) | J16: LN(Pt/Pt−1)
A17: R13 | B17: Best single-day return for Stock B. | I17: =IF(H17="","",IFERROR(IF(ISNUMBER('Answer Key'!$D$44),IF(ABS(H17-'Answer Key'!$D$44)<=MAX(0.0001,ABS('Answer Key'!$D$44)*0.001),"✓ Correct","✗ Try again"),IF(TRIM(H17)=TRIM('Answer Key'!$D$44),"✓ Correct","✗ Try again")),"✗ Try again")) | J17: MAX of return column
A18: R14 | B18: Date of Stock B's best day. | I18: =IF(H18="","",IFERROR(IF(ISNUMBER('Answer Key'!$D$45),IF(ABS(H18-'Answer Key'!$D$45)<=MAX(0.0001,ABS('Answer Key'!$D$45)*0.001),"✓ Correct","✗ Try again"),IF(TRIM(H18)=TRIM('Answer Key'!$D$45),"✓ Correct","✗ Try again")),"✗ Try again")) | J18: INDEX/MATCH — align date and return rows carefully!
A19: R15 | B19: On how many days did Stock A's return beat the Benchmark's? | I19: =IF(H19="","",IFERROR(IF(ISNUMBER('Answer Key'!$D$46),IF(ABS(H19-'Answer Key'!$D$46)<=MAX(0.0001,ABS('Answer Key'!$D$46)*0.001),"✓ Correct","✗ Try again"),IF(TRIM(H19)=TRIM('Answer Key'!$D$46),"✓ Correct","✗ Try again")),"✗ Try again")) | J19: SUMPRODUCT(--(rA>rM))
A20: R16 | B20: Calendar-year 2025 return of Stock A (last close on/before 2025-12-31 ÷ last close on/before 2024-12-31 − 1). | I20: =IF(H20="","",IFERROR(IF(ISNUMBER('Answer Key'!$D$47),IF(ABS(H20-'Answer Key'!$D$47)<=MAX(0.0001,ABS('Answer Key'!$D$47)*0.001),"✓ Correct","✗ Try again"),IF(TRIM(H20)=TRIM('Answer Key'!$D$47),"✓ Correct","✗ Try again")),"✗ Try again")) | J20: MATCH(date, dates, 1) approximate match
A21: R17 | B21: March 2026 monthly return of Stock A (last close on/before 3/31/2026 ÷ last close on/before 2/28/2026 − 1). | I21: =IF(H21="","",IFERROR(IF(ISNUMBER('Answer Key'!$D$48),IF(ABS(H21-'Answer Key'!$D$48)<=MAX(0.0001,ABS('Answer Key'!$D$48)*0.001),"✓ Correct","✗ Try again"),IF(TRIM(H21)=TRIM('Answer Key'!$D$48),"✓ Correct","✗ Try again")),"✗ Try again")) | J21: Same approximate-match pattern; EOMONTH helps
A22: R18 | B22: Most recent 21-day annualized volatility of Stock A (last 21 daily returns). | I22: =IF(H22="","",IFERROR(IF(ISNUMBER('Answer Key'!$D$49),IF(ABS(H22-'Answer Key'!$D$49)<=MAX(0.0001,ABS('Answer Key'!$D$49)*0.001),"✓ Correct","✗ Try again"),IF(TRIM(H22)=TRIM('Answer Key'!$D$49),"✓ Correct","✗ Try again")),"✗ Try again")) | J22: STDEV of last 21 returns × √252; OFFSET optional
A23: R19 | B23: Sortino ratio of Stock A = (AVERAGE(r)×252 − rf) ÷ downside dev, where downside dev = SQRT(SUMPRODUCT((r<0)×r²)/COUNT(r)) × √252. | I23: =IF(H23="","",IFERROR(IF(ISNUMBER('Answer Key'!$D$50),IF(ABS(H23-'Answer Key'!$D$50)<=MAX(0.0001,ABS('Answer Key'!$D$50)*0.001),"✓ Correct","✗ Try again"),IF(TRIM(H23)=TRIM('Answer Key'!$D$50),"✓ Correct","✗ Try again")),"✗ Try again")) | J23: SUMPRODUCT((r<0)*r^2)
G24: Score: | H24: =COUNTIF(I5:I23,"✓ Correct")&" / 19" -> 0 / 19
A27: DATA
A28: Risk-free rate is in G (annual). Use 252 trading days per year. Build helper columns in E onward (green = workspace).
A30: Date | B30: Stock A | C30: Stock B | D30: Benchmark | F30: Risk-free (annual) | G30: 0.04
A31: 45566 | B31: 48.2 | C31: 121.55 | D31: 5712.4
A32: 45567 | B32: 48.71 | C32: 121.25 | D32: 5750.58
A33: 45568 | B33: 49.28 | C33: 120.91 | D33: 5754.61
A34: 45569 | B34: 50.01 | C34: 124.17 | D34: 5828.14
A35: 45572 | B35: 50.78 | C35: 124.96 | D35: 5854.95
A36: 45573 | B36: 50.03 | C36: 125.47 | D36: 5879.95
A37: 45574 | B37: 51.01 | C37: 128.53 | D37: 5906.11
A38: 45575 | B38: 49.75 | C38: 127.69 | D38: 5821.27
A39: 45576 | B39: 50.07 | C39: 126.6 | D39: 5813.46
A40: 45579 | B40: 50.06 | C40: 127.29 | D40: 5800.11
A41: 45580 | B41: 48.58 | C41: 126.09 | D41: 5814.08
A42: 45581 | B42: 47.35 | C42: 126.27 | D42: 5736.31
... A534: 46269 | B534: 51.41 | C534: 157.26 | D534: 6973.73

Sheet 4_Screening
A1: 4 · Ranking, Percentiles & Value Screens
A2: 50-stock universe. Build valuation multiples, rank, z-score, composite value score, quintiles, winsorize.
A4: # | B4: Task | H4: Your Answer | I4: Check | J4: Hint (functions to use)
A5: S1 | B5: P/B of SLTN. | I5: =IF(H5="","",IFERROR(IF(ISNUMBER('Answer Key'!$D$51),IF(ABS(H5-'Answer Key'!$D$51)<=MAX(0.0001,ABS('Answer Key'!$D$51)*0.001),"✓ Correct","✗ Try again"),IF(TRIM(H5)=TRIM('Answer Key'!$D$51),"✓ Correct","✗ Try again")),"✗ Try again")) | J5: Price / BVPS
A6: S2 | B6: Rank of SLTN on P/B where 1 = cheapest (lowest P/B). | I6: =IF(H6="","",IFERROR(IF(ISNUMBER('Answer Key'!$D$52),IF(ABS(H6-'Answer Key'!$D$52)<=MAX(0.0001,ABS('Answer Key'!$D$52)*0.001),"✓ Correct","✗ Try again"),IF(TRIM(H6)=TRIM('Answer Key'!$D$52),"✓ Correct","✗ Try again")),"✗ Try again")) | J6: RANK.EQ(x, range, 1) — 1 = ascending
A7: S3 | B7: Percentile rank of SLTN's P/B within the universe (0–1). | I7: =IF(H7="","",IFERROR(IF(ISNUMBER('Answer Key'!$D$53),IF(ABS(H7-'Answer Key'!$D$53)<=MAX(0.0001,ABS('Answer Key'!$D$53)*0.001),"✓ Correct","✗ Try again"),IF(TRIM(H7)=TRIM('Answer Key'!$D$53),"✓ Correct","✗ Try again")),"✗ Try again")) | J7: PERCENTRANK.INC
A8: S4 | B8: How many stocks have negative EPS? | I8: =IF(H8="","",IFERROR(IF(ISNUMBER('Answer Key'!$D$54),IF(ABS(H8-'Answer Key'!$D$54)<=MAX(0.0001,ABS('Answer Key'!$D$54)*0.001),"✓ Correct","✗ Try again"),IF(TRIM(H8)=TRIM('Answer Key'!$D$54),"✓ Correct","✗ Try again")),"✗ Try again")) | J8: COUNTIF "<0"
A9: S5 | B9: 80th percentile P/E among POSITIVE-EPS stocks only. | I9: =IF(H9="","",IFERROR(IF(ISNUMBER('Answer Key'!$D$55),IF(ABS(H9-'Answer Key'!$D$55)<=MAX(0.0001,ABS('Answer Key'!$D$55)*0.001),"✓ Correct","✗ Try again"),IF(TRIM(H9)=TRIM('Answer Key'!$D$55),"✓ Correct","✗ Try again")),"✗ Try again")) | J9: Helper =IF(EPS>0,Price/EPS,"") then PERCENTILE.INC
A10: S6 | B10: Median EV/EBITDA of the universe. | I10: =IF(H10="","",IFERROR(IF(ISNUMBER('Answer Key'!$D$56),IF(ABS(H10-'Answer Key'!$D$56)<=MAX(0.0001,ABS('Answer Key'!$D$56)*0.001),"✓ Correct","✗ Try again"),IF(TRIM(H10)=TRIM('Answer Key'!$D$56),"✓ Correct","✗ Try again")),"✗ Try again")) | J10: MEDIAN
A11: S7 | B11: First quartile (25th percentile) EV/EBITDA. | I11: =IF(H11="","",IFERROR(IF(ISNUMBER('Answer Key'!$D$57),IF(ABS(H11-'Answer Key'!$D$57)<=MAX(0.0001,ABS('Answer Key'!$D$57)*0.001),"✓ Correct","✗ Try again"),IF(TRIM(H11)=TRIM('Answer Key'!$D$57),"✓ Correct","✗ Try again")),"✗ Try again")) | J11: QUARTILE.INC(range,1)
A12: S8 | B12: Z-score of SLTN's ROE vs the universe. | I12: =IF(H12="","",IFERROR(IF(ISNUMBER('Answer Key'!$D$58),IF(ABS(H12-'Answer Key'!$D$58)<=MAX(0.0001,ABS('Answer Key'!$D$58)*0.001),"✓ Correct","✗ Try again"),IF(TRIM(H12)=TRIM('Answer Key'!$D$58),"✓ Correct","✗ Try again")),"✗ Try again")) | J12: STANDARDIZE(x, AVERAGE, STDEV.S)
A13: S9 | B13: Composite value score = average of three ranks: P/B (ascending), EARNINGS YIELD E/P (DESCENDING, so loss-makers rank worst), EV/EBITDA (ascending). Use RANK.EQ. Which ticker has the BEST (lowest) composite? Why rank E/P instead of P/E? | I13: =IF(H13="","",IFERROR(IF(ISNUMBER('Answer Key'!$D$59),IF(ABS(H13-'Answer Key'!$D$59)<=MAX(0.0001,ABS('Answer Key'!$D$59)*0.001),"✓ Correct","✗ Try again"),IF(TRIM(H13)=TRIM('Answer Key'!$D$59),"✓ Correct","✗ Try again")),"✗ Try again")) | J13: Three RANK.EQ helper columns, AVERAGE, then INDEX/MATCH on MIN
A14: S10 | B14: Quintile of HZLN on composite: Quintile = ROUNDUP(5 × RANK.EQ(composite, all composites, 1) / COUNT, 0). 1 = cheapest. | I14: =IF(H14="","",IFERROR(IF(ISNUMBER('Answer Key'!$D$60),IF(ABS(H14-'Answer Key'!$D$60)<=MAX(0.0001,ABS('Answer Key'!$D$60)*0.001),"✓ Correct","✗ Try again"),IF(TRIM(H14)=TRIM('Answer Key'!$D$60),"✓ Correct","✗ Try again")),"✗ Try again")) | J14: RANK.EQ then ROUNDUP
A15: S11 | B15: Average ROE of Quintile 1 (cheapest) stocks. | I15: =IF(H15="","",IFERROR(IF(ISNUMBER('Answer Key'!$D$61),IF(ABS(H15-'Answer Key'!$D$61)<=MAX(0.0001,ABS('Answer Key'!$D$61)*0.001),"✓ Correct","✗ Try again"),IF(TRIM(H15)=TRIM('Answer Key'!$D$61),"✓ Correct","✗ Try again")),"✗ Try again")) | J15: AVERAGEIFS on your quintile column
A16: S12 | B16: Winsorized mean ROE: cap each ROE at the 5th and 95th percentiles (PERCENTILE.INC), then average. | I16: =IF(H16="","",IFERROR(IF(ISNUMBER('Answer Key'!$D$62),IF(ABS(H16-'Answer Key'!$D$62)<=MAX(0.0001,ABS('Answer Key'!$D$62)*0.001),"✓ Correct","✗ Try again"),IF(TRIM(H16)=TRIM('Answer Key'!$D$62),"✓ Correct","✗ Try again")),"✗ Try again")) | J16: =MIN(MAX(x,P5),P95) helper column
A17: S13 | B17: Sector-relative P/B of SLTN: its P/B ÷ the AVERAGE P/B of its own sector. | I17: =IF(H17="","",IFERROR(IF(ISNUMBER('Answer Key'!$D$63),IF(ABS(H17-'Answer Key'!$D$63)<=MAX(0.0001,ABS('Answer Key'!$D$63)*0.001),"✓ Correct","✗ Try again"),IF(TRIM(H17)=TRIM('Answer Key'!$D$63),"✓ Correct","✗ Try again")),"✗ Try again")) | J17: AVERAGEIFS on helper P/B column
G18: Score: | H18: =COUNTIF(I5:I17,"✓ Correct")&" / 13" -> 0 / 13
A21: DATA
A22: Per-share data in $; EV and EBITDA in $bn. Note: some EPS are negative. Build helper columns in J onward (green = workspace).
A24: Ticker | B24: Sector | C24: Price | D24: BVPS | E24: EPS | F24: EV ($bn) | G24: EBITDA ($bn) | H24: ROE
A25: LMRA | B25: Technology | C25: 206.36 | D25: 133.29 | E25: 20.79 | F25: 4.49 | G25: 0.65 | H25: 0.1456
A26: MRDN | B26: Health Care | C26: 219.39 | D26: 100.88 | E26: 27.76 | F26: 16.29 | G26: 1.41 | H26: 0.1727
A27: NOVX | B27: Consumer | C27: 75.63 | D27: 52.53 | E27: 7.81 | F27: 7.01 | G27: 0.81 | H27: 0.1747
A28: OKRA | B28: Industrials | C28: 149.08 | D28: 199.45 | E28: 8.24 | F28: 60.11 | G28: 8.85 | H28: 1.25
A29: PLMT | B29: Industrials | C29: 94.95 | D29: 30.26 | E29: 6.68 | F29: 30.69 | G29: 2.46 | H29: 0.1075
A30: QRSN | B30: Energy | C30: 110.34 | D30: 114.26 | E30: 7.41 | F30: 5.46 | G30: 0.47 | H30: 0.1399
A31: RDGE | B31: Technology | C31: 109.69 | D31: 40.05 | E31: -7.5 | F31: 18.7 | G31: 2.55 | H31: 0.186
A32: SLTN | B32: Health Care | C32: 72.1 | D32: 30.75 | E32: 4.9 | F32: 16.27 | G32: 1.2 | H32: 0.0849
A33: TRVO | B33: Energy | C33: 18.91 | D33: 28.03 | E33: 0.54 | F33: 62.11 | G33: 7.64 | H33: 0.0486
A34: ULMN | B34: Health Care | C34: 172.14 | D34: 166.52 | E34: -4.16 | F34: 5.75 | G34: 0.71 | H34: 0.2002
A35: VSTR | B35: Financials | C35: 157.67 | D35: 117.8 | E35: 5.22 | F35: 2.54 | G35: 0.27 | H35: 0.2074
A36: WNDL | B36: Consumer | C36: 187.32 | D36: 168.22 | E36: -3.94 | F36: 12.07 | G36: 1.74 | H36: 0.1559
... A74: IVRY | B74: Financials | C74: 130.45 | D74: 35.19 | E74: 8.04 | F74: 9.61 | G74: 1.81 | H74: 0.2332

Sheet 5_Regression
A1: 5 · Statistics & Regression
A2: 60 months of excess returns for one stock and three factors (Mkt-RF, SMB, HML). Single- and multi-factor regressions.
A4: # | B4: Task | H4: Your Answer | I4: Check | J4: Hint (functions to use)
A5: G1 | B5: Correlation between the stock's excess return and Mkt-RF. | I5: =IF(H5="","",IFERROR(IF(ISNUMBER('Answer Key'!$D$64),IF(ABS(H5-'Answer Key'!$D$64)<=MAX(0.0001,ABS('Answer Key'!$D$64)*0.001),"✓ Correct","✗ Try again"),IF(TRIM(H5)=TRIM('Answer Key'!$D$64),"✓ Correct","✗ Try again")),"✗ Try again")) | J5: CORREL
A6: G2 | B6: Single-factor (CAPM) beta. | I6: =IF(H6="","",IFERROR(IF(ISNUMBER('Answer Key'!$D$65),IF(ABS(H6-'Answer Key'!$D$65)<=MAX(0.0001,ABS('Answer Key'!$D$65)*0.001),"✓ Correct","✗ Try again"),IF(TRIM(H6)=TRIM('Answer Key'!$D$65),"✓ Correct","✗ Try again")),"✗ Try again")) | J6: SLOPE(known_y, known_x)
A7: G3 | B7: Single-factor monthly alpha (intercept). | I7: =IF(H7="","",IFERROR(IF(ISNUMBER('Answer Key'!$D$66),IF(ABS(H7-'Answer Key'!$D$66)<=MAX(0.0001,ABS('Answer Key'!$D$66)*0.001),"✓ Correct","✗ Try again"),IF(TRIM(H7)=TRIM('Answer Key'!$D$66),"✓ Correct","✗ Try again")),"✗ Try again")) | J7: INTERCEPT
A8: G4 | B8: Annualized alpha (simple: monthly × 12). | I8: =IF(H8="","",IFERROR(IF(ISNUMBER('Answer Key'!$D$67),IF(ABS(H8-'Answer Key'!$D$67)<=MAX(0.0001,ABS('Answer Key'!$D$67)*0.001),"✓ Correct","✗ Try again"),IF(TRIM(H8)=TRIM('Answer Key'!$D$67),"✓ Correct","✗ Try again")),"✗ Try again")) | J8: ×12
A9: G5 | B9: R² of the single-factor regression. | I9: =IF(H9="","",IFERROR(IF(ISNUMBER('Answer Key'!$D$68),IF(ABS(H9-'Answer Key'!$D$68)<=MAX(0.0001,ABS('Answer Key'!$D$68)*0.001),"✓ Correct","✗ Try again"),IF(TRIM(H9)=TRIM('Answer Key'!$D$68),"✓ Correct","✗ Try again")),"✗ Try again")) | J9: RSQ (= CORREL²)
A10: G6 | B10: SAMPLE covariance between stock and Mkt-RF. Then confirm beta = COVARIANCE.S / VAR.S. | I10: =IF(H10="","",IFERROR(IF(ISNUMBER('Answer Key'!$D$69),IF(ABS(H10-'Answer Key'!$D$69)<=MAX(0.0001,ABS('Answer Key'!$D$69)*0.001),"✓ Correct","✗ Try again"),IF(TRIM(H10)=TRIM('Answer Key'!$D$69),"✓ Correct","✗ Try again")),"✗ Try again")) | J10: COVARIANCE.S (COVAR is population!)
A11: G7 | B11: 3-factor regression (Mkt-RF, SMB, HML): market beta. | I11: =IF(H11="","",IFERROR(IF(ISNUMBER('Answer Key'!$D$70),IF(ABS(H11-'Answer Key'!$D$70)<=MAX(0.0001,ABS('Answer Key'!$D$70)*0.001),"✓ Correct","✗ Try again"),IF(TRIM(H11)=TRIM('Answer Key'!$D$70),"✓ Correct","✗ Try again")),"✗ Try again")) | J11: =INDEX(LINEST(y, C:E), 1, 3)
A12: G8 | B12: 3-factor: SMB loading. | I12: =IF(H12="","",IFERROR(IF(ISNUMBER('Answer Key'!$D$71),IF(ABS(H12-'Answer Key'!$D$71)<=MAX(0.0001,ABS('Answer Key'!$D$71)*0.001),"✓ Correct","✗ Try again"),IF(TRIM(H12)=TRIM('Answer Key'!$D$71),"✓ Correct","✗ Try again")),"✗ Try again")) | J12: INDEX(LINEST(...),1,2)
A13: G9 | B13: 3-factor: HML loading. Is this stock value- or growth-tilted? | I13: =IF(H13="","",IFERROR(IF(ISNUMBER('Answer Key'!$D$72),IF(ABS(H13-'Answer Key'!$D$72)<=MAX(0.0001,ABS('Answer Key'!$D$72)*0.001),"✓ Correct","✗ Try again"),IF(TRIM(H13)=TRIM('Answer Key'!$D$72),"✓ Correct","✗ Try again")),"✗ Try again")) | J13: INDEX(LINEST(...),1,1)
A14: G10 | B14: 3-factor: monthly intercept (alpha). | I14: =IF(H14="","",IFERROR(IF(ISNUMBER('Answer Key'!$D$73),IF(ABS(H14-'Answer Key'!$D$73)<=MAX(0.0001,ABS('Answer Key'!$D$73)*0.001),"✓ Correct","✗ Try again"),IF(TRIM(H14)=TRIM('Answer Key'!$D$73),"✓ Correct","✗ Try again")),"✗ Try again")) | J14: INDEX(LINEST(...),1,4)
A15: G11 | B15: 3-factor R². | I15: =IF(H15="","",IFERROR(IF(ISNUMBER('Answer Key'!$D$74),IF(ABS(H15-'Answer Key'!$D$74)<=MAX(0.0001,ABS('Answer Key'!$D$74)*0.001),"✓ Correct","✗ Try again"),IF(TRIM(H15)=TRIM('Answer Key'!$D$74),"✓ Correct","✗ Try again")),"✗ Try again")) | J15: LINEST with stats=TRUE; R² is row 3, col 1
A16: G12 | B16: t-stat of the single-factor beta = beta ÷ its standard error. | I16: =IF(H16="","",IFERROR(IF(ISNUMBER('Answer Key'!$D$75),IF(ABS(H16-'Answer Key'!$D$75)<=MAX(0.0001,ABS('Answer Key'!$D$75)*0.001),"✓ Correct","✗ Try again"),IF(TRIM(H16)=TRIM('Answer Key'!$D$75),"✓ Correct","✗ Try again")),"✗ Try again")) | J16: SE of slope is row 2, col 1 of LINEST(...,TRUE,TRUE)
A17: G13 | B17: Annualized Sharpe of the stock's excess returns (monthly mean ÷ monthly std × √12). | I17: =IF(H17="","",IFERROR(IF(ISNUMBER('Answer Key'!$D$76),IF(ABS(H17-'Answer Key'!$D$76)<=MAX(0.0001,ABS('Answer Key'!$D$76)*0.001),"✓ Correct","✗ Try again"),IF(TRIM(H17)=TRIM('Answer Key'!$D$76),"✓ Correct","✗ Try again")),"✗ Try again")) | J17: AVERAGE / STDEV.S × SQRT(12)
G18: Score: | H18: =COUNTIF(I5:I17,"✓ Correct")&" / 13" -> 0 / 13
A21: DATA
A22: Monthly returns (decimals). LINEST returns coefficients in REVERSE order of the X columns, intercept last.
A24: Month | B24: Stock Excess Ret | C24: Mkt-RF | D24: SMB | E24: HML
A25: 44500 | B25: 0.04228 | C25: 0.02998 | D25: -0.02442 | E25: -0.01825
A26: 44530 | B26: 0.0371 | C26: 0.01717 | D26: 0.0149 | E26: 0.03698
A27: 44561 | B27: 0.00942 | C27: 0.01448 | D27: -0.02879 | E27: 0.04333
A28: 44592 | B28: -0.01439 | C28: -0.02397 | D28: 0.05806 | E28: 0.04694
A29: 44620 | B29: 0.03415 | C29: 0.07624 | D29: -0.01654 | E29: -0.02268
A30: 44651 | B30: 0.10391 | C30: 0.03665 | D30: 0.06069 | E30: 0.06246
A31: 44681 | B31: 0.02034 | C31: 0.02977 | D31: -0.03182 | E31: 0.00549
A32: 44712 | B32: 0.06785 | C32: 0.02393 | D32: 0.01918 | E32: -0.00561
A33: 44742 | B33: 0.02846 | C33: 0.05416 | D33: -0.03499 | E33: -0.00491
A34: 44773 | B34: 0.06429 | C34: 0.02973 | D34: -0.03923 | E34: 0.02005
A35: 44804 | B35: 0.06077 | C35: 0.04054 | D35: 0.00579 | E35: 0.00353
A36: 44834 | B36: -0.04403 | C36: -0.0456 | D36: 0.02133 | E36: -0.00331
... A84: 46295 | B84: 0.01761 | C84: -0.0154 | D84: 0.05747 | E84: -0.02015

Sheet 6_Valuation
A1: 6 · Valuation & Accounting Mechanics
A2: Meridian Consumer Brands (fictional). $mm except per-share. Compute multiples, margins, CAGR, implied value, and a mini-DCF.
A4: # | B4: Task | H4: Your Answer | I4: Check | J4: Hint (functions to use)
A5: V1 | B5: Market capitalization ($mm), using 2025 diluted shares. | I5: =IF(H5="","",IFERROR(IF(ISNUMBER('Answer Key'!$D$77),IF(ABS(H5-'Answer Key'!$D$77)<=MAX(0.0001,ABS('Answer Key'!$D$77)*0.001),"✓ Correct","✗ Try again"),IF(TRIM(H5)=TRIM('Answer Key'!$D$77),"✓ Correct","✗ Try again")),"✗ Try again")) | J5: Price × shares
A6: V2 | B6: Enterprise value ($mm) = Mkt cap + Debt − Cash + Minority Interest + Preferred. | I6: =IF(H6="","",IFERROR(IF(ISNUMBER('Answer Key'!$D$78),IF(ABS(H6-'Answer Key'!$D$78)<=MAX(0.0001,ABS('Answer Key'!$D$78)*0.001),"✓ Correct","✗ Try again"),IF(TRIM(H6)=TRIM('Answer Key'!$D$78),"✓ Correct","✗ Try again")),"✗ Try again")) | J6: Add all non-common claims, subtract cash
A7: V3 | B7: 2025 EBITDA ($mm). | I7: =IF(H7="","",IFERROR(IF(ISNUMBER('Answer Key'!$D$79),IF(ABS(H7-'Answer Key'!$D$79)<=MAX(0.0001,ABS('Answer Key'!$D$79)*0.001),"✓ Correct","✗ Try again"),IF(TRIM(H7)=TRIM('Answer Key'!$D$79),"✓ Correct","✗ Try again")),"✗ Try again")) | J7: Rev − COGS − SG&A
A8: V4 | B8: EV / 2025 EBITDA. | I8: =IF(H8="","",IFERROR(IF(ISNUMBER('Answer Key'!$D$80),IF(ABS(H8-'Answer Key'!$D$80)<=MAX(0.0001,ABS('Answer Key'!$D$80)*0.001),"✓ Correct","✗ Try again"),IF(TRIM(H8)=TRIM('Answer Key'!$D$80),"✓ Correct","✗ Try again")),"✗ Try again"))
A9: V5 | B9: 2025 Net Income ($mm). | I9: =IF(H9="","",IFERROR(IF(ISNUMBER('Answer Key'!$D$81),IF(ABS(H9-'Answer Key'!$D$81)<=MAX(0.0001,ABS('Answer Key'!$D$81)*0.001),"✓ Correct","✗ Try again"),IF(TRIM(H9)=TRIM('Answer Key'!$D$81),"✓ Correct","✗ Try again")),"✗ Try again")) | J9: EBITDA − D&A − Interest − Tax
A10: V6 | B10: P/E on 2025 earnings (Mkt cap ÷ Net income). | I10: =IF(H10="","",IFERROR(IF(ISNUMBER('Answer Key'!$D$82),IF(ABS(H10-'Answer Key'!$D$82)<=MAX(0.0001,ABS('Answer Key'!$D$82)*0.001),"✓ Correct","✗ Try again"),IF(TRIM(H10)=TRIM('Answer Key'!$D$82),"✓ Correct","✗ Try again")),"✗ Try again")) | J10: Or Price ÷ EPS
A11: V7 | B11: 2025 gross margin. | I11: =IF(H11="","",IFERROR(IF(ISNUMBER('Answer Key'!$D$83),IF(ABS(H11-'Answer Key'!$D$83)<=MAX(0.0001,ABS('Answer Key'!$D$83)*0.001),"✓ Correct","✗ Try again"),IF(TRIM(H11)=TRIM('Answer Key'!$D$83),"✓ Correct","✗ Try again")),"✗ Try again")) | J11: (Rev − COGS)/Rev
A12: V8 | B12: 2025 EBITDA margin. | I12: =IF(H12="","",IFERROR(IF(ISNUMBER('Answer Key'!$D$84),IF(ABS(H12-'Answer Key'!$D$84)<=MAX(0.0001,ABS('Answer Key'!$D$84)*0.001),"✓ Correct","✗ Try again"),IF(TRIM(H12)=TRIM('Answer Key'!$D$84),"✓ Correct","✗ Try again")),"✗ Try again")) | J12: EBITDA/Rev
A13: V9 | B13: Revenue CAGR 2021→2025 (4 periods, not 5!). | I13: =IF(H13="","",IFERROR(IF(ISNUMBER('Answer Key'!$D$85),IF(ABS(H13-'Answer Key'!$D$85)<=MAX(0.0001,ABS('Answer Key'!$D$85)*0.001),"✓ Correct","✗ Try again"),IF(TRIM(H13)=TRIM('Answer Key'!$D$85),"✓ Correct","✗ Try again")),"✗ Try again")) | J13: (end/start)^(1/n) − 1 or RRI
A14: V10 | B14: 2025 free-cash-flow yield = (CFO − Capex) ÷ Mkt cap. | I14: =IF(H14="","",IFERROR(IF(ISNUMBER('Answer Key'!$D$86),IF(ABS(H14-'Answer Key'!$D$86)<=MAX(0.0001,ABS('Answer Key'!$D$86)*0.001),"✓ Correct","✗ Try again"),IF(TRIM(H14)=TRIM('Answer Key'!$D$86),"✓ Correct","✗ Try again")),"✗ Try again"))
A15: V11 | B15: Net debt / 2025 EBITDA (net debt = Debt − Cash). | I15: =IF(H15="","",IFERROR(IF(ISNUMBER('Answer Key'!$D$87),IF(ABS(H15-'Answer Key'!$D$87)<=MAX(0.0001,ABS('Answer Key'!$D$87)*0.001),"✓ Correct","✗ Try again"),IF(TRIM(H15)=TRIM('Answer Key'!$D$87),"✓ Correct","✗ Try again")),"✗ Try again"))
A16: V12 | B16: 2025 dividend payout ratio. | I16: =IF(H16="","",IFERROR(IF(ISNUMBER('Answer Key'!$D$88),IF(ABS(H16-'Answer Key'!$D$88)<=MAX(0.0001,ABS('Answer Key'!$D$88)*0.001),"✓ Correct","✗ Try again"),IF(TRIM(H16)=TRIM('Answer Key'!$D$88),"✓ Correct","✗ Try again")),"✗ Try again")) | J16: Dividends ÷ Net income
A17: V13 | B17: 2025 interest coverage (EBIT ÷ Interest). | I17: =IF(H17="","",IFERROR(IF(ISNUMBER('Answer Key'!$D$89),IF(ABS(H17-'Answer Key'!$D$89)<=MAX(0.0001,ABS('Answer Key'!$D$89)*0.001),"✓ Correct","✗ Try again"),IF(TRIM(H17)=TRIM('Answer Key'!$D$89),"✓ Correct","✗ Try again")),"✗ Try again"))
A18: V14 | B18: Implied share price if re-rated to the peer EV/EBITDA multiple. (Bridge EV → equity, ÷ shares.) | I18: =IF(H18="","",IFERROR(IF(ISNUMBER('Answer Key'!$D$90),IF(ABS(H18-'Answer Key'!$D$90)<=MAX(0.0001,ABS('Answer Key'!$D$90)*0.001),"✓ Correct","✗ Try again"),IF(TRIM(H18)=TRIM('Answer Key'!$D$90),"✓ Correct","✗ Try again")),"✗ Try again")) | J18: (Multiple × EBITDA − Debt + Cash − MI − Pref) / Shares
A19: V15 | B19: Upside/(downside) to that implied price vs current price. | I19: =IF(H19="","",IFERROR(IF(ISNUMBER('Answer Key'!$D$91),IF(ABS(H19-'Answer Key'!$D$91)<=MAX(0.0001,ABS('Answer Key'!$D$91)*0.001),"✓ Correct","✗ Try again"),IF(TRIM(H19)=TRIM('Answer Key'!$D$91),"✓ Correct","✗ Try again")),"✗ Try again")) | J19: Implied / Current − 1
A20: V16 | B20: Mini-DCF implied share price: FCF₀ = 2025 CFO − Capex. Grow FCF at the 5-yr growth rate for years 1–5, discount at WACC (end-of-year). Terminal value at year 5 = FCF₅×(1+g)/(WACC−g), discounted 5 years. EV → equity (same bridge) → ÷ 2025 shares. | I20: =IF(H20="","",IFERROR(IF(ISNUMBER('Answer Key'!$D$92),IF(ABS(H20-'Answer Key'!$D$92)<=MAX(0.0001,ABS('Answer Key'!$D$92)*0.001),"✓ Correct","✗ Try again"),IF(TRIM(H20)=TRIM('Answer Key'!$D$92),"✓ Correct","✗ Try again")),"✗ Try again")) | J20: Lay out years 1–5 in a row; NPV(WACC, FCF1:FCF5) + TV/(1+WACC)^5
G21: Score: | H21: =COUNTIF(I5:I20,"✓ Correct")&" / 16" -> 0 / 16
A24: DATA
A25: SG&A excludes D&A. EBITDA = Revenue − COGS − SG&A. EBIT = EBITDA − D&A. Net Income = EBIT − Interest − Tax. Capex shown as positive.
A27: ($mm) | B27: 2021 | C27: 2022 | D27: 2023 | E27: 2024 | F27: 2025
A28: Revenue | B28: 4000 | C28: 4288 | D28: 4536.7 | E28: 4827 | F28: 5073.2
A29: COGS | B29: 2360 | C29: 2508.5 | D29: 2640.4 | E29: 2790 | F29: 2917.1
A30: SG&A (ex-D&A) | B30: 884 | C30: 939.1 | D30: 989 | E30: 1042.6 | F30: 1085.7
A31: D&A | B31: 164 | C31: 175.8 | D31: 186 | E31: 197.9 | F31: 208
A32: Interest Expense | B32: 62 | C32: 64.5 | D32: 70.2 | E32: 68.8 | F32: 66
A33: Income Tax | B33: 124.5 | C33: 141 | D33: 153 | E33: 171 | F33: 187.2
A34: Cash from Operations | B34: 550.6 | C34: 637.5 | D34: 730.2 | E34: 715.5 | F34: 818.3
A35: Capex | B35: 180 | C35: 193 | D35: 204.2 | E35: 217.2 | F35: 228.3
A36: Dividends Paid | B36: 154.1 | C36: 174.5 | D36: 189.3 | E36: 211.5 | F36: 231.5
A37: Diluted Shares (mm) | B37: 262 | C37: 259.4 | D37: 256.1 | E37: 253.8 | F37: 250.2
A39: Market Data & Assumptions
A40: Share Price ($) | B40: 33.4
A41: Total Debt | B41: 1520
A42: Cash | B42: 410
A43: Minority Interest | B43: 48
A44: Preferred Stock | B44: 100
A45: Peer EV/EBITDA | B45: 8 | C45: Practice assumptions (blue/yellow = inputs)
A46: WACC | B46: 0.09
A47: FCF growth, yrs 1–5 | B47: 0.05
A48: Terminal growth | B48: 0.025

Sheet Cheat_Sheet
A1: Cheat Sheet — Formulas & Shortcuts
A2: Skim this 10 minutes before the call.
A4: LOOKUPS
A5: XLOOKUP | B5: =XLOOKUP(val, lookup_rng, return_rng, [if_not_found], [match_mode]) | C5: match_mode −1 = exact or next smaller (dates!). Looks left fine.
A6: INDEX / MATCH | B6: =INDEX(return_rng, MATCH(val, lookup_rng, 0)) | C6: 0 = exact. 1 = largest ≤ val (sorted asc). Works in every Excel version.
A7: Two-way lookup | B7: =INDEX(grid, MATCH(row_val,row_hdr,0), MATCH(col_val,col_hdr,0)) | C7: Row first, column second.
A8: IFERROR / IFNA | B8: =IFERROR(formula, "Not Found") | C8: IFNA is safer — only traps not-found errors, so it will not hide real bugs.
A9: Cleaning | B9: TRIM, UPPER, CLEAN, VALUE, TEXT, EXACT | C9: Text-numbers: VALUE(TRIM(x)) or multiply by 1. "a"="A" is TRUE — use EXACT for case.
A10: Text split | B10: =LEFT(x,FIND(" ",x)-1) =TEXTBEFORE(x," ") | C10: MID(x,start,len), RIGHT, LEN, SUBSTITUTE.
A11: CONDITIONAL MATH
A12: SUMIFS / COUNTIFS / AVERAGEIFS | B12: =SUMIFS(sum_rng, crit_rng1, crit1, crit_rng2, ">"&cell) | C12: Sum range FIRST in SUMIFS (last in SUMIF). Criteria are AND.
A13: OR logic | B13: =SUM(SUMIFS(sum,crit,{"A","B"})) | C13: Or just add two SUMIFS.
A14: MAXIFS / MINIFS | B14: =MAXIFS(max_rng, crit_rng, crit) | C14: Excel 2019+.
A15: SUMPRODUCT | B15: =SUMPRODUCT((rng="X")*weights*values)/SUMIFS(weights,rng,"X") | C15: Weighted averages, multi-condition counts with --(cond).
A16: RETURNS & RISK
A17: Simple return | B17: =P1/P0-1 | C17: Cumulative: =PRODUCT(1+r)-1 or last/first−1.
A18: Log return | B18: =LN(P1/P0) | C18: Additive over time; sum = LN(last/first).
A19: CAGR | B19: =(end/start)^(1/years)-1 or =RRI(n,start,end) | C19: Daily: ^(252/N). Count periods, not data points.
A20: Ann. vol | B20: =STDEV.S(daily r)*SQRT(252) | C20: Monthly: ×SQRT(12).
A21: Sharpe | B21: =(AVERAGE(r)*252-rf)/ann_vol | C21: Sortino: downside dev in denominator.
A22: Max drawdown | B22: Runmax: =MAX($B$2:B2); DD: =B2/runmax-1; =MIN(DD) | C22: Anchor the TOP of the range only.
A23: Beta | B23: =SLOPE(stock_r, market_r) | C23: = COVARIANCE.S/VAR.S. y comes FIRST.
A24: Tracking error / IR | B24: TE=STDEV.S(rA−rB)*SQRT(252); IR=AVG(active)*252/TE
A25: RANKING & STATS
A26: RANK.EQ | B26: =RANK.EQ(x, rng, 1) | C26: 1 = ascending (smallest = 1). 0/omitted = descending.
A27: PERCENTRANK.INC | B27: =PERCENTRANK.INC(rng, x) | C27: Returns 0–1.
A28: PERCENTILE / QUARTILE | B28: =PERCENTILE.INC(rng,0.8) =QUARTILE.INC(rng,1) | C28: Text/blank cells are ignored.
A29: Z-score | B29: =STANDARDIZE(x, AVERAGE(rng), STDEV.S(rng))
A30: Winsorize | B30: =MIN(MAX(x,P5),P95) | C30: Kill outlier influence before averaging.
A31: CORREL / RSQ | B31: =CORREL(a,b) =RSQ(y,x) | C31: RSQ = CORREL² for one factor.
A32: LINEST | B32: =INDEX(LINEST(y, X_multi, TRUE, TRUE), row, col) | C32: Coefs REVERSED vs X columns; intercept last. Row 2 = SEs, row 3 col 1 = R².
A33: VALUATION
A34: EV | B34: =MktCap + Debt − Cash + Minority Interest + Preferred | C34: Equity value = EV − those claims.
A35: NPV | B35: =NPV(rate, CF1:CFn) | C35: Assumes first cash flow is at END of period 1. Don't include t=0.
A36: Terminal value | B36: =FCF_n*(1+g)/(WACC−g) | C36: Then discount /(1+WACC)^n.
A37: SHORTCUTS (Win / Mac)
A38: Anchor ($) | B38: F4 / Cmd+T | C38: Cycles $A$1 → A$1 → $A1 → A1.
A39: Jump / select to edge | B39: Ctrl+Arrow, Ctrl+Shift+Arrow / Cmd+Arrow
A40: Fill down / right | B40: Ctrl+D / Ctrl+R | C40: Or double-click the fill handle.
A41: AutoSum | B41: Alt+= / Cmd+Shift+T
A42: Table / Filter | B42: Ctrl+T, Ctrl+Shift+L
A43: Paste special values | B43: Ctrl+Alt+V, V / Ctrl+Cmd+V
A44: Trace precedents | B44: Ctrl+[ | C44: Great for narrating your logic on a screen share.
A45: Show formulas | B45: Ctrl+`
A46: Format cells | B46: Ctrl+1 / Cmd+1 | C46: Ctrl+Shift+% = percent.

Sheet Answer Key
A1: Answer Key — no peeking until you've tried
A2: Live formulas. 'Model solution' shows the Excel a candidate would type (may use XLOOKUP etc.).
A4: Tab | B4: # | C4: Task | D4: Answer | E4: Model solution / talking point
A5: 1_Lookups | B5: L1 | C5: What sector is FENX in? (Use the reference table.) | D5: =INDEX(1_Lookups!$C$25:$C$54,MATCH("FENX",1_Lookups!$A$25:$A$54,0)) -> Energy | E5: =XLOOKUP("FENX",A:A,C:C) or =INDEX(C:C,MATCH("FENX",A:A,0))
A6: 1_Lookups | B6: L2 | C6: Reverse lookup: what is the ticker for 'Harbor Logistics'? (Ticker column is to the LEFT of company name.) | D6: =INDEX(1_Lookups!$A$25:$A$54,MATCH("Harbor Logistics",1_Lookups!$B$25:$B$54,0)) -> HRBR | E6: =INDEX(A:A,MATCH("Harbor Logistics",B:B,0)) — VLOOKUP fails here because the return column is left of the lookup column.
A7: 1_Lookups | B7: L3 | C7: How many rows in the raw blotter have a 'dirty' ticker (leading/trailing spaces or lowercase)? | D7: =SUM(Key_Work!$G$25:$G$67) -> 13 | E7: =SUMPRODUCT(--NOT(EXACT(G_rng,UPPER(TRIM(G_rng))))) — note "abc"="ABC" is TRUE in Excel, so you need EXACT for case.
A8: 1_Lookups | B8: L4 | C8: How many prices in the raw blotter are stored as TEXT rather than numbers? | D8: =SUM(Key_Work!$H$25:$H$67) -> 10 | E8: =SUMPRODUCT(--ISTEXT(I_rng)) — text numbers left-align and silently break SUM/AVERAGE.
A9: 1_Lookups | B9: L5 | C9: Total market value (price × shares) across ALL blotter rows, after converting text prices to numbers. Include duplicates and unknown tickers. | D9: =SUM(Key_Work!$C$25:$C$67) -> 14901707 | E9: Helper: =VALUE(TRIM(I2))*J2, then SUM. Plain =SUMPRODUCT(I:I,J:J) treats text as 0 and understates.
A10: 1_Lookups | B10: L6 | C10: After cleaning tickers (TRIM + UPPER), how many blotter rows have a ticker NOT in the reference table? | D10: =COUNTA(1_Lookups!$F$25:$F$67)-SUM(Key_Work!$D$25:$D$67) -> 3 | E10: Helper: =ISNA(MATCH(UPPER(TRIM(G2)),RefTickers,0)), then count TRUEs.
A11: 1_Lookups | B11: L7 | C11: Total market value of blotter rows in the Energy sector (look up each row's sector first; all rows incl. duplicates). | D11: =SUMIFS(Key_Work!$C$25:$C$67,Key_Work!$E$25:$E$67,"Energy") -> 4264708 | E11: Helper sector: =IFERROR(XLOOKUP(UPPER(TRIM(G2)),A:A,C:C),"Not Found"); then =SUMIFS(MV,Sector,"Energy").
A12: 1_Lookups | B12: L8 | C12: How many rows are duplicate copies (same Trade ID appearing again after its first occurrence)? | D12: =SUM(Key_Work!$F$25:$F$67) -> 3 | E12: Helper: =COUNTIF($F$first:F2,F2)>1, count TRUEs. (Or Data → Remove Duplicates and compare row counts.)
A13: 1_Lookups | B13: L9 | C13: Two-way lookup: MRDN's closing price on 2026-06-30 from the month-end grid. | D13: =INDEX(1_Lookups!$N$25:$Y$54,MATCH("MRDN",1_Lookups!$M$25:$M$54,0),MATCH(DATE(2026,6,30),1_Lookups!$N$24:$Y$24,0)) -> 137.64 | E13: =INDEX(N:Y, MATCH("MRDN",M:M,0), MATCH(DATE(2026,6,30),N$hdr:Y$hdr,0)) or nested XLOOKUP.
A14: 1_Lookups | B14: L10 | C14: Extract the plain ticker from the BBG ID of trade T1017 (e.g. 'ABC US Equity' → 'ABC'). | D14: =LEFT(INDEX(1_Lookups!$K$25:$K$67,MATCH("T1017",1_Lookups!$F$25:$F$67,0)),FIND(" ",INDEX(1_Lookups!$K$25:$K$67,MATCH("T1017",1_Lookups!$F$25:$F$67,0)))-1) -> BRKN | E14: =LEFT(K2,FIND(" ",K2)-1) or =TEXTBEFORE(K2," ")
A15: 1_Lookups | B15: L11 | C15: What is the company name for trade T1033? (Its raw ticker is dirty — clean it inside the lookup.) | D15: =INDEX(1_Lookups!$B$25:$B$54,MATCH(UPPER(TRIM(INDEX(1_Lookups!$G$25:$G$67,MATCH("T1033",1_Lookups!$F$25:$F$67,0)))),1_Lookups!$A$25:$A$54,0)) -> Lamarra Foods | E15: =XLOOKUP(UPPER(TRIM(G_T1033)),A:A,B:B)
A16: 1_Lookups | B16: L12 | C16: Approximate match: for trade T1025, return its ticker's most recent month-end close ON OR BEFORE the trade date. | D16: =INDEX(1_Lookups!$N$25:$Y$54,MATCH(UPPER(TRIM(INDEX(1_Lookups!$G$25:$G$67,MATCH("T1025",1_Lookups!$F$25:$F$67,0)))),1_Lookups!$M$25:$M$54,0),MATCH(INDEX(1_Lookups!$H$25:$H$67,MATCH("T1025",1_Lookups!$F$25:$F$67,0)),1_Lookups!$N$24:$Y$24,1)) -> 53.52 | E16: =INDEX(grid, MATCH(ticker,M:M,0), MATCH(trade_date, hdr, 1)) — match_type 1 = largest value ≤ lookup (XLOOKUP: match_mode -1).
A17: 1_Lookups | B17: L13 | C17: Total market value EXCLUDING duplicate rows AND rows with tickers not in the reference table. | D17: =SUMPRODUCT(Key_Work!$C$25:$C$67,1-Key_Work!$F$25:$F$67,Key_Work!$D$25:$D$67) -> 12598904 | E17: =SUMIFS(MV, DupFlag, FALSE, InRef, TRUE) — this is the 'clean' number you'd actually report.
A18: 2_Aggregation | B18: A1 | C18: Total market cap of the Financials sector ($bn). | D18: =SUMIFS(2_Aggregation!$D$26:$D$85,2_Aggregation!$B$26:$B$85,"Financials") -> 203.62 | E18: =SUMIFS(D:D,B:B,"Financials")
A19: 2_Aggregation | B19: A2 | C19: How many Technology stocks returned more than 10% over the past year? | D19: =COUNTIFS(2_Aggregation!$B$26:$B$85,"Technology",2_Aggregation!$H$26:$H$85,">0.1") -> 4 | E19: =COUNTIFS(B:B,"Technology",H:H,">"&0.1)
A20: 2_Aggregation | B20: A3 | C20: Average P/E of US Industrials (ignore NM). | D20: =AVERAGEIFS(2_Aggregation!$F$26:$F$85,2_Aggregation!$B$26:$B$85,"Industrials",2_Aggregation!$C$26:$C$85,"US") -> 11.45 | E20: =AVERAGEIFS(F:F,B:B,"Industrials",C:C,"US")
A21: 2_Aggregation | B21: A4 | C21: Market-cap-weighted average 1Y return of Health Care. | D21: =SUMPRODUCT((2_Aggregation!$B$26:$B$85="Health Care")*2_Aggregation!$D$26:$D$85*2_Aggregation!$H$26:$H$85)/SUMIFS(2_Aggregation!$D$26:$D$85,2_Aggregation!$B$26:$B$85,"Health Care") -> 0.097558664 | E21: =SUMPRODUCT((B:B="Health Care")*D:D*H:H)/SUMIFS(D:D,B:B,"Health Care") — weighted ≠ simple AVERAGEIFS.
A22: 2_Aggregation | B22: A5 | C22: Highest dividend yield in Energy. | D22: =_xlfn.MAXIFS(2_Aggregation!$G$26:$G$85,2_Aggregation!$B$26:$B$85,"Energy") -> 0.0355 | E22: =MAXIFS(G:G,B:B,"Energy")
A23: 2_Aggregation | B23: A6 | C23: Lowest P/E among UK stocks (ignore NM). | D23: =_xlfn.MINIFS(2_Aggregation!$F$26:$F$85,2_Aggregation!$C$26:$C$85,"UK") -> 6.8 | E23: =MINIFS(F:F,C:C,"UK")
A24: 2_Aggregation | B24: A7 | C24: How many stocks have a market cap between $10bn and $50bn inclusive? | D24: =COUNTIFS(2_Aggregation!$D$26:$D$85,">=10",2_Aggregation!$D$26:$D$85,"<=50") -> 48 | E24: =COUNTIFS(D:D,">=10",D:D,"<=50")
A25: 2_Aggregation | B25: A8 | C25: Combined market cap of Technology OR Health Care. | D25: =SUMIFS(2_Aggregation!$D$26:$D$85,2_Aggregation!$B$26:$B$85,"Technology")+SUMIFS(2_Aggregation!$D$26:$D$85,2_Aggregation!$B$26:$B$85,"Health Care") -> 413.63 | E25: =SUM(SUMIFS(D:D,B:B,{"Technology","Health Care"})) — SUMIFS criteria are AND; OR needs addition.
A26: 2_Aggregation | B26: A9 | C26: Which sector has the largest total market cap? (text) | D26: =INDEX(Key_Work!$J$5:$J$10,MATCH(MAX(Key_Work!$K$5:$K$10),Key_Work!$K$5:$K$10,0)) -> Consumer | E26: Sector list + SUMIFS column, then =INDEX(sectors,MATCH(MAX(totals),totals,0)). (Or a pivot sorted descending.)
A27: 2_Aggregation | B27: A10 | C27: AGGREGATE P/E of Energy = total cap ÷ total net income (include loss-makers). Why is this better than averaging P/Es? | D27: =SUMIFS(2_Aggregation!$D$26:$D$85,2_Aggregation!$B$26:$B$85,"Energy")/SUMIFS(2_Aggregation!$E$26:$E$85,2_Aggregation!$B$26:$B$85,"Energy") -> 12.642313 | E27: =SUMIFS(cap,sector,"Energy")/SUMIFS(NI,sector,"Energy"). Average P/E is distorted by tiny-earnings outliers and drops losses; aggregate P/E is the harmonic, cap-weighted view.
A28: 2_Aggregation | B28: A11 | C28: PIVOT: Build a PivotTable of average 1Y Return by Sector (rows) × Country (cols). What is Japan / Technology? | D28: =AVERAGEIFS(2_Aggregation!$H$26:$H$85,2_Aggregation!$C$26:$C$85,"Japan",2_Aggregation!$B$26:$B$85,"Technology") -> -0.049066667 | E28: Pivot: Rows=Sector, Columns=Country, Values=1Y Return (Summarize by Average). Cross-check: =AVERAGEIFS(H:H,C:C,"Japan",B:B,"Technology")
A29: 2_Aggregation | B29: A12 | C29: What % of total universe market cap is rated 'Buy'? | D29: =SUMIFS(2_Aggregation!$D$26:$D$85,2_Aggregation!$I$26:$I$85,"Buy")/SUM(2_Aggregation!$D$26:$D$85) -> 0.4341209 | E29: =SUMIFS(D:D,I:I,"Buy")/SUM(D:D)
A30: 2_Aggregation | B30: A13 | C30: How many stocks have a P/E of 'NM'? | D30: =COUNTIF(2_Aggregation!$F$26:$F$85,"NM") -> 10 | E30: =COUNTIF(F:F,"NM")
A31: 2_Aggregation | B31: A14 | C31: Average 1Y return of the 10 largest stocks by market cap. | D31: =AVERAGEIFS(2_Aggregation!$H$26:$H$85,2_Aggregation!$D$26:$D$85,">="&LARGE(2_Aggregation!$D$26:$D$85,10)) -> 0.08663 | E31: =AVERAGEIFS(H:H,D:D,">="&LARGE(D:D,10))
A32: 3_Returns | B32: R1 | C32: Total (cumulative) return of Stock A over the full period. | D32: =3_Returns!B534/3_Returns!B31-1 -> 0.06659751 | E32: =B_last/B_first-1
A33: 3_Returns | B33: R2 | C33: Total return of Stock B — compute it by compounding daily returns: PRODUCT(1+r)−1. Confirm it equals last/first−1. | D33: =3_Returns!C534/3_Returns!C31-1 -> 0.29378856 | E33: =PRODUCT(1+F3:F505)-1 — identical to price ratio; good sanity check.
A34: 3_Returns | B34: R3 | C34: Annualized return (CAGR) of Stock A. Use 252 trading days/yr and N = number of daily return observations. | D34: =(3_Returns!B534/3_Returns!B31)^(252/COUNT(Key_Work!$M$32:$M$534))-1 -> 0.032828269 | E34: =(1+R1)^(252/COUNT(rA))-1 (N = 503)
A35: 3_Returns | B35: R4 | C35: Annualized volatility of Stock A (sample std dev of daily returns). | D35: =STDEV(Key_Work!$M$32:$M$534)*SQRT(252) -> 0.28500028 | E35: =STDEV.S(rA)*SQRT(252)
A36: 3_Returns | B36: R5 | C36: Sharpe ratio of Stock A = (AVERAGE(daily r)×252 − rf) ÷ annualized vol. | D36: =(AVERAGE(Key_Work!$M$32:$M$534)*252-3_Returns!$G$30)/(STDEV(Key_Work!$M$32:$M$534)*SQRT(252)) -> 0.11488782 | E36: =(AVERAGE(rA)*252-$G$rf)/R4
A37: 3_Returns | B37: R6 | C37: Maximum drawdown of Stock A (peak-to-trough, as a negative %). | D37: =MIN(Key_Work!$Q$31:$Q$534) -> -0.39109903 | E37: Helper E: =MAX($B$first:B2); F: =B2/E2-1; answer =MIN(F:F)
A38: 3_Returns | B38: R7 | C38: On what date did Stock A hit its max-drawdown trough? | D38: =INDEX(3_Returns!$A$31:$A$534,MATCH(MIN(Key_Work!$Q$31:$Q$534),Key_Work!$Q$31:$Q$534,0)) -> 46162 | E38: =INDEX(A:A,MATCH(MIN(DD),DD,0))
A39: 3_Returns | B39: R8 | C39: Beta of Stock A vs the Benchmark (daily returns). | D39: =SLOPE(Key_Work!$M$32:$M$534,Key_Work!$O$32:$O$534) -> 1.2160546 | E39: =SLOPE(rA,rM) — equivalently COVARIANCE.S(rA,rM)/VAR.S(rM)
A40: 3_Returns | B40: R9 | C40: Correlation of daily returns: Stock A vs Stock B. | D40: =CORREL(Key_Work!$M$32:$M$534,Key_Work!$N$32:$N$534) -> 0.38803164 | E40: =CORREL(rA,rB)
A41: 3_Returns | B41: R10 | C41: Annualized tracking error of Stock A vs Benchmark (std dev of daily active return × √252). | D41: =STDEV(Key_Work!$S$32:$S$534)*SQRT(252) -> 0.21529472 | E41: =STDEV.S(rA-rM)*SQRT(252)
A42: 3_Returns | B42: R11 | C42: Information ratio of Stock A = (AVERAGE(active r)×252) ÷ tracking error. | D42: =AVERAGE(Key_Work!$S$32:$S$534)*252/(STDEV(Key_Work!$S$32:$S$534)*SQRT(252)) -> -0.18286905 | E42: =AVERAGE(rA-rM)*252/R10
A43: 3_Returns | B43: R12 | C43: Sum of Stock A's daily LOG returns. (Should equal LN(last/first) — why?) | D43: =SUM(Key_Work!$R$32:$R$534) -> 0.064473685 | E43: =SUM(LN(B3/B2)...) = LN(B_last/B_first). Log returns are additive across time; simple returns are additive across assets.
A44: 3_Returns | B44: R13 | C44: Best single-day return for Stock B. | D44: =MAX(Key_Work!$N$32:$N$534) -> 0.034174407 | E44: =MAX(rB)
A45: 3_Returns | B45: R14 | C45: Date of Stock B's best day. | D45: =INDEX(3_Returns!$A$32:$A$534,MATCH(MAX(Key_Work!$N$32:$N$534),Key_Work!$N$32:$N$534,0)) -> 46142 | E45: =INDEX(A3:A505,MATCH(MAX(rB),rB,0)) — off-by-one is the classic error.
A46: 3_Returns | B46: R15 | C46: On how many days did Stock A's return beat the Benchmark's? | D46: =SUM(Key_Work!$T$32:$T$534) -> 242 | E46: =SUMPRODUCT(--(rA>rM))
A47: 3_Returns | B47: R16 | C47: Calendar-year 2025 return of Stock A (last close on/before 2025-12-31 ÷ last close on/before 2024-12-31 − 1). | D47: =INDEX(3_Returns!$B$31:$B$534,MATCH(DATE(2025,12,31),3_Returns!$A$31:$A$534,1))/INDEX(3_Returns!$B$31:$B$534,MATCH(DATE(2024,12,31),3_Returns!$A$31:$A$534,1))-1 -> 0.32174522 | E47: =INDEX(B:B,MATCH(DATE(2025,12,31),A:A,1))/INDEX(B:B,MATCH(DATE(2024,12,31),A:A,1))-1 (or XLOOKUP match_mode -1)
A48: 3_Returns | B48: R17 | C48: March 2026 monthly return of Stock A (last close on/before 3/31/2026 ÷ last close on/before 2/28/2026 − 1). | D48: =INDEX(3_Returns!$B$31:$B$534,MATCH(DATE(2026,3,31),3_Returns!$A$31:$A$534,1))/INDEX(3_Returns!$B$31:$B$534,MATCH(DATE(2026,2,28),3_Returns!$A$31:$A$534,1))-1 -> -0.17799114 | E48: =XLOOKUP(EOMONTH(...),A:A,B:B,,-1)/XLOOKUP(EOMONTH(...,-1),A:A,B:B,,-1)-1
A49: 3_Returns | B49: R18 | C49: Most recent 21-day annualized volatility of Stock A (last 21 daily returns). | D49: =STDEV(Key_Work!$M$514:$M$534)*SQRT(252) -> 0.23862461 | E49: =STDEV.S(last 21 returns)*SQRT(252)
A50: 3_Returns | B50: R19 | C50: Sortino ratio of Stock A = (AVERAGE(r)×252 − rf) ÷ downside dev, where downside dev = SQRT(SUMPRODUCT((r<0)×r²)/COUNT(r)) × √252. | D50: =(AVERAGE(Key_Work!$M$32:$M$534)*252-3_Returns!$G$30)/(SQRT(SUMPRODUCT((Key_Work!$M$32:$M$534<0)*Key_Work!$M$32:$M$534^2)/COUNT(Key_Work!$M$32:$M$534))*SQRT(252)) -> 0.17041195 | E50: =(AVERAGE(rA)*252-rf)/(SQRT(SUMPRODUCT((rA<0)*rA^2)/COUNT(rA))*SQRT(252))
A51: 4_Screening | B51: S1 | C51: P/B of SLTN. | D51: =INDEX(Key_Work!$V$25:$V$74,MATCH("SLTN",4_Screening!$A$25:$A$74,0)) -> 2.3447154 | E51: Helper P/B = C2/D2, then look up.
A52: 4_Screening | B52: S2 | C52: Rank of SLTN on P/B where 1 = cheapest (lowest P/B). | D52: =INDEX(Key_Work!$Y$25:$Y$74,MATCH("SLTN",4_Screening!$A$25:$A$74,0)) -> 39 | E52: =RANK.EQ(PB_x, PB_range, 1)
A53: 4_Screening | B53: S3 | C53: Percentile rank of SLTN's P/B within the universe (0–1). | D53: =PERCENTRANK(Key_Work!$V$25:$V$74,INDEX(Key_Work!$V$25:$V$74,MATCH("SLTN",4_Screening!$A$25:$A$74,0))) -> 0.776 | E53: =PERCENTRANK.INC(PB_range, PB_x)
A54: 4_Screening | B54: S4 | C54: How many stocks have negative EPS? | D54: =COUNTIF(4_Screening!$E$25:$E$74,"<0") -> 10 | E54: =COUNTIF(E:E,"<0")
A55: 4_Screening | B55: S5 | C55: 80th percentile P/E among POSITIVE-EPS stocks only. | D55: =PERCENTILE(Key_Work!$AE$25:$AE$74,0.8) -> 28.079368 | E55: Helper: =IF(E2>0,C2/E2,""); =PERCENTILE.INC(helper,0.8). Blank text is ignored.
A56: 4_Screening | B56: S6 | C56: Median EV/EBITDA of the universe. | D56: =MEDIAN(Key_Work!$X$25:$X$74) -> 9.1478842 | E56: =MEDIAN(EV/EBITDA helper)
A57: 4_Screening | B57: S7 | C57: First quartile (25th percentile) EV/EBITDA. | D57: =QUARTILE(Key_Work!$X$25:$X$74,1) -> 7.7556082 | E57: =QUARTILE.INC(range,1)
A58: 4_Screening | B58: S8 | C58: Z-score of SLTN's ROE vs the universe. | D58: =STANDARDIZE(INDEX(4_Screening!$H$25:$H$74,MATCH("SLTN",4_Screening!$A$25:$A$74,0)),AVERAGE(4_Screening!$H$25:$H$74),STDEV(4_Screening!$H$25:$H$74)) -> -0.35462246 | E58: =STANDARDIZE(H_x,AVERAGE(H:H),STDEV.S(H:H))
A59: 4_Screening | B59: S9 | C59: Composite value score = average of three ranks: P/B (ascending), EARNINGS YIELD E/P (DESCENDING, so loss-makers rank worst), EV/EBITDA (ascending). Use RANK.EQ. Which ticker has the BEST (lowest) composite? Why rank E/P instead of P/E? | D59: =INDEX(4_Screening!$A$25:$A$74,MATCH(MIN(Key_Work!$AB$25:$AB$74),Key_Work!$AB$25:$AB$74,0)) -> LMRA | E59: Ranking P/E ascending would put negative-P/E (loss-making) stocks at the top as 'cheapest'. E/P ranked descending is monotonic in value and handles losses correctly.
A60: 4_Screening | B60: S10 | C60: Quintile of HZLN on composite: Quintile = ROUNDUP(5 × RANK.EQ(composite, all composites, 1) / COUNT, 0). 1 = cheapest. | D60: =INDEX(Key_Work!$AD$25:$AD$74,MATCH("HZLN",4_Screening!$A$25:$A$74,0)) -> 3 | E60: =ROUNDUP(5*RANK.EQ(comp,comp_rng,1)/COUNT(comp_rng),0)
A61: 4_Screening | B61: S11 | C61: Average ROE of Quintile 1 (cheapest) stocks. | D61: =AVERAGEIFS(4_Screening!$H$25:$H$74,Key_Work!$AD$25:$AD$74,1) -> 0.24172 | E61: =AVERAGEIFS(H:H,Quintile,1)
A62: 4_Screening | B62: S12 | C62: Winsorized mean ROE: cap each ROE at the 5th and 95th percentiles (PERCENTILE.INC), then average. | D62: =AVERAGE(Key_Work!$AF$25:$AF$74) -> 0.1476712 | E62: P5=PERCENTILE.INC(H,0.05), P95=PERCENTILE.INC(H,0.95); helper =MIN(MAX(H2,P5),P95); AVERAGE. Compare to raw mean — outliers matter.
A63: 4_Screening | B63: S13 | C63: Sector-relative P/B of SLTN: its P/B ÷ the AVERAGE P/B of its own sector. | D63: =INDEX(Key_Work!$V$25:$V$74,MATCH("SLTN",4_Screening!$A$25:$A$74,0))/AVERAGEIFS(Key_Work!$V$25:$V$74,4_Screening!$B$25:$B$74,INDEX(4_Screening!$B$25:$B$74,MATCH("SLTN",4_Screening!$A$25:$A$74,0))) -> 1.1174179 | E63: =PB_x/AVERAGEIFS(PB_range,B:B,B_x)
A64: 5_Regression | B64: G1 | C64: Correlation between the stock's excess return and Mkt-RF. | D64: =CORREL(5_Regression!$B$25:$B$84,5_Regression!$C$25:$C$84) -> 0.81418739 | E64: =CORREL(B:B,C:C)
A65: 5_Regression | B65: G2 | C65: Single-factor (CAPM) beta. | D65: =SLOPE(5_Regression!$B$25:$B$84,5_Regression!$C$25:$C$84) -> 1.0821375 | E65: =SLOPE(B,C)
A66: 5_Regression | B66: G3 | C66: Single-factor monthly alpha (intercept). | D66: =INTERCEPT(5_Regression!$B$25:$B$84,5_Regression!$C$25:$C$84) -> 0.0016857156 | E66: =INTERCEPT(B,C)
A67: 5_Regression | B67: G4 | C67: Annualized alpha (simple: monthly × 12). | D67: =INTERCEPT(5_Regression!$B$25:$B$84,5_Regression!$C$25:$C$84)*12 -> 0.020228587 | E67: =G3*12
A68: 5_Regression | B68: G5 | C68: R² of the single-factor regression. | D68: =RSQ(5_Regression!$B$25:$B$84,5_Regression!$C$25:$C$84) -> 0.66290111 | E68: =RSQ(B,C) or =CORREL(B,C)^2
A69: 5_Regression | B69: G6 | C69: SAMPLE covariance between stock and Mkt-RF. Then confirm beta = COVARIANCE.S / VAR.S. | D69: =COVAR(5_Regression!$B$25:$B$84,5_Regression!$C$25:$C$84)*COUNT(5_Regression!$B$25:$B$84)/(COUNT(5_Regression!$B$25:$B$84)-1) -> 0.0022676471 | E69: =COVARIANCE.S(B,C); beta check: =COVARIANCE.S(B,C)/VAR.S(C)
A70: 5_Regression | B70: G7 | C70: 3-factor regression (Mkt-RF, SMB, HML): market beta. | D70: =INDEX(LINEST(5_Regression!$B$25:$B$84,5_Regression!$C$25:$E$84),1,3) -> 1.1339439 | E70: =INDEX(LINEST(B,C:E),1,3) — output order is HML, SMB, Mkt, Intercept.
A71: 5_Regression | B71: G8 | C71: 3-factor: SMB loading. | D71: =INDEX(LINEST(5_Regression!$B$25:$B$84,5_Regression!$C$25:$E$84),1,2) -> 0.43225305 | E71: =INDEX(LINEST(B,C:E),1,2)
A72: 5_Regression | B72: G9 | C72: 3-factor: HML loading. Is this stock value- or growth-tilted? | D72: =INDEX(LINEST(5_Regression!$B$25:$B$84,5_Regression!$C$25:$E$84),1,1) -> 0.57795597 | E72: =INDEX(LINEST(B,C:E),1,1). Positive HML = value tilt.
A73: 5_Regression | B73: G10 | C73: 3-factor: monthly intercept (alpha). | D73: =INDEX(LINEST(5_Regression!$B$25:$B$84,5_Regression!$C$25:$E$84),1,4) -> 0.0025999847 | E73: =INDEX(LINEST(B,C:E),1,4)
A74: 5_Regression | B74: G11 | C74: 3-factor R². | D74: =INDEX(LINEST(5_Regression!$B$25:$B$84,5_Regression!$C$25:$E$84,TRUE(),TRUE()),3,1) -> 0.80590682 | E74: =INDEX(LINEST(B,C:E,TRUE,TRUE),3,1)
A75: 5_Regression | B75: G12 | C75: t-stat of the single-factor beta = beta ÷ its standard error. | D75: =SLOPE(5_Regression!$B$25:$B$84,5_Regression!$C$25:$C$84)/INDEX(LINEST(5_Regression!$B$25:$B$84,5_Regression!$C$25:$C$84,TRUE(),TRUE()),2,1) -> 10.679716 | E75: =INDEX(LINEST(B,C,TRUE,TRUE),1,1)/INDEX(LINEST(B,C,TRUE,TRUE),2,1)
A76: 5_Regression | B76: G13 | C76: Annualized Sharpe of the stock's excess returns (monthly mean ÷ monthly std × √12). | D76: =AVERAGE(5_Regression!$B$25:$B$84)/STDEV(5_Regression!$B$25:$B$84)*SQRT(12) -> 0.71178389 | E76: =AVERAGE(B)/STDEV.S(B)*SQRT(12)
A77: 6_Valuation | B77: V1 | C77: Market capitalization ($mm), using 2025 diluted shares. | D77: =(6_Valuation!$B$40*6_Valuation!$F$37) -> 8356.68 | E77: =Price*Shares_2025
A78: 6_Valuation | B78: V2 | C78: Enterprise value ($mm) = Mkt cap + Debt − Cash + Minority Interest + Preferred. | D78: =((6_Valuation!$B$40*6_Valuation!$F$37)+(6_Valuation!$B$41-6_Valuation!$B$42+6_Valuation!$B$43+6_Valuation!$B$44)) -> 9614.68 | E78: =MktCap+Debt-Cash+MI+Pref
A79: 6_Valuation | B79: V3 | C79: 2025 EBITDA ($mm). | D79: =(6_Valuation!$F$28-6_Valuation!$F$29-6_Valuation!$F$30) -> 1070.4 | E79: =Rev-COGS-SGA
A80: 6_Valuation | B80: V4 | C80: EV / 2025 EBITDA. | D80: =((6_Valuation!$B$40*6_Valuation!$F$37)+(6_Valuation!$B$41-6_Valuation!$B$42+6_Valuation!$B$43+6_Valuation!$B$44))/(6_Valuation!$F$28-6_Valuation!$F$29-6_Valuation!$F$30) -> 8.9823244 | E80: =V2/V3
A81: 6_Valuation | B81: V5 | C81: 2025 Net Income ($mm). | D81: =(((6_Valuation!$F$28-6_Valuation!$F$29-6_Valuation!$F$30)-6_Valuation!$F$31)-6_Valuation!$F$32-6_Valuation!$F$33) -> 609.2 | E81: =EBITDA-D&A-Interest-Tax
A82: 6_Valuation | B82: V6 | C82: P/E on 2025 earnings (Mkt cap ÷ Net income). | D82: =(6_Valuation!$B$40*6_Valuation!$F$37)/(((6_Valuation!$F$28-6_Valuation!$F$29-6_Valuation!$F$30)-6_Valuation!$F$31)-6_Valuation!$F$32-6_Valuation!$F$33) -> 13.717466 | E82: =MktCap/NI (= Price/(NI/Shares))
A83: 6_Valuation | B83: V7 | C83: 2025 gross margin. | D83: =(6_Valuation!$F$28-6_Valuation!$F$29)/6_Valuation!$F$28 -> 0.42499803 | E83: =(Rev-COGS)/Rev
A84: 6_Valuation | B84: V8 | C84: 2025 EBITDA margin. | D84: =(6_Valuation!$F$28-6_Valuation!$F$29-6_Valuation!$F$30)/6_Valuation!$F$28 -> 0.21099109 | E84: =EBITDA/Rev
A85: 6_Valuation | B85: V9 | C85: Revenue CAGR 2021→2025 (4 periods, not 5!). | D85: =(6_Valuation!$F$28/6_Valuation!$B$28)^(1/4)-1 -> 0.061220176 | E85: =(F/B)^(1/4)-1 or =RRI(4,B,F)
A86: 6_Valuation | B86: V10 | C86: 2025 free-cash-flow yield = (CFO − Capex) ÷ Mkt cap. | D86: =(6_Valuation!$F$34-6_Valuation!$F$35)/(6_Valuation!$B$40*6_Valuation!$F$37) -> 0.070602201 | E86: =(CFO-Capex)/MktCap
A87: 6_Valuation | B87: V11 | C87: Net debt / 2025 EBITDA (net debt = Debt − Cash). | D87: =(6_Valuation!$B$41-6_Valuation!$B$42)/(6_Valuation!$F$28-6_Valuation!$F$29-6_Valuation!$F$30) -> 1.0369955 | E87: =(Debt-Cash)/EBITDA
A88: 6_Valuation | B88: V12 | C88: 2025 dividend payout ratio. | D88: =6_Valuation!$F$36/(((6_Valuation!$F$28-6_Valuation!$F$29-6_Valuation!$F$30)-6_Valuation!$F$31)-6_Valuation!$F$32-6_Valuation!$F$33) -> 0.38000657 | E88: =Divs/NI
A89: 6_Valuation | B89: V13 | C89: 2025 interest coverage (EBIT ÷ Interest). | D89: =((6_Valuation!$F$28-6_Valuation!$F$29-6_Valuation!$F$30)-6_Valuation!$F$31)/6_Valuation!$F$32 -> 13.066667 | E89: =EBIT/Interest
A90: 6_Valuation | B90: V14 | C90: Implied share price if re-rated to the peer EV/EBITDA multiple. (Bridge EV → equity, ÷ shares.) | D90: =(6_Valuation!$B$45*(6_Valuation!$F$28-6_Valuation!$F$29-6_Valuation!$F$30)-(6_Valuation!$B$41-6_Valuation!$B$42+6_Valuation!$B$43+6_Valuation!$B$44))/6_Valuation!$F$37 -> 29.197442 | E90: =(8.0*EBITDA-Debt+Cash-MI-Pref)/Shares
A91: 6_Valuation | B91: V15 | C91: Upside/(downside) to that implied price vs current price. | D91: =((6_Valuation!$B$45*(6_Valuation!$F$28-6_Valuation!$F$29-6_Valuation!$F$30)-(6_Valuation!$B$41-6_Valuation!$B$42+6_Valuation!$B$43+6_Valuation!$B$44))/6_Valuation!$F$37)/6_Valuation!$B$40-1 -> -0.12582509 | E91: =V14/Price-1
A92: 6_Valuation | B92: V16 | C92: Mini-DCF implied share price: FCF₀ = 2025 CFO − Capex. Grow FCF at the 5-yr growth rate for years 1–5, discount at WACC (end-of-year). Terminal value at year 5 = FCF₅×(1+g)/(WACC−g), discounted 5 years. EV → equity (same bridge) → ÷ 2025 shares. | D92: =Key_Work!$AJ$12 -> 36.371652 | E92: =(NPV(WACC,FCF1:FCF5)+FCF5*(1+g)/(WACC-g)/(1+WACC)^5 - Debt+Cash-MI-Pref)/Shares
