Workbook

Sheet Comparison
A1: iPhone Carrier Deal Comparison — ZIP 10016 (New York, NY) — single line, 36-month view
A2: Checked 2026-09-28 on each carrier's official site. 'Not stated' = not shown on the site. Cost in col 9 is a formula from the 'Cost Calc' tab (blue inputs there are editable). Taxes/fees excluded unless noted.
A4: Carrier | B4: iPhone model (storage) with best offer | C4: Retail price (MSRP) | D4: Discount amount ($) and type | E4: How discount is delivered | F4: Trade-in terms | G4: Extra bonuses | H4: Plan requirements | I4: Est. total cost over credit period (1 line, $) | J4: Available in ZIP 10016? | K4: Key catches / fine print | L4: Source URL(s) | M4: Date checked
A5: T-Mobile | B5: iPhone 18 Pro 256GB (tie: iPhone 18 Pro Max 256GB gets the same $1,200, leaving $99.99 to pay) | C5: $1,199.99 (18 Pro 256GB); $1,299.99 (18 Pro Max 256GB) | D5: Up to $1,200 — FULL on 18 Pro ("On Us"); Partial on 18 Pro Max ($99.99 left) | E5: Monthly bill credits over up to 36 months. Credits stop if you cancel the entire account (remaining finance balance due) and end if you pay off the device early. | F5: NOT required if you switch and port in your number (new line). Alternative path: trade in an eligible phone in ANY condition on Experience Beyond (examples: 'Save $1,200: iPhone 16; Save $930: iPhone 14; Save $500: iPhone 6'). Credit is fixed by trade-in model, not condition. | G5: Not stated for this offer. Plan perks on Experience Beyond 2.0: Netflix Standard with ads on us, Apple TV $3/mo, T-Satellite, 5-Year Price Guarantee, early upgrades at new-customer deal pricing. | H5: Experience Beyond 2.0 (new & existing members); Experience Beyond / Go5G Next also qualify for existing members only. 1 line = $100/mo with AutoPay ($105 without). Min. 1 line. No-trade path needs new line + port-in from AT&T, Verizon or other eligible carrier; trade-in path open to upgrades. No home internet required. | I5: ='Cost Calc'!J3 -> 3635 | J5: Not ZIP-gated — site never asked for a ZIP; national offer | K5: '$100+/mo. plan w/AutoPay' required. $35 device connection charge; tax on pre-credit price due at sale. Credits start within 2 bill cycles. Max 4 discounted devices/account. May need to reactivate lines cancelled in past 90 days. Not combinable with some offers. Cheaper Experience More 2.0 ($85/mo) only gets iPhone 17 256GB on us (up to $930). | L5: https://www.t-mobile.com/offers/apple-iphone-deals https://www.t-mobile.com/cell-phone-plans | M5: 2026-09-28
A6: Verizon | B6: iPhone 18 Pro 256GB (tie: iPhone 18 Pro Max also 'up to $1,200', leaving ~$99.99) | C6: $1,199.99 (18 Pro); $1,299.99 (18 Pro Max) | D6: Up to $1,200 — FULL on 18 Pro if your trade-in qualifies for the max | E6: Trade-in/promo credit applied monthly over 36 months on the Verizon bill; 0% APR device payment. Promo credit ends if eligibility requirements are no longer met. | F6: REQUIRED. Old device must be traded in within 30 days of purchase; must be Apple, Google, Motorola or Samsung; no activation lock / lost-stolen. Credit depends on model: site's checker showed iPhone 15 = $1,200; iPhone 13 = $600. Site also advertises 'Any condition guaranteed'. For upgrades, phone must be active on the account 60 days before trade-in. | G6: Bundle offer: Apple Watch Series 12 and iPad also 'on us' (up to $600 promo credit per device over 36 mos) — each needs its own new line on a service plan (min. $20/mo w/AutoPay per watch/iPad). | H6: Unlimited Ultimate (myPlan) ONLY: $95/mo for 1 line with AutoPay & paper-free billing ($105 without). NEW LINE required. Unlimited Plus ($80) and Unlimited Welcome ($65) do NOT get the 18 Pro offer; Simplicity Plan not listed as eligible. No home internet required. | I6: ='Cost Calc'!J4 -> 3460 | J6: Not ZIP-gated — site never asked for a ZIP; national offer | K6: Must keep Unlimited Ultimate at min. $95/mo for 36 months. You give up your trade-in phone. 'Promo credit may change based on other Unlimited plans.' Not combinable with other phone offers. $40 activation fee per device. Existing-customer upgrade pricing requires sign-in (not checked). | L6: https://www.verizon.com/shop/online/myplan-phone-deals/ https://www.verizon.com/smartphones/apple-iphone-18-pro/ https://www.verizon.com/smartphones/apple-iphone-17e/ https://www.verizon.com/plans/unlimited/myplan/ https://www.verizon.com/plans/unlimited/ | M6: 2026-09-28
A7: AT&T | B7: iPhone 18 Pro 256GB (tie: iPhone 18 Pro Max, same up to $1,200 off) | C7: $1,199.99 (18 Pro 256GB) | D7: Up to $1,200 — FULL on 18 Pro (on Premium 2.0 or higher) | E7: Bill credits applied over the 36-month installment term, starting within 3 bills. Canceling service stops credits and remaining device balance is due; early payoff or upgrade may stop credits. | F7: REQUIRED. For $1,200: trade in iPhone 14 or newer (excl. 16e) in ANY condition, or an eligible Samsung/Pixel/Moto with min. $180 trade-in value. Must be completed within 30 days; trade-in device can't be on an existing installment plan. Credit amount is fixed by plan tier, not condition (for eligible iPhones). | G7: Not stated. | H7: AT&T Premium 2.0 or higher (Elite 2.0 also qualifies). Offer terms: min. $100/mo for a single line before discounts; AutoPay + paperless (bank) discount is $10/line → ~$90/mo (1-line after-discount price not displayed directly). New AND existing customers; new line OR upgrade. Tier pay-outs: Extra 2.0 = up to $930; Value 2.0 = max $500; any other eligible unlimited plan w/ older iPhone = max $350. AT&T 55+, Value Plus plans not eligible. No home internet required. | I7: ='Cost Calc'!J5 -> 3275 | J7: Not ZIP-gated — site never asked for a ZIP; national offer | K7: Dropping to a cheaper plan reduces or stops credits. If adding a new line, don't cancel any other line within 90 days. $35 activation/upgrade fee; tax on full retail price. AutoPay discount only $5 with debit card, $0 with most credit cards. | L7: https://www.att.com/deals/iphone-deals/ https://www.att.com/buy/phones/apple-iphone-18-pro.html https://www.att.com/plans/unlimited-data-plans/ | M7: 2026-09-28
A8: Spectrum Mobile | B8: iPhone 18 Pro 256GB (18 Pro Max and 17 Pro also 'Save $600') | C8: $1,199.99 (18 Pro 256GB) | D8: $600 — PARTIAL ($16.67/mo vs $33.33/mo); $599.99 left to pay before any trade-in value | E8: Monthly credits over 36 months on a device payment plan. Disconnecting the line or upgrading early forfeits unapplied credits; the $10/mo plan credit ends if the line changes plans. | F8: Not required for the $600 price shown. Optional: '$240 trade-in bonus' (offer valid 9/12/2026–11/8/2026) plus the device's trade-in value (must be > $0), over 36 months. Site is unclear whether the $240 is part of the $600 or extra — the $16.67 price displayed even with 'Skip trade-in' selected. | G8: Unlimited Plus Premium includes up to $360 device credit ($10/mo × 36), free smartwatch data plan. New customers: first line $20/mo for 1 year. Phone balance payoff up to $2,500/account for 2–5 port-in lines (limit one per account). | H8: Unlimited Plus Premium: $50/mo (new customers $20/mo first line for 1 year). Spectrum Internet AND Auto Pay required. Qualified residential customers only (no outstanding Spectrum balance). $600 price shown for new purchase; line type not stated. | I8: ='Cost Calc'!J6 -> 2039.99 | J8: Not verified — availability check requires a full street address (not entered). Spectrum markets Internet service in New York, NY. | K8: Spectrum Internet required (cost NOT included in col 9). Only a partial discount. First-year $20 rate reverts to $50. Activation fee additional (amount not stated). Other Spectrum plans get only $240 off ($26.67/mo). | L8: https://www.spectrum.com/mobile/mobile-deals spectrum.com iPhone 18 Pro product page (via 'Order now' on deals page) https://www.spectrum.com/mobile/plans/unlimited-data https://www.spectrum.com/internet-service/new-york/new-york | M8: 2026-09-28
A9: Xfinity Mobile | B9: iPhone 18 Pro Max (base storage; $36.11/mo) | C9: $36.11/mo × 36 = $1,299.96 shown; full retail not displayed | D9: Trade-in credits 'value up to $1,300' — FULL ('on us') only if your trade-in qualifies for max; actual value varies | E9: Monthly trade-in credits over 36-month Device Payment Agreement. If Mobile Plus line isn't maintained or payments are accelerated, remaining credits are forfeited. | F9: REQUIRED — 'qualifying trade-in'; complete within 21 days of ship date. Credit value varies (up to $1,300) and can't exceed phone retail price. Qualifying models: Not stated. | G9: Mobile Plus includes lifetime device protection (Xfinity Mobile Care Plus), yearly upgrades with a guaranteed discount, unlimited hotspot (reduced after 50 GB), 4K video. Runner-up: $400 off a new iPhone with no trade-in (new Mobile Plus line). | H9: Mobile Plus: $45/mo with Xfinity Internet; new customers $15/mo for first year. New Mobile Plus line OR upgrade on existing Mobile Plus line (new & existing members). Xfinity Internet (residential post-pay) REQUIRED. AutoPay requirement: Not stated. | I9: ='Cost Calc'!J7 -> 1260 | J9: UNVERIFIED — FLAG: check requires street address; site only says 'Not available in all areas'. Xfinity is generally not the cable provider in Manhattan, so assume likely NOT available until confirmed. | K9: Offer ends 10/8/2026. Xfinity Internet required (cost NOT included). Out-of-stock phones not eligible; not combinable with other device offers. Equipment, taxes, regulatory recovery fees extra. | L9: https://www.xfinity.com/mobile/ https://www.xfinity.com/mobile/learn/plan https://www.xfinity.com/mobile/shop?category=device&brand=apple https://www.xfinity.com/local/ny/new-york | M9: 2026-09-28
A11: Summary — ranked by value to a single-line customer in NYC
A12: 1. AT&T (best overall for most NYC single-line buyers): iPhone 18 Pro fully covered ($1,200) on Premium 2.0, open to new AND existing customers, and at ~$90/mo it has the lowest 36-mo cost of the three national carriers (~$3,275). Biggest catch: you must trade in an iPhone 14 or newer (any condition) and stay on Premium 2.0+ — dropping to Extra cuts the credit to $930.
A13: 2. T-Mobile (best if you have no phone worth trading): iPhone 18 Pro on us with NO trade-in for switchers who port in, ~$3,635 over 36 mos. Biggest catch: requires the $100/mo Experience Beyond 2.0 plan; Experience More only gets iPhone 17 free.
A14: 3. Verizon: same $1,200 on iPhone 18 Pro (~$3,460 over 36 mos). Biggest catch: Unlimited Ultimate ($95/mo) and a NEW line are required, and the credit depends on your trade-in (iPhone 13 = only $600). Your read is mostly right — the Simplicity Plan isn't listed as eligible for any iPhone offer, all three myPlan tiers get some deals (e.g., iPhone 17e $700 off), but the flagship offer needs Ultimate specifically.
A15: 4. Xfinity Mobile: lowest paper cost (~$1,260 over 36 mos for phone + plan) and up to $1,300 in trade-in credits on the 18 Pro Max. Biggest catch: requires Xfinity Internet, which could not be confirmed at 10016 and is likely not offered in Manhattan — probably not usable.
A16: 5. Spectrum Mobile: cheap plan (~$2,040 incl. $599.99 left on the phone) but only $600 off. Biggest catch: requires Spectrum Internet (not included in the cost figure) — though Spectrum is the likely cable provider in Kips Bay/Murray Hill, so it's worth a look if you already have Spectrum Internet.
A17: Caveat: cable-carrier totals exclude the required home internet bill; national-carrier totals exclude taxes, fees and the value of the phone you trade in.

Sheet Samsung Deals
A1: Samsung Galaxy Carrier Deal Comparison — ZIP 10016 (New York, NY) — single line, 36-month view
A2: Checked 2026-09-28 on each carrier's official site. 'Not stated' = not shown on the site. Col 9 is a formula from the cost block at the bottom of this tab (blue inputs editable). Taxes/fees excluded unless noted.
A4: Carrier | B4: Samsung model (storage) with best offer | C4: Retail price (MSRP) | D4: Discount amount ($) and type | E4: How discount is delivered | F4: Trade-in terms | G4: Extra bonuses | H4: Plan requirements | I4: Est. total cost over credit period (1 line, $) | J4: Available in ZIP 10016? | K4: Key catches / fine print | L4: Source URL(s) | M4: Date checked
A5: T-Mobile | B5: Galaxy Z Fold8 256GB | C5: $1,899.99 | D5: Up to $1,900 — FULL ('On Us') if your trade-in qualifies for the max | E5: Up to $1,900 via 24 or 36 monthly bill credits (depends on finance term). Credits end if you pay off early; contact T-Mobile before cancelling the whole account, or credits stop and the finance balance is due. | F5: REQUIRED. Credit depends on the model you trade in (site examples: Galaxy S26 = $1,900; Galaxy S22 = $1,100; Galaxy A71 = $550). Trade-in terms apply. | G5: Plan perks on Experience Beyond 2.0 (Netflix Standard w/ ads, Apple TV $3/mo, T-Satellite, 5-Year Price Guarantee). Page also advertises 'Switch and save $750' ($100 virtual prepaid Mastercard with eligible port-in + benefits value). | H5: Experience Beyond 2.0 (new & existing members); Experience Beyond / Go5G Next (existing only). 1 line = $100/mo with AutoPay. New or existing customers. No home internet required. | I5: =J22 -> 3635 | J5: Not ZIP-gated — site never asked for a ZIP; national offer | K5: '$100+/mo. plan w/AutoPay' required. $35 device connection charge; tax on pre-credit price. Max 4 discounted devices/account. No-trade alternatives: $1,100 off Galaxy Z Fold8 Ultra or Z Flip8 (new line on Experience More/Beyond); Galaxy S26 FE on us (up to $800, new line). | L5: https://www.t-mobile.com/offers/samsung-phone-deals https://www.t-mobile.com/cell-phone-plans | M5: 2026-09-28
A6: Verizon | B6: Galaxy S26 Ultra 256GB | C6: $1,299.99 | D6: $1,119.99 — PARTIAL ($5/mo, $180 total left to pay) | E6: Promo credit applied to account over 36 months ($31.11/mo); ends if eligibility requirements are no longer met or line is canceled/moved to an ineligible plan. 0% APR device payment. | F6: NOT required. | G6: Not stated for this offer. Product page says activation fees are waived for new customers ('$40 savings'). | H6: Unlimited Ultimate ONLY: $95/mo for 1 line with AutoPay & paper-free billing. NEW LINE required. No home internet required. | I6: =J23 -> 3640 | J6: Not ZIP-gated — site never asked for a ZIP; national offer | K6: Line must stay on Unlimited Ultimate for 36 months. 'Promo credit may change based on other Unlimited plans'; not combinable with other offers. Offer panel lists a $40 activation fee while the product page says it's waived for new customers — conflicting. Runner-ups: Galaxy S26+ save $1,100 (full); Z Fold8 / Fold8 Ultra up to $1,100 with trade-in; S26 FE on us, no trade-in (new line on myPlan). | L6: https://www.verizon.com/smartphones/samsung-galaxy-s26-ultra/ https://www.verizon.com/shop/online/myplan-phone-deals/ https://www.verizon.com/plans/unlimited/myplan/ | M6: 2026-09-28
A7: AT&T | B7: Galaxy S26 Ultra (base storage; tie: Galaxy Z Fold8 also up to $1,100 but $799.99 left) | C7: $1,299.99 | D7: Up to $1,100 — PARTIAL ($5.56/mo, ~$199.99 left) | E7: Bill credits over the 36-month installment term, starting within 3 bills. Lowering plan reduces/stops credits; canceling stops credits and remaining balance is due; early payoff/upgrade may stop credits. | F7: REQUIRED. For $1,100: trade in Galaxy S22+, Z Flip4, Z Fold3 or higher in ANY condition, or an eligible smartphone worth $95+. Lesser tiers: up to $900 with Galaxy S10/Note10/Z Flip3 or higher (or phone worth $35–94). Complete within 30 days; trade-in can't be on an installment plan. | G7: Not stated. | H7: AT&T Extra 2.0 or higher (min. $80/mo single line before discounts; ~$70 with $10 AutoPay+paperless via bank). Value 2.0 = up to $500 on S26 series; Starter/Starter SL (existing) max $900. New & existing customers; new line or upgrade. AT&T 55+ and Value Plus plans not eligible. No home internet required. | I7: =J24 -> 2754.99 | J7: Not ZIP-gated — site never asked for a ZIP; national offer | K7: Offer applies to S26+ and S26 Ultra ('S26 device not eligible for this offer'). If adding a new line, don't cancel any other line within 90 days. $35 activation/upgrade fee; tax on full retail. Runner-up: Galaxy S26 $0/mo with new line, no trade-in (~$900). | L7: https://www.att.com/buy/phones/samsung-galaxy-s26-ultra.html https://www.att.com/buy/phones/samsung-galaxy-z-fold8.html https://www.att.com/buy/phones/browse/samsung_hasdeals/ | M7: 2026-09-28
A8: Spectrum Mobile | B8: Galaxy Z Fold8 256GB | C8: $1,899.99 | D8: $1,459.80 ('over $1,400 off') — PARTIAL ($12.22/mo vs $52.77/mo; ~$440 left) | E8: Monthly credits over 36 months on a device payment plan; disconnecting or upgrading early forfeits unapplied credits; $10/mo plan credit ends if line changes plans. | F8: Shown price did not require selecting a trade-in, but the page also lists a '$900 trade-in bonus — eligible trade-in required' (valid 8/7/2026–9/30/2026). Unclear whether the $900 is inside the $1,459.80 or extra. Trade-in value itself: Not stated. | G8: Unlimited Plus Premium includes up to $360 device credit ($10/mo × 36), free smartwatch data plan; new customers first line $20/mo for 1 year. Phone balance payoff up to $2,500/account for 2–5 port-in lines. | H8: Unlimited Plus Premium: $50/mo (new customers $20/mo first line for 1 year). Spectrum Internet AND Auto Pay required. Qualified residential customers only. Other Spectrum plans: $22.22/mo (~$1,100 off). | I8: =J25 -> 1880.19 | J8: Not verified — availability check requires a full street address (not entered). Spectrum markets Internet service in New York, NY. | K8: Spectrum Internet required (cost NOT included). $900 trade-in bonus expires 9/30/2026. Activation fee additional (amount not stated). Runner-ups: Galaxy S26 and Z Flip8 'at no cost' on Unlimited Plus Premium. | L8: https://www.spectrum.com/mobile/mobile-deals spectrum.com Galaxy Z Fold8 product page (via 'Order now') https://www.spectrum.com/mobile/plans/unlimited-data | M8: 2026-09-28
A9: Xfinity Mobile | B9: Galaxy Z Fold8 (base storage; tie: Z Fold8 Ultra also up to $1,200, more left to pay) | C9: $52.77/mo × 36 = $1,899.72 shown; full retail not displayed | D9: Trade-in credits 'value up to $1,200' — PARTIAL (from $19.44/mo; ~$700 left) | E9: Monthly trade-in credits over 36-month Device Payment Agreement; forfeited if Mobile Plus line isn't maintained or payments are accelerated. | F9: REQUIRED — 'qualifying trade-in'; complete within 21 days of ship date; value varies and can't exceed phone retail price. Qualifying models: Not stated. | G9: Mobile Plus includes lifetime device protection, yearly upgrades with guaranteed discount, unlimited hotspot (reduced after 50 GB), 4K video. | H9: Mobile Plus: $45/mo with Xfinity Internet; new customers $15/mo first year. NEW Mobile Plus line required. Xfinity Internet (residential post-pay) REQUIRED. AutoPay requirement: Not stated. | I9: =J26 -> 1959.72 | J9: UNVERIFIED — FLAG: check requires street address; Xfinity is generally not the cable provider in Manhattan — assume likely NOT available until confirmed. | K9: Offer ends 10/8/2026. Xfinity Internet required (cost NOT included). Not combinable with other device offers; out-of-stock phones not eligible. Galaxy Z Flip8, S26+, S26, S26 FE listed from $0.00/mo. | L9: https://www.xfinity.com/mobile/shop?category=device&brand=samsung https://www.xfinity.com/mobile/learn/plan | M9: 2026-09-28
A11: Summary — ranked by value to a single-line customer in NYC
A12: 1. AT&T (best overall value): up to $1,100 off Galaxy S26 Ultra on the cheaper Extra 2.0 plan (~$70/mo), new or existing customers — lowest 36-mo cost of the national carriers (~$2,755). Biggest catch: needs a Galaxy S22+/Z Flip4/Z Fold3-or-newer trade-in (any condition) for the full $1,100.
A13: 2. Verizon (best with no trade-in): $1,119.99 off Galaxy S26 Ultra, no trade-in, ~$3,640 over 36 mos. Biggest catch: new line on Unlimited Ultimate ($95/mo) required for all 36 months.
A14: 3. T-Mobile (largest dollar discount): Galaxy Z Fold8 fully on us — up to $1,900 — ~$3,635 over 36 mos. Biggest catch: the $1,900 needs a recent trade-in (Galaxy S26 = $1,900; S22 only $1,100) plus the $100/mo Experience Beyond 2.0 plan.
A15: 4. Spectrum Mobile: ~$1,460 off Galaxy Z Fold8 on Unlimited Plus Premium, ~$1,880 total over 36 mos. Biggest catch: Spectrum Internet required (not in the total), and the $900 trade-in bonus it may depend on expires 9/30/2026.
A16: 5. Xfinity Mobile: up to $1,200 trade-in credit on Galaxy Z Fold8, ~$1,960 over 36 mos. Biggest catch: requires Xfinity Internet, unverified and likely unavailable at 10016; new Mobile Plus line required.
A17: Caveat: cable-carrier totals exclude the required home internet bill; national-carrier totals exclude taxes, fees and the value of any phone traded in.
A20: Cost calculation (blue = inputs from carrier sites; black = formulas). Excludes taxes and required home internet.
A21: Carrier | B21: Retail price | C21: Max promo credit | D21: Phone cost after credit | E21: Promo-period monthly rate | F21: Promo months | G21: Regular monthly rate (AutoPay) | H21: Credit period (months) | I21: One-time fees | J21: Total 36-mo cost | K21: Notes
A22: T-Mobile | B22: 1899.99 | C22: 1900 | D22: =MAX(0,B22-C22) -> 0 | E22: 100 | F22: 0 | G22: 100 | H22: 36 | I22: 35 | J22: =D22+E22*F22+G22*(H22-F22)+I22 -> 3635 | K22: Experience Beyond 2.0 $100 w/AutoPay; $35 connection charge; assumes trade-in earns full $1,900.
A23: Verizon | B23: 1299.99 | C23: 1119.99 | D23: =MAX(0,B23-C23) -> 180 | E23: 95 | F23: 0 | G23: 95 | H23: 36 | I23: 40 | J23: =D23+E23*F23+G23*(H23-F23)+I23 -> 3640 | K23: Unlimited Ultimate $95; $40 activation used (product page says waived for new customers).
A24: AT&T | B24: 1299.99 | C24: 1100 | D24: =MAX(0,B24-C24) -> 199.99 | E24: 70 | F24: 0 | G24: 70 | H24: 36 | I24: 35 | J24: =D24+E24*F24+G24*(H24-F24)+I24 -> 2754.99 | K24: Extra 2.0 $80 before discounts less $10 AutoPay/paperless (bank) = $70 (derived); $35 fee; assumes full $1,100 tier.
A25: Spectrum Mobile | B25: 1899.99 | C25: 1459.8 | D25: =MAX(0,B25-C25) -> 440.19 | E25: 20 | F25: 12 | G25: 50 | H25: 36 | I25: 0 | J25: =D25+E25*F25+G25*(H25-F25)+I25 -> 1880.19 | K25: ($52.77-$12.22) x 36 = $1,459.80. Premium $20 first year then $50. Activation fee not stated. Internet excluded.
A26: Xfinity Mobile | B26: 1899.72 | C26: 1200 | D26: =MAX(0,B26-C26) -> 699.72 | E26: 15 | F26: 12 | G26: 45 | H26: 36 | I26: 0 | J26: =D26+E26*F26+G26*(H26-F26)+I26 -> 1959.72 | K26: $52.77 x 36. Mobile Plus $15 first year then $45. Assumes max trade-in credit. Internet excluded.

Sheet Cost Calc
A1: Estimated 36-month cost, 1 line (blue = inputs from carrier sites; black = formulas). Excludes taxes and required home internet.
A2: Carrier | B2: Retail price | C2: Max promo credit | D2: Phone cost after credit | E2: Promo-period monthly rate | F2: Promo months | G2: Regular monthly rate (AutoPay) | H2: Credit period (months) | I2: One-time fees | J2: Total 36-mo cost | K2: Notes
A3: T-Mobile | B3: 1199.99 | C3: 1200 | D3: =MAX(0,B3-C3) -> 0 | E3: 100 | F3: 0 | G3: 100 | H3: 36 | I3: 35 | J3: =D3+E3*F3+G3*(H3-F3)+I3 -> 3635
A4: Verizon | B4: 1199.99 | C4: 1200 | D4: =MAX(0,B4-C4) -> 0 | E4: 95 | F4: 0 | G4: 95 | H4: 36 | I4: 40 | J4: =D4+E4*F4+G4*(H4-F4)+I4 -> 3460
A5: AT&T | B5: 1199.99 | C5: 1200 | D5: =MAX(0,B5-C5) -> 0 | E5: 90 | F5: 0 | G5: 90 | H5: 36 | I5: 35 | J5: =D5+E5*F5+G5*(H5-F5)+I5 -> 3275
A6: Spectrum Mobile | B6: 1199.99 | C6: 600 | D6: =MAX(0,B6-C6) -> 599.99 | E6: 20 | F6: 12 | G6: 50 | H6: 36 | I6: 0 | J6: =D6+E6*F6+G6*(H6-F6)+I6 -> 2039.99
A7: Xfinity Mobile | B7: 1299.96 | C7: 1300 | D7: =MAX(0,B7-C7) -> 0 | E7: 15 | F7: 12 | G7: 45 | H7: 36 | I7: 0 | J7: =D7+E7*F7+G7*(H7-F7)+I7 -> 1260

Sheet Other Offers & Eligibility
A1: Runner-up iPhone offers and plan-eligibility detail (as seen 2026-09-28)
A2: Carrier | B2: Offer | C2: Value | D2: Conditions (as stated)
A3: T-Mobile | B3: iPhone 18 Pro Max 'under $100' | C3: Up to $1,200 (256GB $1,299.99) | D3: Experience Beyond 2.0; switch+port-in OR any-condition trade-in
A4: T-Mobile | B4: iPhone 17 Pro on us with trade | C4: Up to $1,100 (256GB $1,099.99) | D4: $100+/mo plan; eligible trade-in (e.g., iPhone 16 = $1,100); existing Go5G Next members qualify
A5: T-Mobile | B5: iPhone 17 on us, no trade-in | C5: Up to $930 (256GB $929.99) | D5: Experience More 2.0 ($85/mo 1 line) or Beyond 2.0; new line + port-in
A6: T-Mobile | B6: iPhone 16 on us / iPhone Air on us w/ trade / 2 iPhone 17e on us | C6: Varies | D6: 16: switch on Experience More/Beyond; Air: any-condition trade on Beyond; 17e: 2 switched lines on Essentials $80/mo
A7: Verizon | B7: iPhone 17e 'Save $700' | C7: $700 (full; retail $699.99) | D7: New line; Unlimited Welcome ($65), Plus ($80) or Ultimate ($95) — Simplicity not listed
A8: Verizon | B8: iPhone 17 Pro Max / 17 Pro 'Save $1000' | C8: $1,000 | D8: Shown on myPlan phone deals page; details not opened
A9: Verizon | B9: Plan eligibility check | C9: — | D9: Simplicity Plan: $45/line w/AutoPay, $30 with $15 Switch & Save discount — not named in any iPhone offer terms seen. myPlan: Welcome/Plus/Ultimate named for 17e; Ultimate only for 18 Pro/Pro Max $1,200.
A10: AT&T | B10: iPhone 17 Pro Max new line, no trade-in | C10: $14.99/mo vs $33.34/mo (~$660 over 36 mos) | D10: New line + eligible plan; includes extra $5.56/mo credit
A11: AT&T | B11: iPhone 17 / 17e | C11: 17: $0/mo with trade-in; 17e: $0.99/mo new line, no trade | D11: Eligible plan required
A12: AT&T | B12: Tiered credits (18 Pro/Pro Max trade-in offer) | C12: Elite/Premium 2.0: $1,200 · Extra 2.0: $930 · Value 2.0: $500 · other unlimited: $350 | D12: New & existing; new line or upgrade; iPhone 14+ any condition
A13: Spectrum | B13: iPhone 17 / iPhone Air | C13: 'Over $500 off' | D13: Unlimited Plus Premium
A14: Xfinity | B14: $400 off a new iPhone | C14: $400, no trade-in | D14: New Mobile Plus line + device payment plan; ends 10/8
