Workbook
Name IQ_CH: 110000
Name IQ_CQ: 5000
Name IQ_CY: 10000
Name IQ_DAILY: 500000
Name IQ_FH: 100000
Name IQ_FQ: 500
Name IQ_FY: 1000
Name IQ_LTM: 2000
Name IQ_MONTH: 15000
Name IQ_NTM: 6000
Name IQ_WEEK: 50000
Name IQ_YTD: 3000

Sheet Summary 2025
A1: 2025 Theatrical Releases
A2: Title | B2: Parent Company | C2: Release Date | D2: Release Quarter | E2: Release Type
A3: ='2025'!A2 -> From Ground Zero | B3: ='2025'!C2 -> Independent / Other | C3: ='2025'!D2 -> 45660 | D3: ='2025'!H2 -> Q1 2025 | E3: ='2025'!I2 -> Limited
A4: ='2025'!A3 -> Georgia O’Keeffe: The Brightness of Light | B4: ='2025'!C3 -> Independent / Other | C4: ='2025'!D3 -> 45660 | D4: ='2025'!H3 -> Q1 2025 | E4: ='2025'!I3 -> Limited
A5: ='2025'!A5 -> The Damned | B5: ='2025'!C5 -> Independent / Other | C5: ='2025'!D4 -> 45660 | D5: ='2025'!H5 -> Q1 2025 | E5: ='2025'!I5 -> Wide
A6: ='2025'!A6 -> The Last Republican | B6: ='2025'!C6 -> Independent / Other | C6: ='2025'!D5 -> 45660 | D6: ='2025'!H6 -> Q1 2025 | E6: ='2025'!I6 -> Limited
A7: ='2025'!A7 -> The Monster Beneath Us | B7: ='2025'!C7 -> Independent / Other | C7: ='2025'!D6 -> 45660 | D7: ='2025'!H7 -> Q1 2025 | E7: ='2025'!I7 -> Limited
A8: ='2025'!A9 -> Better Man | B8: ='2025'!C9 -> Paramount | C8: ='2025'!D7 -> 45660 | D8: ='2025'!H9 -> Q1 2025 | E8: ='2025'!I9 -> Wide
A9: ='2025'!A10 -> Birdeater | B9: ='2025'!C10 -> Independent / Other | C9: ='2025'!D8 -> 45665 | D9: ='2025'!H10 -> Q1 2025 | E9: ='2025'!I10 -> Limited
A10: ='2025'!A11 -> Black Diamond | B10: ='2025'!C11 -> Independent / Other | C10: ='2025'!D9 -> 45667 | D10: ='2025'!H11 -> Q1 2025 | E10: ='2025'!I11 -> Limited
A11: ='2025'!A12 -> Black Zone | B11: ='2025'!C12 -> Independent / Other | C11: ='2025'!D10 -> 45667 | D11: ='2025'!H12 -> Q1 2025 | E11: ='2025'!I12 -> Limited
A12: ='2025'!A13 -> Den of Thieves 2: Pantera | B12: ='2025'!C13 -> Lionsgate | C12: ='2025'!D11 -> 45667 | D12: ='2025'!H13 -> Q1 2025 | E12: ='2025'!I13 -> Wide
A13: ='2025'!A14 -> Diane Warren: Relentless | B13: ='2025'!C14 -> Independent / Other | C13: ='2025'!D12 -> 45667 | D13: ='2025'!H14 -> Q1 2025 | E13: ='2025'!I14 -> Limited
A14: ='2025'!A15 -> Eat the Night | B14: ='2025'!C15 -> Independent / Other | C14: ='2025'!D13 -> 45667 | D14: ='2025'!H15 -> Q1 2025 | E14: ='2025'!I15 -> Limited
A15: ='2025'!A16 -> Every Little Thing | B15: ='2025'!C16 -> Independent / Other | C15: ='2025'!D14 -> 45667 | D15: ='2025'!H16 -> Q1 2025 | E15: ='2025'!I16 -> Limited
A16: ='2025'!A17 -> Extremely Unique Dynamic | B16: ='2025'!C17 -> Independent / Other | C16: ='2025'!D15 -> 45667 | D16: ='2025'!H17 -> Q1 2025 | E16: ='2025'!I17 -> Limited
A17: ='2025'!A18 -> Finist: The First Warrior | B17: ='2025'!C18 -> Independent / Other | C17: ='2025'!D16 -> 45667 | D17: ='2025'!H18 -> Q1 2025 | E17: ='2025'!I18 -> Limited
A18: ='2025'!A19 -> Game Changer | B18: ='2025'!C19 -> Independent / Other | C18: ='2025'!D17 -> 45667 | D18: ='2025'!H19 -> Q1 2025 | E18: ='2025'!I19 -> Wide
A19: ='2025'!A20 -> Hard Truths | B19: ='2025'!C20 -> Bleecker Street | C19: ='2025'!D18 -> 45667 | D19: ='2025'!H20 -> Q1 2025 | E19: ='2025'!I20 -> Limited
... A34: ='2025'!A35 -> Savor | B34: ='2025'!C35 -> Independent / Other | C34: ='2025'!D33 -> 45667 | D34: ='2025'!H35 -> Q1 2025 | E34: ='2025'!I35 -> Limited
A35: ='2025'!A37 -> Daaku Maharaaj | B35: ='2025'!C37 -> Independent / Other | C35: ='2025'!D34 -> 45667 | D35: ='2025'!H37 -> Q1 2025 | E35: ='2025'!I37 -> Limited
A36: ='2025'!A38 -> Peter Pan’s Neverland Nightmare | B36: ='2025'!C38 -> Independent / Other | C36: ='2025'!D35 -> 45668 | D36: ='2025'!H38 -> Q1 2025 | E36: ='2025'!I38 -> Wide
A37: ='2025'!A39 -> Kadhalikka Neramillai | B37: ='2025'!C39 -> Independent / Other | C37: ='2025'!D36 -> 45668 | D37: ='2025'!H39 -> Q1 2025 | E37: ='2025'!I39 -> Limited
A38: ='2025'!A40 -> Pay Dirt: The Story of Supercross | B38: ='2025'!C40 -> Independent / Other | C38: ='2025'!D37 -> 45669 | D38: ='2025'!H40 -> Q1 2025 | E38: ='2025'!I40 -> Limited
A39: ='2025'!A41 -> Sankrathiki Vasthunam | B39: ='2025'!C41 -> Independent / Other | C39: ='2025'!D38 -> 45670 | D39: ='2025'!H41 -> Q1 2025 | E39: ='2025'!I41 -> Limited
A40: ='2025'!A42 -> Praavinkoodu Shappu | B40: ='2025'!C42 -> Independent / Other | C40: ='2025'!D39 -> 45671 | D40: ='2025'!H42 -> Q1 2025 | E40: ='2025'!I42 -> Limited
A41: ='2025'!A43 -> Alarum | B41: ='2025'!C43 -> Lionsgate | C41: ='2025'!D40 -> 45671 | D41: ='2025'!H43 -> Q1 2025 | E41: ='2025'!I43 -> Limited
A42: ='2025'!A44 -> Autumn and the Black Jaguar | B42: ='2025'!C44 -> Independent / Other | C42: ='2025'!D41 -> 45671 | D42: ='2025'!H44 -> Q1 2025 | E42: ='2025'!I44 -> Limited
A43: ='2025'!A45 -> Azaad | B43: ='2025'!C45 -> Independent / Other | C43: ='2025'!D42 -> 45673 | D43: ='2025'!H45 -> Q1 2025 | E43: ='2025'!I45 -> Limited
A44: ='2025'!A46 -> Both Eyes Open | B44: ='2025'!C46 -> IFC | C44: ='2025'!D43 -> 45674 | D44: ='2025'!H46 -> Q1 2025 | E44: ='2025'!I46 -> Limited
A45: ='2025'!A47 -> DIG! XX | B45: ='2025'!C47 -> Independent / Other | C45: ='2025'!D44 -> 45674 | D45: ='2025'!H47 -> Q1 2025 | E45: ='2025'!I47 -> Limited
A46: ='2025'!A48 -> El Heredero | B46: ='2025'!C48 -> Independent / Other | C46: ='2025'!D45 -> 45674 | D46: ='2025'!H48 -> Q1 2025 | E46: ='2025'!I48 -> Limited
A47: ='2025'!A49 -> Emergency | B47: ='2025'!C49 -> Independent / Other | C47: ='2025'!D46 -> 45674 | D47: ='2025'!H49 -> Q1 2025 | E47: ='2025'!I49 -> Limited
A48: ='2025'!A51 -> Grand Theft Hamlet | B48: ='2025'!C51 -> Independent / Other | C48: ='2025'!D47 -> 45674 | D48: ='2025'!H51 -> Q1 2025 | E48: ='2025'!I51 -> Limited
A49: ='2025'!A52 -> Hold Me Close | B49: ='2025'!C52 -> Independent / Other | C49: ='2025'!D48 -> 45674 | D49: ='2025'!H52 -> Q1 2025 | E49: ='2025'!I52 -> Limited
A50: ='2025'!A53 -> I’m Still Here | B50: ='2025'!C53 -> Sony | C50: ='2025'!D49 -> 45674 | D50: ='2025'!H53 -> Q1 2025 | E50: ='2025'!I53 -> Wide
A51: ='2025'!A54 -> Left Behind | B51: ='2025'!C54 -> Independent / Other | C51: ='2025'!D50 -> 45674 | D51: ='2025'!H54 -> Q1 2025 | E51: ='2025'!I54 -> Limited
A52: ='2025'!A55 -> Night Call | B52: ='2025'!C55 -> Independent / Other | C52: ='2025'!D51 -> 45674 | D52: ='2025'!H55 -> Q1 2025 | E52: ='2025'!I55 -> Limited
A53: ='2025'!A56 -> One of Them Days | B53: ='2025'!C56 -> Sony | C53: ='2025'!D52 -> 45674 | D53: ='2025'!H56 -> Q1 2025 | E53: ='2025'!I56 -> Wide
A54: ='2025'!A57 -> Sing Sing | B54: ='2025'!C57 -> A24 | C54: ='2025'!D53 -> 45674 | D54: ='2025'!H57 -> Q1 2025 | E54: ='2025'!I57 -> Limited
A55: ='2025'!A58 -> The Room Next Door | B55: ='2025'!C58 -> Sony | C55: ='2025'!D54 -> 45674 | D55: ='2025'!H58 -> Q1 2025 | E55: ='2025'!I58 -> Wide
A56: ='2025'!A59 -> Wish You Were Here | B56: ='2025'!C59 -> Lionsgate | C56: ='2025'!D55 -> 45674 | D56: ='2025'!H59 -> Q1 2025 | E56: ='2025'!I59 -> Limited
A57: ='2025'!A60 -> Wolf Man | B57: ='2025'!C60 -> Universal / NBCU | C57: ='2025'!D56 -> 45674 | D57: ='2025'!H60 -> Q1 2025 | E57: ='2025'!I60 -> Wide
A58: ='2025'!A61 -> The Wasps | B58: ='2025'!C61 -> Unknown | C58: ='2025'!D57 -> 45674 | D58: ='2025'!H61 -> Q1 2025 | E58: ='2025'!I61 -> Limited
A59: ='2025'!A62 -> UFC 311: Makhachev vs. Tsarukyan 2 | B59: ='2025'!C62 -> Independent / Other | C59: ='2025'!D58 -> 45674 | D59: ='2025'!H62 -> Q1 2025 | E59: ='2025'!I62 -> Special Engagement
A60: ='2025'!A64 -> Reckonings | B60: ='2025'!C64 -> Unknown | C60: ='2025'!D59 -> 45674 | D60: ='2025'!H64 -> Q1 2025 | E60: ='2025'!I64 -> Limited
A61: ='2025'!A65 -> A Legend | B61: ='2025'!C65 -> Independent / Other | C61: ='2025'!D60 -> 45674 | D61: ='2025'!H65 -> Q1 2025 | E61: ='2025'!I65 -> Limited
A62: ='2025'!A66 -> Marked Men: Rule & Shaw | B62: ='2025'!C66 -> Independent / Other | C62: ='2025'!D61 -> 45675 | D62: ='2025'!H66 -> Q1 2025 | E62: ='2025'!I66 -> Special Engagement
A63: ='2025'!A67 -> Dominic and the Ladies’ Purse | B63: ='2025'!C67 -> Unknown | C63: ='2025'!D62 -> 45675 | D63: ='2025'!H67 -> Q1 2025 | E63: ='2025'!I67 -> Limited
A64: ='2025'!A68 -> Narayaneente Moonaanmakkal | B64: ='2025'!C68 -> Independent / Other | C64: ='2025'!D63 -> 45676 | D64: ='2025'!H68 -> Q1 2025 | E64: ='2025'!I68 -> Limited
A65: ='2025'!A69 -> The Colors Within in IMAX | B65: ='2025'!C69 -> Independent / Other | C65: ='2025'!D64 -> 45677 | D65: ='2025'!H69 -> Q1 2025 | E65: ='2025'!I69 -> Special Engagement
A66: ='2025'!A70 -> Blades in the Darkness | B66: ='2025'!C70 -> Independent / Other | C66: ='2025'!D65 -> 45678 | D66: ='2025'!H70 -> Q1 2025 | E66: ='2025'!I70 -> Limited
A67: ='2025'!A71 -> Boonie Bears:Time Twist | B67: ='2025'!C71 -> Independent / Other | C67: ='2025'!D66 -> 45679 | D67: ='2025'!H71 -> Q1 2025 | E67: ='2025'!I71 -> Limited
A68: ='2025'!A72 -> Brave the Dark | B68: ='2025'!C72 -> Angel Studios | C68: ='2025'!D67 -> 45680 | D68: ='2025'!H72 -> Q1 2025 | E68: ='2025'!I72 -> Wide
A69: ='2025'!A73 -> Disfluency | B69: ='2025'!C73 -> Independent / Other | C69: ='2025'!D68 -> 45680 | D69: ='2025'!H73 -> Q1 2025 | E69: ='2025'!I73 -> Limited
A70: ='2025'!A74 -> Flight Risk | B70: ='2025'!C74 -> Lionsgate | C70: ='2025'!D69 -> 45680 | D70: ='2025'!H74 -> Q1 2025 | E70: ='2025'!I74 -> Wide
A71: ='2025'!A75 -> Hathya | B71: ='2025'!C75 -> Independent / Other | C71: ='2025'!D70 -> 45681 | D71: ='2025'!H75 -> Q1 2025 | E71: ='2025'!I75 -> Limited
... A108: ='2025'!A112 -> No Other Land | B108: ='2025'!C112 -> Independent / Other | C108: ='2025'!D107 -> 45688 | D108: ='2025'!H112 -> Q1 2025 | E108: ='2025'!I112 -> Limited
A109: ='2025'!A114 -> Round the Decay | B109: ='2025'!C114 -> Independent / Other | C109: ='2025'!D108 -> 45688 | D109: ='2025'!H114 -> Q1 2025 | E109: ='2025'!I114 -> Limited
A110: ='2025'!A116 -> The Kingdom | B110: ='2025'!C116 -> Unknown | C110: ='2025'!D109 -> 45688 | D110: ='2025'!H116 -> Q1 2025 | E110: ='2025'!I116 -> Limited
A111: ='2025'!A117 -> Time Passages | B111: ='2025'!C117 -> Independent / Other | C111: ='2025'!D110 -> 45688 | D111: ='2025'!H117 -> Q1 2025 | E111: ='2025'!I117 -> Limited
A112: ='2025'!A118 -> Valiant One | B112: ='2025'!C118 -> Independent / Other | C112: ='2025'!D111 -> 45688 | D112: ='2025'!H118 -> Q1 2025 | E112: ='2025'!I118 -> Wide
A113: ='2025'!A121 -> IU Concert: The Winning | B113: ='2025'!C121 -> Independent / Other | C113: ='2025'!D112 -> 45688 | D113: ='2025'!H121 -> Q1 2025 | E113: ='2025'!I121 -> Limited
A114: ='2025'!A122 -> A Knight’s War | B114: ='2025'!C122 -> Independent / Other | C114: ='2025'!D113 -> 45688 | D114: ='2025'!H122 -> Q1 2025 | E114: ='2025'!I122 -> Limited
A115: ='2025'!A124 -> Are You There? | B115: ='2025'!C124 -> Independent / Other | C115: ='2025'!D114 -> 45688 | D115: ='2025'!H124 -> Q1 2025 | E115: ='2025'!I124 -> Limited
A116: ='2025'!A125 -> Armand | B116: ='2025'!C125 -> IFC | C116: ='2025'!D115 -> 45688 | D116: ='2025'!H125 -> Q1 2025 | E116: ='2025'!I125 -> Wide
A117: ='2025'!A126 -> Becoming Led Zeppelin | B117: ='2025'!C126 -> Sony | C117: ='2025'!D116 -> 45688 | D117: ='2025'!H126 -> Q1 2025 | E117: ='2025'!I126 -> Wide
A118: ='2025'!A127 -> Black Panthers of WWII | B118: ='2025'!C127 -> Independent / Other | C118: ='2025'!D117 -> 45688 | D118: ='2025'!H127 -> Q1 2025 | E118: ='2025'!I127 -> Limited
A119: ='2025'!A128 -> Bring Them Down | B119: ='2025'!C128 -> Independent / Other | C119: ='2025'!D118 -> 45688 | D119: ='2025'!H128 -> Q1 2025 | E119: ='2025'!I128 -> Limited
A120: ='2025'!A129 -> Dark Nuns | B120: ='2025'!C129 -> Independent / Other | C120: ='2025'!D119 -> 45693 | D120: ='2025'!H129 -> Q1 2025 | E120: ='2025'!I129 -> Limited
A121: ='2025'!A130 -> Heart Eyes | B121: ='2025'!C130 -> Sony | C121: ='2025'!D120 -> 45693 | D121: ='2025'!H130 -> Q1 2025 | E121: ='2025'!I130 -> Wide
A122: ='2025'!A131 -> I Love You Forever | B122: ='2025'!C131 -> Independent / Other | C122: ='2025'!D121 -> 45693 | D122: ='2025'!H131 -> Q1 2025 | E122: ='2025'!I131 -> Limited
A123: ='2025'!A132 -> Jazzy | B123: ='2025'!C132 -> Independent / Other | C123: ='2025'!D122 -> 45695 | D123: ='2025'!H132 -> Q1 2025 | E123: ='2025'!I132 -> Limited
A124: ='2025'!A133 -> Love Hurts | B124: ='2025'!C133 -> Universal / NBCU | C124: ='2025'!D123 -> 45695 | D124: ='2025'!H133 -> Q1 2025 | E124: ='2025'!I133 -> Wide
A125: ='2025'!A136 -> Parthenope | B125: ='2025'!C136 -> A24 | C125: ='2025'!D124 -> 45695 | D125: ='2025'!H136 -> Q1 2025 | E125: ='2025'!I136 -> Limited
A126: ='2025'!A137 -> Renner | B126: ='2025'!C137 -> Independent / Other | C126: ='2025'!D125 -> 45695 | D126: ='2025'!H137 -> Q1 2025 | E126: ='2025'!I137 -> Limited
A127: ='2025'!A138 -> Suze | B127: ='2025'!C138 -> Independent / Other | C127: ='2025'!D126 -> 45695 | D127: ='2025'!H138 -> Q1 2025 | E127: ='2025'!I138 -> Limited
A128: ='2025'!A139 -> Vishwastha | B128: ='2025'!C139 -> Unknown | C128: ='2025'!D127 -> 45695 | D128: ='2025'!H139 -> Q1 2025 | E128: ='2025'!I139 -> Limited
A129: ='2025'!A140 -> When I’m Ready | B129: ='2025'!C140 -> Independent / Other | C129: ='2025'!D128 -> 45695 | D129: ='2025'!H140 -> Q1 2025 | E129: ='2025'!I140 -> Limited
A130: ='2025'!A141 -> UFC 312: du Plessis vs. Strickland 2 | B130: ='2025'!C141 -> Independent / Other | C130: ='2025'!D129 -> 45695 | D130: ='2025'!H141 -> Q1 2025 | E130: ='2025'!I141 -> Special Engagement
A131: ='2025'!A142 -> Attack on Titan the Movie: THE LAST ATTACK | B131: ='2025'!C142 -> Sony | C131: ='2025'!D130 -> 45695 | D131: ='2025'!H142 -> Q1 2025 | E131: ='2025'!I142 -> Special Engagement
A132: ='2025'!A143 -> Ski: The Greatest Ski Tour of All Time | B132: ='2025'!C143 -> Independent / Other | C132: ='2025'!D131 -> 45695 | D132: ='2025'!H143 -> Q1 2025 | E132: ='2025'!I143 -> Limited
A133: ='2025'!A144 -> Lifers: A Local H Movie | B133: ='2025'!C144 -> Unknown | C133: ='2025'!D132 -> 45695 | D133: ='2025'!H144 -> Q1 2025 | E133: ='2025'!I144 -> Limited
A134: ='2025'!A147 -> 2025 Oscar Shorts | B134: ='2025'!C147 -> Independent / Other | C134: ='2025'!D133 -> 45695 | D134: ='2025'!H147 -> Q1 2025 | E134: ='2025'!I147 -> Limited
A135: ='2025'!A148 -> Brahma Anandam | B135: ='2025'!C148 -> Independent / Other | C135: ='2025'!D134 -> 45695 | D135: ='2025'!H148 -> Q1 2025 | E135: ='2025'!I148 -> Limited
A136: ='2025'!A149 -> Bromance | B136: ='2025'!C149 -> Independent / Other | C136: ='2025'!D135 -> 45695 | D136: ='2025'!H149 -> Q1 2025 | E136: ='2025'!I149 -> Limited
A137: ='2025'!A150 -> Captain America: Brave New World | B137: ='2025'!C150 -> Disney | C137: ='2025'!D136 -> 45695 | D137: ='2025'!H150 -> Q1 2025 | E137: ='2025'!I150 -> Wide
A138: ='2025'!A151 -> Chhaava | B138: ='2025'!C151 -> Independent / Other | C138: ='2025'!D137 -> 45695 | D138: ='2025'!H151 -> Q1 2025 | E138: ='2025'!I151 -> Limited
A139: ='2025'!A152 -> Daveed | B139: ='2025'!C152 -> Independent / Other | C139: ='2025'!D138 -> 45695 | D139: ='2025'!H152 -> Q1 2025 | E139: ='2025'!I152 -> Limited
A140: ='2025'!A154 -> Illti | B140: ='2025'!C154 -> Unknown | C140: ='2025'!D139 -> 45695 | D140: ='2025'!H154 -> Q1 2025 | E140: ='2025'!I154 -> Limited
A141: ='2025'!A155 -> Kid Snow | B141: ='2025'!C155 -> Independent / Other | C141: ='2025'!D140 -> 45695 | D141: ='2025'!H155 -> Q1 2025 | E141: ='2025'!I155 -> Limited
A142: ='2025'!A156 -> Laila | B142: ='2025'!C156 -> Independent / Other | C142: ='2025'!D141 -> 45696 | D142: ='2025'!H156 -> Q1 2025 | E142: ='2025'!I156 -> Limited
A143: ='2025'!A157 -> Ne Zha 2 | B143: ='2025'!C157 -> Independent / Other | C143: ='2025'!D142 -> 45698 | D143: ='2025'!H157 -> Q1 2025 | E143: ='2025'!I157 -> Wide
A144: ='2025'!A158 -> Paddington in Peru | B144: ='2025'!C158 -> Sony | C144: ='2025'!D143 -> 45699 | D144: ='2025'!H158 -> Q1 2025 | E144: ='2025'!I158 -> Wide
A145: ='2025'!A159 -> Painkili | B145: ='2025'!C159 -> Independent / Other | C145: ='2025'!D144 -> 45700 | D145: ='2025'!H159 -> Q1 2025 | E145: ='2025'!I159 -> Limited
A146: ='2025'!A160 -> Rounding | B146: ='2025'!C160 -> Independent / Other | C146: ='2025'!D145 -> 45701 | D146: ='2025'!H160 -> Q1 2025 | E146: ='2025'!I160 -> Limited
A147: ='2025'!A161 -> Sex Love Venice | B147: ='2025'!C161 -> Independent / Other | C147: ='2025'!D146 -> 45701 | D147: ='2025'!H161 -> Q1 2025 | E147: ='2025'!I161 -> Limited
A148: ='2025'!A162 -> SNL50: The Homecoming Concert | B148: ='2025'!C162 -> Independent / Other | C148: ='2025'!D147 -> 45702 | D148: ='2025'!H162 -> Q1 2025 | E148: ='2025'!I162 -> Special Engagement
A149: ='2025'!A163 -> The Long Game | B149: ='2025'!C163 -> Independent / Other | C149: ='2025'!D148 -> 45702 | D149: ='2025'!H163 -> Q1 2025 | E149: ='2025'!I163 -> Limited
A150: ='2025'!A164 -> The Vortex | B150: ='2025'!C164 -> Independent / Other | C150: ='2025'!D149 -> 45702 | D150: ='2025'!H164 -> Q1 2025 | E150: ='2025'!I164 -> Limited
...

Sheet Summary 2026
A1: 2026 Releases
A2: Title | B2: Parent Company | C2: Release Date | D2: Release Quarter | E2: Release Type
A3: ='2026'!A2 -> Ikkis | B3: ='2026'!C2 -> Independent / Other | C3: ='2026'!D2 -> 46023 | D3: ='2026'!H2 -> Q1 2026 | E3: ='2026'!I2 -> Limited
A4: ='2026'!A3 -> Patang | B4: ='2026'!C3 -> Unknown | C4: ='2026'!D3 -> 46023 | D4: ='2026'!H3 -> Q1 2026 | E4: ='2026'!I3 -> Limited
A5: ='2026'!A4 -> KIDZ BOP LIVE: The Concert Movie | B5: ='2026'!C4 -> Independent / Other | C5: ='2026'!D4 -> 46024 | D5: ='2026'!H4 -> Q1 2026 | E5: ='2026'!I4 -> Limited
A6: ='2026'!A5 -> The Dutchman | B6: ='2026'!C5 -> Independent / Other | C6: ='2026'!D5 -> 46024 | D6: ='2026'!H5 -> Q1 2026 | E6: ='2026'!I5 -> Limited
A7: ='2026'!A6 -> We Bury the Dead | B7: ='2026'!C6 -> Independent / Other | C7: ='2026'!D6 -> 46024 | D7: ='2026'!H6 -> Q1 2026 | E7: ='2026'!I6 -> Limited
A8: ='2026'!A7 -> Lupin the IIIRD: The Movie — The Immortal Bloodline | B8: ='2026'!C7 -> Independent / Other | C8: ='2026'!D7 -> 46026 | D8: ='2026'!H7 -> Q1 2026 | E8: ='2026'!I7 -> Limited
A9: ='2026'!A8 -> Weathered: Inside the LA Firestorm | B9: ='2026'!C8 -> Independent / Other | C9: ='2026'!D8 -> 46029 | D9: ='2026'!H8 -> Q1 2026 | E9: ='2026'!I8 -> Limited
A10: ='2026'!A10 -> The Raja Saab | B10: ='2026'!C10 -> Independent / Other | C10: ='2026'!D9 -> 46030 | D10: ='2026'!H10 -> Q1 2026 | E10: ='2026'!I10 -> Wide
A11: ='2026'!A11 -> 31 Candles | B11: ='2026'!C11 -> Independent / Other | C11: ='2026'!D10 -> 46030 | D11: ='2026'!H11 -> Q1 2026 | E11: ='2026'!I11 -> Limited
A12: ='2026'!A12 -> All That’s Left Of You | B12: ='2026'!C12 -> Independent / Other | C12: ='2026'!D11 -> 46031 | D12: ='2026'!H12 -> Q1 2026 | E12: ='2026'!I12 -> Limited
A13: ='2026'!A13 -> Bulls | B13: ='2026'!C13 -> Independent / Other | C13: ='2026'!D12 -> 46031 | D13: ='2026'!H13 -> Q1 2026 | E13: ='2026'!I13 -> Limited
A14: ='2026'!A14 -> Buratino | B14: ='2026'!C14 -> Unknown | C14: ='2026'!D13 -> 46031 | D14: ='2026'!H14 -> Q1 2026 | E14: ='2026'!I14 -> Limited
A15: ='2026'!A15 -> Dead Man’s Wire | B15: ='2026'!C15 -> Independent / Other | C15: ='2026'!D14 -> 46031 | D15: ='2026'!H15 -> Q1 2026 | E15: ='2026'!I15 -> Wide
A16: ='2026'!A16 -> Greenland 2: Migration | B16: ='2026'!C16 -> Lionsgate | C16: ='2026'!D15 -> 46031 | D16: ='2026'!H16 -> Q1 2026 | E16: ='2026'!I16 -> Wide
A17: ='2026'!A17 -> Holding Liat | B17: ='2026'!C17 -> Independent / Other | C17: ='2026'!D16 -> 46031 | D17: ='2026'!H17 -> Q1 2026 | E17: ='2026'!I17 -> Limited
A18: ='2026'!A18 -> I Was a Stranger | B18: ='2026'!C18 -> Angel Studios | C18: ='2026'!D17 -> 46031 | D18: ='2026'!H18 -> Q1 2026 | E18: ='2026'!I18 -> Wide
A19: ='2026'!A19 -> Is This Thing On? | B19: ='2026'!C19 -> Disney | C19: ='2026'!D18 -> 46031 | D19: ='2026'!H19 -> Q1 2026 | E19: ='2026'!I19 -> Wide
A20: ='2026'!A20 -> Magellan | B20: ='2026'!C20 -> Independent / Other | C20: ='2026'!D19 -> 46031 | D20: ='2026'!H20 -> Q1 2026 | E20: ='2026'!I20 -> Limited
A21: ='2026'!A21 -> My Neighbor Adolf | B21: ='2026'!C21 -> Independent / Other | C21: ='2026'!D20 -> 46031 | D21: ='2026'!H21 -> Q1 2026 | E21: ='2026'!I21 -> Limited
... A23: ='2026'!A23 -> Oscar Shaw | B23: ='2026'!C23 -> Independent / Other | C23: ='2026'!D22 -> 46031 | D23: ='2026'!H23 -> Q1 2026 | E23: ='2026'!I23 -> Limited
A24: ='2026'!A25 -> Primate | B24: ='2026'!C25 -> Paramount | C24: ='2026'!D23 -> 46031 | D24: ='2026'!H25 -> Q1 2026 | E24: ='2026'!I25 -> Wide
A25: ='2026'!A26 -> Sleepwalker | B25: ='2026'!C26 -> Independent / Other | C25: ='2026'!D24 -> 46031 | D25: ='2026'!H26 -> Q1 2026 | E25: ='2026'!I26 -> Limited
A26: ='2026'!A27 -> The Voice of Hind Rajab | B26: ='2026'!C27 -> Independent / Other | C26: ='2026'!D25 -> 46031 | D26: ='2026'!H27 -> Q1 2026 | E26: ='2026'!I27 -> Limited
A27: ='2026'!A28 -> Young Mothers | B27: ='2026'!C28 -> Independent / Other | C27: ='2026'!D26 -> 46031 | D27: ='2026'!H28 -> Q1 2026 | E27: ='2026'!I28 -> Limited
A28: ='2026'!A29 -> Mana ShankaraVaraprasad Garu | B28: ='2026'!C29 -> Independent / Other | C28: ='2026'!D27 -> 46031 | D28: ='2026'!H29 -> Q1 2026 | E28: ='2026'!I29 -> Limited
A29: ='2026'!A30 -> Godfrey: Rebel with a Cause | B29: ='2026'!C30 -> Independent / Other | C29: ='2026'!D28 -> 46031 | D29: ='2026'!H30 -> Q1 2026 | E29: ='2026'!I30 -> Limited
A30: ='2026'!A31 -> Nari Nari Naduma Murari | B30: ='2026'!C31 -> Independent / Other | C30: ='2026'!D29 -> 46034 | D30: ='2026'!H31 -> Q1 2026 | E30: ='2026'!I31 -> Limited
A31: ='2026'!A32 -> Once Upon My Mother | B31: ='2026'!C32 -> Unknown | C31: ='2026'!D30 -> 46036 | D31: ='2026'!H32 -> Q1 2026 | E31: ='2026'!I32 -> Limited
A32: ='2026'!A33 -> TTT: Thalaivar Thambi Thalamaiyil | B32: ='2026'!C33 -> Independent / Other | C32: ='2026'!D31 -> 46036 | D32: ='2026'!H33 -> Q1 2026 | E32: ='2026'!I33 -> Limited
A33: ='2026'!A34 -> 28 Years Later: The Bone Temple | B33: ='2026'!C34 -> Sony | C33: ='2026'!D32 -> 46036 | D33: ='2026'!H34 -> Q1 2026 | E33: ='2026'!I34 -> Wide
A34: ='2026'!A35 -> A Private Life | B34: ='2026'!C35 -> Sony | C34: ='2026'!D33 -> 46037 | D34: ='2026'!H35 -> Q1 2026 | E34: ='2026'!I35 -> Limited
A35: ='2026'!A36 -> A Useful Ghost | B35: ='2026'!C36 -> Independent / Other | C35: ='2026'!D34 -> 46038 | D35: ='2026'!H36 -> Q1 2026 | E35: ='2026'!I36 -> Limited
... A42: ='2026'!A43 -> Leave | B42: ='2026'!C43 -> Independent / Other | C42: ='2026'!D41 -> 46038 | D42: ='2026'!H43 -> Q1 2026 | E42: ='2026'!I43 -> Limited
A43: ='2026'!A45 -> Night Patrol | B43: ='2026'!C45 -> IFC | C43: ='2026'!D42 -> 46038 | D43: ='2026'!H45 -> Q1 2026 | E43: ='2026'!I45 -> Wide
A44: ='2026'!A46 -> No Other Choice | B44: ='2026'!C46 -> Neon | C44: ='2026'!D43 -> 46038 | D44: ='2026'!H46 -> Q1 2026 | E44: ='2026'!I46 -> Wide
A45: ='2026'!A48 -> Shuffle | B45: ='2026'!C48 -> Independent / Other | C45: ='2026'!D44 -> 46038 | D45: ='2026'!H48 -> Q1 2026 | E45: ='2026'!I48 -> Limited
A46: ='2026'!A49 -> Signing Tony Raymond | B46: ='2026'!C49 -> Independent / Other | C46: ='2026'!D45 -> 46038 | D46: ='2026'!H49 -> Q1 2026 | E46: ='2026'!I49 -> Limited
A47: ='2026'!A50 -> Sound of Falling | B47: ='2026'!C50 -> Unknown | C47: ='2026'!D46 -> 46038 | D47: ='2026'!H50 -> Q1 2026 | E47: ='2026'!I50 -> Limited
A48: ='2026'!A51 -> The Choral | B48: ='2026'!C51 -> Sony | C48: ='2026'!D47 -> 46038 | D48: ='2026'!H51 -> Q1 2026 | E48: ='2026'!I51 -> Wide
A49: ='2026'!A52 -> The Fire Raven | B49: ='2026'!C52 -> Independent / Other | C49: ='2026'!D48 -> 46038 | D49: ='2026'!H52 -> Q1 2026 | E49: ='2026'!I52 -> Limited
A50: ='2026'!A54 -> Vaa Vaathiyaar | B50: ='2026'!C54 -> Independent / Other | C50: ='2026'!D49 -> 46038 | D50: ='2026'!H54 -> Q1 2026 | E50: ='2026'!I54 -> Limited
A51: ='2026'!A57 -> Zombie Land Saga: Yumeginga Paradise | B51: ='2026'!C57 -> Sony | C51: ='2026'!D50 -> 46038 | D51: ='2026'!H57 -> Q1 2026 | E51: ='2026'!I57 -> Limited
A52: ='2026'!A58 -> 267 | B52: ='2026'!C58 -> Unknown | C52: ='2026'!D51 -> 46038 | D52: ='2026'!H58 -> Q1 2026 | E52: ='2026'!I58 -> Limited
A53: ='2026'!A59 -> 2DIE4 | B53: ='2026'!C59 -> Independent / Other | C53: ='2026'!D52 -> 46038 | D53: ='2026'!H59 -> Q1 2026 | E53: ='2026'!I59 -> Special Engagement
A54: ='2026'!A60 -> Mr. Nobody Against Putin | B54: ='2026'!C60 -> Independent / Other | C54: ='2026'!D53 -> 46038 | D54: ='2026'!H60 -> Q1 2026 | E54: ='2026'!I60 -> Limited
A55: ='2026'!A61 -> Chatha Pacha: The Ring of Rowdies | B55: ='2026'!C61 -> Unknown | C55: ='2026'!D54 -> 46038 | D55: ='2026'!H61 -> Q1 2026 | E55: ='2026'!I61 -> Limited
A56: ='2026'!A62 -> Cosmic Princess Kaguya! | B56: ='2026'!C62 -> Netflix | C56: ='2026'!D55 -> 46039 | D56: ='2026'!H62 -> Q1 2026 | E56: ='2026'!I62 -> Limited
A57: ='2026'!A63 -> Megadeth: Behind the Mask | B57: ='2026'!C63 -> Independent / Other | C57: ='2026'!D56 -> 46040 | D57: ='2026'!H63 -> Q1 2026 | E57: ='2026'!I63 -> Special Engagement
A58: ='2026'!A64 -> Arco | B58: ='2026'!C64 -> Neon | C58: ='2026'!D57 -> 46041 | D58: ='2026'!H64 -> Q1 2026 | E58: ='2026'!I64 -> Limited
A59: ='2026'!A65 -> Baby Girl | B59: ='2026'!C65 -> Unknown | C59: ='2026'!D58 -> 46043 | D59: ='2026'!H65 -> Q1 2026 | E59: ='2026'!I65 -> Limited
A60: ='2026'!A66 -> Border 2 | B60: ='2026'!C66 -> Independent / Other | C60: ='2026'!D59 -> 46043 | D60: ='2026'!H66 -> Q1 2026 | E60: ='2026'!I66 -> Limited
A61: ='2026'!A67 -> Clika | B61: ='2026'!C67 -> Sony | C61: ='2026'!D60 -> 46043 | D61: ='2026'!H67 -> Q1 2026 | E61: ='2026'!I67 -> Limited
A62: ='2026'!A69 -> Dollface: The Motion Picture | B62: ='2026'!C69 -> Unknown | C62: ='2026'!D61 -> 46044 | D62: ='2026'!H69 -> Q1 2026 | E62: ='2026'!I69 -> Limited
A63: ='2026'!A70 -> Dooba Dooba | B63: ='2026'!C70 -> Independent / Other | C63: ='2026'!D62 -> 46044 | D63: ='2026'!H70 -> Q1 2026 | E63: ='2026'!I70 -> Limited
A64: ='2026'!A71 -> H is for Hawk | B64: ='2026'!C71 -> Independent / Other | C64: ='2026'!D63 -> 46044 | D64: ='2026'!H71 -> Q1 2026 | E64: ='2026'!I71 -> Wide
A65: ='2026'!A72 -> He’s Watching You | B65: ='2026'!C72 -> Independent / Other | C65: ='2026'!D64 -> 46045 | D65: ='2026'!H72 -> Q1 2026 | E65: ='2026'!I72 -> Limited
A66: ='2026'!A73 -> In Cold Light | B66: ='2026'!C73 -> Independent / Other | C66: ='2026'!D65 -> 46045 | D66: ='2026'!H73 -> Q1 2026 | E66: ='2026'!I73 -> Limited
A67: ='2026'!A74 -> Its Presence Between Us | B67: ='2026'!C74 -> Unknown | C67: ='2026'!D66 -> 46045 | D67: ='2026'!H74 -> Q1 2026 | E67: ='2026'!I74 -> Limited
A68: ='2026'!A75 -> Magic Mushrooms | B68: ='2026'!C75 -> Independent / Other | C68: ='2026'!D67 -> 46045 | D68: ='2026'!H75 -> Q1 2026 | E68: ='2026'!I75 -> Limited
A69: ='2026'!A76 -> Mercy | B69: ='2026'!C76 -> Amazon | C69: ='2026'!D68 -> 46045 | D69: ='2026'!H76 -> Q1 2026 | E69: ='2026'!I76 -> Wide
A70: ='2026'!A77 -> Pennu Case | B70: ='2026'!C77 -> Independent / Other | C70: ='2026'!D69 -> 46045 | D70: ='2026'!H77 -> Q1 2026 | E70: ='2026'!I77 -> Limited
A71: ='2026'!A78 -> Return to Silent Hill | B71: ='2026'!C78 -> Independent / Other | C71: ='2026'!D70 -> 46045 | D71: ='2026'!H78 -> Q1 2026 | E71: ='2026'!I78 -> Wide
A72: ='2026'!A79 -> Sinners | B72: ='2026'!C79 -> Warner Bros. Discovery | C72: ='2026'!D71 -> 46045 | D72: ='2026'!H79 -> Q1 2026 | E72: ='2026'!I79 -> Wide
A73: ='2026'!A80 -> Standout: The Ben Kjar Story | B73: ='2026'!C80 -> Angel Studios | C73: ='2026'!D72 -> 46045 | D73: ='2026'!H80 -> Q1 2026 | E73: ='2026'!I80 -> Limited
... A78: ='2026'!A85 -> UFC 324: Gaethje vs. Pimblett | B78: ='2026'!C85 -> Independent / Other | C78: ='2026'!D77 -> 46045 | D78: ='2026'!H85 -> Q1 2026 | E78: ='2026'!I85 -> Special Engagement
A79: ='2026'!A87 -> A Poet | B79: ='2026'!C87 -> Independent / Other | C79: ='2026'!D78 -> 46045 | D79: ='2026'!H87 -> Q1 2026 | E79: ='2026'!I87 -> Limited
A80: ='2026'!A88 -> Back to the Past | B80: ='2026'!C88 -> Independent / Other | C80: ='2026'!D79 -> 46045 | D80: ='2026'!H88 -> Q1 2026 | E80: ='2026'!I88 -> Limited
A81: ='2026'!A90 -> Busted Water Pipes | B81: ='2026'!C90 -> Independent / Other | C81: ='2026'!D80 -> 46045 | D81: ='2026'!H90 -> Q1 2026 | E81: ='2026'!I90 -> Limited
A82: ='2026'!A91 -> Fish, Fists and Ambergris! | B82: ='2026'!C91 -> Independent / Other | C82: ='2026'!D81 -> 46045 | D82: ='2026'!H91 -> Q1 2026 | E82: ='2026'!I91 -> Limited
A83: ='2026'!A92 -> Gandhi Talks | B83: ='2026'!C92 -> Independent / Other | C83: ='2026'!D82 -> 46045 | D83: ='2026'!H92 -> Q1 2026 | E83: ='2026'!I92 -> Limited
A84: ='2026'!A93 -> Infinite Icon: A Visual Memoir | B84: ='2026'!C93 -> Independent / Other | C84: ='2026'!D83 -> 46045 | D84: ='2026'!H93 -> Q1 2026 | E84: ='2026'!I93 -> Limited
A85: ='2026'!A94 -> Iron Lung | B85: ='2026'!C94 -> Independent / Other | C85: ='2026'!D84 -> 46045 | D85: ='2026'!H94 -> Q1 2026 | E85: ='2026'!I94 -> Wide
A86: ='2026'!A95 -> Islands | B86: ='2026'!C95 -> Independent / Other | C86: ='2026'!D85 -> 46046 | D86: ='2026'!H95 -> Q1 2026 | E86: ='2026'!I95 -> Limited
A87: ='2026'!A96 -> Mardaani 3 | B87: ='2026'!C96 -> Independent / Other | C87: ='2026'!D86 -> 46047 | D87: ='2026'!H96 -> Q1 2026 | E87: ='2026'!I96 -> Limited
A88: ='2026'!A97 -> Medias Hermanas | B88: ='2026'!C97 -> Independent / Other | C88: ='2026'!D87 -> 46052 | D88: ='2026'!H97 -> Q1 2026 | E88: ='2026'!I97 -> Limited
A89: ='2026'!A98 -> Melania | B89: ='2026'!C98 -> Amazon | C89: ='2026'!D88 -> 46052 | D89: ='2026'!H98 -> Q1 2026 | E89: ='2026'!I98 -> Wide
A90: ='2026'!A99 -> Moses the Black | B90: ='2026'!C99 -> Independent / Other | C90: ='2026'!D89 -> 46052 | D90: ='2026'!H99 -> Q1 2026 | E90: ='2026'!I99 -> Limited
A91: ='2026'!A100 -> Natchez | B91: ='2026'!C100 -> Independent / Other | C91: ='2026'!D90 -> 46052 | D91: ='2026'!H100 -> Q1 2026 | E91: ='2026'!I100 -> Limited
A92: ='2026'!A101 -> Om Shanti Shanti Shantihi | B92: ='2026'!C101 -> Independent / Other | C92: ='2026'!D91 -> 46052 | D92: ='2026'!H101 -> Q1 2026 | E92: ='2026'!I101 -> Limited
... A161: ='2026'!A170 -> O’Romeo | B161: ='2026'!C170 -> Independent / Other | C161: ='2026'!D160 -> 46066 | D161: ='2026'!H170 -> Q1 2026 | E161: ='2026'!I170 -> Limited
A162: ='2026'!A172 -> Step Back, Doors Closing | B162: ='2026'!C172 -> Independent / Other | C162: ='2026'!D161 -> 46066 | D162: ='2026'!H172 -> Q1 2026 | E162: ='2026'!I172 -> Limited
A163: ='2026'!A173 -> The Haunted Forest | B163: ='2026'!C173 -> Independent / Other | C163: ='2026'!D162 -> 46066 | D163: ='2026'!H173 -> Q1 2026 | E163: ='2026'!I173 -> Limited
A164: ='2026'!A174 -> The Mortuary Assistant | B164: ='2026'!C174 -> Independent / Other | C164: ='2026'!D163 -> 46066 | D164: ='2026'!H174 -> Q1 2026 | E164: ='2026'!I174 -> Limited
A165: ='2026'!A175 -> The Observance | B165: ='2026'!C175 -> Unknown | C165: ='2026'!D164 -> 46066 | D165: ='2026'!H175 -> Q1 2026 | E165: ='2026'!I175 -> Limited
A166: ='2026'!A176 -> The Swedish Connection | B166: ='2026'!C176 -> Netflix | C166: ='2026'!D165 -> 46066 | D166: ='2026'!H176 -> Q1 2026 | E166: ='2026'!I176 -> Limited
A167: ='2026'!A178 -> Tu Yaa Main | B167: ='2026'!C178 -> Independent / Other | C167: ='2026'!D166 -> 46066 | D167: ='2026'!H178 -> Q1 2026 | E167: ='2026'!I178 -> Limited
A168: ='2026'!A179 -> “Wuthering Heights” | B168: ='2026'!C179 -> Warner Bros. Discovery | C168: ='2026'!D167 -> 46066 | D168: ='2026'!H179 -> Q1 2026 | E168: ='2026'!I179 -> Wide
A169: ='2026'!A180 -> Couple Friendly | B169: ='2026'!C180 -> Independent / Other | C169: ='2026'!D168 -> 46066 | D169: ='2026'!H180 -> Q1 2026 | E169: ='2026'!I180 -> Limited
A170: ='2026'!A181 -> Seetha Payanam | B170: ='2026'!C181 -> Independent / Other | C170: ='2026'!D169 -> 46066 | D170: ='2026'!H181 -> Q1 2026 | E170: ='2026'!I181 -> Limited
A171: ='2026'!A182 -> The Apocalypse of St. John | B171: ='2026'!C182 -> Independent / Other | C171: ='2026'!D170 -> 46066 | D171: ='2026'!H182 -> Q1 2026 | E171: ='2026'!I182 -> Special Engagement
A172: ='2026'!A184 -> Blades of the Guardians | B172: ='2026'!C184 -> Independent / Other | C172: ='2026'!D171 -> 46066 | D172: ='2026'!H184 -> Q1 2026 | E172: ='2026'!I184 -> Limited
A173: ='2026'!A185 -> Chase Atlantic: Lost in Heaven | B173: ='2026'!C185 -> Independent / Other | C173: ='2026'!D172 -> 46066 | D173: ='2026'!H185 -> Q1 2026 | E173: ='2026'!I185 -> Special Engagement
A174: ='2026'!A186 -> Dump of Untitled Pieces | B174: ='2026'!C186 -> Unknown | C174: ='2026'!D173 -> 46066 | D174: ='2026'!H186 -> Q1 2026 | E174: ='2026'!I186 -> Festival Screening
A175: ='2026'!A187 -> Paul McCartney: Man on the Run | B175: ='2026'!C187 -> Independent / Other | C175: ='2026'!D174 -> 46066 | D175: ='2026'!H187 -> Q1 2026 | E175: ='2026'!I187 -> Special Engagement
A176: ='2026'!A188 -> 2026 Oscar Shorts | B176: ='2026'!C188 -> Independent / Other | C176: ='2026'!D175 -> 46066 | D176: ='2026'!H188 -> Q1 2026 | E176: ='2026'!I188 -> Limited
A177: ='2026'!A189 -> Assi | B177: ='2026'!C189 -> Independent / Other | C177: ='2026'!D176 -> 46066 | D177: ='2026'!H189 -> Q1 2026 | E177: ='2026'!I189 -> Limited
A178: ='2026'!A190 -> Bambukat 2 | B178: ='2026'!C190 -> Independent / Other | C178: ='2026'!D177 -> 46066 | D178: ='2026'!H190 -> Q1 2026 | E178: ='2026'!I190 -> Limited
A179: ='2026'!A191 -> Billy Preston: That’s the Way God Planned It | B179: ='2026'!C191 -> Independent / Other | C179: ='2026'!D178 -> 46066 | D179: ='2026'!H191 -> Q1 2026 | E179: ='2026'!I191 -> Limited
...

Sheet Summary 2027
A1: 2027 Releases
A2: Title | B2: Parent Company | C2: Release Date | D2: Release Quarter | E2: Release Type
A3: ='2027'!A2 -> Bagworm | B3: ='2027'!C2 -> Independent / Other | C3: ='2027'!D2 -> 46388 | D3: ='2027'!H2 -> Q1 2027 | E3: ='2027'!I2 -> Limited
A4: ='2027'!A3 -> Pendulum | B4: ='2027'!C3 -> Independent / Other | C4: ='2027'!D3 -> 46388 | D4: ='2027'!H3 -> Q1 2027 | E4: ='2027'!I3 -> Wide
A5: ='2027'!A4 -> The Meltdown | B5: ='2027'!C4 -> Independent / Other | C5: ='2027'!D4 -> 46388 | D5: ='2027'!H4 -> Q1 2027 | E5: ='2027'!I4 -> Limited
A6: ='2027'!A5 -> Untitled Shudder Horror Film | B6: ='2027'!C5 -> Independent / Other | C6: ='2027'!D5 -> 46395 | D6: ='2027'!H5 -> Q1 2027 | E6: ='2027'!I5 -> Limited
A7: ='2027'!A6 -> Children of Blood and Bone | B7: ='2027'!C6 -> Paramount | C7: ='2027'!D6 -> 46402 | D7: ='2027'!H6 -> Q1 2027 | E7: ='2027'!I6 -> Wide
A8: ='2027'!A7 -> The Beekeeper 2 | B8: ='2027'!C7 -> Amazon | C8: ='2027'!D7 -> 46402 | D8: ='2027'!H7 -> Q1 2027 | E8: ='2027'!I7 -> Wide
A9: ='2027'!A8 -> Untitled Blumhouse Event Film | B9: ='2027'!C8 -> Universal / NBCU | C9: ='2027'!D8 -> 46402 | D9: ='2027'!H8 -> Q1 2027 | E9: ='2027'!I8 -> Wide
A10: ='2027'!A9 -> Air Bud Returns | B10: ='2027'!C9 -> Independent / Other | C10: ='2027'!D9 -> 46409 | D10: ='2027'!H9 -> Q1 2027 | E10: ='2027'!I9 -> Wide
A11: ='2027'!A10 -> Animal Friends | B11: ='2027'!C10 -> Warner Bros. Discovery | C11: ='2027'!D10 -> 46409 | D11: ='2027'!H10 -> Q1 2027 | E11: ='2027'!I10 -> Wide
A12: ='2027'!A11 -> The Third Parent | B12: ='2027'!C11 -> Bleecker Street | C12: ='2027'!D11 -> 46409 | D12: ='2027'!H11 -> Q1 2027 | E12: ='2027'!I11 -> Wide
A13: ='2027'!A12 -> Drag | B13: ='2027'!C12 -> Independent / Other | C13: ='2027'!D12 -> 46416 | D13: ='2027'!H12 -> Q1 2027 | E13: ='2027'!I12 -> Wide
A14: ='2027'!A13 -> Karoshi | B14: ='2027'!C13 -> Lionsgate | C14: ='2027'!D13 -> 46416 | D14: ='2027'!H13 -> Q1 2027 | E14: ='2027'!I13 -> Wide
... A23: ='2027'!A22 -> CoComelon: The Movie | B23: ='2027'!C22 -> Universal / NBCU | C23: ='2027'!D22 -> 46437 | D23: ='2027'!H22 -> Q1 2027 | E23: ='2027'!I22 -> Wide
A24: ='2027'!A24 -> Untitled Neon Horror Film | B24: ='2027'!C24 -> Neon | C24: ='2027'!D23 -> 46437 | D24: ='2027'!H24 -> Q1 2027 | E24: ='2027'!I24 -> Wide
A25: ='2027'!A25 -> Wife & Dog | B25: ='2027'!C25 -> Independent / Other | C25: ='2027'!D24 -> 46437 | D25: ='2027'!H25 -> Q1 2027 | E25: ='2027'!I25 -> Wide
A26: ='2027'!A26 -> K-Pop: The Debut | B26: ='2027'!C26 -> Paramount | C26: ='2027'!D25 -> 46437 | D26: ='2027'!H26 -> Q1 2027 | E26: ='2027'!I26 -> Wide
A27: ='2027'!A27 -> Live Like That | B27: ='2027'!C27 -> Sony | C27: ='2027'!D26 -> 46444 | D27: ='2027'!H27 -> Q1 2027 | E27: ='2027'!I27 -> Wide
A28: ='2027'!A28 -> The Revenge of La Llorona | B28: ='2027'!C28 -> Warner Bros. Discovery | C28: ='2027'!D27 -> 46444 | D28: ='2027'!H28 -> Q1 2027 | E28: ='2027'!I28 -> Wide
A29: ='2027'!A29 -> Gatto | B29: ='2027'!C29 -> Disney | C29: ='2027'!D28 -> 46444 | D29: ='2027'!H29 -> Q1 2027 | E29: ='2027'!I29 -> Wide
A30: ='2027'!A30 -> The Thomas Crown Affair | B30: ='2027'!C30 -> Amazon | C30: ='2027'!D29 -> 46451 | D30: ='2027'!H30 -> Q1 2027 | E30: ='2027'!I30 -> Wide
A31: ='2027'!A31 -> Untitled DC Event Film | B31: ='2027'!C31 -> Warner Bros. Discovery | C31: ='2027'!D30 -> 46451 | D31: ='2027'!H31 -> Q1 2027 | E31: ='2027'!I31 -> Wide
A32: ='2027'!A32 -> Untitled Mike Flanagan Exorcist Film | B32: ='2027'!C32 -> Universal / NBCU | C32: ='2027'!D31 -> 46451 | D32: ='2027'!H32 -> Q1 2027 | E32: ='2027'!I32 -> Wide
A33: ='2027'!A33 -> Untitled The Chosen Season 6 Finale Film | B33: ='2027'!C33 -> Amazon | C33: ='2027'!D32 -> 46458 | D33: ='2027'!H33 -> Q1 2027 | E33: ='2027'!I33 -> Wide
A34: ='2027'!A34 -> Untitled Warner Bros. Event Film | B34: ='2027'!C34 -> Warner Bros. Discovery | C34: ='2027'!D33 -> 46458 | D34: ='2027'!H34 -> Q1 2027 | E34: ='2027'!I34 -> Wide
A35: ='2027'!A35 -> Sonic the Hedgehog 4 | B35: ='2027'!C35 -> Paramount | C35: ='2027'!D34 -> 46458 | D35: ='2027'!H35 -> Q1 2027 | E35: ='2027'!I35 -> Wide
... A107: ='2027'!A107 -> Zac Power | B107: ='2027'!C107 -> Independent / Other | C107: ='2027'!D106 -> 46752 | D107: ='2027'!H107 -> TBD 2027 | E107: ='2027'!I107 -> Wide

Sheet Data ->

Sheet 2025
A1: Title | B1: Distributor | C1: Parent Company | D1: Release Date | E1: Date Precision | F1: Date (as sourced) | G1: Wide Expansion Date | H1: Release Quarter | I1: Release Type | J1: Is Re-release | K1: Is IMAX | L1: Domestic BO (Lifetime) | M1: BO Caveat | N1: Is Canceled | O1: Is Catalog Aggregate | P1: Dup BO Flag | Q1: Merge Span (days) | R1: In Scope
A2: From Ground Zero | B2: Watermelon Pictures | C2: Independent / Other | D2: 45660 | E2: exact | F2: 2025-01-03 | H2: Q1 2025 | I2: Limited | J2: FALSE | K2: FALSE | L2: 330188 | N2: FALSE | O2: FALSE | P2: FALSE | Q2: 0 | R2: FALSE
A3: Georgia O’Keeffe: The Brightness of Light | B3: Cargo Film & Releasing | C3: Independent / Other | D3: 45660 | E3: exact | F3: 2025-01-03 | H3: Q1 2025 | I3: Limited | J3: FALSE | K3: FALSE | L3: 166349 | N3: FALSE | O3: FALSE | P3: FALSE | Q3: 0 | R3: FALSE
A4: Se7en | B4: Warner Bros. | C4: Warner Bros. Discovery | D4: 45660 | E4: exact | F4: 2025-01-03 | H4: Q1 2025 | I4: Special Engagement | J4: TRUE | K4: TRUE | L4: 101871174 | M4: Lifetime gross incl. original run - not 2025 revenue | N4: FALSE | O4: FALSE | P4: FALSE | Q4: 0 | R4: TRUE
A5: The Damned | B5: Vertical Entertainment | C5: Independent / Other | D5: 45660 | E5: exact | F5: 2025-01-03 | H5: Q1 2025 | I5: Wide | J5: FALSE | K5: FALSE | L5: 1342796 | N5: FALSE | O5: FALSE | P5: FALSE | Q5: 0 | R5: FALSE
A6: The Last Republican | B6: Media Courthouse Documentary Collective | C6: Independent / Other | D6: 45660 | E6: exact | F6: 2025-01-03 | H6: Q1 2025 | I6: Limited | J6: FALSE | K6: FALSE | N6: FALSE | O6: FALSE | P6: FALSE | Q6: 0 | R6: FALSE
A7: The Monster Beneath Us | B7: Vertical Entertainment | C7: Independent / Other | D7: 45660 | E7: exact | F7: 2025-01-03 | H7: Q1 2025 | I7: Limited | J7: FALSE | K7: FALSE | N7: FALSE | O7: FALSE | P7: FALSE | Q7: 0 | R7: FALSE
A8: AXCN: Paprika | B8: Iconic Releasing | C8: Independent / Other | D8: 45665 | E8: exact | F8: 2025-01-08 | H8: Q1 2025 | I8: Special Engagement | J8: TRUE | K8: FALSE | L8: 881302 | M8: Lifetime gross incl. original run - not 2025 revenue | N8: FALSE | O8: FALSE | P8: FALSE | Q8: 0 | R8: FALSE
A9: Better Man | B9: Paramount Pictures | C9: Paramount | D9: 45667 | E9: exact | F9: 2025-01-10 | H9: Q1 2025 | I9: Wide | J9: FALSE | K9: FALSE | L9: 1983648 | N9: FALSE | O9: FALSE | P9: FALSE | Q9: 0 | R9: TRUE
A10: Birdeater | B10: Dark Sky Films | C10: Independent / Other | D10: 45667 | E10: exact | F10: 2025-01-10 | H10: Q1 2025 | I10: Limited | J10: FALSE | K10: FALSE | N10: FALSE | O10: FALSE | P10: FALSE | Q10: 0 | R10: FALSE
A11: Black Diamond | B11: Brainstorm Media | C11: Independent / Other | D11: 45667 | E11: exact | F11: 2025-01-10 | H11: Q1 2025 | I11: Limited | J11: FALSE | K11: FALSE | N11: FALSE | O11: FALSE | P11: FALSE | Q11: 0 | R11: FALSE
A12: Black Zone | B12: Black Zone Productions | C12: Independent / Other | D12: 45667 | E12: exact | F12: 2025-01-10 | H12: Q1 2025 | I12: Limited | J12: FALSE | K12: FALSE | N12: FALSE | O12: FALSE | P12: FALSE | Q12: 0 | R12: FALSE
A13: Den of Thieves 2: Pantera | B13: Lionsgate | C13: Lionsgate | D13: 45667 | E13: exact | F13: 2025-01-10 | H13: Q1 2025 | I13: Wide | J13: FALSE | K13: FALSE | L13: 36015016 | N13: FALSE | O13: FALSE | P13: FALSE | Q13: 0 | R13: TRUE
A14: Diane Warren: Relentless | B14: Greenwich | C14: Independent / Other | D14: 45667 | E14: exact | F14: 2025-01-10 | H14: Q1 2025 | I14: Limited | J14: FALSE | K14: FALSE | N14: FALSE | O14: FALSE | P14: FALSE | Q14: 0 | R14: FALSE
A15: Eat the Night | B15: Altered Innocence | C15: Independent / Other | D15: 45667 | E15: exact | F15: 2025-01-10 | H15: Q1 2025 | I15: Limited | J15: FALSE | K15: FALSE | N15: FALSE | O15: FALSE | P15: FALSE | Q15: 0 | R15: FALSE
A16: Every Little Thing | B16: Kino Lorber | C16: Independent / Other | D16: 45667 | E16: exact | F16: 2025-01-10 | H16: Q1 2025 | I16: Limited | J16: FALSE | K16: FALSE | L16: 200679 | N16: FALSE | O16: FALSE | P16: FALSE | Q16: 0 | R16: FALSE
A17: Extremely Unique Dynamic | B17: Strand Releasing | C17: Independent / Other | D17: 45667 | E17: exact | F17: 2025-01-10 | H17: Q1 2025 | I17: Limited | J17: FALSE | K17: FALSE | L17: 38207 | N17: FALSE | O17: FALSE | P17: FALSE | Q17: 0 | R17: FALSE
A18: Finist: The First Warrior | B18: START | C18: Independent / Other | D18: 45667 | E18: exact | F18: 2025-01-10 | H18: Q1 2025 | I18: Limited | J18: FALSE | K18: FALSE | N18: FALSE | O18: FALSE | P18: FALSE | Q18: 0 | R18: FALSE
A19: Game Changer | B19: Shloka Entertainments | C19: Independent / Other | D19: 45667 | E19: exact | F19: 2025-01-10 | H19: Q1 2025 | I19: Wide | J19: FALSE | K19: FALSE | L19: 2060000 | N19: FALSE | O19: FALSE | P19: FALSE | Q19: 0 | R19: FALSE
A20: Hard Truths | B20: Bleecker Street | C20: Bleecker Street | D20: 45667 | E20: exact | F20: 2025-01-10 | H20: Q1 2025 | I20: Limited | J20: FALSE | K20: FALSE | L20: 811683 | N20: FALSE | O20: FALSE | P20: FALSE | Q20: 0 | R20: TRUE
A21: Hazard | B21: Emphatic Films | C21: Independent / Other | D21: 45667 | E21: exact | F21: 2025-01-10 | H21: Q1 2025 | I21: Limited | J21: FALSE | K21: FALSE | N21: FALSE | O21: FALSE | P21: FALSE | Q21: 0 | R21: FALSE
A22: Laws of Man | B22: Saban Films | C22: Independent / Other | D22: 45667 | E22: exact | F22: 2025-01-10 | H22: Q1 2025 | I22: Limited | J22: FALSE | K22: FALSE | N22: FALSE | O22: FALSE | P22: FALSE | Q22: 0 | R22: FALSE
A23: Oceans Are The Real Continents | B23: Film Movement | C23: Independent / Other | D23: 45667 | E23: exact | F23: 2025-01-10 | H23: Q1 2025 | I23: Limited | J23: FALSE | K23: FALSE | N23: FALSE | O23: FALSE | P23: FALSE | Q23: 0 | R23: FALSE
A24: Octopus with Broken Arms | B24: CMC Pictures | C24: Independent / Other | D24: 45667 | E24: exact | F24: 2025-01-10 | H24: Q1 2025 | I24: Limited | J24: FALSE | K24: FALSE | N24: FALSE | O24: FALSE | P24: FALSE | Q24: 0 | R24: FALSE
A25: Putin | B25: Horizon Events | C25: Independent / Other | D25: 45667 | E25: exact | F25: 2025-01-10 | H25: Q1 2025 | I25: Limited | J25: FALSE | K25: FALSE | N25: FALSE | O25: FALSE | P25: FALSE | Q25: 0 | R25: FALSE
A26: Sangeet Manapman | B26: Jio Studios | C26: Independent / Other | D26: 45667 | E26: exact | F26: 2025-01-10 | H26: Q1 2025 | I26: Limited | J26: FALSE | K26: FALSE | N26: FALSE | O26: FALSE | P26: FALSE | Q26: 0 | R26: FALSE
A27: Sanju Weds Geetha 2 | C27: Unknown | D27: 45667 | E27: exact | F27: 2025-01-10 | H27: Q1 2025 | I27: Limited | J27: FALSE | K27: FALSE | N27: FALSE | O27: FALSE | P27: FALSE | Q27: 0 | R27: FALSE
A28: Somewhere in Montana | B28: Nova Vento Entertainment | C28: Independent / Other | D28: 45667 | E28: exact | F28: 2025-01-10 | H28: Q1 2025 | I28: Limited | J28: FALSE | K28: FALSE | N28: FALSE | O28: FALSE | P28: FALSE | Q28: 0 | R28: FALSE
A29: Survive | B29: Samuel Goldwyn Films | C29: Independent / Other | D29: 45667 | E29: exact | F29: 2025-01-10 | H29: Q1 2025 | I29: Limited | J29: FALSE | K29: FALSE | N29: FALSE | O29: FALSE | P29: FALSE | Q29: 0 | R29: FALSE
A30: The Last Showgirl | B30: Roadside Attractions | C30: Independent / Other | D30: 45667 | E30: exact | F30: 2025-01-10 | H30: Q1 2025 | I30: Wide | J30: FALSE | K30: FALSE | L30: 4799804 | N30: FALSE | O30: FALSE | P30: FALSE | Q30: 0 | R30: FALSE
A31: The Prosecutor | B31: Well Go USA | C31: Independent / Other | D31: 45667 | E31: exact | F31: 2025-01-10 | H31: Q1 2025 | I31: Limited | J31: FALSE | K31: FALSE | L31: 407965 | N31: FALSE | O31: FALSE | P31: FALSE | Q31: 0 | R31: FALSE
A32: Turn Me On | B32: Vertical Entertainment | C32: Independent / Other | D32: 45667 | E32: exact | F32: 2025-01-10 | H32: Q1 2025 | I32: Limited | J32: FALSE | K32: FALSE | N32: FALSE | O32: FALSE | P32: FALSE | Q32: 0 | R32: FALSE
A33: Uninvited | B33: Mentorque Productions | C33: Independent / Other | D33: 45667 | E33: exact | F33: 2025-01-10 | H33: Q1 2025 | I33: Limited | J33: FALSE | K33: FALSE | N33: FALSE | O33: FALSE | P33: FALSE | Q33: 0 | R33: FALSE
A34: Vanangaan | B34: V House Productions | C34: Independent / Other | D34: 45667 | E34: exact | F34: 2025-01-10 | H34: Q1 2025 | I34: Limited | J34: FALSE | K34: FALSE | N34: FALSE | O34: FALSE | P34: FALSE | Q34: 0 | R34: FALSE
A35: Savor | B35: Barnshow Productions | C35: Independent / Other | D35: 45668 | E35: exact | F35: 2025-01-11 | H35: Q1 2025 | I35: Limited | J35: FALSE | K35: FALSE | N35: FALSE | O35: FALSE | P35: FALSE | Q35: 0 | R35: FALSE
A36: Talk To Me | B36: A24 | C36: A24 | D36: 45668 | E36: exact | F36: 2025-01-11 | H36: Q1 2025 | I36: Special Engagement | J36: TRUE | K36: TRUE | L36: 48299436 | M36: Lifetime gross incl. original run - not 2025 revenue | N36: FALSE | O36: FALSE | P36: FALSE | Q36: 0 | R36: TRUE
A37: Daaku Maharaaj | B37: Shloka Entertainments | C37: Independent / Other | D37: 45669 | E37: exact | F37: 2025-01-12 | H37: Q1 2025 | I37: Limited | J37: FALSE | K37: FALSE | N37: FALSE | O37: FALSE | P37: FALSE | Q37: 0 | R37: FALSE
A38: Peter Pan’s Neverland Nightmare | B38: Iconic Releasing | C38: Independent / Other | D38: 45670 | E38: exact | F38: 2025-01-13 | H38: Q1 2025 | I38: Wide | J38: FALSE | K38: FALSE | L38: 230515 | N38: FALSE | O38: FALSE | P38: FALSE | Q38: 0 | R38: FALSE
A39: Kadhalikka Neramillai | B39: Red Giant Movies | C39: Independent / Other | D39: 45671 | E39: exact | F39: 2025-01-14 | H39: Q1 2025 | I39: Limited | J39: FALSE | K39: FALSE | N39: FALSE | O39: FALSE | P39: FALSE | Q39: 0 | R39: FALSE
A40: Pay Dirt: The Story of Supercross | B40: Monkey Wrench Films | C40: Independent / Other | D40: 45671 | E40: exact | F40: 2025-01-14 | H40: Q1 2025 | I40: Limited | J40: FALSE | K40: FALSE | N40: FALSE | O40: FALSE | P40: FALSE | Q40: 0 | R40: FALSE
A41: Sankrathiki Vasthunam | B41: Sri Venkateswara Creations | C41: Independent / Other | D41: 45671 | E41: exact | F41: 2025-01-14 | H41: Q1 2025 | I41: Limited | J41: FALSE | K41: FALSE | N41: FALSE | O41: FALSE | P41: FALSE | Q41: 0 | R41: FALSE
A42: Praavinkoodu Shappu | B42: Nirvana Studios | C42: Independent / Other | D42: 45673 | E42: exact | F42: 2025-01-16 | H42: Q1 2025 | I42: Limited | J42: FALSE | K42: FALSE | N42: FALSE | O42: FALSE | P42: FALSE | Q42: 0 | R42: FALSE
A43: Alarum | B43: Lionsgate | C43: Lionsgate | D43: 45674 | E43: exact | F43: 2025-01-17 | H43: Q1 2025 | I43: Limited | J43: FALSE | K43: FALSE | N43: FALSE | O43: FALSE | P43: FALSE | Q43: 0 | R43: TRUE
A44: Autumn and the Black Jaguar | B44: Blue Fox Entertainment | C44: Independent / Other | D44: 45674 | E44: exact | F44: 2025-01-17 | H44: Q1 2025 | I44: Limited | J44: FALSE | K44: FALSE | L44: 172560 | N44: FALSE | O44: FALSE | P44: FALSE | Q44: 0 | R44: FALSE
A45: Azaad | B45: AA Films | C45: Independent / Other | D45: 45674 | E45: exact | F45: 2025-01-17 | H45: Q1 2025 | I45: Limited | J45: FALSE | K45: FALSE | N45: FALSE | O45: FALSE | P45: FALSE | Q45: 0 | R45: FALSE
A46: Both Eyes Open | B46: IFC Films | C46: IFC | D46: 45674 | E46: exact | F46: 2025-01-17 | H46: Q1 2025 | I46: Limited | J46: FALSE | K46: FALSE | N46: FALSE | O46: FALSE | P46: FALSE | Q46: 0 | R46: TRUE
A47: DIG! XX | B47: Oscilloscope Pictures | C47: Independent / Other | D47: 45674 | E47: exact | F47: 2025-01-17 | H47: Q1 2025 | I47: Limited | J47: FALSE | K47: FALSE | L47: 47086 | N47: FALSE | O47: FALSE | P47: FALSE | Q47: 0 | R47: FALSE
A48: El Heredero | B48: Spanglish Movies | C48: Independent / Other | D48: 45674 | E48: exact | F48: 2025-01-17 | H48: Q1 2025 | I48: Limited | J48: FALSE | K48: FALSE | N48: FALSE | O48: FALSE | P48: FALSE | Q48: 0 | R48: FALSE
A49: Emergency | B49: Zee Studios | C49: Independent / Other | D49: 45674 | E49: exact | F49: 2025-01-17 | H49: Q1 2025 | I49: Limited | J49: FALSE | K49: FALSE | N49: FALSE | O49: FALSE | P49: FALSE | Q49: 0 | R49: FALSE
A50: Girls Town | B50: October Films | C50: Independent / Other | D50: 45674 | E50: exact | F50: 2025-01-17 | H50: Q1 2025 | I50: Limited | J50: TRUE | K50: FALSE | L50: 508332 | M50: Lifetime gross incl. original run - not 2025 revenue | N50: FALSE | O50: FALSE | P50: FALSE | Q50: 0 | R50: FALSE
A51: Grand Theft Hamlet | B51: MUBI | C51: Independent / Other | D51: 45674 | E51: exact | F51: 2025-01-17 | H51: Q1 2025 | I51: Limited | J51: FALSE | K51: FALSE | L51: 143543 | N51: FALSE | O51: FALSE | P51: FALSE | Q51: 0 | R51: FALSE
A52: Hold Me Close | B52: Viva Pictures | C52: Independent / Other | D52: 45674 | E52: exact | F52: 2025-01-17 | H52: Q1 2025 | I52: Limited | J52: FALSE | K52: FALSE | N52: FALSE | O52: FALSE | P52: FALSE | Q52: 0 | R52: FALSE
A53: I’m Still Here | B53: Sony Pictures Classics | C53: Sony | D53: 45674 | E53: exact | F53: 2025-01-17 | G53: 45695 | H53: Q1 2025 | I53: Wide | J53: FALSE | K53: FALSE | L53: 6233517 | N53: FALSE | O53: FALSE | P53: FALSE | Q53: 21 | R53: TRUE
A54: Left Behind | B54: Abramorama Films | C54: Independent / Other | D54: 45674 | E54: exact | F54: 2025-01-17 | H54: Q1 2025 | I54: Limited | J54: FALSE | K54: FALSE | N54: FALSE | O54: FALSE | P54: FALSE | Q54: 0 | R54: FALSE
A55: Night Call | B55: Magnet Releasing | C55: Independent / Other | D55: 45674 | E55: exact | F55: 2025-01-17 | H55: Q1 2025 | I55: Limited | J55: FALSE | K55: FALSE | L55: 10980 | N55: FALSE | O55: FALSE | P55: FALSE | Q55: 0 | R55: FALSE
A56: One of Them Days | B56: Sony Pictures | C56: Sony | D56: 45674 | E56: exact | F56: 2025-01-17 | H56: Q1 2025 | I56: Wide | J56: FALSE | K56: FALSE | L56: 50054690 | N56: FALSE | O56: FALSE | P56: FALSE | Q56: 0 | R56: TRUE
A57: Sing Sing | B57: A24 | C57: A24 | D57: 45674 | E57: exact | F57: 2025-01-17 | H57: Q1 2025 | I57: Limited | J57: FALSE | K57: FALSE | L57: 3018278 | N57: FALSE | O57: FALSE | P57: FALSE | Q57: 0 | R57: TRUE
A58: The Room Next Door | B58: Sony Pictures Classics | C58: Sony | D58: 45674 | E58: exact | F58: 2025-01-17 | H58: Q1 2025 | I58: Wide | J58: FALSE | K58: FALSE | L58: 2519490 | N58: FALSE | O58: FALSE | P58: FALSE | Q58: 0 | R58: TRUE
A59: Wish You Were Here | B59: Lionsgate | C59: Lionsgate | D59: 45674 | E59: exact | F59: 2025-01-17 | H59: Q1 2025 | I59: Limited | J59: FALSE | K59: FALSE | N59: FALSE | O59: FALSE | P59: FALSE | Q59: 0 | R59: TRUE
A60: Wolf Man | B60: Universal | C60: Universal / NBCU | D60: 45674 | E60: exact | F60: 2025-01-17 | H60: Q1 2025 | I60: Wide | J60: FALSE | K60: TRUE | L60: 20707280 | N60: FALSE | O60: FALSE | P60: FALSE | Q60: 0 | R60: TRUE
A61: The Wasps | C61: Unknown | D61: 45675 | E61: exact | F61: 2025-01-18 | H61: Q1 2025 | I61: Limited | J61: FALSE | K61: FALSE | N61: FALSE | O61: FALSE | P61: FALSE | Q61: 0 | R61: FALSE
A62: UFC 311: Makhachev vs. Tsarukyan 2 | B62: Iconic Releasing | C62: Independent / Other | D62: 45675 | E62: exact | F62: 2025-01-18 | H62: Q1 2025 | I62: Special Engagement | J62: FALSE | K62: FALSE | L62: 334988 | N62: FALSE | O62: FALSE | P62: FALSE | Q62: 0 | R62: FALSE
A63: The Goonies | B63: Fathom Events | C63: Independent / Other | D63: 45676 | E63: exact | F63: 2025-01-19 | H63: Q1 2025 | I63: Special Engagement | J63: TRUE | K63: FALSE | L63: 69427173 | M63: Lifetime gross incl. original run - not 2025 revenue | N63: FALSE | O63: FALSE | P63: FALSE | Q63: 0 | R63: FALSE
A64: Reckonings | C64: Unknown | D64: 45677 | E64: exact | F64: 2025-01-20 | H64: Q1 2025 | I64: Limited | J64: FALSE | K64: FALSE | N64: FALSE | O64: FALSE | P64: FALSE | Q64: 0 | R64: FALSE
A65: A Legend | B65: Well Go USA | C65: Independent / Other | D65: 45678 | E65: exact | F65: 2025-01-21 | H65: Q1 2025 | I65: Limited | J65: FALSE | K65: FALSE | N65: FALSE | O65: FALSE | P65: FALSE | Q65: 0 | R65: FALSE
A66: Marked Men: Rule & Shaw | B66: Fathom Entertainment | C66: Independent / Other | D66: 45679 | E66: exact | F66: 2025-01-22 | H66: Q1 2025 | I66: Special Engagement | J66: FALSE | K66: FALSE | N66: FALSE | O66: FALSE | P66: FALSE | Q66: 0 | R66: FALSE
A67: Dominic and the Ladies’ Purse | C67: Unknown | D67: 45680 | E67: exact | F67: 2025-01-23 | H67: Q1 2025 | I67: Limited | J67: FALSE | K67: FALSE | N67: FALSE | O67: FALSE | P67: FALSE | Q67: 0 | R67: FALSE
A68: Narayaneente Moonaanmakkal | B68: Goodwill Entertainments | C68: Independent / Other | D68: 45680 | E68: exact | F68: 2025-01-23 | H68: Q1 2025 | I68: Limited | J68: FALSE | K68: FALSE | N68: FALSE | O68: FALSE | P68: FALSE | Q68: 0 | R68: FALSE
A69: The Colors Within in IMAX | B69: GKIDS | C69: Independent / Other | D69: 45680 | E69: exact | F69: 2025-01-23 | H69: Q1 2025 | I69: Special Engagement | J69: FALSE | K69: FALSE | L69: 557116 | N69: FALSE | O69: FALSE | P69: FALSE | Q69: 0 | R69: FALSE
A70: Blades in the Darkness | B70: Indican Pictures | C70: Independent / Other | D70: 45681 | E70: exact | F70: 2025-01-24 | H70: Q1 2025 | I70: Limited | J70: FALSE | K70: FALSE | L70: 10072 | N70: FALSE | O70: FALSE | P70: FALSE | Q70: 0 | R70: FALSE
A71: Boonie Bears:Time Twist | B71: Viva Pictures | C71: Independent / Other | D71: 45681 | E71: exact | F71: 2025-01-24 | H71: Q1 2025 | I71: Limited | J71: FALSE | K71: FALSE | N71: FALSE | O71: FALSE | P71: FALSE | Q71: 0 | R71: FALSE
A72: Brave the Dark | B72: Angel Studios | C72: Angel Studios | D72: 45681 | E72: exact | F72: 2025-01-24 | H72: Q1 2025 | I72: Wide | J72: FALSE | K72: FALSE | L72: 4525443 | N72: FALSE | O72: FALSE | P72: FALSE | Q72: 0 | R72: TRUE
A73: Disfluency | B73: Buffalo 8 | C73: Independent / Other | D73: 45681 | E73: exact | F73: 2025-01-24 | H73: Q1 2025 | I73: Limited | J73: FALSE | K73: FALSE | N73: FALSE | O73: FALSE | P73: FALSE | Q73: 0 | R73: FALSE
A74: Flight Risk | B74: Lionsgate | C74: Lionsgate | D74: 45681 | E74: exact | F74: 2025-01-24 | H74: Q1 2025 | I74: Wide | J74: FALSE | K74: FALSE | L74: 29783527 | N74: FALSE | O74: FALSE | P74: FALSE | Q74: 0 | R74: TRUE
A75: Hathya | B75: Shaurya Cinemas | C75: Independent / Other | D75: 45681 | E75: exact | F75: 2025-01-24 | H75: Q1 2025 | I75: Limited | J75: FALSE | K75: FALSE | N75: FALSE | O75: FALSE | P75: FALSE | Q75: 0 | R75: FALSE
A76: Inheritance | B76: IFC Films | C76: IFC | D76: 45681 | E76: exact | F76: 2025-01-24 | H76: Q1 2025 | I76: Wide | J76: FALSE | K76: FALSE | L76: 192223 | N76: FALSE | O76: FALSE | P76: FALSE | Q76: 0 | R76: TRUE
A77: Into the Deep | B77: Saban Films | C77: Independent / Other | D77: 45681 | E77: exact | F77: 2025-01-24 | H77: Q1 2025 | I77: Limited | J77: FALSE | K77: FALSE | N77: FALSE | O77: FALSE | P77: FALSE | Q77: 0 | R77: FALSE
A78: Liza: A Truly Terrific Absolutely True Story | B78: Kino Lorber | C78: Independent / Other | D78: 45681 | E78: exact | F78: 2025-01-24 | H78: Q1 2025 | I78: Limited | J78: FALSE | K78: FALSE | L78: 222775 | N78: FALSE | O78: FALSE | P78: FALSE | Q78: 0 | R78: FALSE
A79: Myth of Man | B79: Double Edge Films | C79: Independent / Other | D79: 45681 | E79: exact | F79: 2025-01-24 | H79: Q1 2025 | I79: Limited | J79: FALSE | K79: FALSE | N79: FALSE | O79: FALSE | P79: FALSE | Q79: 0 | R79: FALSE
A80: Presence | B80: Neon | C80: Neon | D80: 45681 | E80: exact | F80: 2025-01-24 | H80: Q1 2025 | I80: Wide | J80: FALSE | K80: FALSE | L80: 6900045 | N80: FALSE | O80: FALSE | P80: FALSE | Q80: 0 | R80: TRUE
A81: Riot on Redchurch Street | B81: Freestyle Releasing | C81: Independent / Other | D81: 45681 | E81: exact | F81: 2025-01-24 | H81: Q1 2025 | I81: Limited | J81: FALSE | K81: FALSE | N81: FALSE | O81: FALSE | P81: FALSE | Q81: 0 | R81: FALSE
A82: Rose | B82: Cohen Media Group | C82: Independent / Other | D82: 45681 | E82: exact | F82: 2025-01-24 | H82: Q1 2025 | I82: Limited | J82: FALSE | K82: FALSE | N82: FALSE | O82: FALSE | P82: FALSE | Q82: 0 | R82: FALSE
A83: Sherlock Holmes Mare of the Night | B83: TriGoldwynProd | C83: Independent / Other | D83: 45681 | E83: exact | F83: 2025-01-24 | H83: Q1 2025 | I83: Limited | J83: FALSE | K83: FALSE | N83: FALSE | O83: FALSE | P83: FALSE | Q83: 0 | R83: FALSE
A84: Sky Force | C84: Unknown | D84: 45681 | E84: exact | F84: 2025-01-24 | H84: Q1 2025 | I84: Limited | J84: FALSE | K84: FALSE | N84: FALSE | O84: FALSE | P84: FALSE | Q84: 0 | R84: FALSE
A85: Sunray: Fallen Soldier | B85: Vertigo Releasing | C85: Independent / Other | D85: 45681 | E85: exact | F85: 2025-01-24 | H85: Q1 2025 | I85: Limited | J85: FALSE | K85: FALSE | N85: FALSE | O85: FALSE | P85: FALSE | Q85: 0 | R85: FALSE
A86: The Brutalist | B86: A24 | C86: A24 | D86: 45681 | E86: exact | F86: 2025-01-24 | H86: Q1 2025 | I86: Wide | J86: FALSE | K86: FALSE | L86: 16249415 | N86: FALSE | O86: FALSE | P86: FALSE | Q86: 0 | R86: TRUE
A87: The Colors Within | B87: GKIDS | C87: Independent / Other | D87: 45681 | E87: exact | F87: 2025-01-24 | H87: Q1 2025 | I87: Limited | J87: FALSE | K87: FALSE | L87: 557116 | N87: FALSE | O87: FALSE | P87: FALSE | Q87: 0 | R87: FALSE
A88: Zombie Strain | B88: Dark Sky Films | C88: Independent / Other | D88: 45681 | E88: exact | F88: 2025-01-24 | H88: Q1 2025 | I88: Limited | J88: FALSE | K88: FALSE | N88: FALSE | O88: FALSE | P88: FALSE | Q88: 0 | R88: FALSE
A89: MetOpera: Aida (2024-2025) | B89: Fathom Entertainment | C89: Independent / Other | D89: 45682 | E89: exact | F89: 2025-01-25 | H89: Q1 2025 | I89: Special Engagement | J89: FALSE | K89: FALSE | N89: FALSE | O89: FALSE | P89: FALSE | Q89: 0 | R89: FALSE
A90: Between Borders | B90: Fathom Entertainment | C90: Independent / Other | D90: 45683 | E90: exact | F90: 2025-01-26 | H90: Q1 2025 | I90: Special Engagement | J90: FALSE | K90: FALSE | N90: FALSE | O90: FALSE | P90: FALSE | Q90: 0 | R90: FALSE
A91: André is an Idiot | C91: Unknown | D91: 45684 | E91: exact | F91: 2025-01-27 | H91: Q1 2025 | I91: Festival Screening | J91: FALSE | K91: FALSE | N91: FALSE | O91: FALSE | P91: FALSE | Q91: 0 | R91: FALSE
A92: Eric Clapton Unplugged… Over 30 Years Later | C92: Unknown | D92: 45684 | E92: exact | F92: 2025-01-27 | H92: Q1 2025 | I92: Limited | J92: FALSE | K92: FALSE | N92: FALSE | O92: FALSE | P92: FALSE | Q92: 0 | R92: FALSE
A93: Life After | C93: Unknown | D93: 45684 | E93: exact | F93: 2025-01-27 | H93: Q1 2025 | I93: Festival Screening | J93: FALSE | K93: FALSE | N93: FALSE | O93: FALSE | P93: FALSE | Q93: 0 | R93: FALSE
A94: Zodiac Killer Project | C94: Unknown | D94: 45684 | E94: exact | F94: 2025-01-27 | H94: Q1 2025 | I94: Festival Screening | J94: FALSE | K94: FALSE | L94: 19957 | N94: FALSE | O94: FALSE | P94: TRUE | Q94: 0 | R94: FALSE
A95: Not an Artist | B95: Utopia | C95: Independent / Other | D95: 45685 | E95: exact | F95: 2025-01-28 | H95: Q1 2025 | I95: Special Engagement | J95: FALSE | K95: FALSE | N95: FALSE | O95: FALSE | P95: FALSE | Q95: 0 | R95: FALSE
A96: (G)I-dle World Tour [iDol] in Cinemas | B96: Trafalgar Releasing | C96: Independent / Other | D96: 45686 | E96: exact | F96: 2025-01-29 | H96: Q1 2025 | I96: Special Engagement | J96: FALSE | K96: FALSE | N96: FALSE | O96: FALSE | P96: FALSE | Q96: 0 | R96: FALSE
A97: Creation of the Gods II: Demon Force | B97: Well Go USA | C97: Independent / Other | D97: 45686 | E97: exact | F97: 2025-01-29 | H97: Q1 2025 | I97: Limited | J97: FALSE | K97: TRUE | L97: 1853487 | N97: FALSE | O97: FALSE | P97: FALSE | Q97: 2 | R97: FALSE
A98: Detective Chinatown 1900 | B98: CMC Pictures | C98: Independent / Other | D98: 45686 | E98: exact | F98: 2025-01-29 | H98: Q1 2025 | I98: Limited | J98: FALSE | K98: FALSE | N98: FALSE | O98: FALSE | P98: FALSE | Q98: 0 | R98: FALSE
A99: Hit N Fun | C99: Unknown | D99: 45686 | E99: exact | F99: 2025-01-29 | H99: Q1 2025 | I99: Limited | J99: FALSE | K99: FALSE | N99: FALSE | O99: FALSE | P99: FALSE | Q99: 0 | R99: FALSE
A100: 2121 | B100: Indican Pictures | C100: Independent / Other | D100: 45688 | E100: exact | F100: 2025-01-31 | H100: Q1 2025 | I100: Limited | J100: FALSE | K100: FALSE | L100: 25552 | N100: FALSE | O100: FALSE | P100: FALSE | Q100: 0 | R100: FALSE
...

Sheet 2026
A1: Title | B1: Distributor | C1: Parent Company | D1: Release Date | E1: Date Precision | F1: Date (as sourced) | G1: Wide Expansion Date | H1: Release Quarter | I1: Release Type | J1: Is Re-release | K1: Is IMAX | L1: Domestic BO (Lifetime) | M1: BO Caveat | N1: Is Canceled | O1: Is Catalog Aggregate | P1: Dup BO Flag | Q1: Merge Span (days) | R1: In Scope
A2: Ikkis | B2: Yash Raj Films | C2: Independent / Other | D2: 46023 | E2: exact | F2: 2026-01-01 | H2: Q1 2026 | I2: Limited | J2: FALSE | K2: FALSE | N2: FALSE | O2: FALSE | P2: FALSE | Q2: 0 | R2: FALSE
A3: Patang | C3: Unknown | D3: 46023 | E3: exact | F3: 2026-01-01 | H3: Q1 2026 | I3: Limited | J3: FALSE | K3: FALSE | N3: FALSE | O3: FALSE | P3: FALSE | Q3: 0 | R3: FALSE
A4: KIDZ BOP LIVE: The Concert Movie | B4: Fathom Entertainment | C4: Independent / Other | D4: 46024 | E4: exact | F4: 2026-01-02 | H4: Q1 2026 | I4: Limited | J4: FALSE | K4: FALSE | N4: FALSE | O4: FALSE | P4: FALSE | Q4: 0 | R4: FALSE
A5: The Dutchman | B5: Inaugural Entertainment | C5: Independent / Other | D5: 46024 | E5: exact | F5: 2026-01-02 | H5: Q1 2026 | I5: Limited | J5: FALSE | K5: FALSE | N5: FALSE | O5: FALSE | P5: FALSE | Q5: 0 | R5: FALSE
A6: We Bury the Dead | B6: Vertical Entertainment | C6: Independent / Other | D6: 46024 | E6: exact | F6: 2026-01-02 | H6: Q1 2026 | I6: Limited | J6: FALSE | K6: FALSE | L6: 3711918 | N6: FALSE | O6: FALSE | P6: FALSE | Q6: 0 | R6: FALSE
A7: Lupin the IIIRD: The Movie — The Immortal Bloodline | B7: GKIDS | C7: Independent / Other | D7: 46026 | E7: exact | F7: 2026-01-04 | H7: Q1 2026 | I7: Limited | J7: FALSE | K7: FALSE | L7: 121507 | N7: FALSE | O7: FALSE | P7: FALSE | Q7: 0 | R7: FALSE
A8: Weathered: Inside the LA Firestorm | B8: PBS Distribution | C8: Independent / Other | D8: 46029 | E8: exact | F8: 2026-01-07 | H8: Q1 2026 | I8: Limited | J8: FALSE | K8: FALSE | N8: FALSE | O8: FALSE | P8: FALSE | Q8: 0 | R8: FALSE
A9: Labyrinth | B9: Fathom Events | C9: Independent / Other | D9: 46030 | E9: exact | F9: 2026-01-08 | H9: Q1 2026 | I9: Limited | J9: TRUE | K9: FALSE | L9: 12729917 | M9: Lifetime gross incl. original run - not 2026 revenue | N9: FALSE | O9: FALSE | P9: FALSE | Q9: 0 | R9: FALSE
A10: The Raja Saab | B10: Prathyangira Cinemas | C10: Independent / Other | D10: 46030 | E10: exact | F10: 2026-01-08 | H10: Q1 2026 | I10: Wide | J10: FALSE | K10: FALSE | L10: 2300000 | N10: FALSE | O10: FALSE | P10: FALSE | Q10: 0 | R10: FALSE
A11: 31 Candles | B11: Level 33 | C11: Independent / Other | D11: 46031 | E11: exact | F11: 2026-01-09 | H11: Q1 2026 | I11: Limited | J11: FALSE | K11: FALSE | N11: FALSE | O11: FALSE | P11: FALSE | Q11: 0 | R11: FALSE
A12: All That’s Left Of You | B12: Watermelon Pictures | C12: Independent / Other | D12: 46031 | E12: exact | F12: 2026-01-09 | H12: Q1 2026 | I12: Limited | J12: FALSE | K12: FALSE | L12: 514374 | N12: FALSE | O12: FALSE | P12: FALSE | Q12: 0 | R12: FALSE
A13: Bulls | B13: VRC | C13: Independent / Other | D13: 46031 | E13: exact | F13: 2026-01-09 | H13: Q1 2026 | I13: Limited | J13: FALSE | K13: FALSE | N13: FALSE | O13: FALSE | P13: FALSE | Q13: 0 | R13: FALSE
A14: Buratino | C14: Unknown | D14: 46031 | E14: exact | F14: 2026-01-09 | H14: Q1 2026 | I14: Limited | J14: FALSE | K14: FALSE | N14: FALSE | O14: FALSE | P14: FALSE | Q14: 0 | R14: FALSE
A15: Dead Man’s Wire | B15: Row K Entertainment | C15: Independent / Other | D15: 46031 | E15: exact | F15: 2026-01-09 | G15: 46038 | H15: Q1 2026 | I15: Wide | J15: FALSE | K15: FALSE | L15: 2236813 | N15: FALSE | O15: FALSE | P15: FALSE | Q15: 7 | R15: FALSE
A16: Greenland 2: Migration | B16: Lionsgate | C16: Lionsgate | D16: 46031 | E16: exact | F16: 2026-01-09 | H16: Q1 2026 | I16: Wide | J16: FALSE | K16: FALSE | L16: 17770308 | N16: FALSE | O16: FALSE | P16: FALSE | Q16: 0 | R16: TRUE
A17: Holding Liat | B17: The Film Collaborative | C17: Independent / Other | D17: 46031 | E17: exact | F17: 2026-01-09 | H17: Q1 2026 | I17: Limited | J17: FALSE | K17: FALSE | L17: 78535 | N17: FALSE | O17: FALSE | P17: FALSE | Q17: 0 | R17: FALSE
A18: I Was a Stranger | B18: Angel Studios | C18: Angel Studios | D18: 46031 | E18: exact | F18: 2026-01-09 | H18: Q1 2026 | I18: Wide | J18: FALSE | K18: FALSE | L18: 2008685 | N18: FALSE | O18: FALSE | P18: FALSE | Q18: 0 | R18: TRUE
A19: Is This Thing On? | B19: Searchlight Pictures | C19: Disney | D19: 46031 | E19: exact | F19: 2026-01-09 | H19: Q1 2026 | I19: Wide | J19: FALSE | K19: FALSE | L19: 6185385 | N19: FALSE | O19: FALSE | P19: FALSE | Q19: 0 | R19: TRUE
A20: Magellan | B20: Janus Films | C20: Independent / Other | D20: 46031 | E20: exact | F20: 2026-01-09 | H20: Q1 2026 | I20: Limited | J20: FALSE | K20: FALSE | L20: 231318 | N20: FALSE | O20: FALSE | P20: FALSE | Q20: 0 | R20: FALSE
A21: My Neighbor Adolf | B21: Cohen Media Group | C21: Independent / Other | D21: 46031 | E21: exact | F21: 2026-01-09 | H21: Q1 2026 | I21: Limited | J21: FALSE | K21: FALSE | N21: FALSE | O21: FALSE | P21: FALSE | Q21: 0 | R21: FALSE
A22: OBEX | B22: Oscilloscope Pictures | C22: Independent / Other | D22: 46031 | E22: exact | F22: 2026-01-09 | H22: Q1 2026 | I22: Limited | J22: FALSE | K22: FALSE | L22: 48257 | N22: FALSE | O22: FALSE | P22: FALSE | Q22: 0 | R22: FALSE
A23: Oscar Shaw | B23: Samuel Goldwyn Films | C23: Independent / Other | D23: 46031 | E23: exact | F23: 2026-01-09 | H23: Q1 2026 | I23: Limited | J23: FALSE | K23: FALSE | N23: FALSE | O23: FALSE | P23: FALSE | Q23: 0 | R23: FALSE
A24: Port of Shadows | B24: Rialto Pictures | C24: Independent / Other | D24: 46031 | E24: exact | F24: 2026-01-09 | H24: Q1 2026 | I24: Limited | J24: TRUE | K24: FALSE | L24: 35962 | M24: Lifetime gross incl. original run - not 2026 revenue | N24: FALSE | O24: FALSE | P24: FALSE | Q24: 0 | R24: FALSE
A25: Primate | B25: Paramount Pictures | C25: Paramount | D25: 46031 | E25: exact | F25: 2026-01-09 | H25: Q1 2026 | I25: Wide | J25: FALSE | K25: FALSE | L25: 25635665 | N25: FALSE | O25: FALSE | P25: FALSE | Q25: 0 | R25: TRUE
A26: Sleepwalker | B26: Brainstorm Media | C26: Independent / Other | D26: 46031 | E26: exact | F26: 2026-01-09 | H26: Q1 2026 | I26: Limited | J26: FALSE | K26: FALSE | N26: FALSE | O26: FALSE | P26: FALSE | Q26: 0 | R26: FALSE
A27: The Voice of Hind Rajab | B27: WILLA | C27: Independent / Other | D27: 46031 | E27: exact | F27: 2026-01-09 | H27: Q1 2026 | I27: Limited | J27: FALSE | K27: FALSE | L27: 955679 | N27: FALSE | O27: FALSE | P27: FALSE | Q27: 0 | R27: FALSE
A28: Young Mothers | B28: Music Box Films | C28: Independent / Other | D28: 46031 | E28: exact | F28: 2026-01-09 | H28: Q1 2026 | I28: Limited | J28: FALSE | K28: FALSE | L28: 13032 | N28: FALSE | O28: FALSE | P28: FALSE | Q28: 0 | R28: FALSE
A29: Mana ShankaraVaraprasad Garu | B29: Sarigama Cinemas | C29: Independent / Other | D29: 46034 | E29: exact | F29: 2026-01-12 | H29: Q1 2026 | I29: Limited | J29: FALSE | K29: FALSE | N29: FALSE | O29: FALSE | P29: FALSE | Q29: 0 | R29: FALSE
A30: Godfrey: Rebel with a Cause | B30: Gathr Films | C30: Independent / Other | D30: 46036 | E30: exact | F30: 2026-01-14 | H30: Q1 2026 | I30: Limited | J30: FALSE | K30: FALSE | N30: FALSE | O30: FALSE | P30: FALSE | Q30: 0 | R30: FALSE
A31: Nari Nari Naduma Murari | B31: Sarigama Cinemas | C31: Independent / Other | D31: 46036 | E31: exact | F31: 2026-01-14 | H31: Q1 2026 | I31: Limited | J31: FALSE | K31: FALSE | N31: FALSE | O31: FALSE | P31: FALSE | Q31: 0 | R31: FALSE
A32: Once Upon My Mother | C32: Unknown | D32: 46036 | E32: exact | F32: 2026-01-14 | H32: Q1 2026 | I32: Limited | J32: FALSE | K32: FALSE | N32: FALSE | O32: FALSE | P32: FALSE | Q32: 0 | R32: FALSE
A33: TTT: Thalaivar Thambi Thalamaiyil | B33: Prathyangira Cinemas | C33: Independent / Other | D33: 46037 | E33: exact | F33: 2026-01-15 | H33: Q1 2026 | I33: Limited | J33: FALSE | K33: FALSE | N33: FALSE | O33: FALSE | P33: FALSE | Q33: 0 | R33: FALSE
A34: 28 Years Later: The Bone Temple | B34: Sony Pictures | C34: Sony | D34: 46038 | E34: exact | F34: 2026-01-16 | H34: Q1 2026 | I34: Wide | J34: FALSE | K34: FALSE | L34: 25147583 | N34: FALSE | O34: FALSE | P34: FALSE | Q34: 0 | R34: TRUE
A35: A Private Life | B35: Sony Pictures Classics | C35: Sony | D35: 46038 | E35: exact | F35: 2026-01-16 | H35: Q1 2026 | I35: Limited | J35: FALSE | K35: FALSE | L35: 1421315 | N35: FALSE | O35: FALSE | P35: FALSE | Q35: 0 | R35: TRUE
A36: A Useful Ghost | B36: Cineverse | C36: Independent / Other | D36: 46038 | E36: exact | F36: 2026-01-16 | H36: Q1 2026 | I36: Limited | J36: FALSE | K36: FALSE | N36: FALSE | O36: FALSE | P36: FALSE | Q36: 0 | R36: FALSE
A37: All You Need Is Kill | B37: GKIDS | C37: Independent / Other | D37: 46038 | E37: exact | F37: 2026-01-16 | H37: Q1 2026 | I37: Wide | J37: FALSE | K37: FALSE | L37: 695290 | N37: FALSE | O37: FALSE | P37: FALSE | Q37: 0 | R37: FALSE
A38: Charlie the Wonderdog | B38: Viva Pictures | C38: Independent / Other | D38: 46038 | E38: exact | F38: 2026-01-16 | H38: Q1 2026 | I38: Wide | J38: FALSE | K38: FALSE | L38: 2003436 | N38: FALSE | O38: FALSE | P38: FALSE | Q38: 0 | R38: FALSE
A39: Deepfaking Sam Altman | B39: Abramorama Films | C39: Independent / Other | D39: 46038 | E39: exact | F39: 2026-01-16 | H39: Q1 2026 | I39: Limited | J39: FALSE | K39: FALSE | N39: FALSE | O39: FALSE | P39: FALSE | Q39: 0 | R39: FALSE
A40: Happy Patel: Khatarnak Jasoos | B40: Shree Krishna Film | C40: Independent / Other | D40: 46038 | E40: exact | F40: 2026-01-16 | H40: Q1 2026 | I40: Limited | J40: FALSE | K40: FALSE | N40: FALSE | O40: FALSE | P40: FALSE | Q40: 0 | R40: FALSE
A41: Jury of Her Peers | C41: Unknown | D41: 46038 | E41: exact | F41: 2026-01-16 | H41: Q1 2026 | I41: Limited | J41: FALSE | K41: FALSE | N41: FALSE | O41: FALSE | P41: FALSE | Q41: 0 | R41: FALSE
A42: Killer Whale | B42: Lionsgate | C42: Lionsgate | D42: 46038 | E42: exact | F42: 2026-01-16 | H42: Q1 2026 | I42: Limited | J42: FALSE | K42: FALSE | N42: FALSE | O42: FALSE | P42: FALSE | Q42: 0 | R42: TRUE
A43: Leave | B43: Footage Films | C43: Independent / Other | D43: 46038 | E43: exact | F43: 2026-01-16 | H43: Q1 2026 | I43: Limited | J43: FALSE | K43: FALSE | N43: FALSE | O43: FALSE | P43: FALSE | Q43: 0 | R43: FALSE
A44: Madagascar | B44: Universal | C44: Universal / NBCU | D44: 46038 | E44: exact | F44: 2026-01-16 | H44: Q1 2026 | I44: Wide | J44: TRUE | K44: FALSE | L44: 194304665 | M44: Lifetime gross incl. original run - not 2026 revenue | N44: FALSE | O44: FALSE | P44: FALSE | Q44: 0 | R44: TRUE
A45: Night Patrol | B45: IFC Films | C45: IFC | D45: 46038 | E45: exact | F45: 2026-01-16 | H45: Q1 2026 | I45: Wide | J45: FALSE | K45: FALSE | L45: 372115 | N45: FALSE | O45: FALSE | P45: FALSE | Q45: 0 | R45: TRUE
A46: No Other Choice | B46: Neon | C46: Neon | D46: 46038 | E46: exact | F46: 2026-01-16 | H46: Q1 2026 | I46: Wide | J46: FALSE | K46: FALSE | L46: 10011859 | N46: FALSE | O46: FALSE | P46: FALSE | Q46: 0 | R46: TRUE
A47: Queen Kelly | B47: Kino Lorber | C47: Independent / Other | D47: 46038 | E47: exact | F47: 2026-01-16 | H47: Q1 2026 | I47: Limited | J47: TRUE | K47: FALSE | L47: 50221 | M47: Lifetime gross incl. original run - not 2026 revenue | N47: FALSE | O47: FALSE | P47: FALSE | Q47: 0 | R47: FALSE
A48: Shuffle | B48: Abramorama Films | C48: Independent / Other | D48: 46038 | E48: exact | F48: 2026-01-16 | H48: Q1 2026 | I48: Limited | J48: FALSE | K48: FALSE | N48: FALSE | O48: FALSE | P48: FALSE | Q48: 0 | R48: FALSE
A49: Signing Tony Raymond | B49: Iconic Releasing | C49: Independent / Other | D49: 46038 | E49: exact | F49: 2026-01-16 | H49: Q1 2026 | I49: Limited | J49: FALSE | K49: FALSE | N49: FALSE | O49: FALSE | P49: FALSE | Q49: 0 | R49: FALSE
A50: Sound of Falling | C50: Unknown | D50: 46038 | E50: exact | F50: 2026-01-16 | H50: Q1 2026 | I50: Limited | J50: FALSE | K50: FALSE | L50: 88547 | N50: FALSE | O50: FALSE | P50: FALSE | Q50: 0 | R50: FALSE
A51: The Choral | B51: Sony Pictures Classics | C51: Sony | D51: 46038 | E51: exact | F51: 2026-01-16 | H51: Q1 2026 | I51: Wide | J51: FALSE | K51: FALSE | L51: 1020176 | N51: FALSE | O51: FALSE | P51: FALSE | Q51: 0 | R51: TRUE
A52: The Fire Raven | B52: China Lion Film Distribution | C52: Independent / Other | D52: 46038 | E52: exact | F52: 2026-01-16 | H52: Q1 2026 | I52: Limited | J52: FALSE | K52: FALSE | N52: FALSE | O52: FALSE | P52: FALSE | Q52: 0 | R52: FALSE
A53: The Lord of the Rings: The Fellowship of the Ring | B53: Fathom Events | C53: Independent / Other | D53: 46038 | E53: exact | F53: 2026-01-16 | H53: Q1 2026 | I53: Special Engagement | J53: TRUE | K53: FALSE | L53: 325680679 | M53: Lifetime gross incl. original run - not 2026 revenue | N53: FALSE | O53: FALSE | P53: FALSE | Q53: 0 | R53: FALSE
A54: Vaa Vaathiyaar | B54: Prathyangira Cinemas | C54: Independent / Other | D54: 46038 | E54: exact | F54: 2026-01-16 | H54: Q1 2026 | I54: Limited | J54: FALSE | K54: FALSE | N54: FALSE | O54: FALSE | P54: FALSE | Q54: 0 | R54: FALSE
A55: The Lord of the Rings: The Two Towers | B55: Fathom Events | C55: Independent / Other | D55: 46039 | E55: exact | F55: 2026-01-17 | H55: Q1 2026 | I55: Special Engagement | J55: TRUE | K55: FALSE | L55: 349701429 | M55: Lifetime gross incl. original run - not 2026 revenue | N55: FALSE | O55: FALSE | P55: FALSE | Q55: 0 | R55: FALSE
A56: The Lord of the Rings: The Return of the King | B56: Fathom Events | C56: Independent / Other | D56: 46040 | E56: exact | F56: 2026-01-18 | H56: Q1 2026 | I56: Special Engagement | J56: TRUE | K56: FALSE | L56: 383381648 | M56: Lifetime gross incl. original run - not 2026 revenue | N56: FALSE | O56: FALSE | P56: FALSE | Q56: 0 | R56: FALSE
A57: Zombie Land Saga: Yumeginga Paradise | B57: Sony Pictures | C57: Sony | D57: 46041 | E57: exact | F57: 2026-01-19 | H57: Q1 2026 | I57: Limited | J57: FALSE | K57: FALSE | L57: 87333 | N57: FALSE | O57: FALSE | P57: FALSE | Q57: 0 | R57: TRUE
A58: 267 | C58: Unknown | D58: 46043 | E58: exact | F58: 2026-01-21 | H58: Q1 2026 | I58: Limited | J58: FALSE | K58: FALSE | N58: FALSE | O58: FALSE | P58: FALSE | Q58: 0 | R58: FALSE
A59: 2DIE4 | B59: Abramorama Films | C59: Independent / Other | D59: 46043 | E59: exact | F59: 2026-01-21 | H59: Q1 2026 | I59: Special Engagement | J59: FALSE | K59: TRUE | N59: FALSE | O59: FALSE | P59: FALSE | Q59: 0 | R59: FALSE
A60: Mr. Nobody Against Putin | B60: Kino Lorber | C60: Independent / Other | D60: 46043 | E60: exact | F60: 2026-01-21 | H60: Q1 2026 | I60: Limited | J60: FALSE | K60: FALSE | L60: 270123 | N60: FALSE | O60: FALSE | P60: FALSE | Q60: 0 | R60: FALSE
A61: Chatha Pacha: The Ring of Rowdies | C61: Unknown | D61: 46044 | E61: exact | F61: 2026-01-22 | H61: Q1 2026 | I61: Limited | J61: FALSE | K61: FALSE | N61: FALSE | O61: FALSE | P61: FALSE | Q61: 0 | R61: FALSE
A62: Cosmic Princess Kaguya! | B62: Netflix | C62: Netflix | D62: 46044 | E62: exact | F62: 2026-01-22 | H62: Q1 2026 | I62: Limited | J62: FALSE | K62: FALSE | N62: FALSE | O62: FALSE | P62: FALSE | Q62: 0 | R62: TRUE
A63: Megadeth: Behind the Mask | B63: Trafalgar Releasing | C63: Independent / Other | D63: 46044 | E63: exact | F63: 2026-01-22 | H63: Q1 2026 | I63: Special Engagement | J63: FALSE | K63: FALSE | N63: FALSE | O63: FALSE | P63: FALSE | Q63: 0 | R63: FALSE
A64: Arco | B64: Neon | C64: Neon | D64: 46045 | E64: exact | F64: 2026-01-23 | H64: Q1 2026 | I64: Limited | J64: FALSE | K64: FALSE | L64: 1000913 | N64: FALSE | O64: FALSE | P64: FALSE | Q64: 0 | R64: TRUE
A65: Baby Girl | C65: Unknown | D65: 46045 | E65: exact | F65: 2026-01-23 | H65: Q1 2026 | I65: Limited | J65: FALSE | K65: FALSE | N65: FALSE | O65: FALSE | P65: FALSE | Q65: 0 | R65: FALSE
A66: Border 2 | B66: AA Films | C66: Independent / Other | D66: 46045 | E66: exact | F66: 2026-01-23 | H66: Q1 2026 | I66: Limited | J66: FALSE | K66: FALSE | N66: FALSE | O66: FALSE | P66: FALSE | Q66: 0 | R66: FALSE
A67: Clika | B67: Sony Pictures | C67: Sony | D67: 46045 | E67: exact | F67: 2026-01-23 | H67: Q1 2026 | I67: Limited | J67: FALSE | K67: FALSE | L67: 2644377 | N67: FALSE | O67: FALSE | P67: FALSE | Q67: 0 | R67: TRUE
A68: Conversation Piece | B68: Kino Lorber | C68: Independent / Other | D68: 46045 | E68: exact | F68: 2026-01-23 | H68: Q1 2026 | I68: Limited | J68: TRUE | K68: FALSE | L68: 22678 | M68: Lifetime gross incl. original run - not 2026 revenue | N68: FALSE | O68: FALSE | P68: FALSE | Q68: 0 | R68: FALSE
A69: Dollface: The Motion Picture | C69: Unknown | D69: 46045 | E69: exact | F69: 2026-01-23 | H69: Q1 2026 | I69: Limited | J69: FALSE | K69: FALSE | N69: FALSE | O69: FALSE | P69: FALSE | Q69: 0 | R69: FALSE
A70: Dooba Dooba | B70: Dark Sky Films | C70: Independent / Other | D70: 46045 | E70: exact | F70: 2026-01-23 | H70: Q1 2026 | I70: Limited | J70: FALSE | K70: FALSE | N70: FALSE | O70: FALSE | P70: FALSE | Q70: 0 | R70: FALSE
A71: H is for Hawk | B71: Roadside Attractions | C71: Independent / Other | D71: 46045 | E71: exact | F71: 2026-01-23 | H71: Q1 2026 | I71: Wide | J71: FALSE | K71: FALSE | L71: 342239 | N71: FALSE | O71: FALSE | P71: FALSE | Q71: 0 | R71: FALSE
A72: He’s Watching You | B72: VRC | C72: Independent / Other | D72: 46045 | E72: exact | F72: 2026-01-23 | H72: Q1 2026 | I72: Limited | J72: FALSE | K72: FALSE | N72: FALSE | O72: FALSE | P72: FALSE | Q72: 0 | R72: FALSE
A73: In Cold Light | B73: Saban Films | C73: Independent / Other | D73: 46045 | E73: exact | F73: 2026-01-23 | H73: Q1 2026 | I73: Limited | J73: FALSE | K73: FALSE | N73: FALSE | O73: FALSE | P73: FALSE | Q73: 0 | R73: FALSE
A74: Its Presence Between Us | C74: Unknown | D74: 46045 | E74: exact | F74: 2026-01-23 | H74: Q1 2026 | I74: Limited | J74: FALSE | K74: FALSE | N74: FALSE | O74: FALSE | P74: FALSE | Q74: 0 | R74: FALSE
A75: Magic Mushrooms | B75: Bhavana Studios | C75: Independent / Other | D75: 46045 | E75: exact | F75: 2026-01-23 | H75: Q1 2026 | I75: Limited | J75: FALSE | K75: FALSE | N75: FALSE | O75: FALSE | P75: FALSE | Q75: 0 | R75: FALSE
A76: Mercy | B76: Amazon MGM Studios | C76: Amazon | D76: 46045 | E76: exact | F76: 2026-01-23 | H76: Q1 2026 | I76: Wide | J76: FALSE | K76: TRUE | L76: 24390303 | N76: FALSE | O76: FALSE | P76: FALSE | Q76: 0 | R76: TRUE
A77: Pennu Case | B77: Zee Studios | C77: Independent / Other | D77: 46045 | E77: exact | F77: 2026-01-23 | H77: Q1 2026 | I77: Limited | J77: FALSE | K77: FALSE | N77: FALSE | O77: FALSE | P77: FALSE | Q77: 0 | R77: FALSE
A78: Return to Silent Hill | B78: Iconic Releasing | C78: Independent / Other | D78: 46045 | E78: exact | F78: 2026-01-23 | H78: Q1 2026 | I78: Wide | J78: FALSE | K78: FALSE | L78: 5544971 | N78: FALSE | O78: FALSE | P78: FALSE | Q78: 0 | R78: FALSE
A79: Sinners | B79: Warner Bros. | C79: Warner Bros. Discovery | D79: 46045 | E79: exact | F79: 2026-01-23 | H79: Q1 2026 | I79: Wide | J79: FALSE | K79: FALSE | L79: 279989632 | N79: FALSE | O79: FALSE | P79: FALSE | Q79: 0 | R79: TRUE
A80: Standout: The Ben Kjar Story | B80: Angel Studios | C80: Angel Studios | D80: 46045 | E80: exact | F80: 2026-01-23 | H80: Q1 2026 | I80: Limited | J80: FALSE | K80: FALSE | L80: 629513 | N80: FALSE | O80: FALSE | P80: FALSE | Q80: 0 | R80: TRUE
A81: The Big Johnson | B81: Freestyle Releasing | C81: Independent / Other | D81: 46045 | E81: exact | F81: 2026-01-23 | H81: Q1 2026 | I81: Limited | J81: FALSE | K81: FALSE | N81: FALSE | O81: FALSE | P81: FALSE | Q81: 0 | R81: FALSE
A82: The Containment | B82: Level 33 | C82: Independent / Other | D82: 46045 | E82: exact | F82: 2026-01-23 | H82: Q1 2026 | I82: Limited | J82: FALSE | K82: FALSE | N82: FALSE | O82: FALSE | P82: FALSE | Q82: 0 | R82: FALSE
A83: The Dreamer Cinderella | B83: Atlas Distribution | C83: Independent / Other | D83: 46045 | E83: exact | F83: 2026-01-23 | H83: Q1 2026 | I83: Limited | J83: FALSE | K83: FALSE | N83: FALSE | O83: FALSE | P83: FALSE | Q83: 0 | R83: FALSE
A84: The Testament of Ann Lee | B84: Searchlight Pictures | C84: Disney | D84: 46045 | E84: exact | F84: 2026-01-23 | H84: Q1 2026 | I84: Wide | J84: FALSE | K84: FALSE | L84: 2515021 | N84: FALSE | O84: FALSE | P84: FALSE | Q84: 0 | R84: TRUE
A85: UFC 324: Gaethje vs. Pimblett | B85: Iconic Releasing | C85: Independent / Other | D85: 46046 | E85: exact | F85: 2026-01-24 | H85: Q1 2026 | I85: Special Engagement | J85: FALSE | K85: FALSE | N85: FALSE | O85: FALSE | P85: FALSE | Q85: 0 | R85: FALSE
A86: Hard-Boiled | B86: GKIDS | C86: Independent / Other | D86: 46047 | E86: exact | F86: 2026-01-25 | H86: Q1 2026 | I86: Wide | J86: TRUE | K86: FALSE | L86: 392742 | M86: Lifetime gross incl. original run - not 2026 revenue | N86: FALSE | O86: FALSE | P86: FALSE | Q86: 0 | R86: FALSE
A87: A Poet | B87: 1-2 Special | C87: Independent / Other | D87: 46052 | E87: exact | F87: 2026-01-30 | H87: Q1 2026 | I87: Limited | J87: FALSE | K87: FALSE | L87: 277203 | N87: FALSE | O87: FALSE | P87: FALSE | Q87: 0 | R87: FALSE
A88: Back to the Past | B88: Well Go USA | C88: Independent / Other | D88: 46052 | E88: exact | F88: 2026-01-30 | H88: Q1 2026 | I88: Limited | J88: FALSE | K88: FALSE | L88: 1949379 | N88: FALSE | O88: FALSE | P88: FALSE | Q88: 0 | R88: FALSE
A89: Bitter Rice | B89: Janus Films | C89: Independent / Other | D89: 46052 | E89: exact | F89: 2026-01-30 | H89: Q1 2026 | I89: Limited | J89: TRUE | K89: FALSE | N89: FALSE | O89: FALSE | P89: FALSE | Q89: 0 | R89: FALSE
A90: Busted Water Pipes | B90: China Lion Film Distribution | C90: Independent / Other | D90: 46052 | E90: exact | F90: 2026-01-30 | H90: Q1 2026 | I90: Limited | J90: FALSE | K90: FALSE | N90: FALSE | O90: FALSE | P90: FALSE | Q90: 0 | R90: FALSE
A91: Fish, Fists and Ambergris! | B91: Eastern Edge Films | C91: Independent / Other | D91: 46052 | E91: exact | F91: 2026-01-30 | H91: Q1 2026 | I91: Limited | J91: FALSE | K91: FALSE | N91: FALSE | O91: FALSE | P91: FALSE | Q91: 0 | R91: FALSE
A92: Gandhi Talks | B92: Zee Studios | C92: Independent / Other | D92: 46052 | E92: exact | F92: 2026-01-30 | H92: Q1 2026 | I92: Limited | J92: FALSE | K92: FALSE | N92: FALSE | O92: FALSE | P92: FALSE | Q92: 0 | R92: FALSE
A93: Infinite Icon: A Visual Memoir | B93: CJ4DPlex | C93: Independent / Other | D93: 46052 | E93: exact | F93: 2026-01-30 | H93: Q1 2026 | I93: Limited | J93: FALSE | K93: FALSE | N93: FALSE | O93: FALSE | P93: FALSE | Q93: 0 | R93: FALSE
A94: Iron Lung | B94: Markiplier Studios | C94: Independent / Other | D94: 46052 | E94: exact | F94: 2026-01-30 | H94: Q1 2026 | I94: Wide | J94: FALSE | K94: FALSE | L94: 41111208 | N94: FALSE | O94: FALSE | P94: FALSE | Q94: 0 | R94: FALSE
A95: Islands | B95: Greenwich | C95: Independent / Other | D95: 46052 | E95: exact | F95: 2026-01-30 | H95: Q1 2026 | I95: Limited | J95: FALSE | K95: FALSE | L95: 53192 | N95: FALSE | O95: FALSE | P95: FALSE | Q95: 0 | R95: FALSE
A96: Mardaani 3 | B96: Yash Raj Films | C96: Independent / Other | D96: 46052 | E96: exact | F96: 2026-01-30 | H96: Q1 2026 | I96: Limited | J96: FALSE | K96: FALSE | N96: FALSE | O96: FALSE | P96: FALSE | Q96: 0 | R96: FALSE
A97: Medias Hermanas | B97: Spanglish Movies | C97: Independent / Other | D97: 46052 | E97: exact | F97: 2026-01-30 | H97: Q1 2026 | I97: Limited | J97: FALSE | K97: FALSE | N97: FALSE | O97: FALSE | P97: FALSE | Q97: 0 | R97: FALSE
A98: Melania | B98: Amazon MGM Studios | C98: Amazon | D98: 46052 | E98: exact | F98: 2026-01-30 | H98: Q1 2026 | I98: Wide | J98: FALSE | K98: FALSE | L98: 16357453 | N98: FALSE | O98: FALSE | P98: FALSE | Q98: 0 | R98: TRUE
A99: Moses the Black | B99: Fathom Entertainment | C99: Independent / Other | D99: 46052 | E99: exact | F99: 2026-01-30 | H99: Q1 2026 | I99: Limited | J99: FALSE | K99: FALSE | N99: FALSE | O99: FALSE | P99: FALSE | Q99: 0 | R99: FALSE
A100: Natchez | B100: Oscilloscope Pictures | C100: Independent / Other | D100: 46052 | E100: exact | F100: 2026-01-30 | H100: Q1 2026 | I100: Limited | J100: FALSE | K100: FALSE | L100: 204945 | N100: FALSE | O100: FALSE | P100: FALSE | Q100: 0 | R100: FALSE
...

Sheet 2027
A1: Title | B1: Distributor | C1: Parent Company | D1: Release Date | E1: Date Precision | F1: Date (as sourced) | G1: Wide Expansion Date | H1: Release Quarter | I1: Release Type | J1: Is Re-release | K1: Is IMAX | L1: Domestic BO (Lifetime) | M1: BO Caveat | N1: Is Canceled | O1: Is Catalog Aggregate | P1: Dup BO Flag | Q1: Merge Span (days) | R1: In Scope
A2: Bagworm | B2: Oscilloscope Pictures | C2: Independent / Other | D2: 46388 | E2: season | F2: Winter 2027 | H2: Q1 2027 | I2: Limited | J2: FALSE | K2: FALSE | N2: FALSE | O2: FALSE | P2: FALSE | Q2: 0 | R2: FALSE
A3: Pendulum | B3: Vertical Entertainment | C3: Independent / Other | D3: 46388 | E3: exact | F3: 2027-01-01 | H3: Q1 2027 | I3: Wide | J3: FALSE | K3: FALSE | N3: FALSE | O3: FALSE | P3: FALSE | Q3: 0 | R3: FALSE
A4: The Meltdown | B4: Kino Lorber | C4: Independent / Other | D4: 46388 | E4: quarter | F4: 1st quarter | H4: Q1 2027 | I4: Limited | J4: FALSE | K4: FALSE | N4: FALSE | O4: FALSE | P4: FALSE | Q4: 0 | R4: FALSE
A5: Untitled Shudder Horror Film | B5: Independent Film Company | C5: Independent / Other | D5: 46395 | E5: exact | F5: 2027-01-08 | H5: Q1 2027 | I5: Limited | J5: FALSE | K5: FALSE | N5: FALSE | O5: FALSE | P5: FALSE | Q5: 0 | R5: FALSE
A6: Children of Blood and Bone | B6: Paramount Pictures | C6: Paramount | D6: 46402 | E6: exact | F6: 2027-01-15 | H6: Q1 2027 | I6: Wide | J6: FALSE | K6: TRUE | N6: FALSE | O6: FALSE | P6: FALSE | Q6: 0 | R6: TRUE
A7: The Beekeeper 2 | B7: Amazon MGM Studios | C7: Amazon | D7: 46402 | E7: exact | F7: 2027-01-15 | H7: Q1 2027 | I7: Wide | J7: FALSE | K7: FALSE | N7: FALSE | O7: FALSE | P7: FALSE | Q7: 0 | R7: TRUE
A8: Untitled Blumhouse Event Film | B8: Universal | C8: Universal / NBCU | D8: 46402 | E8: exact | F8: 2027-01-15 | H8: Q1 2027 | I8: Wide | J8: FALSE | K8: FALSE | N8: FALSE | O8: FALSE | P8: FALSE | Q8: 0 | R8: TRUE
A9: Air Bud Returns | B9: Cineverse | C9: Independent / Other | D9: 46409 | E9: exact | F9: 2027-01-22 | H9: Q1 2027 | I9: Wide | J9: FALSE | K9: FALSE | N9: FALSE | O9: FALSE | P9: FALSE | Q9: 0 | R9: FALSE
A10: Animal Friends | B10: Warner Bros. | C10: Warner Bros. Discovery | D10: 46409 | E10: exact | F10: 2027-01-22 | H10: Q1 2027 | I10: Wide | J10: FALSE | K10: FALSE | N10: FALSE | O10: FALSE | P10: FALSE | Q10: 0 | R10: TRUE
A11: The Third Parent | B11: Bleecker Street | C11: Bleecker Street | D11: 46409 | E11: exact | F11: 2027-01-22 | H11: Q1 2027 | I11: Wide | J11: FALSE | K11: FALSE | N11: FALSE | O11: FALSE | P11: FALSE | Q11: 0 | R11: TRUE
A12: Drag | B12: Briarcliff Entertainment | C12: Independent / Other | D12: 46416 | E12: exact | F12: 2027-01-29 | H12: Q1 2027 | I12: Wide | J12: FALSE | K12: FALSE | N12: FALSE | O12: FALSE | P12: FALSE | Q12: 0 | R12: FALSE
A13: Karoshi | B13: Lionsgate | C13: Lionsgate | D13: 46416 | E13: exact | F13: 2027-01-29 | H13: Q1 2027 | I13: Wide | J13: FALSE | K13: FALSE | N13: FALSE | O13: FALSE | P13: FALSE | Q13: 0 | R13: TRUE
... A22: CoComelon: The Movie | B22: Universal | C22: Universal / NBCU | D22: 46437 | E22: exact | F22: 2027-02-19 | H22: Q1 2027 | I22: Wide | J22: FALSE | K22: FALSE | N22: FALSE | O22: FALSE | P22: FALSE | Q22: 0 | R22: TRUE
A23: Star Wars Ep. IV: A New Hope | B23: Walt Disney | C23: Disney | D23: 46437 | E23: exact | F23: 2027-02-19 | H23: Q1 2027 | I23: Wide | J23: TRUE | K23: FALSE | L23: 460998007 | M23: Lifetime gross incl. original run - not 2027 revenue | N23: FALSE | O23: FALSE | P23: FALSE | Q23: 0 | R23: TRUE
A24: Untitled Neon Horror Film | B24: Neon | C24: Neon | D24: 46437 | E24: exact | F24: 2027-02-19 | H24: Q1 2027 | I24: Wide | J24: FALSE | K24: FALSE | N24: FALSE | O24: FALSE | P24: FALSE | Q24: 0 | R24: TRUE
A25: Wife & Dog | B25: Black Bear Pictures | C25: Independent / Other | D25: 46437 | E25: exact | F25: 2027-02-19 | H25: Q1 2027 | I25: Wide | J25: FALSE | K25: FALSE | N25: FALSE | O25: FALSE | P25: FALSE | Q25: 0 | R25: FALSE
A26: K-Pop: The Debut | B26: Paramount Pictures | C26: Paramount | D26: 46444 | E26: exact | F26: 2027-02-26 | H26: Q1 2027 | I26: Wide | J26: FALSE | K26: FALSE | N26: FALSE | O26: FALSE | P26: FALSE | Q26: 0 | R26: TRUE
A27: Live Like That | B27: Sony Pictures | C27: Sony | D27: 46444 | E27: exact | F27: 2027-02-26 | H27: Q1 2027 | I27: Wide | J27: FALSE | K27: FALSE | N27: FALSE | O27: FALSE | P27: FALSE | Q27: 0 | R27: TRUE
A28: The Revenge of La Llorona | B28: Warner Bros. | C28: Warner Bros. Discovery | D28: 46444 | E28: exact | F28: 2027-02-26 | H28: Q1 2027 | I28: Wide | J28: FALSE | K28: FALSE | N28: FALSE | O28: FALSE | P28: FALSE | Q28: 0 | R28: TRUE
A29: Gatto | B29: Walt Disney | C29: Disney | D29: 46451 | E29: exact | F29: 2027-03-05 | H29: Q1 2027 | I29: Wide | J29: FALSE | K29: FALSE | N29: FALSE | O29: FALSE | P29: FALSE | Q29: 0 | R29: TRUE
A30: The Thomas Crown Affair | B30: Amazon MGM Studios | C30: Amazon | D30: 46451 | E30: exact | F30: 2027-03-05 | H30: Q1 2027 | I30: Wide | J30: FALSE | K30: TRUE | N30: FALSE | O30: FALSE | P30: FALSE | Q30: 0 | R30: TRUE
A31: Untitled DC Event Film | B31: Warner Bros. | C31: Warner Bros. Discovery | D31: 46451 | E31: exact | F31: 2027-03-05 | H31: Q1 2027 | I31: Wide | J31: FALSE | K31: FALSE | N31: FALSE | O31: FALSE | P31: FALSE | Q31: 0 | R31: TRUE
A32: Untitled Mike Flanagan Exorcist Film | B32: Universal | C32: Universal / NBCU | D32: 46458 | E32: exact | F32: 2027-03-12 | H32: Q1 2027 | I32: Wide | J32: FALSE | K32: FALSE | N32: FALSE | O32: FALSE | P32: FALSE | Q32: 0 | R32: TRUE
A33: Untitled The Chosen Season 6 Finale Film | B33: Amazon MGM Studios | C33: Amazon | D33: 46458 | E33: exact | F33: 2027-03-12 | H33: Q1 2027 | I33: Wide | J33: FALSE | K33: FALSE | N33: FALSE | O33: FALSE | P33: FALSE | Q33: 0 | R33: TRUE
A34: Untitled Warner Bros. Event Film | B34: Warner Bros. | C34: Warner Bros. Discovery | D34: 46458 | E34: exact | F34: 2027-03-12 | H34: Q1 2027 | I34: Wide | J34: FALSE | K34: FALSE | N34: FALSE | O34: FALSE | P34: FALSE | Q34: 0 | R34: TRUE
A35: Sonic the Hedgehog 4 | B35: Paramount Pictures | C35: Paramount | D35: 46465 | E35: exact | F35: 2027-03-19 | H35: Q1 2027 | I35: Wide | J35: FALSE | K35: FALSE | N35: FALSE | O35: FALSE | P35: FALSE | Q35: 0 | R35: TRUE
... A41: Untitled Universal Event Film | B41: Universal | C41: Universal / NBCU | D41: 46479 | E41: exact | F41: 2027-04-02 | H41: Q2 2027 | I41: Wide | J41: FALSE | K41: FALSE | N41: FALSE | O41: FALSE | P41: FALSE | Q41: 0 | R41: TRUE
A42: Varanasi | C42: Unknown | D42: 46484 | E42: exact | F42: 2027-04-07 | H42: Q2 2027 | I42: Wide | J42: FALSE | K42: FALSE | N42: FALSE | O42: FALSE | P42: FALSE | Q42: 0 | R42: FALSE
A43: Boys for Life | B43: Paramount Pictures | C43: Paramount | D43: 46486 | E43: exact | F43: 2027-04-09 | H43: Q2 2027 | I43: Wide | J43: FALSE | K43: FALSE | N43: FALSE | O43: FALSE | P43: FALSE | Q43: 0 | R43: TRUE
A44: Panic Carefully | B44: Warner Bros. | C44: Warner Bros. Discovery | D44: 46486 | E44: exact | F44: 2027-04-09 | H44: Q2 2027 | I44: Wide | J44: FALSE | K44: FALSE | N44: FALSE | O44: FALSE | P44: FALSE | Q44: 0 | R44: TRUE
A45: Not Alone | B45: Universal | C45: Universal / NBCU | D45: 46493 | E45: exact | F45: 2027-04-16 | H45: Q2 2027 | I45: Wide | J45: FALSE | K45: FALSE | N45: FALSE | O45: FALSE | P45: FALSE | Q45: 0 | R45: TRUE
A46: F.A.S.T. | B46: Warner Bros. | C46: Warner Bros. Discovery | D46: 46500 | E46: exact | F46: 2027-04-23 | H46: Q2 2027 | I46: Wide | J46: FALSE | K46: FALSE | N46: FALSE | O46: FALSE | P46: FALSE | Q46: 0 | R46: TRUE
A47: Spaceballs: The New One | B47: Amazon MGM Studios | C47: Amazon | D47: 46500 | E47: exact | F47: 2027-04-23 | H47: Q2 2027 | I47: Wide | J47: FALSE | K47: FALSE | N47: FALSE | O47: FALSE | P47: FALSE | Q47: 0 | R47: TRUE
A48: Monitor | B48: Searchlight Pictures | C48: Disney | D48: 46507 | E48: exact | F48: 2027-04-30 | H48: Q2 2027 | I48: Wide | J48: FALSE | K48: FALSE | N48: FALSE | O48: FALSE | P48: FALSE | Q48: 0 | R48: TRUE
A49: The Legend of Zelda | B49: Sony Pictures | C49: Sony | D49: 46507 | E49: exact | F49: 2027-04-30 | H49: Q2 2027 | I49: Wide | J49: FALSE | K49: TRUE | N49: FALSE | O49: FALSE | P49: FALSE | Q49: 0 | R49: TRUE
A50: The Resurrection of the Christ: Part One | B50: Lionsgate | C50: Lionsgate | D50: 46513 | E50: exact | F50: 2027-05-06 | H50: Q2 2027 | I50: Wide | J50: FALSE | K50: FALSE | N50: FALSE | O50: FALSE | P50: FALSE | Q50: 0 | R50: TRUE
A51: Bad Fairies | B51: Warner Bros. | C51: Warner Bros. Discovery | D51: 46528 | E51: exact | F51: 2027-05-21 | H51: Q2 2027 | I51: Wide | J51: FALSE | K51: FALSE | N51: FALSE | O51: FALSE | P51: FALSE | Q51: 0 | R51: TRUE
A52: The Catch | B52: Universal | C52: Universal / NBCU | D52: 46528 | E52: exact | F52: 2027-05-21 | H52: Q2 2027 | I52: Wide | J52: FALSE | K52: FALSE | N52: FALSE | O52: FALSE | P52: FALSE | Q52: 0 | R52: TRUE
A53: Untitled Paranormal Activity Film | B53: Paramount Pictures | C53: Paramount | D53: 46528 | E53: exact | F53: 2027-05-21 | H53: Q2 2027 | I53: Wide | J53: FALSE | K53: FALSE | N53: FALSE | O53: FALSE | P53: FALSE | Q53: 0 | R53: TRUE
A54: Star Wars: Starfighter | B54: Walt Disney | C54: Disney | D54: 46535 | E54: exact | F54: 2027-05-28 | H54: Q2 2027 | I54: Wide | J54: FALSE | K54: FALSE | N54: FALSE | O54: FALSE | P54: FALSE | Q54: 0 | R54: TRUE
... A107: Zac Power | B107: Viva Pictures | C107: Independent / Other | D107: 46752 | E107: year | F107: During 2027 | H107: TBD 2027 | I107: Wide | J107: FALSE | K107: FALSE | N107: FALSE | O107: FALSE | P107: FALSE | Q107: 0 | R107: FALSE
